Workbook

Sheet Payroll Mr Shin
A1: CÔNG TY TNHH SHINSUNG VINA
A2: Lô CN04, khu công nghiệp Cẩm Khê, TT.Cẩm Khê, H.Cẩm Khê, T.Phú Thọ
A3: PAYROLL AUGUST 2024
A4: From 1st -31th August 2024
A6: Tỷ giá Vietinbank: 31/08/2024 | C6: 24520 | D6: 25020
A8: STT (No) | B8: Họ và tên (First and last name) | C8: Vị trí (Location) | D8: Giờ công cơ bản thực tế (The actual basic hourly) | E8: Giờ công làm thêm (Hours of overtime) | I8: Lương cơ bản (Basic salary) USD | J8: Lương cơ bản (Basic salary) | K8: Các khoản phụ cấp (Allowances) | Q8: Tổng các khoản phụ cấp (Total allowances) | R8: Lương đóng bảo hiểm | S8: Lương giờ công | T8: Tổng lương giờ công cơ bản | U8: Lương giờ công làm thêm | Z8: Tổng lương | AA8: BH tính vào chi phí / Isuarance payable by company | AF8: BH khấu trừ lương / Isuarance deductions from salary | AJ8: Thuế TNCN /Personal income tax | AQ8: Thực nhận | AS8: Số tài khoản | AT8: Ký nhận
E9: Tăng ca ngày | F9: Tăng ca đêm | G9: Tăng ca CN 200% | H9: Tăng ca ngày lễ 300% | K9: Phụ cấp trách nhiệm | L9: Phụ cấp điện thoại | M9: Phụ cấp xăng xe | N9: Phụ cấp nhà ở | O9: Phụ cấp đi lại | P9: Chuyên cần (Diligence) | U9: Tăng ca ngày 150% | V9: Tăng ca đêm | W9: Tăng ca CN 200% | X9: Tăng ca ngày lễ 300% | Y9: Tổng lương làm thêm | AA9: Lương đóng bảo hiểm/Salary base for insurance | AB9: BHXH / Social Insurance 17.5% | AC9: BHYT / Health Insurance 3%건강보험 (회사분) | AD9: BHTN / Unemployment Insurance 1% | AE9: Cộng /Amount Isurance | AF9: BHXH / Social Insurance 8% | AG9: BHYT / Health Insurance 1,5% 건강보험 (개인분) | AH9: BHTN / Unemployment Insurance 1% | AI9: Cộng 10.5%/Amount Isurance | AJ9: Giảm trừ bản thân (기본공제금 ) (VND) | AK9: Số người phụ thuộc /Number Deduction family | AL9: Giảm trừ người phụ thuộc /deduction-family 4400000/1person | AM9: Tax excemption | AN9: Thu nhập chịu thuế | AO9: Thu nhập tính thuế (과세 대상 금액) (VND) | AP9: Thuế TNCN (개인소득세) ( VND) | AQ9: VND | AR9: USD (Quy đổi)
A10: -1 | B10: -2 | C10: -3 | D10: -4 | E10: -5 | F10: (5a) | G10: -6 | H10: -7 | J10: -8 | K10: -9 | L10: -10 | M10: -11 | N10: (11 a) | O10: (11b) | P10: -12 | Q10: (13)=10+11+11a+11b+ 12 | R10: (14)=(8)+(9) | S10: (15)=(14)/4 | T10: (16)=(15)*(4) | U10: (17)=(5)* (15)*150% | V10: (17a) | W10: (18)=(6)* (15)*200% | X10: (19)=(7)* (15)*300% | Y10: (20)= (17)+(18)+(19) | Z10: (21)=(13)+(16)+ (20) | AA10: (22)=(8)+ (10) | AB10: (23)=(22)x17% | AC10: (24)=(22)x3% | AD10: 25 | AE10: (26)=(23)+(24) | AF10: 27 | AG10: (28)=(22)x1.5% | AH10: 29 | AI10: (30)=(27)+(28)+(29) | AJ10: -31 | AK10: (31a) | AL10: (32)= (31a)x4400000 | AM10: -33 | AN10: (34)=(21)-(33) | AO10: (35)=(21)-(31)-(32)-(33) | AP10: -36 | AQ10: -37 | AR10: -38 | AS10: -39 | AT10: -40
A11: 1 | B11: Shin Chun Ki | C11: TGĐ | D11: 208 | J11: =2500*D6 -> 62550000 | Q11: =SUM(L11:P11) -> 0 | R11: =J11+K11 -> 62550000 | S11: =R11/D11 -> 300721.15 | T11: =S11*D11 -> 62550000 | U11: =S11*E11*150% -> 0 | W11: =S11*G11*200% -> 0 | X11: =S11*H11*300% -> 0 | Y11: =SUM(U11:X11) -> 0 | Z11: =Q11+T11+Y11 -> 62550000 | AA11: 29800000 | AB11: =AA11*5% -> 1490000 | AC11: =AA11*3% -> 894000 | AE11: =AB11+AC11+AD11 -> 2384000 | AG11: =AA11*1.5% -> 447000 | AI11: =AF11+AG11+AH11 -> 447000 | AJ11: 11000000 | AK11: 3 | AL11: =AK11*4400000 -> 13200000 | AM11: =L11 -> 0 | AN11: =Z11-AM11 -> 62550000 | AO11: =(Z11-AJ11-AL11-AM11-AI11) -> 37903000 | AP11: =ROUND(IF(AO11<=5000000,AO11*5%,IF(AND(AO11>5000000,AO11<=10000000),AO11*10%-250000,IF(AND(AO11>10000000,AO11<=18000000),AO11*15%-750000,IF(AND(AO11>18000000,AO11<=32000000),AO11*20%-1650000,IF(AND(AO11>32000000,AO11<=52000000),AO11*25%-3250000,IF(AND(AO11>52000000,AO11<80000000),AO11*30%-5850000,IF(AO11>80000000,AO11*35%-9850000))))))),0) -> 6225750 | AQ11: =Z11-AI11-AP11 -> 55877250 | AR11: =+AQ11/D6 -> 2233.3034
A12: 1 | B12: Shin Chun Ki | C12: Nhà quản lý | D12: 216 | I12: =6000*0.85 -> 5100 | J12: =I12*D6 -> 127602000 | Q12: =SUM(L12:P12) -> 0 | R12: =J12+K12 -> 127602000 | S12: =R12/D12 -> 590750 | T12: =S12*D12 -> 127602000 | U12: =S12*E12*150% -> 0 | W12: =S12*G12*200% -> 0 | X12: =S12*H12*300% -> 0 | Y12: =SUM(U12:X12) -> 0 | Z12: =Q12+T12+Y12 -> 127602000 | AA12: 46800000 | AB12: =AA12*17.5% -> 8190000 | AC12: =+AA12*3% -> 1404000 | AE12: =AB12+AC12+AD12 -> 9594000 | AF12: =AA12*8% -> 3744000 | AG12: =+AA12*1.5% -> 702000 | AI12: =AF12+AG12+AH12 -> 4446000 | AJ12: 11000000 | AK12: 3 | AL12: =+AK12*4400000 -> 13200000 | AN12: =Z12-AM12 -> 127602000 | AO12: =(AN12-AJ12-AL12-AI12) -> 98956000 | AP12: =ROUND(IF(AO12<=5000000,AO12*5%,IF(AND(AO12>5000000,AO12<=10000000),AO12*10%-250000,IF(AND(AO12>10000000,AO12<=18000000),AO12*15%-750000,IF(AND(AO12>18000000,AO12<=32000000),AO12*20%-1650000,IF(AND(AO12>32000000,AO12<=52000000),AO12*25%-3250000,IF(AND(AO12>52000000,AO12<80000000),AO12*30%-5850000,IF(AO12>80000000,AO12*35%-9850000))))))),0) -> 24784600 | AQ12: =Z12-AI12-AP12 -> 98371400 | AR12: =AQ12/D6 -> 3931.7106 | AS12: 109871163330
B14: Scheduling | V14: Manager | AG14: Manager | AS14: Director- general
AQ19: =AP12+'Mr. Lim'!AS11+Mr.Moon!AS11+'Mr. Yang'!AS11+'Mr. Choi'!AS11+'Mr. Hwang'!AS11+'Payroll Office'!BM23+'Payroll of factory (SOI) '!BN27 -> 67940860 | AS19: =AR12+'Mr. Lim'!AV11+'Mr. Yang'!AV11 -> 7759.2389
AQ20: =AP12+'Mr. Lim'!AS11+Mr.Moon!AS11+'Mr. Yang'!AS11+'Mr. Choi'!AS11+'Mr. Hwang'!AS11+'Payroll Office'!BM23+'Payroll of factory (SOI) '!BN27+'Payroll of factory '!BM22 -> 67940860
AL23: =AE12+'Mr. Lim'!AE11+'Mr. Yang'!AE11+'Mr. Hwang'!AE11+'Payroll Office'!BB23+'Payroll of factory '!BB22+'Payroll of factory (SOI) '!BC27+'Payroll of factory (DET).1'!BD40 -> 116191080

Sheet Mr. Lim
A1: CÔNG TY TNHH SHINSUNG VINA
A2: Lô CN04, khu công nghiệp Cẩm Khê, TT.Cẩm Khê, H.Cẩm Khê, T.Phú Thọ
A3: PAYROLL AUGUST 2024
A4: From 1st -31th August 2024
A6: ='Payroll Mr Shin'!A6 -> Tỷ giá Vietinbank: 31/08/2024 | C6: ='Payroll Mr Shin'!C6 -> 24520 | D6: ='Payroll Mr Shin'!D6 -> 25020
A8: STT (No) | B8: Họ và tên (First and last name) | C8: Vị trí (Location) | D8: Giờ công cơ bản thực tế (The actual basic hourly) | E8: Giờ công làm thêm (Hours of overtime) | I8: Lương cơ bản (Basic salary) USD | J8: Lương cơ bản (Basic salary) | K8: Các khoản phụ cấp (Allowances) | Q8: Tổng các khoản phụ cấp (Total allowances) | R8: Lương đóng bảo hiểm | S8: Lương giờ công | T8: Tổng lương giờ công cơ bản | U8: Lương giờ công làm thêm | Z8: Tổng lương | AA8: BH tính vào chi phí / Isuarance payable by company | AF8: BH khấu trừ lương / Isuarance deductions from salary | AJ8: Thuế TNCN /Personal income tax | AT8: Khấu trừ Thuế TNCN | AU8: Thực nhận | AW8: Số tài khoản | AX8: Ký nhận
E9: Tăng ca ngày | F9: Tăng ca đêm | G9: Tăng ca CN 200% | H9: Tăng ca ngày lễ 300% | K9: Phụ cấp trách nhiệm | L9: Phụ cấp điện thoại | M9: Phụ cấp xăng xe | N9: Phụ cấp nhà ở | O9: Phụ cấp đi lại | P9: Chuyên cần (Diligence) | U9: Tăng ca ngày 150% | V9: Tăng ca đêm | W9: Tăng ca CN 200% | X9: Tăng ca ngày lễ 300% | Y9: Tổng lương làm thêm | AA9: Lương đóng bảo hiểm/Salary base for insurance | AB9: BHXH / Social Insurance 17% | AC9: BHYT / Health Insurance 3%건강보험 (회사분) | AD9: BHTN / Unemployment Insurance 1% | AE9: Cộng /Amount Isurance | AF9: BHXH / Social Insurance 8% | AG9: BHYT / Health Insurance 1,5% 건강보험 (개인분) | AH9: BHTN / Unemployment Insurance 1% | AI9: Cộng 10.5%/Amount Isurance | AJ9: Giảm trừ bản thân (기본공제금 ) (VND) | AK9: Số người phụ thuộc /Number Deduction family | AL9: Giảm trừ người phụ thuộc /deduction-family 4400000/1person | AM9: Tax excemption | AN9: Thu nhập chịu thuế | AO9: 15% TNCN | AP9: Tiền thuê nhà thực tế | AQ9: Thu nhập chịu thuế bao gồm tiền thuê nhà | AR9: Thu nhập tính thuế (과세 대상 금액) VND | AS9: Thuế TNCN (개인소득세) ( VND) | AU9: VND | AV9: USD (Quy đổi)
A10: -1 | B10: -2 | C10: -3 | D10: -4 | E10: -5 | F10: (5a) | G10: -6 | H10: -7 | J10: -8 | K10: -9 | L10: -10 | M10: -11 | N10: (11 a) | O10: (11b) | P10: -12 | Q10: (13)=10+11+11a+11b+ 12 | R10: (14)=(8)+(9) | S10: (15)=(14)/4 | T10: (16)=(15)*(4) | U10: (17)=(5)* (15)*150% | V10: (17a) | W10: (18)=(6)* (15)*200% | X10: (19)=(7)* (15)*300% | Y10: (20)= (17)+(18)+(19) | Z10: (21)=(13)+(16)+ (20) | AA10: (22)=(8)+ (10) | AB10: (23)=(22)x17.5% | AC10: (24)=(22)x3% | AD10: 25 | AE10: (26)=(23)+(24) | AF10: (27)=(22)x8% | AG10: (28)=(22)x1.5% | AH10: 29 | AI10: (30)=(27)+(28)+(29) | AJ10: -31 | AK10: (31a) | AL10: (32)= (31a)x4400000 | AM10: -33 | AN10: (34)=(21)-(33) | AO10: -32 | AP10: (34)=(21)-(33) | AQ10: -31 | AR10: (35)=(21)-(31)-(32)-(33) | AS10: -36 | AT10: -36 | AU10: -37 | AV10: -38 | AW10: -39 | AX10: -40
A11: 1 | B11: Lim Heungsub | C11: CG | D11: 216 | I11: =3500*0.85 -> 2975 | J11: =I11*D6 -> 74434500 | Q11: =SUM(L11:P11) -> 0 | S11: =J11/D11 -> 344604.17 | T11: =S11*D11 -> 74434500 | U11: =S11*E11*150% -> 0 | W11: =S11*G11*200% -> 0 | X11: =S11*H11*300% -> 0 | Y11: =SUM(U11:X11) -> 0 | Z11: =Q11+T11+Y11 -> 74434500 | AA11: 46800000 | AB11: =AA11*17.5% -> 8190000 | AC11: =+AA11*3% -> 1404000 | AE11: =AB11+AC11+AD11 -> 9594000 | AF11: =AA11*0.08 -> 3744000 | AG11: =+AA11*1.5% -> 702000 | AI11: =AF11+AG11+AH11 -> 4446000 | AJ11: 11000000 | AK11: 1 | AL11: =+AK11*4400000 -> 4400000 | AN11: =Z11-AM11 -> 74434500 | AO11: =AN11*15% -> 11165175 | AP11: =2000000/5 -> 400000 | AQ11: =AN11+AP11 -> 74834500 | AR11: =(AQ11-AJ11-AL11-AI11) -> 54988500 | AS11: =ROUND(IF(AR11<=5000000,AR11*5%,IF(AND(AR11>5000000,AR11<=10000000),AR11*10%-250000,IF(AND(AR11>10000000,AR11<=18000000),AR11*15%-750000,IF(AND(AR11>18000000,AR11<=32000000),AR11*20%-1650000,IF(AND(AR11>32000000,AR11<=52000000),AR11*25%-3250000,IF(AND(AR11>52000000,AR11<80000000),AR11*30%-5850000,IF(AR11>80000000,AR11*35%-9850000))))))),0) -> 10646550 | AT11: 0 | AU11: =Z11-AI11-AS11-AT11 -> 59341950 | AV11: =AU11/D6 -> 2371.7806 | AW11: 103873550905
B13: Scheduling | AI13: Manager | AW13: Director- general

Sheet Mr.Moon
A1: CÔNG TY TNHH SHINSUNG VINA
A2: Lô CN04, khu công nghiệp Cẩm Khê, TT.Cẩm Khê, H.Cẩm Khê, T.Phú Thọ
A3: PAYROLL AUGUST 2024
A4: From 1st -31th August 2024
A6: ='Payroll Mr Shin'!A6 -> Tỷ giá Vietinbank: 31/08/2024 | C6: ='Payroll Mr Shin'!C6 -> 24520 | D6: ='Payroll Mr Shin'!D6 -> 25020
A8: STT (No) | B8: Họ và tên (First and last name) | C8: Vị trí (Location) | D8: Giờ công cơ bản thực tế (The actual basic hourly) | E8: Giờ công làm thêm (Hours of overtime) | I8: Lương cơ bản (Basic salary) USD | J8: Lương cơ bản (Basic salary) | K8: Các khoản phụ cấp (Allowances) | Q8: Tổng các khoản phụ cấp (Total allowances) | R8: Lương đóng bảo hiểm | S8: Lương giờ công | T8: Tổng lương giờ công cơ bản | U8: Lương giờ công làm thêm | Z8: Tổng lương | AA8: BH tính vào chi phí / Isuarance payable by company | AF8: BH khấu trừ lương / Isuarance deductions from salary | AJ8: Thuế TNCN /Personal income tax | AT8: Khấu trừ Thuế TNCN | AU8: Thực nhận | AW8: Số tài khoản | AX8: Ký nhận
E9: Tăng ca ngày | F9: Tăng ca đêm | G9: Tăng ca CN 200% | H9: Tăng ca ngày lễ 300% | K9: Phụ cấp trách nhiệm | L9: Phụ cấp điện thoại | M9: Phụ cấp xăng xe | N9: Phụ cấp nhà ở | O9: Phụ cấp đi lại | P9: Chuyên cần (Diligence) | U9: Tăng ca ngày 150% | V9: Tăng ca đêm | W9: Tăng ca CN 200% | X9: Tăng ca ngày lễ 300% | Y9: Tổng lương làm thêm | AA9: Lương đóng bảo hiểm/Salary base for insurance | AB9: BHXH / Social Insurance 17% | AC9: BHYT / Health Insurance 3%건강보험 (회사분) | AD9: BHTN / Unemployment Insurance 1% | AE9: Cộng /Amount Isurance | AF9: BHXH / Social Insurance 8% | AG9: BHYT / Health Insurance 1,5% 건강보험 (개인분) | AH9: BHTN / Unemployment Insurance 1% | AI9: Cộng 10.5%/Amount Isurance | AJ9: Giảm trừ bản thân (기본공제금 ) (VND) | AK9: Số người phụ thuộc /Number Deduction family | AL9: Giảm trừ người phụ thuộc /deduction-family 4400000/1person | AM9: Tax excemption | AN9: Thu nhập chịu thuế | AO9: 15% TNCN | AP9: Tiền thuê nhà thực tế | AQ9: Thu nhập chịu thuế bao gồm tiền thuê nhà | AR9: Thu nhập tính thuế (과세 대상 금액) VND | AS9: Thuế TNCN (개인소득세) ( VND) | AU9: VND | AV9: USD (Quy đổi)
A10: -1 | B10: -2 | C10: -3 | D10: -4 | E10: -5 | F10: (5a) | G10: -6 | H10: -7 | J10: -8 | K10: -9 | L10: -10 | M10: -11 | N10: (11 a) | O10: (11b) | P10: -12 | Q10: (13)=10+11+11a+11b+ 12 | R10: (14)=(8)+(9) | S10: (15)=(14)/4 | T10: (16)=(15)*(4) | U10: (17)=(5)* (15)*150% | V10: (17a) | W10: (18)=(6)* (15)*200% | X10: (19)=(7)* (15)*300% | Y10: (20)= (17)+(18)+(19) | Z10: (21)=(13)+(16)+ (20) | AA10: (22)=(8)+ (10) | AB10: (23)=(22)x17.5% | AC10: (24)=(22)x3% | AD10: 25 | AE10: (26)=(23)+(24) | AF10: (27)=(22)x8% | AG10: (28)=(22)x1.5% | AH10: 29 | AI10: (30)=(27)+(28)+(29) | AJ10: -31 | AK10: (31a) | AL10: (32)= (31a)x4400000 | AM10: -33 | AN10: (34)=(21)-(33) | AO10: -32 | AP10: (34)=(21)-(33) | AQ10: -31 | AR10: (35)=(21)-(31)-(32)-(33) | AS10: -36 | AT10: -36 | AU10: -37 | AV10: -38 | AW10: -39 | AX10: -40
A11: 1 | B11: Moon Han Soo | C11: GĐĐH | D11: 216 | I11: =3500*0.85 -> 2975 | J11: =I11*D6 -> 74434500 | Q11: =SUM(L11:P11) -> 0 | S11: =J11/D11 -> 344604.17 | T11: =S11*D11 -> 74434500 | U11: =S11*E11*150% -> 0 | W11: =S11*G11*200% -> 0 | X11: =S11*H11*300% -> 0 | Y11: =SUM(U11:X11) -> 0 | Z11: =Q11+T11+Y11 -> 74434500 | AA11: 0 | AB11: =AA11*17.5% -> 0 | AC11: =+AA11*3% -> 0 | AE11: =AB11+AC11+AD11 -> 0 | AF11: =AA11*0.08 -> 0 | AG11: =+AA11*1.5% -> 0 | AI11: =AF11+AG11+AH11 -> 0 | AJ11: 11000000 | AK11: 0 | AL11: =+AK11*4400000 -> 0 | AN11: =Z11-AM11 -> 74434500 | AO11: =AN11*15% -> 11165175 | AP11: =2000000/5 -> 400000 | AQ11: =AN11+AP11 -> 74834500 | AR11: =(AQ11-AJ11-AL11-AI11) -> 63834500 | AS11: =ROUND(IF(AR11<=5000000,AR11*5%,IF(AND(AR11>5000000,AR11<=10000000),AR11*10%-250000,IF(AND(AR11>10000000,AR11<=18000000),AR11*15%-750000,IF(AND(AR11>18000000,AR11<=32000000),AR11*20%-1650000,IF(AND(AR11>32000000,AR11<=52000000),AR11*25%-3250000,IF(AND(AR11>52000000,AR11<80000000),AR11*30%-5850000,IF(AR11>80000000,AR11*35%-9850000))))))),0) -> 13300350 | AT11: 0 | AU11: =Z11-AI11-AS11-AT11 -> 61134150 | AV11: =AU11/D6 -> 2443.4113 | AW11: 103873550905
B13: Scheduling | V13: Manager | AH13: Manager | AW13: Director- general

Sheet Mr. Yang
A1: CÔNG TY TNHH SHINSUNG VINA
A2: Lô CN04, khu công nghiệp Cẩm Khê, TT.Cẩm Khê, H.Cẩm Khê, T.Phú Thọ
A3: PAYROLL AUGUST 2024
A4: From 1st -31th August 2024
A6: ='Payroll Mr Shin'!A6 -> Tỷ giá Vietinbank: 31/08/2024 | C6: ='Payroll Mr Shin'!C6 -> 24520 | D6: ='Payroll Mr Shin'!D6 -> 25020
A8: STT (No) | B8: Họ và tên (First and last name) | C8: Vị trí (Location) | D8: Giờ công cơ bản thực tế (The actual basic hourly) | E8: Giờ công làm thêm (Hours of overtime) | I8: Lương cơ bản (Basic salary) USD | J8: Lương cơ bản (Basic salary) | K8: Các khoản phụ cấp (Allowances) | Q8: Tổng các khoản phụ cấp (Total allowances) | R8: Lương đóng bảo hiểm | S8: Lương giờ công | T8: Tổng lương giờ công cơ bản | U8: Lương giờ công làm thêm | Z8: Tổng lương | AA8: BH tính vào chi phí / Isuarance payable by company | AF8: BH khấu trừ lương / Isuarance deductions from salary | AJ8: Thuế TNCN /Personal income tax | AT8: Khấu trừ Thuế TNCN | AU8: Thực nhận | AW8: Số tài khoản | AX8: Ký nhận
E9: Tăng ca ngày | F9: Tăng ca đêm | G9: Tăng ca CN 200% | H9: Tăng ca ngày lễ 300% | K9: Phụ cấp trách nhiệm | L9: Phụ cấp điện thoại | M9: Phụ cấp xăng xe | N9: Phụ cấp nhà ở | O9: Phụ cấp đi lại | P9: Chuyên cần (Diligence) | U9: Tăng ca ngày 150% | V9: Tăng ca đêm | W9: Tăng ca CN 200% | X9: Tăng ca ngày lễ 300% | Y9: Tổng lương làm thêm | AA9: Lương đóng bảo hiểm/Salary base for insurance | AB9: BHXH / Social Insurance 17% | AC9: BHYT / Health Insurance 3%건강보험 (회사분) | AD9: BHTN / Unemployment Insurance 1% | AE9: Cộng /Amount Isurance | AF9: BHXH / Social Insurance 8% | AG9: BHYT / Health Insurance 1,5% 건강보험 (개인분) | AH9: BHTN / Unemployment Insurance 1% | AI9: Cộng 10.5%/Amount Isurance | AJ9: Giảm trừ bản thân (기본공제금 ) (VND) | AK9: Số người phụ thuộc /Number Deduction family | AL9: Giảm trừ người phụ thuộc /deduction-family 4400000/1person | AM9: Tax excemption | AN9: Thu nhập chịu thuế | AO9: 15% TNCN | AP9: Tiền thuê nhà thực tế | AQ9: Thu nhập chịu thuế bao gồm tiền thuê nhà | AR9: Thu nhập tính thuế (과세 대상 금액) VND | AS9: Thuế TNCN (개인소득세) ( VND) | AU9: VND | AV9: USD (Quy đổi)
A10: -1 | B10: -2 | C10: -3 | D10: -4 | E10: -5 | F10: (5a) | G10: -6 | H10: -7 | J10: -8 | K10: -9 | L10: -10 | M10: -11 | N10: (11 a) | O10: (11b) | P10: -12 | Q10: (13)=10+11+11a+11b+ 12 | R10: (14)=(8)+(9) | S10: (15)=(14)/4 | T10: (16)=(15)*(4) | U10: (17)=(5)* (15)*150% | V10: (17a) | W10: (18)=(6)* (15)*200% | X10: (19)=(7)* (15)*300% | Y10: (20)= (17)+(18)+(19) | Z10: (21)=(13)+(16)+ (20) | AA10: (22)=(8)+ (10) | AB10: (23)=(22)x17.5% | AC10: (24)=(22)x3% | AD10: 25 | AE10: (26)=(23)+(24) | AF10: (27)=(22)x8% | AG10: (28)=(22)x1.5% | AH10: 29 | AI10: (30)=(27)+(28)+(29) | AJ10: -31 | AK10: (31a) | AL10: (32)= (31a)x4400000 | AM10: -33 | AN10: (34)=(21)-(33) | AO10: -32 | AP10: (34)=(21)-(33) | AQ10: -31 | AR10: (35)=(21)-(31)-(32)-(33) | AS10: -36 | AT10: -36 | AU10: -37 | AV10: -38 | AW10: -39 | AX10: -40
A11: 1 | B11: Yang Dao Jun | C11: LĐKT | D11: 216 | I11: =2000*0.85 -> 1700 | J11: =I11*D6 -> 42534000 | Q11: =SUM(L11:P11) -> 0 | S11: =J11/D11 -> 196916.67 | T11: =S11*D11 -> 42534000 | U11: =S11*E11*150% -> 0 | W11: =S11*G11*200% -> 0 | X11: =S11*H11*300% -> 0 | Y11: =SUM(U11:X11) -> 0 | Z11: =Q11+T11+Y11 -> 42534000 | AA11: 41242000 | AB11: =AA11*17.5% -> 7217350 | AC11: =+AA11*3% -> 1237260 | AE11: =AB11+AC11+AD11 -> 8454610 | AF11: =AA11*0.08 -> 3299360 | AG11: =+AA11*1.5% -> 618630 | AI11: =AF11+AG11+AH11 -> 3917990 | AJ11: 11000000 | AK11: 2 | AL11: =+AK11*4400000 -> 8800000 | AN11: =Z11-AM11 -> 42534000 | AO11: =AN11*15% -> 6380100 | AP11: =2000000/5 -> 400000 | AQ11: =AN11+AP11 -> 42934000 | AR11: =(AQ11-AJ11-AL11-AI11) -> 19216010 | AS11: =ROUND(IF(AR11<=5000000,AR11*5%,IF(AND(AR11>5000000,AR11<=10000000),AR11*10%-250000,IF(AND(AR11>10000000,AR11<=18000000),AR11*15%-750000,IF(AND(AR11>18000000,AR11<=32000000),AR11*20%-1650000,IF(AND(AR11>32000000,AR11<=52000000),AR11*25%-3250000,IF(AND(AR11>52000000,AR11<80000000),AR11*30%-5850000,IF(AR11>80000000,AR11*35%-9850000))))))),0) -> 2193202 | AT11: 0 | AU11: =Z11-AI11-AS11-AT11 -> 36422808 | AV11: =AU11/D6 -> 1455.7477 | AW11: 103873550905
B13: Scheduling | V13: Manager | AI13: Manager | AW13: Director- general

Sheet Mr. Choi
A1: CÔNG TY TNHH SHINSUNG VINA
A2: Lô CN04, khu công nghiệp Cẩm Khê, TT.Cẩm Khê, H.Cẩm Khê, T.Phú Thọ
A3: PAYROLL AUGUST 2024
A4: From 1st -31th August 2024
A6: ='Payroll Mr Shin'!A6 -> Tỷ giá Vietinbank: 31/08/2024 | C6: ='Payroll Mr Shin'!C6 -> 24520 | D6: ='Payroll Mr Shin'!D6 -> 25020
A8: STT (No) | B8: Họ và tên (First and last name) | C8: Vị trí (Location) | D8: Giờ công cơ bản thực tế (The actual basic hourly) | E8: Giờ công làm thêm (Hours of overtime) | I8: Lương cơ bản (Basic salary) USD | J8: Lương cơ bản (Basic salary) | K8: Các khoản phụ cấp (Allowances) | Q8: Tổng các khoản phụ cấp (Total allowances) | R8: Lương đóng bảo hiểm | S8: Lương giờ công | T8: Tổng lương giờ công cơ bản | U8: Lương giờ công làm thêm | Z8: Tổng lương | AA8: BH tính vào chi phí / Isuarance payable by company | AF8: BH khấu trừ lương / Isuarance deductions from salary | AJ8: Thuế TNCN /Personal income tax | AT8: Khấu trừ Thuế TNCN | AU8: Thực nhận | AW8: Số tài khoản | AX8: Ký nhận
E9: Tăng ca ngày | F9: Tăng ca đêm | G9: Tăng ca CN 200% | H9: Tăng ca ngày lễ 300% | K9: Phụ cấp trách nhiệm | L9: Phụ cấp điện thoại | M9: Phụ cấp xăng xe | N9: Phụ cấp nhà ở | O9: Phụ cấp đi lại | P9: Chuyên cần (Diligence) | U9: Tăng ca ngày 150% | V9: Tăng ca đêm | W9: Tăng ca CN 200% | X9: Tăng ca ngày lễ 300% | Y9: Tổng lương làm thêm | AA9: Lương đóng bảo hiểm/Salary base for insurance | AB9: BHXH / Social Insurance 17% | AC9: BHYT / Health Insurance 3%건강보험 (회사분) | AD9: BHTN / Unemployment Insurance 1% | AE9: Cộng /Amount Isurance | AF9: BHXH / Social Insurance 8% | AG9: BHYT / Health Insurance 1,5% 건강보험 (개인분) | AH9: BHTN / Unemployment Insurance 1% | AI9: Cộng 10.5%/Amount Isurance | AJ9: Giảm trừ bản thân (기본공제금 ) (VND) | AK9: Số người phụ thuộc /Number Deduction family | AL9: Giảm trừ người phụ thuộc /deduction-family 4400000/1person | AM9: Tax excemption | AN9: Thu nhập chịu thuế | AO9: 15% TNCN | AP9: Tiền thuê nhà thực tế | AQ9: Thu nhập chịu thuế bao gồm tiền thuê nhà | AR9: Thu nhập tính thuế (과세 대상 금액) VND | AS9: Thuế TNCN (개인소득세) ( VND) | AU9: VND | AV9: USD (Quy đổi)
A10: -1 | B10: -2 | C10: -3 | D10: -4 | E10: -5 | F10: (5a) | G10: -6 | H10: -7 | J10: -8 | K10: -9 | L10: -10 | M10: -11 | N10: (11 a) | O10: (11b) | P10: -12 | Q10: (13)=10+11+11a+11b+ 12 | R10: (14)=(8)+(9) | S10: (15)=(14)/4 | T10: (16)=(15)*(4) | U10: (17)=(5)* (15)*150% | V10: (17a) | W10: (18)=(6)* (15)*200% | X10: (19)=(7)* (15)*300% | Y10: (20)= (17)+(18)+(19) | Z10: (21)=(13)+(16)+ (20) | AA10: (22)=(8)+ (10) | AB10: (23)=(22)x17.5% | AC10: (24)=(22)x3% | AD10: 25 | AE10: (26)=(23)+(24) | AF10: (27)=(22)x8% | AG10: (28)=(22)x1.5% | AH10: 29 | AI10: (30)=(27)+(28)+(29) | AJ10: -31 | AK10: (31a) | AL10: (32)= (31a)x4400000 | AM10: -33 | AN10: (34)=(21)-(33) | AO10: -32 | AP10: (34)=(21)-(33) | AQ10: -31 | AR10: (35)=(21)-(31)-(32)-(33) | AS10: -36 | AT10: -36 | AU10: -37 | AV10: -38 | AW10: -39 | AX10: -40
A11: 1 | B11: Choi Jin Sun | C11: LĐKT | D11: 216 | I11: =3500*0.85 -> 2975 | J11: =I11*D6 -> 74434500 | Q11: =SUM(L11:P11) -> 0 | S11: =J11/D11 -> 344604.17 | T11: =S11*D11 -> 74434500 | U11: =S11*E11*150% -> 0 | W11: =S11*G11*200% -> 0 | X11: =S11*H11*300% -> 0 | Y11: =SUM(U11:X11) -> 0 | Z11: =Q11+T11+Y11 -> 74434500 | AA11: 0 | AB11: =AA11*17.5% -> 0 | AC11: =+AA11*3% -> 0 | AE11: =AB11+AC11+AD11 -> 0 | AF11: =AA11*0.08 -> 0 | AG11: =+AA11*1.5% -> 0 | AI11: =AF11+AG11+AH11 -> 0 | AJ11: 11000000 | AK11: 1 | AL11: =+AK11*4400000 -> 4400000 | AN11: =Z11-AM11 -> 74434500 | AO11: =AN11*15% -> 11165175 | AP11: =2000000/5 -> 400000 | AQ11: =AN11+AP11 -> 74834500 | AR11: =(AQ11-AJ11-AL11-AI11) -> 59434500 | AS11: =ROUND(IF(AR11<=5000000,AR11*5%,IF(AND(AR11>5000000,AR11<=10000000),AR11*10%-250000,IF(AND(AR11>10000000,AR11<=18000000),AR11*15%-750000,IF(AND(AR11>18000000,AR11<=32000000),AR11*20%-1650000,IF(AND(AR11>32000000,AR11<=52000000),AR11*25%-3250000,IF(AND(AR11>52000000,AR11<80000000),AR11*30%-5850000,IF(AR11>80000000,AR11*35%-9850000))))))),0) -> 11980350 | AT11: 0 | AU11: =Z11-AI11-AS11-AT11 -> 62454150 | AV11: =AU11/D6 -> 2496.1691 | AW11: 103873550905 | AX11: =AV11+Mr.Moon!AV11 -> 4939.5803
B13: Scheduling | AI13: Manager | AW13: Director- general
AV18: =AV11+Mr.Moon!AV11 -> 4939.5803
AV21: =AV11+Mr.Moon!AV11 -> 4939.5803

Sheet Mr. Hwang
A1: CÔNG TY TNHH SHINSUNG VINA
A2: Lô CN04, khu công nghiệp Cẩm Khê, TT.Cẩm Khê, H.Cẩm Khê, T.Phú Thọ
A3: PAYROLL AUGUST 2024
A4: From 1st -31th August 2024
A6: ='Payroll Mr Shin'!A6 -> Tỷ giá Vietinbank: 31/08/2024 | C6: ='Payroll Mr Shin'!C6 -> 24520 | D6: ='Payroll Mr Shin'!D6 -> 25020
A8: STT (No) | B8: Họ và tên (First and last name) | C8: Vị trí (Location) | D8: Giờ công cơ bản thực tế (The actual basic hourly) | E8: Giờ công làm thêm (Hours of overtime) | I8: Lương cơ bản (Basic salary) USD | J8: Lương cơ bản (Basic salary) | K8: Các khoản phụ cấp (Allowances) | Q8: Tổng các khoản phụ cấp (Total allowances) | R8: Lương đóng bảo hiểm | S8: Lương giờ công | T8: Tổng lương giờ công cơ bản | U8: Lương giờ công làm thêm | Z8: Tổng lương | AA8: BH tính vào chi phí / Isuarance payable by company | AF8: BH khấu trừ lương / Isuarance deductions from salary | AJ8: Thuế TNCN /Personal income tax | AT8: Khấu trừ Thuế TNCN | AU8: Thực nhận (VND) | AV8: Thực nhận quy đổi ( USD) | AW8: Số tài khoản | AX8: Ký nhận
E9: Tăng ca ngày | F9: Tăng ca đêm | G9: Tăng ca CN 200% | H9: Tăng ca ngày lễ 300% | K9: Phụ cấp trách nhiệm | L9: Phụ cấp điện thoại | M9: Phụ cấp xăng xe | N9: Phụ cấp nhà ở | O9: Phụ cấp đi lại | P9: Chuyên cần (Diligence) | U9: Tăng ca ngày 150% | V9: Tăng ca đêm | W9: Tăng ca CN 200% | X9: Tăng ca ngày lễ 300% | Y9: Tổng lương làm thêm | AA9: Lương đóng bảo hiểm/Salary base for insurance | AB9: BHXH / Social Insurance 17% | AC9: BHYT / Health Insurance 3%건강보험 (회사분) | AD9: BHTN / Unemployment Insurance 1% | AE9: Cộng /Amount Isurance | AF9: BHXH / Social Insurance 8% | AG9: BHYT / Health Insurance 1,5% 건강보험 (개인분) | AH9: BHTN / Unemployment Insurance 1% | AI9: Cộng 10.5%/Amount Isurance | AJ9: Giảm trừ bản thân (기본공제금 ) (VND) | AK9: Số người phụ thuộc /Number Deduction family | AL9: Giảm trừ người phụ thuộc /deduction-family 4400000/1person | AM9: Tax excemption | AN9: Thu nhập chịu thuế | AO9: 15% TNCN | AP9: Tiền thuê nhà thực tế | AQ9: Thu nhập chịu thuế bao gồm tiền thuê nhà | AR9: Thu nhập tính thuế (과세 대상 금액) VND | AS9: Thuế TNCN (개인소득세) ( VND)
A10: -1 | B10: -2 | C10: -3 | D10: -4 | E10: -5 | F10: (5a) | G10: -6 | H10: -7 | J10: -8 | K10: -9 | L10: -10 | M10: -11 | N10: (11 a) | O10: (11b) | P10: -12 | Q10: (13)=10+11+11a+11b+ 12 | R10: (14)=(8)+(9) | S10: (15)=(14)/4 | T10: (16)=(15)*(4) | U10: (17)=(5)* (15)*150% | V10: (17a) | W10: (18)=(6)* (15)*200% | X10: (19)=(7)* (15)*300% | Y10: (20)= (17)+(18)+(19) | Z10: (21)=(13)+(16)+ (20) | AA10: (22)=(8)+ (10) | AB10: (23)=(22)x17.5% | AC10: (24)=(22)x3% | AD10: 25 | AE10: (26)=(23)+(24) | AF10: (27)=(22)x8% | AG10: (28)=(22)x1.5% | AH10: 29 | AI10: (30)=(27)+(28)+(29) | AJ10: -31 | AK10: (31a) | AL10: (32)= (31a)x4400000 | AM10: -33 | AN10: (34)=(21)-(33) | AO10: -32 | AP10: (34)=(21)-(33) | AQ10: -31 | AR10: (35)=(21)-(31)-(32)-(33) | AS10: -36 | AT10: -36 | AU10: -37 | AV10: -37.333333 | AW10: -37.833333 | AX10: -39
A11: 1 | B11: Hwang Seungyun | C11: LĐKT | D11: 216 | J11: =50000000*0.85 -> 42500000 | Q11: =SUM(L11:P11) -> 0 | S11: =J11/D11 -> 196759.26 | T11: =S11*D11 -> 42500000 | U11: =S11*E11*150% -> 0 | W11: =S11*G11*200% -> 0 | X11: =S11*H11*300% -> 0 | Y11: =SUM(U11:X11) -> 0 | Z11: =Q11+T11+Y11 -> 42500000 | AA11: 0 | AB11: =AA11*17.5% -> 0 | AC11: =+AA11*3% -> 0 | AE11: =AB11+AC11+AD11 -> 0 | AF11: =AA11*0.08 -> 0 | AG11: =+AA11*1.5% -> 0 | AI11: =AF11+AG11+AH11 -> 0 | AJ11: 11000000 | AK11: 0 | AL11: 0 | AN11: =Z11-AM11 -> 42500000 | AO11: =AN11*15% -> 6375000 | AP11: =2000000/5 -> 400000 | AQ11: =AN11+AP11 -> 42900000 | AR11: =(AQ11-AJ11-AL11-AI11) -> 31900000 | AS11: =ROUND(IF(AR11<=5000000,AR11*5%,IF(AND(AR11>5000000,AR11<=10000000),AR11*10%-250000,IF(AND(AR11>10000000,AR11<=18000000),AR11*15%-750000,IF(AND(AR11>18000000,AR11<=32000000),AR11*20%-1650000,IF(AND(AR11>32000000,AR11<=52000000),AR11*25%-3250000,IF(AND(AR11>52000000,AR11<80000000),AR11*30%-5850000,IF(AR11>80000000,AR11*35%-9850000))))))),0) -> 4730000 | AT11: 0 | AU11: =Z11-AI11-AS11-AT11 -> 37770000 | AV11: =AU11/D6 -> 1509.5923 | AW11: 103873550905
B13: Scheduling | V13: Manager | AH13: Manager | AW13: Director- general
AV16: =AU11+#REF! -> #REF!

Sheet Payroll Office
A1: CÔNG TY TNHH SHINSUNG VINA
A2: Lô CN04, khu công nghiệp Cẩm Khê, TT.Cẩm Khê, H.Cẩm Khê, T.Phú Thọ
A3: PAYROLL AUGUST 2024
A4: From 1st -31th August 2024
BO6: VND
A7: STT (No) | B7: Họ và tên (First and last name) | C7: Vị trí (Location) | D7: Tổng số giờ công chuẩn | E7: Giờ công cơ bản thực tế (The actual basic hourly) | G7: Số bữa phụ | H7: Giờ công làm thêm (Hours of overtime) | Q7: Lương đóng bảo hiểm | U7: Các khoản phụ cấp (Allowances) | AF7: Thưởng Tết Âm lịch 20% (Ngày lễ 02/09) | AG7: HT làm thêm ngày lễ 01/05 | AH7: Tổng phụ cấp không đóng BH được nhận (Total allowances) | AI7: Lương đóng bảo hiểm | AJ7: Lương giờ công | AK7: Tổng lương giờ công cơ bản | AL7: Lương giờ công làm thêm | AV7: Tổng lương | AW7: BH tính vào chi phí / Isuarance payable by company | BC7: BH khấu trừ lương / Isuarance deductions from salary | BG7: Thuế TNCN | BO7: Thực nhận | BP7: Số tài khoản | BQ7: Ký nhận
E8: Ca ngày | F8: Ca đêm | H8: Tăng ca 150% | I8: Tăng ca đêm 195% | J8: CN ngày 200% | K8: CN đêm 260% | L8: Tăng ca ngày CN 300% | M8: Tăng ca đêm CN 390% | N8: Ngày lễ ngày 300% | O8: Ngày lễ đêm 390% | P8: TC lễ (450%) | Q8: Lương cơ bản (Basic salary) | R8: Phụ cấp trách nhiệm/ Responsibility allowance | S8: PC ngoại ngữ/ Foreign language support | T8: Phụ cấp thâm niên/ Seniority allowances | U8: HT điện thoại /Phone charges/ 26 Công | V8: HT điện thoại /Phone charges | W8: HT xăng xe /Fuel costs for vehicles/ 26 Công | X8: HT xăng xe /Fuel costs for vehicles | Y8: HT nhà ở /Housing support/ 26 Công | Z8: HT nhà ở /Housing support | AA8: HT đi lại/ Mobility assistance | AB8: HT con nhỏ/ Support workers with small children | AC8: Thưởng Chuyên cần / Attendance Bonus | AD8: Trợ cấp bữa phụ /Snack allowance | AE8: Thưởng sinh nhật tháng 08 /Birthday in August | AL8: Tăng ca ngày | AM8: Tăng ca đêm | AN8: CN ngày | AO8: CN đêm | AP8: Tăng ca ngày CN | AQ8: Tăng ca đêm CN | AR8: Ngày lễ ngày | AS8: Ngày lễ đêm | AT8: TC lễ | AU8: Tổng lương làm thêm | AW8: Lương đóng bảo hiểm/Salary base for insurance | AX8: BHXH / Social Insurance 17.5% | AY8: BHYT / Health Insurance 3%건강보험 (회사분) | AZ8: BHTN / Unemployment Insurance 1% | BA8: KPCĐ 2% | BB8: Cộng /Amount Isurance | BC8: BHXH / Social Insurance 8% | BD8: BHYT / Health Insurance 1,5% 건강보험 (개인분) | BE8: BHTN / Unemployment Insurance 1% | BF8: Cộng 10.5%/Amount Isurance | BG8: Giảm trừ bản thân (기본공제금 ) (VND) | BH8: Số người phụ thuộc /Number Deduction family | BI8: Giảm trừ người phụ thuộc /deduction-family 4400000/1person | BJ8: Tax excemption | BK8: Thu nhập chịu thuế | BL8: Thu nhập tính thuế (과세 대상 금액) VND | BM8: Thuế TNCN (개인소득세) ( VND) | BN8: Đoàn phí
A9: -1 | B9: -2 | C9: -3 | E9: -4 | F9: -5 | H9: -5 | J9: (5a) | K9: -6 | N9: -7 | Q9: -8 | R9: -9 | S9: (9a) | V9: -10 | X9: -11 | Z9: (11 a) | AA9: (11b) | AB9: (11c) | AC9: -12 | AH9: (13)=10+11+11a+11b+ 12 | AI9: (14)=(8)+ (9)+(9a) | AJ9: (15)=(14)/4 | AK9: (16)=(15)*(4) | AL9: (17)=(5)* (15)*150% | AN9: (17a) | AO9: (18)=(6)* (15)*200% | AR9: (19)=(7)* (15)*300% | AU9: (20)= (17)+(18)+(19) | AV9: (21)=(13)+(16)+ (20) | AW9: (22)=(8)+ (10) | AX9: (23)=(22)x17% | AY9: (24)=(22)x3% | AZ9: (25)=(22)x1% | BB9: (26)=(23)+(24)+ (25) | BC9: (27)=(22)x8% | BD9: (28)=(22)x1.5% | BE9: (29)=(22)x1% | BF9: (30)=(27)+(28)+(29) | BG9: -31 | BH9: (31a) | BI9: (32)= (31a)x4400000 | BJ9: -33 | BK9: (34)=(21)-(33) | BL9: (35)=(34)-(30)-(31)-(32) | BM9: -36 | BO9: -37
A10: 1 | B10: Nguyễn Minh Đức | C10: Tổng quản lý | D10: 216 | E10: 216 | Q10: 21550000 | T10: =1500000 -> 1500000 | U10: 2000000 | V10: =3000000 -> 3000000 | Z10: =2000000 -> 2000000 | AD10: =G10*13000 -> 0 | AH10: =V10+X10+Z10+AA10+AB10+AC10+AD10+AE10 -> 5000000 | AI10: =Q10+R10+S10+T10 -> 23050000 | AJ10: =AI10/D10 -> 106712.96 | AK10: =AJ10*E10 -> 23050000 | AM10: =AJ10*I10*150%*130% -> 0 | AN10: =J10*200%*AJ10 -> 0 | AP10: =L10*AJ10*300% -> 0 | AU10: =SUM(AL10:AT10) -> 0 | AV10: =AH10+AK10+AU10+AG10+AF10 -> 28050000 | BA10: =AW10*2% -> 0 | BF10: =BC10+BD10+BE10 -> 0 | BG10: 11000000 | BH10: 2 | BI10: =BH10*4400000 -> 8800000 | BJ10: =V10+AA10 -> 3000000 | BK10: =AV10-BJ10-AJ10*H10*0.5-AJ10*I10*0.95-AJ10*J10-AJ10*K10*1.6-AJ10*L10*2-AJ10*M10*2.9-AJ10*N10*2-AJ10*O10*2.9-P10*3.5 -> 25050000 | BL10: =IF(BK10-BI10-BG10-BF10<0,0,BK10-BI10-BG10-BF10) -> 5250000 | BM10: =ROUND(IF(BL10<=5000000,BL10*5%,IF(AND(BL10>5000000,BL10<=10000000),BL10*10%-250000,IF(AND(BL10>10000000,BL10<=18000000),BL10*15%-750000,IF(AND(BL10>18000000,BL10<=32000000),BL10*20%-1650000,IF(AND(BL10>32000000,BL10<=52000000),BL10*25%-3250000,IF(AND(BL10>52000000,BL10<80000000),BL10*30%-585000,IF(BL10>80000000,BL10*35%-9850000))))))),0) -> 275000 | BN10: 35000 | BO10: =AV10-BF10-BM10-BN10 -> 27740000 | BP10: 101883483888
A11: =A10+1 -> 2 | B11: Nguyễn Thị Thu | C11: Kế toán | D11: 208 | E11: 184 | Q11: 5450000 | R11: 5000000 | T11: 300000 | U11: 1200000 | V11: =IF((E11+F11)>=160,U11, U11/D11*(E11+F11)) -> 1200000 | W11: 1400000 | X11: =IF((E11+F11)>=160,W11, W11/208*(E11+F11)) -> 1400000 | Y11: 1400000 | Z11: =IF((E11+F11)>=160,Y11, Y11/208*(E11+F11)) -> 1400000 | AB11: 20000 | AC11: 500000 | AD11: =G11*13000 -> 0 | AE11: 100000 | AH11: =V11+X11+Z11+AA11+AB11+AC11+AD11+AE11 -> 4620000 | AI11: =Q11+R11+S11+T11 -> 10750000 | AJ11: =AI11/D11 -> 51682.692 | AK11: =AJ11*E11 -> 9509615.4 | AL11: =AJ11*H11*150% -> 0 | AM11: =AJ11*I11*150%*130% -> 0 | AN11: =J11*200%*AJ11 -> 0 | AO11: =AJ11*K11*200% -> 0 | AP11: =L11*AJ11*300% -> 0 | AR11: =AJ11*N11*300% -> 0 | AU11: =SUM(AL11:AT11) -> 0 | AV11: =AH11+AK11+AU11+AG11+AF11 -> 14129615 | AW11: =Q11+R11+S11+T11 -> 10750000 | AX11: =AW11*17.5% -> 1881250 | AY11: =AW11*3% -> 322500 | AZ11: =AW11*1% -> 107500 | BA11: =AW11*2% -> 215000 | BB11: =AX11+AY11+AZ11+BA11 -> 2526250 | BC11: =AW11*8% -> 860000 | BD11: =AW11*1.5% -> 161250 | BE11: =AW11*1% -> 107500 | BF11: =BC11+BD11+BE11 -> 1128750 | BG11: 11000000 | BH11: 2 | BI11: =BH11*4400000 -> 8800000 | BJ11: =V11 -> 1200000 | BK11: =AV11-BJ11-AJ11*H11*0.5-AJ11*I11*0.95-AJ11*J11-AJ11*K11*1.6-AJ11*L11*2-AJ11*M11*2.9-AJ11*N11*2-AJ11*O11*2.9-P11*3.5 -> 12929615 | BL11: =IF(BK11-BI11-BG11-BF11<0,0,BK11-BI11-BG11-BF11) -> 0 | BM11: =ROUND(IF(BL11<=5000000,BL11*5%,IF(AND(BL11>5000000,BL11<=10000000),BL11*10%-250000,IF(AND(BL11>10000000,BL11<=18000000),BL11*15%-750000,IF(AND(BL11>18000000,BL11<=32000000),BL11*20%-1650000,IF(AND(BL11>32000000,BL11<=52000000),BL11*25%-3250000,IF(AND(BL11>52000000,BL11<80000000),BL11*30%-585000,IF(BL11>80000000,BL11*35%-9850000))))))),0) -> 0 | BN11: 35000 | BO11: =AV11-BF11-BM11-BN11 -> 12965865 | BP11: 107876999632
A12: =A11+1 -> 3 | B12: Nguyễn Thị Kim Liên | C12: Kế toán | D12: 208 | E12: 184 | Q12: 5450000 | R12: 2000000 | T12: 600000 | U12: 800000 | V12: =IF((E12+F12)>=160,U12, U12/D12*(E12+F12)) -> 800000 | W12: 700000 | X12: =IF((E12+F12)>=160,W12, W12/208*(E12+F12)) -> 700000 | Y12: 700000 | Z12: =IF((E12+F12)>=160,Y12, Y12/208*(E12+F12)) -> 700000 | AC12: 500000 | AD12: =G12*13000 -> 0 | AH12: =V12+X12+Z12+AA12+AB12+AC12+AD12+AE12 -> 2700000 | AI12: =Q12+R12+S12+T12 -> 8050000 | AJ12: =AI12/D12 -> 38701.923 | AK12: =AJ12*E12 -> 7121153.8 | AL12: =AJ12*H12*150% -> 0 | AM12: =AJ12*I12*150%*130% -> 0 | AN12: =J12*200%*AJ12 -> 0 | AO12: =AJ12*K12*200% -> 0 | AP12: =L12*AJ12*300% -> 0 | AR12: =AJ12*N12*300% -> 0 | AU12: =SUM(AL12:AT12) -> 0 | AV12: =AH12+AK12+AU12+AG12+AF12 -> 9821153.8 | AW12: =Q12+R12+S12+T12 -> 8050000 | AX12: =AW12*17.5% -> 1408750 | AY12: =AW12*3% -> 241500 | AZ12: =AW12*1% -> 80500 | BA12: =AW12*2% -> 161000 | BB12: =AX12+AY12+AZ12+BA12 -> 1891750 | BC12: =AW12*8% -> 644000 | BD12: =AW12*1.5% -> 120750 | BE12: =AW12*1% -> 80500 | BF12: =BC12+BD12+BE12 -> 845250 | BG12: 11000000 | BH12: 0 | BI12: =BH12*4400000 -> 0 | BJ12: =V12 -> 800000 | BK12: 10724760 | BL12: =IF(BK12-BI12-BG12-BF12<0,0,BK12-BI12-BG12-BF12) -> 0 | BM12: =ROUND(IF(BL12<=5000000,BL12*5%,IF(AND(BL12>5000000,BL12<=10000000),BL12*10%-250000,IF(AND(BL12>10000000,BL12<=18000000),BL12*15%-750000,IF(AND(BL12>18000000,BL12<=32000000),BL12*20%-1650000,IF(AND(BL12>32000000,BL12<=52000000),BL12*25%-3250000,IF(AND(BL12>52000000,BL12<80000000),BL12*30%-585000,IF(BL12>80000000,BL12*35%-9850000))))))),0) -> 0 | BN12: 35000 | BO12: =AV12-BF12-BM12-BN12 -> 8940903.8 | BP12: 103875891817
A13: =A12+1 -> 4 | B13: Dương Thị Vân | C13: Kế toán | D13: 208 | E13: 184 | Q13: 5190000 | R13: 500000 | U13: 700000 | V13: =IF((E13+F13)>=160,U13, U13/D13*(E13+F13)) -> 700000 | W13: 700000 | X13: =IF((E13+F13)>=160,W13, W13/208*(E13+F13)) -> 700000 | Y13: 700000 | Z13: =IF((E13+F13)>=160,Y13, Y13/208*(E13+F13)) -> 700000 | AC13: 500000 | AD13: =G13*13000 -> 0 | AH13: =V13+X13+Z13+AA13+AB13+AC13+AD13+AE13 -> 2600000 | AI13: =Q13+R13+S13+T13 -> 5690000 | AJ13: =AI13/D13 -> 27355.769 | AK13: =AJ13*E13 -> 5033461.5 | AL13: =AJ13*H13*150% -> 0 | AM13: =AJ13*I13*150%*130% -> 0 | AN13: =J13*200%*AJ13 -> 0 | AP13: =L13*AJ13*300% -> 0 | AR13: =AJ13*N13*300% -> 0 | AU13: =SUM(AL13:AT13) -> 0 | AV13: =AH13+AK13+AU13+AG13+AF13 -> 7633461.5 | AW13: =Q13+R13+S13+T13 -> 5690000 | AX13: =AW13*17.5% -> 995750 | AY13: =AW13*3% -> 170700 | AZ13: =AW13*1% -> 56900 | BA13: =AW13*2% -> 113800 | BB13: =AX13+AY13+AZ13+BA13 -> 1337150 | BC13: =AW13*8% -> 455200 | BD13: =AW13*1.5% -> 85350 | BE13: =AW13*1% -> 56900 | BF13: =BC13+BD13+BE13 -> 597450 | BG13: 11000000 | BH13: 0 | BI13: =BH13*4400000 -> 0 | BJ13: =V13 -> 700000 | BK13: =AV13-BJ13-AJ13*H13*0.5-AJ13*I13*0.95-AJ13*J13-AJ13*K13*1.6-AJ13*L13*2-AJ13*M13*2.9-AJ13*N13*2-AJ13*O13*2.9-P13*3.5 -> 6933461.5 | BL13: =IF(BK13-BI13-BG13-BF13<0,0,BK13-BI13-BG13-BF13) -> 0 | BM13: =ROUND(IF(BL13<=5000000,BL13*5%,IF(AND(BL13>5000000,BL13<=10000000),BL13*10%-250000,IF(AND(BL13>10000000,BL13<=18000000),BL13*15%-750000,IF(AND(BL13>18000000,BL13<=32000000),BL13*20%-1650000,IF(AND(BL13>32000000,BL13<=52000000),BL13*25%-3250000,IF(AND(BL13>52000000,BL13<80000000),BL13*30%-585000,IF(BL13>80000000,BL13*35%-9850000))))))),0) -> 0 | BN13: 35000 | BO13: =AV13-BF13-BM13-BN13 -> 7001011.5 | BP13: 104873387926
A14: =A13+1 -> 5 | B14: Nguyễn Thị Lý (Từ 01-24/08) | C14: HCNS | D14: 208 | E14: 152 | Q14: 4000000 | U14: 700000 | W14: 1000000 | Y14: 1000000 | AD14: =G14*13000 -> 0 | AH14: =V14+X14+Z14+AA14+AB14+AC14+AD14+AE14 -> 0 | AI14: =Q14+R14+S14+T14 -> 4000000 | AJ14: =AI14/D14 -> 19230.769 | AK14: =AJ14*E14 -> 2923076.9 | AL14: =AJ14*H14*150% -> 0 | AM14: =AJ14*I14*150%*130% -> 0 | AN14: =J14*200%*AJ14 -> 0 | AP14: =L14*AJ14*300% -> 0 | AR14: =AJ14*N14*300% -> 0 | AU14: =SUM(AL14:AT14) -> 0 | AV14: =AH14+AK14+AU14+AG14+AF14 -> 2923076.9 | AW14: 0 | AX14: =AW14*17.5% -> 0 | AY14: =AW14*3% -> 0 | AZ14: =AW14*1% -> 0 | BA14: =AW14*2% -> 0 | BB14: =AX14+AY14+AZ14+BA14 -> 0 | BC14: =AW14*8% -> 0 | BD14: =AW14*1.5% -> 0 | BE14: =AW14*1% -> 0 | BF14: =BC14+BD14+BE14 -> 0 | BG14: 11000000 | BH14: 0 | BI14: =BH14*4400000 -> 0 | BJ14: =V14 -> 0 | BK14: =AV14-BJ14-AJ14*H14*0.5-AJ14*I14*0.95-AJ14*J14-AJ14*K14*1.6-AJ14*L14*2-AJ14*M14*2.9-AJ14*N14*2-AJ14*O14*2.9-P14*3.5 -> 2923076.9 | BL14: =IF(BK14-BI14-BG14-BF14<0,0,BK14-BI14-BG14-BF14) -> 0 | BM14: =ROUND(IF(BL14<=5000000,BL14*5%,IF(AND(BL14>5000000,BL14<=10000000),BL14*10%-250000,IF(AND(BL14>10000000,BL14<=18000000),BL14*15%-750000,IF(AND(BL14>18000000,BL14<=32000000),BL14*20%-1650000,IF(AND(BL14>32000000,BL14<=52000000),BL14*25%-3250000,IF(AND(BL14>52000000,BL14<80000000),BL14*30%-585000,IF(BL14>80000000,BL14*35%-9850000))))))),0) -> 0 | BO14: =AV14-BF14-BM14-BN14 -> 2923076.9 | BP14: 104873387926 | BQ14: =BO14+BO15 -> 6580139.2
A15: =A14+1 -> 6 | B15: Nguyễn Thị Lý (Từ 25-31/08) | C15: HCNS | D15: 208 | E15: 40 | Q15: 4706000 | R15: 300000 | U15: 700000 | V15: 700000 | W15: 1000000 | X15: 1000000 | Y15: 1000000 | Z15: 1000000 | AB15: 20000 | AC15: 500000 | AD15: =G15*13000 -> 0 | AH15: =V15+X15+Z15+AA15+AB15+AC15+AD15+AE15 -> 3220000 | AI15: =Q15+R15+S15+T15 -> 5006000 | AJ15: =AI15/D15 -> 24067.308 | AK15: =AJ15*E15 -> 962692.31 | AL15: =AJ15*H15*150% -> 0 | AM15: =AJ15*I15*150%*130% -> 0 | AN15: =J15*200%*AJ15 -> 0 | AP15: =L15*AJ15*300% -> 0 | AR15: =AJ15*N15*300% -> 0 | AU15: =SUM(AL15:AT15) -> 0 | AV15: =AH15+AK15+AU15+AG15+AF15 -> 4182692.3 | AW15: =Q15+R15+S15+T15 -> 5006000 | AX15: =AW15*17.5% -> 876050 | AY15: =AW15*3% -> 150180 | AZ15: =AW15*1% -> 50060 | BA15: =AW15*2% -> 100120 | BB15: =AX15+AY15+AZ15+BA15 -> 1176410 | BC15: =AW15*8% -> 400480 | BD15: =AW15*1.5% -> 75090 | BE15: =AW15*1% -> 50060 | BF15: =BC15+BD15+BE15 -> 525630 | BG15: 11000000 | BH15: 0 | BI15: =BH15*4400000 -> 0 | BJ15: =V15 -> 700000 | BK15: =AV15-BJ15-AJ15*H15*0.5-AJ15*I15*0.95-AJ15*J15-AJ15*K15*1.6-AJ15*L15*2-AJ15*M15*2.9-AJ15*N15*2-AJ15*O15*2.9-P15*3.5 -> 3482692.3 | BL15: =IF(BK15-BI15-BG15-BF15<0,0,BK15-BI15-BG15-BF15) -> 0 | BM15: =ROUND(IF(BL15<=5000000,BL15*5%,IF(AND(BL15>5000000,BL15<=10000000),BL15*10%-250000,IF(AND(BL15>10000000,BL15<=18000000),BL15*15%-750000,IF(AND(BL15>18000000,BL15<=32000000),BL15*20%-1650000,IF(AND(BL15>32000000,BL15<=52000000),BL15*25%-3250000,IF(AND(BL15>52000000,BL15<80000000),BL15*30%-585000,IF(BL15>80000000,BL15*35%-9850000))))))),0) -> 0 | BO15: =AV15-BF15-BM15-BN15 -> 3657062.3 | BP15: 104873387926 | BQ15: =AV14+AV15 -> 7105769.2
A16: =A15+1 -> 7 | B16: Phạm Thị Chín | C16: Tạp vụ | D16: 208 | E16: 216 | H16: 0.5 | Q16: 4064000 | R16: 1000000 | T16: 900000 | U16: 600000 | V16: =IF((E16+F16)>=160,U16, U16/D16*(E16+F16)) -> 600000 | W16: 600000 | X16: =IF((E16+F16)>=160,W16, W16/208*(E16+F16)) -> 600000 | Y16: 600000 | Z16: =IF((E16+F16)>=160,Y16, Y16/208*(E16+F16)) -> 600000 | AC16: 500000 | AD16: =G16*13000 -> 0 | AH16: =V16+X16+Z16+AA16+AB16+AC16+AD16+AE16 -> 2300000 | AI16: =Q16+R16+S16+T16 -> 5964000 | AJ16: =AI16/D16 -> 28673.077 | AK16: =AJ16*E16 -> 6193384.6 | AL16: =AJ16*H16*150% -> 21504.808 | AM16: =AJ16*I16*150%*130% -> 0 | AN16: =J16*200%*AJ16 -> 0 | AO16: =AJ16*K16*200% -> 0 | AP16: =L16*AJ16*300% -> 0 | AR16: 0 | AU16: =SUM(AL16:AT16) -> 21504.808 | AV16: =AH16+AK16+AU16+AG16+AF16 -> 8514889.4 | AW16: =Q16+R16+S16+T16 -> 5964000 | AX16: =AW16*17.5% -> 1043700 | AY16: =AW16*3% -> 178920 | AZ16: =AW16*1% -> 59640 | BA16: =AW16*2% -> 119280 | BB16: =AX16+AY16+AZ16+BA16 -> 1401540 | BC16: =AW16*8% -> 477120 | BD16: =AW16*1.5% -> 89460 | BE16: =AW16*1% -> 59640 | BF16: =BC16+BD16+BE16 -> 626220 | BG16: 11000000 | BI16: =BH16*4400000 -> 0 | BJ16: =V16 -> 600000 | BK16: =AV16-BJ16-AJ16*H16*0.5-AJ16*I16*0.95-AJ16*J16-AJ16*K16*1.6-AJ16*L16*2-AJ16*M16*2.9-AJ16*N16*2-AJ16*O16*2.9-P16*3.5 -> 7907721.2 | BL16: =IF(BK16-BI16-BG16-BF16<0,0,BK16-BI16-BG16-BF16) -> 0 | BM16: =ROUND(IF(BL16<=5000000,BL16*5%,IF(AND(BL16>5000000,BL16<=10000000),BL16*10%-250000,IF(AND(BL16>10000000,BL16<=18000000),BL16*15%-750000,IF(AND(BL16>18000000,BL16<=32000000),BL16*20%-1650000,IF(AND(BL16>32000000,BL16<=52000000),BL16*25%-3250000,IF(AND(BL16>52000000,BL16<80000000),BL16*30%-585000,IF(BL16>80000000,BL16*35%-9850000))))))),0) -> 0 | BN16: 35000 | BO16: =AV16-BF16-BM16-BN16 -> 7853669.4 | BP16: 104871827327
A17: =A16+1 -> 8 | B17: Nguyễn Khắc Linh | C17: Nấu ăn | D17: 208 | E17: 216 | Q17: 4706000 | R17: 1200000 | T17: 900000 | U17: 400000 | V17: =IF((E17+F17)>=160,U17, U17/D17*(E17+F17)) -> 400000 | W17: 400000 | X17: =IF((E17+F17)>=160,W17, W17/208*(E17+F17)) -> 400000 | Y17: 400000 | Z17: =IF((E17+F17)>=160,Y17, Y17/208*(E17+F17)) -> 400000 | AB17: 20000 | AC17: 500000 | AD17: =G17*13000 -> 0 | AH17: =V17+X17+Z17+AA17+AB17+AC17+AD17+AE17 -> 1720000 | AI17: =Q17+R17+S17+T17 -> 6806000 | AJ17: =AI17/D17 -> 32721.154 | AK17: =AJ17*E17 -> 7067769.2 | AL17: =AJ17*H17*150% -> 0 | AM17: =AJ17*I17*150%*130% -> 0 | AN17: =J17*200%*AJ17 -> 0 | AO17: =AJ17*K17*200% -> 0 | AP17: =L17*AJ17*300% -> 0 | AR17: 0 | AU17: =SUM(AL17:AT17) -> 0 | AV17: =AH17+AK17+AU17+AG17+AF17 -> 8787769.2 | AW17: =Q17+R17+S17+T17 -> 6806000 | AX17: =AW17*17.5% -> 1191050 | AY17: =AW17*3% -> 204180 | AZ17: =AW17*1% -> 68060 | BA17: =AW17*2% -> 136120 | BB17: =AX17+AY17+AZ17+BA17 -> 1599410 | BC17: =AW17*8% -> 544480 | BD17: =AW17*1.5% -> 102090 | BE17: =AW17*1% -> 68060 | BF17: =BC17+BD17+BE17 -> 714630 | BG17: 11000000 | BH17: 0 | BI17: =BH17*4400000 -> 0 | BJ17: =V17 -> 400000 | BK17: =AV17-BJ17-AJ17*H17*0.5-AJ17*I17*0.95-AJ17*J17-AJ17*K17*1.6-AJ17*L17*2-AJ17*M17*2.9-AJ17*N17*2-AJ17*O17*2.9-P17*3.5 -> 8387769.2 | BL17: =IF(BK17-BI17-BG17-BF17<0,0,BK17-BI17-BG17-BF17) -> 0 | BM17: =ROUND(IF(BL17<=5000000,BL17*5%,IF(AND(BL17>5000000,BL17<=10000000),BL17*10%-250000,IF(AND(BL17>10000000,BL17<=18000000),BL17*15%-750000,IF(AND(BL17>18000000,BL17<=32000000),BL17*20%-1650000,IF(AND(BL17>32000000,BL17<=52000000),BL17*25%-3250000,IF(AND(BL17>52000000,BL17<80000000),BL17*30%-585000,IF(BL17>80000000,BL17*35%-9850000))))))),0) -> 0 | BN17: 35000 | BO17: =AV17-BF17-BM17-BN17 -> 8038139.2 | BP17: 104872539680
A18: =A17+1 -> 9 | B18: Hoàng Việt Dũng | C18: Lái xe | D18: 208 | E18: 183 | H18: 31 | I18: 1.5 | J18: 1.5 | K18: 2.5 | Q18: 4480000 | R18: 1200000 | S18: 400000 | T18: 600000 | U18: 300000 | V18: =IF((E18+F18)>=160,U18, U18/D18*(E18+F18)) -> 300000 | W18: 600000 | X18: =IF((E18+F18)>=160,W18, W18/208*(E18+F18)) -> 600000 | Y18: 600000 | Z18: =IF((E18+F18)>=160,Y18, Y18/208*(E18+F18)) -> 600000 | AB18: 20000 | AC18: 500000 | AD18: =G18*13000 -> 0 | AH18: =V18+X18+Z18+AA18+AB18+AC18+AD18+AE18 -> 2020000 | AI18: =Q18+R18+S18+T18 -> 6680000 | AJ18: =AI18/D18 -> 32115.385 | AK18: =AJ18*E18 -> 5877115.4 | AL18: =AJ18*H18*150% -> 1493365.4 | AM18: =AJ18*I18*150%*130% -> 93937.5 | AN18: =J18*200%*AJ18 -> 96346.154 | AO18: =AJ18*K18*200% -> 160576.92 | AP18: =L18*AJ18*300% -> 0 | AR18: =AJ18*N18*300% -> 0 | AS18: =AJ18*O18*390% -> 0 | AU18: =SUM(AL18:AT18) -> 1844226 | AV18: =AH18+AK18+AU18+AG18+AF18 -> 9741341.3 | AW18: =Q18+R18+S18+T18 -> 6680000 | AX18: =AW18*17.5% -> 1169000 | AY18: =AW18*3% -> 200400 | AZ18: =AW18*1% -> 66800 | BA18: =AW18*2% -> 133600 | BB18: =AX18+AY18+AZ18+BA18 -> 1569800 | BC18: =AW18*8% -> 534400 | BD18: =AW18*1.5% -> 100200 | BE18: =AW18*1% -> 66800 | BF18: =BC18+BD18+BE18 -> 701400 | BG18: 11000000 | BH18: 0 | BI18: =BH18*4400000 -> 0 | BJ18: =V18 -> 300000 | BK18: =AV18-BJ18-AJ18*H18*0.5-AJ18*I18*0.95-AJ18*J18-AJ18*K18*1.6-AJ18*L18*2-AJ18*M18*2.9-AJ18*N18*2-AJ18*O18*2.9-P18*3.5 -> 8721153.8 | BL18: =IF(BK18-BI18-BG18-BF18<0,0,BK18-BI18-BG18-BF18) -> 0 | BM18: =ROUND(IF(BL18<=5000000,BL18*5%,IF(AND(BL18>5000000,BL18<=10000000),BL18*10%-250000,IF(AND(BL18>10000000,BL18<=18000000),BL18*15%-750000,IF(AND(BL18>18000000,BL18<=32000000),BL18*20%-1650000,IF(AND(BL18>32000000,BL18<=52000000),BL18*25%-3250000,IF(AND(BL18>52000000,BL18<80000000),BL18*30%-585000,IF(BL18>80000000,BL18*35%-9850000))))))),0) -> 0 | BN18: 35000 | BO18: =AV18-BF18-BM18-BN18 -> 9004941.3 | BP18: 104872402810
A19: =A18+1 -> 10 | B19: Đào Thị Thu Hằng | C19: TPKD | D19: 208 | E19: 184 | Q19: 10600000 | R19: 4000000 | S19: 2000000 | T19: 600000 | U19: 3000000 | V19: =IF((E19+F19)>=160,U19, U19/D19*(E19+F19)) -> 3000000 | W19: 1600000 | X19: =IF((E19+F19)>=160,W19, W19/208*(E19+F19)) -> 1600000 | Y19: 3000000 | Z19: =IF((E19+F19)>=160,Y19, Y19/208*(E19+F19)) -> 3000000 | AB19: 20000 | AC19: 500000 | AD19: =G19*13000 -> 0 | AH19: =V19+X19+Z19+AA19+AB19+AC19+AD19+AE19 -> 8120000 | AI19: =Q19+R19+S19+T19 -> 17200000 | AJ19: =AI19/D19 -> 82692.308 | AK19: =AJ19*E19 -> 15215385 | AL19: =AJ19*H19*150% -> 0 | AM19: =AJ19*I19*150%*130% -> 0 | AN19: =J19*200%*AJ19 -> 0 | AO19: =AJ19*K19*200% -> 0 | AP19: =L19*AJ19*300% -> 0 | AR19: =AJ19*N19*300% -> 0 | AU19: =SUM(AL19:AT19) -> 0 | AV19: =AH19+AK19+AU19+AG19+AF19 -> 23335385 | AW19: =Q19+R19+S19+T19 -> 17200000 | AX19: =AW19*17.5% -> 3010000 | AY19: =AW19*3% -> 516000 | AZ19: =AW19*1% -> 172000 | BA19: =AW19*2% -> 344000 | BB19: =AX19+AY19+AZ19+BA19 -> 4042000 | BC19: =AW19*8% -> 1376000 | BD19: =AW19*1.5% -> 258000 | BE19: =AW19*1% -> 172000 | BF19: =BC19+BD19+BE19 -> 1806000 | BG19: 11000000 | BH19: 2 | BI19: =BH19*4400000 -> 8800000 | BJ19: =V19 -> 3000000 | BK19: 22222163 | BL19: =IF(BK19-BI19-BG19-BF19<0,0,BK19-BI19-BG19-BF19) -> 616163 | BM19: =ROUND(IF(BL19<=5000000,BL19*5%,IF(AND(BL19>5000000,BL19<=10000000),BL19*10%-250000,IF(AND(BL19>10000000,BL19<=18000000),BL19*15%-750000,IF(AND(BL19>18000000,BL19<=32000000),BL19*20%-1650000,IF(AND(BL19>32000000,BL19<=52000000),BL19*25%-3250000,IF(AND(BL19>52000000,BL19<80000000),BL19*30%-585000,IF(BL19>80000000,BL19*35%-9850000))))))),0) -> 30808 | BN19: 35000 | BO19: =AV19-BF19-BM19-BN19 -> 21463577 | BP19: 100875693796
A20: =A19+1 -> 11 | B20: Vũ Thị Khánh Linh | C20: XNK | D20: 208 | E20: 184 | Q20: 5190000 | U20: 300000 | V20: =IF((E20+F20)>=160,U20, U20/D20*(E20+F20)) -> 300000 | W20: 1000000 | X20: =IF((E20+F20)>=160,W20, W20/208*(E20+F20)) -> 1000000 | Y20: 1000000 | Z20: =IF((E20+F20)>=160,Y20, Y20/208*(E20+F20)) -> 1000000 | AC20: 500000 | AD20: =G20*13000 -> 0 | AE20: 100000 | AH20: =V20+X20+Z20+AA20+AB20+AC20+AD20+AE20 -> 2900000 | AI20: =Q20+R20+S20+T20 -> 5190000 | AJ20: =AI20/D20 -> 24951.923 | AK20: =AJ20*E20 -> 4591153.8 | AL20: =AJ20*H20*150% -> 0 | AM20: =AJ20*I20*150%*130% -> 0 | AN20: =J20*200%*AJ20 -> 0 | AP20: =L20*AJ20*300% -> 0 | AR20: =AJ20*N20*300% -> 0 | AU20: =SUM(AL20:AT20) -> 0 | AV20: =AH20+AK20+AU20+AG20+AF20 -> 7491153.8 | AW20: =Q20+R20+S20+T20 -> 5190000 | AX20: =AW20*17.5% -> 908250 | AY20: =AW20*3% -> 155700 | AZ20: =AW20*1% -> 51900 | BA20: =AW20*2% -> 103800 | BB20: =AX20+AY20+AZ20+BA20 -> 1219650 | BC20: =AW20*8% -> 415200 | BD20: =AW20*1.5% -> 77850 | BE20: =AW20*1% -> 51900 | BF20: =BC20+BD20+BE20 -> 544950 | BG20: 11000000 | BI20: =BH20*4400000 -> 0 | BJ20: =V20 -> 300000 | BK20: =AV20-BJ20-AJ20*H20*0.5-AJ20*I20*0.95-AJ20*J20-AJ20*K20*1.6-AJ20*L20*2-AJ20*M20*2.9-AJ20*N20*2-AJ20*O20*2.9-P20*3.5 -> 7191153.8 | BL20: =IF(BK20-BI20-BG20-BF20<0,0,BK20-BI20-BG20-BF20) -> 0 | BM20: =ROUND(IF(BL20<=5000000,BL20*5%,IF(AND(BL20>5000000,BL20<=10000000),BL20*10%-250000,IF(AND(BL20>10000000,BL20<=18000000),BL20*15%-750000,IF(AND(BL20>18000000,BL20<=32000000),BL20*20%-1650000,IF(AND(BL20>32000000,BL20<=52000000),BL20*25%-3250000,IF(AND(BL20>52000000,BL20<80000000),BL20*30%-585000,IF(BL20>80000000,BL20*35%-9850000))))))),0) -> 0 | BN20: 35000 | BO20: =AV20-BF20-BM20-BN20 -> 6911203.8
A21: =A20+1 -> 12 | B21: Nghiêm Thị Ngọc Ánh | C21: NVKD | D21: 208 | E21: 184 | Q21: 5450000 | R21: 500000 | T21: 300000 | U21: 700000 | V21: =IF((E21+F21)>=160,U21, U21/D21*(E21+F21)) -> 700000 | W21: 800000 | X21: =IF((E21+F21)>=160,W21, W21/208*(E21+F21)) -> 800000 | Y21: 700000 | Z21: =IF((E21+F21)>=160,Y21, Y21/208*(E21+F21)) -> 700000 | AA21: 1710000 | AC21: 500000 | AD21: =G21*13000 -> 0 | AH21: =V21+X21+Z21+AA21+AB21+AC21+AD21+AE21 -> 4410000 | AI21: =Q21+R21+S21+T21 -> 6250000 | AJ21: =AI21/D21 -> 30048.077 | AK21: =AJ21*E21 -> 5528846.2 | AL21: =AJ21*H21*150% -> 0 | AM21: =AJ21*I21*150%*130% -> 0 | AN21: =J21*200%*AJ21 -> 0 | AO21: =AJ21*K21*200% -> 0 | AP21: =L21*AJ21*300% -> 0 | AR21: =AJ21*N21*300% -> 0 | AU21: =SUM(AL21:AT21) -> 0 | AV21: =AH21+AK21+AU21+AG21+AF21 -> 9938846.2 | AW21: =Q21+R21+S21+T21 -> 6250000 | AX21: =AW21*17.5% -> 1093750 | AY21: =AW21*3% -> 187500 | AZ21: =AW21*1% -> 62500 | BA21: =AW21*2% -> 125000 | BB21: =AX21+AY21+AZ21+BA21 -> 1468750 | BC21: =AW21*8% -> 500000 | BD21: =AW21*1.5% -> 93750 | BE21: =AW21*1% -> 62500 | BF21: =BC21+BD21+BE21 -> 656250 | BG21: 11000000 | BI21: =BH21*4400000 -> 0 | BJ21: =V21 -> 700000 | BK21: =AV21-BJ21-AJ21*H21*0.5-AJ21*I21*0.95-AJ21*J21-AJ21*K21*1.6-AJ21*L21*2-AJ21*M21*2.9-AJ21*N21*2-AJ21*O21*2.9-P21*3.5 -> 9238846.2 | BL21: =IF(BK21-BI21-BG21-BF21<0,0,BK21-BI21-BG21-BF21) -> 0 | BM21: =ROUND(IF(BL21<=5000000,BL21*5%,IF(AND(BL21>5000000,BL21<=10000000),BL21*10%-250000,IF(AND(BL21>10000000,BL21<=18000000),BL21*15%-750000,IF(AND(BL21>18000000,BL21<=32000000),BL21*20%-1650000,IF(AND(BL21>32000000,BL21<=52000000),BL21*25%-3250000,IF(AND(BL21>52000000,BL21<80000000),BL21*30%-585000,IF(BL21>80000000,BL21*35%-9850000))))))),0) -> 0 | BN21: 35000 | BO21: =AV21-BF21-BM21-BN21 -> 9247596.2 | BP21: 104877225771
A22: =A21+1 -> 13 | B22: Phan Thị Thanh Tâm | C22: XNK | D22: 208 | E22: 184 | Q22: 5190000 | R22: 500000 | V22: =IF((E22+F22)>=160,U22, U22/D22*(E22+F22)) -> 0 | W22: 1600000 | X22: =IF((E22+F22)>=160,W22, W22/208*(E22+F22)) -> 1600000 | Y22: 1600000 | Z22: =IF((E22+F22)>=160,Y22, Y22/208*(E22+F22)) -> 1600000 | AA22: 230000 | AC22: 500000 | AD22: =G22*13000 -> 0 | AH22: =V22+X22+Z22+AA22+AB22+AC22+AD22+AE22 -> 3930000 | AI22: =Q22+R22+S22+T22 -> 5690000 | AJ22: =AI22/D22 -> 27355.769 | AK22: =AJ22*E22 -> 5033461.5 | AL22: =AJ22*H22*150% -> 0 | AM22: =AJ22*I22*150%*130% -> 0 | AN22: =J22*200%*AJ22 -> 0 | AP22: =L22*AJ22*300% -> 0 | AR22: =AJ22*N22*300% -> 0 | AU22: =SUM(AL22:AT22) -> 0 | AV22: =AH22+AK22+AU22+AG22+AF22 -> 8963461.5 | AW22: =Q22+R22+S22+T22 -> 5690000 | AX22: =AW22*17.5% -> 995750 | AY22: =AW22*3% -> 170700 | AZ22: =AW22*1% -> 56900 | BA22: =AW22*2% -> 113800 | BB22: =AX22+AY22+AZ22+BA22 -> 1337150 | BC22: =AW22*8% -> 455200 | BD22: =AW22*1.5% -> 85350 | BE22: =AW22*1% -> 56900 | BF22: =BC22+BD22+BE22 -> 597450 | BG22: 11000000 | BH22: 0 | BI22: =BH22*4400000 -> 0 | BJ22: =V22 -> 0 | BK22: =AV22-BJ22-AJ22*H22*0.5-AJ22*I22*0.95-AJ22*J22-AJ22*K22*1.6-AJ22*L22*2-AJ22*M22*2.9-AJ22*N22*2-AJ22*O22*2.9-P22*3.5 -> 8963461.5 | BL22: =IF(BK22-BI22-BG22-BF22<0,0,BK22-BI22-BG22-BF22) -> 0 | BM22: =ROUND(IF(BL22<=5000000,BL22*5%,IF(AND(BL22>5000000,BL22<=10000000),BL22*10%-250000,IF(AND(BL22>10000000,BL22<=18000000),BL22*15%-750000,IF(AND(BL22>18000000,BL22<=32000000),BL22*20%-1650000,IF(AND(BL22>32000000,BL22<=52000000),BL22*25%-3250000,IF(AND(BL22>52000000,BL22<80000000),BL22*30%-585000,IF(BL22>80000000,BL22*35%-9850000))))))),0) -> 0 | BN22: 35000 | BO22: =AV22-BF22-BM22-BN22 -> 8331011.5
A23: Tổng | D23: =SUM(D10:D22) -> 2712 | E23: =SUM(E10:E22) -> 2311 | F23: =SUM(F10:F22) -> 0 | G23: =SUM(G10:G22) -> 0 | I23: =SUM(I10:I22) -> 1.5 | J23: =SUM(J10:J22) -> 1.5 | K23: =SUM(K10:K22) -> 2.5 | L23: =SUM(L10:L22) -> 0 | M23: =SUM(M10:M22) -> 0 | N23: =SUM(N10:N22) -> 0 | O23: =SUM(O10:O22) -> 0 | P23: =SUM(P10:P22) -> 0 | ... AE23: =SUM(AE10:AE22) -> 200000 | AG23: =SUM(AG10:AG22) -> 0 | AH23: =SUM(AH10:AH22) -> 43540000 | AI23: =SUM(AI10:AI22) -> 110326000 | AJ23: =SUM(AJ10:AJ22) -> 526309.12 | AK23: =SUM(AK10:AK22) -> 98107115 | AL23: =SUM(AL10:AL22) -> 1514870.2 | AM23: =SUM(AM10:AM22) -> 93937.5 | AN23: =SUM(AN10:AN22) -> 96346.154 | ... BO23: =SUM(BO10:BO22) -> 1.3407806e+08 | BQ23: =BO23+'Payroll of factory '!BO22+'Payroll of factory (SOI) '!BQ27+'Payroll of factory (DET).1'!BR40 -> 5.7076869e+08
B25: Scheduling | AF25: Manager | BO25: Director- general

Sheet Payroll of factory  
A1: CÔNG TY TNHH SHINSUNG VINA
A2: Lô CN04, khu công nghiệp Cẩm Khê, TT.Cẩm Khê, H.Cẩm Khê, T.Phú Thọ
A3: ='Payroll Office'!A3:BO3 -> PAYROLL AUGUST 2024
A4: ='Payroll Office'!A4:BO4 -> From 1st -31th August 2024
A6: STT (No) | B6: Họ và tên (First and last name) | C6: Vị trí (Location) | D6: Tổng giờ công chuẩn | E6: Giờ công cơ bản thực tế (The actual basic hourly) | G6: Số bữa phụ | H6: Giờ công làm thêm (Hours of overtime) | Q6: Lương cơ bản (Basic salary) | U6: Các khoản phụ cấp (Allowances) | AF6: Thưởng Tết Âm lịch 20% (Ngày lễ 02/09) | AG6: Khấu trừ khác | AH6: Tổng phụ cấp không đóng BH được nhận (Total allowances) | AI6: Lương đóng bảo hiểm | AJ6: Lương giờ công | AK6: Tổng lương giờ công cơ bản | AL6: Lương giờ công làm thêm | AV6: Tổng lương | AW6: BH tính vào chi phí / Isuarance payable by company | BC6: BH khấu trừ lương / Isuarance deductions from salary | BG6: Thuế TNCN | BN6: Đoàn phí | BO6: Thực nhận | BP6: Số tài khoản | BQ6: Ký nhận
E7: Ca ngày | F7: Ca đêm | H7: Tăng ca 150% | I7: Tăng ca đêm 195% | J7: CN ngày 200% | K7: CN đêm 260% | L7: Tăng ca ngày CN 300% | M7: Tăng ca đêm CN 390% | N7: Ngày lễ ngày 300% | O7: Ngày lễ đêm 390% | P7: TC lễ (450%) | Q7: Lương cơ bản (Basic salary) | R7: Phụ cấp trách nhiệm/ Responsibility allowance | S7: PC ngoại ngữ/ Foreign language support | T7: Phụ cấp thâm niên/ Seniority allowances | U7: HT điện thoại /Phone charges/ 26 Công | V7: HT điện thoại /Phone charges | W7: HT xăng xe /Fuel costs for vehicles/ 26 Công | X7: HT xăng xe /Fuel costs for vehicles | Y7: HT nhà ở /Housing support/ 26 Công | Z7: HT nhà ở /Housing support | AA7: Phụ cấp đi lại | AB7: HT con nhỏ /Supporting children | AC7: Thưởng Chuyên cần /Reward for diligence | AD7: Trợ cấp bữa phụ /Snack allowance | AE7: ='Payroll Office'!AE8 -> Thưởng sinh nhật tháng 08 /Birthday in August | AL7: Tăng ca ngày | AM7: Tăng ca đêm | AN7: CN ngày | AO7: CN đêm | AP7: Tăng ca ngày CN | AQ7: Tăng ca đêm CN | AR7: Ngày lễ ngày | AS7: Ngày lễ đêm | AT7: TC lễ | AU7: Tổng lương làm thêm | AW7: Lương đóng bảo hiểm/Salary base for insurance | AX7: BHXH / Social Insurance 17% | AY7: BHYT / Health Insurance 3%건강보험 (회사분) | AZ7: BHTN / Unemployment Insurance 1% | BA7: KPCĐ 2% | BB7: Cộng /Amount Isurance | BC7: BHXH / Social Insurance 8% | BD7: BHYT / Health Insurance 1,5% 건강보험 (개인분) | BE7: BHTN / Unemployment Insurance 1% | BF7: Cộng 10.5%/Amount Isurance | BG7: Giảm trừ bản thân (기본공제금 ) (VND) | BH7: Số người phụ thuộc /Number Deduction family | BI7: Giảm trừ người phụ thuộc /deduction-family 4400000/1person | BJ7: Tax excemption | BK7: Thu nhập chịu thuế | BL7: Thu nhập tính thuế (과세 대상 금액) VND | BM7: Thuế TNCN (개인소득세) ( VND)
A8: -1 | B8: -2 | C8: -3 | E8: (4a) | F8: (4b) | H8: (5a) | I8: (5b) | J8: (6a) | K8: (6b) | L8: (6c) | M8: (6d) | N8: 6e | O8: -7 | P8: 7a | Q8: -8 | R8: -9 | T8: (11c) | V8: -10 | X8: -11 | Z8: (11 a) | AB8: (11b) | AC8: -12 | AD8: -17 | AH8: -13 | AI8: -14 | AJ8: -15 | AK8: -16 | AL8: -18 | AM8: -19 | AN8: -20 | AO8: 17c=6b*15*200%*130% | AP8: (18)=(6c)* (15)*200%*150% | AQ8: 18a=6d*15*200%*150%*130% | AR8: (19)=(6e)* (15)*300% | AS8: 19a=7*15*130%*300% | AT8: 19b=7a*15*150%*300% | AU8: -21 | AV8: -22 | AW8: -23 | AX8: -24 | AY8: -25 | AZ8: -26 | BB8: -27 | BC8: -28 | BD8: -29 | BE8: -30 | BF8: -31 | BG8: -32 | BH8: -33 | BI8: -34 | BJ8: -35 | BK8: -36 | BL8: -36 | BM8: -37 | BO8: -39
A9: 1 | B9: Nguyễn Thị Hân | C9: TKS | D9: 208 | E9: 192 | H9: 0.5 | Q9: 5141000 | R9: 1300000 | T9: 600000 | U9: 1000000 | V9: =IF((E9+F9)>=160, U9, U9/D9*(E9+F9)) -> 1000000 | W9: 1000000 | X9: =IF((E9+F9)>=160, W9, W9/D9*(E9+F9)) -> 1000000 | Y9: 1000000 | Z9: =IF((E9+F9)>=160, Y9, Y9/D9*(E9+F9)) -> 1000000 | AA9: 0 | AB9: 20000 | AC9: =IF(E9>=184,500000,0) -> 500000 | AD9: =G9*13000 -> 0 | AE9: 0 | AH9: =V9+Z9+X9+AA9+AB9+AC9+AD9+AE9 -> 3520000 | AI9: =Q9+R9+T9 -> 7041000 | AJ9: =AI9/208 -> 33850.962 | AK9: =AJ9*(E9+F9*130%) -> 6499384.6 | AL9: =AJ9*H9*150% -> 25388.221 | AM9: =AJ9*I9*150%*130% -> 0 | AN9: =+AJ9*J9*200% -> 0 | AO9: =AJ9*K9*200%*130% -> 0 | AP9: =AJ9*L9*200%*150% -> 0 | AQ9: =AJ9*M9*200%*150%*130% -> 0 | AR9: =N9*AJ9*300% -> 0 | AS9: =AJ9*O9*300% -> 0 | AT9: =P9*AJ9*150%*300% -> 0 | AU9: =SUM(AL9:AT9) -> 25388.221 | AV9: =AH9+AK9+AU9+AG9+AF9 -> 10044773 | AW9: =Q9+R9+T9 -> 7041000 | AX9: =AW9*17.5% -> 1232175 | AY9: =AW9*3% -> 211230 | AZ9: =AW9*1% -> 70410 | BA9: =AW9*2% -> 140820 | BB9: =AX9+AY9+AZ9+BA9 -> 1654635 | BC9: =AW9*8% -> 563280 | BD9: =AW9*1.5% -> 105615 | BE9: =AW9*1% -> 70410 | BF9: =BC9+BD9+BE9 -> 739305 | BG9: 11000000 | BH9: 1 | BI9: =BH9*4400000 -> 4400000 | BJ9: =V9+AA9 -> 1000000 | BK9: =AV9-BJ9-AJ9*H9*0.5-AJ9*I9*0.95-AJ9*J9-AJ9*K9*1.6-AJ9*L9*2-AJ9*M9*2.9-AJ9*N9*2-AJ9*O9*2.9-AJ9*P9*3.5 -> 9036310.1 | BL9: =IF(BK9-BG9-BF9-BI9<0,0,BK9-BG9-BI9-BF9) -> 0 | BM9: =ROUND(IF(BL9<=5000000,BL9*5%,IF(AND(BL9>5000000,BL9<=10000000),BL9*10%-250000,IF(AND(BL9>10000000,BL9<=18000000),BL9*15%-750000,IF(AND(BL9>18000000,BL9<=32000000),BL9*20%-1650000,IF(AND(BL9>32000000,BL9<=52000000),BL9*25%-3250000,IF(AND(BL9>52000000,BL9<80000000),BL9*30%-585000,IF(BL9>80000000,BL9*35%-9850000))))))),0) -> 0 | BN9: 35000 | BO9: =AV9-BF9-BM9-BN9 -> 9270467.8 | BP9: 109878080755
A10: 2 | B10: Đỗ Thị Kim Liên (Từ ngày 01-04/08) | C10: TKS | D10: 208 | E10: 24 | Q10: 5190000 | R10: 0 | S10: 0 | T10: 0 | U10: 0 | V10: =IF((E10+F10)>=160, U10, U10/D10*(E10+F10)) -> 0 | W10: 1200000 | AD10: =G10*13000 -> 0 | AH10: =V10+Z10+X10+AA10+AB10+AC10+AD10+AE10 -> 0 | AI10: =Q10+R10+T10 -> 5190000 | AJ10: =AI10/208 -> 24951.923 | AK10: =AJ10*(E10+F10*130%) -> 598846.15 | AL10: =AJ10*H10*150% -> 0 | AM10: =AJ10*I10*150%*130% -> 0 | AN10: =+AJ10*J10*200% -> 0 | AO10: =AJ10*K10*200%*130% -> 0 | AP10: =AJ10*L10*200%*150% -> 0 | AQ10: =AJ10*M10*200%*150%*130% -> 0 | AR10: =N10*AJ10*300% -> 0 | AS10: =AJ10*O10*300% -> 0 | AT10: =P10*AJ10*150%*300% -> 0 | AU10: =SUM(AL10:AT10) -> 0 | AV10: =AH10+AK10+AU10+AG10+AF10 -> 598846.15 | AW10: 0 | AX10: =AW10*17.5% -> 0 | AY10: =AW10*3% -> 0 | AZ10: =AW10*1% -> 0 | BA10: =AW10*2% -> 0 | BB10: =AX10+AY10+AZ10+BA10 -> 0 | BC10: =AW10*8% -> 0 | BD10: =AW10*1.5% -> 0 | BE10: =AW10*1% -> 0 | BF10: =BC10+BD10+BE10 -> 0 | BG10: 11000000 | BI10: =BH10*4400000 -> 0 | BJ10: =V10+AA10 -> 0 | BK10: =AV10-BJ10-AJ10*H10*0.5-AJ10*I10*0.95-AJ10*J10-AJ10*K10*1.6-AJ10*L10*2-AJ10*M10*2.9-AJ10*N10*2-AJ10*O10*2.9-AJ10*P10*3.5 -> 598846.15 | BL10: =IF(BK10-BG10-BF10-BI10<0,0,BK10-BG10-BI10-BF10) -> 0 | BM10: =ROUND(IF(BL10<=5000000,BL10*5%,IF(AND(BL10>5000000,BL10<=10000000),BL10*10%-250000,IF(AND(BL10>10000000,BL10<=18000000),BL10*15%-750000,IF(AND(BL10>18000000,BL10<=32000000),BL10*20%-1650000,IF(AND(BL10>32000000,BL10<=52000000),BL10*25%-3250000,IF(AND(BL10>52000000,BL10<80000000),BL10*30%-585000,IF(BL10>80000000,BL10*35%-9850000))))))),0) -> 0 | BN10: 0 | BO10: =AV10-BF10-BM10-BN10 -> 598846.15 | BQ10: =BO10+BO11 -> 7423906.2
A11: 3 | B11: Đỗ Thị Kim Liên (Từ ngày 05-31/08) | C11: TKS | D11: 208 | E11: 160 | H11: 0.5 | Q11: 5450000 | R11: 0 | S11: 0 | T11: 300000 | U11: 0 | V11: =IF((E11+F11)>=160, U11, U11/D11*(E11+F11)) -> 0 | W11: 1200000 | X11: =IF((E11+F11)>=160, W11, W11/D11*(E11+F11)) -> 1200000 | Y11: 1300000 | Z11: =IF((E11+F11)>=160, Y11, Y11/D11*(E11+F11)) -> 1300000 | AA11: 0 | AB11: 20000 | AC11: 500000 | AD11: =G11*13000 -> 0 | AH11: =V11+Z11+X11+AA11+AB11+AC11+AD11+AE11 -> 3020000 | AI11: =Q11+R11+T11 -> 5750000 | AJ11: =AI11/208 -> 27644.231 | AK11: =AJ11*(E11+F11*130%) -> 4423076.9 | AL11: =AJ11*H11*150% -> 20733.173 | AM11: =AJ11*I11*150%*130% -> 0 | AN11: =+AJ11*J11*200% -> 0 | AO11: =AJ11*K11*200%*130% -> 0 | AP11: =AJ11*L11*200%*150% -> 0 | AQ11: =AJ11*M11*200%*150%*130% -> 0 | AR11: =N11*AJ11*300% -> 0 | AS11: =AJ11*O11*300% -> 0 | AT11: =P11*AJ11*150%*300% -> 0 | AU11: =SUM(AL11:AT11) -> 20733.173 | AV11: =AH11+AK11+AU11+AG11+AF11 -> 7463810.1 | AW11: =Q11+R11+T11 -> 5750000 | AX11: =AW11*17.5% -> 1006250 | AY11: =AW11*3% -> 172500 | AZ11: =AW11*1% -> 57500 | BA11: =AW11*2% -> 115000 | BB11: =AX11+AY11+AZ11+BA11 -> 1351250 | BC11: =AW11*8% -> 460000 | BD11: =AW11*1.5% -> 86250 | BE11: =AW11*1% -> 57500 | BF11: =BC11+BD11+BE11 -> 603750 | BG11: 11000000 | BI11: =BH11*4400000 -> 0 | BJ11: =V11+AA11 -> 0 | BK11: =AV11-BJ11-AJ11*H11*0.5-AJ11*I11*0.95-AJ11*J11-AJ11*K11*1.6-AJ11*L11*2-AJ11*M11*2.9-AJ11*N11*2-AJ11*O11*2.9-AJ11*P11*3.5 -> 7456899 | BL11: =IF(BK11-BG11-BF11-BI11<0,0,BK11-BG11-BI11-BF11) -> 0 | BM11: =ROUND(IF(BL11<=5000000,BL11*5%,IF(AND(BL11>5000000,BL11<=10000000),BL11*10%-250000,IF(AND(BL11>10000000,BL11<=18000000),BL11*15%-750000,IF(AND(BL11>18000000,BL11<=32000000),BL11*20%-1650000,IF(AND(BL11>32000000,BL11<=52000000),BL11*25%-3250000,IF(AND(BL11>52000000,BL11<80000000),BL11*30%-585000,IF(BL11>80000000,BL11*35%-9850000))))))),0) -> 0 | BN11: 35000 | BO11: =AV11-BF11-BM11-BN11 -> 6825060.1
A12: 4 | B12: Trần Đại Lượng (Từ ngày 01-12/08) | C12: VHXN | D12: 208 | E12: 72 | Q12: 4267000 | R12: 947000 | T12: 600000 | U12: 700000 | AD12: =G12*13000 -> 0 | AE12: 0 | AH12: =V12+Z12+X12+AA12+AB12+AC12+AD12+AE12 -> 0 | AI12: =Q12+R12+T12 -> 5814000 | AJ12: =AI12/208 -> 27951.923 | AK12: =AJ12*(E12+F12*130%) -> 2012538.5 | AL12: =AJ12*H12*150% -> 0 | AM12: =AJ12*I12*150%*130% -> 0 | AN12: =+AJ12*J12*200% -> 0 | AO12: =AJ12*K12*200%*130% -> 0 | AP12: =AJ12*L12*200%*150% -> 0 | AQ12: =AJ12*M12*200%*150%*130% -> 0 | AR12: =N12*AJ12*300% -> 0 | AS12: =AJ12*O12*300% -> 0 | AT12: =P12*AJ12*150%*300% -> 0 | AU12: =SUM(AL12:AT12) -> 0 | AV12: =AH12+AK12+AU12+AG12+AF12 -> 2012538.5 | AX12: =AW12*17.5% -> 0 | AY12: =AW12*3% -> 0 | AZ12: =AW12*1% -> 0 | BA12: =AW12*2% -> 0 | BB12: =AX12+AY12+AZ12+BA12 -> 0 | BC12: =AW12*8% -> 0 | BD12: =AW12*1.5% -> 0 | BE12: =AW12*1% -> 0 | BF12: =BC12+BD12+BE12 -> 0 | BG12: 11000000 | BI12: =BH12*4400000 -> 0 | BJ12: =V12+AA12 -> 0 | BK12: =AV12-BJ12-AJ12*H12*0.5-AJ12*I12*0.95-AJ12*J12-AJ12*K12*1.6-AJ12*L12*2-AJ12*M12*2.9-AJ12*N12*2-AJ12*O12*2.9-AJ12*P12*3.5 -> 2012538.5 | BL12: =IF(BK12-BG12-BF12-BI12<0,0,BK12-BG12-BI12-BF12) -> 0 | BM12: =ROUND(IF(BL12<=5000000,BL12*5%,IF(AND(BL12>5000000,BL12<=10000000),BL12*10%-250000,IF(AND(BL12>10000000,BL12<=18000000),BL12*15%-750000,IF(AND(BL12>18000000,BL12<=32000000),BL12*20%-1650000,IF(AND(BL12>32000000,BL12<=52000000),BL12*25%-3250000,IF(AND(BL12>52000000,BL12<80000000),BL12*30%-585000,IF(BL12>80000000,BL12*35%-9850000))))))),0) -> 0 | BO12: =AV12-BF12-BM12-BN12 -> 2012538.5 | BQ12: =BO12+BO13 -> 7462876.2
A13: 5 | B13: Trần Đại Lượng (Từ ngày 13-31/08) | C13: VHXN | D13: 208 | E13: 120 | Q13: 4267000 | R13: 947000 | T13: 900000 | U13: 700000 | V13: 700000 | W13: 700000 | X13: 700000 | Y13: 700000 | Z13: 700000 | AA13: 0 | AC13: 500000 | AD13: =G13*13000 -> 0 | AE13: 0 | AH13: =V13+Z13+X13+AA13+AB13+AC13+AD13+AE13 -> 2600000 | AI13: =Q13+R13+T13 -> 6114000 | AJ13: =AI13/208 -> 29394.231 | AK13: =AJ13*(E13+F13*130%) -> 3527307.7 | AL13: =AJ13*H13*150% -> 0 | AM13: =AJ13*I13*150%*130% -> 0 | AN13: =+AJ13*J13*200% -> 0 | AO13: =AJ13*K13*200%*130% -> 0 | AP13: =AJ13*L13*200%*150% -> 0 | AQ13: =AJ13*M13*200%*150%*130% -> 0 | AR13: =N13*AJ13*300% -> 0 | AS13: =AJ13*O13*300% -> 0 | AT13: =P13*AJ13*150%*300% -> 0 | AU13: =SUM(AL13:AT13) -> 0 | AV13: =AH13+AK13+AU13+AG13+AF13 -> 6127307.7 | AW13: =Q13+R13+T13 -> 6114000 | AX13: =AW13*17.5% -> 1069950 | AY13: =AW13*3% -> 183420 | AZ13: =AW13*1% -> 61140 | BA13: =AW13*2% -> 122280 | BB13: =AX13+AY13+AZ13+BA13 -> 1436790 | BC13: =AW13*8% -> 489120 | BD13: =AW13*1.5% -> 91710 | BE13: =AW13*1% -> 61140 | BF13: =BC13+BD13+BE13 -> 641970 | BG13: 11000000 | BI13: =BH13*4400000 -> 0 | BJ13: =V13+AA13 -> 700000 | BK13: =AV13-BJ13-AJ13*H13*0.5-AJ13*I13*0.95-AJ13*J13-AJ13*K13*1.6-AJ13*L13*2-AJ13*M13*2.9-AJ13*N13*2-AJ13*O13*2.9-AJ13*P13*3.5 -> 5427307.7 | BL13: =IF(BK13-BG13-BF13-BI13<0,0,BK13-BG13-BI13-BF13) -> 0 | BM13: =ROUND(IF(BL13<=5000000,BL13*5%,IF(AND(BL13>5000000,BL13<=10000000),BL13*10%-250000,IF(AND(BL13>10000000,BL13<=18000000),BL13*15%-750000,IF(AND(BL13>18000000,BL13<=32000000),BL13*20%-1650000,IF(AND(BL13>32000000,BL13<=52000000),BL13*25%-3250000,IF(AND(BL13>52000000,BL13<80000000),BL13*30%-585000,IF(BL13>80000000,BL13*35%-9850000))))))),0) -> 0 | BN13: 35000 | BO13: =AV13-BF13-BM13-BN13 -> 5450337.7
A14: 6 | B14: Nguyễn Thị Khởi | C14: VSS | D14: 208 | E14: 184 | H14: 2 | Q14: 4064000 | R14: 0 | T14: 600000 | U14: 300000 | V14: =IF((E14+F14)>=160, U14, U14/D14*(E14+F14)) -> 300000 | W14: 300000 | X14: =IF((E14+F14)>=160, W14, W14/D14*(E14+F14)) -> 300000 | Y14: 0 | Z14: =IF((E14+F14)>=160, Y14, Y14/D14*(E14+F14)) -> 0 | AA14: 0 | AC14: =IF(E14>=184,500000,0) -> 500000 | AD14: =G14*13000 -> 0 | AE14: 0 | AH14: =V14+Z14+X14+AA14+AB14+AC14+AD14+AE14 -> 1100000 | AI14: =Q14+R14+T14 -> 4664000 | AJ14: =AI14/208 -> 22423.077 | AK14: =AJ14*(E14+F14*130%) -> 4125846.2 | AL14: =AJ14*H14*150% -> 67269.231 | AM14: =AJ14*I14*150%*130% -> 0 | AN14: =+AJ14*J14*200% -> 0 | AO14: =AJ14*K14*200%*130% -> 0 | AP14: =AJ14*L14*200%*150% -> 0 | AQ14: =AJ14*M14*200%*150%*130% -> 0 | AR14: =N14*AJ14*300% -> 0 | AS14: =AJ14*O14*300% -> 0 | AT14: =P14*AJ14*150%*300% -> 0 | AU14: =SUM(AL14:AT14) -> 67269.231 | AV14: =AH14+AK14+AU14+AG14+AF14 -> 5293115.4 | AW14: =Q14+R14+T14 -> 4664000 | AX14: =AW14*17.5% -> 816200 | AY14: =AW14*3% -> 139920 | AZ14: =AW14*1% -> 46640 | BA14: =AW14*2% -> 93280 | BB14: =AX14+AY14+AZ14+BA14 -> 1096040 | BC14: =AW14*8% -> 373120 | BD14: =AW14*1.5% -> 69960 | BE14: =AW14*1% -> 46640 | BF14: =BC14+BD14+BE14 -> 489720 | BG14: 11000000 | BI14: =BH14*4400000 -> 0 | BJ14: =V14+AA14 -> 300000 | BK14: =AV14-BJ14-AJ14*H14*0.5-AJ14*I14*0.95-AJ14*J14-AJ14*K14*1.6-AJ14*L14*2-AJ14*M14*2.9-AJ14*N14*2-AJ14*O14*2.9-AJ14*P14*3.5 -> 4970692.3 | BL14: =IF(BK14-BG14-BF14-BI14<0,0,BK14-BG14-BI14-BF14) -> 0 | BM14: =ROUND(IF(BL14<=5000000,BL14*5%,IF(AND(BL14>5000000,BL14<=10000000),BL14*10%-250000,IF(AND(BL14>10000000,BL14<=18000000),BL14*15%-750000,IF(AND(BL14>18000000,BL14<=32000000),BL14*20%-1650000,IF(AND(BL14>32000000,BL14<=52000000),BL14*25%-3250000,IF(AND(BL14>52000000,BL14<80000000),BL14*30%-585000,IF(BL14>80000000,BL14*35%-9850000))))))),0) -> 0 | BN14: 35000 | BO14: =AV14-BF14-BM14-BN14 -> 4768395.4 | BP14: 108878727028 | BQ14: =SUM(BO9:BO14)+'Payroll of factory (SOI) '!BQ10 -> 39985496
A15: 7 | B15: Hoàng Thị Bích Thành | C15: VPD | D15: 208 | E15: 192 | H15: 5 | Q15: 5450000 | R15: 1300000 | T15: 600000 | U15: 1400000 | V15: =IF((E15+F15)>=160, U15, U15/D15*(E15+F15)) -> 1400000 | W15: 1400000 | X15: =IF((E15+F15)>=160, W15, W15/D15*(E15+F15)) -> 1400000 | Y15: 1400000 | Z15: =IF((E15+F15)>=160, Y15, Y15/D15*(E15+F15)) -> 1400000 | AA15: 0 | AC15: =IF(E15>=184,500000,0) -> 500000 | AD15: =G15*13000 -> 0 | AE15: 0 | AH15: =V15+Z15+X15+AA15+AB15+AC15+AD15+AE15 -> 4700000 | AI15: =Q15+R15+T15 -> 7350000 | AJ15: =AI15/208 -> 35336.538 | AK15: =AJ15*(E15+F15*130%) -> 6784615.4 | AL15: =AJ15*H15*150% -> 265024.04 | AM15: =AJ15*I15*150%*130% -> 0 | AN15: =+AJ15*J15*200% -> 0 | AO15: =AJ15*K15*200%*130% -> 0 | AP15: =AJ15*L15*200%*150% -> 0 | AQ15: =AJ15*M15*200%*150%*130% -> 0 | AR15: =N15*AJ15*300% -> 0 | AS15: =AJ15*O15*300% -> 0 | AT15: =P15*AJ15*150%*300% -> 0 | AU15: =SUM(AL15:AT15) -> 265024.04 | AV15: =AH15+AK15+AU15+AG15+AF15 -> 11749639 | AW15: =Q15+R15+T15 -> 7350000 | AX15: =AW15*17.5% -> 1286250 | AY15: =AW15*3% -> 220500 | AZ15: =AW15*1% -> 73500 | BA15: =AW15*2% -> 147000 | BB15: =AX15+AY15+AZ15+BA15 -> 1727250 | BC15: =AW15*8% -> 588000 | BD15: =AW15*1.5% -> 110250 | BE15: =AW15*1% -> 73500 | BF15: =BC15+BD15+BE15 -> 771750 | BG15: 11000000 | BH15: 1 | BI15: =BH15*4400000 -> 4400000 | BJ15: =V15+AA15 -> 1400000 | BK15: =AV15-BJ15-AJ15*H15*0.5-AJ15*I15*0.95-AJ15*J15-AJ15*K15*1.6-AJ15*L15*2-AJ15*M15*2.9-AJ15*N15*2-AJ15*O15*2.9-AJ15*P15*3.5 -> 10261298 | BL15: =IF(BK15-BG15-BF15-BI15<0,0,BK15-BG15-BI15-BF15) -> 0 | BM15: =ROUND(IF(BL15<=5000000,BL15*5%,IF(AND(BL15>5000000,BL15<=10000000),BL15*10%-250000,IF(AND(BL15>10000000,BL15<=18000000),BL15*15%-750000,IF(AND(BL15>18000000,BL15<=32000000),BL15*20%-1650000,IF(AND(BL15>32000000,BL15<=52000000),BL15*25%-3250000,IF(AND(BL15>52000000,BL15<80000000),BL15*30%-585000,IF(BL15>80000000,BL15*35%-9850000))))))),0) -> 0 | BN15: 35000 | BO15: =AV15-BF15-BM15-BN15 -> 10942889 | BP15: 101874719380
A16: 8 | B16: Nguyễn Thị Định | C16: TKD | D16: 208 | E16: 184 | H16: 1 | Q16: 4940000 | R16: 1000000 | T16: 600000 | U16: 0 | V16: =IF((E16+F16)>=160, U16, U16/D16*(E16+F16)) -> 0 | W16: 600000 | X16: =IF((E16+F16)>=160, W16, W16/D16*(E16+F16)) -> 600000 | Y16: 600000 | Z16: =IF((E16+F16)>=160, Y16, Y16/D16*(E16+F16)) -> 600000 | AA16: 0 | AB16: 40000 | AC16: =IF(E16>=184,500000,0) -> 500000 | AD16: =G16*13000 -> 0 | AE16: 100000 | AH16: =V16+Z16+X16+AA16+AB16+AC16+AD16+AE16 -> 1840000 | AI16: =Q16+R16+T16 -> 6540000 | AJ16: =AI16/208 -> 31442.308 | AK16: =AJ16*(E16+F16*130%) -> 5785384.6 | AL16: =AJ16*H16*150% -> 47163.462 | AM16: =AJ16*I16*150%*130% -> 0 | AN16: =+AJ16*J16*200% -> 0 | AO16: =AJ16*K16*200%*130% -> 0 | AP16: =AJ16*L16*200%*150% -> 0 | AQ16: =AJ16*M16*200%*150%*130% -> 0 | AR16: =N16*AJ16*300% -> 0 | AS16: =AJ16*O16*300% -> 0 | AT16: =P16*AJ16*150%*300% -> 0 | AU16: =SUM(AL16:AT16) -> 47163.462 | AV16: =AH16+AK16+AU16+AG16+AF16 -> 7672548.1 | AW16: =Q16+R16+T16 -> 6540000 | AX16: =AW16*17.5% -> 1144500 | AY16: =AW16*3% -> 196200 | AZ16: =AW16*1% -> 65400 | BA16: =AW16*2% -> 130800 | BB16: =AX16+AY16+AZ16+BA16 -> 1536900 | BC16: =AW16*8% -> 523200 | BD16: =AW16*1.5% -> 98100 | BE16: =AW16*1% -> 65400 | BF16: =BC16+BD16+BE16 -> 686700 | BG16: 11000000 | BI16: =BH16*4400000 -> 0 | BJ16: =V16+AA16 -> 0 | BK16: =AV16-BJ16-AJ16*H16*0.5-AJ16*I16*0.95-AJ16*J16-AJ16*K16*1.6-AJ16*L16*2-AJ16*M16*2.9-AJ16*N16*2-AJ16*O16*2.9-AJ16*P16*3.5 -> 7656826.9 | BL16: =IF(BK16-BG16-BF16-BI16<0,0,BK16-BG16-BI16-BF16) -> 0 | BM16: =ROUND(IF(BL16<=5000000,BL16*5%,IF(AND(BL16>5000000,BL16<=10000000),BL16*10%-250000,IF(AND(BL16>10000000,BL16<=18000000),BL16*15%-750000,IF(AND(BL16>18000000,BL16<=32000000),BL16*20%-1650000,IF(AND(BL16>32000000,BL16<=52000000),BL16*25%-3250000,IF(AND(BL16>52000000,BL16<80000000),BL16*30%-585000,IF(BL16>80000000,BL16*35%-9850000))))))),0) -> 0 | BN16: 35000 | BO16: =AV16-BF16-BM16-BN16 -> 6950848.1 | BP16: 101874719380
A17: 9 | B17: Dương Thị Đoàn | C17: TKD | D17: 208 | E17: 184 | H17: 1.5 | Q17: 5450000 | R17: 0 | T17: 300000 | U17: 800000 | V17: =IF((E17+F17)>=160, U17, U17/D17*(E17+F17)) -> 800000 | W17: 600000 | X17: =IF((E17+F17)>=160, W17, W17/D17*(E17+F17)) -> 600000 | Y17: 600000 | Z17: =IF((E17+F17)>=160, Y17, Y17/D17*(E17+F17)) -> 600000 | AA17: 0 | AB17: 20000 | AC17: =IF(E17>=184,500000,0) -> 500000 | AD17: =G17*13000 -> 0 | AE17: 0 | AH17: =V17+Z17+X17+AA17+AB17+AC17+AD17+AE17 -> 2520000 | AI17: =Q17+R17+T17 -> 5750000 | AJ17: =AI17/208 -> 27644.231 | AK17: =AJ17*(E17+F17*130%) -> 5086538.5 | AL17: =AJ17*H17*150% -> 62199.519 | AM17: =AJ17*I17*150%*130% -> 0 | AN17: =+AJ17*J17*200% -> 0 | AO17: =AJ17*K17*200%*130% -> 0 | AP17: =AJ17*L17*200%*150% -> 0 | AQ17: =AJ17*M17*200%*150%*130% -> 0 | AR17: =N17*AJ17*300% -> 0 | AS17: =AJ17*O17*300% -> 0 | AT17: =P17*AJ17*150%*300% -> 0 | AU17: =SUM(AL17:AT17) -> 62199.519 | AV17: =AH17+AK17+AU17+AG17+AF17 -> 7668738 | AW17: =Q17+R17+T17 -> 5750000 | AX17: =AW17*17.5% -> 1006250 | AY17: =AW17*3% -> 172500 | AZ17: =AW17*1% -> 57500 | BA17: =AW17*2% -> 115000 | BB17: =AX17+AY17+AZ17+BA17 -> 1351250 | BC17: =AW17*8% -> 460000 | BD17: =AW17*1.5% -> 86250 | BE17: =AW17*1% -> 57500 | BF17: =BC17+BD17+BE17 -> 603750 | BG17: 11000000 | BI17: =BH17*4400000 -> 0 | BJ17: =V17+AA17 -> 800000 | BK17: =AV17-BJ17-AJ17*H17*0.5-AJ17*I17*0.95-AJ17*J17-AJ17*K17*1.6-AJ17*L17*2-AJ17*M17*2.9-AJ17*N17*2-AJ17*O17*2.9-AJ17*P17*3.5 -> 6848004.8 | BL17: =IF(BK17-BG17-BF17-BI17<0,0,BK17-BG17-BI17-BF17) -> 0 | BM17: =ROUND(IF(BL17<=5000000,BL17*5%,IF(AND(BL17>5000000,BL17<=10000000),BL17*10%-250000,IF(AND(BL17>10000000,BL17<=18000000),BL17*15%-750000,IF(AND(BL17>18000000,BL17<=32000000),BL17*20%-1650000,IF(AND(BL17>32000000,BL17<=52000000),BL17*25%-3250000,IF(AND(BL17>52000000,BL17<80000000),BL17*30%-585000,IF(BL17>80000000,BL17*35%-9850000))))))),0) -> 0 | BN17: 35000 | BO17: =AV17-BF17-BM17-BN17 -> 7029988 | BP17: 109878508547
A18: 10 | B18: Lại Thị Huyền | C18: TKD | D18: 208 | E18: 184 | H18: 3 | Q18: 5450000 | R18: 0 | T18: 300000 | U18: 300000 | V18: =IF((E18+F18)>=160, U18, U18/D18*(E18+F18)) -> 300000 | W18: 800000 | X18: =IF((E18+F18)>=160, W18, W18/D18*(E18+F18)) -> 800000 | Y18: 1000000 | Z18: =IF((E18+F18)>=160, Y18, Y18/D18*(E18+F18)) -> 1000000 | AA18: 0 | AC18: =IF(E18>=184,500000,0) -> 500000 | AD18: =G18*13000 -> 0 | AE18: 0 | AH18: =V18+Z18+X18+AA18+AB18+AC18+AD18+AE18 -> 2600000 | AI18: =Q18+R18+T18 -> 5750000 | AJ18: =AI18/208 -> 27644.231 | AK18: =AJ18*(E18+F18*130%) -> 5086538.5 | AL18: =AJ18*H18*150% -> 124399.04 | AM18: =AJ18*I18*150%*130% -> 0 | AN18: =+AJ18*J18*200% -> 0 | AO18: =AJ18*K18*200%*130% -> 0 | AP18: =AJ18*L18*200%*150% -> 0 | AQ18: =AJ18*M18*200%*150%*130% -> 0 | AR18: =N18*AJ18*300% -> 0 | AS18: =AJ18*O18*300% -> 0 | AT18: =P18*AJ18*150%*300% -> 0 | AU18: =SUM(AL18:AT18) -> 124399.04 | AV18: =AH18+AK18+AU18+AG18+AF18 -> 7810937.5 | AW18: =Q18+R18+T18 -> 5750000 | AX18: =AW18*17.5% -> 1006250 | AY18: =AW18*3% -> 172500 | AZ18: =AW18*1% -> 57500 | BA18: =AW18*2% -> 115000 | BB18: =AX18+AY18+AZ18+BA18 -> 1351250 | BC18: =AW18*8% -> 460000 | BD18: =AW18*1.5% -> 86250 | BE18: =AW18*1% -> 57500 | BF18: =BC18+BD18+BE18 -> 603750 | BG18: 11000001 | BI18: =BH18*4400000 -> 0 | BJ18: =V18+AA18 -> 300000 | BK18: =AV18-BJ18-AJ18*H18*0.5-AJ18*I18*0.95-AJ18*J18-AJ18*K18*1.6-AJ18*L18*2-AJ18*M18*2.9-AJ18*N18*2-AJ18*O18*2.9-AJ18*P18*3.5 -> 7469471.2 | BL18: =IF(BK18-BG18-BF18-BI18<0,0,BK18-BG18-BI18-BF18) -> 0 | BM18: =ROUND(IF(BL18<=5000000,BL18*5%,IF(AND(BL18>5000000,BL18<=10000000),BL18*10%-250000,IF(AND(BL18>10000000,BL18<=18000000),BL18*15%-750000,IF(AND(BL18>18000000,BL18<=32000000),BL18*20%-1650000,IF(AND(BL18>32000000,BL18<=52000000),BL18*25%-3250000,IF(AND(BL18>52000000,BL18<80000000),BL18*30%-585000,IF(BL18>80000000,BL18*35%-9850000))))))),0) -> 0 | BN18: 35000 | BO18: =AV18-BF18-BM18-BN18 -> 7172187.5 | BP18: 106878497832
A19: 11 | B19: Đinh Thị Thu Thảo | C19: VSD | D19: 208 | E19: 184 | Q19: 4064000 | R19: 0 | T19: 600000 | U19: 400000 | V19: =IF((E19+F19)>=160, U19, U19/D19*(E19+F19)) -> 400000 | W19: 300000 | X19: =IF((E19+F19)>=160, W19, W19/D19*(E19+F19)) -> 300000 | Y19: 300000 | Z19: =IF((E19+F19)>=160, Y19, Y19/D19*(E19+F19)) -> 300000 | AA19: 0 | AC19: =IF(E19>=184,500000,0) -> 500000 | AD19: =G19*13000 -> 0 | AE19: 0 | AH19: =V19+Z19+X19+AA19+AB19+AC19+AD19+AE19 -> 1500000 | AI19: =Q19+R19+T19 -> 4664000 | AJ19: =AI19/208 -> 22423.077 | AK19: =AJ19*(E19+F19*130%) -> 4125846.2 | AL19: =AJ19*H19*150% -> 0 | AM19: =AJ19*I19*150%*130% -> 0 | AN19: =+AJ19*J19*200% -> 0 | AO19: =AJ19*K19*200%*130% -> 0 | AP19: =AJ19*L19*200%*150% -> 0 | AQ19: =AJ19*M19*200%*150%*130% -> 0 | AR19: =N19*AJ19*300% -> 0 | AS19: =AJ19*O19*300% -> 0 | AT19: =P19*AJ19*150%*300% -> 0 | AU19: =SUM(AL19:AT19) -> 0 | AV19: =AH19+AK19+AU19+AG19+AF19 -> 5625846.2 | AW19: =Q19+R19+T19 -> 4664000 | AX19: =AW19*17.5% -> 816200 | AY19: =AW19*3% -> 139920 | AZ19: =AW19*1% -> 46640 | BA19: =AW19*2% -> 93280 | BB19: =AX19+AY19+AZ19+BA19 -> 1096040 | BC19: =AW19*8% -> 373120 | BD19: =AW19*1.5% -> 69960 | BE19: =AW19*1% -> 46640 | BF19: =BC19+BD19+BE19 -> 489720 | BG19: 11000000 | BI19: =BH19*4400000 -> 0 | BJ19: =V19+AA19 -> 400000 | BK19: =AV19-BJ19-AJ19*H19*0.5-AJ19*I19*0.95-AJ19*J19-AJ19*K19*1.6-AJ19*L19*2-AJ19*M19*2.9-AJ19*N19*2-AJ19*O19*2.9-AJ19*P19*3.5 -> 5225846.2 | BL19: =IF(BK19-BG19-BF19-BI19<0,0,BK19-BG19-BI19-BF19) -> 0 | BM19: =ROUND(IF(BL19<=5000000,BL19*5%,IF(AND(BL19>5000000,BL19<=10000000),BL19*10%-250000,IF(AND(BL19>10000000,BL19<=18000000),BL19*15%-750000,IF(AND(BL19>18000000,BL19<=32000000),BL19*20%-1650000,IF(AND(BL19>32000000,BL19<=52000000),BL19*25%-3250000,IF(AND(BL19>52000000,BL19<80000000),BL19*30%-585000,IF(BL19>80000000,BL19*35%-9850000))))))),0) -> 0 | BN19: 35000 | BO19: =AV19-BF19-BM19-BN19 -> 5101126.2 | BP19: 104875693792
A20: 12 | B20: Đào Văn Mạnh | C20: Thợ điện | D20: 208 | E20: 184 | J20: 1.5 | Q20: 4480000 | R20: 800000 | T20: 600000 | U20: 900000 | V20: =IF((E20+F20)>=160, U20, U20/D20*(E20+F20)) -> 900000 | W20: 1000000 | X20: =IF((E20+F20)>=160, W20, W20/D20*(E20+F20)) -> 1000000 | Y20: 1000000 | Z20: =IF((E20+F20)>=160, Y20, Y20/D20*(E20+F20)) -> 1000000 | AA20: 0 | AC20: =IF(E20>=184,500000,0) -> 500000 | AD20: =G20*13000 -> 0 | AE20: 0 | AH20: =V20+Z20+X20+AA20+AB20+AC20+AD20+AE20 -> 3400000 | AI20: =Q20+R20+T20 -> 5880000 | AJ20: =AI20/208 -> 28269.231 | AK20: =AJ20*(E20+F20*130%) -> 5201538.5 | AL20: =AJ20*H20*150% -> 0 | AM20: =AJ20*I20*150%*130% -> 0 | AN20: =+AJ20*J20*200% -> 84807.692 | AO20: =AJ20*K20*200%*130% -> 0 | AP20: =AJ20*L20*200%*150% -> 0 | AQ20: =AJ20*M20*200%*150%*130% -> 0 | AR20: =N20*AJ20*300% -> 0 | AS20: =AJ20*O20*300% -> 0 | AT20: =P20*AJ20*150%*300% -> 0 | AU20: =SUM(AL20:AT20) -> 84807.692 | AV20: =AH20+AK20+AU20+AG20+AF20 -> 8686346.2 | AW20: =Q20+R20+T20 -> 5880000 | AX20: =AW20*17.5% -> 1029000 | AY20: =AW20*3% -> 176400 | AZ20: =AW20*1% -> 58800 | BA20: =AW20*2% -> 117600 | BB20: =AX20+AY20+AZ20+BA20 -> 1381800 | BC20: =AW20*8% -> 470400 | BD20: =AW20*1.5% -> 88200 | BE20: =AW20*1% -> 58800 | BF20: =BC20+BD20+BE20 -> 617400 | BG20: 11000000 | BI20: =BH20*4400000 -> 0 | BJ20: =V20+AA20 -> 900000 | BK20: =AV20-BJ20-AJ20*H20*0.5-AJ20*I20*0.95-AJ20*J20-AJ20*K20*1.6-AJ20*L20*2-AJ20*M20*2.9-AJ20*N20*2-AJ20*O20*2.9-AJ20*P20*3.5 -> 7743942.3 | BL20: =IF(BK20-BG20-BF20-BI20<0,0,BK20-BG20-BI20-BF20) -> 0 | BM20: =ROUND(IF(BL20<=5000000,BL20*5%,IF(AND(BL20>5000000,BL20<=10000000),BL20*10%-250000,IF(AND(BL20>10000000,BL20<=18000000),BL20*15%-750000,IF(AND(BL20>18000000,BL20<=32000000),BL20*20%-1650000,IF(AND(BL20>32000000,BL20<=52000000),BL20*25%-3250000,IF(AND(BL20>52000000,BL20<80000000),BL20*30%-585000,IF(BL20>80000000,BL20*35%-9850000))))))),0) -> 0 | BN20: 35000 | BO20: =AV20-BF20-BM20-BN20 -> 8033946.2 | BP20: 101876513499
A21: 13 | B21: Hà Đức Thịnh | C21: VHXN | D21: 208 | E21: 184 | H21: 0 | Q21: 4940000 | R21: 0 | T21: 300000 | U21: 600000 | V21: =IF((E21+F21)>=160, U21, U21/D21*(E21+F21)) -> 600000 | W21: 800000 | X21: =IF((E21+F21)>=160, W21, W21/D21*(E21+F21)) -> 800000 | Y21: 800000 | Z21: =IF((E21+F21)>=160, Y21, Y21/D21*(E21+F21)) -> 800000 | AA21: 0 | AB21: 20000 | AC21: =IF(E21>=184,500000,0) -> 500000 | AD21: =G21*13000 -> 0 | AE21: 0 | AH21: =V21+Z21+X21+AA21+AB21+AC21+AD21+AE21 -> 2720000 | AI21: =Q21+R21+T21 -> 5240000 | AJ21: =AI21/208 -> 25192.308 | AK21: =AJ21*(E21+F21*130%) -> 4635384.6 | AL21: =AJ21*H21*150% -> 0 | AM21: =AJ21*I21*150%*130% -> 0 | AN21: =+AJ21*J21*200% -> 0 | AO21: =AJ21*K21*200%*130% -> 0 | AP21: =AJ21*L21*200%*150% -> 0 | AQ21: =AJ21*M21*200%*150%*130% -> 0 | AR21: =N21*AJ21*300% -> 0 | AS21: =AJ21*O21*300% -> 0 | AT21: =P21*AJ21*150%*300% -> 0 | AU21: =SUM(AL21:AT21) -> 0 | AV21: =AH21+AK21+AU21+AG21+AF21 -> 7355384.6 | AW21: =Q21+R21+T21 -> 5240000 | AX21: =AW21*17.5% -> 917000 | AY21: =AW21*3% -> 157200 | AZ21: =AW21*1% -> 52400 | BA21: =AW21*2% -> 104800 | BB21: =AX21+AY21+AZ21+BA21 -> 1231400 | BC21: =AW21*8% -> 419200 | BD21: =AW21*1.5% -> 78600 | BE21: =AW21*1% -> 52400 | BF21: =BC21+BD21+BE21 -> 550200 | BG21: 11000000 | BI21: =BH21*4400000 -> 0 | BJ21: =V21+AA21 -> 600000 | BK21: =AV21-BJ21-AJ21*H21*0.5-AJ21*I21*0.95-AJ21*J21-AJ21*K21*1.6-AJ21*L21*2-AJ21*M21*2.9-AJ21*N21*2-AJ21*O21*2.9-AJ21*P21*3.5 -> 6755384.6 | BL21: =IF(BK21-BG21-BF21-BI21<0,0,BK21-BG21-BI21-BF21) -> 0 | BM21: =ROUND(IF(BL21<=5000000,BL21*5%,IF(AND(BL21>5000000,BL21<=10000000),BL21*10%-250000,IF(AND(BL21>10000000,BL21<=18000000),BL21*15%-750000,IF(AND(BL21>18000000,BL21<=32000000),BL21*20%-1650000,IF(AND(BL21>32000000,BL21<=52000000),BL21*25%-3250000,IF(AND(BL21>52000000,BL21<80000000),BL21*30%-585000,IF(BL21>80000000,BL21*35%-9850000))))))),0) -> 0 | BN21: 35000 | BO21: =AV21-BF21-BM21-BN21 -> 6770184.6 | BP21: 109878727109 | BQ21: =BQ22+'Payroll of factory (DET).1'!BR40 -> 2.7216682e+08
A22: Tổng | D22: =SUM(D9:D21) -> 2704 | E22: =SUM(E9:E21) -> 2048 | F22: =SUM(F9:F21) -> 0 | G22: =SUM(G9:G21) -> 0 | H22: =SUM(H9:H21) -> 13.5 | I22: =SUM(I9:I21) -> 0 | J22: =SUM(J9:J21) -> 1.5 | K22: =SUM(K9:K21) -> 0 | ... BO22: =SUM(BO9:BO21) -> 80926816 | BQ22: =SUM(BO15:BO21) -> 52001170
B24: Scheduling | AF24: Manager | BF24: Director- general

Sheet Payroll of factory (SOI) 
A1: CÔNG TY TNHH SHINSUNG VINA
A2: Lô CN04, khu công nghiệp Cẩm Khê, TT.Cẩm Khê, H.Cẩm Khê, T.Phú Thọ
A3: ='Payroll Office'!A3:BO3 -> PAYROLL AUGUST 2024
A4: ='Payroll Office'!A4:BO4 -> From 1st -31th August 2024
BQ6: VND
A7: STT (No) | B7: Họ và tên (First and last name) | C7: Vị trí (Location) | D7: Số giờ công chuẩn | E7: Giờ công cơ bản thực tế (The actual basic hourly) | G7: Số bữa phụ | H7: Giờ công làm thêm (Hours of overtime) | Q7: Lương cơ bản (Basic salary) | U7: Các khoản phụ cấp (Allowances) | AF7: Thưởng Tết Âm lịch 20% (Ngày lễ 02/09) | AG7: Khấu trừ khác | AH7: Tổng phụ cấp không đóng BH được nhận (Total allowances) | AI7: Lương đóng bảo hiểm /Salary for insurance | AJ7: Lương giờ công /Salary for insurance | AK7: Tổng lương giờ công cơ bản /Total base salary | AL7: Lương giờ công làm thêm | AV7: Bổ sung lương T11 | AW7: Tổng lương | AX7: BH tính vào chi phí / Isuarance payable by company | BD7: BH khấu trừ lương / Isuarance deductions from salary | BH7: Thuế TNCN | BO7: Đoàn phí | BQ7: Thực nhận | BR7: Số tài khoản | BS7: Ký nhận
E8: Ca ngày (100%) | F8: Ca đêm (130%) | H8: Tăng ca 150% | I8: Tăng ca đêm 195% | J8: CN ngày 200% | K8: CN đêm 260% | L8: Tăng ca ngày CN 300% | M8: Tăng ca đêm CN 390% | N8: Ngày lễ ngày 300% | O8: Ngày lễ đêm 390% | P8: TC lễ (450%) | Q8: Lương cơ bản (Basic salary) | R8: Phụ cấp trách nhiệm/ Responsibility allowance | S8: PC ngoại ngữ/ Foreign language support | T8: Phụ cấp thâm niên/ Seniority allowances | U8: HT điện thoại /Phone charges/ 26 Công | V8: HT điện thoại /Phone charges | W8: HT xăng xe /Fuel costs for vehicles/ 26 Công | X8: HT xăng xe /Fuel costs for vehicles | Y8: HT nhà ở /Housing support/ 26 Công | Z8: HT nhà ở /Housing support | AA8: Phụ cấp đi lại | AB8: HT con nhỏ /Supporting children | AC8: Thưởng Chuyên cần /Reward for diligence | AD8: Trợ cấp bữa phụ /Snack allowance | AE8: ='Payroll Office'!AE8 -> Thưởng sinh nhật tháng 08 /Birthday in August | AL8: Tăng ca ngày | AM8: Tăng ca đêm | AN8: CN ngày | AO8: CN đêm | AP8: Tăng ca ngày CN | AQ8: Tăng ca đêm CN | AR8: Ngày lễ ngày | AS8: Ngày lễ đêm | AT8: TC lễ | AU8: Tổng lương làm thêm | AX8: Lương đóng bảo hiểm/Salary base for insurance | AY8: BHXH / Social Insurance 17.5% | AZ8: BHYT / Health Insurance 3%건강보험 (회사분) | BA8: BHTN / Unemployment Insurance 1% | BB8: KPCĐ 2% | BC8: Cộng /Amount Isurance | BD8: BHXH / Social Insurance 8% | BE8: BHYT / Health Insurance 1,5% 건강보험 (개인분) | BF8: BHTN / Unemployment Insurance 1% | BG8: Cộng 10.5%/Amount Isurance | BH8: Giảm trừ bản thân (기본공제금 ) (VND) | BI8: Số người phụ thuộc /Number Deduction family | BJ8: Giảm trừ người phụ thuộc /deduction-family 4400000/1person | BK8: Thu nhập miễn thuế /Tax excemption | BL8: Thu nhập chịu thuế | BM8: Thu nhập tính thuế (과세 대상 금액) VND | BN8: Thuế TNCN (개인소득세) ( VND)
A9: -1 | B9: -2 | C9: -3 | E9: (4a) | F9: (4b) | H9: (5a) | I9: (5b) | J9: (6a) | K9: (6b) | L9: (6c) | M9: (6d) | N9: 6e | O9: -7 | P9: 7a | Q9: -8 | R9: -9 | X9: -11 | Z9: (11 a) | AB9: (11b) | AC9: -12 | AD9: -13 | AE9: -14 | AF9: -15 | AH9: (16)=10+11+11a+11b+ 12 | AI9: (14)=(8)+(9) | AJ9: (15)=(14)/4 | AK9: (16)=(15)*(4a+4b*130%) | AL9: (17)=(5a)* (15)*150% | AM9: 17a=5b*15*150%*130% | AN9: 17b=6a*15*200% | AO9: 17c=6b*15*200%*130% | AP9: (18)=(6c)* (15)*200%*150% | AQ9: 18a=6d*15*200%*150%*130% | AR9: (19)=(6e)* (15)*300% | AS9: 19a=7*15*130%*300% | AT9: 19b=7a*15*150%*300% | AU9: (20)= (17)+(18)+(19) | AW9: (21)=(13)+(16)+ (20) | AX9: (22)=(8)+ (10) | AY9: (23)=(22)x17% | AZ9: (24)=(22)x3% | BA9: (25)=(22)x1% | BC9: (26)=(23)+(24)+ (25) | BD9: (27)=(22)x8% | BE9: (28)=(22)x1.5% | BF9: (29)=(22)x1% | BG9: (30)=(27)+(28)+(29) | BH9: -31 | BI9: (31a) | BJ9: (32)= (31a)x4400000 | BK9: (33)=(16)+(16a) | BL9: (34)=(21)-(33) | BM9: (35)=(21)-(31)-(32)-(33) | BN9: -36
A10: 1 | B10: Đinh Công Trường | C10: TTT | D10: 208 | E10: 130.5 | F10: 58.5 | G10: 19 | H10: 45 | I10: 13.5 | Q10: 4267000 | R10: 1500000 | T10: 900000 | U10: 0 | V10: =IF((E10+F10)>=180, U10, U10/D10*(E10+F10)) -> 0 | W10: 700000 | X10: =IF((E10+F10)>=180, W10, W10/D10*(E10+F10)) -> 700000 | Y10: 700000 | Z10: =IF((E10+F10)>=180, Y10, Y10/D10*(E10+F10)) -> 700000 | AA10: 0 | AB10: 20000 | AC10: 500000 | AD10: =G10*13000 -> 247000 | AH10: =V10+X10+Z10+AB10+AC10+AD10+AE10 -> 2167000 | AI10: =Q10+R10+T10 -> 6667000 | AJ10: =AI10/D10 -> 32052.885 | AK10: =AJ10*(E10+F10*130%) -> 6620523.3 | AL10: =AJ10*H10*150% -> 2163569.7 | AM10: =AJ10*I10*150%*130% -> 843792.19 | AN10: =+AJ10*J10*200% -> 0 | AO10: =AJ10*K10*200%*130% -> 0 | AP10: =AJ10*L10*200%*150% -> 0 | AQ10: =AJ10*M10*200%*150%*130% -> 0 | AR10: =N10*AJ10*300% -> 0 | AS10: =AJ10*O10*130%*300% -> 0 | AT10: =P10*AJ10*150%*300% -> 0 | AU10: =SUM(AL10:AT10) -> 3007361.9 | AW10: =AH10+AK10+AU10+AF10-AG10 -> 11794885 | AX10: =Q10+R10+T10 -> 6667000 | AY10: =AX10*17.5% -> 1166725 | AZ10: =AX10*3% -> 200010 | BA10: =AX10*1% -> 66670 | BB10: =AX10*2% -> 133340 | BC10: =AY10+AZ10+BA10+BB10 -> 1566745 | BD10: =AX10*8% -> 533360 | BE10: =AX10*1.5% -> 100005 | BF10: =AX10*1% -> 66670 | BG10: =BD10+BE10+BF10 -> 700035 | BH10: 11000000 | BI10: 1 | BJ10: =BI10*4400000 -> 4400000 | BK10: =V10+AA10+AD10 -> 247000 | BL10: =AW10-BK10-F10*0.3*AJ10 -> 10985357 | BM10: =IF(BL10-BH10-BJ10-BG10<0,0,BL10-BH10-BJ10-BG10) -> 0 | BN10: =ROUND(IF(BM10<=5000000,BM10*5%,IF(AND(BM10>5000000,BM10<=10000000),BM10*10%-250000,IF(AND(BM10>10000000,BM10<=18000000),BM10*15%-750000,IF(AND(BM10>18000000,BM10<=32000000),BM10*20%-1650000,IF(AND(BM10>32000000,BM10<=52000000),BM10*25%-3250000,IF(AND(BM10>52000000,BM10<80000000),BM10*30%-585000,IF(BM10>80000000,BM10*35%-9850000))))))),0) -> 0 | BO10: 35000 | BQ10: =AW10-BG10-BN10-BO10 -> 11059850 | BR10: 103872539872
A11: =A10+1 -> 2 | B11: Nguyễn Trang Điền | C11: TT | D11: 208 | E11: 111 | F11: 78 | G11: 20 | H11: 43 | I11: 18 | Q11: 4267000 | R11: 1300000 | T11: 900000 | U11: 0 | V11: =IF((E11+F11)>=180, U11, U11/D11*(E11+F11)) -> 0 | W11: 300000 | X11: =IF((E11+F11)>=180, W11, W11/D11*(E11+F11)) -> 300000 | Y11: 300000 | Z11: =IF((E11+F11)>=180, Y11, Y11/D11*(E11+F11)) -> 300000 | AA11: 0 | AB11: 40000 | AC11: 500000 | AD11: =G11*13000 -> 260000 | AH11: =V11+X11+Z11+AB11+AC11+AD11+AE11 -> 1400000 | AI11: =Q11+R11+T11 -> 6467000 | AJ11: =AI11/D11 -> 31091.346 | AK11: =AJ11*(E11+F11*130%) -> 6603801.9 | AL11: =AJ11*H11*150% -> 2005391.8 | AM11: =AJ11*I11*150%*130% -> 1091306.2 | AN11: =+AJ11*J11*200% -> 0 | AO11: =AJ11*K11*200%*130% -> 0 | AP11: =AJ11*L11*200%*150% -> 0 | AQ11: =AJ11*M11*200%*150%*130% -> 0 | AR11: =N11*AJ11*300% -> 0 | AS11: =AJ11*O11*130%*300% -> 0 | AT11: =P11*AJ11*150%*300% -> 0 | AU11: =SUM(AL11:AT11) -> 3096698.1 | AW11: =AH11+AK11+AU11+AF11-AG11 -> 11100500 | AX11: =Q11+R11+T11 -> 6467000 | AY11: =AX11*17.5% -> 1131725 | AZ11: =AX11*3% -> 194010 | BA11: =AX11*1% -> 64670 | BB11: =AX11*2% -> 129340 | BC11: =AY11+AZ11+BA11+BB11 -> 1519745 | BD11: =AX11*8% -> 517360 | BE11: =AX11*1.5% -> 97005 | BF11: =AX11*1% -> 64670 | BG11: =BD11+BE11+BF11 -> 679035 | BH11: 11000000 | BI11: 1 | BJ11: =BI11*4400000 -> 4400000 | BK11: =V11+AA11+AD11 -> 260000 | BL11: 11559432 | BM11: =IF(BL11-BH11-BJ11-BG11<0,0,BL11-BH11-BJ11-BG11) -> 0 | BN11: =ROUND(IF(BM11<=5000000,BM11*5%,IF(AND(BM11>5000000,BM11<=10000000),BM11*10%-250000,IF(AND(BM11>10000000,BM11<=18000000),BM11*15%-750000,IF(AND(BM11>18000000,BM11<=32000000),BM11*20%-1650000,IF(AND(BM11>32000000,BM11<=52000000),BM11*25%-3250000,IF(AND(BM11>52000000,BM11<80000000),BM11*30%-585000,IF(BM11>80000000,BM11*35%-9850000))))))),0) -> 0 | BO11: 35000 | BQ11: =AW11-BG11-BN11-BO11 -> 10386465 | BR11: 101872993965
A12: =A11+1 -> 3 | B12: Quán Văn Công | C12: TT | D12: 208 | E12: 110.5 | F12: 78 | G12: 20 | H12: 43 | I12: 18 | Q12: 4267000 | R12: 1300000 | T12: 900000 | U12: 0 | V12: =IF((E12+F12)>=180, U12, U12/D12*(E12+F12)) -> 0 | W12: 300000 | X12: =IF((E12+F12)>=180, W12, W12/D12*(E12+F12)) -> 300000 | Y12: 300000 | Z12: =IF((E12+F12)>=180, Y12, Y12/D12*(E12+F12)) -> 300000 | AA12: 0 | AC12: 500000 | AD12: =G12*13000 -> 260000 | AH12: =V12+X12+Z12+AB12+AC12+AD12+AE12 -> 1360000 | AI12: =Q12+R12+T12 -> 6467000 | AJ12: =AI12/D12 -> 31091.346 | AK12: =AJ12*(E12+F12*130%) -> 6588256.2 | AL12: =AJ12*H12*150% -> 2005391.8 | AM12: =AJ12*I12*150%*130% -> 1091306.2 | AN12: =+AJ12*J12*200% -> 0 | AO12: =AJ12*K12*200%*130% -> 0 | AP12: =AJ12*L12*200%*150% -> 0 | AQ12: =AJ12*M12*200%*150%*130% -> 0 | AR12: =N12*AJ12*300% -> 0 | AS12: =AJ12*O12*130%*300% -> 0 | AT12: =P12*AJ12*150%*300% -> 0 | AU12: =SUM(AL12:AT12) -> 3096698.1 | AW12: =AH12+AK12+AU12+AF12-AG12 -> 11044954 | AX12: =Q12+R12+T12 -> 6467000 | AY12: =AX12*17.5% -> 1131725 | AZ12: =AX12*3% -> 194010 | BA12: =AX12*1% -> 64670 | BB12: =AX12*2% -> 129340 | BC12: =AY12+AZ12+BA12+BB12 -> 1519745 | BD12: =AX12*8% -> 517360 | BE12: =AX12*1.5% -> 97005 | BF12: =AX12*1% -> 64670 | BG12: =BD12+BE12+BF12 -> 679035 | BH12: 11000000 | BJ12: =BI12*4400000 -> 0 | BK12: =V12+AA12+AD12 -> 260000 | BL12: =AW12-BK12-F12*0.3*AJ12 -> 10057417 | BM12: =IF(BL12-BH12-BJ12-BG12<0,0,BL12-BH12-BJ12-BG12) -> 0 | BN12: =ROUND(IF(BM12<=5000000,BM12*5%,IF(AND(BM12>5000000,BM12<=10000000),BM12*10%-250000,IF(AND(BM12>10000000,BM12<=18000000),BM12*15%-750000,IF(AND(BM12>18000000,BM12<=32000000),BM12*20%-1650000,IF(AND(BM12>32000000,BM12<=52000000),BM12*25%-3250000,IF(AND(BM12>52000000,BM12<80000000),BM12*30%-585000,IF(BM12>80000000,BM12*35%-9850000))))))),0) -> 0 | BO12: 35000 | BQ12: =AW12-BG12-BN12-BO12 -> 10330919 | BR12: 104872771448
A13: =A12+1 -> 4 | B13: Bùi Xuân Huy | C13: TT | D13: 208 | E13: 137 | F13: 52 | G13: 19 | H13: 48.5 | I13: 10.5 | Q13: 4267000 | R13: 1300000 | T13: 900000 | U13: 0 | V13: =IF((E13+F13)>=180, U13, U13/D13*(E13+F13)) -> 0 | W13: 300000 | X13: =IF((E13+F13)>=180, W13, W13/D13*(E13+F13)) -> 300000 | Y13: 300000 | Z13: =IF((E13+F13)>=180, Y13, Y13/D13*(E13+F13)) -> 300000 | AA13: 0 | AC13: 500000 | AD13: =G13*13000 -> 247000 | AH13: =V13+X13+Z13+AB13+AC13+AD13+AE13 -> 1347000 | AI13: =Q13+R13+T13 -> 6467000 | AJ13: =AI13/D13 -> 31091.346 | AK13: =AJ13*(E13+F13*130%) -> 6361289.4 | AL13: =AJ13*H13*150% -> 2261895.4 | AM13: =AJ13*I13*150%*130% -> 636595.31 | AN13: =+AJ13*J13*200% -> 0 | AO13: =AJ13*K13*200%*130% -> 0 | AP13: =AJ13*L13*200%*150% -> 0 | AQ13: =AJ13*M13*200%*150%*130% -> 0 | AR13: =N13*AJ13*300% -> 0 | AS13: =AJ13*O13*130%*300% -> 0 | AT13: =P13*AJ13*150%*300% -> 0 | AU13: =SUM(AL13:AT13) -> 2898490.7 | AW13: =AH13+AK13+AU13+AF13-AG13 -> 10606780 | AX13: =Q13+R13+T13 -> 6467000 | AY13: =AX13*17.5% -> 1131725 | AZ13: =AX13*3% -> 194010 | BA13: =AX13*1% -> 64670 | BB13: =AX13*2% -> 129340 | BC13: =AY13+AZ13+BA13+BB13 -> 1519745 | BD13: =AX13*8% -> 517360 | BE13: =AX13*1.5% -> 97005 | BF13: =AX13*1% -> 64670 | BG13: =BD13+BE13+BF13 -> 679035 | BH13: 11000000 | BJ13: =BI13*4400000 -> 0 | BK13: =V13+AA13+AD13 -> 247000 | BL13: =AW13-BK13-F13*0.3*AJ13 -> 9874755.2 | BM13: =IF(BL13-BH13-BJ13-BG13<0,0,BL13-BH13-BJ13-BG13) -> 0 | BN13: =ROUND(IF(BM13<=5000000,BM13*5%,IF(AND(BM13>5000000,BM13<=10000000),BM13*10%-250000,IF(AND(BM13>10000000,BM13<=18000000),BM13*15%-750000,IF(AND(BM13>18000000,BM13<=32000000),BM13*20%-1650000,IF(AND(BM13>32000000,BM13<=52000000),BM13*25%-3250000,IF(AND(BM13>52000000,BM13<80000000),BM13*30%-585000,IF(BM13>80000000,BM13*35%-9850000))))))),0) -> 0 | BO13: 35000 | BQ13: =AW13-BG13-BN13-BO13-BP13 -> 9892745.2 | BR13: 105872771447
A14: =A13+1 -> 5 | B14: Trần Đức Hậu | C14: TP | D14: 208 | E14: 130.5 | F14: 58.5 | G14: 19 | H14: 44 | I14: 13.5 | Q14: 4267000 | R14: 800000 | T14: 900000 | U14: 0 | V14: =IF((E14+F14)>=180, U14, U14/D14*(E14+F14)) -> 0 | W14: 300000 | X14: =IF((E14+F14)>=180, W14, W14/D14*(E14+F14)) -> 300000 | Y14: 300000 | Z14: =IF((E14+F14)>=180, Y14, Y14/D14*(E14+F14)) -> 300000 | AA14: 0 | AB14: 60000 | AC14: 500000 | AD14: =G14*13000 -> 247000 | AH14: =V14+X14+Z14+AB14+AC14+AD14+AE14 -> 1407000 | AI14: =Q14+R14+T14 -> 5967000 | AJ14: =AI14/D14 -> 28687.5 | AK14: =AJ14*(E14+F14*130%) -> 5925403.1 | AL14: =AJ14*H14*150% -> 1893375 | AM14: =AJ14*I14*150%*130% -> 755198.44 | AN14: =+AJ14*J14*200% -> 0 | AO14: =AJ14*K14*200%*130% -> 0 | AP14: =AJ14*L14*200%*150% -> 0 | AQ14: =AJ14*M14*200%*150%*130% -> 0 | AR14: =N14*AJ14*300% -> 0 | AS14: =AJ14*O14*130%*300% -> 0 | AT14: =P14*AJ14*150%*300% -> 0 | AU14: =SUM(AL14:AT14) -> 2648573.4 | AW14: =AH14+AK14+AU14+AF14-AG14 -> 9980976.6 | AX14: =Q14+R14+T14 -> 5967000 | AY14: =AX14*17.5% -> 1044225 | AZ14: =AX14*3% -> 179010 | BA14: =AX14*1% -> 59670 | BB14: =AX14*2% -> 119340 | BC14: =AY14+AZ14+BA14+BB14 -> 1402245 | BD14: =AX14*8% -> 477360 | BE14: =AX14*1.5% -> 89505 | BF14: =AX14*1% -> 59670 | BG14: =BD14+BE14+BF14 -> 626535 | BH14: 11000000 | BI14: 1 | BJ14: =BI14*4400000 -> 4400000 | BK14: =V14+AA14+AD14 -> 247000 | BL14: =AW14-BK14-F14*0.3*AJ14 -> 9230510.9 | BM14: =IF(BL14-BH14-BJ14-BG14<0,0,BL14-BH14-BJ14-BG14) -> 0 | BN14: =ROUND(IF(BM14<=5000000,BM14*5%,IF(AND(BM14>5000000,BM14<=10000000),BM14*10%-250000,IF(AND(BM14>10000000,BM14<=18000000),BM14*15%-750000,IF(AND(BM14>18000000,BM14<=32000000),BM14*20%-1650000,IF(AND(BM14>32000000,BM14<=52000000),BM14*25%-3250000,IF(AND(BM14>52000000,BM14<80000000),BM14*30%-585000,IF(BM14>80000000,BM14*35%-9850000))))))),0) -> 0 | BO14: 35000 | BQ14: =AW14-BG14-BN14-BO14 -> 9319441.6 | BR14: 103006386745
A15: =A14+1 -> 6 | B15: Trịnh Ngọc Tất | C15: CN | D15: 208 | E15: 128 | F15: 52 | G15: 19 | H15: 48 | I15: 10.5 | Q15: 4267000 | R15: 300000 | T15: 900000 | U15: 0 | V15: =IF((E15+F15)>=180, U15, U15/D15*(E15+F15)) -> 0 | W15: 300000 | X15: =IF((E15+F15)>=180, W15, W15/D15*(E15+F15)) -> 300000 | Y15: 300000 | Z15: =IF((E15+F15)>=180, Y15, Y15/D15*(E15+F15)) -> 300000 | AA15: 0 | AC15: 500000 | AD15: =G15*13000 -> 247000 | AH15: =V15+X15+Z15+AB15+AC15+AD15+AE15 -> 1347000 | AI15: =Q15+R15+T15 -> 5467000 | AJ15: =AI15/D15 -> 26283.654 | AK15: =AJ15*(E15+F15*130%) -> 5141082.7 | AL15: =AJ15*H15*150% -> 1892423.1 | AM15: =AJ15*I15*150%*130% -> 538157.81 | AN15: =+AJ15*J15*200% -> 0 | AO15: =AJ15*K15*200%*130% -> 0 | AP15: =AJ15*L15*200%*150% -> 0 | AQ15: =AJ15*M15*200%*150%*130% -> 0 | AR15: =N15*AJ15*300% -> 0 | AS15: =AJ15*O15*130%*300% -> 0 | AT15: =P15*AJ15*150%*300% -> 0 | AU15: =SUM(AL15:AT15) -> 2430580.9 | AW15: =AH15+AK15+AU15+AF15-AG15 -> 8918663.6 | AX15: =Q15+R15+T15 -> 5467000 | AY15: =AX15*17.5% -> 956725 | AZ15: =AX15*3% -> 164010 | BA15: =AX15*1% -> 54670 | BB15: =AX15*2% -> 109340 | BC15: =AY15+AZ15+BA15+BB15 -> 1284745 | BD15: =AX15*8% -> 437360 | BE15: =AX15*1.5% -> 82005 | BF15: =AX15*1% -> 54670 | BG15: =BD15+BE15+BF15 -> 574035 | BH15: 11000000 | BJ15: =BI15*4400000 -> 0 | BK15: =V15+AA15+AD15 -> 247000 | BL15: =AW15-BK15-F15*0.3*AJ15 -> 8261638.6 | BM15: =IF(BL15-BH15-BJ15-BG15<0,0,BL15-BH15-BJ15-BG15) -> 0 | BN15: =ROUND(IF(BM15<=5000000,BM15*5%,IF(AND(BM15>5000000,BM15<=10000000),BM15*10%-250000,IF(AND(BM15>10000000,BM15<=18000000),BM15*15%-750000,IF(AND(BM15>18000000,BM15<=32000000),BM15*20%-1650000,IF(AND(BM15>32000000,BM15<=52000000),BM15*25%-3250000,IF(AND(BM15>52000000,BM15<80000000),BM15*30%-585000,IF(BM15>80000000,BM15*35%-9850000))))))),0) -> 0 | BO15: 35000 | BQ15: =AW15-BG15-BN15-BO15 -> 8309628.6 | BR15: 103872994007
A16: =A15+1 -> 7 | B16: Đinh Ngọc Cương | C16: CN | D16: 208 | E16: 111 | F16: 78 | G16: 20 | H16: 42 | I16: 18 | Q16: 4267000 | R16: 300000 | T16: 600000 | U16: 0 | V16: =IF((E16+F16)>=180, U16, U16/D16*(E16+F16)) -> 0 | W16: 300000 | X16: =IF((E16+F16)>=180, W16, W16/D16*(E16+F16)) -> 300000 | Y16: 300000 | Z16: =IF((E16+F16)>=180, Y16, Y16/D16*(E16+F16)) -> 300000 | AA16: 0 | AC16: 500000 | AD16: =G16*13000 -> 260000 | AH16: =V16+X16+Z16+AB16+AC16+AD16+AE16 -> 1360000 | AI16: =Q16+R16+T16 -> 5167000 | AJ16: =AI16/D16 -> 24841.346 | AK16: =AJ16*(E16+F16*130%) -> 5276301.9 | AL16: =AJ16*H16*150% -> 1565004.8 | AM16: =AJ16*I16*150%*130% -> 871931.25 | AN16: =+AJ16*J16*200% -> 0 | AO16: =AJ16*K16*200%*130% -> 0 | AP16: =AJ16*L16*200%*150% -> 0 | AQ16: =AJ16*M16*200%*150%*130% -> 0 | AR16: =N16*AJ16*300% -> 0 | AS16: =AJ16*O16*130%*300% -> 0 | AT16: =P16*AJ16*150%*300% -> 0 | AU16: =SUM(AL16:AT16) -> 2436936.1 | AW16: =AH16+AK16+AU16+AF16-AG16 -> 9073238 | AX16: =Q16+R16+T16 -> 5167000 | AY16: =AX16*17.5% -> 904225 | AZ16: =AX16*3% -> 155010 | BA16: =AX16*1% -> 51670 | BB16: =AX16*2% -> 103340 | BC16: =AY16+AZ16+BA16+BB16 -> 1214245 | BD16: =AX16*8% -> 413360 | BE16: =AX16*1.5% -> 77505 | BF16: =AX16*1% -> 51670 | BG16: =BD16+BE16+BF16 -> 542535 | BH16: 11000000 | BJ16: =BI16*4400000 -> 0 | BK16: =V16+AA16+AD16 -> 260000 | BL16: =AW16-BK16-F16*0.3*AJ16 -> 8231950.5 | BM16: =IF(BL16-BH16-BJ16-BG16<0,0,BL16-BH16-BJ16-BG16) -> 0 | BN16: =ROUND(IF(BM16<=5000000,BM16*5%,IF(AND(BM16>5000000,BM16<=10000000),BM16*10%-250000,IF(AND(BM16>10000000,BM16<=18000000),BM16*15%-750000,IF(AND(BM16>18000000,BM16<=32000000),BM16*20%-1650000,IF(AND(BM16>32000000,BM16<=52000000),BM16*25%-3250000,IF(AND(BM16>52000000,BM16<80000000),BM16*30%-585000,IF(BM16>80000000,BM16*35%-9850000))))))),0) -> 0 | BO16: 35000 | BQ16: =AW16-BG16-BN16-BO16 -> 8495703 | BR16: 105875696614
A17: =A16+1 -> 8 | B17: Trần Mạnh Hùng | C17: CN | D17: 208 | E17: 137 | F17: 52 | G17: 19 | H17: 48 | I17: 10.5 | Q17: 4267000 | T17: 900000 | U17: 0 | V17: =IF((E17+F17)>=180, U17, U17/D17*(E17+F17)) -> 0 | W17: 300000 | X17: =IF((E17+F17)>=180, W17, W17/D17*(E17+F17)) -> 300000 | Y17: 300000 | Z17: =IF((E17+F17)>=180, Y17, Y17/D17*(E17+F17)) -> 300000 | AA17: 0 | AC17: 500000 | AD17: =G17*13000 -> 247000 | AH17: =V17+X17+Z17+AB17+AC17+AD17+AE17 -> 1347000 | AI17: =Q17+R17+T17 -> 5167000 | AJ17: =AI17/D17 -> 24841.346 | AK17: =AJ17*(E17+F17*130%) -> 5082539.4 | AL17: =AJ17*H17*150% -> 1788576.9 | AM17: =AJ17*I17*150%*130% -> 508626.56 | AN17: =+AJ17*J17*200% -> 0 | AO17: =AJ17*K17*200%*130% -> 0 | AP17: =AJ17*L17*200%*150% -> 0 | AQ17: =AJ17*M17*200%*150%*130% -> 0 | AR17: =N17*AJ17*300% -> 0 | AS17: =AJ17*O17*130%*300% -> 0 | AT17: =P17*AJ17*150%*300% -> 0 | AU17: =SUM(AL17:AT17) -> 2297203.5 | AW17: =AH17+AK17+AU17+AF17-AG17 -> 8726742.9 | AX17: =Q17+R17+T17 -> 5167000 | AY17: =AX17*17.5% -> 904225 | AZ17: =AX17*3% -> 155010 | BA17: =AX17*1% -> 51670 | BB17: =AX17*2% -> 103340 | BC17: =AY17+AZ17+BA17+BB17 -> 1214245 | BD17: =AX17*8% -> 413360 | BE17: =AX17*1.5% -> 77505 | BF17: =AX17*1% -> 51670 | BG17: =BD17+BE17+BF17 -> 542535 | BH17: 11000000 | BJ17: =BI17*4400000 -> 0 | BK17: =V17+AA17+AD17 -> 247000 | BL17: =AW17-BK17-F17*0.3*AJ17 -> 8092217.9 | BM17: =IF(BL17-BH17-BJ17-BG17<0,0,BL17-BH17-BJ17-BG17) -> 0 | BN17: =ROUND(IF(BM17<=5000000,BM17*5%,IF(AND(BM17>5000000,BM17<=10000000),BM17*10%-250000,IF(AND(BM17>10000000,BM17<=18000000),BM17*15%-750000,IF(AND(BM17>18000000,BM17<=32000000),BM17*20%-1650000,IF(AND(BM17>32000000,BM17<=52000000),BM17*25%-3250000,IF(AND(BM17>52000000,BM17<80000000),BM17*30%-585000,IF(BM17>80000000,BM17*35%-9850000))))))),0) -> 0 | BO17: 35000 | BQ17: =AW17-BG17-BN17-BO17 -> 8149207.9 | BR17: 101873372347
A18: =A17+1 -> 9 | B18: Bùi Di Kết | C18: CN | D18: 208 | E18: 123 | F18: 32.5 | G18: 14 | H18: 35 | I18: 7.5 | Q18: 4267000 | R18: 300000 | T18: 600000 | U18: 0 | V18: =IF((E18+F18)>=180, U18, U18/D18*(E18+F18)) -> 0 | W18: 300000 | X18: =IF((E18+F18)>=180, W18, W18/D18*(E18+F18)) -> 224278.85 | Y18: 300000 | Z18: =IF((E18+F18)>=180, Y18, Y18/D18*(E18+F18)) -> 224278.85 | AA18: 0 | AC18: 0 | AD18: =G18*13000 -> 182000 | AH18: =V18+X18+Z18+AB18+AC18+AD18+AE18 -> 630557.69 | AI18: =Q18+R18+T18 -> 5167000 | AJ18: =AI18/D18 -> 24841.346 | AK18: =AJ18*(E18+F18*130%) -> 4105032.5 | AL18: =AJ18*H18*150% -> 1304170.7 | AM18: =AJ18*I18*150%*130% -> 363304.69 | AN18: =+AJ18*J18*200% -> 0 | AO18: =AJ18*K18*200%*130% -> 0 | AP18: =AJ18*L18*200%*150% -> 0 | AQ18: =AJ18*M18*200%*150%*130% -> 0 | AR18: =N18*AJ18*300% -> 0 | AS18: =AJ18*O18*130%*300% -> 0 | AT18: =P18*AJ18*150%*300% -> 0 | AU18: =SUM(AL18:AT18) -> 1667475.4 | AW18: =AH18+AK18+AU18+AF18-AG18 -> 6403065.5 | AX18: =Q18+R18+T18 -> 5167000 | AY18: =AX18*17.5% -> 904225 | AZ18: =AX18*3% -> 155010 | BA18: =AX18*1% -> 51670 | BB18: =AX18*2% -> 103340 | BC18: =AY18+AZ18+BA18+BB18 -> 1214245 | BD18: =AX18*8% -> 413360 | BE18: =AX18*1.5% -> 77505 | BF18: =AX18*1% -> 51670 | BG18: =BD18+BE18+BF18 -> 542535 | BH18: 11000000 | BJ18: =BI18*4400000 -> 0 | BK18: =V18+AA18+AD18 -> 182000 | BL18: =AW18-BK18-F18*0.3*AJ18 -> 5978862.4 | BM18: =IF(BL18-BH18-BJ18-BG18<0,0,BL18-BH18-BJ18-BG18) -> 0 | BN18: =ROUND(IF(BM18<=5000000,BM18*5%,IF(AND(BM18>5000000,BM18<=10000000),BM18*10%-250000,IF(AND(BM18>10000000,BM18<=18000000),BM18*15%-750000,IF(AND(BM18>18000000,BM18<=32000000),BM18*20%-1650000,IF(AND(BM18>32000000,BM18<=52000000),BM18*25%-3250000,IF(AND(BM18>52000000,BM18<80000000),BM18*30%-585000,IF(BM18>80000000,BM18*35%-9850000))))))),0) -> 0 | BO18: 35000 | BQ18: =AW18-BG18-BN18-BO18 -> 5825530.5 | BR18: 105875693791
A19: =A18+1 -> 10 | B19: Nguyễn Văn Đoàn | C19: CN | D19: 208 | E19: 111 | F19: 78 | G19: 20 | H19: 42 | I19: 18 | Q19: 4267000 | T19: 600000 | U19: 0 | V19: =IF((E19+F19)>=180, U19, U19/D19*(E19+F19)) -> 0 | W19: 300000 | X19: =IF((E19+F19)>=180, W19, W19/D19*(E19+F19)) -> 300000 | Y19: 300000 | Z19: =IF((E19+F19)>=180, Y19, Y19/D19*(E19+F19)) -> 300000 | AA19: 0 | AC19: 500000 | AD19: =G19*13000 -> 260000 | AH19: =V19+X19+Z19+AB19+AC19+AD19+AE19 -> 1360000 | AI19: =Q19+R19+T19 -> 4867000 | AJ19: =AI19/D19 -> 23399.038 | AK19: =AJ19*(E19+F19*130%) -> 4969955.8 | AL19: =AJ19*H19*150% -> 1474139.4 | AM19: =AJ19*I19*150%*130% -> 821306.25 | AN19: =+AJ19*J19*200% -> 0 | AO19: =AJ19*K19*200%*130% -> 0 | AP19: =AJ19*L19*200%*150% -> 0 | AQ19: =AJ19*M19*200%*150%*130% -> 0 | AR19: =N19*AJ19*300% -> 0 | AS19: =AJ19*O19*130%*300% -> 0 | AT19: =P19*AJ19*150%*300% -> 0 | AU19: =SUM(AL19:AT19) -> 2295445.7 | AW19: =AH19+AK19+AU19+AF19-AG19 -> 8625401.4 | AX19: =Q19+R19+T19 -> 4867000 | AY19: =AX19*17.5% -> 851725 | AZ19: =AX19*3% -> 146010 | BA19: =AX19*1% -> 48670 | BB19: =AX19*2% -> 97340 | BC19: =AY19+AZ19+BA19+BB19 -> 1143745 | BD19: =AX19*8% -> 389360 | BE19: =AX19*1.5% -> 73005 | BF19: =AX19*1% -> 48670 | BG19: =BD19+BE19+BF19 -> 511035 | BH19: 11000000 | BJ19: =BI19*4400000 -> 0 | BK19: =V19+AA19+AD19 -> 260000 | BL19: =AW19-BK19-F19*0.3*AJ19 -> 7817863.9 | BM19: =IF(BL19-BH19-BJ19-BG19<0,0,BL19-BH19-BJ19-BG19) -> 0 | BN19: =ROUND(IF(BM19<=5000000,BM19*5%,IF(AND(BM19>5000000,BM19<=10000000),BM19*10%-250000,IF(AND(BM19>10000000,BM19<=18000000),BM19*15%-750000,IF(AND(BM19>18000000,BM19<=32000000),BM19*20%-1650000,IF(AND(BM19>32000000,BM19<=52000000),BM19*25%-3250000,IF(AND(BM19>52000000,BM19<80000000),BM19*30%-585000,IF(BM19>80000000,BM19*35%-9850000))))))),0) -> 0 | BO19: 35000 | BQ19: =AW19-BG19-BN19-BO19 -> 8079366.4 | BR19: 106875693790
A20: =A19+1 -> 11 | B20: Trịnh Bá Vàng | C20: CN | D20: 208 | E20: 130.5 | F20: 58.5 | G20: 19 | H20: 43.5 | I20: 13.5 | Q20: 4267000 | R20: 300000 | T20: 600000 | U20: 0 | V20: =IF((E20+F20)>=180, U20, U20/D20*(E20+F20)) -> 0 | W20: 300000 | X20: =IF((E20+F20)>=180, W20, W20/D20*(E20+F20)) -> 300000 | Y20: 300000 | Z20: =IF((E20+F20)>=180, Y20, Y20/D20*(E20+F20)) -> 300000 | AA20: 0 | AB20: 40000 | AC20: 500000 | AD20: =G20*13000 -> 247000 | AH20: =V20+X20+Z20+AB20+AC20+AD20+AE20 -> 1387000 | AI20: =Q20+R20+T20 -> 5167000 | AJ20: =AI20/D20 -> 24841.346 | AK20: =AJ20*(E20+F20*130%) -> 5130980 | AL20: =AJ20*H20*150% -> 1620897.8 | AM20: =AJ20*I20*150%*130% -> 653948.44 | AN20: =+AJ20*J20*200% -> 0 | AO20: =AJ20*K20*200%*130% -> 0 | AP20: =AJ20*L20*200%*150% -> 0 | AQ20: =AJ20*M20*200%*150%*130% -> 0 | AR20: =N20*AJ20*300% -> 0 | AS20: =AJ20*O20*130%*300% -> 0 | AT20: =P20*AJ20*150%*300% -> 0 | AU20: =SUM(AL20:AT20) -> 2274846.3 | AW20: =AH20+AK20+AU20+AF20-AG20 -> 8792826.3 | AX20: =Q20+R20+T20 -> 5167000 | AY20: =AX20*17.5% -> 904225 | AZ20: =AX20*3% -> 155010 | BA20: =AX20*1% -> 51670 | BB20: =AX20*2% -> 103340 | BC20: =AY20+AZ20+BA20+BB20 -> 1214245 | BD20: =AX20*8% -> 413360 | BE20: =AX20*1.5% -> 77505 | BF20: =AX20*1% -> 51670 | BG20: =BD20+BE20+BF20 -> 542535 | BH20: 11000000 | BJ20: =BI20*4400000 -> 0 | BK20: =V20+AA20+AD20 -> 247000 | BL20: =AW20-BK20-F20*0.3*AJ20 -> 8109860.7 | BM20: =IF(BL20-BH20-BJ20-BG20<0,0,BL20-BH20-BJ20-BG20) -> 0 | BN20: =ROUND(IF(BM20<=5000000,BM20*5%,IF(AND(BM20>5000000,BM20<=10000000),BM20*10%-250000,IF(AND(BM20>10000000,BM20<=18000000),BM20*15%-750000,IF(AND(BM20>18000000,BM20<=32000000),BM20*20%-1650000,IF(AND(BM20>32000000,BM20<=52000000),BM20*25%-3250000,IF(AND(BM20>52000000,BM20<80000000),BM20*30%-585000,IF(BM20>80000000,BM20*35%-9850000))))))),0) -> 0 | BO20: 35000 | BQ20: =AW20-BG20-BN20-BO20 -> 8215291.3 | BR20: 102876026588
A21: =A20+1 -> 12 | B21: Trần Văn Đoàn | C21: CN | D21: 208 | E21: 126.5 | F21: 71.5 | G21: 21 | H21: 46.5 | I21: 16.5 | Q21: 4267000 | T21: 600000 | U21: 0 | V21: =IF((E21+F21)>=180, U21, U21/D21*(E21+F21)) -> 0 | W21: 300000 | X21: =IF((E21+F21)>=180, W21, W21/D21*(E21+F21)) -> 300000 | Y21: 300000 | Z21: =IF((E21+F21)>=180, Y21, Y21/D21*(E21+F21)) -> 300000 | AA21: 0 | AB21: 20000 | AC21: 500000 | AD21: =G21*13000 -> 273000 | AH21: =V21+X21+Z21+AB21+AC21+AD21+AE21 -> 1393000 | AI21: =Q21+R21+T21 -> 4867000 | AJ21: =AI21/D21 -> 23399.038 | AK21: =AJ21*(E21+F21*130%) -> 5134919 | AL21: =AJ21*H21*150% -> 1632082.9 | AM21: =AJ21*I21*150%*130% -> 752864.06 | AN21: =+AJ21*J21*200% -> 0 | AO21: =AJ21*K21*200%*130% -> 0 | AP21: =AJ21*L21*200%*150% -> 0 | AQ21: =AJ21*M21*200%*150%*130% -> 0 | AR21: =N21*AJ21*300% -> 0 | AS21: =AJ21*O21*130%*300% -> 0 | AT21: =P21*AJ21*150%*300% -> 0 | AU21: =SUM(AL21:AT21) -> 2384947 | AW21: =AH21+AK21+AU21+AF21-AG21 -> 8912866 | AX21: =Q21+R21+T21 -> 4867000 | AY21: =AX21*17.5% -> 851725 | AZ21: =AX21*3% -> 146010 | BA21: =AX21*1% -> 48670 | BB21: =AX21*2% -> 97340 | BC21: =AY21+AZ21+BA21+BB21 -> 1143745 | BD21: =AX21*8% -> 389360 | BE21: =AX21*1.5% -> 73005 | BF21: =AX21*1% -> 48670 | BG21: =BD21+BE21+BF21 -> 511035 | BH21: 11000000 | BJ21: =BI21*4400000 -> 0 | BK21: =V21+AA21+AD21 -> 273000 | BL21: =AW21-BK21-F21*0.3*AJ21 -> 8137956.6 | BM21: =IF(BL21-BH21-BJ21-BG21<0,0,BL21-BH21-BJ21-BG21) -> 0 | BN21: =ROUND(IF(BM21<=5000000,BM21*5%,IF(AND(BM21>5000000,BM21<=10000000),BM21*10%-250000,IF(AND(BM21>10000000,BM21<=18000000),BM21*15%-750000,IF(AND(BM21>18000000,BM21<=32000000),BM21*20%-1650000,IF(AND(BM21>32000000,BM21<=52000000),BM21*25%-3250000,IF(AND(BM21>52000000,BM21<80000000),BM21*30%-585000,IF(BM21>80000000,BM21*35%-9850000))))))),0) -> 0 | BO21: 35000 | BQ21: =AW21-BG21-BN21-BO21 -> 8366831 | BR21: 106876025190
A22: =A21+1 -> 13 | B22: Trịnh Xuân Bồng | C22: CN | D22: 208 | E22: 137 | F22: 52 | G22: 18 | H22: 45 | I22: 10.5 | Q22: 4267000 | T22: 300000 | U22: 0 | V22: =IF((E22+F22)>=180, U22, U22/D22*(E22+F22)) -> 0 | W22: 300000 | X22: =IF((E22+F22)>=180, W22, W22/D22*(E22+F22)) -> 300000 | Y22: 300000 | Z22: =IF((E22+F22)>=180, Y22, Y22/D22*(E22+F22)) -> 300000 | AA22: 0 | AC22: 500000 | AD22: =G22*13000 -> 234000 | AH22: =V22+X22+Z22+AB22+AC22+AD22+AE22 -> 1334000 | AI22: =Q22+R22+T22 -> 4567000 | AJ22: =AI22/D22 -> 21956.731 | AK22: =AJ22*(E22+F22*130%) -> 4492347.1 | AL22: =AJ22*H22*150% -> 1482079.3 | AM22: =AJ22*I22*150%*130% -> 449564.06 | AN22: =+AJ22*J22*200% -> 0 | AO22: =AJ22*K22*200%*130% -> 0 | AP22: =AJ22*L22*200%*150% -> 0 | AQ22: =AJ22*M22*200%*150%*130% -> 0 | AR22: =N22*AJ22*300% -> 0 | AS22: =AJ22*O22*130%*300% -> 0 | AT22: =P22*AJ22*150%*300% -> 0 | AU22: =SUM(AL22:AT22) -> 1931643.4 | AW22: =AH22+AK22+AU22+AF22-AG22 -> 7757990.5 | AX22: =Q22+R22+T22 -> 4567000 | AY22: =AX22*17.5% -> 799225 | AZ22: =AX22*3% -> 137010 | BA22: =AX22*1% -> 45670 | BB22: =AX22*2% -> 91340 | BC22: =AY22+AZ22+BA22+BB22 -> 1073245 | BD22: =AX22*8% -> 365360 | BE22: =AX22*1.5% -> 68505 | BF22: =AX22*1% -> 45670 | BG22: =BD22+BE22+BF22 -> 479535 | BH22: 11000000 | BJ22: =BI22*4400000 -> 0 | BK22: =V22+AA22+AD22 -> 234000 | BL22: =AW22-BK22-F22*0.3*AJ22 -> 7181465.5 | BM22: =IF(BL22-BH22-BJ22-BG22<0,0,BL22-BH22-BJ22-BG22) -> 0 | BN22: =ROUND(IF(BM22<=5000000,BM22*5%,IF(AND(BM22>5000000,BM22<=10000000),BM22*10%-250000,IF(AND(BM22>10000000,BM22<=18000000),BM22*15%-750000,IF(AND(BM22>18000000,BM22<=32000000),BM22*20%-1650000,IF(AND(BM22>32000000,BM22<=52000000),BM22*25%-3250000,IF(AND(BM22>52000000,BM22<80000000),BM22*30%-585000,IF(BM22>80000000,BM22*35%-9850000))))))),0) -> 0 | BO22: 35000 | BQ22: =AW22-BG22-BN22-BO22 -> 7243455.5 | BR22: 105878734423
A23: =A22+1 -> 14 | B23: Bùi Văn Tâm | C23: CN | D23: 208 | E23: 123.5 | F23: 52 | G23: 14 | H23: 33 | I23: 10.5 | Q23: 4064000 | U23: 0 | V23: =IF((E23+F23)>=180, U23, U23/D23*(E23+F23)) -> 0 | W23: 300000 | X23: =IF((E23+F23)>=180, W23, W23/D23*(E23+F23)) -> 253125 | Y23: 300000 | Z23: =IF((E23+F23)>=180, Y23, Y23/D23*(E23+F23)) -> 253125 | AA23: 0 | AD23: =G23*13000 -> 182000 | AH23: =V23+X23+Z23+AB23+AC23+AD23+AE23 -> 688250 | AI23: =Q23+R23+T23 -> 4064000 | AJ23: =AI23/D23 -> 19538.462 | AK23: =AJ23*(E23+F23*130%) -> 3733800 | AL23: =AJ23*H23*150% -> 967153.85 | AM23: =AJ23*I23*150%*130% -> 400050 | AN23: =+AJ23*J23*200% -> 0 | AO23: =AJ23*K23*200%*130% -> 0 | AP23: =AJ23*L23*200%*150% -> 0 | AQ23: =AJ23*M23*200%*150%*130% -> 0 | AR23: =N23*AJ23*300% -> 0 | AS23: =AJ23*O23*130%*300% -> 0 | AT23: =P23*AJ23*150%*300% -> 0 | AU23: =SUM(AL23:AT23) -> 1367203.8 | AW23: =AH23+AK23+AU23+AF23-AG23 -> 5789253.8 | AX23: =Q23+R23+T23 -> 4064000 | AY23: =AX23*17.5% -> 711200 | AZ23: =AX23*3% -> 121920 | BA23: =AX23*1% -> 40640 | BB23: =AX23*2% -> 81280 | BC23: =AY23+AZ23+BA23+BB23 -> 955040 | BD23: =AX23*8% -> 325120 | BE23: =AX23*1.5% -> 60960 | BF23: =AX23*1% -> 40640 | BG23: =BD23+BE23+BF23 -> 426720 | BH23: 11000000 | BJ23: =BI23*4400000 -> 0 | BK23: =V23+AA23+AD23 -> 182000 | BL23: =AW23-BK23-F23*0.3*AJ23 -> 5302453.8 | BM23: =IF(BL23-BH23-BJ23-BG23<0,0,BL23-BH23-BJ23-BG23) -> 0 | BN23: =ROUND(IF(BM23<=5000000,BM23*5%,IF(AND(BM23>5000000,BM23<=10000000),BM23*10%-250000,IF(AND(BM23>10000000,BM23<=18000000),BM23*15%-750000,IF(AND(BM23>18000000,BM23<=32000000),BM23*20%-1650000,IF(AND(BM23>32000000,BM23<=52000000),BM23*25%-3250000,IF(AND(BM23>52000000,BM23<80000000),BM23*30%-585000,IF(BM23>80000000,BM23*35%-9850000))))))),0) -> 0 | BO23: 35000 | BQ23: =AW23-BG23-BN23-BO23 -> 5327533.8 | BR23: 105878734423
A24: =A23+1 -> 15 | B24: Nguyễn Ngọc Đông | C24: CN | D24: 208 | E24: 124 | F24: 65 | G24: 17 | H24: 36 | I24: 15 | Q24: 4064000 | U24: 0 | V24: =IF((E24+F24)>=180, U24, U24/D24*(E24+F24)) -> 0 | W24: 300000 | X24: =IF((E24+F24)>=180, W24, W24/D24*(E24+F24)) -> 300000 | Y24: 300000 | Z24: =IF((E24+F24)>=180, Y24, Y24/D24*(E24+F24)) -> 300000 | AA24: 0 | AC24: 500000 | AD24: =G24*13000 -> 221000 | AH24: =V24+X24+Z24+AB24+AC24+AD24+AE24 -> 1321000 | AI24: =Q24+R24+T24 -> 4064000 | AJ24: =AI24/D24 -> 19538.462 | AK24: =AJ24*(E24+F24*130%) -> 4073769.2 | AL24: =AJ24*H24*150% -> 1055076.9 | AM24: =AJ24*I24*150%*130% -> 571500 | AN24: =+AJ24*J24*200% -> 0 | AO24: =AJ24*K24*200%*130% -> 0 | AP24: =AJ24*L24*200%*150% -> 0 | AQ24: =AJ24*M24*200%*150%*130% -> 0 | AR24: =N24*AJ24*300% -> 0 | AS24: =AJ24*O24*130%*300% -> 0 | AT24: =P24*AJ24*150%*300% -> 0 | AU24: =SUM(AL24:AT24) -> 1626576.9 | AW24: =AH24+AK24+AU24+AF24-AG24 -> 7021346.2 | AX24: =Q24+R24+T24 -> 4064000 | AY24: =AX24*17.5% -> 711200 | AZ24: =AX24*3% -> 121920 | BA24: =AX24*1% -> 40640 | BB24: =AX24*2% -> 81280 | BC24: =AY24+AZ24+BA24+BB24 -> 955040 | BD24: =AX24*8% -> 325120 | BE24: =AX24*1.5% -> 60960 | BF24: =AX24*1% -> 40640 | BG24: =BD24+BE24+BF24 -> 426720 | BH24: 11000000 | BJ24: =BI24*4400000 -> 0 | BK24: =V24+AA24+AD24 -> 221000 | BL24: =AW24-BK24-F24*0.3*AJ24 -> 6419346.2 | BM24: =IF(BL24-BH24-BJ24-BG24<0,0,BL24-BH24-BJ24-BG24) -> 0 | BN24: =ROUND(IF(BM24<=5000000,BM24*5%,IF(AND(BM24>5000000,BM24<=10000000),BM24*10%-250000,IF(AND(BM24>10000000,BM24<=18000000),BM24*15%-750000,IF(AND(BM24>18000000,BM24<=32000000),BM24*20%-1650000,IF(AND(BM24>32000000,BM24<=52000000),BM24*25%-3250000,IF(AND(BM24>52000000,BM24<80000000),BM24*30%-585000,IF(BM24>80000000,BM24*35%-9850000))))))),0) -> 0 | BO24: 35000 | BQ24: =AW24-BG24-BN24-BO24 -> 6559626.2 | BR24: 105878734423
A25: =A24+1 -> 16 | B25: Lại Đức Long | C25: CN | D25: 208 | E25: 86.5 | F25: 26 | G25: 10 | H25: 25.5 | I25: 4.5 | Q25: 4064000 | U25: 0 | V25: =IF((E25+F25)>=180, U25, U25/D25*(E25+F25)) -> 0 | W25: 300000 | X25: =IF((E25+F25)>=180, W25, W25/D25*(E25+F25)) -> 162259.62 | Y25: 300000 | Z25: =IF((E25+F25)>=180, Y25, Y25/D25*(E25+F25)) -> 162259.62 | AA25: 0 | AC25: 0 | AD25: =G25*13000 -> 130000 | AH25: =V25+X25+Z25+AB25+AC25+AD25+AE25 -> 454519.23 | AI25: =Q25+R25+T25 -> 4064000 | AJ25: =AI25/D25 -> 19538.462 | AK25: =AJ25*(E25+F25*130%) -> 2350476.9 | AL25: =AJ25*H25*150% -> 747346.15 | AM25: =AJ25*I25*150%*130% -> 171450 | AN25: =+AJ25*J25*200% -> 0 | AO25: =AJ25*K25*200%*130% -> 0 | AP25: =AJ25*L25*200%*150% -> 0 | AQ25: =AJ25*M25*200%*150%*130% -> 0 | AR25: =N25*AJ25*300% -> 0 | AS25: =AJ25*O25*130%*300% -> 0 | AT25: =P25*AJ25*150%*300% -> 0 | AU25: =SUM(AL25:AT25) -> 918796.15 | AW25: =AH25+AK25+AU25+AF25-AG25 -> 3723792.3 | AX25: =Q25+R25+T25 -> 4064000 | AY25: =AX25*17.5% -> 711200 | AZ25: =AX25*3% -> 121920 | BA25: =AX25*1% -> 40640 | BB25: =AX25*2% -> 81280 | BC25: =AY25+AZ25+BA25+BB25 -> 955040 | BD25: =AX25*8% -> 325120 | BE25: =AX25*1.5% -> 60960 | BF25: =AX25*1% -> 40640 | BG25: =BD25+BE25+BF25 -> 426720 | BH25: 11000000 | BJ25: =BI25*4400000 -> 0 | BK25: =V25+AA25+AD25 -> 130000 | BL25: =AW25-BK25-F25*0.3*AJ25 -> 3441392.3 | BM25: =IF(BL25-BH25-BJ25-BG25<0,0,BL25-BH25-BJ25-BG25) -> 0 | BN25: =ROUND(IF(BM25<=5000000,BM25*5%,IF(AND(BM25>5000000,BM25<=10000000),BM25*10%-250000,IF(AND(BM25>10000000,BM25<=18000000),BM25*15%-750000,IF(AND(BM25>18000000,BM25<=32000000),BM25*20%-1650000,IF(AND(BM25>32000000,BM25<=52000000),BM25*25%-3250000,IF(AND(BM25>52000000,BM25<80000000),BM25*30%-585000,IF(BM25>80000000,BM25*35%-9850000))))))),0) -> 0 | BO25: 35000 | BQ25: =AW25-BG25-BN25-BO25 -> 3262072.3 | BR25: 105878734423
A26: =A25+1 -> 17 | B26: Hán Thế Trọng | C26: CN | D26: 208 | E26: 130.5 | F26: 58.5 | G26: 19 | H26: 44.5 | I26: 13.5 | Q26: 4064000 | U26: 0 | V26: =IF((E26+F26)>=180, U26, U26/D26*(E26+F26)) -> 0 | W26: 300000 | X26: =IF((E26+F26)>=180, W26, W26/D26*(E26+F26)) -> 300000 | Y26: 300000 | Z26: =IF((E26+F26)>=180, Y26, Y26/D26*(E26+F26)) -> 300000 | AA26: 0 | AC26: 500000 | AD26: =G26*13000 -> 247000 | AH26: =V26+X26+Z26+AB26+AC26+AD26+AE26 -> 1347000 | AI26: =Q26+R26+T26 -> 4064000 | AJ26: =AI26/D26 -> 19538.462 | AK26: =AJ26*(E26+F26*130%) -> 4035669.2 | AL26: =AJ26*H26*150% -> 1304192.3 | AM26: =AJ26*I26*150%*130% -> 514350 | AN26: =+AJ26*J26*200% -> 0 | AO26: =AJ26*K26*200%*130% -> 0 | AP26: =AJ26*L26*200%*150% -> 0 | AQ26: =AJ26*M26*200%*150%*130% -> 0 | AR26: =N26*AJ26*300% -> 0 | AS26: =AJ26*O26*130%*300% -> 0 | AT26: =P26*AJ26*150%*300% -> 0 | AU26: =SUM(AL26:AT26) -> 1818542.3 | AW26: =AH26+AK26+AU26+AF26-AG26 -> 7201211.5 | AX26: =Q26+R26+T26 -> 4064000 | AY26: =AX26*17.5% -> 711200 | AZ26: =AX26*3% -> 121920 | BA26: =AX26*1% -> 40640 | BB26: =AX26*2% -> 81280 | BC26: =AY26+AZ26+BA26+BB26 -> 955040 | BD26: =AX26*8% -> 325120 | BE26: =AX26*1.5% -> 60960 | BF26: =AX26*1% -> 40640 | BG26: =BD26+BE26+BF26 -> 426720 | BH26: 11000000 | BJ26: =BI26*4400000 -> 0 | BK26: =V26+AA26+AD26 -> 247000 | BL26: =AW26-BK26-F26*0.3*AJ26 -> 6611311.5 | BM26: =IF(BL26-BH26-BJ26-BG26<0,0,BL26-BH26-BJ26-BG26) -> 0 | BN26: =ROUND(IF(BM26<=5000000,BM26*5%,IF(AND(BM26>5000000,BM26<=10000000),BM26*10%-250000,IF(AND(BM26>10000000,BM26<=18000000),BM26*15%-750000,IF(AND(BM26>18000000,BM26<=32000000),BM26*20%-1650000,IF(AND(BM26>32000000,BM26<=52000000),BM26*25%-3250000,IF(AND(BM26>52000000,BM26<80000000),BM26*30%-585000,IF(BM26>80000000,BM26*35%-9850000))))))),0) -> 0 | BQ26: =AW26-BG26-BN26-BO26 -> 6774491.5 | BR26: 105878734423
A27: Tổng | D27: =SUM(D10:D22) -> 2704 | E27: =SUM(E10:E26) -> 2088 | F27: =SUM(F10:F26) -> 1001 | G27: =SUM(G10:G26) -> 307 | H27: =SUM(H10:H26) -> 712.5 | I27: =SUM(I10:I26) -> 222 | J27: =SUM(J10:J25) -> 0 | K27: =SUM(K10:K25) -> 0 | L27: =SUM(L10:L25) -> 0 | M27: =SUM(M10:M25) -> 0 | N27: =SUM(N10:N25) -> 0 | O27: =SUM(O10:O25) -> 0 | P27: =SUM(P10:P25) -> 0 | Q27: =SUM(Q10:Q26) -> 71727000 | R27: =SUM(R10:R26) -> 7400000 | S27: =SUM(S10:S26) -> 0 | T27: =SUM(T10:T26) -> 9600000 | U27: =SUM(U10:U26) -> 0 | V27: =SUM(V10:V26) -> 0 | W27: =SUM(W10:W26) -> 5500000 | X27: =SUM(X10:X26) -> 5239663.5 | ... BO27: =SUM(BO10:BO26) -> 560000 | BQ27: =SUM(BQ10:BQ26) -> 1.3559816e+08 | BR27: =SUM(BR10:BR26) -> 0
B29: Scheduling | AF29: Manager | BG29: Director- general
AF32: =AF27-AF10 -> 0

Sheet Payroll of factory (DET).1
A1: CÔNG TY TNHH SHINSUNG VINA
A2: Lô CN04, khu công nghiệp Cẩm Khê, TT.Cẩm Khê, H.Cẩm Khê, T.Phú Thọ
A3: ='Payroll Office'!A3:BO3 -> PAYROLL AUGUST 2024
A4: ='Payroll Office'!A4:BO4 -> From 1st -31th August 2024
BP6: VND
A7: STT (No) | B7: Họ và tên (First and last name) | C7: Vị trí (Location) | D7: Tổng giờ công chuẩn | E7: Giờ công cơ bản thực tế (The actual basic hourly) | G7: Số bữa phụ | H7: Giờ công làm thêm (Hours of overtime) | Q7: Lương đóng bảo hiểm | U7: Các khoản phụ cấp (Allowances) | AF7: Thưởng Tết Âm lịch 20% (Ngày lễ 02/09) | AG7: Khấu trừ khác | AH7: Tổng phụ cấp không đóng BH được nhận (Total allowances) | AI7: Lương đóng bảo hiểm /Salary for insurance | AJ7: Lương giờ công /Salary for insurance | AK7: Tổng lương giờ công cơ bản /Total base salary | AM7: Lương giờ công làm thêm | AW7: Bổ sung lương T11 | AX7: Tổng lương | AY7: BH tính vào chi phí / Isuarance payable by company | BE7: BH khấu trừ lương / Isuarance deductions from salary | BI7: Thuế TNCN | BP7: Đoàn phí | BQ7: Khấu trừ khác | BR7: Thực nhận | BS7: Số tài khoản | BT7: Ký nhận
E8: Ca ngày | F8: Ca đêm | H8: Tăng ca 150% | I8: Tăng ca đêm 195% | J8: CN ngày 200% | K8: CN đêm 260% | L8: Tăng ca ngày CN 300% | M8: Tăng ca đêm CN 390% | N8: Ngày lễ ngày 300% | O8: Ngày lễ đêm 390% | P8: TC lễ (450%) | Q8: Lương cơ bản (Basic salary) | R8: Phụ cấp trách nhiệm/ Responsibility allowance | S8: PC ngoại ngữ/ Foreign language support | T8: Phụ cấp thâm niên/ Seniority allowances | U8: HT điện thoại /Phone charges/ 26 Công | V8: HT điện thoại /Phone charges | W8: HT xăng xe /Fuel costs for vehicles/ 26 Công | X8: HT xăng xe /Fuel costs for vehicles | Y8: HT nhà ở /Housing support/ 26 Công | Z8: HT nhà ở /Housing support | AA8: HT con nhỏ /Supporting children | AB8: Phụ cấp đi lại | AC8: Thưởng Chuyên cần /Reward for diligence | AD8: Trợ cấp bữa phụ /Snack allowance | AE8: ='Payroll Office'!AE8 -> Thưởng sinh nhật tháng 08 /Birthday in August | AM8: Tăng ca ngày | AN8: Tăng ca đêm | AO8: CN ngày | AP8: CN đêm | AQ8: Tăng ca ngày CN | AR8: Tăng ca đêm CN | AS8: Ngày lễ ngày | AT8: Ngày lễ đêm | AU8: TC lễ | AV8: Tổng lương làm thêm | AY8: Lương đóng bảo hiểm/Salary base for insurance | AZ8: BHXH / Social Insurance 17.5% | BA8: BHYT / Health Insurance 3%건강보험 (회사분) | BB8: BHTN / Unemployment Insurance 1% | BC8: KPCĐ 2% | BD8: Cộng /Amount Isurance | BE8: BHXH / Social Insurance 8% | BF8: BHYT / Health Insurance 1,5% 건강보험 (개인분) | BG8: BHTN / Unemployment Insurance 1% | BH8: Cộng 10.5%/Amount Isurance | BI8: Giảm trừ bản thân (기본공제금 ) (VND) | BJ8: Số người phụ thuộc /Number Deduction family | BK8: Giảm trừ người phụ thuộc /deduction-family 4400000/1person | BL8: Thu nhập miễn thuế /Tax excemption | BM8: Thu nhập chịu thuế | BN8: Thu nhập tính thuế (과세 대상 금액) VND | BO8: Thuế TNCN (개인소득세) ( VND)
A9: -1 | B9: -2 | C9: -3 | E9: (4a) | F9: (4b) | H9: (5a) | I9: (5b) | J9: (6a) | K9: (6b) | L9: (6c) | M9: (6d) | N9: 6e | O9: -7 | P9: 7a | Q9: -8 | R9: -9 | V9: -10 | X9: -11 | Z9: (11 a) | AA9: (11b) | AC9: -12 | AE9: (12a) | AH9: (13)=10+11+11a+11b+ 12+12a | AI9: (14)=(8)+(9) | AJ9: (15)=(14)/4 | AK9: (16)=(15)*(4a+4b*130%) | AM9: (17)=(5a)* (15)*150% | AN9: 17a=5b*15*150%*130% | AO9: 17b=6a*15*200% | AP9: 17c=6b*15*200%*130% | AQ9: (18)=(6c)* (15)*200%*150% | AR9: 18a=6d*15*200%*150%*130% | AS9: (19)=(6e)* (15)*300% | AT9: 19a=7*15*130%*300% | AU9: 19b=7a*15*150%*300% | AV9: (20)= (17)+(18)+(19) | AX9: (21)=(13)+(16)+ (20) | AY9: (22)=(8)+ (10) | AZ9: (23)=(22)x17% | BA9: (24)=(22)x3% | BB9: (25)=(22)x1% | BD9: (26)=(23)+(24)+ (25) | BE9: (27)=(22)x8% | BF9: (28)=(22)x1.5% | BG9: (29)=(22)x1% | BH9: (30)=(27)+(28)+(29) | BI9: -31 | BJ9: (31a) | BK9: (32)= (31a)x4400000 | BL9: -33 | BM9: (34)=(21)-(33) | BN9: (35)=(21)-(31)-(32)-(33) | BO9: -36 | BP9: -37 | BR9: -38
A10: 1 | B10: Đinh Thị Hải | C10: TT | D10: 208 | E10: 150 | F10: 66 | G10: 20 | H10: 49.5 | I10: 18 | Q10: 4267000 | R10: 1300000 | T10: 600000 | U10: 0 | V10: =IF((E10+F10)>=D10,U10,(E10+F10)*U10/D10) -> 0 | W10: 300000 | X10: =IF((E10+F10)>=160, W10, W10/D10*(E10+F10)) -> 300000 | Y10: 300000 | Z10: =IF((E10+F10)>=160,Y10, Y10/D10*(E10+F10)) -> 300000 | AA10: 20000 | AB10: 0 | AC10: =IF((E10+F10)>=184,500000,0) -> 500000 | AD10: =G10*13000 -> 260000 | AE10: 0 | AH10: =V10+X10+Z10+AA10+AC10+AD10+AE10 -> 1380000 | AI10: =Q10+R10+T10 -> 6167000 | AJ10: =AI10/208 -> 29649.038 | AK10: =AJ10*(E10+F10*130%) -> 6991243.3 | AM10: =AJ10*H10*150% -> 2201441.1 | AN10: =AJ10*I10*150%*130% -> 1040681.2 | AO10: =+AJ10*J10*200% -> 0 | AP10: =AJ10*K10*200%*130% -> 0 | AQ10: =AJ10*L10*200%*150% -> 0 | AR10: =AJ10*M10*200%*150%*130% -> 0 | AS10: =N10*AJ10*300% -> 0 | AT10: =AJ10*O10*130%*300% -> 0 | AU10: =P10*AJ10*150%*300% -> 0 | AV10: =SUM(AM10:AU10) -> 3242122.4 | AX10: =AH10+AK10+AV10++AF10-AG10+AW10 -> 11613366 | AY10: =Q10+R10+T10 -> 6167000 | AZ10: =AY10*17.5% -> 1079225 | BA10: =AY10*3% -> 185010 | BB10: =AY10*1% -> 61670 | BC10: =AY10*2% -> 123340 | BD10: =AZ10+BA10+BB10+BC10 -> 1449245 | BE10: =AY10*8% -> 493360 | BF10: =AY10*1.5% -> 92505 | BG10: =AY10*1% -> 61670 | BH10: =BE10+BF10+BG10 -> 647535 | BI10: 11000000 | BJ10: 0 | BK10: =BJ10*4400000 -> 0 | BL10: =V10+AB10+AD10 -> 260000 | BM10: =AX10-BL10-H10*0.5*AJ10-I10*0.95*AJ10-F10*0.3*AJ10-AJ10*J10-AJ10*K10*1.6-AJ10*L10*2-AJ10*M10*2.9-AJ10*N10*2-AJ10*O10*2.9-AJ10*P10*3.5 -> 9525502.4 | BN10: =IF(BM10-BI10-BK10-BH10<0,0,BM10-BK10-BI10-BH10) -> 0 | BO10: =ROUND(IF(BN10<=5000000,BN10*5%,IF(AND(BN10>5000000,BN10<=10000000),BN10*10%-250000,IF(AND(BN10>10000000,BN10<=18000000),BN10*15%-750000,IF(AND(BN10>18000000,BN10<=32000000),BN10*20%-1650000,IF(AND(BN10>32000000,BN10<=52000000),BN10*25%-3250000,IF(AND(BN10>52000000,BN10<80000000),BN10*30%-585000,IF(BN10>80000000,BN10*35%-9850000))))))),0) -> 0 | BP10: 35000 | BR10: =AX10-BH10-BO10-BP10-BQ10 -> 10930831 | BS10: 106871378362
A11: =A10+1 -> 2 | B11: Hoàng Thị Huyền | C11: TT | D11: 208 | E11: 150 | F11: 66 | G11: 18 | H11: 38 | I11: 20 | Q11: 4267000 | R11: 1300000 | T11: 600000 | U11: 0 | V11: =IF((E11+F11)>=D11,U11,(E11+F11)*U11/D11) -> 0 | W11: 300000 | X11: =IF((E11+F11)>=160, W11, W11/D11*(E11+F11)) -> 300000 | Y11: 300000 | Z11: =IF((E11+F11)>=160,Y11, Y11/D11*(E11+F11)) -> 300000 | AB11: 0 | AC11: =IF((E11+F11)>=184,500000,0) -> 500000 | AD11: =G11*13000 -> 234000 | AE11: 0 | AH11: =V11+X11+Z11+AA11+AC11+AD11+AE11 -> 1334000 | AI11: =Q11+R11+T11 -> 6167000 | AJ11: =AI11/208 -> 29649.038 | AK11: =AJ11*(E11+F11*130%) -> 6991243.3 | AM11: =AJ11*H11*150% -> 1689995.2 | AN11: =AJ11*I11*150%*130% -> 1156312.5 | AO11: =+AJ11*J11*200% -> 0 | AP11: =AJ11*K11*200%*130% -> 0 | AQ11: =AJ11*L11*200%*150% -> 0 | AR11: =AJ11*M11*200%*150%*130% -> 0 | AS11: =N11*AJ11*300% -> 0 | AT11: =AJ11*O11*130%*300% -> 0 | AU11: =P11*AJ11*150%*300% -> 0 | AV11: =SUM(AM11:AU11) -> 2846307.7 | AX11: =AH11+AK11+AV11++AF11-AG11 -> 11171551 | AY11: =Q11+R11+T11 -> 6167000 | AZ11: =AY11*17.5% -> 1079225 | BA11: =AY11*3% -> 185010 | BB11: =AY11*1% -> 61670 | BC11: =AY11*2% -> 123340 | BD11: =AZ11+BA11+BB11+BC11 -> 1449245 | BE11: =AY11*8% -> 493360 | BF11: =AY11*1.5% -> 92505 | BG11: =AY11*1% -> 61670 | BH11: =BE11+BF11+BG11 -> 647535 | BI11: 11000001 | BK11: =BJ11*4400000 -> 0 | BL11: =V11+AB11+AD11 -> 234000 | BM11: =AX11-BL11-H11*0.5*AJ11-I11*0.95*AJ11-F11*0.3*AJ11-AJ11*J11-AJ11*K11*1.6-AJ11*L11*2-AJ11*M11*2.9-AJ11*N11*2-AJ11*O11*2.9-AJ11*P11*3.5 -> 9223836.5 | BN11: =IF(BM11-BI11-BK11-BH11<0,0,BM11-BK11-BI11-BH11) -> 0 | BO11: =ROUND(IF(BN11<=5000000,BN11*5%,IF(AND(BN11>5000000,BN11<=10000000),BN11*10%-250000,IF(AND(BN11>10000000,BN11<=18000000),BN11*15%-750000,IF(AND(BN11>18000000,BN11<=32000000),BN11*20%-1650000,IF(AND(BN11>32000000,BN11<=52000000),BN11*25%-3250000,IF(AND(BN11>52000000,BN11<80000000),BN11*30%-585000,IF(BN11>80000000,BN11*35%-9850000))))))),0) -> 0 | BP11: 35000 | BR11: =AX11-BH11-BO11-BP11 -> 10489016 | BS11: 103874058092
A12: =A11+1 -> 3 | B12: Phan Đức Toàn | C12: TP | D12: 208 | E12: 150 | F12: 66 | G12: 20 | H12: 47 | I12: 20 | Q12: 4267000 | R12: 800000 | T12: 600000 | U12: 0 | V12: =IF((E12+F12)>=D12,U12,(E12+F12)*U12/D12) -> 0 | W12: 300000 | X12: =IF((E12+F12)>=160, W12, W12/D12*(E12+F12)) -> 300000 | Y12: 300000 | Z12: =IF((E12+F12)>=160,Y12, Y12/D12*(E12+F12)) -> 300000 | AB12: 0 | AC12: =IF((E12+F12)>=184,500000,0) -> 500000 | AD12: =G12*13000 -> 260000 | AE12: 0 | AH12: =V12+X12+Z12+AA12+AC12+AD12+AE12 -> 1360000 | AI12: =Q12+R12+T12 -> 5667000 | AJ12: =AI12/208 -> 27245.192 | AK12: =AJ12*(E12+F12*130%) -> 6424416.3 | AM12: =AJ12*H12*150% -> 1920786.1 | AN12: =AJ12*I12*150%*130% -> 1062562.5 | AO12: =+AJ12*J12*200% -> 0 | AP12: =AJ12*K12*200%*130% -> 0 | AQ12: =AJ12*L12*200%*150% -> 0 | AR12: =AJ12*M12*200%*150%*130% -> 0 | AS12: =N12*AJ12*300% -> 0 | AT12: =AJ12*O12*130%*300% -> 0 | AU12: =P12*AJ12*150%*300% -> 0 | AV12: =SUM(AM12:AU12) -> 2983348.6 | AX12: =AH12+AK12+AV12++AF12-AG12 -> 10767765 | AY12: =Q12+R12+T12 -> 5667000 | AZ12: =AY12*17.5% -> 991725 | BA12: =AY12*3% -> 170010 | BB12: =AY12*1% -> 56670 | BC12: =AY12*2% -> 113340 | BD12: =AZ12+BA12+BB12+BC12 -> 1331745 | BE12: =AY12*8% -> 453360 | BF12: =AY12*1.5% -> 85005 | BG12: =AY12*1% -> 56670 | BH12: =BE12+BF12+BG12 -> 595035 | BI12: 11000000 | BK12: =BJ12*4400000 -> 0 | BL12: =V12+AB12+AD12 -> 260000 | BM12: =AX12-BL12-H12*0.5*AJ12-I12*0.95*AJ12-F12*0.3*AJ12-AJ12*J12-AJ12*K12*1.6-AJ12*L12*2-AJ12*M12*2.9-AJ12*N12*2-AJ12*O12*2.9-AJ12*P12*3.5 -> 8810389.4 | BN12: =IF(BM12-BI12-BK12-BH12<0,0,BM12-BK12-BI12-BH12) -> 0 | BO12: =ROUND(IF(BN12<=5000000,BN12*5%,IF(AND(BN12>5000000,BN12<=10000000),BN12*10%-250000,IF(AND(BN12>10000000,BN12<=18000000),BN12*15%-750000,IF(AND(BN12>18000000,BN12<=32000000),BN12*20%-1650000,IF(AND(BN12>32000000,BN12<=52000000),BN12*25%-3250000,IF(AND(BN12>52000000,BN12<80000000),BN12*30%-585000,IF(BN12>80000000,BN12*35%-9850000))))))),0) -> 0 | BP12: 35000 | BR12: =AX12-BH12-BO12-BP12 -> 10137730 | BS12: 100874719381
A13: =A12+1 -> 4 | B13: Vũ Hồng Sơn | C13: TP | D13: 208 | E13: 144.5 | F13: 71.5 | G13: 20 | H13: 42.5 | I13: 21 | Q13: 4267000 | R13: 800000 | T13: 600000 | U13: 0 | V13: =IF((E13+F13)>=D13,U13,(E13+F13)*U13/D13) -> 0 | W13: 300000 | X13: =IF((E13+F13)>=160, W13, W13/D13*(E13+F13)) -> 300000 | Y13: 300000 | Z13: =IF((E13+F13)>=160,Y13, Y13/D13*(E13+F13)) -> 300000 | AB13: 0 | AC13: =IF((E13+F13)>=184,500000,0) -> 500000 | AD13: =G13*13000 -> 260000 | AE13: 0 | AH13: =V13+X13+Z13+AA13+AC13+AD13+AE13 -> 1360000 | AI13: =Q13+R13+T13 -> 5667000 | AJ13: =AI13/208 -> 27245.192 | AK13: =AJ13*(E13+F13*130%) -> 6469370.9 | AM13: =AJ13*H13*150% -> 1736881 | AN13: =AJ13*I13*150%*130% -> 1115690.6 | AO13: =+AJ13*J13*200% -> 0 | AP13: =AJ13*K13*200%*130% -> 0 | AQ13: =AJ13*L13*200%*150% -> 0 | AR13: =AJ13*M13*200%*150%*130% -> 0 | AS13: =N13*AJ13*300% -> 0 | AT13: =AJ13*O13*130%*300% -> 0 | AU13: =P13*AJ13*150%*300% -> 0 | AV13: =SUM(AM13:AU13) -> 2852571.6 | AX13: =AH13+AK13+AV13++AF13-AG13 -> 10681943 | AY13: =Q13+R13+T13 -> 5667000 | AZ13: =AY13*17.5% -> 991725 | BA13: =AY13*3% -> 170010 | BB13: =AY13*1% -> 56670 | BC13: =AY13*2% -> 113340 | BD13: =AZ13+BA13+BB13+BC13 -> 1331745 | BE13: =AY13*8% -> 453360 | BF13: =AY13*1.5% -> 85005 | BG13: =AY13*1% -> 56670 | BH13: =BE13+BF13+BG13 -> 595035 | BI13: 11000000 | BK13: =BJ13*4400000 -> 0 | BL13: =V13+AB13+AD13 -> 260000 | BM13: =AX13-BL13-H13*0.5*AJ13-I13*0.95*AJ13-F13*0.3*AJ13-AJ13*J13-AJ13*K13*1.6-AJ13*L13*2-AJ13*M13*2.9-AJ13*N13*2-AJ13*O13*2.9-AJ13*P13*3.5 -> 8715031.2 | BN13: =IF(BM13-BI13-BK13-BH13<0,0,BM13-BK13-BI13-BH13) -> 0 | BO13: =ROUND(IF(BN13<=5000000,BN13*5%,IF(AND(BN13>5000000,BN13<=10000000),BN13*10%-250000,IF(AND(BN13>10000000,BN13<=18000000),BN13*15%-750000,IF(AND(BN13>18000000,BN13<=32000000),BN13*20%-1650000,IF(AND(BN13>32000000,BN13<=52000000),BN13*25%-3250000,IF(AND(BN13>52000000,BN13<80000000),BN13*30%-585000,IF(BN13>80000000,BN13*35%-9850000))))))),0) -> 0 | BP13: 35000 | BR13: =AX13-BH13-BO13-BP13 -> 10051908 | BS13: 101874719378
A14: =A13+1 -> 5 | B14: Võ Thị Hồng Loan | C14: TP | D14: 208 | E14: 150 | F14: 66 | G14: 18 | H14: 40 | I14: 18 | Q14: 4267000 | R14: 800000 | T14: 600000 | U14: 0 | V14: =IF((E14+F14)>=D14,U14,(E14+F14)*U14/D14) -> 0 | W14: 300000 | X14: =IF((E14+F14)>=160, W14, W14/D14*(E14+F14)) -> 300000 | Y14: 300000 | Z14: =IF((E14+F14)>=160,Y14, Y14/D14*(E14+F14)) -> 300000 | AB14: 0 | AC14: =IF((E14+F14)>=184,500000,0) -> 500000 | AD14: =G14*13000 -> 234000 | AE14: 0 | AH14: =V14+X14+Z14+AA14+AC14+AD14+AE14 -> 1334000 | AI14: =Q14+R14+T14 -> 5667000 | AJ14: =AI14/208 -> 27245.192 | AK14: =AJ14*(E14+F14*130%) -> 6424416.3 | AM14: =AJ14*H14*150% -> 1634711.5 | AN14: =AJ14*I14*150%*130% -> 956306.25 | AO14: =+AJ14*J14*200% -> 0 | AP14: =AJ14*K14*200%*130% -> 0 | AQ14: =AJ14*L14*200%*150% -> 0 | AR14: =AJ14*M14*200%*150%*130% -> 0 | AS14: =N14*AJ14*300% -> 0 | AT14: =AJ14*O14*130%*300% -> 0 | AU14: =P14*AJ14*150%*300% -> 0 | AV14: =SUM(AM14:AU14) -> 2591017.8 | AX14: =AH14+AK14+AV14++AF14-AG14 -> 10349434 | AY14: =Q14+R14+T14 -> 5667000 | AZ14: =AY14*17.5% -> 991725 | BA14: =AY14*3% -> 170010 | BB14: =AY14*1% -> 56670 | BC14: =AY14*2% -> 113340 | BD14: =AZ14+BA14+BB14+BC14 -> 1331745 | BE14: =AY14*8% -> 453360 | BF14: =AY14*1.5% -> 85005 | BG14: =AY14*1% -> 56670 | BH14: =BE14+BF14+BG14 -> 595035 | BI14: 11000000 | BK14: =BJ14*4400000 -> 0 | BL14: =V14+AB14+AD14 -> 234000 | BM14: =AX14-BL14-H14*0.5*AJ14-I14*0.95*AJ14-F14*0.3*AJ14-AJ14*J14-AJ14*K14*1.6-AJ14*L14*2-AJ14*M14*2.9-AJ14*N14*2-AJ14*O14*2.9-AJ14*P14*3.5 -> 8565182.7 | BN14: =IF(BM14-BI14-BK14-BH14<0,0,BM14-BK14-BI14-BH14) -> 0 | BO14: =ROUND(IF(BN14<=5000000,BN14*5%,IF(AND(BN14>5000000,BN14<=10000000),BN14*10%-250000,IF(AND(BN14>10000000,BN14<=18000000),BN14*15%-750000,IF(AND(BN14>18000000,BN14<=32000000),BN14*20%-1650000,IF(AND(BN14>32000000,BN14<=52000000),BN14*25%-3250000,IF(AND(BN14>52000000,BN14<80000000),BN14*30%-585000,IF(BN14>80000000,BN14*35%-9850000))))))),0) -> 0 | BP14: 35000 | BR14: =AX14-BH14-BO14-BP14 -> 9719399.1 | BS14: 109878078907
A15: =A14+1 -> 6 | B15: Nguyễn Thị Huyền | C15: TP | D15: 208 | E15: 150 | F15: 66 | G15: 19 | H15: 42 | I15: 18 | Q15: 4267000 | R15: 800000 | T15: 300000 | U15: 0 | V15: =IF((E15+F15)>=D15,U15,(E15+F15)*U15/D15) -> 0 | W15: 300000 | X15: =IF((E15+F15)>=160, W15, W15/D15*(E15+F15)) -> 300000 | Y15: 300000 | Z15: =IF((E15+F15)>=160,Y15, Y15/D15*(E15+F15)) -> 300000 | AB15: 0 | AC15: =IF((E15+F15)>=184,500000,0) -> 500000 | AD15: =G15*13000 -> 247000 | AE15: 0 | AH15: =V15+X15+Z15+AA15+AC15+AD15+AE15 -> 1347000 | AI15: =Q15+R15+T15 -> 5367000 | AJ15: =AI15/208 -> 25802.885 | AK15: =AJ15*(E15+F15*130%) -> 6084320.2 | AM15: =AJ15*H15*150% -> 1625581.7 | AN15: =AJ15*I15*150%*130% -> 905681.25 | AO15: =+AJ15*J15*200% -> 0 | AP15: =AJ15*K15*200%*130% -> 0 | AQ15: =AJ15*L15*200%*150% -> 0 | AR15: =AJ15*M15*200%*150%*130% -> 0 | AS15: =N15*AJ15*300% -> 0 | AT15: =AJ15*O15*130%*300% -> 0 | AU15: =P15*AJ15*150%*300% -> 0 | AV15: =SUM(AM15:AU15) -> 2531263 | AX15: =AH15+AK15+AV15++AF15-AG15 -> 9962583.2 | AY15: =Q15+R15+T15 -> 5367000 | AZ15: =AY15*17.5% -> 939225 | BA15: =AY15*3% -> 161010 | BB15: =AY15*1% -> 53670 | BC15: =AY15*2% -> 107340 | BD15: =AZ15+BA15+BB15+BC15 -> 1261245 | BE15: =AY15*8% -> 429360 | BF15: =AY15*1.5% -> 80505 | BG15: =AY15*1% -> 53670 | BH15: =BE15+BF15+BG15 -> 563535 | BI15: 11000000 | BK15: =BJ15*4400000 -> 0 | BL15: =V15+AB15+AD15 -> 247000 | BM15: =AX15-BL15-H15*0.5*AJ15-I15*0.95*AJ15-F15*0.3*AJ15-AJ15*J15-AJ15*K15*1.6-AJ15*L15*2-AJ15*M15*2.9-AJ15*N15*2-AJ15*O15*2.9-AJ15*P15*3.5 -> 8221596.2 | BN15: =IF(BM15-BI15-BK15-BH15<0,0,BM15-BK15-BI15-BH15) -> 0 | BO15: =ROUND(IF(BN15<=5000000,BN15*5%,IF(AND(BN15>5000000,BN15<=10000000),BN15*10%-250000,IF(AND(BN15>10000000,BN15<=18000000),BN15*15%-750000,IF(AND(BN15>18000000,BN15<=32000000),BN15*20%-1650000,IF(AND(BN15>32000000,BN15<=52000000),BN15*25%-3250000,IF(AND(BN15>52000000,BN15<80000000),BN15*30%-585000,IF(BN15>80000000,BN15*35%-9850000))))))),0) -> 0 | BP15: 35000 | BR15: =AX15-BH15-BO15-BP15 -> 9364048.2 | BS15: 105871206794
A16: =A15+1 -> 7 | B16: Mai Văn Sáng | C16: CN | D16: 208 | E16: 120.5 | F16: 71.5 | G16: 17 | H16: 33 | I16: 18 | Q16: 4267000 | R16: 300000 | T16: 600000 | U16: 0 | V16: =IF((E16+F16)>=D16,U16,(E16+F16)*U16/D16) -> 0 | W16: 300000 | X16: =IF((E16+F16)>=160, W16, W16/D16*(E16+F16)) -> 300000 | Y16: 300000 | Z16: =IF((E16+F16)>=160,Y16, Y16/D16*(E16+F16)) -> 300000 | AB16: 0 | AC16: =IF((E16+F16)>=184,500000,0) -> 500000 | AD16: =G16*13000 -> 221000 | AE16: 0 | AH16: =V16+X16+Z16+AA16+AC16+AD16+AE16 -> 1321000 | AI16: =Q16+R16+T16 -> 5167000 | AJ16: =AI16/208 -> 24841.346 | AK16: =AJ16*(E16+F16*130%) -> 5302385.3 | AM16: =AJ16*H16*150% -> 1229646.6 | AN16: =AJ16*I16*150%*130% -> 871931.25 | AO16: =+AJ16*J16*200% -> 0 | AP16: =AJ16*K16*200%*130% -> 0 | AQ16: =AJ16*L16*200%*150% -> 0 | AR16: =AJ16*M16*200%*150%*130% -> 0 | AS16: =N16*AJ16*300% -> 0 | AT16: =AJ16*O16*130%*300% -> 0 | AU16: =P16*AJ16*150%*300% -> 0 | AV16: =SUM(AM16:AU16) -> 2101577.9 | AX16: =AH16+AK16+AV16++AF16-AG16 -> 8724963.2 | AY16: =Q16+R16+T16 -> 5167000 | AZ16: =AY16*17.5% -> 904225 | BA16: =AY16*3% -> 155010 | BB16: =AY16*1% -> 51670 | BC16: =AY16*2% -> 103340 | BD16: =AZ16+BA16+BB16+BC16 -> 1214245 | BE16: =AY16*8% -> 413360 | BF16: =AY16*1.5% -> 77505 | BG16: =AY16*1% -> 51670 | BH16: =BE16+BF16+BG16 -> 542535 | BI16: 11000000 | BK16: =BJ16*4400000 -> 0 | BL16: =V16+AB16+AD16 -> 221000 | BM16: =AX16-BL16-H16*0.5*AJ16-I16*0.95*AJ16-F16*0.3*AJ16-AJ16*J16-AJ16*K16*1.6-AJ16*L16*2-AJ16*M16*2.9-AJ16*N16*2-AJ16*O16*2.9-AJ16*P16*3.5 -> 7136447.1 | BN16: =IF(BM16-BI16-BK16-BH16<0,0,BM16-BK16-BI16-BH16) -> 0 | BO16: =ROUND(IF(BN16<=5000000,BN16*5%,IF(AND(BN16>5000000,BN16<=10000000),BN16*10%-250000,IF(AND(BN16>10000000,BN16<=18000000),BN16*15%-750000,IF(AND(BN16>18000000,BN16<=32000000),BN16*20%-1650000,IF(AND(BN16>32000000,BN16<=52000000),BN16*25%-3250000,IF(AND(BN16>52000000,BN16<80000000),BN16*30%-585000,IF(BN16>80000000,BN16*35%-9850000))))))),0) -> 0 | BP16: 35000 | BR16: =AX16-BH16-BO16-BP16 -> 8147428.2 | BS16: 101876323665
A17: =A16+1 -> 8 | B17: Hoàng Lê Anh | C17: CN | D17: 208 | E17: 150 | F17: 66 | G17: 18 | H17: 39 | I17: 20.5 | Q17: 4267000 | R17: 300000 | T17: 300000 | U17: 0 | V17: =IF((E17+F17)>=D17,U17,(E17+F17)*U17/D17) -> 0 | W17: 300000 | X17: =IF((E17+F17)>=160, W17, W17/D17*(E17+F17)) -> 300000 | Y17: 300000 | Z17: =IF((E17+F17)>=160,Y17, Y17/D17*(E17+F17)) -> 300000 | AB17: 0 | AC17: =IF((E17+F17)>=184,500000,0) -> 500000 | AD17: =G17*13000 -> 234000 | AE17: 100000 | AH17: =V17+X17+Z17+AA17+AC17+AD17+AE17 -> 1434000 | AI17: =Q17+R17+T17 -> 4867000 | AJ17: =AI17/208 -> 23399.038 | AK17: =AJ17*(E17+F17*130%) -> 5517493.3 | AM17: =AJ17*H17*150% -> 1368843.8 | AN17: =AJ17*I17*150%*130% -> 935376.56 | AO17: =+AJ17*J17*200% -> 0 | AP17: =AJ17*K17*200%*130% -> 0 | AQ17: =AJ17*L17*200%*150% -> 0 | AR17: =AJ17*M17*200%*150%*130% -> 0 | AS17: =N17*AJ17*300% -> 0 | AT17: =AJ17*O17*130%*300% -> 0 | AU17: =P17*AJ17*150%*300% -> 0 | AV17: =SUM(AM17:AU17) -> 2304220.3 | AX17: =AH17+AK17+AV17++AF17-AG17 -> 9255713.6 | AY17: =Q17+R17+T17 -> 4867000 | AZ17: =AY17*17.5% -> 851725 | BA17: =AY17*3% -> 146010 | BB17: =AY17*1% -> 48670 | BC17: =AY17*2% -> 97340 | BD17: =AZ17+BA17+BB17+BC17 -> 1143745 | BE17: =AY17*8% -> 389360 | BF17: =AY17*1.5% -> 73005 | BG17: =AY17*1% -> 48670 | BH17: =BE17+BF17+BG17 -> 511035 | BI17: 11000000 | BK17: =BJ17*4400000 -> 0 | BL17: =V17+AB17+AD17 -> 234000 | BM17: =AX17-BL17-H17*0.5*AJ17-I17*0.95*AJ17-F17*0.3*AJ17-AJ17*J17-AJ17*K17*1.6-AJ17*L17*2-AJ17*M17*2.9-AJ17*N17*2-AJ17*O17*2.9-AJ17*P17*3.5 -> 7646435.1 | BN17: =IF(BM17-BI17-BK17-BH17<0,0,BM17-BK17-BI17-BH17) -> 0 | BO17: =ROUND(IF(BN17<=5000000,BN17*5%,IF(AND(BN17>5000000,BN17<=10000000),BN17*10%-250000,IF(AND(BN17>10000000,BN17<=18000000),BN17*15%-750000,IF(AND(BN17>18000000,BN17<=32000000),BN17*20%-1650000,IF(AND(BN17>32000000,BN17<=52000000),BN17*25%-3250000,IF(AND(BN17>52000000,BN17<80000000),BN17*30%-585000,IF(BN17>80000000,BN17*35%-9850000))))))),0) -> 0 | BP17: 35000 | BR17: =AX17-BH17-BO17-BP17 -> 8709678.6 | BS17: 105875872100
A18: =A17+1 -> 9 | B18: Đinh Thị Hương | C18: CN | D18: 208 | E18: 136 | F18: 0 | G18: 0 | H18: 0 | I18: 0 | Q18: 4267000 | R18: 300000 | T18: 600000 | U18: 0 | V18: =IF((E18+F18)>=D18,U18,(E18+F18)*U18/D18) -> 0 | W18: 300000 | X18: =IF((E18+F18)>=160, W18, W18/D18*(E18+F18)) -> 196153.85 | Y18: 300000 | Z18: =IF((E18+F18)>=160,Y18, Y18/D18*(E18+F18)) -> 196153.85 | AB18: 0 | AC18: =IF((E18+F18)>=184,500000,0) -> 0 | AD18: =G18*13000 -> 0 | AE18: 0 | AH18: =V18+X18+Z18+AA18+AC18+AD18+AE18 -> 392307.69 | AI18: =Q18+R18+T18 -> 5167000 | AJ18: =AI18/208 -> 24841.346 | AK18: =AJ18*(E18+F18*130%) -> 3378423.1 | AM18: =AJ18*H18*150% -> 0 | AN18: =AJ18*I18*150%*130% -> 0 | AO18: =+AJ18*J18*200% -> 0 | AP18: =AJ18*K18*200%*130% -> 0 | AQ18: =AJ18*L18*200%*150% -> 0 | AR18: =AJ18*M18*200%*150%*130% -> 0 | AS18: =N18*AJ18*300% -> 0 | AT18: =AJ18*O18*130%*300% -> 0 | AU18: =P18*AJ18*150%*300% -> 0 | AV18: =SUM(AM18:AU18) -> 0 | AX18: =AH18+AK18+AV18++AF18-AG18 -> 3770730.8 | AY18: =Q18+R18+T18 -> 5167000 | AZ18: =AY18*17.5% -> 904225 | BA18: =AY18*3% -> 155010 | BB18: =AY18*1% -> 51670 | BC18: =AY18*2% -> 103340 | BD18: =AZ18+BA18+BB18+BC18 -> 1214245 | BE18: =AY18*8% -> 413360 | BF18: =AY18*1.5% -> 77505 | BG18: =AY18*1% -> 51670 | BH18: =BE18+BF18+BG18 -> 542535 | BI18: 11000000 | BK18: =BJ18*4400000 -> 0 | BL18: =V18+AB18+AD18 -> 0 | BM18: =AX18-BL18-H18*0.5*AJ18-I18*0.95*AJ18-F18*0.3*AJ18-AJ18*J18-AJ18*K18*1.6-AJ18*L18*2-AJ18*M18*2.9-AJ18*N18*2-AJ18*O18*2.9-AJ18*P18*3.5 -> 3770730.8 | BN18: =IF(BM18-BI18-BK18-BH18<0,0,BM18-BK18-BI18-BH18) -> 0 | BO18: =ROUND(IF(BN18<=5000000,BN18*5%,IF(AND(BN18>5000000,BN18<=10000000),BN18*10%-250000,IF(AND(BN18>10000000,BN18<=18000000),BN18*15%-750000,IF(AND(BN18>18000000,BN18<=32000000),BN18*20%-1650000,IF(AND(BN18>32000000,BN18<=52000000),BN18*25%-3250000,IF(AND(BN18>52000000,BN18<80000000),BN18*30%-585000,IF(BN18>80000000,BN18*35%-9850000))))))),0) -> 0 | BR18: =AX18-BH18-BO18-BP18 -> 3228195.8 | BS18: 105875872100
A19: =A18+1 -> 10 | B19: Đinh Việt Anh | C19: CN | D19: 208 | E19: 142 | F19: 66 | G19: 18 | H19: 40.5 | I19: 18 | Q19: 4064000 | R19: 0 | T19: 0 | U19: 0 | V19: =IF((E19+F19)>=D19,U19,(E19+F19)*U19/D19) -> 0 | W19: 300000 | X19: =IF((E19+F19)>=160, W19, W19/D19*(E19+F19)) -> 300000 | Y19: 300000 | Z19: =IF((E19+F19)>=160,Y19, Y19/D19*(E19+F19)) -> 300000 | AB19: 0 | AC19: =IF((E19+F19)>=184,500000,0) -> 500000 | AD19: =G19*13000 -> 234000 | AE19: 0 | AH19: =V19+X19+Z19+AA19+AC19+AD19+AE19 -> 1334000 | AI19: =Q19+R19+T19 -> 4064000 | AJ19: =AI19/208 -> 19538.462 | AK19: =AJ19*(E19+F19*130%) -> 4450861.5 | AM19: =AJ19*H19*150% -> 1186961.5 | AN19: =AJ19*I19*150%*130% -> 685800 | AO19: =+AJ19*J19*200% -> 0 | AP19: =AJ19*K19*200%*130% -> 0 | AQ19: =AJ19*L19*200%*150% -> 0 | AR19: =AJ19*M19*200%*150%*130% -> 0 | AS19: =N19*AJ19*300% -> 0 | AT19: =AJ19*O19*130%*300% -> 0 | AU19: =P19*AJ19*150%*300% -> 0 | AV19: =SUM(AM19:AU19) -> 1872761.5 | AX19: =AH19+AK19+AV19++AF19-AG19 -> 7657623.1 | AY19: =Q19+R19+T19 -> 4064000 | AZ19: =AY19*17.5% -> 711200 | BA19: =AY19*3% -> 121920 | BB19: =AY19*1% -> 40640 | BC19: =AY19*2% -> 81280 | BD19: =AZ19+BA19+BB19+BC19 -> 955040 | BE19: =AY19*8% -> 325120 | BF19: =AY19*1.5% -> 60960 | BG19: =AY19*1% -> 40640 | BH19: =BE19+BF19+BG19 -> 426720 | BI19: 11000000 | BK19: =BJ19*4400000 -> 0 | BL19: =V19+AB19+AD19 -> 234000 | BM19: =AX19-BL19-H19*0.5*AJ19-I19*0.95*AJ19-F19*0.3*AJ19-AJ19*J19-AJ19*K19*1.6-AJ19*L19*2-AJ19*M19*2.9-AJ19*N19*2-AJ19*O19*2.9-AJ19*P19*3.5 -> 6307000 | BN19: =IF(BM19-BI19-BK19-BH19<0,0,BM19-BK19-BI19-BH19) -> 0 | BO19: =ROUND(IF(BN19<=5000000,BN19*5%,IF(AND(BN19>5000000,BN19<=10000000),BN19*10%-250000,IF(AND(BN19>10000000,BN19<=18000000),BN19*15%-750000,IF(AND(BN19>18000000,BN19<=32000000),BN19*20%-1650000,IF(AND(BN19>32000000,BN19<=52000000),BN19*25%-3250000,IF(AND(BN19>52000000,BN19<80000000),BN19*30%-585000,IF(BN19>80000000,BN19*35%-9850000))))))),0) -> 0 | BP19: 35000 | BR19: =AX19-BH19-BO19-BP19 -> 7195903.1 | BS19: 104879687511
A20: =A19+1 -> 11 | B20: Phạm Văn Sỹ | C20: CN | D20: 208 | E20: 150 | F20: 66 | G20: 19 | H20: 39.5 | I20: 18 | Q20: 4064000 | R20: 0 | T20: 0 | U20: 0 | V20: =IF((E20+F20)>=D20,U20,(E20+F20)*U20/D20) -> 0 | W20: 300000 | X20: =IF((E20+F20)>=160, W20, W20/D20*(E20+F20)) -> 300000 | Y20: 300000 | Z20: =IF((E20+F20)>=160,Y20, Y20/D20*(E20+F20)) -> 300000 | AB20: 0 | AC20: =IF((E20+F20)>=184,500000,0) -> 500000 | AD20: =G20*13000 -> 247000 | AE20: 100000 | AH20: =V20+X20+Z20+AA20+AC20+AD20+AE20 -> 1447000 | AI20: =Q20+R20+T20 -> 4064000 | AJ20: =AI20/208 -> 19538.462 | AK20: =AJ20*(E20+F20*130%) -> 4607169.2 | AM20: =AJ20*H20*150% -> 1157653.8 | AN20: =AJ20*I20*150%*130% -> 685800 | AO20: =+AJ20*J20*200% -> 0 | AP20: =AJ20*K20*200%*130% -> 0 | AQ20: =AJ20*L20*200%*150% -> 0 | AR20: =AJ20*M20*200%*150%*130% -> 0 | AS20: =N20*AJ20*300% -> 0 | AT20: =AJ20*O20*130%*300% -> 0 | AU20: =P20*AJ20*150%*300% -> 0 | AV20: =SUM(AM20:AU20) -> 1843453.8 | AX20: =AH20+AK20+AV20++AF20-AG20 -> 7897623.1 | AY20: =Q20+R20+T20 -> 4064000 | AZ20: =AY20*17.5% -> 711200 | BA20: =AY20*3% -> 121920 | BB20: =AY20*1% -> 40640 | BC20: =AY20*2% -> 81280 | BD20: =AZ20+BA20+BB20+BC20 -> 955040 | BE20: =AY20*8% -> 325120 | BF20: =AY20*1.5% -> 60960 | BG20: =AY20*1% -> 40640 | BH20: =BE20+BF20+BG20 -> 426720 | BI20: 11000000 | BK20: =BJ20*4400000 -> 0 | BL20: =V20+AB20+AD20 -> 247000 | BM20: =AX20-BL20-H20*0.5*AJ20-I20*0.95*AJ20-F20*0.3*AJ20-AJ20*J20-AJ20*K20*1.6-AJ20*L20*2-AJ20*M20*2.9-AJ20*N20*2-AJ20*O20*2.9-AJ20*P20*3.5 -> 6543769.2 | BN20: =IF(BM20-BI20-BK20-BH20<0,0,BM20-BK20-BI20-BH20) -> 0 | BO20: =ROUND(IF(BN20<=5000000,BN20*5%,IF(AND(BN20>5000000,BN20<=10000000),BN20*10%-250000,IF(AND(BN20>10000000,BN20<=18000000),BN20*15%-750000,IF(AND(BN20>18000000,BN20<=32000000),BN20*20%-1650000,IF(AND(BN20>32000000,BN20<=52000000),BN20*25%-3250000,IF(AND(BN20>52000000,BN20<80000000),BN20*30%-585000,IF(BN20>80000000,BN20*35%-9850000))))))),0) -> 0 | BP20: 0 | BR20: =AX20-BH20-BO20-BP20 -> 7470903.1 | BS20: 104879687511
A21: =A20+1 -> 12 | B21: Trần Thị Hoa | C21: CN | D21: 208 | E21: 144.5 | F21: 71.5 | G21: 19 | H21: 37.5 | I21: 19.5 | Q21: 4064000 | R21: 0 | T21: 0 | U21: 0 | V21: =IF((E21+F21)>=D21,U21,(E21+F21)*U21/D21) -> 0 | W21: 300000 | X21: =IF((E21+F21)>=160, W21, W21/D21*(E21+F21)) -> 300000 | Y21: 300000 | Z21: =IF((E21+F21)>=160,Y21, Y21/D21*(E21+F21)) -> 300000 | AB21: 0 | AC21: =IF((E21+F21)>=184,500000,0) -> 500000 | AD21: =G21*13000 -> 247000 | AE21: 0 | AH21: =V21+X21+Z21+AA21+AC21+AD21+AE21 -> 1347000 | AI21: =Q21+R21+T21 -> 4064000 | AJ21: =AI21/208 -> 19538.462 | AK21: =AJ21*(E21+F21*130%) -> 4639407.7 | AM21: =AJ21*H21*150% -> 1099038.5 | AN21: =AJ21*I21*150%*130% -> 742950 | AO21: =+AJ21*J21*200% -> 0 | AP21: =AJ21*K21*200%*130% -> 0 | AQ21: =AJ21*L21*200%*150% -> 0 | AR21: =AJ21*M21*200%*150%*130% -> 0 | AS21: =N21*AJ21*300% -> 0 | AT21: =AJ21*O21*130%*300% -> 0 | AU21: =P21*AJ21*150%*300% -> 0 | AV21: =SUM(AM21:AU21) -> 1841988.5 | AX21: =AH21+AK21+AV21++AF21-AG21 -> 7828396.2 | AY21: =Q21+R21+T21 -> 4064000 | AZ21: =AY21*17.5% -> 711200 | BA21: =AY21*3% -> 121920 | BB21: =AY21*1% -> 40640 | BC21: =AY21*2% -> 81280 | BD21: =AZ21+BA21+BB21+BC21 -> 955040 | BE21: =AY21*8% -> 325120 | BF21: =AY21*1.5% -> 60960 | BG21: =AY21*1% -> 40640 | BH21: =BE21+BF21+BG21 -> 426720 | BI21: 11000000 | BK21: =BJ21*4400000 -> 0 | BL21: =V21+AB21+AD21 -> 247000 | BM21: =AX21-BL21-H21*0.5*AJ21-I21*0.95*AJ21-F21*0.3*AJ21-AJ21*J21-AJ21*K21*1.6-AJ21*L21*2-AJ21*M21*2.9-AJ21*N21*2-AJ21*O21*2.9-AJ21*P21*3.5 -> 6434000 | BN21: =IF(BM21-BI21-BK21-BH21<0,0,BM21-BK21-BI21-BH21) -> 0 | BO21: =ROUND(IF(BN21<=5000000,BN21*5%,IF(AND(BN21>5000000,BN21<=10000000),BN21*10%-250000,IF(AND(BN21>10000000,BN21<=18000000),BN21*15%-750000,IF(AND(BN21>18000000,BN21<=32000000),BN21*20%-1650000,IF(AND(BN21>32000000,BN21<=52000000),BN21*25%-3250000,IF(AND(BN21>52000000,BN21<80000000),BN21*30%-585000,IF(BN21>80000000,BN21*35%-9850000))))))),0) -> 0 | BP21: 35000 | BR21: =AX21-BH21-BO21-BP21 -> 7366676.2 | BS21: 104879687511
A22: =A21+1 -> 13 | B22: Hoàng Thị Tuyết Nhung | C22: CN | D22: 208 | E22: 161 | F22: 55 | G22: 19 | H22: 42 | I22: 15 | Q22: 4064000 | R22: 0 | T22: 0 | U22: 0 | V22: =IF((E22+F22)>=D22,U22,(E22+F22)*U22/D22) -> 0 | W22: 300000 | X22: =IF((E22+F22)>=160, W22, W22/D22*(E22+F22)) -> 300000 | Y22: 300000 | Z22: =IF((E22+F22)>=160,Y22, Y22/D22*(E22+F22)) -> 300000 | AB22: 0 | AC22: =IF((E22+F22)>=184,500000,0) -> 500000 | AD22: =G22*13000 -> 247000 | AE22: 0 | AH22: =V22+X22+Z22+AA22+AC22+AD22+AE22 -> 1347000 | AI22: =Q22+R22+T22 -> 4064000 | AJ22: =AI22/208 -> 19538.462 | AK22: =AJ22*(E22+F22*130%) -> 4542692.3 | AM22: =AJ22*H22*150% -> 1230923.1 | AN22: =AJ22*I22*150%*130% -> 571500 | AO22: =+AJ22*J22*200% -> 0 | AP22: =AJ22*K22*200%*130% -> 0 | AQ22: =AJ22*L22*200%*150% -> 0 | AR22: =AJ22*M22*200%*150%*130% -> 0 | AS22: =N22*AJ22*300% -> 0 | AT22: =AJ22*O22*130%*300% -> 0 | AU22: =P22*AJ22*150%*300% -> 0 | AV22: =SUM(AM22:AU22) -> 1802423.1 | AX22: =AH22+AK22+AV22++AF22-AG22 -> 7692115.4 | AY22: =Q22+R22+T22 -> 4064000 | AZ22: =AY22*17.5% -> 711200 | BA22: =AY22*3% -> 121920 | BB22: =AY22*1% -> 40640 | BC22: =AY22*2% -> 81280 | BD22: =AZ22+BA22+BB22+BC22 -> 955040 | BE22: =AY22*8% -> 325120 | BF22: =AY22*1.5% -> 60960 | BG22: =AY22*1% -> 40640 | BH22: =BE22+BF22+BG22 -> 426720 | BI22: 11000000 | BK22: =BJ22*4400000 -> 0 | BL22: =V22+AB22+AD22 -> 247000 | BM22: =AX22-BL22-H22*0.5*AJ22-I22*0.95*AJ22-F22*0.3*AJ22-AJ22*J22-AJ22*K22*1.6-AJ22*L22*2-AJ22*M22*2.9-AJ22*N22*2-AJ22*O22*2.9-AJ22*P22*3.5 -> 6434000 | BN22: =IF(BM22-BI22-BK22-BH22<0,0,BM22-BK22-BI22-BH22) -> 0 | BO22: =ROUND(IF(BN22<=5000000,BN22*5%,IF(AND(BN22>5000000,BN22<=10000000),BN22*10%-250000,IF(AND(BN22>10000000,BN22<=18000000),BN22*15%-750000,IF(AND(BN22>18000000,BN22<=32000000),BN22*20%-1650000,IF(AND(BN22>32000000,BN22<=52000000),BN22*25%-3250000,IF(AND(BN22>52000000,BN22<80000000),BN22*30%-585000,IF(BN22>80000000,BN22*35%-9850000))))))),0) -> 0 | BP22: 35000 | BR22: =AX22-BH22-BO22-BP22 -> 7230395.4 | BS22: 104879687511
A23: =A22+1 -> 14 | B23: Hà Đăng Cao | C23: CN | D23: 208 | E23: 144.5 | F23: 71.5 | G23: 17 | H23: 31.5 | I23: 19.5 | Q23: 4064000 | R23: 0 | T23: 0 | U23: 0 | V23: =IF((E23+F23)>=D23,U23,(E23+F23)*U23/D23) -> 0 | W23: 300000 | X23: =IF((E23+F23)>=160, W23, W23/D23*(E23+F23)) -> 300000 | Y23: 300000 | Z23: =IF((E23+F23)>=160,Y23, Y23/D23*(E23+F23)) -> 300000 | AB23: 0 | AC23: =IF((E23+F23)>=184,500000,0) -> 500000 | AD23: =G23*13000 -> 221000 | AE23: 0 | AH23: =V23+X23+Z23+AA23+AC23+AD23+AE23 -> 1321000 | AI23: =Q23+R23+T23 -> 4064000 | AJ23: =AI23/208 -> 19538.462 | AK23: =AJ23*(E23+F23*130%) -> 4639407.7 | AM23: =AJ23*H23*150% -> 923192.31 | AN23: =AJ23*I23*150%*130% -> 742950 | AO23: =+AJ23*J23*200% -> 0 | AP23: =AJ23*K23*200%*130% -> 0 | AQ23: =AJ23*L23*200%*150% -> 0 | AR23: =AJ23*M23*200%*150%*130% -> 0 | AS23: =N23*AJ23*300% -> 0 | AT23: =AJ23*O23*130%*300% -> 0 | AU23: =P23*AJ23*150%*300% -> 0 | AV23: =SUM(AM23:AU23) -> 1666142.3 | AX23: =AH23+AK23+AV23++AF23-AG23 -> 7626550 | AY23: =Q23+R23+T23 -> 4064000 | AZ23: =AY23*17.5% -> 711200 | BA23: =AY23*3% -> 121920 | BB23: =AY23*1% -> 40640 | BC23: =AY23*2% -> 81280 | BD23: =AZ23+BA23+BB23+BC23 -> 955040 | BE23: =AY23*8% -> 325120 | BF23: =AY23*1.5% -> 60960 | BG23: =AY23*1% -> 40640 | BH23: =BE23+BF23+BG23 -> 426720 | BI23: 11000000 | BK23: =BJ23*4400000 -> 0 | BL23: =V23+AB23+AD23 -> 221000 | BM23: =AX23-BL23-H23*0.5*AJ23-I23*0.95*AJ23-F23*0.3*AJ23-AJ23*J23-AJ23*K23*1.6-AJ23*L23*2-AJ23*M23*2.9-AJ23*N23*2-AJ23*O23*2.9-AJ23*P23*3.5 -> 6316769.2 | BN23: =IF(BM23-BI23-BK23-BH23<0,0,BM23-BK23-BI23-BH23) -> 0 | BO23: =ROUND(IF(BN23<=5000000,BN23*5%,IF(AND(BN23>5000000,BN23<=10000000),BN23*10%-250000,IF(AND(BN23>10000000,BN23<=18000000),BN23*15%-750000,IF(AND(BN23>18000000,BN23<=32000000),BN23*20%-1650000,IF(AND(BN23>32000000,BN23<=52000000),BN23*25%-3250000,IF(AND(BN23>52000000,BN23<80000000),BN23*30%-585000,IF(BN23>80000000,BN23*35%-9850000))))))),0) -> 0 | BP23: 35000 | BR23: =AX23-BH23-BO23-BP23 -> 7164830 | BS23: 104879687511
A24: =A23+1 -> 15 | B24: Nguyễn Hồng Quân | C24: CN | D24: 208 | E24: 144.5 | F24: 71.5 | G24: 18 | H24: 34.5 | I24: 19.5 | Q24: 4064000 | R24: 0 | T24: 0 | U24: 0 | V24: =IF((E24+F24)>=D24,U24,(E24+F24)*U24/D24) -> 0 | W24: 300000 | X24: =IF((E24+F24)>=160, W24, W24/D24*(E24+F24)) -> 300000 | Y24: 300000 | Z24: =IF((E24+F24)>=160,Y24, Y24/D24*(E24+F24)) -> 300000 | AC24: =IF((E24+F24)>=184,500000,0) -> 500000 | AD24: =G24*13000 -> 234000 | AE24: 0 | AH24: =V24+X24+Z24+AA24+AC24+AD24+AE24 -> 1334000 | AI24: =Q24+R24+T24 -> 4064000 | AJ24: =AI24/208 -> 19538.462 | AK24: =AJ24*(E24+F24*130%) -> 4639407.7 | AM24: =AJ24*H24*150% -> 1011115.4 | AN24: =AJ24*I24*150%*130% -> 742950 | AO24: =+AJ24*J24*200% -> 0 | AP24: =AJ24*K24*200%*130% -> 0 | AQ24: =AJ24*L24*200%*150% -> 0 | AR24: =AJ24*M24*200%*150%*130% -> 0 | AS24: =N24*AJ24*300% -> 0 | AT24: =AJ24*O24*130%*300% -> 0 | AU24: =P24*AJ24*150%*300% -> 0 | AV24: =SUM(AM24:AU24) -> 1754065.4 | AX24: =AH24+AK24+AV24++AF24-AG24 -> 7727473.1 | AY24: =Q24+R24+T24 -> 4064000 | AZ24: =AY24*17.5% -> 711200 | BA24: =AY24*3% -> 121920 | BB24: =AY24*1% -> 40640 | BC24: =AY24*2% -> 81280 | BD24: =AZ24+BA24+BB24+BC24 -> 955040 | BE24: =AY24*8% -> 325120 | BF24: =AY24*1.5% -> 60960 | BG24: =AY24*1% -> 40640 | BH24: =BE24+BF24+BG24 -> 426720 | BI24: 11000000 | BK24: =BJ24*4400000 -> 0 | BL24: =V24+AB24+AD24 -> 234000 | BM24: =AX24-BL24-H24*0.5*AJ24-I24*0.95*AJ24-F24*0.3*AJ24-AJ24*J24-AJ24*K24*1.6-AJ24*L24*2-AJ24*M24*2.9-AJ24*N24*2-AJ24*O24*2.9-AJ24*P24*3.5 -> 6375384.6 | BN24: =IF(BM24-BI24-BK24-BH24<0,0,BM24-BK24-BI24-BH24) -> 0 | BO24: =ROUND(IF(BN24<=5000000,BN24*5%,IF(AND(BN24>5000000,BN24<=10000000),BN24*10%-250000,IF(AND(BN24>10000000,BN24<=18000000),BN24*15%-750000,IF(AND(BN24>18000000,BN24<=32000000),BN24*20%-1650000,IF(AND(BN24>32000000,BN24<=52000000),BN24*25%-3250000,IF(AND(BN24>52000000,BN24<80000000),BN24*30%-585000,IF(BN24>80000000,BN24*35%-9850000))))))),0) -> 0 | BP24: 35000 | BR24: =AX24-BH24-BO24-BP24 -> 7265753.1 | BS24: 104879687511
A25: =A24+1 -> 16 | B25: Đinh Thị Thơm | C25: CN | D25: 208 | E25: 142 | F25: 66 | G25: 19 | H25: 43.5 | I25: 19 | Q25: 4064000 | R25: 0 | T25: 0 | U25: 0 | V25: =IF((E25+F25)>=D25,U25,(E25+F25)*U25/D25) -> 0 | W25: 300000 | X25: =IF((E25+F25)>=160, W25, W25/D25*(E25+F25)) -> 300000 | Y25: 300000 | Z25: =IF((E25+F25)>=160,Y25, Y25/D25*(E25+F25)) -> 300000 | AC25: =IF((E25+F25)>=184,500000,0) -> 500000 | AD25: =G25*13000 -> 247000 | AE25: 0 | AH25: =V25+X25+Z25+AA25+AC25+AD25+AE25 -> 1347000 | AI25: =Q25+R25+T25 -> 4064000 | AJ25: =AI25/208 -> 19538.462 | AK25: =AJ25*(E25+F25*130%) -> 4450861.5 | AM25: =AJ25*H25*150% -> 1274884.6 | AN25: =AJ25*I25*150%*130% -> 723900 | AO25: =+AJ25*J25*200% -> 0 | AP25: =AJ25*K25*200%*130% -> 0 | AQ25: =AJ25*L25*200%*150% -> 0 | AR25: =AJ25*M25*200%*150%*130% -> 0 | AS25: =N25*AJ25*300% -> 0 | AT25: =AJ25*O25*130%*300% -> 0 | AU25: =P25*AJ25*150%*300% -> 0 | AV25: =SUM(AM25:AU25) -> 1998784.6 | AX25: =AH25+AK25+AV25++AF25-AG25 -> 7796646.2 | AY25: =Q25+R25+T25 -> 4064000 | AZ25: =AY25*17.5% -> 711200 | BA25: =AY25*3% -> 121920 | BB25: =AY25*1% -> 40640 | BC25: =AY25*2% -> 81280 | BD25: =AZ25+BA25+BB25+BC25 -> 955040 | BE25: =AY25*8% -> 325120 | BF25: =AY25*1.5% -> 60960 | BG25: =AY25*1% -> 40640 | BH25: =BE25+BF25+BG25 -> 426720 | BI25: 11000000 | BK25: =BJ25*4400000 -> 0 | BL25: =V25+AB25+AD25 -> 247000 | BM25: =AX25-BL25-H25*0.5*AJ25-I25*0.95*AJ25-F25*0.3*AJ25-AJ25*J25-AJ25*K25*1.6-AJ25*L25*2-AJ25*M25*2.9-AJ25*N25*2-AJ25*O25*2.9-AJ25*P25*3.5 -> 6385153.8 | BN25: =IF(BM25-BI25-BK25-BH25<0,0,BM25-BK25-BI25-BH25) -> 0 | BO25: =ROUND(IF(BN25<=5000000,BN25*5%,IF(AND(BN25>5000000,BN25<=10000000),BN25*10%-250000,IF(AND(BN25>10000000,BN25<=18000000),BN25*15%-750000,IF(AND(BN25>18000000,BN25<=32000000),BN25*20%-1650000,IF(AND(BN25>32000000,BN25<=52000000),BN25*25%-3250000,IF(AND(BN25>52000000,BN25<80000000),BN25*30%-585000,IF(BN25>80000000,BN25*35%-9850000))))))),0) -> 0 | BP25: 35000 | BR25: =AX25-BH25-BO25-BP25 -> 7334926.2 | BS25: 104879687511
A26: =A25+1 -> 17 | B26: Hoàng Thị Luân | C26: CN | D26: 208 | E26: 139.5 | F26: 60.5 | G26: 17 | H26: 36 | I26: 16.5 | Q26: 4064000 | R26: 0 | T26: 0 | U26: 0 | V26: =IF((E26+F26)>=D26,U26,(E26+F26)*U26/D26) -> 0 | W26: 300000 | X26: =IF((E26+F26)>=160, W26, W26/D26*(E26+F26)) -> 300000 | Y26: 300000 | Z26: =IF((E26+F26)>=160,Y26, Y26/D26*(E26+F26)) -> 300000 | AC26: =IF((E26+F26)>=184,500000,0) -> 500000 | AD26: =G26*13000 -> 221000 | AE26: 100000 | AH26: =V26+X26+Z26+AA26+AC26+AD26+AE26 -> 1421000 | AI26: =Q26+R26+T26 -> 4064000 | AJ26: =AI26/208 -> 19538.462 | AK26: =AJ26*(E26+F26*130%) -> 4262315.4 | AM26: =AJ26*H26*150% -> 1055076.9 | AN26: =AJ26*I26*150%*130% -> 628650 | AO26: =+AJ26*J26*200% -> 0 | AP26: =AJ26*K26*200%*130% -> 0 | AQ26: =AJ26*L26*200%*150% -> 0 | AR26: =AJ26*M26*200%*150%*130% -> 0 | AS26: =N26*AJ26*300% -> 0 | AT26: =AJ26*O26*130%*300% -> 0 | AU26: =P26*AJ26*150%*300% -> 0 | AV26: =SUM(AM26:AU26) -> 1683726.9 | AX26: =AH26+AK26+AV26++AF26-AG26 -> 7367042.3 | AY26: =Q26+R26+T26 -> 4064000 | AZ26: =AY26*17.5% -> 711200 | BA26: =AY26*3% -> 121920 | BB26: =AY26*1% -> 40640 | BC26: =AY26*2% -> 81280 | BD26: =AZ26+BA26+BB26+BC26 -> 955040 | BE26: =AY26*8% -> 325120 | BF26: =AY26*1.5% -> 60960 | BG26: =AY26*1% -> 40640 | BH26: =BE26+BF26+BG26 -> 426720 | BI26: 11000000 | BK26: =BJ26*4400000 -> 0 | BL26: =V26+AB26+AD26 -> 221000 | BM26: =AX26-BL26-H26*0.5*AJ26-I26*0.95*AJ26-F26*0.3*AJ26-AJ26*J26-AJ26*K26*1.6-AJ26*L26*2-AJ26*M26*2.9-AJ26*N26*2-AJ26*O26*2.9-AJ26*P26*3.5 -> 6133461.5 | BN26: =IF(BM26-BI26-BK26-BH26<0,0,BM26-BK26-BI26-BH26) -> 0 | BO26: =ROUND(IF(BN26<=5000000,BN26*5%,IF(AND(BN26>5000000,BN26<=10000000),BN26*10%-250000,IF(AND(BN26>10000000,BN26<=18000000),BN26*15%-750000,IF(AND(BN26>18000000,BN26<=32000000),BN26*20%-1650000,IF(AND(BN26>32000000,BN26<=52000000),BN26*25%-3250000,IF(AND(BN26>52000000,BN26<80000000),BN26*30%-585000,IF(BN26>80000000,BN26*35%-9850000))))))),0) -> 0 | BP26: 35000 | BR26: =AX26-BH26-BO26-BP26 -> 6905322.3 | BS26: 104879687511
A27: =A26+1 -> 18 | B27: Nguyễn Mạnh Hùng | C27: CN | D27: 208 | E27: 113 | F27: 55 | G27: 15 | H27: 33 | I27: 15 | Q27: 4064000 | R27: 0 | T27: 0 | U27: 0 | V27: =IF((E27+F27)>=D27,U27,(E27+F27)*U27/D27) -> 0 | W27: 300000 | X27: =IF((E27+F27)>=160, W27, W27/D27*(E27+F27)) -> 300000 | Y27: 300000 | Z27: =IF((E27+F27)>=160,Y27, Y27/D27*(E27+F27)) -> 300000 | AC27: =IF((E27+F27)>=184,500000,0) -> 0 | AD27: =G27*13000 -> 195000 | AE27: 0 | AH27: =V27+X27+Z27+AA27+AC27+AD27+AE27 -> 795000 | AI27: =Q27+R27+T27 -> 4064000 | AJ27: =AI27/208 -> 19538.462 | AK27: =AJ27*(E27+F27*130%) -> 3604846.2 | AM27: =AJ27*H27*150% -> 967153.85 | AN27: =AJ27*I27*150%*130% -> 571500 | AO27: =+AJ27*J27*200% -> 0 | AP27: =AJ27*K27*200%*130% -> 0 | AQ27: =AJ27*L27*200%*150% -> 0 | AR27: =AJ27*M27*200%*150%*130% -> 0 | AS27: =N27*AJ27*300% -> 0 | AT27: =AJ27*O27*130%*300% -> 0 | AU27: =P27*AJ27*150%*300% -> 0 | AV27: =SUM(AM27:AU27) -> 1538653.8 | AX27: =AH27+AK27+AV27++AF27-AG27 -> 5938500 | AY27: =Q27+R27+T27 -> 4064000 | AZ27: =AY27*17.5% -> 711200 | BA27: =AY27*3% -> 121920 | BB27: =AY27*1% -> 40640 | BC27: =AY27*2% -> 81280 | BD27: =AZ27+BA27+BB27+BC27 -> 955040 | BE27: =AY27*8% -> 325120 | BF27: =AY27*1.5% -> 60960 | BG27: =AY27*1% -> 40640 | BH27: =BE27+BF27+BG27 -> 426720 | BI27: 11000000 | BK27: =BJ27*4400000 -> 0 | BL27: =V27+AB27+AD27 -> 195000 | BM27: =AX27-BL27-H27*0.5*AJ27-I27*0.95*AJ27-F27*0.3*AJ27-AJ27*J27-AJ27*K27*1.6-AJ27*L27*2-AJ27*M27*2.9-AJ27*N27*2-AJ27*O27*2.9-AJ27*P27*3.5 -> 4820307.7 | BN27: =IF(BM27-BI27-BK27-BH27<0,0,BM27-BK27-BI27-BH27) -> 0 | BO27: =ROUND(IF(BN27<=5000000,BN27*5%,IF(AND(BN27>5000000,BN27<=10000000),BN27*10%-250000,IF(AND(BN27>10000000,BN27<=18000000),BN27*15%-750000,IF(AND(BN27>18000000,BN27<=32000000),BN27*20%-1650000,IF(AND(BN27>32000000,BN27<=52000000),BN27*25%-3250000,IF(AND(BN27>52000000,BN27<80000000),BN27*30%-585000,IF(BN27>80000000,BN27*35%-9850000))))))),0) -> 0 | BP27: 35000 | BR27: =AX27-BH27-BO27-BP27 -> 5476780 | BS27: 104879687511
A28: =A27+1 -> 19 | B28: Lê Duy Công | C28: CN | D28: 208 | E28: 150 | F28: 66 | G28: 19 | H28: 40.5 | I28: 18 | Q28: 4064000 | R28: 0 | T28: 0 | U28: 0 | V28: =IF((E28+F28)>=D28,U28,(E28+F28)*U28/D28) -> 0 | W28: 300000 | X28: =IF((E28+F28)>=160, W28, W28/D28*(E28+F28)) -> 300000 | Y28: 300000 | Z28: =IF((E28+F28)>=160,Y28, Y28/D28*(E28+F28)) -> 300000 | AC28: =IF((E28+F28)>=184,500000,0) -> 500000 | AD28: =G28*13000 -> 247000 | AE28: 0 | AH28: =V28+X28+Z28+AA28+AC28+AD28+AE28 -> 1347000 | AI28: =Q28+R28+T28 -> 4064000 | AJ28: =AI28/208 -> 19538.462 | AK28: =AJ28*(E28+F28*130%) -> 4607169.2 | AM28: =AJ28*H28*150% -> 1186961.5 | AN28: =AJ28*I28*150%*130% -> 685800 | AO28: =+AJ28*J28*200% -> 0 | AP28: =AJ28*K28*200%*130% -> 0 | AQ28: =AJ28*L28*200%*150% -> 0 | AR28: =AJ28*M28*200%*150%*130% -> 0 | AS28: =N28*AJ28*300% -> 0 | AT28: =AJ28*O28*130%*300% -> 0 | AU28: =P28*AJ28*150%*300% -> 0 | AV28: =SUM(AM28:AU28) -> 1872761.5 | AX28: =AH28+AK28+AV28++AF28-AG28 -> 7826930.8 | AY28: =Q28+R28+T28 -> 4064000 | AZ28: =AY28*17.5% -> 711200 | BA28: =AY28*3% -> 121920 | BB28: =AY28*1% -> 40640 | BC28: =AY28*2% -> 81280 | BD28: =AZ28+BA28+BB28+BC28 -> 955040 | BE28: =AY28*8% -> 325120 | BF28: =AY28*1.5% -> 60960 | BG28: =AY28*1% -> 40640 | BH28: =BE28+BF28+BG28 -> 426720 | BI28: 11000000 | BK28: =BJ28*4400000 -> 0 | BL28: =V28+AB28+AD28 -> 247000 | BM28: =AX28-BL28-H28*0.5*AJ28-I28*0.95*AJ28-F28*0.3*AJ28-AJ28*J28-AJ28*K28*1.6-AJ28*L28*2-AJ28*M28*2.9-AJ28*N28*2-AJ28*O28*2.9-AJ28*P28*3.5 -> 6463307.7 | BN28: =IF(BM28-BI28-BK28-BH28<0,0,BM28-BK28-BI28-BH28) -> 0 | BO28: =ROUND(IF(BN28<=5000000,BN28*5%,IF(AND(BN28>5000000,BN28<=10000000),BN28*10%-250000,IF(AND(BN28>10000000,BN28<=18000000),BN28*15%-750000,IF(AND(BN28>18000000,BN28<=32000000),BN28*20%-1650000,IF(AND(BN28>32000000,BN28<=52000000),BN28*25%-3250000,IF(AND(BN28>52000000,BN28<80000000),BN28*30%-585000,IF(BN28>80000000,BN28*35%-9850000))))))),0) -> 0 | BP28: 35000 | BR28: =AX28-BH28-BO28-BP28 -> 7365210.8 | BS28: 104879687511
A29: =A28+1 -> 20 | B29: Nguyễn Công Kiên | C29: CN | D29: 208 | E29: 150 | F29: 66 | G29: 19 | H29: 40.5 | I29: 18 | Q29: 4064000 | R29: 0 | T29: 0 | U29: 0 | V29: =IF((E29+F29)>=D29,U29,(E29+F29)*U29/D29) -> 0 | W29: 300000 | X29: =IF((E29+F29)>=160, W29, W29/D29*(E29+F29)) -> 300000 | Y29: 300000 | Z29: =IF((E29+F29)>=160,Y29, Y29/D29*(E29+F29)) -> 300000 | AC29: =IF((E29+F29)>=184,500000,0) -> 500000 | AD29: =G29*13000 -> 247000 | AE29: 0 | AH29: =V29+X29+Z29+AA29+AC29+AD29+AE29 -> 1347000 | AI29: =Q29+R29+T29 -> 4064000 | AJ29: =AI29/208 -> 19538.462 | AK29: =AJ29*(E29+F29*130%) -> 4607169.2 | AM29: =AJ29*H29*150% -> 1186961.5 | AN29: =AJ29*I29*150%*130% -> 685800 | AO29: =+AJ29*J29*200% -> 0 | AP29: =AJ29*K29*200%*130% -> 0 | AQ29: =AJ29*L29*200%*150% -> 0 | AR29: =AJ29*M29*200%*150%*130% -> 0 | AS29: =N29*AJ29*300% -> 0 | AT29: =AJ29*O29*130%*300% -> 0 | AU29: =P29*AJ29*150%*300% -> 0 | AV29: =SUM(AM29:AU29) -> 1872761.5 | AX29: =AH29+AK29+AV29++AF29-AG29 -> 7826930.8 | AY29: =Q29+R29+T29 -> 4064000 | AZ29: =AY29*17.5% -> 711200 | BA29: =AY29*3% -> 121920 | BB29: =AY29*1% -> 40640 | BC29: =AY29*2% -> 81280 | BD29: =AZ29+BA29+BB29+BC29 -> 955040 | BE29: =AY29*8% -> 325120 | BF29: =AY29*1.5% -> 60960 | BG29: =AY29*1% -> 40640 | BH29: =BE29+BF29+BG29 -> 426720 | BI29: 11000000 | BK29: =BJ29*4400000 -> 0 | BL29: =V29+AB29+AD29 -> 247000 | BM29: =AX29-BL29-H29*0.5*AJ29-I29*0.95*AJ29-F29*0.3*AJ29-AJ29*J29-AJ29*K29*1.6-AJ29*L29*2-AJ29*M29*2.9-AJ29*N29*2-AJ29*O29*2.9-AJ29*P29*3.5 -> 6463307.7 | BN29: =IF(BM29-BI29-BK29-BH29<0,0,BM29-BK29-BI29-BH29) -> 0 | BO29: =ROUND(IF(BN29<=5000000,BN29*5%,IF(AND(BN29>5000000,BN29<=10000000),BN29*10%-250000,IF(AND(BN29>10000000,BN29<=18000000),BN29*15%-750000,IF(AND(BN29>18000000,BN29<=32000000),BN29*20%-1650000,IF(AND(BN29>32000000,BN29<=52000000),BN29*25%-3250000,IF(AND(BN29>52000000,BN29<80000000),BN29*30%-585000,IF(BN29>80000000,BN29*35%-9850000))))))),0) -> 0 | BP29: 35000 | BR29: =AX29-BH29-BO29-BP29 -> 7365210.8 | BS29: 104879687511
A30: =A29+1 -> 21 | B30: Hà Quang Nhất | C30: CN | D30: 208 | E30: 144.5 | F30: 71.5 | G30: 19 | H30: 37.5 | I30: 19.5 | Q30: 4064000 | R30: 0 | T30: 0 | U30: 0 | V30: =IF((E30+F30)>=D30,U30,(E30+F30)*U30/D30) -> 0 | W30: 300000 | X30: =IF((E30+F30)>=160, W30, W30/D30*(E30+F30)) -> 300000 | Y30: 300000 | Z30: =IF((E30+F30)>=160,Y30, Y30/D30*(E30+F30)) -> 300000 | AA30: 20000 | AC30: =IF((E30+F30)>=184,500000,0) -> 500000 | AD30: =G30*13000 -> 247000 | AE30: 0 | AH30: =V30+X30+Z30+AA30+AC30+AD30+AE30 -> 1367000 | AI30: =Q30+R30+T30 -> 4064000 | AJ30: =AI30/208 -> 19538.462 | AK30: =AJ30*(E30+F30*130%) -> 4639407.7 | AM30: =AJ30*H30*150% -> 1099038.5 | AN30: =AJ30*I30*150%*130% -> 742950 | AO30: =+AJ30*J30*200% -> 0 | AP30: =AJ30*K30*200%*130% -> 0 | AQ30: =AJ30*L30*200%*150% -> 0 | AR30: =AJ30*M30*200%*150%*130% -> 0 | AS30: =N30*AJ30*300% -> 0 | AT30: =AJ30*O30*130%*300% -> 0 | AU30: =P30*AJ30*150%*300% -> 0 | AV30: =SUM(AM30:AU30) -> 1841988.5 | AX30: =AH30+AK30+AV30++AF30-AG30 -> 7848396.2 | AY30: =Q30+R30+T30 -> 4064000 | AZ30: =AY30*17.5% -> 711200 | BA30: =AY30*3% -> 121920 | BB30: =AY30*1% -> 40640 | BC30: =AY30*2% -> 81280 | BD30: =AZ30+BA30+BB30+BC30 -> 955040 | BE30: =AY30*8% -> 325120 | BF30: =AY30*1.5% -> 60960 | BG30: =AY30*1% -> 40640 | BH30: =BE30+BF30+BG30 -> 426720 | BI30: 11000000 | BK30: =BJ30*4400000 -> 0 | BL30: =V30+AB30+AD30 -> 247000 | BM30: =AX30-BL30-H30*0.5*AJ30-I30*0.95*AJ30-F30*0.3*AJ30-AJ30*J30-AJ30*K30*1.6-AJ30*L30*2-AJ30*M30*2.9-AJ30*N30*2-AJ30*O30*2.9-AJ30*P30*3.5 -> 6454000 | BN30: =IF(BM30-BI30-BK30-BH30<0,0,BM30-BK30-BI30-BH30) -> 0 | BO30: =ROUND(IF(BN30<=5000000,BN30*5%,IF(AND(BN30>5000000,BN30<=10000000),BN30*10%-250000,IF(AND(BN30>10000000,BN30<=18000000),BN30*15%-750000,IF(AND(BN30>18000000,BN30<=32000000),BN30*20%-1650000,IF(AND(BN30>32000000,BN30<=52000000),BN30*25%-3250000,IF(AND(BN30>52000000,BN30<80000000),BN30*30%-585000,IF(BN30>80000000,BN30*35%-9850000))))))),0) -> 0 | BP30: 35000 | BR30: =AX30-BH30-BO30-BP30 -> 7386676.2 | BS30: 104879687511
A31: =A30+1 -> 22 | B31: Hoàng Hương Hùng | C31: CN | D31: 208 | E31: 109 | F31: 55 | G31: 13 | H31: 25.5 | I31: 15 | Q31: 4064000 | R31: 0 | T31: 0 | U31: 0 | V31: =IF((E31+F31)>=D31,U31,(E31+F31)*U31/D31) -> 0 | W31: 300000 | X31: =IF((E31+F31)>=160, W31, W31/D31*(E31+F31)) -> 300000 | Y31: 300000 | Z31: =IF((E31+F31)>=160,Y31, Y31/D31*(E31+F31)) -> 300000 | AC31: =IF((E31+F31)>=184,500000,0) -> 0 | AD31: =G31*13000 -> 169000 | AE31: 0 | AH31: =V31+X31+Z31+AA31+AC31+AD31+AE31 -> 769000 | AI31: =Q31+R31+T31 -> 4064000 | AJ31: =AI31/208 -> 19538.462 | AK31: =AJ31*(E31+F31*130%) -> 3526692.3 | AM31: =AJ31*H31*150% -> 747346.15 | AN31: =AJ31*I31*150%*130% -> 571500 | AO31: =+AJ31*J31*200% -> 0 | AP31: =AJ31*K31*200%*130% -> 0 | AQ31: =AJ31*L31*200%*150% -> 0 | AR31: =AJ31*M31*200%*150%*130% -> 0 | AS31: =N31*AJ31*300% -> 0 | AT31: =AJ31*O31*130%*300% -> 0 | AU31: =P31*AJ31*150%*300% -> 0 | AV31: =SUM(AM31:AU31) -> 1318846.2 | AX31: =AH31+AK31+AV31++AF31-AG31 -> 5614538.5 | AY31: =Q31+R31+T31 -> 4064000 | AZ31: =AY31*17.5% -> 711200 | BA31: =AY31*3% -> 121920 | BB31: =AY31*1% -> 40640 | BC31: =AY31*2% -> 81280 | BD31: =AZ31+BA31+BB31+BC31 -> 955040 | BE31: =AY31*8% -> 325120 | BF31: =AY31*1.5% -> 60960 | BG31: =AY31*1% -> 40640 | BH31: =BE31+BF31+BG31 -> 426720 | BI31: 11000000 | BK31: =BJ31*4400000 -> 0 | BL31: =V31+AB31+AD31 -> 169000 | BM31: =AX31-BL31-H31*0.5*AJ31-I31*0.95*AJ31-F31*0.3*AJ31-AJ31*J31-AJ31*K31*1.6-AJ31*L31*2-AJ31*M31*2.9-AJ31*N31*2-AJ31*O31*2.9-AJ31*P31*3.5 -> 4595615.4 | BN31: =IF(BM31-BI31-BK31-BH31<0,0,BM31-BK31-BI31-BH31) -> 0 | BO31: =ROUND(IF(BN31<=5000000,BN31*5%,IF(AND(BN31>5000000,BN31<=10000000),BN31*10%-250000,IF(AND(BN31>10000000,BN31<=18000000),BN31*15%-750000,IF(AND(BN31>18000000,BN31<=32000000),BN31*20%-1650000,IF(AND(BN31>32000000,BN31<=52000000),BN31*25%-3250000,IF(AND(BN31>52000000,BN31<80000000),BN31*30%-585000,IF(BN31>80000000,BN31*35%-9850000))))))),0) -> 0 | BP31: 35000 | BR31: =AX31-BH31-BO31-BP31 -> 5152818.5 | BS31: 104879687511
A32: =A31+1 -> 23 | B32: Hoàng Văn Đinh | C32: CN | D32: 208 | E32: 120.5 | F32: 71.5 | G32: 17 | H32: 31.5 | I32: 19.5 | Q32: 4267000 | R32: 0 | T32: 600000 | U32: 0 | V32: =IF((E32+F32)>=D32,U32,(E32+F32)*U32/D32) -> 0 | W32: 300000 | X32: =IF((E32+F32)>=160, W32, W32/D32*(E32+F32)) -> 300000 | Y32: 300000 | Z32: =IF((E32+F32)>=160,Y32, Y32/D32*(E32+F32)) -> 300000 | AA32: 20000 | AC32: =IF((E32+F32)>=184,500000,0) -> 500000 | AD32: =G32*13000 -> 221000 | AE32: 0 | AH32: =V32+X32+Z32+AA32+AC32+AD32+AE32 -> 1341000 | AI32: =Q32+R32+T32 -> 4867000 | AJ32: =AI32/208 -> 23399.038 | AK32: =AJ32*(E32+F32*130%) -> 4994524.8 | AM32: =AJ32*H32*150% -> 1105604.6 | AN32: =AJ32*I32*150%*130% -> 889748.44 | AO32: =+AJ32*J32*200% -> 0 | AP32: =AJ32*K32*200%*130% -> 0 | AQ32: =AJ32*L32*200%*150% -> 0 | AR32: =AJ32*M32*200%*150%*130% -> 0 | AS32: =N32*AJ32*300% -> 0 | AT32: =AJ32*O32*130%*300% -> 0 | AU32: =P32*AJ32*150%*300% -> 0 | AV32: =SUM(AM32:AU32) -> 1995353 | AX32: =AH32+AK32+AV32++AF32-AG32 -> 8330877.8 | AY32: =Q32+R32+T32 -> 4867000 | AZ32: =AY32*17.5% -> 851725 | BA32: =AY32*3% -> 146010 | BB32: =AY32*1% -> 48670 | BC32: =AY32*2% -> 97340 | BD32: =AZ32+BA32+BB32+BC32 -> 1143745 | BE32: =AY32*8% -> 389360 | BF32: =AY32*1.5% -> 73005 | BG32: =AY32*1% -> 48670 | BH32: =BE32+BF32+BG32 -> 511035 | BI32: 11000000 | BK32: =BJ32*4400000 -> 0 | BL32: =V32+AB32+AD32 -> 221000 | BM32: =AX32-BL32-H32*0.5*AJ32-I32*0.95*AJ32-F32*0.3*AJ32-AJ32*J32-AJ32*K32*1.6-AJ32*L32*2-AJ32*M32*2.9-AJ32*N32*2-AJ32*O32*2.9-AJ32*P32*3.5 -> 6805966.3 | BN32: =IF(BM32-BI32-BK32-BH32<0,0,BM32-BK32-BI32-BH32) -> 0 | BO32: =ROUND(IF(BN32<=5000000,BN32*5%,IF(AND(BN32>5000000,BN32<=10000000),BN32*10%-250000,IF(AND(BN32>10000000,BN32<=18000000),BN32*15%-750000,IF(AND(BN32>18000000,BN32<=32000000),BN32*20%-1650000,IF(AND(BN32>32000000,BN32<=52000000),BN32*25%-3250000,IF(AND(BN32>52000000,BN32<80000000),BN32*30%-585000,IF(BN32>80000000,BN32*35%-9850000))))))),0) -> 0 | BP32: 0 | BR32: =AX32-BH32-BO32-BP32 -> 7819842.8 | BS32: 104879687511
A33: =A32+1 -> 24 | B33: Nguyễn Văn Sơn | C33: CN | D33: 208 | E33: 131.5 | F33: 60.5 | G33: 17 | H33: 36 | I33: 16.5 | Q33: 4064000 | R33: 0 | T33: 0 | U33: 0 | V33: =IF((E33+F33)>=D33,U33,(E33+F33)*U33/D33) -> 0 | W33: 300000 | X33: =IF((E33+F33)>=160, W33, W33/D33*(E33+F33)) -> 300000 | Y33: 300000 | Z33: =IF((E33+F33)>=160,Y33, Y33/D33*(E33+F33)) -> 300000 | AC33: =IF((E33+F33)>=184,500000,0) -> 500000 | AD33: =G33*13000 -> 221000 | AE33: 0 | AH33: =V33+X33+Z33+AA33+AC33+AD33+AE33 -> 1321000 | AI33: =Q33+R33+T33 -> 4064000 | AJ33: =AI33/208 -> 19538.462 | AK33: =AJ33*(E33+F33*130%) -> 4106007.7 | AM33: =AJ33*H33*150% -> 1055076.9 | AN33: =AJ33*I33*150%*130% -> 628650 | AO33: =+AJ33*J33*200% -> 0 | AP33: =AJ33*K33*200%*130% -> 0 | AQ33: =AJ33*L33*200%*150% -> 0 | AR33: =AJ33*M33*200%*150%*130% -> 0 | AS33: =N33*AJ33*300% -> 0 | AT33: =AJ33*O33*130%*300% -> 0 | AU33: =P33*AJ33*150%*300% -> 0 | AV33: =SUM(AM33:AU33) -> 1683726.9 | AX33: =AH33+AK33+AV33++AF33-AG33 -> 7110734.6 | AY33: =Q33+R33+T33 -> 4064000 | AZ33: =AY33*17.5% -> 711200 | BA33: =AY33*3% -> 121920 | BB33: =AY33*1% -> 40640 | BC33: =AY33*2% -> 81280 | BD33: =AZ33+BA33+BB33+BC33 -> 955040 | BE33: =AY33*8% -> 325120 | BF33: =AY33*1.5% -> 60960 | BG33: =AY33*1% -> 40640 | BH33: =BE33+BF33+BG33 -> 426720 | BI33: 11000000 | BK33: =BJ33*4400000 -> 0 | BL33: =V33+AB33+AD33 -> 221000 | BM33: =AX33-BL33-H33*0.5*AJ33-I33*0.95*AJ33-F33*0.3*AJ33-AJ33*J33-AJ33*K33*1.6-AJ33*L33*2-AJ33*M33*2.9-AJ33*N33*2-AJ33*O33*2.9-AJ33*P33*3.5 -> 5877153.8 | BN33: =IF(BM33-BI33-BK33-BH33<0,0,BM33-BK33-BI33-BH33) -> 0 | BO33: =ROUND(IF(BN33<=5000000,BN33*5%,IF(AND(BN33>5000000,BN33<=10000000),BN33*10%-250000,IF(AND(BN33>10000000,BN33<=18000000),BN33*15%-750000,IF(AND(BN33>18000000,BN33<=32000000),BN33*20%-1650000,IF(AND(BN33>32000000,BN33<=52000000),BN33*25%-3250000,IF(AND(BN33>52000000,BN33<80000000),BN33*30%-585000,IF(BN33>80000000,BN33*35%-9850000))))))),0) -> 0 | BP33: 0 | BR33: =AX33-BH33-BO33-BP33 -> 6684014.6 | BS33: 104879687511
A34: =A33+1 -> 25 | B34: Hoàng Xuân Huy | C34: CN | D34: 208 | E34: 208 | F34: 0 | G34: 21 | H34: 63 | I34: 0 | Q34: 4064000 | R34: 0 | T34: 0 | U34: 0 | V34: =IF((E34+F34)>=D34,U34,(E34+F34)*U34/D34) -> 0 | W34: 300000 | X34: =IF((E34+F34)>=160, W34, W34/D34*(E34+F34)) -> 300000 | Y34: 300000 | Z34: =IF((E34+F34)>=160,Y34, Y34/D34*(E34+F34)) -> 300000 | AC34: =IF((E34+F34)>=184,500000,0) -> 500000 | AD34: =G34*13000 -> 273000 | AE34: 0 | AH34: =V34+X34+Z34+AA34+AC34+AD34+AE34 -> 1373000 | AI34: =Q34+R34+T34 -> 4064000 | AJ34: =AI34/208 -> 19538.462 | AK34: =AJ34*(E34+F34*130%) -> 4064000 | AM34: =AJ34*H34*150% -> 1846384.6 | AN34: =AJ34*I34*150%*130% -> 0 | AO34: =+AJ34*J34*200% -> 0 | AP34: =AJ34*K34*200%*130% -> 0 | AQ34: =AJ34*L34*200%*150% -> 0 | AR34: =AJ34*M34*200%*150%*130% -> 0 | AS34: =N34*AJ34*300% -> 0 | AT34: =AJ34*O34*130%*300% -> 0 | AU34: =P34*AJ34*150%*300% -> 0 | AV34: =SUM(AM34:AU34) -> 1846384.6 | AX34: =AH34+AK34+AV34++AF34-AG34 -> 7283384.6 | AY34: =Q34+R34+T34 -> 4064000 | AZ34: =AY34*17.5% -> 711200 | BA34: =AY34*3% -> 121920 | BB34: =AY34*1% -> 40640 | BC34: =AY34*2% -> 81280 | BD34: =AZ34+BA34+BB34+BC34 -> 955040 | BE34: =AY34*8% -> 325120 | BF34: =AY34*1.5% -> 60960 | BG34: =AY34*1% -> 40640 | BH34: =BE34+BF34+BG34 -> 426720 | BI34: 11000000 | BK34: =BJ34*4400000 -> 0 | BL34: =V34+AB34+AD34 -> 273000 | BM34: =AX34-BL34-H34*0.5*AJ34-I34*0.95*AJ34-F34*0.3*AJ34-AJ34*J34-AJ34*K34*1.6-AJ34*L34*2-AJ34*M34*2.9-AJ34*N34*2-AJ34*O34*2.9-AJ34*P34*3.5 -> 6394923.1 | BN34: =IF(BM34-BI34-BK34-BH34<0,0,BM34-BK34-BI34-BH34) -> 0 | BO34: =ROUND(IF(BN34<=5000000,BN34*5%,IF(AND(BN34>5000000,BN34<=10000000),BN34*10%-250000,IF(AND(BN34>10000000,BN34<=18000000),BN34*15%-750000,IF(AND(BN34>18000000,BN34<=32000000),BN34*20%-1650000,IF(AND(BN34>32000000,BN34<=52000000),BN34*25%-3250000,IF(AND(BN34>52000000,BN34<80000000),BN34*30%-585000,IF(BN34>80000000,BN34*35%-9850000))))))),0) -> 0 | BP34: 0 | BR34: =AX34-BH34-BO34-BP34 -> 6856664.6 | BS34: 104879687511
A35: =A34+1 -> 26 | B35: Ngô Quang Nam | C35: CN | D35: 208 | E35: 161 | F35: 55 | G35: 22 | H35: 51 | I35: 15 | Q35: 4064000 | R35: 0 | T35: 0 | U35: 0 | V35: =IF((E35+F35)>=D35,U35,(E35+F35)*U35/D35) -> 0 | W35: 300000 | X35: =IF((E35+F35)>=160, W35, W35/D35*(E35+F35)) -> 300000 | Y35: 300000 | Z35: =IF((E35+F35)>=160,Y35, Y35/D35*(E35+F35)) -> 300000 | AA35: 20000 | AC35: =IF((E35+F35)>=184,500000,0) -> 500000 | AD35: =G35*13000 -> 286000 | AE35: 0 | AH35: =V35+X35+Z35+AA35+AC35+AD35+AE35 -> 1406000 | AI35: =Q35+R35+T35 -> 4064000 | AJ35: =AI35/208 -> 19538.462 | AK35: =AJ35*(E35+F35*130%) -> 4542692.3 | AM35: =AJ35*H35*150% -> 1494692.3 | AN35: =AJ35*I35*150%*130% -> 571500 | AO35: =+AJ35*J35*200% -> 0 | AP35: =AJ35*K35*200%*130% -> 0 | AQ35: =AJ35*L35*200%*150% -> 0 | AR35: =AJ35*M35*200%*150%*130% -> 0 | AS35: =N35*AJ35*300% -> 0 | AT35: =AJ35*O35*130%*300% -> 0 | AU35: =P35*AJ35*150%*300% -> 0 | AV35: =SUM(AM35:AU35) -> 2066192.3 | AX35: =AH35+AK35+AV35++AF35-AG35 -> 8014884.6 | AY35: =Q35+R35+T35 -> 4064000 | AZ35: =AY35*17.5% -> 711200 | BA35: =AY35*3% -> 121920 | BB35: =AY35*1% -> 40640 | BC35: =AY35*2% -> 81280 | BD35: =AZ35+BA35+BB35+BC35 -> 955040 | BE35: =AY35*8% -> 325120 | BF35: =AY35*1.5% -> 60960 | BG35: =AY35*1% -> 40640 | BH35: =BE35+BF35+BG35 -> 426720 | BI35: 11000000 | BK35: =BJ35*4400000 -> 0 | BL35: =V35+AB35+AD35 -> 286000 | BM35: =AX35-BL35-H35*0.5*AJ35-I35*0.95*AJ35-F35*0.3*AJ35-AJ35*J35-AJ35*K35*1.6-AJ35*L35*2-AJ35*M35*2.9-AJ35*N35*2-AJ35*O35*2.9-AJ35*P35*3.5 -> 6629846.2 | BN35: =IF(BM35-BI35-BK35-BH35<0,0,BM35-BK35-BI35-BH35) -> 0 | BO35: =ROUND(IF(BN35<=5000000,BN35*5%,IF(AND(BN35>5000000,BN35<=10000000),BN35*10%-250000,IF(AND(BN35>10000000,BN35<=18000000),BN35*15%-750000,IF(AND(BN35>18000000,BN35<=32000000),BN35*20%-1650000,IF(AND(BN35>32000000,BN35<=52000000),BN35*25%-3250000,IF(AND(BN35>52000000,BN35<80000000),BN35*30%-585000,IF(BN35>80000000,BN35*35%-9850000))))))),0) -> 0 | BP35: 0 | BR35: =AX35-BH35-BO35-BP35 -> 7588164.6 | BS35: 104879687511
A36: =A35+1 -> 27 | B36: Đỗ Văn Hà | C36: CN | D36: 208 | E36: 140 | F36: 0 | G36: 13 | H36: 40 | I36: 0 | Q36: 4064000 | R36: 0 | T36: 0 | U36: 0 | V36: =IF((E36+F36)>=D36,U36,(E36+F36)*U36/D36) -> 0 | W36: 300000 | X36: =IF((E36+F36)>=160, W36, W36/D36*(E36+F36)) -> 201923.08 | Y36: 300000 | Z36: =IF((E36+F36)>=160,Y36, Y36/D36*(E36+F36)) -> 201923.08 | AC36: =IF((E36+F36)>=184,500000,0) -> 0 | AD36: =G36*13000 -> 169000 | AE36: 0 | AH36: =V36+X36+Z36+AA36+AC36+AD36+AE36 -> 572846.15 | AI36: =Q36+R36+T36 -> 4064000 | AJ36: =AI36/208 -> 19538.462 | AK36: =AJ36*(E36+F36*130%) -> 2735384.6 | AM36: =AJ36*H36*150% -> 1172307.7 | AN36: =AJ36*I36*150%*130% -> 0 | AO36: =+AJ36*J36*200% -> 0 | AP36: =AJ36*K36*200%*130% -> 0 | AQ36: =AJ36*L36*200%*150% -> 0 | AR36: =AJ36*M36*200%*150%*130% -> 0 | AS36: =N36*AJ36*300% -> 0 | AT36: =AJ36*O36*130%*300% -> 0 | AU36: =P36*AJ36*150%*300% -> 0 | AV36: =SUM(AM36:AU36) -> 1172307.7 | AX36: =AH36+AK36+AV36++AF36-AG36 -> 4480538.5 | AY36: =Q36+R36+T36 -> 4064000 | AZ36: =AY36*17.5% -> 711200 | BA36: =AY36*3% -> 121920 | BB36: =AY36*1% -> 40640 | BC36: =AY36*2% -> 81280 | BD36: =AZ36+BA36+BB36+BC36 -> 955040 | BE36: =AY36*8% -> 325120 | BF36: =AY36*1.5% -> 60960 | BG36: =AY36*1% -> 40640 | BH36: =BE36+BF36+BG36 -> 426720 | BI36: 11000000 | BK36: =BJ36*4400000 -> 0 | BL36: =V36+AB36+AD36 -> 169000 | BM36: =AX36-BL36-H36*0.5*AJ36-I36*0.95*AJ36-F36*0.3*AJ36-AJ36*J36-AJ36*K36*1.6-AJ36*L36*2-AJ36*M36*2.9-AJ36*N36*2-AJ36*O36*2.9-AJ36*P36*3.5 -> 3920769.2 | BN36: =IF(BM36-BI36-BK36-BH36<0,0,BM36-BK36-BI36-BH36) -> 0 | BO36: =ROUND(IF(BN36<=5000000,BN36*5%,IF(AND(BN36>5000000,BN36<=10000000),BN36*10%-250000,IF(AND(BN36>10000000,BN36<=18000000),BN36*15%-750000,IF(AND(BN36>18000000,BN36<=32000000),BN36*20%-1650000,IF(AND(BN36>32000000,BN36<=52000000),BN36*25%-3250000,IF(AND(BN36>52000000,BN36<80000000),BN36*30%-585000,IF(BN36>80000000,BN36*35%-9850000))))))),0) -> 0 | BP36: 0 | BR36: =AX36-BH36-BO36-BP36 -> 4053818.5 | BS36: 104879687511
A37: =A36+1 -> 28 | B37: Nguyễn Việt Hưng | C37: QC (TT) | D37: 208 | E37: 184 | F37: 0 | G37: 0 | H37: 2.5 | I37: 0 | Q37: 4267000 | R37: 1300000 | T37: 900000 | U37: 400000 | V37: =IF((E37+F37)>=160,U37,(E37+F37)*U37/D37) -> 400000 | W37: 300000 | X37: =IF((E37+F37)>=160, W37, W37/D37*(E37+F37)) -> 300000 | Y37: 300000 | Z37: =IF((E37+F37)>=160,Y37, Y37/D37*(E37+F37)) -> 300000 | AB37: 0 | AC37: =IF((E37+F37)>=184,500000,0) -> 500000 | AD37: =G37*13000 -> 0 | AE37: 0 | AH37: =V37+X37+Z37+AA37+AC37+AD37+AE37 -> 1500000 | AI37: =Q37+R37+T37 -> 6467000 | AJ37: =AI37/208 -> 31091.346 | AK37: =AJ37*(E37+F37*130%) -> 5720807.7 | AM37: =AJ37*H37*150% -> 116592.55 | AN37: =AJ37*I37*150%*130% -> 0 | AO37: =+AJ37*J37*200% -> 0 | AP37: =AJ37*K37*200%*130% -> 0 | AQ37: =AJ37*L37*200%*150% -> 0 | AR37: =AJ37*M37*200%*150%*130% -> 0 | AS37: =N37*AJ37*300% -> 0 | AT37: =AJ37*O37*130%*300% -> 0 | AU37: =P37*AJ37*150%*300% -> 0 | AV37: =SUM(AM37:AU37) -> 116592.55 | AX37: =AH37+AK37+AV37++AF37-AG37 -> 7337400.2 | AY37: =Q37+R37+T37 -> 6467000 | AZ37: =AY37*17.5% -> 1131725 | BA37: =AY37*3% -> 194010 | BB37: =AY37*1% -> 64670 | BC37: =AY37*2% -> 129340 | BD37: =AZ37+BA37+BB37+BC37 -> 1519745 | BE37: =AY37*8% -> 517360 | BF37: =AY37*1.5% -> 97005 | BG37: =AY37*1% -> 64670 | BH37: =BE37+BF37+BG37 -> 679035 | BI37: 11000000 | BK37: =BJ37*4400000 -> 0 | BL37: =V37+AB37+AD37 -> 400000 | BM37: =AX37-BL37-H37*0.5*AJ37-I37*0.95*AJ37-F37*0.3*AJ37-AJ37*J37-AJ37*K37*1.6-AJ37*L37*2-AJ37*M37*2.9-AJ37*N37*2-AJ37*O37*2.9-AJ37*P37*3.5 -> 6898536.1 | BN37: =IF(BM37-BI37-BK37-BH37<0,0,BM37-BK37-BI37-BH37) -> 0 | BO37: =ROUND(IF(BN37<=5000000,BN37*5%,IF(AND(BN37>5000000,BN37<=10000000),BN37*10%-250000,IF(AND(BN37>10000000,BN37<=18000000),BN37*15%-750000,IF(AND(BN37>18000000,BN37<=32000000),BN37*20%-1650000,IF(AND(BN37>32000000,BN37<=52000000),BN37*25%-3250000,IF(AND(BN37>52000000,BN37<80000000),BN37*30%-585000,IF(BN37>80000000,BN37*35%-9850000))))))),0) -> 0 | BP37: 35000 | BR37: =AX37-BH37-BO37-BP37 -> 6623365.2 | BS37: 105872539677
A38: =A37+1 -> 29 | B38: Nguyễn Hữu Lư | C38: QC | D38: 208 | E38: 148 | F38: 0 | G38: 0 | H38: 1.5 | I38: 0 | Q38: 4267000 | R38: 800000 | T38: 600000 | U38: 400000 | V38: 400000 | W38: 300000 | X38: =IF((E38+F38)>=160, W38, W38/D38*(E38+F38)) -> 213461.54 | Y38: 300000 | Z38: =IF((E38+F38)>=160,Y38, Y38/D38*(E38+F38)) -> 213461.54 | AB38: 0 | AC38: =IF((E38+F38)>=184,500000,0) -> 0 | AD38: =G38*13000 -> 0 | AE38: 0 | AH38: =V38+X38+Z38+AA38+AC38+AD38+AE38 -> 826923.08 | AI38: =Q38+R38+T38 -> 5667000 | AJ38: =AI38/208 -> 27245.192 | AK38: =AJ38*(E38+F38*130%) -> 4032288.5 | AM38: =AJ38*H38*150% -> 61301.683 | AN38: =AJ38*I38*150%*130% -> 0 | AO38: =+AJ38*J38*200% -> 0 | AP38: =AJ38*K38*200%*130% -> 0 | AQ38: =AJ38*L38*200%*150% -> 0 | AR38: =AJ38*M38*200%*150%*130% -> 0 | AS38: =N38*AJ38*300% -> 0 | AT38: =AJ38*O38*130%*300% -> 0 | AU38: =P38*AJ38*150%*300% -> 0 | AV38: =SUM(AM38:AU38) -> 61301.683 | AX38: =AH38+AK38+AV38++AF38-AG38 -> 4920513.2 | AY38: =Q38+R38+T38 -> 5667000 | AZ38: =AY38*17.5% -> 991725 | BA38: =AY38*3% -> 170010 | BB38: =AY38*1% -> 56670 | BC38: =AY38*2% -> 113340 | BD38: =AZ38+BA38+BB38+BC38 -> 1331745 | BE38: =AY38*8% -> 453360 | BF38: =AY38*1.5% -> 85005 | BG38: =AY38*1% -> 56670 | BH38: =BE38+BF38+BG38 -> 595035 | BI38: 11000000 | BK38: =BJ38*4400000 -> 0 | BL38: =V38+AB38+AD38 -> 400000 | BM38: =AX38-BL38-H38*0.5*AJ38-I38*0.95*AJ38-F38*0.3*AJ38-AJ38*J38-AJ38*K38*1.6-AJ38*L38*2-AJ38*M38*2.9-AJ38*N38*2-AJ38*O38*2.9-AJ38*P38*3.5 -> 4500079.3 | BN38: =IF(BM38-BI38-BK38-BH38<0,0,BM38-BK38-BI38-BH38) -> 0 | BO38: =ROUND(IF(BN38<=5000000,BN38*5%,IF(AND(BN38>5000000,BN38<=10000000),BN38*10%-250000,IF(AND(BN38>10000000,BN38<=18000000),BN38*15%-750000,IF(AND(BN38>18000000,BN38<=32000000),BN38*20%-1650000,IF(AND(BN38>32000000,BN38<=52000000),BN38*25%-3250000,IF(AND(BN38>52000000,BN38<80000000),BN38*30%-585000,IF(BN38>80000000,BN38*35%-9850000))))))),0) -> 0 | BP38: 35000 | BR38: =AX38-BH38-BO38-BP38 -> 4290478.2 | BS38: 106876052285
A39: =A38+1 -> 30 | B39: Nguyễn Thanh Hải | C39: QC | D39: 208 | E39: 192 | F39: 0 | G39: 0 | H39: 0 | I39: 0 | Q39: 4064000 | R39: 0 | T39: 0 | U39: 400000 | V39: =IF((E39+F39)>=160,U39,(E39+F39)*U39/D39) -> 400000 | W39: 300000 | X39: =IF((E39+F39)>=160, W39, W39/D39*(E39+F39)) -> 300000 | Y39: 300000 | Z39: =IF((E39+F39)>=160,Y39, Y39/D39*(E39+F39)) -> 300000 | AC39: =IF((E39+F39)>=184,500000,0) -> 500000 | AD39: =G39*13000 -> 0 | AE39: 0 | AH39: =V39+X39+Z39+AA39+AC39+AD39+AE39 -> 1500000 | AI39: =Q39+R39+T39 -> 4064000 | AJ39: =AI39/208 -> 19538.462 | AK39: =AJ39*(E39+F39*130%) -> 3751384.6 | AM39: =AJ39*H39*150% -> 0 | AN39: =AJ39*I39*150%*130% -> 0 | AO39: =+AJ39*J39*200% -> 0 | AP39: =AJ39*K39*200%*130% -> 0 | AQ39: =AJ39*L39*200%*150% -> 0 | AR39: =AJ39*M39*200%*150%*130% -> 0 | AS39: =N39*AJ39*300% -> 0 | AT39: =AJ39*O39*130%*300% -> 0 | AU39: =P39*AJ39*150%*300% -> 0 | AV39: =SUM(AM39:AU39) -> 0 | AX39: =AH39+AK39+AV39++AF39-AG39 -> 5251384.6 | AY39: =Q39+R39+T39 -> 4064000 | AZ39: =AY39*17.5% -> 711200 | BA39: =AY39*3% -> 121920 | BB39: =AY39*1% -> 40640 | BC39: =AY39*2% -> 81280 | BD39: =AZ39+BA39+BB39+BC39 -> 955040 | BE39: =AY39*8% -> 325120 | BF39: =AY39*1.5% -> 60960 | BG39: =AY39*1% -> 40640 | BH39: =BE39+BF39+BG39 -> 426720 | BI39: 11000000 | BK39: =BJ39*4400000 -> 0 | BL39: =V39+AB39+AD39 -> 400000 | BM39: =AX39-BL39-H39*0.5*AJ39-I39*0.95*AJ39-F39*0.3*AJ39-AJ39*J39-AJ39*K39*1.6-AJ39*L39*2-AJ39*M39*2.9-AJ39*N39*2-AJ39*O39*2.9-AJ39*P39*3.5 -> 4851384.6 | BN39: =IF(BM39-BI39-BK39-BH39<0,0,BM39-BK39-BI39-BH39) -> 0 | BO39: =ROUND(IF(BN39<=5000000,BN39*5%,IF(AND(BN39>5000000,BN39<=10000000),BN39*10%-250000,IF(AND(BN39>10000000,BN39<=18000000),BN39*15%-750000,IF(AND(BN39>18000000,BN39<=32000000),BN39*20%-1650000,IF(AND(BN39>32000000,BN39<=52000000),BN39*25%-3250000,IF(AND(BN39>52000000,BN39<80000000),BN39*30%-585000,IF(BN39>80000000,BN39*35%-9850000))))))),0) -> 0 | BP39: 35000 | BR39: =AX39-BH39-BO39-BP39 -> 4789664.6 | BS39: 104879687511
A40: TỔNG CỘNG | D40: =SUM(D10:D39) -> 6240 | E40: =SUM(E10:E39) -> 4420.5 | F40: =SUM(F10:F39) -> 1567.5 | G40: =SUM(G10:G39) -> 471 | H40: =SUM(H10:H39) -> 1038.5 | I40: =SUM(I10:I39) -> 435 | J40: =SUM(J10:J39) -> 0 | K40: =SUM(K10:K33) -> 0 | L40: =SUM(L10:L33) -> 0 | M40: =SUM(M10:M33) -> 0 | N40: =SUM(N10:N33) -> 0 | O40: =SUM(O10:O33) -> 0 | P40: =SUM(P10:P33) -> 0 | Q40: =SUM(Q10:Q39) -> 124356000 | R40: =SUM(R10:R39) -> 8800000 | S40: =SUM(S10:S39) -> 0 | T40: =SUM(T10:T39) -> 6900000 | U40: =SUM(U10:U39) -> 1200000 | V40: =SUM(V10:V39) -> 1200000 | W40: =SUM(W10:W39) -> 9000000 | X40: =SUM(X10:X39) -> 8711538.5 | ... BP40: =SUM(BP10:BP39) -> 805000 | BR40: =SUM(BR10:BR39) -> 2.2016565e+08 | BS40: =BR40+'Payroll of factory (SOI) '!BQ27+'Payroll Office'!BO23+'Payroll of factory '!BO22 -> 5.7076869e+08 | BT40: =BR40+'Payroll of factory '!BQ22 -> 2.7216682e+08 | BU40: 6.6963405e+08 | BV40: =BT40-BU40 -> -3.9746723e+08
B42: Scheduling | AH42: Manager | BR42: Director- general
BT47: =BR40+'Payroll of factory (SOI) '!BQ27+'Payroll of factory '!BO22+'Payroll Office'!BO23 -> 5.7076869e+08
