Workbook

Sheet Summary 
B2: Exchange Rate : | AK2: 26115 | AO2: 25695 | AS2: 25670 | AW2: 25550 | BA2: 25550
B3: Month | C3: Dec 2025 | F3: =LEFT(C3,3)&"/"&LEFT(G3,3) -> Dec/Nov | G3: Nov 2025 | J3: =LEFT(G3,3)&"/"&LEFT(K3,3) -> Nov/Oct | K3: Oct 2025 | N3: =LEFT(K3,3)&"/"&LEFT(O3,3) -> Oct/Sep | O3: Sep 2025 | R3: Sep/Aug | S3: 45870 | V3: Aug/Jul | W3: 45839 | Z3: Jul/Jun | AA3: 45809 | AD3: Jun/May | AE3: 45778 | AH3: May/ Apr | AI3: 45748 | AL3: Apr/Mar | AM3: 45717 | AP3: Mar/Feb | AQ3: 45689 | AT3: Feb/Jan | AU3: Jan 2025 | AX3: Jan/Dec 24 | AY3: Dec 2024
B4: Payment | C4: Workers qty | D4: Salary - Net | E4: USD | F4: VND % | G4: Workers qty | H4: Salary - Net | I4: USD | J4: VND % | K4: Workers qty | L4: Salary - Net | M4: USD | N4: VND % | O4: Workers qty | P4: Salary - Net | Q4: USD | R4: VND % | S4: Workers qty | T4: Salary - Net | U4: USD | V4: VND % | W4: Workers qty | X4: Salary - Net | Y4: USD | Z4: VND % | AA4: Workers qty | AB4: Salary - Net | AC4: USD | AD4: VND % | AE4: Workers qty | AF4: Salary - Net | AG4: USD | AH4: VND % | AI4: Workers qty | AJ4: Salary - Net | AK4: USD | AL4: VND % | AM4: Workers qty | AN4: Salary - Net | AO4: USD | AP4: VND % | AQ4: Workers qty | AR4: Salary - Net | AS4: USD | AT4: VND % | AU4: Workers qty | AV4: Salary - Net | AW4: USD | AX4: VND % | AY4: Workers qty | AZ4: Salary - Net | BA4: USD
B5: FACTORY A | AI5: =+COUNTIFS('Salary sheet'!$E$6:$E$1291,$B5) -> 284 | AJ5: =SUMIFS('Salary sheet'!$AT$6:$AT$1291,'Salary sheet'!$E$6:$E$1291,$B5) -> 2557339954 | AK5: =+AJ5/AK$2 -> 97926.094 | AL5: =+AJ5/AN5 -> 0.93402165 | AM5: 292 | AN5: 2737987890 | AO5: 106557.22 | AP5: =+AN5/AR5 -> 1.0615978 | AQ5: 294 | AR5: 2579119677 | AS5: =+AR5/AS$2 -> 100472.13 | AT5: =+AR5/AV5 -> 1.2425969 | AU5: 283 | AV5: 2075588342 | AW5: =+AV5/AW$2 -> 81236.334 | AX5: =+AV5/AZ5 -> 0.66709289 | AY5: 299 | AZ5: 3111393293 | BA5: =+AZ5/BA$2 -> 121776.65
B6: FACTORY B | AI6: =+COUNTIFS('Salary sheet'!$E$6:$E$1291,$B6) -> 179 | AJ6: =SUMIFS('Salary sheet'!$AT$6:$AT$1291,'Salary sheet'!$E$6:$E$1291,$B6) -> 1600986183 | AK6: =+AJ6/AK$2 -> 61305.234 | AL6: =+AJ6/AN6 -> 0.99214116 | AM6: 181 | AN6: 1613667746 | AO6: 62800.846 | AP6: =+AN6/AR6 -> 1.0191866 | AQ6: 183 | AR6: 1583289853 | AS6: =+AR6/AS$2 -> 61678.607 | AT6: =+AR6/AV6 -> 1.4817185 | AU6: 172 | AV6: 1068549731 | AW6: =+AV6/AW$2 -> 41821.907 | AX6: =+AV6/AZ6 -> 0.58605134 | AY6: 176 | AZ6: 1823303950 | BA6: =+AZ6/BA$2 -> 71362.19
B7: FACTORY D | AI7: =+COUNTIFS('Salary sheet'!$E$6:$E$1291,$B7) -> 184 | AJ7: =SUMIFS('Salary sheet'!$AT$6:$AT$1291,'Salary sheet'!$E$6:$E$1291,$B7) -> 1470715569 | AK7: =+AJ7/AK$2 -> 56316.889 | AL7: =+AJ7/AN7 -> 0.98769743 | AM7: 178 | AN7: 1489034513 | AO7: 57950.36 | AP7: =+AN7/AR7 -> 1.0954997 | AQ7: 182 | AR7: 1359228551 | AS7: =+AR7/AS$2 -> 52950.08 | AT7: =+AR7/AV7 -> 1.1558625 | AU7: 183 | AV7: 1175943112 | AW7: =+AV7/AW$2 -> 46025.171 | AX7: =+AV7/AZ7 -> 0.59832064 | AY7: 192 | AZ7: 1965406217 | BA7: =+AZ7/BA$2 -> 76923.922
A8: FACTORY H | B8: FACTORY O | AI8: =+COUNTIFS('Salary sheet'!$E$6:$E$1291,$B8) -> 155 | AJ8: =SUMIFS('Salary sheet'!$AT$6:$AT$1291,'Salary sheet'!$E$6:$E$1291,$B8) -> 1872902206 | AK8: =+AJ8/AK$2 -> 71717.488 | AL8: =+AJ8/AN8 -> 0.9867829 | AM8: 157 | AN8: 1897988109 | AO8: 73866.048 | AP8: =+AN8/AR8 -> 1.0056226 | AQ8: 155 | AR8: 1887376198 | AS8: =+AR8/AS$2 -> 73524.589 | AT8: =+AR8/AV8 -> 1.5306626 | AU8: 154 | AV8: 1233045199 | AW8: =+AV8/AW$2 -> 48260.086 | AX8: =+AV8/AZ8 -> 0.56642305 | AY8: 160 | AZ8: 2176898007 | BA8: =+AZ8/BA$2 -> 85201.488
B9: Foreign Salary SK1 | AI9: 2 | AJ9: =+'Foreign Salary'!$R8+'Foreign Salary'!$R9 -> 363503937 | AK9: =+AJ9/AK$2 -> 13919.354 | AL9: =+AJ9/AN9 -> 1.0152882 | AM9: 2 | AN9: 358030287 | AO9: 13933.85 | AP9: =+AN9/AR9 -> 1.0009108 | AQ9: 2 | AR9: 357704475 | AS9: =+AR9/AS$2 -> 13934.728 | AT9: =+AR9/AV9 -> 0.96952673 | AU9: 2 | AV9: 368947512 | AW9: =+AV9/AW$2 -> 14440.216 | AX9: =+AV9/AZ9 -> 1.2044588 | AY9: 2 | AZ9: 306318075 | BA9: =+AZ9/BA$2 -> 11988.966
B10: Total SK1 | AI10: =SUM(AI5:AI9) -> 804 | AJ10: =SUM(AJ5:AJ9) -> 7865447849 | AK10: =SUM(AK5:AK9) -> 301185.06 | AL10: =+AJ10/AN10 -> 0.97143769 | AM10: =SUM(AM5:AM9) -> 810 | AN10: =SUM(AN5:AN9) -> 8096708545 | AO10: =SUM(AO5:AO9) -> 315108.33 | AP10: =+AN10/AR10 -> 1.0424877 | AQ10: =SUM(AQ5:AQ9) -> 816 | AR10: =SUM(AR5:AR9) -> 7766718754 | AS10: =SUM(AS5:AS9) -> 302560.14 | AT10: =+AR10/AV10 -> 1.3114863 | AU10: =SUM(AU5:AU9) -> 794 | AV10: =SUM(AV5:AV9) -> 5922073896 | AW10: =SUM(AW5:AW9) -> 231783.71 | AX10: =+AV10/D42 -> 0.75292266 | AY10: =SUM(AY5:AY9) -> 829 | AZ10: =SUM(AZ5:AZ9) -> 9383319542 | BA10: =SUM(BA5:BA9) -> 367253.21
B11: %/ Total SNK | AI11: =+AI10/AI16 -> 0.62373933 | AJ11: =+AJ10/AJ16 -> 0.60194504 | AK11: =+AK10/AK16 -> 0.60194504 | AL11: =+AJ11/AN11 -> 0.94901159 | AM11: =+AM10/AM16 -> 0.625966 | AN11: =+AN10/AN16 -> 0.63428629 | AO11: =+AO10/AO16 -> 0.63428629 | AP11: =+AN11/AR11 -> 0.97150395 | AQ11: =+AQ10/AQ16 -> 0.63949843 | AR11: =+AR10/AR16 -> 0.65289111 | AS11: =+AS10/AS16 -> 0.65289111 | AT11: =+AR11/AV11 -> 0.99989139 | AU11: =+AU10/AU16 -> 0.63826367 | AV11: =+AV10/AV16 -> 0.65296202 | AW11: =+AW10/AW16 -> 0.65296202 | AX11: =+AV11/D43 -> 1.0847536 | AY11: =+AY10/AY16 -> 0.6357362 | AZ11: =+AZ10/AZ16 -> 0.63486324 | BA11: =+BA10/BA16 -> 0.63486324
B12: SK2 | AI12: =+COUNTIFS('Salary sheet'!$E$6:$E$1291,$B12) -> 484 | AJ12: =SUMIFS('Salary sheet'!$AT$6:$AT$1291,'Salary sheet'!$E$6:$E$1291,$B12) -> 5084279703 | AK12: =+AJ12/AK$2 -> 194688.1 | AL12: =+AJ12/AN12 -> 1.1156454 | AM12: 483 | AN12: 4557254283 | AO12: 177359.58 | AP12: =+AN12/AR12 -> 1.1365265 | AQ12: 459 | AR12: 4009809182 | AS12: =+AR12/AS$2 -> 156206.05 | AT12: =+AR12/AV12 -> 1.325788 | AU12: 449 | AV12: 3024472478 | AW12: =+AV12/AW$2 -> 118374.66 | AX12: =+AV12/AZ12 -> 0.57160649 | AY12: 474 | AZ12: 5291179390 | BA12: =+AZ12/BA$2 -> 207091.17
B13: Foreign Salary SK2 | AI13: 1 | AJ13: =+'Foreign Salary'!$R10 -> 116993364 | AK13: =+AJ13/AK$2 -> 4479.9297 | AL13: =+AJ13/AN13 -> 1.0529828 | AM13: 1 | AN13: 111106627 | AO13: 4324.0563 | AP13: =+AN13/AR13 -> 0.93086126 | AQ13: 1 | AR13: 119358955 | AS13: =+AR13/AS$2 -> 4649.745 | AT13: =+AR13/AV13 -> 0.97034311 | AU13: 1 | AV13: 123006959 | AW13: =+AV13/AW$2 -> 4814.3624 | AX13: =+AV13/AZ13 -> 1.1652191 | AY13: 1 | AZ13: 105565520 | BA13: =+AZ13/BA$2 -> 4131.7229
B14: Total SK2 | AI14: =SUM(AI12:AI13) -> 485 | AJ14: =SUM(AJ12:AJ13) -> 5201273067 | AK14: =SUM(AK12:AK13) -> 199168.03 | AL14: =+AJ14/AN14 -> 1.114154 | AM14: =SUM(AM12:AM13) -> 484 | AN14: =SUM(AN12:AN13) -> 4668360910 | AO14: =SUM(AO12:AO13) -> 181683.63 | AP14: =+AN14/AR14 -> 1.1305815 | AQ14: =SUM(AQ12:AQ13) -> 460 | AR14: =SUM(AR12:AR13) -> 4129168137 | AS14: =SUM(AS12:AS13) -> 160855.79 | AT14: =+AR14/AV14 -> 1.3118968 | AU14: =SUM(AU12:AU13) -> 450 | AV14: =SUM(AV12:AV13) -> 3147479437 | AW14: =SUM(AW12:AW13) -> 123189.02 | AX14: =+AV14/D46 -> 0.60513636 | AY14: =SUM(AY12:AY13) -> 475 | AZ14: =SUM(AZ12:AZ13) -> 5396744910 | BA14: =SUM(BA12:BA13) -> 211222.89
B15: %/ Total SNK | AI15: =+AI14/AI16 -> 0.37626067 | AJ15: =+AJ14/AJ16 -> 0.39805496 | AK15: =+AK14/AK16 -> 0.39805496 | AL15: =+AJ15/AN15 -> 1.0884332 | AM15: =+AM14/AM16 -> 0.374034 | AN15: =+AN14/AN16 -> 0.36571371 | AO15: =+AO14/AO16 -> 0.36571371 | AP15: =+AN15/AR15 -> 1.0535994 | AQ15: =+AQ14/AQ16 -> 0.36050157 | AR15: =+AR14/AR16 -> 0.34710889 | AS15: =+AS14/AS16 -> 0.34710889 | AT15: =+AR15/AV15 -> 1.0002043 | AU15: =+AU14/AU16 -> 0.36173633 | AV15: =+AV14/AV16 -> 0.34703798 | AW15: =+AW14/AW16 -> 0.34703798 | AX15: =+AV15/D47 -> 0.87183432 | AY15: =+AY14/AY16 -> 0.3642638 | AZ15: =+AZ14/AZ16 -> 0.36513676 | BA15: =+BA14/BA16 -> 0.36513676
B16: G. Total SNK | AI16: =+AI10+AI14 -> 1289 | AJ16: =+AJ14+AJ10 -> 13066720916 | AK16: =+AK14+AK10 -> 500353.09 | AL16: =+AJ16/AN16 -> 1.023631 | AM16: =+AM10+AM14 -> 1294 | AN16: =+AN14+AN10 -> 12765069455 | AO16: =+AO14+AO10 -> 496791.96 | AP16: =+AN16/AR16 -> 1.0730658 | AQ16: =+AQ10+AQ14 -> 1276 | AR16: =+AR14+AR10 -> 11895886891 | AS16: =+AS14+AS10 -> 463415.93 | AT16: =+AR16/AV16 -> 1.3116287 | AU16: =+AU10+AU14 -> 1244 | AV16: =+AV14+AV10 -> 9069553333 | AW16: =+AW14+AW10 -> 354972.73 | AX16: =+AV16/D48 -> 0.69409559 | AY16: =+AY10+AY14 -> 1304 | AZ16: =+AZ10+AZ14 -> 14780064452 | BA16: =+AZ16/BA$2 -> 578476.1
B17: 1st advance Jan 2025 | AV17: 3472403477 | AW17: =+AV17/AW$2 -> 135906.2 | AZ17: 0
B18: Total Salary (net) Jan 2025 | AV18: =+AV17+AV16 -> 12541956810 | AW18: =+AV18/AW$2 -> 490878.94 | AX18: =+AV18/AZ18 -> 0.84857254 | AZ18: =+AZ16 -> 14780064452 | BA18: =+AZ18/BA2 -> 578476.1
AJ19: =+AJ16-'TOTAL(payment)'!L119 -> 0 | AU19: Paid : 1. 13Th month bonus (Transfer 20 Jan):320,410 Usd (Including : Working: $292,479 + Quit $6,216 + Maternity ;$ 6,924 + Foreign $ 14,791) 2. 1ST - Salary Jan (Transfer 20 Jan): 135,906 Usd (Including : Working: $134,677 + Quit $1,229) 3. Balance: 354,973 Usd (Transfer 10 Feb) 4. Total: 811,289 Usd. | AZ19: Remark: 1. Dec salary: $ 509,979 2. Balance annual leave: $ 68,497 (including maternity leave workers) Total pay: $ 578,476
A21: Exchange Rate : | C21: =+C3 -> Dec 2025 | D21: =+E2 -> 0 | G21: =+G3 -> Nov 2025 | H21: =+I2 -> 0 | K21: =+K3 -> Oct 2025 | L21: =+M2 -> 0 | O21: =+O3 -> Sep 2025 | P21: =+Q2 -> 0 | S21: =+S3 -> 45870 | T21: =+U2 -> 0 | W21: =+W3 -> 45839 | X21: =+Y2 -> 0 | AA21: =+AA3 -> 45809 | AB21: =+AC2 -> 0 | AE21: =+AE3 -> 45778 | AF21: =+AG2 -> 0 | AI21: =+AI3 -> 45748 | AJ21: =+AK2 -> 26115 | AM21: =+AM3 -> 45717 | AN21: =+AO2 -> 25695 | AQ21: =+AQ3 -> 45689 | AR21: =+AS2 -> 25670 | AU21: =+AU3 -> Jan 2025 | AV21: =+AW2 -> 25550 | AY21: =+AY3 -> Dec 2024 | AZ21: =+BA2 -> 25550
B22: Payment | C22: Amount (vnd) | D22: Amount (usd) | G22: Amount (vnd) | H22: Amount (usd) | K22: Amount (vnd) | L22: Amount (usd) | O22: Amount (vnd) | P22: Amount (usd) | S22: Amount (vnd) | T22: Amount (usd) | W22: Amount (vnd) | X22: Amount (usd) | AA22: Amount (vnd) | AB22: Amount (usd) | AE22: Amount (vnd) | AF22: Amount (usd) | AI22: Amount (vnd) | AJ22: Amount (usd) | AM22: Amount (vnd) | AN22: Amount (usd) | AQ22: Amount (vnd) | AR22: Amount (usd) | AU22: Amount (vnd) | AV22: Amount (usd) | AY22: Amount (vnd) | AZ22: Amount (usd)
B23: Workers qty | C23: =+C16 -> 0 | G23: =+G16 -> 0 | K23: =+K16 -> 0 | O23: =+O16 -> 0 | S23: =+S16 -> 0 | W23: =+W16 -> 0 | AA23: =+AA16 -> 0 | AE23: =+AE16 -> 0 | AI23: =+AI16 -> 1289 | AM23: =+AM16 -> 1294 | AQ23: =+AQ16 -> 1276 | AU23: =+AU16 -> 1244 | AY23: =+AY16 -> 1304
B24: Audit - Transfer | D24: =+C24/D21 -> #DIV/0! | H24: =+G24/H21 -> #DIV/0! | L24: =+K24/L21 -> #DIV/0! | P24: =+O24/P21 -> #DIV/0! | T24: =+S24/T21 -> #DIV/0! | X24: =+W24/X21 -> #DIV/0! | AB24: =+AA24/AB21 -> #DIV/0! | AI24: 11404670194 | AJ24: =+AI24/AJ21 -> 436709.56 | AM24: 11233667325 | AN24: 437192.73 | AQ24: 10526744334 | AR24: 410079.64 | AU24: 7248978461 | AV24: 283717.36 | AY24: =+[1]Transfer!$E$1297 -> 12386227850 | AZ24: =+AY24/AZ21 -> 484783.87
B25: Audit - Cash | D25: =+C25/D21 -> #DIV/0! | H25: =+G25/H21 -> #DIV/0! | L25: =+K25/L21 -> #DIV/0! | P25: =+O25/P21 -> #DIV/0! | T25: =+S25/T21 -> #DIV/0! | X25: =+W25/X21 -> #DIV/0! | AB25: =+AA25/AB21 -> #DIV/0! | AI25: 39396723 | AJ25: =+AI25/AJ21 -> 1508.586 | AM25: 62018199 | AN25: 2413.6291 | AQ25: 86533289 | AR25: 3370.9891 | AU25: 25112048 | AV25: 982.85902 | AY25: =+[1]Cash!$F$15 -> 101169004 | AZ25: =+AY25/AZ21 -> 3959.6479
B26: Outside - Transfer | D26: =+C26/D21 -> #DIV/0! | H26: =+G26/H21 -> #DIV/0! | L26: =+K26/L21 -> #DIV/0! | P26: =+O26/P21 -> #DIV/0! | T26: =+S26/T21 -> #DIV/0! | X26: =+W26/X21 -> #DIV/0! | AB26: =+AA26/AB21 -> #DIV/0! | AI26: 1139015986 | AJ26: =+AI26/AJ21 -> 43615.393 | AM26: 997637463 | AN26: 38826.132 | AQ26: 795791116 | AR26: 31000.823 | AU26: 1297654296 | AV26: 50788.818 | AY26: =+'[2]Transfer - Outside'!$E$1120 -> 1862073874 | AZ26: =+AY26/AZ21 -> 72879.604
B27: Outside - Cash | D27: =+C27/D21 -> #DIV/0! | H27: =+G27/H21 -> #DIV/0! | L27: =+K27/L21 -> #DIV/0! | P27: =+O27/P21 -> #DIV/0! | T27: =+S27/T21 -> #DIV/0! | X27: =+W27/X21 -> #DIV/0! | AB27: =+AA27/AB21 -> #DIV/0! | AI27: 3140712 | AJ27: =+AI27/AJ21 -> 120.26468 | AM27: 2609554 | AN27: 101.55882 | AQ27: 9754722 | AR27: 380.00475 | AU27: 5854057 | AV27: 229.1216 | AY27: =+'[2]Cash - Outside'!$F$14 -> 18710129 | AZ27: =+AY27/AZ21 -> 732.29468
B28: Total Salary VN | D28: =SUM(D24:D27) -> #DIV/0! | G28: =SUM(G24:G27) -> 0 | H28: =SUM(H24:H27) -> #DIV/0! | K28: =SUM(K24:K27) -> 0 | L28: =SUM(L24:L27) -> #DIV/0! | O28: =SUM(O24:O27) -> 0 | P28: =SUM(P24:P27) -> #DIV/0! | S28: =SUM(S24:S27) -> 0 | T28: =SUM(T24:T27) -> #DIV/0! | W28: =SUM(W24:W27) -> 0 | X28: =SUM(X24:X27) -> #DIV/0! | AA28: =SUM(AA24:AA27) -> 0 | AB28: =SUM(AB24:AB27) -> #DIV/0! | AE28: =SUM(AE24:AE27) -> 0 | AF28: =SUM(AF24:AF27) -> 0 | AI28: =SUM(AI24:AI27) -> 12586223615 | AJ28: =SUM(AJ24:AJ27) -> 481953.8 | AM28: =SUM(AM24:AM27) -> 12295932541 | AN28: =SUM(AN24:AN27) -> 478534.05 | AQ28: =SUM(AQ24:AQ27) -> 11418823461 | AR28: =SUM(AR24:AR27) -> 444831.46 | AU28: =SUM(AU24:AU27) -> 8577598862 | AV28: =SUM(AV24:AV27) -> 335718.16 | AY28: =SUM(AY24:AY27) -> 14368180857 | AZ28: =SUM(AZ24:AZ27) -> 562355.42
B29: Foreign | D29: =+C29/D21 -> #DIV/0! | H29: =+G29/H21 -> #DIV/0! | L29: =+K29/L21 -> #DIV/0! | P29: =+O29/P21 -> #DIV/0! | T29: =+S29/T21 -> #DIV/0! | X29: =+W29/X21 -> #DIV/0! | AB29: =+AA29/AB21 -> #DIV/0! | AI29: 480497301 | AJ29: =+AI29/AJ21 -> 18399.284 | AM29: 469136914 | AN29: 18257.907 | AQ29: 477063430 | AR29: 18584.473 | AU29: =+'[3]Foreign Salary'!V11 -> 491954471 | AV29: =+AU29/AV$21 -> 19254.578 | AY29: 411883595 | AZ29: =+AY29/AZ21 -> 16120.689
B30: Total Slary VN & Foreign | C30: =+C29+C28 -> 0 | D30: =+D29+D28 -> #DIV/0! | G30: =+G29+G28 -> 0 | H30: =+H29+H28 -> #DIV/0! | K30: =+K29+K28 -> 0 | L30: =+L29+L28 -> #DIV/0! | O30: =+O29+O28 -> 0 | P30: =+P29+P28 -> #DIV/0! | S30: =+S29+S28 -> 0 | T30: =+T29+T28 -> #DIV/0! | W30: =+W29+W28 -> 0 | X30: =+X29+X28 -> #DIV/0! | AA30: =+AA29+AA28 -> 0 | AB30: =+AB29+AB28 -> #DIV/0! | AE30: =+AE29+AE28 -> 0 | AF30: =+AF29+AF28 -> 0 | AI30: =+AI29+AI28 -> 13066720916 | AJ30: =+AJ29+AJ28 -> 500353.09 | AM30: =+AM29+AM28 -> 12765069455 | AN30: =+AN29+AN28 -> 496791.96 | AQ30: =+AQ29+AQ28 -> 11895886891 | AR30: =+AR29+AR28 -> 463415.93 | AU30: =+AU29+AU28 -> 9069553333 | AV30: =+AV29+AV28 -> 354972.73 | AY30: =+AY29+AY28 -> 14780064452 | AZ30: =+AZ29+AZ28 -> 578476.1
C31: =+C30-D16 -> 0 | D31: =+D30-E16 -> #DIV/0! | G31: =+G30-H16 -> 0 | H31: =+H30-I16 -> #DIV/0! | K31: =+K30-L16 -> 0 | L31: =+L30-M16 -> #DIV/0! | O31: =+O30-P16 -> 0 | P31: =+P30-Q16 -> #DIV/0! | S31: =+S30-T16 -> 0 | T31: =+T30-U16 -> #DIV/0! | W31: =+W30-X16 -> 0 | X31: =+X30-Y16 -> #DIV/0! | AA31: =+AA30-AB16 -> 0 | AB31: =+AB30-AC16 -> #DIV/0! | AE31: =+AE30-AF16 -> 0 | AF31: =+AF30-AG16 -> 0 | AI31: =+AI30-AJ16 -> 0 | AJ31: =+AJ30-AK16 -> 0 | AM31: =+AM30-AN16 -> 0 | AQ31: =+AQ30-AR16 -> 0
B33: Exchange Rate : | E33: 25550 | I33: 25460 | M33: 25410 | Q33: 24695 | U33: 25000 | Y33: 25400 | AC33: 25473 | AG33: 25474 | AK33: 25435 | AO33: 24915 | AS33: 24770 | AW33: 24525
B34: Month | C34: Dec 2024 | F34: =LEFT(C34,3)&"/"&LEFT(G34,3) -> Dec/Nov | G34: Nov 2024 | J34: =LEFT(G34,3)&"/"&LEFT(K34,3) -> Nov/Oct | K34: Oct 2024 | N34: =LEFT(K34,3)&"/"&LEFT(O34,3) -> Oct/Sep | O34: Sep 2024 | R34: Sep/Aug | S34: Aug 2024 | V34: Aug/Jul | W34: Jul 2024 | Z34: Jul/Jun | AA34: Jun 2024 | AD34: Jun/May | AE34: May 2024 | AH34: May/ Apr | AI34: 45383 | AL34: Apr/Mar | AM34: 45352 | AP34: Mar/Feb | AQ34: 45323 | AT34: Feb/Jan | AU34: 45292 | AX34: Jan/Dec 23
B35: Actual working days | C35: 26 | G35: 26 | K35: 26 | O35: 26 | S35: 26 | W35: 26 | AA35: 26 | AE35: 26 | AI35: 26 | AM35: 26 | AQ35: 26 | AU35: 26
B36: Payment | C36: Workers qty | D36: Salary - Net | E36: USD | F36: VND % | G36: Workers qty | H36: Salary - Net | I36: USD | J36: VND % | K36: Workers qty | L36: Salary - Net | M36: USD | N36: VND % | O36: Workers qty | P36: Salary - Net | Q36: USD | R36: VND % | S36: Workers qty | T36: Salary - Net | U36: USD | V36: VND % | W36: Workers qty | X36: Salary - Net | Y36: USD | Z36: VND % | AA36: Workers qty | AB36: Salary - Net | AC36: USD | AD36: VND % | AE36: Workers qty | AF36: Salary - Net | AG36: USD | AH36: VND % | AI36: Workers qty | AJ36: Salary - Net | AK36: USD | AL36: VND % | AM36: Workers qty | AN36: Salary - Net | AO36: USD | AP36: VND % | AQ36: Workers qty | AR36: Salary - Net | AS36: USD | AT36: VND % | AU36: Workers qty | AV36: Salary - Net | AW36: USD | AX36: VND %
B37: FACTORY A | C37: =COUNTIFS('Salary sheet'!$E$6:$E$1291,'Summary '!$B37) -> 284 | D37: =SUMIFS('Salary sheet'!$AT$6:$AT$1291,'Salary sheet'!$E$6:$E$1291,'Summary '!$B37) -> 2557339954 | E37: =+D37/E$33 -> 100091.58 | F37: =+D37/H37 -> 0.99923511 | G37: 284 | H37: 2559297530 | I37: =+H37/I$33 -> 100522.29 | J37: =+H37/L37 -> 0.76376754 | K37: 280 | L37: 3350885451 | M37: =+L37/M$33 -> 131872.71 | N37: =+L37/P37 -> 1.210269 | O37: 275 | P37: 2768711215 | Q37: =+P37/Q$33 -> 112116.27 | R37: =+P37/T37 -> 0.99547932 | S37: 268 | T37: 2781284525 | U37: =+T37/U$33 -> 111251.38 | V37: =+T37/X37 -> 1.0905772 | W37: 276 | X37: 2550286758 | Y37: =+X37/Y$33 -> 100404.99 | Z37: =+X37/AB37 -> 1.3131807 | AA37: 279 | AB37: 1942068482 | AC37: =+AB37/AC$33 -> 76240.273 | AD37: =+AB37/AF37 -> 0.83625026 | AE37: 278 | AF37: 2322353211 | AG37: 91165.628 | AH37: =+AF37/AJ37 -> 1.0947982 | AI37: 286 | AJ37: 2121261444 | AK37: =+AJ37/AK$33 -> 83399.31 | AL37: =+AJ37/AN37 -> 0.90816188 | AM37: 283 | AN37: 2335774601 | AO37: 93749.733 | AP37: =+AN37/AR37 -> 1.3542485 | AQ37: 283 | AR37: 1724775425 | AS37: =+AR37/AS$33 -> 69631.628 | AT37: =+AR37/AV37 -> 0.45422459 | AU37: 284 | AV37: 3797186401 | AW37: =+AV37/AW$33 -> 154829.21 | AX37: =+AV37/C69 -> 1.5147269
B38: FACTORY B | C38: =COUNTIFS('Salary sheet'!$E$6:$E$1291,'Summary '!$B38) -> 179 | D38: =SUMIFS('Salary sheet'!$AT$6:$AT$1291,'Salary sheet'!$E$6:$E$1291,'Summary '!$B38) -> 1600986183 | E38: =+D38/E$33 -> 62660.907 | F38: =+D38/H38 -> 1.0189403 | G38: 176 | H38: 1571226754 | I38: =+H38/I$33 -> 61713.541 | J38: =+H38/L38 -> 0.83445991 | K38: 175 | L38: 1882926592 | M38: =+L38/M$33 -> 74101.794 | N38: =+L38/P38 -> 0.99921757 | O38: 179 | P38: 1884401007 | Q38: =+P38/Q$33 -> 76306.986 | R38: =+P38/T38 -> 1.1920416 | S38: 166 | T38: 1580818209 | U38: =+T38/U$33 -> 63232.728 | V38: =+T38/X38 -> 1.1442225 | W38: 154 | X38: 1381565351 | Y38: =+X38/Y$33 -> 54392.337 | Z38: =+X38/AB38 -> 1.1405857 | AA38: 151 | AB38: 1211277153 | AC38: =+AB38/AC$33 -> 47551.413 | AD38: =+AB38/AF38 -> 0.92195726 | AE38: 159 | AF38: 1313810533 | AG38: 51574.568 | AH38: =+AF38/AJ38 -> 1.1575076 | AI38: 149 | AJ38: 1135034061 | AK38: =+AJ38/AK$33 -> 44624.889 | AL38: =+AJ38/AN38 -> 0.97302649 | AM38: 146 | AN38: 1166498628 | AO38: 46819.13 | AP38: =+AN38/AR38 -> 1.2683849 | AQ38: 138 | AR38: 919672454 | AS38: =+AR38/AS$33 -> 37128.48 | AT38: =+AR38/AV38 -> 0.50498659 | AU38: 129 | AV38: 1821181916 | AW38: =+AV38/AW$33 -> 74258.182 | AX38: =+AV38/C70 -> 1.5029032
B39: FACTORY D | C39: =COUNTIFS('Salary sheet'!$E$6:$E$1291,'Summary '!$B39) -> 184 | D39: =SUMIFS('Salary sheet'!$AT$6:$AT$1291,'Salary sheet'!$E$6:$E$1291,'Summary '!$B39) -> 1470715569 | E39: =+D39/E$33 -> 57562.253 | F39: =+D39/H39 -> 0.88311721 | G39: 189 | H39: 1665368487 | I39: =+H39/I$33 -> 65411.174 | J39: =+H39/L39 -> 0.85546819 | K39: 190 | L39: 1946733389 | M39: =+L39/M$33 -> 76612.884 | N39: =+L39/P39 -> 1.0779244 | O39: 183 | P39: 1806001732 | Q39: =+P39/Q$33 -> 73132.283 | R39: =+P39/T39 -> 1.0681507 | S39: 172 | T39: 1690774336 | U39: =+T39/U$33 -> 67630.973 | V39: =+T39/X39 -> 0.9885454 | W39: 175 | X39: 1710365888 | Y39: =+X39/Y$33 -> 67337.24 | Z39: =+X39/AB39 -> 1.2684615 | AA39: 180 | AB39: 1348378264 | AC39: =+AB39/AC$33 -> 52933.626 | AD39: =+AB39/AF39 -> 0.77249546 | AE39: 188 | AF39: 1745483744 | AG39: 68520.207 | AH39: =+AF39/AJ39 -> 1.1435757 | AI39: 205 | AJ39: 1526338648 | AK39: =+AJ39/AK$33 -> 60009.383 | AL39: =+AJ39/AN39 -> 1.0036466 | AM39: 199 | AN39: 1520792976 | AO39: 61039.252 | AP39: =+AN39/AR39 -> 1.2604651 | AQ39: 188 | AR39: 1206533181 | AS39: =+AR39/AS$33 -> 48709.454 | AT39: =+AR39/AV39 -> 0.46778096 | AU39: 194 | AV39: 2579269513 | AW39: =+AV39/AW$33 -> 105168.99 | AX39: =+AV39/C71 -> 1.5996359
A40: FACTORY H | B40: FACTORY O | C40: =COUNTIFS('Salary sheet'!$E$6:$E$1291,'Summary '!$B40) -> 155 | D40: =SUMIFS('Salary sheet'!$AT$6:$AT$1291,'Salary sheet'!$E$6:$E$1291,'Summary '!$B40) -> 1872902206 | E40: =+D40/E$33 -> 73303.413 | F40: =+D40/H40 -> 1.0410426 | G40: 156 | H40: 1799064027 | I40: =+H40/I$33 -> 70662.373 | J40: =+H40/L40 -> 0.89633304 | K40: 160 | L40: 2007137919 | M40: =+L40/M$33 -> 78990.079 | N40: =+L40/P40 -> 1.0470994 | O40: 160 | P40: 1916855199 | Q40: =+P40/Q$33 -> 77621.186 | R40: =+P40/T40 -> 0.92674332 | S40: 160 | T40: 2068377682 | U40: =+T40/U$33 -> 82735.107 | V40: =+T40/X40 -> 1.0534306 | W40: 158 | X40: 1963468458 | Y40: =+X40/Y$33 -> 77301.908 | Z40: =+X40/AB40 -> 1.128515 | AA40: 154 | AB40: 1739869178 | AC40: =+AB40/AC$33 -> 68302.484 | AD40: =+AB40/AF40 -> 0.95925352 | AE40: 154 | AF40: 1813774087 | AG40: 71200.993 | AH40: =+AF40/AJ40 -> 1.0596974 | AI40: 152 | AJ40: 1711596163 | AK40: =+AJ40/AK$33 -> 67292.949 | AL40: =+AJ40/AN40 -> 1.0303208 | AM40: 157 | AN40: 1661226461 | AO40: 66675.756 | AP40: =+AN40/AR40 -> 1.144399 | AQ40: 151 | AR40: 1451614713 | AS40: =+AR40/AS$33 -> 58603.743 | AT40: =+AR40/AV40 -> 0.47044582 | AU40: 150 | AV40: 3085615057 | AW40: =+AV40/AW$33 -> 125815.09 | AX40: =+AV40/C72 -> 1.5996506
B41: Foreign Salary SK1 | C41: 2 | D41: =+'Foreign Salary'!$R8+'Foreign Salary'!$R9 -> 363503937 | E41: =+D41/E$33 -> 14227.16 | F41: =+D41/H41 -> 1.1905645 | G41: 2 | H41: 305320650 | I41: =+H41/I$33 -> 11992.17 | J41: =+H41/L41 -> 0.96743673 | K41: 2 | L41: 315597537 | M41: =+L41/M$33 -> 12420.21 | N41: =+L41/P41 -> 1.0687261 | O41: 2 | P41: 295302537 | Q41: =+P41/Q$33 -> 11957.989 | R41: =+P41/T41 -> 0.95462449 | S41: 2 | T41: 309338950 | U41: =+T41/U$33 -> 12373.558 | V41: =+T41/X41 -> 0.98533648 | W41: 2 | X41: 313942450 | Y41: =+X41/Y$33 -> 12359.939 | Z41: =+X41/AB41 -> 1.0284478 | AA41: 2 | AB41: 305258522 | AC41: =+AB41/AC$33 -> 11983.611 | AD41: =+AB41/AF41 -> 0.96561716 | AE41: 2 | AF41: 316127897 | AG41: 12409.826 | AH41: =+AF41/AJ41 -> 1.0370378 | AI41: 2 | AJ41: 304837387 | AK41: =+AJ41/AK$33 -> 11984.957 | AL41: =+AJ41/AN41 -> 1.0192691 | AM41: 2 | AN41: 299074487 | AO41: 12235.095 | AP41: =+AN41/AR41 -> 1.0054021 | AQ41: 2 | AR41: 297467525 | AS41: =+AR41/AS$33 -> 12009.186 | AT41: =+AR41/AV41 -> 0.5155377 | AU41: 2 | AV41: 577004406 | AW41: =+AV41/AW$33 -> 23527.193 | AX41: =+AV41/C73 -> 1.9705568
B42: Total SK1 | C42: =SUM(C37:C41) -> 804 | D42: =SUM(D37:D41) -> 7865447849 | E42: =SUM(E37:E41) -> 307845.32 | F42: =+D42/H42 -> 0.99559134 | G42: =SUM(G37:G41) -> 807 | H42: =SUM(H37:H41) -> 7900277448 | I42: =SUM(I37:I41) -> 310301.55 | J42: =+H42/L42 -> 0.83132105 | K42: =SUM(K37:K41) -> 807 | L42: =SUM(L37:L41) -> 9503280888 | M42: =SUM(M37:M41) -> 373997.67 | N42: =+L42/P42 -> 1.0959501 | O42: =SUM(O37:O41) -> 799 | P42: =SUM(P37:P41) -> 8671271690 | Q42: =SUM(Q37:Q41) -> 351134.71 | R42: =+P42/T42 -> 1.0285482 | S42: =SUM(S37:S41) -> 768 | T42: =SUM(T37:T41) -> 8430593702 | U42: =SUM(U37:U41) -> 337223.75 | V42: =+T42/X42 -> 1.0645188 | W42: =SUM(W37:W41) -> 765 | X42: =SUM(X37:X41) -> 7919628905 | Y42: =SUM(Y37:Y41) -> 311796.41 | Z42: =+X42/AB42 -> 1.2096851 | AA42: =SUM(AA37:AA41) -> 766 | AB42: =SUM(AB37:AB41) -> 6546851599 | AC42: =SUM(AC37:AC41) -> 257011.41 | AD42: =+AB42/AF42 -> 0.87157139 | AE42: =SUM(AE37:AE41) -> 781 | AF42: =SUM(AF37:AF41) -> 7511549472 | AG42: =SUM(AG37:AG41) -> 294871.22 | AH42: =+AF42/AJ42 -> 1.1047911 | AI42: =SUM(AI37:AI41) -> 794 | AJ42: =SUM(AJ37:AJ41) -> 6799067703 | AK42: =SUM(AK37:AK41) -> 267311.49 | AL42: =+AJ42/AN42 -> 0.9736088 | AM42: =SUM(AM37:AM41) -> 787 | AN42: =SUM(AN37:AN41) -> 6983367153 | AO42: =SUM(AO37:AO41) -> 280518.97 | AP42: =+AN42/AR42 -> 1.2470158 | AQ42: =SUM(AQ37:AQ41) -> 762 | AR42: =SUM(AR37:AR41) -> 5600063298 | AS42: =SUM(AS37:AS41) -> 226082.49 | AT42: =+AR42/AV42 -> 0.47217047 | AU42: =SUM(AU37:AU41) -> 759 | AV42: =SUM(AV37:AV41) -> 11860257293 | AW42: =SUM(AW37:AW41) -> 483598.67 | AX42: =+AV42/C74 -> 1.5703178
B43: %/ Total SNK | C43: =+C42/C48 -> 0.62373933 | D43: =+D42/D48 -> 0.60194504 | E43: =+E42/E48 -> 0.60194504 | G43: =+G42/G48 -> 0.624613 | H43: =+H42/H48 -> 0.6287349 | I43: =+I42/I48 -> 0.6287349 | K43: =+K42/K48 -> 0.6236476 | L43: =+L42/L48 -> 0.65573114 | M43: =+M42/M48 -> 0.65573114 | O43: =+O42/O48 -> 0.62913386 | P43: =+P42/P48 -> 0.63335215 | Q43: =+Q42/Q48 -> 0.63335215 | S43: =+S42/S48 -> 0.62693878 | T43: =+T42/T48 -> 0.61244505 | U43: =+U42/U48 -> 0.61244505 | W43: =+W42/W48 -> 0.62859491 | X43: =+X42/X48 -> 0.60180683 | Y43: =+Y42/Y48 -> 0.60180683 | AA43: =+AA42/AA48 -> 0.63253509 | AB43: =+AB42/AB48 -> 0.60725431 | AC43: =+AC42/AC48 -> 0.60725431 | AE43: =+AE42/AE48 -> 0.63444354 | AF43: =+AF42/AF48 -> 0.60886068 | AG43: =+AG42/AG48 -> 0.60886068 | AI43: =+AI42/AI48 -> 0.63367917 | AJ43: =+AJ42/AJ48 -> 0.60390815 | AK43: =+AK42/AK48 -> 0.60390815 | AM43: =+AM42/AM48 -> 0.63010408 | AN43: =+AN42/AN48 -> 0.63871048 | AO43: =+AO42/AO48 -> 0.63923756 | AP43: =+AN43/AR43 -> 1.0061164 | AQ43: =+AQ42/AQ48 -> 0.6387259 | AR43: =+AR42/AR48 -> 0.63482763 | AS43: =+AS42/AS48 -> 0.63482763 | AT43: =+AR43/AV43 -> 0.98830034 | AU43: =+AU42/AU48 -> 0.64816396 | AV43: =+AV42/AV48 -> 0.64234282 | AW43: =+AW42/AW48 -> 0.64234282 | AX43: =+AV43/C75 -> 1.0221616
B44: SK2 | C44: =COUNTIFS('Salary sheet'!$E$6:$E$1291,'Summary '!$B44) -> 484 | D44: =SUMIFS('Salary sheet'!$AT$6:$AT$1291,'Salary sheet'!$E$6:$E$1291,'Summary '!$B44) -> 5084279703 | E44: =+D44/E$33 -> 198993.33 | F44: =+D44/H44 -> 1.1150112 | G44: 484 | H44: 4559846271 | I44: =+H44/I$33 -> 179098.44 | J44: =+H44/L44 -> 0.93426132 | K44: 486 | L44: 4880696864 | M44: =+L44/M$33 -> 192077.8 | N44: =+L44/P44 -> 0.99253436 | O44: 470 | P44: 4917408448 | Q44: =+P44/Q$33 -> 199125.67 | R44: =+P44/T44 -> 0.94062958 | S44: 456 | T44: 5227784187 | U44: =+T44/U$33 -> 209111.37 | V44: =+T44/X44 -> 1.0187651 | W44: 451 | X44: 5131491174 | Y44: =+X44/Y$33 -> 202027.21 | Z44: =+X44/AB44 -> 1.2430118 | AA44: 444 | AB44: 4128272152 | AC44: =+AB44/AC$33 -> 162064.62 | AD44: =+AB44/AF44 -> 0.87538983 | AE44: 449 | AF44: 4715924287 | AG44: 185126.96 | AH44: =+AF44/AJ44 -> 1.0832308 | AI44: 458 | AJ44: 4353573029 | AK44: =+AJ44/AK$33 -> 171164.66 | AL44: =+AJ44/AN44 -> 1.1318871 | AM44: 461 | AN44: 3846296324 | AO44: 154376.73 | AP44: =+AN44/AR44 -> 1.2335824 | AQ44: 430 | AR44: 3117988940 | AS44: =+AR44/AS$33 -> 125877.63 | AT44: =+AR44/AV44 -> 0.4868943 | AU44: 411 | AV44: 6403831208 | AW44: =+AV44/AW$33 -> 261114.42 | AX44: =+AV44/C76 -> 1.4658862
B45: Foreign Salary SK2 | C45: 1 | D45: =+'Foreign Salary'!$R10 -> 116993364 | E45: =+D45/E$33 -> 4578.9966 | F45: =+D45/H45 -> 1.1117687 | G45: 1 | H45: 105231744 | I45: =+H45/I$33 -> 4133.2185 | J45: =+H45/L45 -> 0.96835361 | K45: 1 | L45: 108670782 | M45: =+L45/M$33 -> 4276.6935 | N45: =+L45/P45 -> 1.0612936 | O45: 1 | P45: 102394644 | Q45: =+P45/Q$33 -> 4146.3715 | R45: =+P45/T45 -> 0.95613931 | S45: 1 | T45: 107091763 | U45: =+T45/U$33 -> 4283.6705 | V45: =+T45/X45 -> 0.98581908 | W45: 1 | X45: 108632269 | Y45: =+X45/Y$33 -> 4276.861 | Z45: =+X45/AB45 -> 1.0253468 | AA45: 1 | AB45: 105946855 | AC45: =+AB45/AC$33 -> 4159.1825 | AD45: =+AB45/AF45 -> 0.96680809 | AE45: 1 | AF45: 109584163 | AG45: 4301.8043 | AH45: =+AF45/AJ45 -> 1.0357091 | AI45: 1 | AJ45: 105805928 | AK45: =+AJ45/AK$33 -> 4159.8556 | AL45: =+AJ45/AN45 -> 1.018565 | AM45: 1 | AN45: 103877442 | AO45: 4246.6758 | AP45: =+AN45/AR45 -> 1.0052037 | AQ45: 1 | AR45: 103339691 | AS45: =+AR45/AS$33 -> 4171.9698 | AT45: =+AR45/AV45 -> 0.51676808 | AU45: 1 | AV45: 199973054 | AW45: =+AV45/AW$33 -> 8153.8452 | AX45: =+AV45/C77 -> 2.0531134
B46: Total SK2 | C46: =SUM(C44:C45) -> 485 | D46: =SUM(D44:D45) -> 5201273067 | E46: =SUM(E44:E45) -> 203572.33 | F46: =+D46/H46 -> 1.1149381 | G46: =SUM(G44:G45) -> 485 | H46: =SUM(H44:H45) -> 4665078015 | I46: =SUM(I44:I45) -> 183231.66 | J46: =+H46/L46 -> 0.93500386 | K46: =SUM(K44:K45) -> 487 | L46: =SUM(L44:L45) -> 4989367646 | M46: =SUM(M44:M45) -> 196354.49 | N46: =+L46/P46 -> 0.99393692 | O46: =SUM(O44:O45) -> 471 | P46: =SUM(P44:P45) -> 5019803092 | Q46: =SUM(Q44:Q45) -> 203272.04 | R46: =+P46/T46 -> 0.94094092 | S46: =SUM(S44:S45) -> 457 | T46: =SUM(T44:T45) -> 5334875950 | U46: =SUM(U44:U45) -> 213395.04 | V46: =+T46/X46 -> 1.0180821 | W46: =SUM(W44:W45) -> 452 | X46: =SUM(X44:X45) -> 5240123443 | Y46: =SUM(Y44:Y45) -> 206304.07 | Z46: =+X46/AB46 -> 1.2375655 | AA46: =SUM(AA44:AA45) -> 445 | AB46: =SUM(AB44:AB45) -> 4234219007 | AC46: =SUM(AC44:AC45) -> 166223.81 | AD46: =+AB46/AF46 -> 0.87746588 | AE46: =SUM(AE44:AE45) -> 450 | AF46: =SUM(AF44:AF45) -> 4825508450 | AG46: =SUM(AG44:AG45) -> 189428.77 | AH46: =+AF46/AJ46 -> 1.0821032 | AI46: =SUM(AI44:AI45) -> 459 | AJ46: =SUM(AJ44:AJ45) -> 4459378957 | AK46: =SUM(AK44:AK45) -> 175324.51 | AL46: =+AJ46/AN46 -> 1.128907 | AM46: =SUM(AM44:AM45) -> 462 | AN46: =SUM(AN44:AN45) -> 3950173766 | AO46: =SUM(AO44:AO45) -> 158623.41 | AP46: =+AN46/AR46 -> 1.2262561 | AQ46: =SUM(AQ44:AQ45) -> 431 | AR46: =SUM(AR44:AR45) -> 3221328631 | AS46: =SUM(AS44:AS45) -> 130049.6 | AT46: =+AR46/AV46 -> 0.48779893 | AU46: =SUM(AU44:AU45) -> 412 | AV46: =SUM(AV44:AV45) -> 6603804262 | AW46: =SUM(AW44:AW45) -> 269268.27 | AX46: =+AV46/C78 -> 1.4786932
B47: %/ Total SNK | C47: =+C46/C48 -> 0.37626067 | D47: =+D46/D48 -> 0.39805496 | E47: =+E46/E48 -> 0.39805496 | G47: =+G46/G48 -> 0.375387 | H47: =+H46/H48 -> 0.3712651 | I47: =+I46/I48 -> 0.3712651 | K47: =+K46/K48 -> 0.3763524 | L47: =+L46/L48 -> 0.34426886 | M47: =+M46/M48 -> 0.34426886 | O47: =+O46/O48 -> 0.37086614 | P47: =+P46/P48 -> 0.36664785 | Q47: =+Q46/Q48 -> 0.36664785 | S47: =+S46/S48 -> 0.37306122 | T47: =+T46/T48 -> 0.38755495 | U47: =+U46/U48 -> 0.38755495 | W47: =+W46/W48 -> 0.37140509 | X47: =+X46/X48 -> 0.39819317 | Y47: =+Y46/Y48 -> 0.39819317 | AA47: =+AA46/AA48 -> 0.36746491 | AB47: =+AB46/AB48 -> 0.39274569 | AC47: =+AC46/AC48 -> 0.39274569 | AE47: =+AE46/AE48 -> 0.36555646 | AF47: =+AF46/AF48 -> 0.39113932 | AG47: =+AG46/AG48 -> 0.39113932 | AI47: =+AI46/AI48 -> 0.36632083 | AJ47: =+AJ46/AJ48 -> 0.39609185 | AK47: =+AK46/AK48 -> 0.39609185 | AM47: =+AM46/AM48 -> 0.36989592 | AN47: =+AN46/AN48 -> 0.36128952 | AO47: =+AO46/AO48 -> 0.3614659 | AP47: =+AN47/AR47 -> 0.98936707 | AQ47: =+AQ46/AQ48 -> 0.3612741 | AR47: =+AR46/AR48 -> 0.36517237 | AS47: =+AS46/AS48 -> 0.36517237 | AT47: =+AR47/AV47 -> 1.0210123 | AU47: =+AU46/AU48 -> 0.35183604 | AV47: =+AV46/AV48 -> 0.35765718 | AW47: =+AW46/AW48 -> 0.35765718 | AX47: =+AV47/C79 -> 0.96252072
B48: G. Total SNK | C48: =+C42+C46 -> 1289 | D48: =+D42+D46 -> 13066720916 | E48: =+D48/E$33 -> 511417.65 | F48: =+D48/H48 -> 1.0399006 | G48: =+G42+G46 -> 1292 | H48: =+H42+H46 -> 12565355463 | I48: =+H48/I$33 -> 493533.21 | J48: =+H48/L48 -> 0.86701581 | K48: =+K42+K46 -> 1294 | L48: =+L42+L46 -> 14492648534 | M48: =+L48/M$33 -> 570352.17 | N48: =+L48/P48 -> 1.0585472 | O48: =+O42+O46 -> 1270 | P48: =+P42+P46 -> 13691074782 | Q48: =+P48/Q$33 -> 554406.75 | R48: =+P48/T48 -> 0.99459554 | S48: =+S42+S46 -> 1225 | T48: =+T42+T46 -> 13765469652 | U48: =+T48/U$33 -> 550618.79 | V48: =+T48/X48 -> 1.046028 | W48: =+W42+W46 -> 1217 | X48: =+X42+X46 -> 13159752348 | Y48: =+X48/Y$33 -> 518100.49 | Z48: =+X48/AB48 -> 1.220635 | AA48: =+AA42+AA46 -> 1211 | AB48: =+AB42+AB46 -> 10781070606 | AC48: =+AB48/AC$33 -> 423235.21 | AD48: =+AB48/AF48 -> 0.87387695 | AE48: =+AE42+AE46 -> 1231 | AF48: =+AF42+AF46 -> 12337057922 | AG48: =+AF48/AG$33 -> 484299.99 | AH48: =+AF48/AJ48 -> 1.0958046 | AI48: =+AI42+AI46 -> 1253 | AJ48: =+AJ42+AJ46 -> 11258446660 | AK48: =+AJ48/AK$33 -> 442636 | AL48: =+AJ48/AN48 -> 1.0297164 | AM48: =+AM42+AM46 -> 1249 | AN48: =+AN42+AN46 -> 10933540919 | AO48: =+AN48/AO$33 -> 438833.67 | AP48: =+AN48/AR48 -> 1.2394349 | AQ48: =+AQ42+AQ46 -> 1193 | AR48: =+AR42+AR46 -> 8821391929 | AS48: =+AR48/AS$33 -> 356132.09 | AT48: =+AR48/AV48 -> 0.4777601 | AU48: =+AU42+AU46 -> 1171 | AV48: =+AV42+AV46 -> 18464061555 | AW48: =+AV48/AW$33 -> 752866.93 | AX48: =+AV48/C80 -> 1.5362716
D49: Remark: 1. Dec salary: $ 509,979 2. Balance annual leave: $ 68,497 (including maternity leave workers) Total pay: $ 578,476 | AU49: Paid : 1. 13Th month bonus (Transfer 02 Feb): 315,534.52 Usd 2. 1ST - Salary Jan (Transfer 05 Feb): 325,644.39 Usd 3. Balance: 111,688.02 Usd (Transfer 23 Feb)
AL50: =0.35*170 -> 59.5
A51: Exchange Rate : | C51: =+C34 -> Dec 2024 | D51: =+E33 -> 25550 | G51: =+G34 -> Nov 2024 | H51: =+I33 -> 25460 | K51: =+K34 -> Oct 2024 | L51: =+M33 -> 25410 | O51: =+O34 -> Sep 2024 | P51: =+Q33 -> 24695 | S51: =+S34 -> Aug 2024 | T51: =+U33 -> 25000 | W51: =+W34 -> Jul 2024 | X51: =+Y33 -> 25400 | AA51: =+AA34 -> Jun 2024 | AB51: =+AC33 -> 25473 | AE51: =+AE34 -> May 2024 | AF51: =+AG33 -> 25474 | AI51: =+AI34 -> 45383 | AJ51: =+AK33 -> 25435 | AM51: =+AM34 -> 45352 | AN51: =+AO33 -> 24915 | AQ51: =+AQ34 -> 45323 | AR51: =+AS33 -> 24770 | AU51: =+AU34 -> 45292 | AV51: =+AW33 -> 24525
B52: Payment | C52: Amount (vnd) | D52: Amount (usd) | G52: Amount (vnd) | H52: Amount (usd) | K52: Amount (vnd) | L52: Amount (usd) | O52: Amount (vnd) | P52: Amount (usd) | S52: Amount (vnd) | T52: Amount (usd) | W52: Amount (vnd) | X52: Amount (usd) | AA52: Amount (vnd) | AB52: Amount (usd) | AE52: Amount (vnd) | AF52: Amount (usd) | AI52: Amount (vnd) | AJ52: Amount (usd) | AM52: Amount (vnd) | AN52: Amount (usd) | AQ52: Amount (vnd) | AR52: Amount (usd) | AU52: Amount (vnd) | AV52: Amount (usd)
B53: Workers qty | C53: =+C48 -> 1289 | G53: =+G48 -> 1292 | K53: =+K48 -> 1294 | O53: =+O48 -> 1270 | S53: =+S48 -> 1225 | W53: =+W48 -> 1217 | AA53: =+AA48 -> 1211 | AE53: =+AE48 -> 1231 | AI53: =+AI48 -> 1253 | AM53: =+AM48 -> 1249 | AQ53: =+AQ48 -> 1193 | AU53: =+AU48 -> 1171
B54: Audit - Transfer | C54: 12386227850 | D54: 484783.87 | G54: 10763005074 | H54: 422741.75 | K54: 11492843309 | L54: 452296.08 | O54: 10953347536 | P54: 443545.15 | S54: 11330394226 | T54: 453215.77 | W54: 11190379007 | X54: 440566.1 | AA54: 10015722102 | AB54: 393189.73 | AE54: 10547466313 | AF54: 414048.3 | AI54: 10453244284 | AJ54: 410978.74 | AM54: 10076082070 | AN54: 404418.31 | AQ54: 8316053573 | AR54: 335730.87 | AU54: 2372779894 | AV54: 96749.435
B55: Audit - Cash | C55: 101169004 | D55: 3959.6479 | G55: 60868160 | H55: 2390.7368 | K55: 130940566 | L55: 5153.1116 | O55: 67869866 | P55: 2748.3242 | S55: 41959971 | T55: 1678.3988 | W55: 44404583 | X55: 1748.2119 | AA55: 39783045 | AB55: 1561.7731 | AE55: 215764202 | AF55: 8469.9773 | AI55: 64339995 | AJ55: 2529.585 | AM55: 102988228 | AN55: 4133.5833 | AQ55: 80202175 | AR55: 3237.8755 | AU55: 1127788 | AV55: 45.98524
B56: Outside - Transfer | C56: 1862073874 | D56: 72879.604 | G56: 1324894873 | H56: 52038.29 | K56: 2423772440 | L56: 95386.558 | O56: 2257274444 | P56: 91406.133 | S56: 1969344799 | T56: 78773.792 | W56: 1496192404 | X56: 58905.213 | AA56: 313957782 | AB56: 12325.12 | AE56: 1126799307 | AF56: 44233.309 | AI56: 324977734 | AJ56: 12776.793 | AM56: 348545986 | AN56: 13989.403 | AQ56: 24328965 | AR56: 982.19479 | AU56: 365240980 | AV56: 14892.599
B57: Outside - Cash | C57: 18710129 | D57: 732.29468 | G57: 6034962 | H57: 237.037 | K57: 20823900 | L57: 819.51594 | O57: 14885755 | P57: 602.78417 | S57: 7339943 | T57: 293.59772 | W57: 6201635 | X57: 244.15886 | AA57: 402300 | AB57: 15.793193 | AE57: 21316040 | AF57: 836.77632 | AI57: 5241332 | AJ57: 206.0677 | AM57: 2972706 | AN57: 119.31391 | AQ57: 0 | AR57: 0 | AU57: 0 | AV57: 0
B58: Total Salary VN | C58: 14368180857 | D58: 562355.42 | G58: 12154803069 | H58: 477407.82 | K58: 14068380215 | L58: 553655.26 | O58: 13293377601 | P58: 538302.39 | S58: 13349038939 | T58: 533961.56 | W58: 12737177629 | X58: 501463.69 | AA58: 10369865229 | AB58: 407092.42 | AE58: 11911345862 | AF58: 467588.36 | AI58: 10847803345 | AJ58: 426491.19 | AM58: 10530588990 | AN58: 422660.61 | AQ58: 8420584713 | AR58: 339950.94 | AU58: 2739148662 | AV58: 111688.02
B59: Foreign | C59: 411883595 | D59: 16120.689 | G59: 410552394 | H59: 16125.389 | K59: 424268319 | L59: 16696.904 | O59: 397697181 | P59: 16104.36 | S59: 416430713 | T59: 16657.229 | W59: 422574719 | X59: 16636.8 | AA59: 411205377 | AB59: 16142.793 | AE59: 425712060 | AF59: 16711.63 | AI59: 410643315 | AJ59: 16144.813 | AM59: 402951929 | AN59: 16173.066 | AQ59: 400807216 | AR59: 16181.155 | AU59: 0 | AV59: 0
B60: Total Slary VN & Foreign | C60: 14780064452 | D60: 578476.1 | G60: 12565355463 | H60: 493533.21 | K60: 14492648534 | L60: 570352.17 | O60: 13691074782 | P60: 554406.75 | S60: 13765469652 | T60: 550618.79 | W60: 13159752348 | X60: 518100.49 | AA60: 10781070606 | AB60: 423235.21 | AE60: 12337057922 | AF60: 484299.99 | AI60: 11258446660 | AJ60: 442636 | AM60: 10933540919 | AN60: 438833.67 | AQ60: 8821391929 | AR60: 356132.09 | AU60: 2739148662 | AV60: 111688.02
C61: =+C60-D48 -> 1713343536 | D61: =+D60-E48 -> 67058.455 | G61: =+G60-H48 -> 0 | H61: =+H60-I48 -> 0 | K61: =+K60-L48 -> 0 | L61: =+L60-M48 -> 0 | O61: =+O60-P48 -> 0 | P61: =+P60-Q48 -> 0 | S61: =+S60-T48 -> 0 | T61: =+T60-U48 -> 0 | W61: =+W60-X48 -> 0 | X61: =+X60-Y48 -> 0 | AA61: =+AA60-AB48 -> 0 | AB61: =+AB60-AC48 -> 0 | AE61: =+AE60-AF48 -> 0 | AF61: =+AF60-AG48 -> 0
D65: 24350 | H65: 24380 | L65: 24680 | P65: 24450 | T65: 24180 | X65: 23805 | AB65: 23700 | AF65: 23610 | AJ65: 23580 | AN65: 23585 | AR65: 23895 | AV65: 23570
B66: 45261 | E66: Dec/Nov | F66: 45231 | I66: Nov/ Oct | J66: 45200 | M66: Oct/ Sep | N66: 45170 | Q66: Sept/ Aug | R66: 45139 | U66: Aug/ Jul | V66: 45108 | Y66: Jul/Jun | Z66: 45078 | AC66: Jun/May | AD66: 45047 | AG66: May/Apr | AH66: 45017 | AK66: Apr/Mar | AL66: 44986 | AO66: Mar/ Feb | AP66: 44958 | AS66: Feb/Jan | AT66: 44927
B67: 26 | F67: 26 | J67: 26 | N67: 26 | R67: 26 | V67: 26 | Z67: 26 | AD67: 26 | AH67: 26 | AL67: 26 | AP67: 26 | AT67: 26
B68: Workers qty | C68: Salary - Net | D68: USD | E68: VND % | F68: Workers qty | G68: Salary - Net | H68: USD | I68: VND % | J68: Workers qty | K68: Salary - Net | L68: USD | M68: VND % | N68: Workers qty | O68: Salary - Net | P68: USD | Q68: VND % | R68: Workers qty | S68: Salary - Net | T68: USD | U68: VND % | V68: Workers qty | W68: Salary - Net | X68: USD | Y68: VND % | Z68: Workers qty | AA68: Salary - Net | AB68: USD | AC68: VND % | AD68: Workers qty | AE68: Salary - Net | AF68: USD | AG68: VND % | AH68: Workers qty | AI68: Salary - Net | AJ68: USD | AK68: VND % | AL68: Workers qty | AM68: Salary - Net | AN68: USD | AO68: VND % | AP68: Workers qty | AQ68: Salary - Net | AR68: USD | AS68: VND % | AT68: Workers qty | AU68: Salary - Net | AV68: USD
B69: 312 | C69: 2506845549 | D69: 102950.54 | E69: =+C69/G69 -> 1.1930122 | F69: 292 | G69: 2101274001 | H69: =+G69/#REF! -> #REF! | I69: =+G69/K69 -> 0.76684472 | J69: 300 | K69: 2740155776 | L69: =+K69/#REF! -> #REF! | M69: =+K69/O69 -> 1.1368673 | N69: 286 | O69: 2410268692 | P69: =+O69/#REF! -> #REF! | Q69: =+O69/S69 -> 0.86808505 | R69: 297 | S69: 2776535201 | T69: =+S69/#REF! -> #REF! | U69: =+S69/W69 -> 1.0624417 | V69: 281 | W69: 2613352952 | X69: =+W69/#REF! -> #REF! | Y69: =+W69/AA69 -> 0.99743201 | Z69: 282 | AA69: 2620081297 | AB69: =+AA69/#REF! -> #REF! | AC69: =+AA69/AE69 -> 1.1748339 | AD69: 296 | AE69: 2230171614 | AF69: =+AE69/#REF! -> #REF! | AG69: =+AE69/AI69 -> 0.85342626 | AH69: 323 | AI69: 2613197780 | AJ69: =+AI69/#REF! -> #REF! | AK69: =+AI69/AM69 -> 0.96083702 | AL69: 327 | AM69: 2719709726 | AN69: =+AM69/#REF! -> #REF! | AO69: =+AM69/AQ69 -> 1.1945145 | AP69: 340 | AQ69: 2276832703 | AR69: =+AQ69/#REF! -> #REF! | AS69: =+AQ69/AU69 -> 1.4461222 | AT69: 340 | AU69: 1574440076 | AV69: 66798.476
B70: 140 | C70: 1211775951 | D70: 49764.926 | E70: =+C70/G70 -> 1.1280041 | F70: 137 | G70: 1074265517 | H70: =+G70/#REF! -> #REF! | I70: =+G70/K70 -> 0.8963368 | J70: 135 | K70: 1198506539 | L70: =+K70/#REF! -> #REF! | M70: =+K70/O70 -> 1.0304379 | N70: 138 | O70: 1163104044 | P70: =+O70/#REF! -> #REF! | Q70: =+O70/S70 -> 0.90064645 | R70: 140 | S70: 1291410240 | T70: =+S70/#REF! -> #REF! | U70: =+S70/W70 -> 1.0804273 | V70: 144 | W70: 1195277281 | X70: =+W70/#REF! -> #REF! | Y70: =+W70/AA70 -> 0.90024226 | Z70: 149 | AA70: 1327728476 | AB70: =+AA70/#REF! -> #REF! | AC70: =+AA70/AE70 -> 1.1120667 | AD70: 142 | AE70: 1193928818 | AF70: =+AE70/#REF! -> #REF! | AG70: =+AE70/AI70 -> 1.0472537 | AH70: 141 | AI70: 1140056941 | AJ70: =+AI70/#REF! -> #REF! | AK70: =+AI70/AM70 -> 0.97872864 | AL70: 151 | AM70: 1164834557 | AN70: =+AM70/#REF! -> #REF! | AO70: =+AM70/AQ70 -> 0.992276 | AP70: 145 | AQ70: 1173901780 | AR70: =+AQ70/#REF! -> #REF! | AS70: =+AQ70/AU70 -> 1.7006725 | AT70: 149 | AU70: 690257385 | AV70: 29285.422
B71: 198 | C71: 1612410322 | D71: 66218.083 | E71: =+C71/G71 -> 1.2319476 | F71: 194 | G71: 1308830251 | H71: =+G71/#REF! -> #REF! | I71: =+G71/K71 -> 0.81043213 | J71: 198 | K71: 1614978232 | L71: =+K71/#REF! -> #REF! | M71: =+K71/O71 -> 1.0454803 | N71: 204 | O71: 1544723762 | P71: =+O71/#REF! -> #REF! | Q71: =+O71/S71 -> 0.78800493 | R71: 215 | S71: 1960297077 | T71: =+S71/#REF! -> #REF! | U71: =+S71/W71 -> 1.0194676 | V71: 210 | W71: 1922863570 | X71: =+W71/#REF! -> #REF! | Y71: =+W71/AA71 -> 1.0136173 | Z71: 213 | AA71: 1897031162 | AB71: =+AA71/#REF! -> #REF! | AC71: =+AA71/AE71 -> 0.9744891 | AD71: 232 | AE71: 1946693055 | AF71: =+AE71/#REF! -> #REF! | AG71: =+AE71/AI71 -> 1.0224703 | AH71: 238 | AI71: 1903911511 | AJ71: =+AI71/#REF! -> #REF! | AK71: =+AI71/AM71 -> 1.0072127 | AL71: 238 | AM71: 1890277571 | AN71: =+AM71/#REF! -> #REF! | AO71: =+AM71/AQ71 -> 0.99847186 | AP71: 250 | AQ71: 1893170605 | AR71: =+AQ71/#REF! -> #REF! | AS71: =+AQ71/AU71 -> 1.5724333 | AT71: 258 | AU71: 1203975155 | AV71: 51080.83
B72: 152 | C72: 1928930676 | D72: 79216.866 | E72: =+C72/G72 -> 1.1994735 | F72: 152 | G72: 1608147751 | H72: =+G72/#REF! -> #REF! | I72: =+G72/K72 -> 0.93158932 | J72: 154 | K72: 1726241085 | L72: =+K72/#REF! -> #REF! | M72: =+K72/O72 -> 1.0286728 | N72: 151 | O72: 1678124562 | P72: =+O72/#REF! -> #REF! | Q72: =+O72/S72 -> 0.96968906 | R72: 141 | S72: 1730580073 | T72: =+S72/#REF! -> #REF! | U72: =+S72/W72 -> 1.0397588 | V72: 135 | W72: 1664405336 | X72: =+W72/#REF! -> #REF! | Y72: =+W72/AA72 -> 1.0214528 | Z72: 136 | AA72: 1629449034 | AB72: =+AA72/#REF! -> #REF! | AC72: =+AA72/AE72 -> 1.0308686 | AD72: 140 | AE72: 1580656419 | AF72: =+AE72/#REF! -> #REF! | AG72: =+AE72/AI72 -> 1.0314273 | AH72: 143 | AI72: 1532494213 | AJ72: =+AI72/#REF! -> #REF! | AK72: =+AI72/AM72 -> 0.9438215 | AL72: 145 | AM72: 1623711918 | AN72: =+AM72/#REF! -> #REF! | AO72: =+AM72/AQ72 -> 1.1360552 | AP72: 146 | AQ72: 1429254371 | AR72: =+AQ72/#REF! -> #REF! | AS72: =+AQ72/AU72 -> 1.4458527 | AT72: 143 | AU72: 988520042 | AV72: 41939.756
B73: 2 | C73: 292812875 | D73: 12025.169 | E73: =+C73/G73 -> 0.99886584 | F73: 2 | G73: 293145350 | H73: =+G73/#REF! -> #REF! | I73: =+G73/K73 -> 0.98878555 | J73: 2 | K73: 296470100 | L73: =+K73/#REF! -> #REF! | M73: =+K73/O73 -> 1.0086723 | N73: 2 | O73: 293921125 | P73: =+O73/#REF! -> #REF! | Q73: =+O73/S73 -> 0.97571851 | R73: 2 | S73: 301235575 | T73: =+S73/#REF! -> #REF! | U73: =+S73/W73 -> 1.0504325 | V73: 2 | W73: 286772912 | X73: =+W73/#REF! -> #REF! | Y73: =+W73/AA73 -> 1.0013897 | Z73: 2 | AA73: 286374950 | AB73: =+AA73/#REF! -> #REF! | AC73: =+AA73/AE73 -> 0.93491825 | AD73: 2 | AE73: 306310151 | AF73: =+AE73/#REF! -> #REF! | AG73: =+AE73/AI73 -> 1.0746026 | AH73: 2 | AI73: 285045050 | AJ73: =+AI73/#REF! -> #REF! | AK73: =+AI73/AM73 -> 1.6274008 | AL73: 2 | AM73: 175153569 | AN73: =+AM73/#REF! -> #REF! | AO73: =+AM73/AQ73 -> 0.60704226 | AP73: 2 | AQ73: 288536037 | AR73: =+AQ73/#REF! -> #REF! | AS73: =+AQ73/AU73 -> 1.7546263 | AT73: 2 | AU73: 164443012 | AV73: 6976.793
B74: 804 | C74: 7552775373 | D74: 310175.58 | E74: =+C74/G74 -> 1.1827708 | F74: =SUM(F69:F73) -> 777 | G74: =SUM(G69:G73) -> 6385662870 | H74: =SUM(H69:H73) -> #REF! | I74: =+G74/K74 -> 0.8428414 | J74: =SUM(J69:J73) -> 789 | K74: =SUM(K69:K73) -> 7576351732 | L74: =SUM(L69:L73) -> #REF! | M74: =+K74/O74 -> 1.0685754 | N74: =SUM(N69:N73) -> 781 | O74: =SUM(O69:O73) -> 7090142185 | P74: =SUM(P69:P73) -> #REF! | Q74: =+O74/S74 -> 0.8796639 | R74: =SUM(R69:R73) -> 795 | S74: =SUM(S69:S73) -> 8060058166 | T74: =SUM(T69:T73) -> #REF! | U74: =+S74/W74 -> 1.0491217 | V74: =SUM(V69:V73) -> 772 | W74: =SUM(W69:W73) -> 7682672051 | X74: =SUM(X69:X73) -> #REF! | Y74: =+W74/AA74 -> 0.98995023 | Z74: =SUM(Z69:Z73) -> 782 | AA74: =SUM(AA69:AA73) -> 7760664919 | AB74: =SUM(AB69:AB73) -> #REF! | AC74: =+AA74/AE74 -> 1.069292 | AD74: =SUM(AD69:AD73) -> 812 | AE74: =SUM(AE69:AE73) -> 7257760057 | AF74: =SUM(AF69:AF73) -> #REF! | AG74: =+AE74/AI74 -> 0.97097606 | AH74: =SUM(AH69:AH73) -> 847 | AI74: =SUM(AI69:AI73) -> 7474705495 | AJ74: =SUM(AJ69:AJ73) -> #REF! | AK74: =+AI74/AM74 -> 0.98693082 | AL74: =SUM(AL69:AL73) -> 863 | AM74: =SUM(AM69:AM73) -> 7573687341 | AN74: =SUM(AN69:AN73) -> #REF! | AO74: =+AM74/AQ74 -> 1.0725027 | AP74: =SUM(AP69:AP73) -> 883 | AQ74: =SUM(AQ69:AQ73) -> 7061695496 | AR74: =SUM(AR69:AR73) -> #REF! | AS74: =+AQ74/AU74 -> 1.5279646 | AT74: 892 | AU74: 4621635670 | AV74: 196081.28
B75: 0.6468222 | C75: 0.62841612 | D75: 0.62841612 | E75: =+C75/G75 -> 0.98809328 | F75: =+F74/F80 -> 0.64966555 | G75: =+G74/G80 -> 0.63598866 | H75: =+H74/H80 -> #REF! | I75: =+G75/K75 -> 0.95506441 | J75: =+J74/J80 -> 0.65260546 | K75: =+K74/K80 -> 0.6659118 | L75: =+L74/L80 -> #REF! | M75: =+K75/O75 -> 1.0462585 | N75: =+N74/N80 -> 0.6438582 | O75: =+O74/O80 -> 0.63646966 | P75: =+P74/P80 -> #REF! | Q75: =+O75/S75 -> 1.0023777 | R75: =+R74/R80 -> 0.64424635 | S75: =+S74/S80 -> 0.63495991 | T75: =+T74/T80 -> #REF! | U75: =+S75/W75 -> 1.0121361 | V75: =+V74/V80 -> 0.63539095 | W75: =+W74/W80 -> 0.62734637 | X75: =+X74/X80 -> #REF! | Y75: =+W75/AA75 -> 1.0507061 | Z75: =+Z74/Z80 -> 0.63680782 | AA75: =+AA74/AA80 -> 0.5970712 | AB75: =+AB74/AB80 -> #REF! | AC75: =+AA75/AE75 -> 1.0042536 | AD75: =+AD74/AD80 -> 0.63786332 | AE75: =+AE74/AE80 -> 0.59454224 | AF75: =+AF74/AF80 -> #REF! | AG75: =+AE75/AI75 -> 0.9482947 | AH75: =+AH74/AH80 -> 0.6397281 | AI75: =+AI74/AI80 -> 0.62695936 | AJ75: =+AJ74/AJ80 -> #REF! | AK75: =+AI75/AM75 -> 1.0297945 | AL75: =+AL74/AL80 -> 0.63831361 | AM75: =+AM74/AM80 -> 0.60881985 | AN75: =+AN74/AN80 -> #REF! | AO75: =+AM75/AQ75 -> 0.98084538 | AP75: =+AP74/AP80 -> 0.63754513 | AQ75: =+AQ74/AQ80 -> 0.6207093 | AR75: =+AR74/AR80 -> #REF! | AS75: =+AQ75/AU75 -> 1.0032892 | AT75: 0.63805436 | AU75: 0.61867437 | AV75: 0.61867437
B76: 438 | C76: 4368573316 | D76: 179407.53 | E76: =+C76/G76 -> 1.2280427 | F76: 418 | G76: 3557346564 | H76: =+G76/#REF! -> #REF! | I76: =+G76/K76 -> 0.96083772 | J76: 419 | K76: 3702338569 | L76: =+K76/#REF! -> #REF! | M76: =+K76/O76 -> 0.93686119 | N76: 431 | O76: 3951853928 | P76: =+O76/#REF! -> #REF! | Q76: =+O76/S76 -> 0.87173732 | R76: 438 | S76: 4533308182 | T76: =+S76/#REF! -> #REF! | U76: =+S76/W76 -> 1.0145241 | V76: 442 | W76: 4468408429 | X76: =+W76/#REF! -> #REF! | Y76: =+W76/AA76 -> 0.86893046 | Z76: 445 | AA76: 5142423525 | AB76: =+AA76/#REF! -> #REF! | AC76: =+AA76/AE76 -> 1.0599711 | AD76: 460 | AE76: 4851475349 | AF76: =+AE76/#REF! -> #REF! | AG76: =+AE76/AI76 -> 1.1144804 | AH76: 476 | AI76: 4353127615 | AJ76: =+AI76/#REF! -> #REF! | AK76: =+AI76/AM76 -> 0.91293224 | AL76: 488 | AM76: 4768292147 | AN76: =+AM76/#REF! -> #REF! | AO76: =+AM76/AQ76 -> 1.1300501 | AP76: 501 | AQ76: 4219540406 | AR76: =+AQ76/#REF! -> #REF! | AS76: =+AQ76/AU76 -> 1.5179892 | AT76: 505 | AU76: 2779690729 | AV76: 117933.42
B77: 1 | C77: 97399908 | D77: 3999.9962 | E77: =+C77/G77 -> 0.99876823 | F77: 1 | G77: 97520030 | H77: =+G77/#REF! -> #REF! | I77: =+G77/K77 -> 0.98784498 | J77: 1 | K77: 98719973 | L77: =+K77/#REF! -> #REF! | M77: =+K77/O77 -> 1.0094069 | N77: 1 | O77: 97799974 | P77: =+O77/#REF! -> #REF! | Q77: =+O77/S77 -> 0.97371432 | R77: 1 | S77: 100440111 | T77: =+S77/#REF! -> #REF! | U77: =+S77/W77 -> 1.0548223 | V77: 1 | W77: 95219931 | X77: =+W77/#REF! -> #REF! | Y77: =+W77/AA77 -> 1.004429 | Z77: 1 | AA77: 94800062 | AB77: =+AA77/#REF! -> #REF! | AC77: =+AA77/AE77 -> 0.9666343 | AD77: 1 | AE77: 98072313 | AF77: =+AE77/#REF! -> #REF! | AG77: =+AE77/AI77 -> 1.0397825 | AH77: 1 | AI77: 94320030 | AJ77: =+AI77/#REF! -> #REF! | AK77: =+AI77/AM77 -> 0.96275832 | AL77: 1 | AM77: 97968543 | AN77: =+AM77/#REF! -> #REF! | AO77: =+AM77/AQ77 -> 1.0249898 | AP77: 1 | AQ77: 95580021 | AR77: =+AQ77/#REF! -> #REF! | AS77: =+AQ77/AU77 -> 1.3872917 | AT77: 1 | AU77: 68896843 | AV77: 2923.0735
B78: 439 | C78: 4465973224 | D78: 183407.52 | E78: =+C78/G78 -> 1.2219251 | F78: =SUM(F76:F77) -> 419 | G78: =SUM(G76:G77) -> 3654866594 | H78: =SUM(H76:H77) -> #REF! | I78: =+G78/K78 -> 0.96153915 | J78: =SUM(J76:J77) -> 420 | K78: =SUM(K76:K77) -> 3801058542 | L78: =SUM(L76:L77) -> #REF! | M78: =+K78/O78 -> 0.93861318 | N78: =SUM(N76:N77) -> 432 | O78: =SUM(O76:O77) -> 4049653902 | P78: =SUM(P76:P77) -> #REF! | Q78: =+O78/S78 -> 0.87394775 | R78: =SUM(R76:R77) -> 439 | S78: =SUM(S76:S77) -> 4633748293 | T78: =SUM(T76:T77) -> #REF! | U78: =+S78/W78 -> 1.015365 | V78: =SUM(V76:V77) -> 443 | W78: =SUM(W76:W77) -> 4563628360 | X78: =SUM(X76:X77) -> #REF! | Y78: =+W78/AA78 -> 0.87138314 | Z78: =SUM(Z76:Z77) -> 446 | AA78: =SUM(AA76:AA77) -> 5237223587 | AB78: =SUM(AB76:AB77) -> #REF! | AC78: =+AA78/AE78 -> 1.0581217 | AD78: =SUM(AD76:AD77) -> 461 | AE78: =SUM(AE76:AE77) -> 4949547662 | AF78: =SUM(AF76:AF77) -> #REF! | AG78: =+AE78/AI78 -> 1.1128962 | AH78: =SUM(AH76:AH77) -> 477 | AI78: =SUM(AI76:AI77) -> 4447447645 | AJ78: =SUM(AJ76:AJ77) -> #REF! | AK78: =+AI78/AM78 -> 0.91393535 | AL78: =SUM(AL76:AL77) -> 489 | AM78: =SUM(AM76:AM77) -> 4866260690 | AN78: =SUM(AN76:AN77) -> #REF! | AO78: =+AM78/AQ78 -> 1.127723 | AP78: =SUM(AP76:AP77) -> 502 | AQ78: =SUM(AQ76:AQ77) -> 4315120427 | AR78: =SUM(AR76:AR77) -> #REF! | AS78: =+AQ78/AU78 -> 1.5148281 | AT78: 506 | AU78: 2848587572 | AV78: 120856.49
B79: 0.3531778 | C79: 0.37158388 | D79: 0.37158388 | E79: =+C79/G79 -> 1.020803 | F79: =+F78/F80 -> 0.35033445 | G79: =+G78/G80 -> 0.36401134 | H79: =+H78/H80 -> #REF! | I79: =+G79/K79 -> 1.0895666 | J79: =+J78/J80 -> 0.34739454 | K79: =+K78/K80 -> 0.3340882 | L79: =+L78/L80 -> #REF! | M79: =+K79/O79 -> 0.9190105 | N79: =+N78/N80 -> 0.3561418 | O79: =+O78/O80 -> 0.36353034 | P79: =+P78/P80 -> #REF! | Q79: =+O79/S79 -> 0.99586415 | R79: =+R78/R80 -> 0.35575365 | S79: =+S78/S80 -> 0.36504009 | T79: =+T78/T80 -> #REF! | U79: =+S79/W79 -> 0.97956939 | V79: =+V78/V80 -> 0.36460905 | W79: =+W78/W80 -> 0.37265363 | X79: =+X78/X80 -> #REF! | Y79: =+W79/AA79 -> 0.92486225 | Z79: =+Z78/Z80 -> 0.36319218 | AA79: =+AA78/AA80 -> 0.4029288 | AB79: =+AB78/AB80 -> #REF! | AC79: =+AA79/AE79 -> 0.99376269 | AD79: =+AD78/AD80 -> 0.36213668 | AE79: =+AE78/AE80 -> 0.40545776 | AF79: =+AF78/AF80 -> #REF! | AG79: =+AE79/AI79 -> 1.0868997 | AH79: =+AH78/AH80 -> 0.3602719 | AI79: =+AI78/AI80 -> 0.37304064 | AJ79: =+AJ78/AJ80 -> #REF! | AK79: =+AI79/AM79 -> 0.95362877 | AL79: =+AL78/AL80 -> 0.36168639 | AM79: =+AM78/AM80 -> 0.39118015 | AN79: =+AN78/AN80 -> #REF! | AO79: =+AM79/AQ79 -> 1.0313465 | AP79: =+AP78/AP80 -> 0.36245487 | AQ79: =+AQ78/AQ80 -> 0.3792907 | AR79: =+AR78/AR80 -> #REF! | AS79: =+AQ79/AU79 -> 0.99466353 | AT79: 0.36194564 | AU79: 0.38132563 | AV79: 0.38132563
B80: 1243 | C80: 12018748597 | D80: 493583.1 | E80: =+C80/G80 -> 1.1970234 | F80: =+F74+F78 -> 1196 | G80: =+G74+G78 -> 10040529464 | H80: =+G80/#REF! -> #REF! | I80: =+G80/K80 -> 0.88249691 | J80: =+J74+J78 -> 1209 | K80: =+K74+K78 -> 11377410274 | L80: =+K80/#REF! -> #REF! | M80: =+K80/O80 -> 1.0213302 | N80: =+N74+N78 -> 1213 | O80: =+O74+O78 -> 11139796087 | P80: =+O80/#REF! -> #REF! | Q80: =+O80/S80 -> 0.87757728 | R80: =+R74+R78 -> 1234 | S80: =+S74+S78 -> 12693806459 | T80: =+S80/#REF! -> #REF! | U80: =+S80/W80 -> 1.0365421 | V80: =+V74+V78 -> 1215 | W80: =+W74+W78 -> 12246300411 | X80: =+W80/#REF! -> #REF! | Y80: =+W80/AA80 -> 0.94217614 | Z80: =+Z74+Z78 -> 1228 | AA80: =+AA74+AA78 -> 12997888506 | AB80: =+AA80/#REF! -> #REF! | AC80: =+AA80/AE80 -> 1.0647629 | AD80: =+AD74+AD78 -> 1273 | AE80: =+AE74+AE78 -> 12207307719 | AF80: =+AE80/#REF! -> #REF! | AG80: =+AE80/AI80 -> 1.023918 | AH80: =+AH74+AH78 -> 1324 | AI80: =+AI74+AI78 -> 11922153140 | AJ80: =+AI80/#REF! -> #REF! | AK80: =+AI80/AM80 -> 0.95837644 | AL80: =+AL74+AL78 -> 1352 | AM80: =+AM74+AM78 -> 12439948031 | AN80: =+AM80/#REF! -> #REF! | AO80: =+AM80/AQ80 -> 1.0934472 | AP80: =+AP74+AP78 -> 1385 | AQ80: =+AQ74+AQ78 -> 11376815923 | AR80: =+AQ80/#REF! -> #REF! | AS80: =+AQ80/AU80 -> 1.5229553 | AT80: 1398 | AU80: 7470223242 | AV80: 316937.77
B81: Remark: Dec pay balance annual leave 2023 for 68,893 USD (Include : 39 Pregnant workers + Mr Michel + Lâm Lý Cỏn (Sick)) | AS81: Bonus 13th month | AT81: 1491 | AU81: 9391343314 | AV81: =+AU81/#REF! -> #REF!
B83: =+B66 -> 45261 | C83: =+D65 -> 24350 | F83: =+F66 -> 45231 | G83: =+H65 -> 24380 | J83: =+J66 -> 45200 | K83: =+L65 -> 24680 | N83: =+N66 -> 45170 | O83: 24450 | R83: =+R66 -> 45139 | S83: =+T65 -> 24180 | V83: =+V66 -> 45108 | W83: =+X65 -> 23805 | Z83: =+Z66 -> 45078 | AA83: =+AB65 -> 23700 | AD83: =+AD66 -> 45047 | AE83: =+AF65 -> 23610 | AH83: =+AH66 -> 45017 | AI83: =+AJ65 -> 23580 | AL83: =+AL66 -> 44986 | AM83: =+AN65 -> 23585 | AP83: 44958 | AQ83: =+AR65 -> 23895 | AT83: 44927 | AU83: =+AV65 -> 23570
B84: Amount (vnd) | C84: Amount (usd) | F84: Amount (vnd) | G84: Amount (usd) | J84: Amount (vnd) | K84: Amount (usd) | N84: Amount (vnd) | O84: Amount (usd) | R84: Amount (vnd) | S84: Amount (usd) | V84: Amount (vnd) | W84: Amount (usd) | Z84: Amount (vnd) | AA84: Amount (usd) | AD84: Amount (vnd) | AE84: Amount (usd) | AH84: Amount (vnd) | AI84: Amount (usd) | AL84: Amount (vnd) | AM84: Amount (usd) | AP84: Amount (vnd) | AQ84: Amount (usd) | AT84: Amount (vnd) | AU84: Amount (usd)
B85: 1243 | F85: =+F80 -> 1196 | J85: =+J80 -> 1209 | N85: =+N80 -> 1213 | R85: =+R80 -> 1234 | V85: =+V80 -> 1215 | Z85: =+Z80 -> 1228 | AD85: =+AD80 -> 1273 | AH85: =+AH80 -> 1324 | AL85: =+AL80 -> 1352 | AP85: =+AP80 -> 1385 | AT85: =+AT80 -> 1398
B86: 11470443072 | C86: 471065.42 | F86: 9588116329 | G86: =+F86/#REF! -> #REF! | J86: 10106038356 | K86: =+J86/#REF! -> #REF! | N86: 10029587406 | O86: =+N86/#REF! -> #REF! | R86: 11050972418 | S86: 457029.46 | V86: 10735383737 | W86: =+V86/#REF! -> #REF! | Z86: 10835350134 | AA86: 457187.77 | AD86: 11265264298 | AE86: =+AD86/#REF! -> #REF! | AH86: 11241305599 | AI86: 476730.52 | AL86: 11516047027 | AM86: =+AL86/#REF! -> #REF! | AP86: 10691752226 | AQ86: =+AP86/#REF! -> #REF! | AT86: 7224740743 | AU86: =+AT86/#REF! -> #REF!
B87: 8623637 | C87: 354.15347 | F87: 13659989 | G87: =+F87/#REF! -> #REF! | J87: 2615385 | K87: =+J87/#REF! -> #REF! | N87: 0 | O87: =+N87/#REF! -> #REF! | R87: 29708301 | S87: 1228.6311 | V87: 12987981 | W87: =+V87/#REF! -> #REF! | Z87: 0 | AA87: 0 | AD87: 0 | AE87: =+AD87/#REF! -> #REF! | AH87: 5577825 | AI87: 236.54898 | AL87: 173083778 | AM87: =+AL87/#REF! -> #REF! | AP87: 148607512 | AQ87: =+AP87/#REF! -> #REF! | AT87: 12142644 | AU87: =+AT87/#REF! -> #REF!
B88: 149469105 | C88: 6138.3616 | F88: 48087766 | G88: =+F88/#REF! -> #REF! | J88: 873566460 | K88: =+J88/#REF! -> #REF! | N88: 718487582 | O88: =+N88/#REF! -> #REF! | R88: 1208419914 | S88: 49976.01 | V88: 1115935850 | W88: =+V88/#REF! -> #REF! | Z88: 1781363360 | AA88: 75163.011 | AD88: 537660957 | AE88: =+AD88/#REF! -> #REF! | AH88: 295431086 | AI88: 12528.884 | AL88: 470761057 | AM88: =+AL88/#REF! -> #REF! | AP88: 148562491 | AQ88: =+AP88/#REF! -> #REF! | AT88: =SUM(AT86:AT87) -> 7236883387 | AU88: =SUM(AU86:AU87) -> #REF!
B89: 0 | C89: 0 | F89: 0 | G89: =+F89/#REF! -> #REF! | J89: 0 | K89: =+J89/#REF! -> #REF! | N89: 0 | O89: =+N89/#REF! -> #REF! | R89: 3030140 | S89: 125.31596 | V89: 0 | W89: =+V89/#REF! -> #REF! | Z89: 0 | AA89: =+Z89/#REF! -> #REF! | AD89: 0 | AE89: =+AD89/#REF! -> #REF! | AH89: 473550 | AI89: 20.082697 | AL89: 6934057 | AM89: =+AL89/#REF! -> #REF! | AP89: 3777636 | AQ89: =+AP89/#REF! -> #REF! | AT89: 233339855 | AU89: =+AT89/#REF! -> #REF!
B90: 11628535814 | C90: 477557.94 | F90: =SUM(F86:F89) -> 9649864084 | G90: =SUM(G86:G89) -> #REF! | J90: =SUM(J86:J89) -> 10982220201 | K90: =SUM(K86:K89) -> #REF! | N90: =SUM(N86:N89) -> 10748074988 | O90: =SUM(O86:O89) -> #REF! | R90: =SUM(R86:R89) -> 12292130773 | S90: =SUM(S86:S89) -> 508359.42 | V90: =SUM(V86:V89) -> 11864307568 | W90: =SUM(W86:W89) -> #REF! | Z90: =SUM(Z86:Z89) -> 12616713494 | AA90: =SUM(AA86:AA89) -> #REF! | AD90: =SUM(AD86:AD89) -> 11802925255 | AE90: =SUM(AE86:AE89) -> #REF! | AH90: =SUM(AH86:AH89) -> 11542788060 | AI90: =SUM(AI86:AI89) -> 489516.03 | AL90: =SUM(AL86:AL89) -> 12166825919 | AM90: =SUM(AM86:AM89) -> #REF! | AP90: =SUM(AP86:AP89) -> 10992699865 | AQ90: =SUM(AQ86:AQ89) -> #REF! | AT90: =+AT89+AT88 -> 7470223242 | AU90: =+AU89+AU88 -> #REF!
B91: 390212783 | C91: 16025.166 | F91: 390665380 | G91: =+F91/#REF! -> #REF! | J91: 395190073 | K91: =+J91/#REF! -> #REF! | N91: 391721099 | O91: =+N91/#REF! -> #REF! | R91: 401675686 | S91: 16611.898 | V91: =+'[4]Foreign Salary'!$R$11 -> 381992843 | W91: =+V91/#REF! -> #REF! | Z91: 381175012 | AA91: 16083.334 | AD91: 404382464 | AE91: =+AD91/#REF! -> #REF! | AH91: 379365080 | AI91: 16088.426 | AL91: 273122112 | AM91: =+AL91/#REF! -> #REF! | AO91: Bonus 13th month | AP91: 384116058 | AQ91: =+AP91/#REF! -> #REF! | AS91: Bonus 13th month | AT91: 9391343314 | AU91: 398444.77
B92: 12018748597 | C92: 493583.1 | F92: =+F91+F90 -> 10040529464 | G92: =+G91+G90 -> #REF! | J92: =+J91+J90 -> 11377410274 | K92: =+K91+K90 -> #REF! | N92: =+N91+N90 -> 11139796087 | O92: =+O91+O90 -> #REF! | R92: =+R91+R90 -> 12693806459 | S92: =+S91+S90 -> 524971.32 | V92: =+V91+V90 -> 12246300411 | W92: =+W91+W90 -> #REF! | Z92: =+Z91+Z90 -> 12997888506 | AA92: =+AA91+AA90 -> #REF! | AD92: =+AD91+AD90 -> 12207307719 | AE92: =+AE91+AE90 -> #REF! | AH92: =+AH91+AH90 -> 11922153140 | AI92: =+AI91+AI90 -> 505604.46 | AL92: =+AL91+AL90 -> 12439948031 | AM92: =+AM91+AM90 -> #REF! | AP92: =+AP91+AP90 -> 11376815923 | AQ92: =+AQ91+AQ90 -> #REF! | AT92: =+AT91+AT90 -> 16861566556 | AU92: 398444.77

Sheet Sheet1
D2: Inside | E2: Outside | F2: Total
B3: 1 | C3: Payment Transfer - Foreign | D3: =+'Foreign Salary'!R11 -> 480497301 | E3: 0 | F3: =SUM(D3:E3) -> 480497301 | G3: =+F3-'Foreign Salary'!R11 -> 0
B4: 2 | C4: Payment Transfer | D4: 10547466313 | E4: 1126799307 | F4: =SUM(D4:E4) -> 11674265620 | G4: =+F4-Transfer!E1279 -> -869420560
B5: 3 | C5: Payment Cash | D5: 215764202 | E5: 21316040 | F5: =SUM(D5:E5) -> 237080242 | G5: =+F5-Cash!F18 -> 194542807
B6: 4 | C6: Payment cash - Ms Quyên Nurse Staff | D6: 0 | E6: 11464288 | F6: =SUM(D6:E6) -> 11464288
C7: Total | D7: =SUM(D3:D6) -> 11243727816 | E7: =SUM(E3:E6) -> 1159579635 | F7: =SUM(F3:F6) -> 12403307451
F8: =+F7-'TOTAL(payment)'!L119 -> -663413465

Sheet Manager
A1: STT | B1: Code | C1: Name | D1: Tổng thu nhập Total Gross Salary | E1: Phụ cấp Phụ Nữ Menstruation allowance | F1: Tiền thực lãnh Net Salary | G1: Bộ phận Dep | H1: Title/ Chức danh
A2: 1 | B2: C3402 | C2: Đoàn Thị Hiếu Loan | D2: =+VLOOKUP(B2,'Salary sheet'!$B$6:$AS$1291,40,0) -> 2562000 | E2: =VLOOKUP(B2,'Salary sheet'!$B$6:$AE$1318,30,0) -> 175961.54 | F2: =+D2-E2 -> 2386038.5 | G2: =VLOOKUP(B2,'Salary sheet'!$B$3:$G$1318,5,0) -> P6 - Production Office | H2: =VLOOKUP(B2,'Salary sheet'!$B$3:$G$1318,6,0) -> Factory manager
A3: 2 | B3: C5841 | C3: Trần Văn Nhân | D3: =+VLOOKUP(B3,'Salary sheet'!$B$6:$AS$1291,40,0) -> 2566200 | E3: =VLOOKUP(B3,'Salary sheet'!$B$6:$AE$1318,30,0) -> 0 | F3: =+D3-E3 -> 2566200 | G3: =VLOOKUP(B3,'Salary sheet'!$B$3:$G$1318,5,0) -> P6 - Production Office | H3: =VLOOKUP(B3,'Salary sheet'!$B$3:$G$1318,6,0) -> Factory manager
A4: 3 | B4: C3465 | C4: Lê Văn Khỏe | D4: =+VLOOKUP(B4,'Salary sheet'!$B$6:$AS$1291,40,0) -> 1944495 | E4: =VLOOKUP(B4,'Salary sheet'!$B$6:$AE$1318,30,0) -> 0 | F4: =+D4-E4 -> 1944495 | G4: =VLOOKUP(B4,'Salary sheet'!$B$3:$G$1318,5,0) -> P5 - Production Office | H4: =VLOOKUP(B4,'Salary sheet'!$B$3:$G$1318,6,0) -> Factory vice manager
A5: 4 | B5: C6068 | C5: Trần Thị Cẩm Linh | D5: =+VLOOKUP(B5,'Salary sheet'!$B$6:$AS$1291,40,0) -> 3034500 | E5: =VLOOKUP(B5,'Salary sheet'!$B$6:$AE$1318,30,0) -> 208413.46 | F5: =+D5-E5 -> 2826086.5 | G5: =VLOOKUP(B5,'Salary sheet'!$B$3:$G$1318,5,0) -> P4 - Production Office | H5: =VLOOKUP(B5,'Salary sheet'!$B$3:$G$1318,6,0) -> Factory manager
A6: 5 | B6: C6347 | C6: Đỗ Thị Thanh Tú | D6: =+VLOOKUP(B6,'Salary sheet'!$B$6:$AS$1291,40,0) -> 3066000 | E6: =VLOOKUP(B6,'Salary sheet'!$B$6:$AE$1318,30,0) -> 210576.93 | F6: =+D6-E6 -> 2855423.1 | G6: =VLOOKUP(B6,'Salary sheet'!$B$3:$G$1318,5,0) -> P0 - Design | H6: =VLOOKUP(B6,'Salary sheet'!$B$3:$G$1318,6,0) -> Design manager
A7: 6 | B7: C6407 | C7: Điểu Dũng | D7: =+VLOOKUP(B7,'Salary sheet'!$B$6:$AS$1291,40,0) -> 2551500 | E7: =VLOOKUP(B7,'Salary sheet'!$B$6:$AE$1318,30,0) -> 0 | F7: =+D7-E7 -> 2551500 | G7: =VLOOKUP(B7,'Salary sheet'!$B$3:$G$1318,5,0) -> P0 - Development | H7: =VLOOKUP(B7,'Salary sheet'!$B$3:$G$1318,6,0) -> Development manager
A8: 7 | B8: V004 | C8: Hồ Mạnh Hoàng | D8: =+VLOOKUP(B8,'Salary sheet'!$B$6:$AS$1291,40,0) -> 1850520 | E8: =VLOOKUP(B8,'Salary sheet'!$B$6:$AE$1318,30,0) -> 0 | F8: =+D8-E8 -> 1850520 | G8: =VLOOKUP(B8,'Salary sheet'!$B$3:$G$1318,5,0) -> P0 - Maintenance | H8: =VLOOKUP(B8,'Salary sheet'!$B$3:$G$1318,6,0) -> Maintenance Leader
A9: 8 | B9: C5097 | C9: Kiều Quốc Minh | D9: =+VLOOKUP(B9,'Salary sheet'!$B$6:$AS$1291,40,0) -> 3227700 | E9: =VLOOKUP(B9,'Salary sheet'!$B$6:$AE$1318,30,0) -> 0 | F9: =+D9-E9 -> 3227700 | G9: =VLOOKUP(B9,'Salary sheet'!$B$3:$G$1318,5,0) -> P0 - GC WIP | H9: =VLOOKUP(B9,'Salary sheet'!$B$3:$G$1318,6,0) -> GC WIP Manager
A10: 9 | B10: C5107 | C10: Roãn Văn Hòa | D10: =+VLOOKUP(B10,'Salary sheet'!$B$6:$AS$1291,40,0) -> 3969000 | E10: =VLOOKUP(B10,'Salary sheet'!$B$6:$AE$1318,30,0) -> 0 | F10: =+D10-E10 -> 3969000 | G10: =VLOOKUP(B10,'Salary sheet'!$B$3:$G$1318,5,0) -> P0 - Production Office | H10: =VLOOKUP(B10,'Salary sheet'!$B$3:$G$1318,6,0) -> Production Manager
A11: 10 | B11: C6332 | C11: Đỗ Văn Thái | D11: =+VLOOKUP(B11,'Salary sheet'!$B$6:$AS$1291,40,0) -> 3097500 | E11: =VLOOKUP(B11,'Salary sheet'!$B$6:$AE$1318,30,0) -> 0 | F11: =+D11-E11 -> 3097500 | G11: =VLOOKUP(B11,'Salary sheet'!$B$3:$G$1318,5,0) -> P1 - Production Office | H11: =VLOOKUP(B11,'Salary sheet'!$B$3:$G$1318,6,0) -> Factory manager
A12: 11 | B12: C0020 | C12: Phan Tuấn Khanh | D12: =+VLOOKUP(B12,'Salary sheet'!$B$6:$AS$1291,40,0) -> 3070200 | E12: =VLOOKUP(B12,'Salary sheet'!$B$6:$AE$1318,30,0) -> 0 | F12: =+D12-E12 -> 3070200 | G12: =VLOOKUP(B12,'Salary sheet'!$B$3:$G$1318,5,0) -> P2 - Production Office | H12: =VLOOKUP(B12,'Salary sheet'!$B$3:$G$1318,6,0) -> Factory manager
A13: 12 | B13: V054 | C13: Huỳnh Ngọc Thảo | D13: =+VLOOKUP(B13,'Salary sheet'!$B$6:$AS$1291,40,0) -> 3301200 | E13: =VLOOKUP(B13,'Salary sheet'!$B$6:$AE$1318,30,0) -> 226730.77 | F13: =+D13-E13 -> 3074469.2 | G13: =VLOOKUP(B13,'Salary sheet'!$B$3:$G$1318,5,0) -> P3 - Production Office | H13: =VLOOKUP(B13,'Salary sheet'!$B$3:$G$1318,6,0) -> Factory manager
... A17: 16 | B17: C14623 | C17: Trần Văn Hoài | D17: =+VLOOKUP(B17,'Salary sheet'!$B$6:$AS$1291,40,0) -> 3811500 | E17: =VLOOKUP(B17,'Salary sheet'!$B$6:$AE$1318,30,0) -> 0 | F17: =+D17-E17 -> 3811500 | G17: =VLOOKUP(B17,'Salary sheet'!$B$3:$G$1318,5,0) -> P5 - Production Office | H17: =VLOOKUP(B17,'Salary sheet'!$B$3:$G$1318,6,0) -> Factory manager
C18: Total | D18: =SUM(D2:D17) -> #N/A | E18: =SUM(E2:E17) -> #N/A | F18: =SUM(F2:F17) -> #N/A | G18: =SUM(G2:G17) -> #N/A | H18: =SUM(H2:H17) -> #N/A

Sheet SS
B1: Content | C1: Jun-May | D1: % | E1: Noted
B2: Working day | C2: 4186.2 | D2: 0.11849927 | E2: Working: Jun.2020: 26 days - May.2020: 24 days
B3: Paid leave | C3: -2887 | D3: -0.86076327 | E3: After Corona epidemic situationm,After Transportation of machinery SK1: Box - SK2: Bag - Normal working
B4: Night work + 30% | C4: 3478.5 | D4: 1.9775441 | E4: After Corona epidemic situation - Normal overtime
B5: Overtime 150% | C5: 41402.5 | D5: 9.3123032 | E5: After Corona epidemic situation - Normal overtime
B6: Overtime 200% | C6: 0 | D6: 0
B7: Overtime 210% | C7: 1267 | D7: 4.4770318 | E7: After Corona epidemic situation - Normal overtime
B9: Content | C9: Jan-Dec | D9: % | E9: Noted
B10: Working day | C10: -7837.9 | D10: -0.22161745 | E10: Jan.22: working day 22 day
E11: Dec: Isolate (7 day) working day 27 day (Total 35.366 day/ 1681 Preson)
B12: Paid leave | C12: 3842 | D12: 6.4033333 | E12: Jan.2022 Holiday 2 day (01+31/Jan/2022)
E13: Dec: No holiday
B14: Night work + 30% | C14: -2045.8 | D14: -0.71232591 | E14: Jan.22: working day 22 day
E15: Dec: Working day 27 day &Night work 2872 Hour
B16: Overtime 150% | C16: -12945 | D16: -0.19960834 | E16: Jan.22: working day 22 day
E17: Dec: Working day 27 day (Overtime 64.852 hour)
B18: Overtime 200% | C18: 1152 | D18: 33.882353 | E18: Jan.2022: Overtime Sunday 1186 Hour
E19: Dec: Overtime Sunday 34 Hour
B20: Overtime 210% | C20: -251 | D20: -0.47809524 | E20: Jan.2022: Working day 22 day (274 Hour)
E21: Dec: Working day 27 day (525 Hour)
B22: Overtime 300% | C22: -254.5 | D22: -1 | E22: Oct.2021 No overtime 300%
B25: Content | C25: Apr | D25: Mar | E25: ="Amount "&C25&" ~ "&D25 -> Amount Apr ~ Mar | F25: % | G25: Note
B26: Working Day | C26: 28967.6 | D26: 31007.9 | E26: =+C26-D26 -> -2040.3 | F26: =+E26/D26 -> -0.065799361 | G26: Apr: Working day 24 day Mar Working day 26 day
B27: Paid Leave | C27: 2981 | D27: 87 | E27: =+C27-D27 -> 2894 | F27: =+E27/D27 -> 33.264368 | G27: Apr: Holiday: 2 day (10/03AL & 30/04) Mar: Marriage leave, funeral | J27: Marriage leave, labor accidents leave, funeral
B28: Annual Leave | E28: =+C28-D28 -> 0 | G28: Balance annual leave 2024
B29: extra pay for night work + 30% | C29: 4497 | D29: 4387 | E29: =+C29-D29 -> 110 | F29: =+E29/D29 -> 0.025074083 | G29: Increased night working hours (due to higher actual working days than last month)
B30: Overtime 150% | C30: 46478.5 | D30: 46222.5 | E30: =+C30-D30 -> 256 | F30: =+E30/D30 -> 0.0055384283 | G30: ~ | K30: Increased overtime 150% : (due to higher actual working days than last month)
B31: Overtime 200% | C31: 568 | D31: 199.5 | E31: =+C31-D31 -> 368.5 | F31: =+E31/D31 -> 1.8471178 | G31: Overtime Sunday
B32: Overtime 210% | C32: 423 | D32: 506.5 | E32: =+C32-D32 -> -83.5 | F32: =+E32/D32 -> -0.16485686 | G32: Increased night working hours (due to higher actual working days than last month)
B33: Overtime 270% | C33: 0 | E33: =+C33-D33 -> 0
B34: Overtime 300% | C34: 136 | D34: 0 | E34: =+C34-D34 -> 136

Sheet TOTAL(payment)
A1: Công ty TNHH Bao Bì Cao Cấp S&K Vina
A3: REPORT - BẢNG TỔNG KẾT LƯƠNG THÁNG 04 2025
A4: SUM OF SALARY OF APR 2025
A6: 0.54444444 | B6: Fac | C6: Dep new | D6: Dep Code | E6: # of worker | F6: Tổng thu nhập Total gross salary | G6: BHXH&BHYT, BHTN Social & Health Ins, Unempl-oyment Benefit | H6: KPCĐ Union Dues | I6: Thuế TNCN Personal Income Tax | J6: Đồng Phục Uniform | K6: Ứng Lương Advance | L6: Số Tiền (VND) Net salary | M6: Average
A7: =SUBTOTAL(3,B$7:B7) -> 1 | B7: Foreigners | C7: Foreigners | E7: 3 | F7: =+'Foreign Salary'!L11 -> 686964617 | G7: =+'Foreign Salary'!M11 -> 13338000 | H7: 0 | I7: =+'Foreign Salary'!P11 -> 193129316 | J7: 0 | K7: 0 | L7: =+(F7)-SUM(G7:K7) -> 480497301 | M7: =+L7/E7 -> 160165767
A8: =SUBTOTAL(3,B$7:B8) -> 2 | B8: SK2 | C8: P0 - Cleaning | D8: P0-CL-1-01 | E8: =COUNTIFS('Salary sheet'!$F$6:$F$2288,C8,'Salary sheet'!$E$6:$E$2288,B8) -> 4 | F8: =+SUMIFS('Salary sheet'!$AN$6:$AN$1292,'Salary sheet'!$F$6:$F$1292,'TOTAL(payment)'!C8,'Salary sheet'!$E$6:$E$1292,'TOTAL(payment)'!B8) -> 38438407 | G8: =+SUMIFS('Salary sheet'!$AO$6:$AO$2288,'Salary sheet'!$F$6:$F$2288,C8,'Salary sheet'!$E$6:$E$2288,B8) -> 2962470 | H8: =+SUMIFS('Salary sheet'!$AP$6:$AP$2288,'Salary sheet'!$F$6:$F$2288,C8,'Salary sheet'!$E$6:$E$2288,B8) -> 176400 | I8: =+SUMIFS('Salary sheet'!$AQ$6:$AQ$2288,'Salary sheet'!$F$6:$F$2288,C8,'Salary sheet'!$E$6:$E$2288,B8) -> 0 | J8: =+SUMIFS('Salary sheet'!$AR$6:$AR$2288,'Salary sheet'!$F$6:$F$2288,C8,'Salary sheet'!$E$6:$E$2288,B8) -> 0 | K8: =SUMIFS('Salary sheet'!$AS$6:$AS$1291,'Salary sheet'!$F$6:$F$1291,'TOTAL(payment)'!C8) -> 0 | L8: =+(F8)-SUM(G8:K8) -> 35299537 | M8: =+L8/E8 -> 8824884.2
A9: =SUBTOTAL(3,B$7:B9) -> 3 | B9: SK2 | C9: P0 - Design | D9: P0-DS-1-01 | E9: =COUNTIFS('Salary sheet'!$F$6:$F$2288,C9,'Salary sheet'!$E$6:$E$2288,B9) -> 4 | F9: =+SUMIFS('Salary sheet'!$AN$6:$AN$1292,'Salary sheet'!$F$6:$F$1292,'TOTAL(payment)'!C9,'Salary sheet'!$E$6:$E$1292,'TOTAL(payment)'!B9) -> 70351442 | G9: =+SUMIFS('Salary sheet'!$AO$6:$AO$2288,'Salary sheet'!$F$6:$F$2288,C9,'Salary sheet'!$E$6:$E$2288,B9) -> 7350000 | H9: =+SUMIFS('Salary sheet'!$AP$6:$AP$2288,'Salary sheet'!$F$6:$F$2288,C9,'Salary sheet'!$E$6:$E$2288,B9) -> 176400 | I9: =+SUMIFS('Salary sheet'!$AQ$6:$AQ$2288,'Salary sheet'!$F$6:$F$2288,C9,'Salary sheet'!$E$6:$E$2288,B9) -> 364524 | J9: =+SUMIFS('Salary sheet'!$AR$6:$AR$2288,'Salary sheet'!$F$6:$F$2288,C9,'Salary sheet'!$E$6:$E$2288,B9) -> 0 | K9: =SUMIFS('Salary sheet'!$AS$6:$AS$1291,'Salary sheet'!$F$6:$F$1291,'TOTAL(payment)'!C9) -> 0 | L9: =+(F9)-SUM(G9:K9) -> 62460518 | M9: =+L9/E9 -> 15615130
A10: =SUBTOTAL(3,B$7:B10) -> 4 | B10: SK2 | C10: P0 - Development | D10: P0-DE-1-01 | E10: =COUNTIFS('Salary sheet'!$F$6:$F$2288,C10,'Salary sheet'!$E$6:$E$2288,B10) -> 13 | F10: =+SUMIFS('Salary sheet'!$AN$6:$AN$1292,'Salary sheet'!$F$6:$F$1292,'TOTAL(payment)'!C10,'Salary sheet'!$E$6:$E$1292,'TOTAL(payment)'!B10) -> 207934161 | G10: =+SUMIFS('Salary sheet'!$AO$6:$AO$2288,'Salary sheet'!$F$6:$F$2288,C10,'Salary sheet'!$E$6:$E$2288,B10) -> 12238905 | H10: =+SUMIFS('Salary sheet'!$AP$6:$AP$2288,'Salary sheet'!$F$6:$F$2288,C10,'Salary sheet'!$E$6:$E$2288,B10) -> 573300 | I10: =+SUMIFS('Salary sheet'!$AQ$6:$AQ$2288,'Salary sheet'!$F$6:$F$2288,C10,'Salary sheet'!$E$6:$E$2288,B10) -> 428727 | J10: =+SUMIFS('Salary sheet'!$AR$6:$AR$2288,'Salary sheet'!$F$6:$F$2288,C10,'Salary sheet'!$E$6:$E$2288,B10) -> 0 | K10: =SUMIFS('Salary sheet'!$AS$6:$AS$1291,'Salary sheet'!$F$6:$F$1291,'TOTAL(payment)'!C10) -> 0 | L10: =+(F10)-SUM(G10:K10) -> 194693229 | M10: =+L10/E10 -> 14976402
A11: =SUBTOTAL(3,B$7:B11) -> 5 | B11: SK2 | C11: P0 - FG Warehouse | D11: P0-FG-1-01 | E11: =COUNTIFS('Salary sheet'!$F$6:$F$2288,C11,'Salary sheet'!$E$6:$E$2288,B11) -> 3 | F11: =+SUMIFS('Salary sheet'!$AN$6:$AN$1292,'Salary sheet'!$F$6:$F$1292,'TOTAL(payment)'!C11,'Salary sheet'!$E$6:$E$1292,'TOTAL(payment)'!B11) -> 34202056 | G11: =+SUMIFS('Salary sheet'!$AO$6:$AO$2288,'Salary sheet'!$F$6:$F$2288,C11,'Salary sheet'!$E$6:$E$2288,B11) -> 2592345 | H11: =+SUMIFS('Salary sheet'!$AP$6:$AP$2288,'Salary sheet'!$F$6:$F$2288,C11,'Salary sheet'!$E$6:$E$2288,B11) -> 132300 | I11: =+SUMIFS('Salary sheet'!$AQ$6:$AQ$2288,'Salary sheet'!$F$6:$F$2288,C11,'Salary sheet'!$E$6:$E$2288,B11) -> 0 | J11: =+SUMIFS('Salary sheet'!$AR$6:$AR$2288,'Salary sheet'!$F$6:$F$2288,C11,'Salary sheet'!$E$6:$E$2288,B11) -> 0 | K11: =SUMIFS('Salary sheet'!$AS$6:$AS$1291,'Salary sheet'!$F$6:$F$1291,'TOTAL(payment)'!C11) -> 0 | L11: =+(F11)-SUM(G11:K11) -> 31477411 | M11: =+L11/E11 -> 10492470
A12: =SUBTOTAL(3,B$7:B12) -> 6 | B12: SK2 | C12: P0 - GA-HR | D12: P0-HR-1-01 | E12: =COUNTIFS('Salary sheet'!$F$6:$F$2288,C12,'Salary sheet'!$E$6:$E$2288,B12) -> 3 | F12: =+SUMIFS('Salary sheet'!$AN$6:$AN$1292,'Salary sheet'!$F$6:$F$1292,'TOTAL(payment)'!C12,'Salary sheet'!$E$6:$E$1292,'TOTAL(payment)'!B12) -> 36890624 | G12: =+SUMIFS('Salary sheet'!$AO$6:$AO$2288,'Salary sheet'!$F$6:$F$2288,C12,'Salary sheet'!$E$6:$E$2288,B12) -> 3727500 | H12: =+SUMIFS('Salary sheet'!$AP$6:$AP$2288,'Salary sheet'!$F$6:$F$2288,C12,'Salary sheet'!$E$6:$E$2288,B12) -> 132300 | I12: =+SUMIFS('Salary sheet'!$AQ$6:$AQ$2288,'Salary sheet'!$F$6:$F$2288,C12,'Salary sheet'!$E$6:$E$2288,B12) -> 0 | J12: =+SUMIFS('Salary sheet'!$AR$6:$AR$2288,'Salary sheet'!$F$6:$F$2288,C12,'Salary sheet'!$E$6:$E$2288,B12) -> 0 | K12: =SUMIFS('Salary sheet'!$AS$6:$AS$1291,'Salary sheet'!$F$6:$F$1291,'TOTAL(payment)'!C12) -> 0 | L12: =+(F12)-SUM(G12:K12) -> 33030824 | M12: =+L12/E12 -> 11010275
A13: =SUBTOTAL(3,B$7:B13) -> 7 | B13: SK2 | C13: P0 - GC WIP | D13: P0-WP-1-01 | E13: =COUNTIFS('Salary sheet'!$F$6:$F$2288,C13,'Salary sheet'!$E$6:$E$2288,B13) -> 10 | F13: =+SUMIFS('Salary sheet'!$AN$6:$AN$1292,'Salary sheet'!$F$6:$F$1292,'TOTAL(payment)'!C13,'Salary sheet'!$E$6:$E$1292,'TOTAL(payment)'!B13) -> 139072979 | G13: =+SUMIFS('Salary sheet'!$AO$6:$AO$2288,'Salary sheet'!$F$6:$F$2288,C13,'Salary sheet'!$E$6:$E$2288,B13) -> 11025420 | H13: =+SUMIFS('Salary sheet'!$AP$6:$AP$2288,'Salary sheet'!$F$6:$F$2288,C13,'Salary sheet'!$E$6:$E$2288,B13) -> 441000 | I13: =+SUMIFS('Salary sheet'!$AQ$6:$AQ$2288,'Salary sheet'!$F$6:$F$2288,C13,'Salary sheet'!$E$6:$E$2288,B13) -> 170615 | J13: =+SUMIFS('Salary sheet'!$AR$6:$AR$2288,'Salary sheet'!$F$6:$F$2288,C13,'Salary sheet'!$E$6:$E$2288,B13) -> 0 | K13: =SUMIFS('Salary sheet'!$AS$6:$AS$1291,'Salary sheet'!$F$6:$F$1291,'TOTAL(payment)'!C13) -> 0 | L13: =+(F13)-SUM(G13:K13) -> 127435944 | M13: =+L13/E13 -> 12743594
A14: =SUBTOTAL(3,B$7:B14) -> 8 | B14: SK2 | C14: P0 - Maintenance | D14: P0-MA-1-01 | E14: =COUNTIFS('Salary sheet'!$F$6:$F$2288,C14,'Salary sheet'!$E$6:$E$2288,B14) -> 5 | F14: =+SUMIFS('Salary sheet'!$AN$6:$AN$1292,'Salary sheet'!$F$6:$F$1292,'TOTAL(payment)'!C14,'Salary sheet'!$E$6:$E$1292,'TOTAL(payment)'!B14) -> 81855000 | G14: =+SUMIFS('Salary sheet'!$AO$6:$AO$2288,'Salary sheet'!$F$6:$F$2288,C14,'Salary sheet'!$E$6:$E$2288,B14) -> 6744990 | H14: =+SUMIFS('Salary sheet'!$AP$6:$AP$2288,'Salary sheet'!$F$6:$F$2288,C14,'Salary sheet'!$E$6:$E$2288,B14) -> 220500 | I14: =+SUMIFS('Salary sheet'!$AQ$6:$AQ$2288,'Salary sheet'!$F$6:$F$2288,C14,'Salary sheet'!$E$6:$E$2288,B14) -> 132102 | J14: =+SUMIFS('Salary sheet'!$AR$6:$AR$2288,'Salary sheet'!$F$6:$F$2288,C14,'Salary sheet'!$E$6:$E$2288,B14) -> 0 | K14: =SUMIFS('Salary sheet'!$AS$6:$AS$1291,'Salary sheet'!$F$6:$F$1291,'TOTAL(payment)'!C14) -> 0 | L14: =+(F14)-SUM(G14:K14) -> 74757408 | M14: =+L14/E14 -> 14951482
A15: =SUBTOTAL(3,B$7:B15) -> 9 | B15: SK2 | C15: P0 - Marketing | D15: P0-MK-1-01 | E15: =COUNTIFS('Salary sheet'!$F$6:$F$2288,C15,'Salary sheet'!$E$6:$E$2288,B15) -> 9 | F15: =+SUMIFS('Salary sheet'!$AN$6:$AN$1292,'Salary sheet'!$F$6:$F$1292,'TOTAL(payment)'!C15,'Salary sheet'!$E$6:$E$1292,'TOTAL(payment)'!B15) -> 160153125 | G15: =+SUMIFS('Salary sheet'!$AO$6:$AO$2288,'Salary sheet'!$F$6:$F$2288,C15,'Salary sheet'!$E$6:$E$2288,B15) -> 16695000 | H15: =+SUMIFS('Salary sheet'!$AP$6:$AP$2288,'Salary sheet'!$F$6:$F$2288,C15,'Salary sheet'!$E$6:$E$2288,B15) -> 396900 | I15: =+SUMIFS('Salary sheet'!$AQ$6:$AQ$2288,'Salary sheet'!$F$6:$F$2288,C15,'Salary sheet'!$E$6:$E$2288,B15) -> 659735 | J15: =+SUMIFS('Salary sheet'!$AR$6:$AR$2288,'Salary sheet'!$F$6:$F$2288,C15,'Salary sheet'!$E$6:$E$2288,B15) -> 0 | K15: =SUMIFS('Salary sheet'!$AS$6:$AS$1291,'Salary sheet'!$F$6:$F$1291,'TOTAL(payment)'!C15) -> 0 | L15: =+(F15)-SUM(G15:K15) -> 142401490 | M15: =+L15/E15 -> 15822388
A16: =SUBTOTAL(3,B$7:B16) -> 10 | B16: SK2 | C16: P0 - Material Warehouse | D16: P0-MW-1-01 | E16: =COUNTIFS('Salary sheet'!$F$6:$F$2288,C16,'Salary sheet'!$E$6:$E$2288,B16) -> 5 | F16: =+SUMIFS('Salary sheet'!$AN$6:$AN$1292,'Salary sheet'!$F$6:$F$1292,'TOTAL(payment)'!C16,'Salary sheet'!$E$6:$E$1292,'TOTAL(payment)'!B16) -> 56711533 | G16: =+SUMIFS('Salary sheet'!$AO$6:$AO$2288,'Salary sheet'!$F$6:$F$2288,C16,'Salary sheet'!$E$6:$E$2288,B16) -> 4168306 | H16: =+SUMIFS('Salary sheet'!$AP$6:$AP$2288,'Salary sheet'!$F$6:$F$2288,C16,'Salary sheet'!$E$6:$E$2288,B16) -> 132300 | I16: =+SUMIFS('Salary sheet'!$AQ$6:$AQ$2288,'Salary sheet'!$F$6:$F$2288,C16,'Salary sheet'!$E$6:$E$2288,B16) -> 33447 | J16: =+SUMIFS('Salary sheet'!$AR$6:$AR$2288,'Salary sheet'!$F$6:$F$2288,C16,'Salary sheet'!$E$6:$E$2288,B16) -> 0 | K16: =SUMIFS('Salary sheet'!$AS$6:$AS$1291,'Salary sheet'!$F$6:$F$1291,'TOTAL(payment)'!C16) -> 186299 | L16: =+(F16)-SUM(G16:K16) -> 52191181 | M16: =+L16/E16 -> 10438236
A17: =SUBTOTAL(3,B$7:B17) -> 11 | B17: SK2 | C17: P0 - Planning | D17: P0-PL-1-01 | E17: =COUNTIFS('Salary sheet'!$F$6:$F$2288,C17,'Salary sheet'!$E$6:$E$2288,B17) -> 9 | F17: =+SUMIFS('Salary sheet'!$AN$6:$AN$1292,'Salary sheet'!$F$6:$F$1292,'TOTAL(payment)'!C17,'Salary sheet'!$E$6:$E$1292,'TOTAL(payment)'!B17) -> 104930197 | G17: =+SUMIFS('Salary sheet'!$AO$6:$AO$2288,'Salary sheet'!$F$6:$F$2288,C17,'Salary sheet'!$E$6:$E$2288,B17) -> 10774995 | H17: =+SUMIFS('Salary sheet'!$AP$6:$AP$2288,'Salary sheet'!$F$6:$F$2288,C17,'Salary sheet'!$E$6:$E$2288,B17) -> 352800 | I17: =+SUMIFS('Salary sheet'!$AQ$6:$AQ$2288,'Salary sheet'!$F$6:$F$2288,C17,'Salary sheet'!$E$6:$E$2288,B17) -> 113181 | J17: =+SUMIFS('Salary sheet'!$AR$6:$AR$2288,'Salary sheet'!$F$6:$F$2288,C17,'Salary sheet'!$E$6:$E$2288,B17) -> 0 | K17: =SUMIFS('Salary sheet'!$AS$6:$AS$1291,'Salary sheet'!$F$6:$F$1291,'TOTAL(payment)'!C17) -> 0 | L17: =+(F17)-SUM(G17:K17) -> 93689221 | M17: =+L17/E17 -> 10409913
A18: =SUBTOTAL(3,B$7:B18) -> 12 | B18: SK2 | C18: P0 - Production Office | D18: P0-PO-1-01 | E18: =COUNTIFS('Salary sheet'!$F$6:$F$2288,C18,'Salary sheet'!$E$6:$E$2288,B18) -> 1 | F18: =+SUMIFS('Salary sheet'!$AN$6:$AN$1292,'Salary sheet'!$F$6:$F$1292,'TOTAL(payment)'!C18,'Salary sheet'!$E$6:$E$1292,'TOTAL(payment)'!B18) -> 38500000 | G18: =+SUMIFS('Salary sheet'!$AO$6:$AO$2288,'Salary sheet'!$F$6:$F$2288,C18,'Salary sheet'!$E$6:$E$2288,B18) -> 3969000 | H18: =+SUMIFS('Salary sheet'!$AP$6:$AP$2288,'Salary sheet'!$F$6:$F$2288,C18,'Salary sheet'!$E$6:$E$2288,B18) -> 44100 | I18: =+SUMIFS('Salary sheet'!$AQ$6:$AQ$2288,'Salary sheet'!$F$6:$F$2288,C18,'Salary sheet'!$E$6:$E$2288,B18) -> 283100 | J18: =+SUMIFS('Salary sheet'!$AR$6:$AR$2288,'Salary sheet'!$F$6:$F$2288,C18,'Salary sheet'!$E$6:$E$2288,B18) -> 0 | K18: =SUMIFS('Salary sheet'!$AS$6:$AS$1291,'Salary sheet'!$F$6:$F$1291,'TOTAL(payment)'!C18) -> 0 | L18: =+(F18)-SUM(G18:K18) -> 34203800 | M18: =+L18/E18 -> 34203800
A19: =SUBTOTAL(3,B$7:B19) -> 13 | B19: SK2 | C19: P0 - Purchasing | D19: P0-PU-1-01 | E19: =COUNTIFS('Salary sheet'!$F$6:$F$2288,C19,'Salary sheet'!$E$6:$E$2288,B19) -> 1 | F19: =+SUMIFS('Salary sheet'!$AN$6:$AN$1292,'Salary sheet'!$F$6:$F$1292,'TOTAL(payment)'!C19,'Salary sheet'!$E$6:$E$1292,'TOTAL(payment)'!B19) -> 9706348 | G19: =+SUMIFS('Salary sheet'!$AO$6:$AO$2288,'Salary sheet'!$F$6:$F$2288,C19,'Salary sheet'!$E$6:$E$2288,B19) -> 1012620 | H19: =+SUMIFS('Salary sheet'!$AP$6:$AP$2288,'Salary sheet'!$F$6:$F$2288,C19,'Salary sheet'!$E$6:$E$2288,B19) -> 44100 | I19: =+SUMIFS('Salary sheet'!$AQ$6:$AQ$2288,'Salary sheet'!$F$6:$F$2288,C19,'Salary sheet'!$E$6:$E$2288,B19) -> 0 | J19: =+SUMIFS('Salary sheet'!$AR$6:$AR$2288,'Salary sheet'!$F$6:$F$2288,C19,'Salary sheet'!$E$6:$E$2288,B19) -> 0 | K19: =SUMIFS('Salary sheet'!$AS$6:$AS$1291,'Salary sheet'!$F$6:$F$1291,'TOTAL(payment)'!C19) -> 0 | L19: =+(F19)-SUM(G19:K19) -> 8649628 | M19: =+L19/E19 -> 8649628
... A118: =SUBTOTAL(3,B$7:B118) -> 112 | B118: FACTORY A | C118: P8 - Slitter | D118: P8-CU-1-01 | E118: =COUNTIFS('Salary sheet'!$F$6:$F$2288,C118,'Salary sheet'!$E$6:$E$2288,B118) -> 1 | F118: =+SUMIFS('Salary sheet'!$AN$6:$AN$1292,'Salary sheet'!$F$6:$F$1292,'TOTAL(payment)'!C118,'Salary sheet'!$E$6:$E$1292,'TOTAL(payment)'!B118) -> 8278438 | G118: =+SUMIFS('Salary sheet'!$AO$6:$AO$2288,'Salary sheet'!$F$6:$F$2288,C118,'Salary sheet'!$E$6:$E$2288,B118) -> 627270 | H118: =+SUMIFS('Salary sheet'!$AP$6:$AP$2288,'Salary sheet'!$F$6:$F$2288,C118,'Salary sheet'!$E$6:$E$2288,B118) -> 44100 | I118: =+SUMIFS('Salary sheet'!$AQ$6:$AQ$2288,'Salary sheet'!$F$6:$F$2288,C118,'Salary sheet'!$E$6:$E$2288,B118) -> 0 | J118: =+SUMIFS('Salary sheet'!$AR$6:$AR$2288,'Salary sheet'!$F$6:$F$2288,C118,'Salary sheet'!$E$6:$E$2288,B118) -> 0 | K118: =SUMIFS('Salary sheet'!$AS$6:$AS$1291,'Salary sheet'!$F$6:$F$1291,'TOTAL(payment)'!C118) -> 0 | L118: =+(F118)-SUM(G118:K118) -> 7607068 | M118: =+L118/E118 -> 7607068
A119: x | E119: =SUM(E7:E118) -> 1289 | F119: =SUM(F7:F118) -> 14329763701 | G119: =SUM(G7:G118) -> 998000257 | H119: =SUM(H7:H118) -> 52434900 | I119: =SUM(I7:I118) -> 208839267 | J119: =SUM(J7:J118) -> 568500 | K119: =SUM(K7:K118) -> 3199861 | L119: =SUM(L7:L118) -> 13066720916 | M119: =SUM(M7:M112) -> 1.3132829e+09 | N119: =+L119-(L7+'Salary sheet'!AT1292) -> 0
E120: =+E119-E7 -> 1286 | F120: =+F119-F7 -> 13642799084 | G120: =+G119-G7 -> 984662257 | H120: =+H119-H7 -> 52434900 | I120: =+I119-I7 -> 15709951 | J120: =+J119-J7 -> 568500 | K120: =+K119-K7 -> 3199861 | L120: =+L119-L7 -> 12586223615 | M120: =+M119-M7 -> 1.1531171e+09
E121: =+E119-E7-E120 -> 0 | F121: =+F119-F7-F120 -> 0 | G121: =+G119-G7-G120 -> 0 | H121: =+H119-H7-H120 -> 0 | I121: =+I119-I7-I120 -> 0 | J121: =+J119-J7-J120 -> 0 | K121: =+K119-K7-K120 -> 0 | L121: =+L119-L7-L120 -> 0
K123: Bình Phước, Ngày 30 tháng 04 năm 2025
B124: Người lập / Prepare by | G124: Kiểm tra/ Checked by | K124: Giám Đốc /Director
B132: Đỗ Thị Vân | G132: Nguyễn Thị Hà | K132: Kim Dong Woo

Sheet Foreign Salary
A1: Công ty TNHH Bao Bì Cao Cấp S&K Vina | H1: 26
A2: Lô B1 -B4 KCn Minh Hưng - Hàn Quốc | V2: SK1 Box | W2: =ROUND(R8/2,0)+ROUND(R9/2,0) -> 181751969
A3: H. Chơn Thành - Bình Phước | V3: SK1 Bag | W3: =+(R9+R8)-W2 -> 181751968
V4: SK2 | W4: =+R10 -> 116993364
A5: BẢNG LƯƠNG THÁNG 04 NĂM 2025 PAY-SHEET OF SALARY APR 2025 | W5: =+W4+W2+W3 -> 480497301
A6: Exchange Rate : 26,115 VND/USD | L6: 26115
A7: Stt No. | B7: Họ và tên Name | C7: Tên người thụ hưởng Beneficiary Name | D7: English name | E7: Fac | F7: Lương cơ bản Basic Salary (USD) | G7: Lương cơ bản Basic Salary (VND) | H7: Ngày công thực tế Actual Workday | I7: Lương cơ bản Basic Salary (USD) | J7: Month | K7: 13Th month bonus | L7: Lương CB Gross Salary VND | M7: BHXH,YT (9.5%) Insurance | N7: Nha o | O7: TNTT | P7: Thuế TNCN Personal income Tax | Q7: Advance | R7: Tiền thực lãnh Net salary VND | S7: Tiền thực lãnh Net salary USD (Paid) | T7: Contract salary | U7: Note
A8: 1 | B8: KIM DONG WOO | C8: KIM DONG WOO | D8: Mr DW | E8: FACTORY O | F8: 10300 | G8: =+F8*$L$6 -> 268984500 | H8: 26 | I8: =+F8/$H$1*H8 -> 10300 | L8: =ROUND((((K8+I8)*$L$6)),0) -> 268984500 | M8: =2340000*20*9.5% -> 4446000 | O8: =L8+N8-M8-11000000 -> 253538500 | P8: =ROUND(35%*O8-9850000,0) -> 78888475 | R8: =ROUND(L8-P8-M8-Q8,0) -> 185650025 | S8: =ROUND(R8/$L$6,2) -> 7108.94 | U8: SK1 Bag/Box
A9: 2 | B9: KIM JE MIN | C9: KIM JE MIN | D9: Mr JM | E9: FACTORY O | F9: 9750 | G9: =+F9*$L$6 -> 254621250 | H9: 26 | I9: =+F9/$H$1*H9 -> 9750 | L9: =ROUND((((K9+I9)*$L$6)),0) -> 254621250 | M9: =2340000*20*9.5% -> 4446000 | O9: =L9+N9-M9-11000000-4400000 -> 234775250 | P9: =ROUND(35%*O9-9850000,0) -> 72321338 | R9: =ROUND(L9-P9-M9-Q9,0) -> 177853912 | S9: =ROUND(R9/$L$6,2) -> 6810.41 | U9: SK1 Bag/Box | V9: ĐK 1 Người phụ thuộc từ tháng 10/2024
A10: 3 | B10: YUE FAMENG | C10: YUE FAMENG | D10: Mr Happy | E10: FACTORY H | F10: 6505.58 | G10: =+F10*$L$6 -> 1.6989322e+08 | H10: 25 | I10: =+F10/$H$1*H10 -> 6255.3654 | L10: =ROUND((((K10+I10)*$L$6)),0) -> 163358867 | M10: =2340000*20*9.5% -> 4446000 | O10: =L10+N10-M10-11000000 -> 147912867 | P10: =ROUND(35%*O10-9850000,0) -> 41919503 | R10: =ROUND(L10-P10-M10-Q10,0) -> 116993364 | S10: =ROUND(R10/$L$6,2) -> 4479.93 | U10: SK2
A11: TOTAL | F11: =SUM(F8:F10) -> 26555.58 | G11: =SUM(G8:G10) -> 6.9349897e+08 | H11: =SUM(H8:H10) -> 77 | I11: =SUM(I8:I10) -> 26305.365 | J11: =SUM(J8:J10) -> 0 | K11: =SUM(K8:K10) -> 0 | L11: =SUM(L8:L10) -> 686964617 | M11: =SUM(M8:M10) -> 13338000 | ... S11: =SUM(S8:S10) -> 18399.28
P14: =+'TOTAL(payment)'!K123 -> Bình Phước, Ngày 30 tháng 04 năm 2025
B15: Người lập / Prepare by | H15: Kiểm tra/ Checked by | P15: Giám Đốc /Director
B23: Đỗ Thị Vân | H23: Nguyễn Thị Hà | P23: Kim Dong Woo

Sheet Salary sheet
M2: 26
A3: REPORT - BẢNG LƯƠNG THÁNG 04 NĂM 2025 PAY - SHEET OF APR 2025
A4: TT No. | B4: Mã thẻ Code | C4: Họ và tên Name | D4: Ngày vào Entry day | F4: Bộ phận Dep | G4: Title/ Chức danh | H4: Lương hợp đồng Contract salary | M4: Ngày làm việc thực tế Actual Working day | O4: Nghỉ có hưởng lương Paid leave | Q4: Ca đêm extra pay for night work + 30%) | S4: Lương, thưởng và các khoản hỗ trợ Salary, bonus, support fee | AG4: Cộng Total | AH4: Tăng ca Overtime | AN4: Tổng thu nhập Total Gross Salary | AO4: Khấu trừ Reduction | AT4: Tiền thực lãnh Net Salary | AU4: Ký nhận Signature | AW4: Tên TK | AX4: Số TK
E5: Fac | H5: Cơ bản Basic salary | I5: Trách nhiệm Responsibility | J5: Phụ cấp NNĐH Hazadouse allowance (>=5% of basic salary) | K5: Phụ cấp chức danh/Title Allowance | L5: Cộng Total | M5: Ngày công Day | N5: Lương CB + trách nhiệm Basic Salary + Responsibility | O5: Ngày công Day | P5: Lương CB + trách nhiệm Basic Salary + Responsibility | Q5: Giờ công Hour | R5: Lương CB + trách nhiệm Basic Salary + Responsibility | S5: Lương CB + trách nhiệm Basic salary + Responsibility | T5: Điện thoại, Telephone fee | U5: Tiền cơm Meal Allowance | V5: Hỗ trợ xăng + nhà trọ, Mileage, house | W5: Thưởng chuyên cần Diligent Bonus | X5: Phụ cấp PCCC PCCC / ATVSV allowance (30% of government basic salary and safety - hygency team) | Y5: Thưởng ABC ABC Bonus | Z5: Thưởng năng suất Production bonus | AA5: Ngày phép | AB5: Phép năm Annual Leave | AC5: Con nhỏ Support for baby (1-6) | AD5: Bảo hiểm, thất nghiệp Additional salary , insurance, Unempl-oyment Benefit, Bù Lương, Công Tác phí | AE5: Phụ cấp Phụ Nữ Menstruation allowance | AF5: 13Th Month Bonus | AH5: 1.5 | AI5: 2 | AJ5: 2.1 | AK5: 2.7 | AL5: 3 | AM5: Tổng tiền Amount | AO5: BHXH +YT, +TN Insurance | AP5: KPCĐ Union Dues | AQ5: Personal Income Tax Thuế TNCN | AR5: Đồng phục Uniform | AS5: Advance Chênh lệch HĐ/ Biên bản Paid | AY5: =+IF(B5="SK2","SK2",IF(B5="FACTORY A","SK1 Box",IF(B5="FACTORY D","SK1 Bag","Chia"))) -> Chia | BA5: =+IF(AY5="SK1 Box","Box",IF(AY5="Seaman","Seaman","Bag")) -> Bag
A6: =SUBTOTAL(3,B$6:B6) -> 1 | B6: C0873 | C6: Trần Thị Kim Phấn | D6: 39707 | E6: FACTORY A | F6: P6 - C.Box Assembly | G6: Box Positioning worker | H6: 5931000 | I6: 200000 | J6: 0 | K6: 0 | L6: =SUM(H6:K6) -> 6131000 | M6: 24 | N6: =ROUND((H6+I6+J6+K6)/IF($M$2>26,26,$M$2)*M6,0) -> 5659385 | O6: 2 | P6: =ROUND((H6+I6+J6+K6)/IF($M$2>26,26,$M$2)*O6,0) -> 471615 | Q6: 0 | R6: =IF(M6>0,ROUND(N6/IF(M6>26,26,M6)/8*Q6*30%,0),0) -> 0 | S6: =N6+P6+R6 -> 6131000 | T6: 0 | U6: 0 | V6: 200000 | W6: 500000 | X6: 0 | Y6: 0 | Z6: 188548 | AC6: 0 | AD6: 0 | AE6: 44213.945 | AG6: =ROUND(SUM(S6:AF6)-AA6,0) -> 7063762 | AH6: 48 | AI6: 0 | AJ6: 0 | AK6: 0 | AL6: 0 | AM6: =ROUND((N6/IF(M6>26,26,M6)/8*(AH6*$AH$5+AI6*$AI$5+AJ6*$AJ$5+AK6*$AK$5+AL6*$AL$5)),0) -> 2122269 | AN6: =ROUND(AG6+AM6,0) -> 9186031 | AO6: 643755 | AP6: 44100 | AQ6: 0 | AR6: 0 | AS6: 0 | AT6: =+ROUND(SUM(AN6:AN6)-SUM(AO6:AS6),0) -> 8498176 | AW6: TRAN THI KIM PHAN | AX6: 050040964964 | AY6: SK1 Box | AZ6: 622 | BA6: =+IF(AY6="SK1 Box","Box",IF(AY6="Seaman","Seaman","Bag")) -> Box
A7: =SUBTOTAL(3,B$6:B7) -> 2 | B7: C1007 | C7: Nguyễn Thị Hướng | D7: 39707 | E7: FACTORY A | F7: P6 - C.Box Assembly | G7: Box Positioning worker | H7: 5931000 | I7: 200000 | J7: 0 | K7: 300000 | L7: =SUM(H7:K7) -> 6431000 | M7: 23.8 | N7: =ROUND((H7+I7+J7+K7)/IF($M$2>26,26,$M$2)*M7,0) -> 5886838 | O7: 2 | P7: =ROUND((H7+I7+J7+K7)/IF($M$2>26,26,$M$2)*O7,0) -> 494692 | Q7: 0 | R7: =IF(M7>0,ROUND(N7/IF(M7>26,26,M7)/8*Q7*30%,0),0) -> 0 | S7: =N7+P7+R7 -> 6381530 | T7: 0 | U7: 0 | V7: 200000 | W7: 500000 | X7: 0 | Y7: 400000 | Z7: 603480 | AC7: 0 | AD7: 0 | AE7: 46377.4 | AG7: =ROUND(SUM(S7:AF7)-AA7,0) -> 8131387 | AH7: 52 | AI7: 0 | AJ7: 0 | AK7: 0 | AL7: 0 | AM7: =ROUND((N7/IF(M7>26,26,M7)/8*(AH7*$AH$5+AI7*$AI$5+AJ7*$AJ$5+AK7*$AK$5+AL7*$AL$5)),0) -> 2411625 | AN7: =ROUND(AG7+AM7,0) -> 10543012 | AO7: 675255 | AP7: 44100 | AQ7: 0 | AR7: 0 | AS7: 0 | AT7: =+ROUND(SUM(AN7:AN7)-SUM(AO7:AS7),0) -> 9823657 | AW7: NGUYEN THI HUONG | AX7: 050040850950 | AY7: SK1 Box | AZ7: 622 | BA7: =+IF(AY7="SK1 Box","Box",IF(AY7="Seaman","Seaman","Bag")) -> Box
A8: =SUBTOTAL(3,B$6:B8) -> 3 | B8: C1009 | C8: Hồ Thị Nga | D8: 39707 | E8: FACTORY A | F8: P6 - C.Box Assembly | G8: Box Positioning worker | H8: 5931000 | I8: 200000 | J8: 0 | K8: 0 | L8: =SUM(H8:K8) -> 6131000 | M8: 24 | N8: =ROUND((H8+I8+J8+K8)/IF($M$2>26,26,$M$2)*M8,0) -> 5659385 | O8: 2 | P8: =ROUND((H8+I8+J8+K8)/IF($M$2>26,26,$M$2)*O8,0) -> 471615 | Q8: 0 | R8: =IF(M8>0,ROUND(N8/IF(M8>26,26,M8)/8*Q8*30%,0),0) -> 0 | S8: =N8+P8+R8 -> 6131000 | T8: 0 | U8: 0 | V8: 200000 | W8: 500000 | X8: 0 | Y8: 400000 | Z8: 600597 | AC8: 0 | AD8: 0 | AE8: 44213.945 | AG8: =ROUND(SUM(S8:AF8)-AA8,0) -> 7875811 | AH8: 52 | AI8: 0 | AJ8: 0 | AK8: 0 | AL8: 0 | AM8: =ROUND((N8/IF(M8>26,26,M8)/8*(AH8*$AH$5+AI8*$AI$5+AJ8*$AJ$5+AK8*$AK$5+AL8*$AL$5)),0) -> 2299125 | AN8: =ROUND(AG8+AM8,0) -> 10174936 | AO8: 643755 | AP8: 44100 | AQ8: 0 | AR8: 0 | AS8: 0 | AT8: =+ROUND(SUM(AN8:AN8)-SUM(AO8:AS8),0) -> 9487081 | AW8: HO THI NGA | AX8: 050040952974 | AY8: SK1 Box | AZ8: 622 | BA8: =+IF(AY8="SK1 Box","Box",IF(AY8="Seaman","Seaman","Bag")) -> Box
A9: =SUBTOTAL(3,B$6:B9) -> 4 | B9: C10454 | C9: Trần Thị Liên | D9: 43556 | E9: FACTORY A | F9: P6 - C.Box Assembly | G9: Box Positioning worker | H9: 5931000 | I9: 200000 | J9: 0 | K9: 0 | L9: =SUM(H9:K9) -> 6131000 | M9: 24 | N9: =ROUND((H9+I9+J9+K9)/IF($M$2>26,26,$M$2)*M9,0) -> 5659385 | O9: 2 | P9: =ROUND((H9+I9+J9+K9)/IF($M$2>26,26,$M$2)*O9,0) -> 471615 | Q9: 0 | R9: =IF(M9>0,ROUND(N9/IF(M9>26,26,M9)/8*Q9*30%,0),0) -> 0 | S9: =N9+P9+R9 -> 6131000 | T9: 0 | U9: 0 | V9: 200000 | W9: 500000 | X9: 0 | Y9: 400000 | Z9: 606304 | AC9: 0 | AD9: 0 | AE9: 44213.945 | AG9: =ROUND(SUM(S9:AF9)-AA9,0) -> 7881518 | AH9: 48 | AI9: 0 | AJ9: 0 | AK9: 0 | AL9: 0 | AM9: =ROUND((N9/IF(M9>26,26,M9)/8*(AH9*$AH$5+AI9*$AI$5+AJ9*$AJ$5+AK9*$AK$5+AL9*$AL$5)),0) -> 2122269 | AN9: =ROUND(AG9+AM9,0) -> 10003787 | AO9: 643755 | AP9: 44100 | AQ9: 0 | AR9: 0 | AS9: 0 | AT9: =+ROUND(SUM(AN9:AN9)-SUM(AO9:AS9),0) -> 9315932 | AW9: TRAN THI LIEN | AX9: 050104743444 | AY9: SK1 Box | AZ9: 622 | BA9: =+IF(AY9="SK1 Box","Box",IF(AY9="Seaman","Seaman","Bag")) -> Box
A10: =SUBTOTAL(3,B$6:B10) -> 5 | B10: C10664 | C10: Nguyễn Hoài Hận | D10: 43595 | E10: FACTORY A | F10: P6 - C.Box Assembly | G10: Box Positioning worker | H10: 5931000 | I10: 200000 | J10: 0 | K10: 0 | L10: =SUM(H10:K10) -> 6131000 | M10: 23.7 | N10: =ROUND((H10+I10+J10+K10)/IF($M$2>26,26,$M$2)*M10,0) -> 5588642 | O10: 2 | P10: =ROUND((H10+I10+J10+K10)/IF($M$2>26,26,$M$2)*O10,0) -> 471615 | Q10: 0 | R10: =IF(M10>0,ROUND(N10/IF(M10>26,26,M10)/8*Q10*30%,0),0) -> 0 | S10: =N10+P10+R10 -> 6060257 | T10: 0 | U10: 0 | V10: 200000 | W10: 500000 | X10: 0 | Y10: 400000 | Z10: 603480 | AC10: 0 | AD10: 0 | AE10: 0 | AG10: =ROUND(SUM(S10:AF10)-AA10,0) -> 7763737 | AH10: 52 | AI10: 0 | AJ10: 0 | AK10: 0 | AL10: 0 | AM10: =ROUND((N10/IF(M10>26,26,M10)/8*(AH10*$AH$5+AI10*$AI$5+AJ10*$AJ$5+AK10*$AK$5+AL10*$AL$5)),0) -> 2299125 | AN10: =ROUND(AG10+AM10,0) -> 10062862 | AO10: 643755 | AP10: 44100 | AQ10: 0 | AR10: 0 | AS10: 0 | AT10: =+ROUND(SUM(AN10:AN10)-SUM(AO10:AS10),0) -> 9375007 | AW10: NGUYEN HOAI HAN | AX10: 050073573855 | AY10: SK1 Box | AZ10: 622 | BA10: =+IF(AY10="SK1 Box","Box",IF(AY10="Seaman","Seaman","Bag")) -> Box
A11: =SUBTOTAL(3,B$6:B11) -> 6 | B11: C10665 | C11: Lê Thị Kiều Loan | D11: 43595 | E11: FACTORY A | F11: P6 - C.Box Assembly | G11: Normal worker | H11: 5931000 | I11: 0 | J11: 0 | K11: 0 | L11: =SUM(H11:K11) -> 5931000 | M11: 24 | N11: =ROUND((H11+I11+J11+K11)/IF($M$2>26,26,$M$2)*M11,0) -> 5474769 | O11: 2 | P11: =ROUND((H11+I11+J11+K11)/IF($M$2>26,26,$M$2)*O11,0) -> 456231 | Q11: 0 | R11: =IF(M11>0,ROUND(N11/IF(M11>26,26,M11)/8*Q11*30%,0),0) -> 0 | S11: =N11+P11+R11 -> 5931000 | T11: 0 | U11: 0 | V11: 200000 | W11: 500000 | X11: 0 | Y11: 300000 | Z11: 606304 | AC11: 0 | AD11: 0 | AE11: 42771.633 | AG11: =ROUND(SUM(S11:AF11)-AA11,0) -> 7580076 | AH11: 40 | AI11: 0 | AJ11: 0 | AK11: 0 | AL11: 0 | AM11: =ROUND((N11/IF(M11>26,26,M11)/8*(AH11*$AH$5+AI11*$AI$5+AJ11*$AJ$5+AK11*$AK$5+AL11*$AL$5)),0) -> 1710865 | AN11: =ROUND(AG11+AM11,0) -> 9290941 | AO11: 622755 | AP11: 44100 | AQ11: 0 | AR11: 0 | AS11: 0 | AT11: =+ROUND(SUM(AN11:AN11)-SUM(AO11:AS11),0) -> 8624086 | AW11: LE THI KIEU LOAN | AX11: 050106514035 | AY11: SK1 Box | AZ11: 622 | BA11: =+IF(AY11="SK1 Box","Box",IF(AY11="Seaman","Seaman","Bag")) -> Box
A12: =SUBTOTAL(3,B$6:B12) -> 7 | B12: C1074 | C12: Phan Thị Thanh Tâm | D12: 39715 | E12: FACTORY A | F12: P6 - C.Box Assembly | G12: Box Positioning worker | H12: 5931000 | I12: 200000 | J12: 0 | K12: 0 | L12: =SUM(H12:K12) -> 6131000 | M12: 23.9 | N12: =ROUND((H12+I12+J12+K12)/IF($M$2>26,26,$M$2)*M12,0) -> 5635804 | O12: 2 | P12: =ROUND((H12+I12+J12+K12)/IF($M$2>26,26,$M$2)*O12,0) -> 471615 | Q12: 0 | R12: =IF(M12>0,ROUND(N12/IF(M12>26,26,M12)/8*Q12*30%,0),0) -> 0 | S12: =N12+P12+R12 -> 6107419 | T12: 0 | U12: 0 | V12: 200000 | W12: 500000 | X12: 0 | Y12: 400000 | Z12: 590658 | AC12: 100000 | AD12: 0 | AE12: 44213.944 | AG12: =ROUND(SUM(S12:AF12)-AA12,0) -> 7942291 | AH12: 52 | AI12: 0 | AJ12: 0 | AK12: 0 | AL12: 0 | AM12: =ROUND((N12/IF(M12>26,26,M12)/8*(AH12*$AH$5+AI12*$AI$5+AJ12*$AJ$5+AK12*$AK$5+AL12*$AL$5)),0) -> 2299125 | AN12: =ROUND(AG12+AM12,0) -> 10241416 | AO12: 643755 | AP12: 44100 | AQ12: 0 | AR12: 0 | AS12: 0 | AT12: =+ROUND(SUM(AN12:AN12)-SUM(AO12:AS12),0) -> 9553561 | AW12: PHAN THI THANH TAM | AX12: 050040932884 | AY12: SK1 Box | AZ12: 622 | BA12: =+IF(AY12="SK1 Box","Box",IF(AY12="Seaman","Seaman","Bag")) -> Box
A13: =SUBTOTAL(3,B$6:B13) -> 8 | B13: C11208 | C13: Lê Thị Bích Linh | D13: 43684 | E13: FACTORY A | F13: P6 - C.Box Assembly | G13: Box Positioning worker | H13: 5931000 | I13: 200000 | J13: 0 | K13: 0 | L13: =SUM(H13:K13) -> 6131000 | M13: 22.6 | N13: =ROUND((H13+I13+J13+K13)/IF($M$2>26,26,$M$2)*M13,0) -> 5329254 | O13: 3 | P13: =ROUND((H13+I13+J13+K13)/IF($M$2>26,26,$M$2)*O13,0) -> 707423 | Q13: 0 | R13: =IF(M13>0,ROUND(N13/IF(M13>26,26,M13)/8*Q13*30%,0),0) -> 0 | S13: =N13+P13+R13 -> 6036677 | T13: 0 | U13: 0 | V13: 200000 | W13: 500000 | X13: 0 | Y13: 400000 | Z13: 558491 | AC13: 0 | AD13: 0 | AE13: 44213.944 | AG13: =ROUND(SUM(S13:AF13)-AA13,0) -> 7739382 | AH13: 48 | AI13: 0 | AJ13: 0 | AK13: 0 | AL13: 0 | AM13: =ROUND((N13/IF(M13>26,26,M13)/8*(AH13*$AH$5+AI13*$AI$5+AJ13*$AJ$5+AK13*$AK$5+AL13*$AL$5)),0) -> 2122269 | AN13: =ROUND(AG13+AM13,0) -> 9861651 | AO13: 643755 | AP13: 44100 | AQ13: 0 | AR13: 0 | AS13: 0 | AT13: =+ROUND(SUM(AN13:AN13)-SUM(AO13:AS13),0) -> 9173796 | AW13: LE THI BICH LINH | AX13: 050111434058 | AY13: SK1 Box | AZ13: 622 | BA13: =+IF(AY13="SK1 Box","Box",IF(AY13="Seaman","Seaman","Bag")) -> Box
A14: =SUBTOTAL(3,B$6:B14) -> 9 | B14: C11863 | C14: Trần Hải Nam | D14: 43874 | E14: FACTORY A | F14: P6 - C.Box Assembly | G14: Stickers Box worker | H14: 5931000 | I14: 200000 | J14: 0 | K14: 0 | L14: =SUM(H14:K14) -> 6131000 | M14: 24 | N14: =ROUND((H14+I14+J14+K14)/IF($M$2>26,26,$M$2)*M14,0) -> 5659385 | O14: 2 | P14: =ROUND((H14+I14+J14+K14)/IF($M$2>26,26,$M$2)*O14,0) -> 471615 | Q14: 0 | R14: =IF(M14>0,ROUND(N14/IF(M14>26,26,M14)/8*Q14*30%,0),0) -> 0 | S14: =N14+P14+R14 -> 6131000 | T14: 0 | U14: 0 | V14: 200000 | W14: 500000 | X14: 0 | Y14: 400000 | Z14: 906304 | AC14: 0 | AD14: 0 | AE14: 0 | AG14: =ROUND(SUM(S14:AF14)-AA14,0) -> 8137304 | AH14: 52 | AI14: 0 | AJ14: 0 | AK14: 0 | AL14: 0 | AM14: =ROUND((N14/IF(M14>26,26,M14)/8*(AH14*$AH$5+AI14*$AI$5+AJ14*$AJ$5+AK14*$AK$5+AL14*$AL$5)),0) -> 2299125 | AN14: =ROUND(AG14+AM14,0) -> 10436429 | AO14: 643755 | AP14: 44100 | AQ14: 0 | AR14: 0 | AS14: 0 | AT14: =+ROUND(SUM(AN14:AN14)-SUM(AO14:AS14),0) -> 9748574 | AW14: TRAN HAI NAM | AX14: 050116653033 | AY14: SK1 Box | AZ14: 622 | BA14: =+IF(AY14="SK1 Box","Box",IF(AY14="Seaman","Seaman","Bag")) -> Box
A15: =SUBTOTAL(3,B$6:B15) -> 10 | B15: C1271 | C15: Hồ Thị Nga | D15: 39766 | E15: FACTORY A | F15: P6 - C.Box Assembly | G15: Box Positioning worker | H15: 5931000 | I15: 200000 | J15: 0 | K15: 0 | L15: =SUM(H15:K15) -> 6131000 | M15: 24 | N15: =ROUND((H15+I15+J15+K15)/IF($M$2>26,26,$M$2)*M15,0) -> 5659385 | O15: 2 | P15: =ROUND((H15+I15+J15+K15)/IF($M$2>26,26,$M$2)*O15,0) -> 471615 | Q15: 0 | R15: =IF(M15>0,ROUND(N15/IF(M15>26,26,M15)/8*Q15*30%,0),0) -> 0 | S15: =N15+P15+R15 -> 6131000 | T15: 0 | U15: 0 | V15: 200000 | W15: 500000 | X15: 0 | Y15: 0 | Z15: 181391 | AC15: 0 | AD15: 0 | AE15: 44213.945 | AG15: =ROUND(SUM(S15:AF15)-AA15,0) -> 7056605 | AH15: 48 | AI15: 0 | AJ15: 0 | AK15: 0 | AL15: 0 | AM15: =ROUND((N15/IF(M15>26,26,M15)/8*(AH15*$AH$5+AI15*$AI$5+AJ15*$AJ$5+AK15*$AK$5+AL15*$AL$5)),0) -> 2122269 | AN15: =ROUND(AG15+AM15,0) -> 9178874 | AO15: 643755 | AP15: 44100 | AQ15: 0 | AR15: 0 | AS15: 0 | AT15: =+ROUND(SUM(AN15:AN15)-SUM(AO15:AS15),0) -> 8491019 | AW15: HO THI NGA | AX15: 050040933910 | AY15: SK1 Box | AZ15: 622 | BA15: =+IF(AY15="SK1 Box","Box",IF(AY15="Seaman","Seaman","Bag")) -> Box
A16: =SUBTOTAL(3,B$6:B16) -> 11 | B16: C12741 | C16: Nguyễn Thị Trúc Ly | D16: 44064 | E16: FACTORY A | F16: P6 - C.Box Assembly | G16: Box Positioning worker | H16: 5931000 | I16: 200000 | J16: 0 | K16: 0 | L16: =SUM(H16:K16) -> 6131000 | M16: 24 | N16: =ROUND((H16+I16+J16+K16)/IF($M$2>26,26,$M$2)*M16,0) -> 5659385 | O16: 2 | P16: =ROUND((H16+I16+J16+K16)/IF($M$2>26,26,$M$2)*O16,0) -> 471615 | Q16: 0 | R16: =IF(M16>0,ROUND(N16/IF(M16>26,26,M16)/8*Q16*30%,0),0) -> 0 | S16: =N16+P16+R16 -> 6131000 | T16: 0 | U16: 0 | V16: 200000 | W16: 500000 | X16: 0 | Y16: 400000 | Z16: 603480 | AC16: 200000 | AD16: 0 | AE16: 44213.945 | AG16: =ROUND(SUM(S16:AF16)-AA16,0) -> 8078694 | AH16: 52 | AI16: 0 | AJ16: 0 | AK16: 0 | AL16: 0 | AM16: =ROUND((N16/IF(M16>26,26,M16)/8*(AH16*$AH$5+AI16*$AI$5+AJ16*$AJ$5+AK16*$AK$5+AL16*$AL$5)),0) -> 2299125 | AN16: =ROUND(AG16+AM16,0) -> 10377819 | AO16: 643755 | AP16: 44100 | AQ16: 0 | AR16: 0 | AS16: 0 | AT16: =+ROUND(SUM(AN16:AN16)-SUM(AO16:AS16),0) -> 9689964 | AW16: NGUYEN THI TRUC LY | AX16: 050114056372 | AY16: SK1 Box | AZ16: 622 | BA16: =+IF(AY16="SK1 Box","Box",IF(AY16="Seaman","Seaman","Bag")) -> Box
A17: =SUBTOTAL(3,B$6:B17) -> 12 | B17: C12781 | C17: Lê Thị Ánh Thương | D17: 44069 | E17: FACTORY A | F17: P6 - C.Box Assembly | G17: Technician worker | H17: 5931000 | I17: 1100000 | J17: 0 | K17: 0 | L17: =SUM(H17:K17) -> 7031000 | M17: 23.7 | N17: =ROUND((H17+I17+J17+K17)/IF($M$2>26,26,$M$2)*M17,0) -> 6409027 | O17: 2 | P17: =ROUND((H17+I17+J17+K17)/IF($M$2>26,26,$M$2)*O17,0) -> 540846 | Q17: 0 | R17: =IF(M17>0,ROUND(N17/IF(M17>26,26,M17)/8*Q17*30%,0),0) -> 0 | S17: =N17+P17+R17 -> 6949873 | T17: 0 | U17: 0 | V17: 200000 | W17: 500000 | X17: 0 | Y17: 400000 | Z17: 585715 | AC17: 100000 | AD17: 0 | AE17: 50704.328 | AG17: =ROUND(SUM(S17:AF17)-AA17,0) -> 8786292 | AH17: 51.5 | AI17: 0 | AJ17: 0 | AK17: 0 | AL17: 0 | AM17: =ROUND((N17/IF(M17>26,26,M17)/8*(AH17*$AH$5+AI17*$AI$5+AJ17*$AJ$5+AK17*$AK$5+AL17*$AL$5)),0) -> 2611273 | AN17: =ROUND(AG17+AM17,0) -> 11397565 | AO17: 738255 | AP17: 44100 | AQ17: 0 | AR17: 0 | AS17: 0 | AT17: =+ROUND(SUM(AN17:AN17)-SUM(AO17:AS17),0) -> 10615210 | AW17: LE THI ANH THUONG | AX17: 050040933661 | AY17: SK1 Box | AZ17: 622 | BA17: =+IF(AY17="SK1 Box","Box",IF(AY17="Seaman","Seaman","Bag")) -> Box
... A261: =SUBTOTAL(3,B$6:B261) -> 256 | B261: C11922 | C261: Nguyễn Thị Hồng Thuận | D261: 43878 | E261: FACTORY A | F261: P6 - Production Office | G261: Factory vice manager | H261: 7643000 | I261: 7300000 | J261: 0 | K261: 0 | L261: =SUM(H261:K261) -> 14943000 | M261: 23.6 | N261: =ROUND((H261+I261+J261+K261)/IF($M$2>26,26,$M$2)*M261,0) -> 13563646 | O261: 2 | P261: =ROUND((H261+I261+J261+K261)/IF($M$2>26,26,$M$2)*O261,0) -> 1149462 | Q261: 0 | R261: =IF(M261>0,ROUND(N261/IF(M261>26,26,M261)/8*Q261*30%,0),0) -> 0 | S261: =N261+P261+R261 -> 14713108 | T261: 0 | U261: 0 | V261: 200000 | W261: 500000 | X261: 0 | Y261: 400000 | Z261: 0 | AC261: 0 | AD261: 0 | AE261: 107762.02 | AG261: =ROUND(SUM(S261:AF261)-AA261,0) -> 15920870 | AH261: 52 | AI261: 0 | AJ261: 0 | AK261: 0 | AL261: 0 | AM261: =ROUND((N261/IF(M261>26,26,M261)/8*(AH261*$AH$5+AI261*$AI$5+AJ261*$AJ$5+AK261*$AK$5+AL261*$AL$5)),0) -> 5603625 | AN261: =ROUND(AG261+AM261,0) -> 21524495 | AO261: 1569015 | AP261: 44100 | AQ261: 0 | AR261: 0 | AS261: 0 | AT261: =+ROUND(SUM(AN261:AN261)-SUM(AO261:AS261),0) -> 19911380 | AW261: NGUYEN THI HONG THUAN | AX261: 050040933090 | AY261: SK1 Box | AZ261: 627 | BA261: =+IF(AY261="SK1 Box","Box",IF(AY261="Seaman","Seaman","Bag")) -> Box
A262: =SUBTOTAL(3,B$6:B262) -> 257 | B262: C3402 | C262: Đoàn Thị Hiếu Loan | D262: 40589 | E262: FACTORY A | F262: P6 - Production Office | G262: Factory manager | H262: 13094000 | I262: 11306000 | J262: 0 | K262: 0 | L262: =SUM(H262:K262) -> 24400000 | M262: 24 | N262: =ROUND((H262+I262+J262+K262)/IF($M$2>26,26,$M$2)*M262,0) -> 22523077 | O262: 2 | P262: =ROUND((H262+I262+J262+K262)/IF($M$2>26,26,$M$2)*O262,0) -> 1876923 | Q262: 0 | R262: =IF(M262>0,ROUND(N262/IF(M262>26,26,M262)/8*Q262*30%,0),0) -> 0 | S262: =N262+P262+R262 -> 24400000 | T262: 150000 | U262: 0 | V262: 0 | W262: 0 | X262: 0 | Y262: 0 | Z262: 0 | AC262: 0 | AD262: 0 | AE262: 175961.54 | AG262: =ROUND(SUM(S262:AF262)-AA262,0) -> 24725962 | AH262: 0 | AI262: 0 | AJ262: 0 | AK262: 0 | AL262: 0 | AM262: =ROUND((N262/IF(M262>26,26,M262)/8*(AH262*$AH$5+AI262*$AI$5+AJ262*$AJ$5+AK262*$AK$5+AL262*$AL$5)),0) -> 0 | AN262: =ROUND(AG262+AM262,0) -> 24725962 | AO262: 2562000 | AP262: 44100 | AQ262: 115698 | AR262: 0 | AS262: 0 | AT262: =+ROUND(SUM(AN262:AN262)-SUM(AO262:AS262),0) -> 22004164 | AW262: DOAN THI HIEU LOAN | AX262: 050153746262 | AY262: SK1 Box | AZ262: 627 | BA262: Manager
A263: =SUBTOTAL(3,B$6:B263) -> 258 | B263: C5606 | C263: Nguyễn Thị Liên | D263: 41369 | E263: FACTORY A | F263: P6 - Production Office | G263: Factory assistant | H263: 6576000 | I263: 2000000 | J263: 0 | K263: 0 | L263: =SUM(H263:K263) -> 8576000 | M263: 23.8 | N263: =ROUND((H263+I263+J263+K263)/IF($M$2>26,26,$M$2)*M263,0) -> 7850338 | O263: 2 | P263: =ROUND((H263+I263+J263+K263)/IF($M$2>26,26,$M$2)*O263,0) -> 659692 | Q263: 0 | R263: =IF(M263>0,ROUND(N263/IF(M263>26,26,M263)/8*Q263*30%,0),0) -> 0 | S263: =N263+P263+R263 -> 8510030 | T263: 0 | U263: 0 | V263: 200000 | W263: 500000 | X263: 0 | Y263: 400000 | Z263: 411209 | AC263: 0 | AD263: 0 | AE263: 61846.15 | AG263: =ROUND(SUM(S263:AF263)-AA263,0) -> 10083085 | AH263: 47 | AI263: 0 | AJ263: 0 | AK263: 0 | AL263: 0 | AM263: =ROUND((N263/IF(M263>26,26,M263)/8*(AH263*$AH$5+AI263*$AI$5+AJ263*$AJ$5+AK263*$AK$5+AL263*$AL$5)),0) -> 2906769 | AN263: =ROUND(AG263+AM263,0) -> 12989854 | AO263: 900480 | AP263: 44100 | AQ263: 0 | AR263: 0 | AS263: 0 | AT263: =+ROUND(SUM(AN263:AN263)-SUM(AO263:AS263),0) -> 12045274 | AW263: NGUYEN THI LIEN | AX263: 050040965057 | AY263: SK1 Box | AZ263: 627 | BA263: =+IF(AY263="SK1 Box","Box",IF(AY263="Seaman","Seaman","Bag")) -> Box
A264: =SUBTOTAL(3,B$6:B264) -> 259 | B264: C5841 | C264: Trần Văn Nhân | D264: 41491 | E264: FACTORY A | F264: P6 - Production Office | G264: Factory manager | H264: 15240000 | I264: 9200000 | J264: 0 | K264: 0 | L264: =SUM(H264:K264) -> 24440000 | M264: 23.7 | N264: =ROUND((H264+I264+J264+K264)/IF($M$2>26,26,$M$2)*M264,0) -> 22278000 | O264: 2 | P264: =ROUND((H264+I264+J264+K264)/IF($M$2>26,26,$M$2)*O264,0) -> 1880000 | Q264: 0 | R264: =IF(M264>0,ROUND(N264/IF(M264>26,26,M264)/8*Q264*30%,0),0) -> 0 | S264: =N264+P264+R264 -> 24158000 | T264: 691923 | U264: 0 | V264: 0 | W264: 0 | X264: 0 | Y264: 0 | Z264: 0 | AC264: 0 | AD264: 0 | AE264: 0 | AG264: =ROUND(SUM(S264:AF264)-AA264,0) -> 24849923 | AH264: 0 | AI264: 0 | AJ264: 0 | AK264: 0 | AL264: 0 | AM264: =ROUND((N264/IF(M264>26,26,M264)/8*(AH264*$AH$5+AI264*$AI$5+AJ264*$AJ$5+AK264*$AK$5+AL264*$AL$5)),0) -> 0 | AN264: =ROUND(AG264+AM264,0) -> 24849923 | AO264: 2566200 | AP264: 44100 | AQ264: 94590 | AR264: 0 | AS264: 0 | AT264: =+ROUND(SUM(AN264:AN264)-SUM(AO264:AS264),0) -> 22145033 | AW264: TRAN VAN NHAN | AX264: 050040817023 | AY264: SK1 Box | AZ264: 627 | BA264: Manager
A265: =SUBTOTAL(3,B$6:B265) -> 260 | B265: C6063 | C265: Đồng Thị Thu Hiền | D265: 41621 | E265: FACTORY A | F265: P6 - Production Office | G265: Factory vice manager | H265: 6876000 | I265: 6600000 | J265: 0 | K265: 0 | L265: =SUM(H265:K265) -> 13476000 | M265: 24 | N265: =ROUND((H265+I265+J265+K265)/IF($M$2>26,26,$M$2)*M265,0) -> 12439385 | O265: 2 | P265: =ROUND((H265+I265+J265+K265)/IF($M$2>26,26,$M$2)*O265,0) -> 1036615 | Q265: 0 | R265: =IF(M265>0,ROUND(N265/IF(M265>26,26,M265)/8*Q265*30%,0),0) -> 0 | S265: =N265+P265+R265 -> 13476000 | T265: 0 | U265: 0 | V265: 200000 | W265: 500000 | X265: 0 | Y265: 400000 | Z265: 0 | AC265: 0 | AD265: 0 | AE265: 97182.695 | AG265: =ROUND(SUM(S265:AF265)-AA265,0) -> 14673183 | AH265: 52 | AI265: 0 | AJ265: 0 | AK265: 0 | AL265: 0 | AM265: =ROUND((N265/IF(M265>26,26,M265)/8*(AH265*$AH$5+AI265*$AI$5+AJ265*$AJ$5+AK265*$AK$5+AL265*$AL$5)),0) -> 5053500 | AN265: =ROUND(AG265+AM265,0) -> 19726683 | AO265: 1414980 | AP265: 44100 | AQ265: 0 | AR265: 0 | AS265: 0 | AT265: =+ROUND(SUM(AN265:AN265)-SUM(AO265:AS265),0) -> 18267603 | AW265: DONG THI THU HIEN | AX265: 050040958301 | AY265: SK1 Box | AZ265: 627 | BA265: =+IF(AY265="SK1 Box","Box",IF(AY265="Seaman","Seaman","Bag")) -> Box
A266: =SUBTOTAL(3,B$6:B266) -> 261 | B266: C13547 | C266: Nguyễn Thị Cẩm Tiên | D266: 44270 | E266: FACTORY A | F266: P6 - QC | G266: QC Worker | H266: 5931000 | I266: 1100000 | J266: 0 | K266: 0 | L266: =SUM(H266:K266) -> 7031000 | M266: 24 | N266: =ROUND((H266+I266+J266+K266)/IF($M$2>26,26,$M$2)*M266,0) -> 6490154 | O266: 2 | P266: =ROUND((H266+I266+J266+K266)/IF($M$2>26,26,$M$2)*O266,0) -> 540846 | Q266: 0 | R266: =IF(M266>0,ROUND(N266/IF(M266>26,26,M266)/8*Q266*30%,0),0) -> 0 | S266: =N266+P266+R266 -> 7031000 | T266: 0 | U266: 0 | V266: 200000 | W266: 500000 | X266: 0 | Y266: 400000 | Z266: 400000 | AC266: 100000 | AD266: 0 | AE266: 50704.328 | AG266: =ROUND(SUM(S266:AF266)-AA266,0) -> 8681704 | AH266: 0 | AI266: 0 | AJ266: 0 | AK266: 0 | AL266: 0 | AM266: =ROUND((N266/IF(M266>26,26,M266)/8*(AH266*$AH$5+AI266*$AI$5+AJ266*$AJ$5+AK266*$AK$5+AL266*$AL$5)),0) -> 0 | AN266: =ROUND(AG266+AM266,0) -> 8681704 | AO266: 738255 | AP266: 44100 | AQ266: 0 | AR266: 0 | AS266: 0 | AT266: =+ROUND(SUM(AN266:AN266)-SUM(AO266:AS266),0) -> 7899349 | AW266: NGUYEN THI CAM TIEN | AX266: 050040965758 | AY266: SK1 Box | AZ266: 622 | BA266: =+IF(AY266="SK1 Box","Box",IF(AY266="Seaman","Seaman","Bag")) -> Box
A267: =SUBTOTAL(3,B$6:B267) -> 262 | B267: C13762 | C267: Nguyễn Thị Tuyết Ngân | D267: 44287 | E267: FACTORY A | F267: P6 - QC | G267: QC worker | H267: 5931000 | I267: 1100000 | J267: 0 | K267: 0 | L267: =SUM(H267:K267) -> 7031000 | M267: 24 | N267: =ROUND((H267+I267+J267+K267)/IF($M$2>26,26,$M$2)*M267,0) -> 6490154 | O267: 2 | P267: =ROUND((H267+I267+J267+K267)/IF($M$2>26,26,$M$2)*O267,0) -> 540846 | Q267: 0 | R267: =IF(M267>0,ROUND(N267/IF(M267>26,26,M267)/8*Q267*30%,0),0) -> 0 | S267: =N267+P267+R267 -> 7031000 | T267: 0 | U267: 0 | V267: 200000 | W267: 500000 | X267: 0 | Y267: 400000 | Z267: 500000 | AC267: 100000 | AD267: 0 | AE267: 50704.328 | AG267: =ROUND(SUM(S267:AF267)-AA267,0) -> 8781704 | AH267: 32.5 | AI267: 0 | AJ267: 0 | AK267: 0 | AL267: 0 | AM267: =ROUND((N267/IF(M267>26,26,M267)/8*(AH267*$AH$5+AI267*$AI$5+AJ267*$AJ$5+AK267*$AK$5+AL267*$AL$5)),0) -> 1647891 | AN267: =ROUND(AG267+AM267,0) -> 10429595 | AO267: 738255 | AP267: 44100 | AQ267: 0 | AR267: 0 | AS267: 0 | AT267: =+ROUND(SUM(AN267:AN267)-SUM(AO267:AS267),0) -> 9647240 | AW267: NGUYEN THI TUYET NGAN | AX267: 050127345462 | AY267: SK1 Box | AZ267: 622 | BA267: =+IF(AY267="SK1 Box","Box",IF(AY267="Seaman","Seaman","Bag")) -> Box
A268: =SUBTOTAL(3,B$6:B268) -> 263 | B268: C15453 | C268: Đặng Vũ Thảo Huyền | D268: 45164 | E268: FACTORY A | F268: P6 - QC | G268: QC worker | H268: 5538000 | I268: 500000 | J268: 0 | K268: 0 | L268: =SUM(H268:K268) -> 6038000 | M268: 23.5 | N268: =ROUND((H268+I268+J268+K268)/IF($M$2>26,26,$M$2)*M268,0) -> 5457423 | O268: 2 | P268: =ROUND((H268+I268+J268+K268)/IF($M$2>26,26,$M$2)*O268,0) -> 464462 | Q268: 0 | R268: =IF(M268>0,ROUND(N268/IF(M268>26,26,M268)/8*Q268*30%,0),0) -> 0 | S268: =N268+P268+R268 -> 5921885 | T268: 0 | U268: 0 | V268: 200000 | W268: 500000 | X268: 0 | Y268: 400000 | Z268: 391700 | AC268: 0 | AD268: 0 | AE268: 43543.269 | AG268: =ROUND(SUM(S268:AF268)-AA268,0) -> 7457128 | AH268: 48 | AI268: 0 | AJ268: 0 | AK268: 0 | AL268: 0 | AM268: =ROUND((N268/IF(M268>26,26,M268)/8*(AH268*$AH$5+AI268*$AI$5+AJ268*$AJ$5+AK268*$AK$5+AL268*$AL$5)),0) -> 2090077 | AN268: =ROUND(AG268+AM268,0) -> 9547205 | AO268: 633990 | AP268: 44100 | AQ268: 0 | AR268: 0 | AS268: 0 | AT268: =+ROUND(SUM(AN268:AN268)-SUM(AO268:AS268),0) -> 8869115 | AW268: DANG VU THAO HUYEN | AX268: 050120705986 | AY268: SK1 Box | AZ268: 622 | BA268: =+IF(AY268="SK1 Box","Box",IF(AY268="Seaman","Seaman","Bag")) -> Box
A269: =SUBTOTAL(3,B$6:B269) -> 264 | B269: C15906 | C269: Phạm Thị Thu Thương | D269: 45419 | E269: FACTORY A | F269: P6 - QC | G269: QC worker | H269: 5274000 | I269: 500000 | J269: 0 | K269: 0 | L269: =SUM(H269:K269) -> 5774000 | M269: 22.8 | N269: =ROUND((H269+I269+J269+K269)/IF($M$2>26,26,$M$2)*M269,0) -> 5063354 | O269: 3 | P269: =ROUND((H269+I269+J269+K269)/IF($M$2>26,26,$M$2)*O269,0) -> 666231 | Q269: 0 | R269: =IF(M269>0,ROUND(N269/IF(M269>26,26,M269)/8*Q269*30%,0),0) -> 0 | S269: =N269+P269+R269 -> 5729585 | T269: 0 | U269: 0 | V269: 200000 | W269: 500000 | X269: 0 | Y269: 400000 | Z269: 380000 | AC269: 0 | AD269: 0 | AE269: 41639.424 | AG269: =ROUND(SUM(S269:AF269)-AA269,0) -> 7251224 | AH269: 40 | AI269: 0 | AJ269: 0 | AK269: 0 | AL269: 0 | AM269: =ROUND((N269/IF(M269>26,26,M269)/8*(AH269*$AH$5+AI269*$AI$5+AJ269*$AJ$5+AK269*$AK$5+AL269*$AL$5)),0) -> 1665577 | AN269: =ROUND(AG269+AM269,0) -> 8916801 | AO269: 606270 | AP269: 44100 | AQ269: 0 | AR269: 0 | AS269: 0 | AT269: =+ROUND(SUM(AN269:AN269)-SUM(AO269:AS269),0) -> 8266431 | AW269: PHAM THI THU THUONG | AX269: 050135011281 | AY269: SK1 Box | AZ269: 622 | BA269: =+IF(AY269="SK1 Box","Box",IF(AY269="Seaman","Seaman","Bag")) -> Box
A270: =SUBTOTAL(3,B$6:B270) -> 265 | B270: C15959 | C270: Khiếu Thị Hoàng Vân | D270: 45444 | E270: FACTORY A | F270: P6 - QC | G270: QC worker | H270: 5274000 | I270: 500000 | J270: 0 | K270: 0 | L270: =SUM(H270:K270) -> 5774000 | M270: 23.8 | N270: =ROUND((H270+I270+J270+K270)/IF($M$2>26,26,$M$2)*M270,0) -> 5285431 | O270: 2 | P270: =ROUND((H270+I270+J270+K270)/IF($M$2>26,26,$M$2)*O270,0) -> 444154 | Q270: 0 | R270: =IF(M270>0,ROUND(N270/IF(M270>26,26,M270)/8*Q270*30%,0),0) -> 0 | S270: =N270+P270+R270 -> 5729585 | T270: 0 | U270: 0 | V270: 200000 | W270: 500000 | X270: 0 | Y270: 400000 | Z270: 396700 | AC270: 0 | AD270: 0 | AE270: 41639.425 | AG270: =ROUND(SUM(S270:AF270)-AA270,0) -> 7267924 | AH270: 52 | AI270: 0 | AJ270: 0 | AK270: 0 | AL270: 0 | AM270: =ROUND((N270/IF(M270>26,26,M270)/8*(AH270*$AH$5+AI270*$AI$5+AJ270*$AJ$5+AK270*$AK$5+AL270*$AL$5)),0) -> 2165250 | AN270: =ROUND(AG270+AM270,0) -> 9433174 | AO270: 606270 | AP270: 44100 | AQ270: 0 | AR270: 0 | AS270: 0 | AT270: =+ROUND(SUM(AN270:AN270)-SUM(AO270:AS270),0) -> 8782804 | AW270: KHIEU THI HOANG VAN | AX270: 050074107580 | AY270: SK1 Box | AZ270: 622 | BA270: =+IF(AY270="SK1 Box","Box",IF(AY270="Seaman","Seaman","Bag")) -> Box
A271: =SUBTOTAL(3,B$6:B271) -> 266 | B271: C16460 | C271: Hà Nguyễn Tấn Trung | D271: 45710 | E271: FACTORY A | F271: P6 - QC | G271: QC worker | H271: 5023000 | I271: 500000 | J271: 0 | K271: 0 | L271: =SUM(H271:K271) -> 5523000 | M271: 23 | N271: =ROUND((H271+I271+J271+K271)/IF($M$2>26,26,$M$2)*M271,0) -> 4885731 | O271: 3 | P271: =ROUND((H271+I271+J271+K271)/IF($M$2>26,26,$M$2)*O271,0) -> 637269 | Q271: 0 | R271: =IF(M271>0,ROUND(N271/IF(M271>26,26,M271)/8*Q271*30%,0),0) -> 0 | S271: =N271+P271+R271 -> 5523000 | T271: 0 | U271: 0 | V271: 200000 | W271: 500000 | X271: 0 | Y271: 400000 | Z271: 383300 | AC271: 0 | AD271: 0 | AE271: 0 | AG271: =ROUND(SUM(S271:AF271)-AA271,0) -> 7006300 | AH271: 44 | AI271: 0 | AJ271: 0 | AK271: 0 | AL271: 0 | AM271: =ROUND((N271/IF(M271>26,26,M271)/8*(AH271*$AH$5+AI271*$AI$5+AJ271*$AJ$5+AK271*$AK$5+AL271*$AL$5)),0) -> 1752490 | AN271: =ROUND(AG271+AM271,0) -> 8758790 | AO271: 579915 | AP271: 0 | AQ271: 0 | AR271: 0 | AS271: 0 | AT271: =+ROUND(SUM(AN271:AN271)-SUM(AO271:AS271),0) -> 8178875 | AW271: HA NGUYEN TAN TRUNG | AX271: 050968075690 | AY271: SK1 Box | AZ271: 622 | BA271: =+IF(AY271="SK1 Box","Box",IF(AY271="Seaman","Seaman","Bag")) -> Box
A272: =SUBTOTAL(3,B$6:B272) -> 267 | B272: C2982 | C272: Đỗ Thị Nga | D272: 40369 | E272: FACTORY A | F272: P6 - QC | G272: QC worker | H272: 5931000 | I272: 1100000 | J272: 0 | K272: 0 | L272: =SUM(H272:K272) -> 7031000 | M272: 23.9 | N272: =ROUND((H272+I272+J272+K272)/IF($M$2>26,26,$M$2)*M272,0) -> 6463112 | O272: 2 | P272: =ROUND((H272+I272+J272+K272)/IF($M$2>26,26,$M$2)*O272,0) -> 540846 | Q272: 0 | R272: =IF(M272>0,ROUND(N272/IF(M272>26,26,M272)/8*Q272*30%,0),0) -> 0 | S272: =N272+P272+R272 -> 7003958 | T272: 0 | U272: 0 | V272: 200000 | W272: 500000 | X272: 0 | Y272: 400000 | Z272: 398300 | AC272: 100000 | AD272: 0 | AE272: 50704.331 | AG272: =ROUND(SUM(S272:AF272)-AA272,0) -> 8652962 | AH272: 52 | AI272: 0 | AJ272: 0 | AK272: 0 | AL272: 0 | AM272: =ROUND((N272/IF(M272>26,26,M272)/8*(AH272*$AH$5+AI272*$AI$5+AJ272*$AJ$5+AK272*$AK$5+AL272*$AL$5)),0) -> 2636625 | AN272: =ROUND(AG272+AM272,0) -> 11289587 | AO272: 738255 | AP272: 44100 | AQ272: 0 | AR272: 0 | AS272: 0 | AT272: =+ROUND(SUM(AN272:AN272)-SUM(AO272:AS272),0) -> 10507232 | AW272: DO THI NGA | AX272: 050040966088 | AY272: SK1 Box | AZ272: 622 | BA272: =+IF(AY272="SK1 Box","Box",IF(AY272="Seaman","Seaman","Bag")) -> Box
A273: =SUBTOTAL(3,B$6:B273) -> 268 | B273: C6248 | C273: Huỳnh Văn Mẫu Tám | D273: 41764 | E273: FACTORY A | F273: P6 - QC | G273: Box QC leader | H273: 8176000 | I273: 3200000 | J273: 0 | K273: 5200000 | L273: =SUM(H273:K273) -> 16576000 | M273: 23.9 | N273: =ROUND((H273+I273+J273+K273)/IF($M$2>26,26,$M$2)*M273,0) -> 15237169 | O273: 2 | P273: =ROUND((H273+I273+J273+K273)/IF($M$2>26,26,$M$2)*O273,0) -> 1275077 | Q273: 0 | R273: =IF(M273>0,ROUND(N273/IF(M273>26,26,M273)/8*Q273*30%,0),0) -> 0 | S273: =N273+P273+R273 -> 16512246 | T273: 0 | U273: 0 | V273: 200000 | W273: 500000 | X273: 0 | Y273: 400000 | Z273: 697100 | AC273: 100000 | AD273: 0 | AE273: 0 | AG273: =ROUND(SUM(S273:AF273)-AA273,0) -> 18409346 | AH273: 49 | AI273: 0 | AJ273: 0 | AK273: 0 | AL273: 0 | AM273: =ROUND((N273/IF(M273>26,26,M273)/8*(AH273*$AH$5+AI273*$AI$5+AJ273*$AJ$5+AK273*$AK$5+AL273*$AL$5)),0) -> 5857385 | AN273: =ROUND(AG273+AM273,0) -> 24266731 | AO273: 1740480 | AP273: 44100 | AQ273: 43689 | AR273: 0 | AS273: 0 | AT273: =+ROUND(SUM(AN273:AN273)-SUM(AO273:AS273),0) -> 22438462 | AW273: HUYNH VAN MAU TAM | AX273: 050042516527 | AY273: SK1 Box | AZ273: 622 | BA273: =+IF(AY273="SK1 Box","Box",IF(AY273="Seaman","Seaman","Bag")) -> Box
A274: =SUBTOTAL(3,B$6:B274) -> 269 | B274: C14461 | C274: Nguyễn Ngọc Tùng | D274: 44604 | E274: FACTORY A | F274: P6 - WIP | G274: WIP worker | H274: 5931000 | I274: 500000 | J274: 0 | K274: 0 | L274: =SUM(H274:K274) -> 6431000 | M274: 23.9 | N274: =ROUND((H274+I274+J274+K274)/IF($M$2>26,26,$M$2)*M274,0) -> 5911573 | O274: 2 | P274: =ROUND((H274+I274+J274+K274)/IF($M$2>26,26,$M$2)*O274,0) -> 494692 | Q274: 0 | R274: =IF(M274>0,ROUND(N274/IF(M274>26,26,M274)/8*Q274*30%,0),0) -> 0 | S274: =N274+P274+R274 -> 6406265 | T274: 0 | U274: 0 | V274: 200000 | W274: 500000 | X274: 0 | Y274: 400000 | Z274: 590813 | AC274: 0 | AD274: 0 | AE274: 0 | AG274: =ROUND(SUM(S274:AF274)-AA274,0) -> 8097078 | AH274: 49 | AI274: 0 | AJ274: 0 | AK274: 0 | AL274: 0 | AM274: =ROUND((N274/IF(M274>26,26,M274)/8*(AH274*$AH$5+AI274*$AI$5+AJ274*$AJ$5+AK274*$AK$5+AL274*$AL$5)),0) -> 2272493 | AN274: =ROUND(AG274+AM274,0) -> 10369571 | AO274: 675255 | AP274: 44100 | AQ274: 0 | AR274: 0 | AS274: 0 | AT274: =+ROUND(SUM(AN274:AN274)-SUM(AO274:AS274),0) -> 9650216 | AW274: NGUYEN NGOC TUNG | AX274: 050131181482 | AY274: SK1 Box | AZ274: 622 | BA274: =+IF(AY274="SK1 Box","Box",IF(AY274="Seaman","Seaman","Bag")) -> Box
A275: =SUBTOTAL(3,B$6:B275) -> 270 | B275: C15431 | C275: Lê Thanh Hiền | D275: 45005 | E275: FACTORY A | F275: P8 - Lami | G275: Auto Machine sub-operator-A | H275: 5815000 | I275: 800000 | J275: 292000 | K275: 100000 | L275: =SUM(H275:K275) -> 7007000 | M275: 18.6 | N275: =ROUND((H275+I275+J275+K275)/IF($M$2>26,26,$M$2)*M275,0) -> 5012700 | O275: 2 | P275: =ROUND((H275+I275+J275+K275)/IF($M$2>26,26,$M$2)*O275,0) -> 539000 | Q275: 0 | R275: =IF(M275>0,ROUND(N275/IF(M275>26,26,M275)/8*Q275*30%,0),0) -> 0 | S275: =N275+P275+R275 -> 5551700 | T275: 0 | U275: 0 | V275: 200000 | W275: 0 | X275: 200000 | Y275: 0 | Z275: 348482 | AC275: 0 | AD275: 0 | AE275: 0 | AG275: =ROUND(SUM(S275:AF275)-AA275,0) -> 6300182 | AH275: 36 | AI275: 0 | AJ275: 0 | AK275: 0 | AL275: 0 | AM275: =ROUND((N275/IF(M275>26,26,M275)/8*(AH275*$AH$5+AI275*$AI$5+AJ275*$AJ$5+AK275*$AK$5+AL275*$AL$5)),0) -> 1819125 | AN275: =ROUND(AG275+AM275,0) -> 8119307 | AO275: 735735 | AP275: 44100 | AQ275: 0 | AR275: 0 | AS275: 0 | AT275: =+ROUND(SUM(AN275:AN275)-SUM(AO275:AS275),0) -> 7339472 | AW275: LE THANH HIEN | AX275: 050122289671 | AY275: Seaman | AZ275: 622 | BA275: =+IF(AY275="SK1 Box","Box",IF(AY275="Seaman","Seaman","Bag")) -> Seaman
A276: =SUBTOTAL(3,B$6:B276) -> 271 | B276: C15564 | C276: Lê Văn Nhớ | D276: 45344 | E276: FACTORY A | F276: P8 - Lami | G276: Auto Machine Assistant-A | H276: 5538000 | I276: 600000 | J276: 278000 | K276: 0 | L276: =SUM(H276:K276) -> 6416000 | M276: 23 | N276: =ROUND((H276+I276+J276+K276)/IF($M$2>26,26,$M$2)*M276,0) -> 5675692 | O276: 2 | P276: =ROUND((H276+I276+J276+K276)/IF($M$2>26,26,$M$2)*O276,0) -> 493538 | Q276: 0 | R276: =IF(M276>0,ROUND(N276/IF(M276>26,26,M276)/8*Q276*30%,0),0) -> 0 | S276: =N276+P276+R276 -> 6169230 | T276: 0 | U276: 0 | V276: 200000 | W276: 0 | X276: 0 | Y276: 400000 | Z276: 371683 | AC276: 0 | AD276: 0 | AE276: 0 | AG276: =ROUND(SUM(S276:AF276)-AA276,0) -> 7140913 | AH276: 44 | AI276: 0 | AJ276: 0 | AK276: 0 | AL276: 0 | AM276: =ROUND((N276/IF(M276>26,26,M276)/8*(AH276*$AH$5+AI276*$AI$5+AJ276*$AJ$5+AK276*$AK$5+AL276*$AL$5)),0) -> 2035846 | AN276: =ROUND(AG276+AM276,0) -> 9176759 | AO276: 673680 | AP276: 44100 | AQ276: 0 | AR276: 0 | AS276: 0 | AT276: =+ROUND(SUM(AN276:AN276)-SUM(AO276:AS276),0) -> 8458979 | AW276: LE VAN NHO | AX276: 050151637091 | AY276: Seaman | AZ276: 622 | BA276: =+IF(AY276="SK1 Box","Box",IF(AY276="Seaman","Seaman","Bag")) -> Seaman
... A279: =SUBTOTAL(3,B$6:B279) -> 274 | B279: C14632 | C279: Nguyễn Chính Tín | D279: 44621 | E279: FACTORY A | F279: P8 - Packing | G279: Packing worker | H279: 5931000 | I279: 200000 | J279: 0 | K279: 0 | L279: =SUM(H279:K279) -> 6131000 | M279: 23.9 | N279: =ROUND((H279+I279+J279+K279)/IF($M$2>26,26,$M$2)*M279,0) -> 5635804 | O279: 2 | P279: =ROUND((H279+I279+J279+K279)/IF($M$2>26,26,$M$2)*O279,0) -> 471615 | Q279: 0 | R279: =IF(M279>0,ROUND(N279/IF(M279>26,26,M279)/8*Q279*30%,0),0) -> 0 | S279: =N279+P279+R279 -> 6107419 | T279: 0 | U279: 0 | V279: 200000 | W279: 500000 | X279: 0 | Y279: 300000 | Z279: 360449 | AC279: 0 | AD279: 0 | AE279: 0 | AG279: =ROUND(SUM(S279:AF279)-AA279,0) -> 7467868 | AH279: 36 | AI279: 0 | AJ279: 0 | AK279: 0 | AL279: 0 | AM279: =ROUND((N279/IF(M279>26,26,M279)/8*(AH279*$AH$5+AI279*$AI$5+AJ279*$AJ$5+AK279*$AK$5+AL279*$AL$5)),0) -> 1591702 | AN279: =ROUND(AG279+AM279,0) -> 9059570 | AO279: 643755 | AP279: 44100 | AQ279: 0 | AR279: 140000 | AS279: 0 | AT279: =+ROUND(SUM(AN279:AN279)-SUM(AO279:AS279),0) -> 8231715 | AW279: NGUYEN CHINH TIN | AX279: 050051381723 | AY279: Seaman | AZ279: 622 | BA279: =+IF(AY279="SK1 Box","Box",IF(AY279="Seaman","Seaman","Bag")) -> Seaman
A280: =SUBTOTAL(3,B$6:B280) -> 275 | B280: C15912 | C280: Dương Kim Đỗ | D280: 45414 | E280: FACTORY A | F280: P8 - Production Office | G280: Factory manager | H280: 14500000 | I280: 13000000 | J280: 0 | K280: 0 | L280: =SUM(H280:K280) -> 27500000 | M280: 24 | N280: =ROUND((H280+I280+J280+K280)/IF($M$2>26,26,$M$2)*M280,0) -> 25384615 | O280: 2 | P280: =ROUND((H280+I280+J280+K280)/IF($M$2>26,26,$M$2)*O280,0) -> 2115385 | Q280: 0 | R280: =IF(M280>0,ROUND(N280/IF(M280>26,26,M280)/8*Q280*30%,0),0) -> 0 | S280: =N280+P280+R280 -> 27500000 | T280: 500000 | U280: 0 | V280: 0 | W280: 0 | X280: 0 | Y280: 0 | Z280: 0 | AC280: 0 | AD280: 0 | AE280: 0 | AG280: =ROUND(SUM(S280:AF280)-AA280,0) -> 28000000 | AH280: 0 | AI280: 0 | AJ280: 0 | AK280: 0 | AL280: 0 | AM280: =ROUND((N280/IF(M280>26,26,M280)/8*(AH280*$AH$5+AI280*$AI$5+AJ280*$AJ$5+AK280*$AK$5+AL280*$AL$5)),0) -> 0 | AN280: =ROUND(AG280+AM280,0) -> 28000000 | AO280: 2887500 | AP280: 44100 | AQ280: 245625 | AR280: 0 | AS280: 0 | AT280: =+ROUND(SUM(AN280:AN280)-SUM(AO280:AS280),0) -> 24822775 | AW280: DUONG KIM DO | AX280: 050153623608 | AY280: Seaman | AZ280: 627 | BA280: Manager
A281: =SUBTOTAL(3,B$6:B281) -> 276 | B281: C13485 | C281: Hồ Vĩnh Bình | D281: 44264 | E281: FACTORY A | F281: P8 - QC | G281: Lab Staff | H281: 6500000 | I281: 3800000 | J281: 0 | K281: 0 | L281: =SUM(H281:K281) -> 10300000 | M281: 24 | N281: =ROUND((H281+I281+J281+K281)/IF($M$2>26,26,$M$2)*M281,0) -> 9507692 | O281: 2 | P281: =ROUND((H281+I281+J281+K281)/IF($M$2>26,26,$M$2)*O281,0) -> 792308 | Q281: 0 | R281: =IF(M281>0,ROUND(N281/IF(M281>26,26,M281)/8*Q281*30%,0),0) -> 0 | S281: =N281+P281+R281 -> 10300000 | T281: 500000 | U281: 0 | V281: 200000 | W281: 500000 | X281: 0 | Y281: 400000 | Z281: 250000 | AC281: 100000 | AD281: 0 | AE281: 0 | AG281: =ROUND(SUM(S281:AF281)-AA281,0) -> 12250000 | AH281: 44 | AI281: 0 | AJ281: 0 | AK281: 0 | AL281: 0 | AM281: =ROUND((N281/IF(M281>26,26,M281)/8*(AH281*$AH$5+AI281*$AI$5+AJ281*$AJ$5+AK281*$AK$5+AL281*$AL$5)),0) -> 3268269 | AN281: =ROUND(AG281+AM281,0) -> 15518269 | AO281: 1081500 | AP281: 44100 | AQ281: 0 | AR281: 0 | AS281: 0 | AT281: =+ROUND(SUM(AN281:AN281)-SUM(AO281:AS281),0) -> 14392669 | AW281: HO VINH BINH | AX281: 050094096895 | AY281: Seaman | AZ281: 622 | BA281: =+IF(AY281="SK1 Box","Box",IF(AY281="Seaman","Seaman","Bag")) -> Seaman
A282: =SUBTOTAL(3,B$6:B282) -> 277 | B282: C16068 | C282: Trần Thị Thảo Sương | D282: 45502 | E282: FACTORY A | F282: P8 - QC | G282: QC worker | H282: 5274000 | I282: 500000 | J282: 0 | K282: 0 | L282: =SUM(H282:K282) -> 5774000 | M282: 22.7 | N282: =ROUND((H282+I282+J282+K282)/IF($M$2>26,26,$M$2)*M282,0) -> 5041146 | O282: 3 | P282: =ROUND((H282+I282+J282+K282)/IF($M$2>26,26,$M$2)*O282,0) -> 666231 | Q282: 0 | R282: =IF(M282>0,ROUND(N282/IF(M282>26,26,M282)/8*Q282*30%,0),0) -> 0 | S282: =N282+P282+R282 -> 5707377 | T282: 0 | U282: 0 | V282: 200000 | W282: 500000 | X282: 0 | Y282: 400000 | Z282: 378300 | AC282: 0 | AD282: 0 | AE282: 41639.422 | AG282: =ROUND(SUM(S282:AF282)-AA282,0) -> 7227316 | AH282: 9 | AI282: 0 | AJ282: 0 | AK282: 0 | AL282: 0 | AM282: =ROUND((N282/IF(M282>26,26,M282)/8*(AH282*$AH$5+AI282*$AI$5+AJ282*$AJ$5+AK282*$AK$5+AL282*$AL$5)),0) -> 374755 | AN282: =ROUND(AG282+AM282,0) -> 7602071 | AO282: 606270 | AP282: 44100 | AQ282: 0 | AR282: 0 | AS282: 0 | AT282: =+ROUND(SUM(AN282:AN282)-SUM(AO282:AS282),0) -> 6951701 | AW282: TRAN THI THAO SUONG | AX282: 050155274732 | AY282: Seaman | AZ282: 622 | BA282: =+IF(AY282="SK1 Box","Box",IF(AY282="Seaman","Seaman","Bag")) -> Seaman
A283: =SUBTOTAL(3,B$6:B283) -> 278 | B283: C10711 | C283: Nguyễn Mạnh Hùng | D283: 43602 | E283: FACTORY A | F283: P8 - Sheeter | G283: Auto Machine operator-C | H283: 5931000 | I283: 2100000 | J283: 0 | K283: 0 | L283: =SUM(H283:K283) -> 8031000 | M283: 23.5 | N283: =ROUND((H283+I283+J283+K283)/IF($M$2>26,26,$M$2)*M283,0) -> 7258788 | O283: 2 | P283: =ROUND((H283+I283+J283+K283)/IF($M$2>26,26,$M$2)*O283,0) -> 617769 | Q283: 0 | R283: =IF(M283>0,ROUND(N283/IF(M283>26,26,M283)/8*Q283*30%,0),0) -> 0 | S283: =N283+P283+R283 -> 7876557 | T283: 0 | U283: 0 | V283: 200000 | W283: 500000 | X283: 0 | Y283: 300000 | Z283: 513173 | AC283: 0 | AD283: 0 | AE283: 0 | AG283: =ROUND(SUM(S283:AF283)-AA283,0) -> 9389730 | AH283: 44 | AI283: 0 | AJ283: 0 | AK283: 0 | AL283: 0 | AM283: =ROUND((N283/IF(M283>26,26,M283)/8*(AH283*$AH$5+AI283*$AI$5+AJ283*$AJ$5+AK283*$AK$5+AL283*$AL$5)),0) -> 2548298 | AN283: =ROUND(AG283+AM283,0) -> 11938028 | AO283: 843255 | AP283: 44100 | AQ283: 0 | AR283: 0 | AS283: 0 | AT283: =+ROUND(SUM(AN283:AN283)-SUM(AO283:AS283),0) -> 11050673 | AW283: NGUYEN MANH HUNG | AX283: 050093875998 | AY283: Seaman | AZ283: 622 | BA283: =+IF(AY283="SK1 Box","Box",IF(AY283="Seaman","Seaman","Bag")) -> Seaman
A284: =SUBTOTAL(3,B$6:B284) -> 279 | B284: C15964 | C284: Võ Thị Thanh Vân | D284: 45446 | E284: FACTORY A | F284: P8 - Sheeter | G284: Auto Machine sub-operator-C | H284: 5274000 | I284: 400000 | J284: 0 | K284: 0 | L284: =SUM(H284:K284) -> 5674000 | M284: 23.6 | N284: =ROUND((H284+I284+J284+K284)/IF($M$2>26,26,$M$2)*M284,0) -> 5150246 | O284: 2 | P284: =ROUND((H284+I284+J284+K284)/IF($M$2>26,26,$M$2)*O284,0) -> 436462 | Q284: 0 | R284: =IF(M284>0,ROUND(N284/IF(M284>26,26,M284)/8*Q284*30%,0),0) -> 0 | S284: =N284+P284+R284 -> 5586708 | T284: 0 | U284: 0 | V284: 200000 | W284: 500000 | X284: 0 | Y284: 400000 | Z284: 427378 | AC284: 0 | AD284: 0 | AE284: 40918.268 | AG284: =ROUND(SUM(S284:AF284)-AA284,0) -> 7155004 | AH284: 36 | AI284: 0 | AJ284: 0 | AK284: 0 | AL284: 0 | AM284: =ROUND((N284/IF(M284>26,26,M284)/8*(AH284*$AH$5+AI284*$AI$5+AJ284*$AJ$5+AK284*$AK$5+AL284*$AL$5)),0) -> 1473058 | AN284: =ROUND(AG284+AM284,0) -> 8628062 | AO284: 595770 | AP284: 44100 | AQ284: 0 | AR284: 0 | AS284: 0 | AT284: =+ROUND(SUM(AN284:AN284)-SUM(AO284:AS284),0) -> 7988192 | AW284: VO THI THANH VAN | AX284: 050130754136 | AY284: Seaman | AZ284: 622 | BA284: =+IF(AY284="SK1 Box","Box",IF(AY284="Seaman","Seaman","Bag")) -> Seaman
A285: =SUBTOTAL(3,B$6:B285) -> 280 | B285: C15998 | C285: Lưu Thị Thu Hà | D285: 45458 | E285: FACTORY A | F285: P8 - Sheeter | G285: Auto Machine sub-operator-C | H285: 5274000 | I285: 400000 | J285: 0 | K285: 0 | L285: =SUM(H285:K285) -> 5674000 | M285: 22.6 | N285: =ROUND((H285+I285+J285+K285)/IF($M$2>26,26,$M$2)*M285,0) -> 4932015 | O285: 3 | P285: =ROUND((H285+I285+J285+K285)/IF($M$2>26,26,$M$2)*O285,0) -> 654692 | Q285: 0 | R285: =IF(M285>0,ROUND(N285/IF(M285>26,26,M285)/8*Q285*30%,0),0) -> 0 | S285: =N285+P285+R285 -> 5586707 | T285: 0 | U285: 0 | V285: 200000 | W285: 500000 | X285: 0 | Y285: 300000 | Z285: 376230 | AC285: 100000 | AD285: 0 | AE285: 40918.266 | AG285: =ROUND(SUM(S285:AF285)-AA285,0) -> 7103855 | AH285: 36 | AI285: 0 | AJ285: 0 | AK285: 0 | AL285: 0 | AM285: =ROUND((N285/IF(M285>26,26,M285)/8*(AH285*$AH$5+AI285*$AI$5+AJ285*$AJ$5+AK285*$AK$5+AL285*$AL$5)),0) -> 1473058 | AN285: =ROUND(AG285+AM285,0) -> 8576913 | AO285: 595770 | AP285: 44100 | AQ285: 0 | AR285: 130000 | AS285: 0 | AT285: =+ROUND(SUM(AN285:AN285)-SUM(AO285:AS285),0) -> 7807043 | AW285: LUU THI THU HA | AX285: 050116972929 | AY285: Seaman | AZ285: 622 | BA285: =+IF(AY285="SK1 Box","Box",IF(AY285="Seaman","Seaman","Bag")) -> Seaman
A286: =SUBTOTAL(3,B$6:B286) -> 281 | B286: C16066 | C286: Đàm Văn Long | D286: 45496 | E286: FACTORY A | F286: P8 - Sheeter | G286: Auto Machine operator-C | H286: 5274000 | I286: 700000 | J286: 0 | K286: 0 | L286: =SUM(H286:K286) -> 5974000 | M286: 24 | N286: =ROUND((H286+I286+J286+K286)/IF($M$2>26,26,$M$2)*M286,0) -> 5514462 | O286: 2 | P286: =ROUND((H286+I286+J286+K286)/IF($M$2>26,26,$M$2)*O286,0) -> 459538 | Q286: 0 | R286: =IF(M286>0,ROUND(N286/IF(M286>26,26,M286)/8*Q286*30%,0),0) -> 0 | S286: =N286+P286+R286 -> 5974000 | T286: 0 | U286: 0 | V286: 200000 | W286: 500000 | X286: 0 | Y286: 400000 | Z286: 415112 | AC286: 0 | AD286: 0 | AE286: 0 | AG286: =ROUND(SUM(S286:AF286)-AA286,0) -> 7489112 | AH286: 48 | AI286: 0 | AJ286: 0 | AK286: 0 | AL286: 0 | AM286: =ROUND((N286/IF(M286>26,26,M286)/8*(AH286*$AH$5+AI286*$AI$5+AJ286*$AJ$5+AK286*$AK$5+AL286*$AL$5)),0) -> 2067923 | AN286: =ROUND(AG286+AM286,0) -> 9557035 | AO286: 627270 | AP286: 44100 | AQ286: 0 | AR286: 0 | AS286: 0 | AT286: =+ROUND(SUM(AN286:AN286)-SUM(AO286:AS286),0) -> 8885665 | AW286: DAM VAN LONG | AX286: 050153900131 | AY286: Seaman | AZ286: 622 | BA286: =+IF(AY286="SK1 Box","Box",IF(AY286="Seaman","Seaman","Bag")) -> Seaman
A287: =SUBTOTAL(3,B$6:B287) -> 282 | B287: C16436 | C287: Châu Khắc Cường | D287: 45701 | E287: FACTORY A | F287: P8 - Sheeter | G287: Auto Machine sub-operator-C | H287: 5023000 | I287: 400000 | J287: 0 | K287: 0 | L287: =SUM(H287:K287) -> 5423000 | M287: 22.9 | N287: =ROUND((H287+I287+J287+K287)/IF($M$2>26,26,$M$2)*M287,0) -> 4776412 | O287: 2 | P287: =ROUND((H287+I287+J287+K287)/IF($M$2>26,26,$M$2)*O287,0) -> 417154 | Q287: 0 | R287: =IF(M287>0,ROUND(N287/IF(M287>26,26,M287)/8*Q287*30%,0),0) -> 0 | S287: =N287+P287+R287 -> 5193566 | T287: 0 | U287: 0 | V287: 200000 | W287: 0 | X287: 0 | Y287: 400000 | Z287: 448574 | AC287: 0 | AD287: 0 | AE287: 0 | AG287: =ROUND(SUM(S287:AF287)-AA287,0) -> 6242140 | AH287: 32 | AI287: 0 | AJ287: 0 | AK287: 0 | AL287: 0 | AM287: =ROUND((N287/IF(M287>26,26,M287)/8*(AH287*$AH$5+AI287*$AI$5+AJ287*$AJ$5+AK287*$AK$5+AL287*$AL$5)),0) -> 1251462 | AN287: =ROUND(AG287+AM287,0) -> 7493602 | AO287: 569415 | AP287: 44100 | AQ287: 0 | AR287: 0 | AS287: 0 | AT287: =+ROUND(SUM(AN287:AN287)-SUM(AO287:AS287),0) -> 6880087 | AW287: CHAU KHAC CUONG | AX287: 050040786225 | AY287: Seaman | AZ287: 622 | BA287: =+IF(AY287="SK1 Box","Box",IF(AY287="Seaman","Seaman","Bag")) -> Seaman
A288: =SUBTOTAL(3,B$6:B288) -> 283 | B288: C16610 | C288: Đỗ Quốc Thái | D288: 45762 | E288: FACTORY A | F288: P8 - Sheeter | G288: New worker | H288: 4694000 | I288: 0 | J288: 0 | K288: 0 | L288: =SUM(H288:K288) -> 4694000 | M288: 13 | N288: =ROUND((H288+I288+J288+K288)/IF($M$2>26,26,$M$2)*M288,0) -> 2347000 | O288: 1 | P288: =ROUND((H288+I288+J288+K288)/IF($M$2>26,26,$M$2)*O288,0) -> 180538 | Q288: 0 | R288: =IF(M288>0,ROUND(N288/IF(M288>26,26,M288)/8*Q288*30%,0),0) -> 0 | S288: =N288+P288+R288 -> 2527538 | T288: 0 | U288: 0 | V288: 108000 | W288: 269000 | X288: 0 | Y288: 81000 | Z288: 205921 | AC288: 0 | AD288: 0 | AE288: 0 | AG288: =ROUND(SUM(S288:AF288)-AA288,0) -> 3191459 | AH288: 12 | AI288: 0 | AJ288: 0 | AK288: 0 | AL288: 0 | AM288: =ROUND((N288/IF(M288>26,26,M288)/8*(AH288*$AH$5+AI288*$AI$5+AJ288*$AJ$5+AK288*$AK$5+AL288*$AL$5)),0) -> 406212 | AN288: =ROUND(AG288+AM288,0) -> 3597671 | AO288: 0 | AP288: 0 | AQ288: 0 | AR288: 0 | AS288: 0 | AT288: =+ROUND(SUM(AN288:AN288)-SUM(AO288:AS288),0) -> 3597671 | AW288: DO QUOC THAI | AX288: 050357954722 | AY288: Seaman | AZ288: 622 | BA288: =+IF(AY288="SK1 Box","Box",IF(AY288="Seaman","Seaman","Bag")) -> Seaman
A289: =SUBTOTAL(3,B$6:B289) -> 284 | B289: C16123 | C289: Quách Văn Hiền | D289: 45528 | E289: FACTORY A | F289: P8 - Slitter | G289: Auto Machine operator-C | H289: 5274000 | I289: 700000 | J289: 0 | K289: 0 | L289: =SUM(H289:K289) -> 5974000 | M289: 22.6 | N289: =ROUND((H289+I289+J289+K289)/IF($M$2>26,26,$M$2)*M289,0) -> 5192785 | O289: 3 | P289: =ROUND((H289+I289+J289+K289)/IF($M$2>26,26,$M$2)*O289,0) -> 689308 | Q289: 0 | R289: =IF(M289>0,ROUND(N289/IF(M289>26,26,M289)/8*Q289*30%,0),0) -> 0 | S289: =N289+P289+R289 -> 5882093 | T289: 0 | U289: 0 | V289: 200000 | W289: 500000 | X289: 0 | Y289: 300000 | Z289: 340843 | AC289: 0 | AD289: 0 | AE289: 0 | AG289: =ROUND(SUM(S289:AF289)-AA289,0) -> 7222936 | AH289: 24.5 | AI289: 0 | AJ289: 0 | AK289: 0 | AL289: 0 | AM289: =ROUND((N289/IF(M289>26,26,M289)/8*(AH289*$AH$5+AI289*$AI$5+AJ289*$AJ$5+AK289*$AK$5+AL289*$AL$5)),0) -> 1055502 | AN289: =ROUND(AG289+AM289,0) -> 8278438 | AO289: 627270 | AP289: 44100 | AQ289: 0 | AR289: 0 | AS289: 0 | AT289: =+ROUND(SUM(AN289:AN289)-SUM(AO289:AS289),0) -> 7607068 | AW289: QUACH VAN HIEN | AX289: 050058821966 | AY289: Seaman | AZ289: 622 | BA289: =+IF(AY289="SK1 Box","Box",IF(AY289="Seaman","Seaman","Bag")) -> Seaman
A290: =SUBTOTAL(3,B$6:B290) -> 285 | B290: C13358 | C290: Phan Hồ Hải | D290: 44257 | E290: FACTORY B | F290: P5 - Auto Paper lami Box | G290: Auto Machine Operator-C | H290: 5931000 | I290: 1500000 | J290: 0 | K290: 0 | L290: =SUM(H290:K290) -> 7431000 | M290: 23.8 | N290: =ROUND((H290+I290+J290+K290)/IF($M$2>26,26,$M$2)*M290,0) -> 6802223 | O290: 2 | P290: =ROUND((H290+I290+J290+K290)/IF($M$2>26,26,$M$2)*O290,0) -> 571615 | Q290: 0 | R290: =IF(M290>0,ROUND(N290/IF(M290>26,26,M290)/8*Q290*30%,0),0) -> 0 | S290: =N290+P290+R290 -> 7373838 | T290: 0 | U290: 0 | V290: 200000 | W290: 500000 | X290: 0 | Y290: 400000 | Z290: 190110 | AC290: 0 | AD290: 0 | AE290: 0 | AG290: =ROUND(SUM(S290:AF290)-AA290,0) -> 8663948 | AH290: 48 | AI290: 0 | AJ290: 0 | AK290: 0 | AL290: 0 | AM290: =ROUND((N290/IF(M290>26,26,M290)/8*(AH290*$AH$5+AI290*$AI$5+AJ290*$AJ$5+AK290*$AK$5+AL290*$AL$5)),0) -> 2572269 | AN290: =ROUND(AG290+AM290,0) -> 11236217 | AO290: 780255 | AP290: 44100 | AQ290: 0 | AR290: 0 | AS290: 0 | AT290: =+ROUND(SUM(AN290:AN290)-SUM(AO290:AS290),0) -> 10411862 | AW290: PHAN HO HAI | AX290: 050126776729 | AY290: SK1 Box | AZ290: 622 | BA290: =+IF(AY290="SK1 Box","Box",IF(AY290="Seaman","Seaman","Bag")) -> Box
A291: =SUBTOTAL(3,B$6:B291) -> 286 | B291: C2287 | C291: Trần Văn Dũng | D291: 40233 | E291: FACTORY B | F291: P5 - Auto Paper lami Box | G291: Auto Machine leader-C | H291: 5931000 | I291: 3500000 | J291: 0 | K291: 200000 | L291: =SUM(H291:K291) -> 9631000 | M291: 23.8 | N291: =ROUND((H291+I291+J291+K291)/IF($M$2>26,26,$M$2)*M291,0) -> 8816069 | O291: 2 | P291: =ROUND((H291+I291+J291+K291)/IF($M$2>26,26,$M$2)*O291,0) -> 740846 | Q291: 0 | R291: =IF(M291>0,ROUND(N291/IF(M291>26,26,M291)/8*Q291*30%,0),0) -> 0 | S291: =N291+P291+R291 -> 9556915 | T291: 0 | U291: 0 | V291: 200000 | W291: 500000 | X291: 0 | Y291: 400000 | Z291: 532606 | AC291: 0 | AD291: 0 | AE291: 0 | AG291: =ROUND(SUM(S291:AF291)-AA291,0) -> 11189521 | AH291: 44 | AI291: 0 | AJ291: 0 | AK291: 0 | AL291: 0 | AM291: =ROUND((N291/IF(M291>26,26,M291)/8*(AH291*$AH$5+AI291*$AI$5+AJ291*$AJ$5+AK291*$AK$5+AL291*$AL$5)),0) -> 3055990 | AN291: =ROUND(AG291+AM291,0) -> 14245511 | AO291: 1011255 | AP291: 44100 | AQ291: 65780 | AR291: 0 | AS291: 0 | AT291: =+ROUND(SUM(AN291:AN291)-SUM(AO291:AS291),0) -> 13124376 | AW291: TRAN VAN DUNG | AX291: 050040819042 | AY291: SK1 Box | AZ291: 622 | BA291: =+IF(AY291="SK1 Box","Box",IF(AY291="Seaman","Seaman","Bag")) -> Box
A292: =SUBTOTAL(3,B$6:B292) -> 287 | B292: C7226 | C292: Võ Minh Thủ | D292: 43179 | E292: FACTORY B | F292: P5 - Auto Paper lami Box | G292: Auto Machine operator-C | H292: 5931000 | I292: 2100000 | J292: 0 | K292: 500000 | L292: =SUM(H292:K292) -> 8531000 | M292: 24 | N292: =ROUND((H292+I292+J292+K292)/IF($M$2>26,26,$M$2)*M292,0) -> 7874769 | O292: 2 | P292: =ROUND((H292+I292+J292+K292)/IF($M$2>26,26,$M$2)*O292,0) -> 656231 | Q292: 0 | R292: =IF(M292>0,ROUND(N292/IF(M292>26,26,M292)/8*Q292*30%,0),0) -> 0 | S292: =N292+P292+R292 -> 8531000 | T292: 0 | U292: 0 | V292: 200000 | W292: 500000 | X292: 0 | Y292: 400000 | Z292: 483317 | AC292: 100000 | AD292: 0 | AE292: 0 | AG292: =ROUND(SUM(S292:AF292)-AA292,0) -> 10214317 | AH292: 48 | AI292: 0 | AJ292: 0 | AK292: 0 | AL292: 0 | AM292: =ROUND((N292/IF(M292>26,26,M292)/8*(AH292*$AH$5+AI292*$AI$5+AJ292*$AJ$5+AK292*$AK$5+AL292*$AL$5)),0) -> 2953038 | AN292: =ROUND(AG292+AM292,0) -> 13167355 | AO292: 895755 | AP292: 44100 | AQ292: 19363 | AR292: 0 | AS292: 0 | AT292: =+ROUND(SUM(AN292:AN292)-SUM(AO292:AS292),0) -> 12208137 | AW292: VO MINH THU | AX292: 050040902543 | AY292: SK1 Box | AZ292: 622 | BA292: =+IF(AY292="SK1 Box","Box",IF(AY292="Seaman","Seaman","Bag")) -> Box
... A378: =SUBTOTAL(3,B$6:B378) -> 373 | B378: C1306 | C378: Nguyễn Thị Thanh Mỹ | D378: 39776 | E378: FACTORY B | F378: P5 - Production Office | G378: Plan staff | H378: 7119000 | I378: 2500000 | J378: 0 | K378: 2000000 | L378: =SUM(H378:K378) -> 11619000 | M378: 22.6 | N378: =ROUND((H378+I378+J378+K378)/IF($M$2>26,26,$M$2)*M378,0) -> 10099592 | O378: 3 | P378: =ROUND((H378+I378+J378+K378)/IF($M$2>26,26,$M$2)*O378,0) -> 1340654 | Q378: 0 | R378: =IF(M378>0,ROUND(N378/IF(M378>26,26,M378)/8*Q378*30%,0),0) -> 0 | S378: =N378+P378+R378 -> 11440246 | T378: 0 | U378: 0 | V378: 200000 | W378: 500000 | X378: 0 | Y378: 400000 | Z378: 345834 | AC378: 100000 | AD378: 0 | AE378: 83790.863 | AG378: =ROUND(SUM(S378:AF378)-AA378,0) -> 13069871 | AH378: 0 | AI378: 0 | AJ378: 0 | AK378: 0 | AL378: 0 | AM378: =ROUND((N378/IF(M378>26,26,M378)/8*(AH378*$AH$5+AI378*$AI$5+AJ378*$AJ$5+AK378*$AK$5+AL378*$AL$5)),0) -> 0 | AN378: =ROUND(AG378+AM378,0) -> 13069871 | AO378: 1219995 | AP378: 44100 | AQ378: 0 | AR378: 0 | AS378: 0 | AT378: =+ROUND(SUM(AN378:AN378)-SUM(AO378:AS378),0) -> 11805776 | AW378: NGUYEN THI THANH MY | AX378: 050040823201 | AY378: SK1 Bag | AZ378: 627 | BA378: =+IF(AY378="SK1 Box","Box",IF(AY378="Seaman","Seaman","Bag")) -> Bag
A379: =SUBTOTAL(3,B$6:B379) -> 374 | B379: C14623 | C379: Trần Văn Hoài | D379: 44621 | E379: FACTORY B | F379: P5 - Production Office | G379: Factory manager | H379: 15800000 | I379: 20500000 | J379: 0 | K379: 0 | L379: =SUM(H379:K379) -> 36300000 | M379: 23.5 | N379: =ROUND((H379+I379+J379+K379)/IF($M$2>26,26,$M$2)*M379,0) -> 32809615 | O379: 2 | P379: =ROUND((H379+I379+J379+K379)/IF($M$2>26,26,$M$2)*O379,0) -> 2792308 | Q379: 0 | R379: =IF(M379>0,ROUND(N379/IF(M379>26,26,M379)/8*Q379*30%,0),0) -> 0 | S379: =N379+P379+R379 -> 35601923 | T379: 490385 | U379: 0 | V379: 0 | W379: 0 | X379: 0 | Y379: 0 | Z379: 0 | AC379: 0 | AD379: 0 | AE379: 0 | AG379: =ROUND(SUM(S379:AF379)-AA379,0) -> 36092308 | AH379: 0 | AI379: 0 | AJ379: 0 | AK379: 0 | AL379: 0 | AM379: =ROUND((N379/IF(M379>26,26,M379)/8*(AH379*$AH$5+AI379*$AI$5+AJ379*$AJ$5+AK379*$AK$5+AL379*$AL$5)),0) -> 0 | AN379: =ROUND(AG379+AM379,0) -> 36092308 | AO379: 3811500 | AP379: 0 | AQ379: 519042 | AR379: 0 | AS379: 0 | AT379: =+ROUND(SUM(AN379:AN379)-SUM(AO379:AS379),0) -> 31761766 | AW379: TRAN VAN HOAI | AX379: 050040818690 | AY379: SK1 Box | AZ379: 627 | BA379: Manager
A380: =SUBTOTAL(3,B$6:B380) -> 375 | B380: C14762 | C380: Bùi Thị Yến Thu | D380: 44649 | E380: FACTORY B | F380: P5 - Production Office | G380: Plan staff | H380: 5773000 | I380: 1900000 | J380: 0 | K380: 0 | L380: =SUM(H380:K380) -> 7673000 | M380: 23 | N380: =ROUND((H380+I380+J380+K380)/IF($M$2>26,26,$M$2)*M380,0) -> 6787654 | O380: 3 | P380: =ROUND((H380+I380+J380+K380)/IF($M$2>26,26,$M$2)*O380,0) -> 885346 | Q380: 0 | R380: =IF(M380>0,ROUND(N380/IF(M380>26,26,M380)/8*Q380*30%,0),0) -> 0 | S380: =N380+P380+R380 -> 7673000 | T380: 0 | U380: 0 | V380: 200000 | W380: 500000 | X380: 0 | Y380: 400000 | Z380: 351955 | AC380: 0 | AD380: 0 | AE380: 55334.136 | AG380: =ROUND(SUM(S380:AF380)-AA380,0) -> 9180289 | AH380: 0 | AI380: 0 | AJ380: 0 | AK380: 0 | AL380: 0 | AM380: =ROUND((N380/IF(M380>26,26,M380)/8*(AH380*$AH$5+AI380*$AI$5+AJ380*$AJ$5+AK380*$AK$5+AL380*$AL$5)),0) -> 0 | AN380: =ROUND(AG380+AM380,0) -> 9180289 | AO380: 805665 | AP380: 44100 | AQ380: 0 | AR380: 0 | AS380: 0 | AT380: =+ROUND(SUM(AN380:AN380)-SUM(AO380:AS380),0) -> 8330524 | AW380: BUI THI YEN THU | AX380: 050066285429 | AY380: SK1 Bag | AZ380: 627 | BA380: =+IF(AY380="SK1 Box","Box",IF(AY380="Seaman","Seaman","Bag")) -> Bag
A381: =SUBTOTAL(3,B$6:B381) -> 376 | B381: C3465 | C381: Lê Văn Khỏe | D381: 40596 | E381: FACTORY B | F381: P5 - Production Office | G381: Factory vice manager | H381: 11219000 | I381: 7300000 | J381: 0 | K381: 0 | L381: =SUM(H381:K381) -> 18519000 | M381: 22.8 | N381: =ROUND((H381+I381+J381+K381)/IF($M$2>26,26,$M$2)*M381,0) -> 16239738 | O381: 3 | P381: =ROUND((H381+I381+J381+K381)/IF($M$2>26,26,$M$2)*O381,0) -> 2136808 | Q381: 0 | R381: =IF(M381>0,ROUND(N381/IF(M381>26,26,M381)/8*Q381*30%,0),0) -> 0 | S381: =N381+P381+R381 -> 18376546 | T381: 0 | U381: 0 | V381: 200000 | W381: 500000 | X381: 0 | Y381: 400000 | Z381: 0 | AC381: 0 | AD381: 0 | AE381: 0 | AG381: =ROUND(SUM(S381:AF381)-AA381,0) -> 19476546 | AH381: 32 | AI381: 0 | AJ381: 0 | AK381: 0 | AL381: 0 | AM381: =ROUND((N381/IF(M381>26,26,M381)/8*(AH381*$AH$5+AI381*$AI$5+AJ381*$AJ$5+AK381*$AK$5+AL381*$AL$5)),0) -> 4273615 | AN381: =ROUND(AG381+AM381,0) -> 23750161 | AO381: 1944495 | AP381: 44100 | AQ381: 34056 | AR381: 0 | AS381: 0 | AT381: =+ROUND(SUM(AN381:AN381)-SUM(AO381:AS381),0) -> 21727510 | AW381: LE VAN KHOE | AX381: 050040934399 | AY381: SK1 Box | AZ381: 627 | BA381: =+IF(AY381="SK1 Box","Box",IF(AY381="Seaman","Seaman","Bag")) -> Box
A382: =SUBTOTAL(3,B$6:B382) -> 377 | B382: C4110 | C382: Đàm Thị Thủy | D382: 40819 | E382: FACTORY B | F382: P5 - Production Office | G382: Factory vice manager | H382: 8076000 | I382: 7300000 | J382: 0 | K382: 0 | L382: =SUM(H382:K382) -> 15376000 | M382: 24 | N382: =ROUND((H382+I382+J382+K382)/IF($M$2>26,26,$M$2)*M382,0) -> 14193231 | O382: 2 | P382: =ROUND((H382+I382+J382+K382)/IF($M$2>26,26,$M$2)*O382,0) -> 1182769 | Q382: 0 | R382: =IF(M382>0,ROUND(N382/IF(M382>26,26,M382)/8*Q382*30%,0),0) -> 0 | S382: =N382+P382+R382 -> 15376000 | T382: 0 | U382: 0 | V382: 200000 | W382: 500000 | X382: 0 | Y382: 400000 | Z382: 0 | AC382: 0 | AD382: 0 | AE382: 110884.62 | AG382: =ROUND(SUM(S382:AF382)-AA382,0) -> 16586885 | AH382: 53 | AI382: 0 | AJ382: 0 | AK382: 0 | AL382: 0 | AM382: =ROUND((N382/IF(M382>26,26,M382)/8*(AH382*$AH$5+AI382*$AI$5+AJ382*$AJ$5+AK382*$AK$5+AL382*$AL$5)),0) -> 5876885 | AN382: =ROUND(AG382+AM382,0) -> 22463770 | AO382: 1614480 | AP382: 44100 | AQ382: 0 | AR382: 0 | AS382: 0 | AT382: =+ROUND(SUM(AN382:AN382)-SUM(AO382:AS382),0) -> 20805190 | AW382: DAM THI THUY | AX382: 050040820369 | AY382: SK1 Bag | AZ382: 627 | BA382: =+IF(AY382="SK1 Box","Box",IF(AY382="Seaman","Seaman","Bag")) -> Bag
A383: =SUBTOTAL(3,B$6:B383) -> 378 | B383: C15710 | C383: Văn Thị Vũ Thường | D383: 45360 | E383: FACTORY B | F383: P5 - QC | G383: Bag QC vice leader | H383: 5538000 | I383: 1900000 | J383: 0 | K383: 0 | L383: =SUM(H383:K383) -> 7438000 | M383: 22 | N383: =ROUND((H383+I383+J383+K383)/IF($M$2>26,26,$M$2)*M383,0) -> 6293692 | O383: 2 | P383: =ROUND((H383+I383+J383+K383)/IF($M$2>26,26,$M$2)*O383,0) -> 572154 | Q383: 0 | R383: =IF(M383>0,ROUND(N383/IF(M383>26,26,M383)/8*Q383*30%,0),0) -> 0 | S383: =N383+P383+R383 -> 6865846 | T383: 0 | U383: 0 | V383: 200000 | W383: 0 | X383: 0 | Y383: 300000 | Z383: 458300 | AC383: 100000 | AD383: 0 | AE383: 53639.42 | AG383: =ROUND(SUM(S383:AF383)-AA383,0) -> 7977785 | AH383: 40 | AI383: 0 | AJ383: 0 | AK383: 0 | AL383: 0 | AM383: =ROUND((N383/IF(M383>26,26,M383)/8*(AH383*$AH$5+AI383*$AI$5+AJ383*$AJ$5+AK383*$AK$5+AL383*$AL$5)),0) -> 2145577 | AN383: =ROUND(AG383+AM383,0) -> 10123362 | AO383: 780990 | AP383: 44100 | AQ383: 0 | AR383: 0 | AS383: 0 | AT383: =+ROUND(SUM(AN383:AN383)-SUM(AO383:AS383),0) -> 9298272 | AW383: VAN THI VU THUONG | AX383: 050040823015 | AY383: SK1 Bag | AZ383: 622 | BA383: =+IF(AY383="SK1 Box","Box",IF(AY383="Seaman","Seaman","Bag")) -> Bag
A384: =SUBTOTAL(3,B$6:B384) -> 379 | B384: C15937 | C384: Lê Thị Cẩm Nhung | D384: 45432 | E384: FACTORY B | F384: P5 - QC | G384: QC worker | H384: 5274000 | I384: 500000 | J384: 0 | K384: 0 | L384: =SUM(H384:K384) -> 5774000 | M384: 24 | N384: =ROUND((H384+I384+J384+K384)/IF($M$2>26,26,$M$2)*M384,0) -> 5329846 | O384: 2 | P384: =ROUND((H384+I384+J384+K384)/IF($M$2>26,26,$M$2)*O384,0) -> 444154 | Q384: 0 | R384: =IF(M384>0,ROUND(N384/IF(M384>26,26,M384)/8*Q384*30%,0),0) -> 0 | S384: =N384+P384+R384 -> 5774000 | T384: 0 | U384: 0 | V384: 200000 | W384: 500000 | X384: 0 | Y384: 400000 | Z384: 400000 | AC384: 0 | AD384: 0 | AE384: 41639.422 | AG384: =ROUND(SUM(S384:AF384)-AA384,0) -> 7315639 | AH384: 48 | AI384: 0 | AJ384: 0 | AK384: 0 | AL384: 0 | AM384: =ROUND((N384/IF(M384>26,26,M384)/8*(AH384*$AH$5+AI384*$AI$5+AJ384*$AJ$5+AK384*$AK$5+AL384*$AL$5)),0) -> 1998692 | AN384: =ROUND(AG384+AM384,0) -> 9314331 | AO384: 606270 | AP384: 44100 | AQ384: 0 | AR384: 0 | AS384: 0 | AT384: =+ROUND(SUM(AN384:AN384)-SUM(AO384:AS384),0) -> 8663961 | AW384: LE THI CAM NHUNG | AX384: 050153430923 | AY384: SK1 Box | AZ384: 622 | BA384: =+IF(AY384="SK1 Box","Box",IF(AY384="Seaman","Seaman","Bag")) -> Box
A385: =SUBTOTAL(3,B$6:B385) -> 380 | B385: C16417 | C385: Huỳnh Thị Thu Hương | D385: 45696 | E385: FACTORY B | F385: P5 - QC | G385: QC worker | H385: 5023000 | I385: 500000 | J385: 0 | K385: 0 | L385: =SUM(H385:K385) -> 5523000 | M385: 24 | N385: =ROUND((H385+I385+J385+K385)/IF($M$2>26,26,$M$2)*M385,0) -> 5098154 | O385: 2 | P385: =ROUND((H385+I385+J385+K385)/IF($M$2>26,26,$M$2)*O385,0) -> 424846 | Q385: 0 | R385: =IF(M385>0,ROUND(N385/IF(M385>26,26,M385)/8*Q385*30%,0),0) -> 0 | S385: =N385+P385+R385 -> 5523000 | T385: 0 | U385: 0 | V385: 200000 | W385: 500000 | X385: 0 | Y385: 400000 | Z385: 400000 | AC385: 0 | AD385: 0 | AE385: 39829.328 | AG385: =ROUND(SUM(S385:AF385)-AA385,0) -> 7062829 | AH385: 48 | AI385: 0 | AJ385: 0 | AK385: 0 | AL385: 0 | AM385: =ROUND((N385/IF(M385>26,26,M385)/8*(AH385*$AH$5+AI385*$AI$5+AJ385*$AJ$5+AK385*$AK$5+AL385*$AL$5)),0) -> 1911808 | AN385: =ROUND(AG385+AM385,0) -> 8974637 | AO385: 579915 | AP385: 44100 | AQ385: 0 | AR385: 0 | AS385: 0 | AT385: =+ROUND(SUM(AN385:AN385)-SUM(AO385:AS385),0) -> 8350622 | AW385: HUYNH THI THU HUONG | AX385: 050133547131 | AY385: SK1 Box | AZ385: 622 | BA385: =+IF(AY385="SK1 Box","Box",IF(AY385="Seaman","Seaman","Bag")) -> Box
A386: =SUBTOTAL(3,B$6:B386) -> 381 | B386: C16447 | C386: Võ Thị Bích Ngọc | D386: 45706 | E386: FACTORY B | F386: P5 - QC | G386: QC worker | H386: 5023000 | I386: 500000 | J386: 0 | K386: 0 | L386: =SUM(H386:K386) -> 5523000 | M386: 22.8 | N386: =ROUND((H386+I386+J386+K386)/IF($M$2>26,26,$M$2)*M386,0) -> 4843246 | O386: 3 | P386: =ROUND((H386+I386+J386+K386)/IF($M$2>26,26,$M$2)*O386,0) -> 637269 | Q386: 0 | R386: =IF(M386>0,ROUND(N386/IF(M386>26,26,M386)/8*Q386*30%,0),0) -> 0 | S386: =N386+P386+R386 -> 5480515 | T386: 0 | U386: 0 | V386: 200000 | W386: 500000 | X386: 0 | Y386: 400000 | Z386: 285000 | AC386: 0 | AD386: 0 | AE386: 39829.326 | AG386: =ROUND(SUM(S386:AF386)-AA386,0) -> 6905344 | AH386: 32 | AI386: 0 | AJ386: 0 | AK386: 0 | AL386: 0 | AM386: =ROUND((N386/IF(M386>26,26,M386)/8*(AH386*$AH$5+AI386*$AI$5+AJ386*$AJ$5+AK386*$AK$5+AL386*$AL$5)),0) -> 1274538 | AN386: =ROUND(AG386+AM386,0) -> 8179882 | AO386: 579915 | AP386: 44100 | AQ386: 0 | AR386: 0 | AS386: 0 | AT386: =+ROUND(SUM(AN386:AN386)-SUM(AO386:AS386),0) -> 7555867 | AW386: VO THI BICH NGOC | AX386: 050118892981 | AY386: SK1 Bag | AZ386: 622 | BA386: =+IF(AY386="SK1 Box","Box",IF(AY386="Seaman","Seaman","Bag")) -> Bag
A387: =SUBTOTAL(3,B$6:B387) -> 382 | B387: C2079 | C387: Huỳnh Mẫu Bảy | D387: 40091 | E387: FACTORY B | F387: P5 - QC | G387: Bag QC leader | H387: 6641000 | I387: 3200000 | J387: 0 | K387: 2000000 | L387: =SUM(H387:K387) -> 11841000 | M387: 24 | N387: =ROUND((H387+I387+J387+K387)/IF($M$2>26,26,$M$2)*M387,0) -> 10930154 | O387: 2 | P387: =ROUND((H387+I387+J387+K387)/IF($M$2>26,26,$M$2)*O387,0) -> 910846 | Q387: 0 | R387: =IF(M387>0,ROUND(N387/IF(M387>26,26,M387)/8*Q387*30%,0),0) -> 0 | S387: =N387+P387+R387 -> 11841000 | T387: 0 | U387: 0 | V387: 200000 | W387: 500000 | X387: 0 | Y387: 400000 | Z387: 700000 | AC387: 0 | AD387: 0 | AE387: 0 | AG387: =ROUND(SUM(S387:AF387)-AA387,0) -> 13641000 | AH387: 51 | AI387: 0 | AJ387: 0 | AK387: 0 | AL387: 0 | AM387: =ROUND((N387/IF(M387>26,26,M387)/8*(AH387*$AH$5+AI387*$AI$5+AJ387*$AJ$5+AK387*$AK$5+AL387*$AL$5)),0) -> 4354983 | AN387: =ROUND(AG387+AM387,0) -> 17995983 | AO387: 1243305 | AP387: 44100 | AQ387: 0 | AR387: 0 | AS387: 0 | AT387: =+ROUND(SUM(AN387:AN387)-SUM(AO387:AS387),0) -> 16708578 | AW387: HUYNH MAU BAY | AX387: 050040931926 | AY387: SK1 Bag | AZ387: 622 | BA387: =+IF(AY387="SK1 Box","Box",IF(AY387="Seaman","Seaman","Bag")) -> Bag
A388: =SUBTOTAL(3,B$6:B388) -> 383 | B388: C5204 | C388: Lê Mộng Hằng | D388: 41172 | E388: FACTORY B | F388: P5 - QC | G388: QC worker | H388: 5931000 | I388: 1100000 | J388: 0 | K388: 0 | L388: =SUM(H388:K388) -> 7031000 | M388: 24 | N388: =ROUND((H388+I388+J388+K388)/IF($M$2>26,26,$M$2)*M388,0) -> 6490154 | O388: 2 | P388: =ROUND((H388+I388+J388+K388)/IF($M$2>26,26,$M$2)*O388,0) -> 540846 | Q388: 0 | R388: =IF(M388>0,ROUND(N388/IF(M388>26,26,M388)/8*Q388*30%,0),0) -> 0 | S388: =N388+P388+R388 -> 7031000 | T388: 0 | U388: 0 | V388: 200000 | W388: 500000 | X388: 0 | Y388: 400000 | Z388: 400000 | AC388: 0 | AD388: 0 | AE388: 50704.328 | AG388: =ROUND(SUM(S388:AF388)-AA388,0) -> 8581704 | AH388: 48 | AI388: 0 | AJ388: 0 | AK388: 0 | AL388: 0 | AM388: =ROUND((N388/IF(M388>26,26,M388)/8*(AH388*$AH$5+AI388*$AI$5+AJ388*$AJ$5+AK388*$AK$5+AL388*$AL$5)),0) -> 2433808 | AN388: =ROUND(AG388+AM388,0) -> 11015512 | AO388: 738255 | AP388: 44100 | AQ388: 0 | AR388: 0 | AS388: 0 | AT388: =+ROUND(SUM(AN388:AN388)-SUM(AO388:AS388),0) -> 10233157 | AW388: LE MONG HANG | AX388: 050040924237 | AY388: SK1 Box | AZ388: 622 | BA388: =+IF(AY388="SK1 Box","Box",IF(AY388="Seaman","Seaman","Bag")) -> Box
A389: =SUBTOTAL(3,B$6:B389) -> 384 | B389: C5531 | C389: Vũ Thị Phương | D389: 41334 | E389: FACTORY B | F389: P5 - QC | G389: QC worker | H389: 5931000 | I389: 1100000 | J389: 0 | K389: 500000 | L389: =SUM(H389:K389) -> 7531000 | M389: 22.9 | N389: =ROUND((H389+I389+J389+K389)/IF($M$2>26,26,$M$2)*M389,0) -> 6633073 | O389: 3 | P389: =ROUND((H389+I389+J389+K389)/IF($M$2>26,26,$M$2)*O389,0) -> 868962 | Q389: 0 | R389: =IF(M389>0,ROUND(N389/IF(M389>26,26,M389)/8*Q389*30%,0),0) -> 0 | S389: =N389+P389+R389 -> 7502035 | T389: 0 | U389: 0 | V389: 200000 | W389: 500000 | X389: 0 | Y389: 400000 | Z389: 381700 | AC389: 100000 | AD389: 0 | AE389: 54310.096 | AG389: =ROUND(SUM(S389:AF389)-AA389,0) -> 9138045 | AH389: 36 | AI389: 0 | AJ389: 0 | AK389: 0 | AL389: 0 | AM389: =ROUND((N389/IF(M389>26,26,M389)/8*(AH389*$AH$5+AI389*$AI$5+AJ389*$AJ$5+AK389*$AK$5+AL389*$AL$5)),0) -> 1955163 | AN389: =ROUND(AG389+AM389,0) -> 11093208 | AO389: 790755 | AP389: 44100 | AQ389: 0 | AR389: 0 | AS389: 0 | AT389: =+ROUND(SUM(AN389:AN389)-SUM(AO389:AS389),0) -> 10258353 | AW389: VU THI PHUONG | AX389: 050040932450 | AY389: SK1 Bag | AZ389: 622 | BA389: =+IF(AY389="SK1 Box","Box",IF(AY389="Seaman","Seaman","Bag")) -> Bag
A390: =SUBTOTAL(3,B$6:B390) -> 385 | B390: C13967 | C390: Lê Thị Huỳnh Như | D390: 44306 | E390: FACTORY B | F390: P5 - Semi HS Bag | G390: Semi Machine sub-operator | H390: 5931000 | I390: 400000 | J390: 0 | K390: 0 | L390: =SUM(H390:K390) -> 6331000 | M390: 24 | N390: =ROUND((H390+I390+J390+K390)/IF($M$2>26,26,$M$2)*M390,0) -> 5844000 | O390: 2 | P390: =ROUND((H390+I390+J390+K390)/IF($M$2>26,26,$M$2)*O390,0) -> 487000 | Q390: 0 | R390: =IF(M390>0,ROUND(N390/IF(M390>26,26,M390)/8*Q390*30%,0),0) -> 0 | S390: =N390+P390+R390 -> 6331000 | T390: 0 | U390: 0 | V390: 200000 | W390: 500000 | X390: 0 | Y390: 400000 | Z390: 556478 | AC390: 100000 | AD390: 0 | AE390: 45656.25 | AG390: =ROUND(SUM(S390:AF390)-AA390,0) -> 8133134 | AH390: 52 | AI390: 0 | AJ390: 0 | AK390: 0 | AL390: 0 | AM390: =ROUND((N390/IF(M390>26,26,M390)/8*(AH390*$AH$5+AI390*$AI$5+AJ390*$AJ$5+AK390*$AK$5+AL390*$AL$5)),0) -> 2374125 | AN390: =ROUND(AG390+AM390,0) -> 10507259 | AO390: 664755 | AP390: 44100 | AQ390: 0 | AR390: 0 | AS390: 0 | AT390: =+ROUND(SUM(AN390:AN390)-SUM(AO390:AS390),0) -> 9798404 | AW390: LE THI HUYNH NHU | AX390: 050127733071 | AY390: SK1 Bag | AZ390: 622 | BA390: =+IF(AY390="SK1 Box","Box",IF(AY390="Seaman","Seaman","Bag")) -> Bag
A391: =SUBTOTAL(3,B$6:B391) -> 386 | B391: C1478 | C391: Nguyễn Thị Ngọc Lan | D391: 39811 | E391: FACTORY B | F391: P5 - Semi HS Bag | G391: Semi machine operator | H391: 5931000 | I391: 900000 | J391: 0 | K391: 0 | L391: =SUM(H391:K391) -> 6831000 | M391: 23 | N391: =ROUND((H391+I391+J391+K391)/IF($M$2>26,26,$M$2)*M391,0) -> 6042808 | O391: 3 | P391: =ROUND((H391+I391+J391+K391)/IF($M$2>26,26,$M$2)*O391,0) -> 788192 | Q391: 0 | R391: =IF(M391>0,ROUND(N391/IF(M391>26,26,M391)/8*Q391*30%,0),0) -> 0 | S391: =N391+P391+R391 -> 6831000 | T391: 0 | U391: 0 | V391: 200000 | W391: 500000 | X391: 0 | Y391: 400000 | Z391: 334718 | AC391: 0 | AD391: 0 | AE391: 49262.022 | AG391: =ROUND(SUM(S391:AF391)-AA391,0) -> 8314980 | AH391: 48 | AI391: 0 | AJ391: 0 | AK391: 0 | AL391: 0 | AM391: =ROUND((N391/IF(M391>26,26,M391)/8*(AH391*$AH$5+AI391*$AI$5+AJ391*$AJ$5+AK391*$AK$5+AL391*$AL$5)),0) -> 2364577 | AN391: =ROUND(AG391+AM391,0) -> 10679557 | AO391: 717255 | AP391: 44100 | AQ391: 0 | AR391: 0 | AS391: 0 | AT391: =+ROUND(SUM(AN391:AN391)-SUM(AO391:AS391),0) -> 9918202 | AW391: NGUYEN THI NGOC LAN | AX391: 050040931748 | AY391: SK1 Bag | AZ391: 622 | BA391: =+IF(AY391="SK1 Box","Box",IF(AY391="Seaman","Seaman","Bag")) -> Bag
... A550: =SUBTOTAL(3,B$6:B550) -> 545 | B550: C16543 | C550: Đỗ Hoài Hận | D550: 45736 | E550: FACTORY D | F550: P4 - FB2-4 | G550: Normal worker | H550: 4694000 | I550: 0 | J550: 0 | K550: 0 | L550: =SUM(H550:K550) -> 4694000 | M550: 23 | N550: =ROUND((H550+I550+J550+K550)/IF($M$2>26,26,$M$2)*M550,0) -> 4152385 | O550: 3 | P550: =ROUND((H550+I550+J550+K550)/IF($M$2>26,26,$M$2)*O550,0) -> 541615 | Q550: 0 | R550: =IF(M550>0,ROUND(N550/IF(M550>26,26,M550)/8*Q550*30%,0),0) -> 0 | S550: =N550+P550+R550 -> 4694000 | T550: 0 | U550: 0 | V550: 200000 | W550: 500000 | X550: 0 | Y550: 400000 | Z550: 185238 | AC550: 0 | AD550: 132864 | AE550: 0 | AG550: =ROUND(SUM(S550:AF550)-AA550,0) -> 6112102 | AH550: 36 | AI550: 0 | AJ550: 0 | AK550: 0 | AL550: 0 | AM550: =ROUND((N550/IF(M550>26,26,M550)/8*(AH550*$AH$5+AI550*$AI$5+AJ550*$AJ$5+AK550*$AK$5+AL550*$AL$5)),0) -> 1218635 | AN550: =ROUND(AG550+AM550,0) -> 7330737 | AO550: 0 | AP550: 0 | AQ550: 0 | AR550: 0 | AS550: 0 | AT550: =+ROUND(SUM(AN550:AN550)-SUM(AO550:AS550),0) -> 7330737 | AW550: DO HOAI HAN | AX550: 056409022006 | AY550: SK1 Bag | AZ550: 622 | BA550: =+IF(AY550="SK1 Box","Box",IF(AY550="Seaman","Seaman","Bag")) -> Bag
A551: =SUBTOTAL(3,B$6:B551) -> 546 | B551: C16629 | C551: Mạc Thị Hòa | D551: 45771 | E551: FACTORY D | F551: P4 - FB2-4 | G551: New worker | H551: 4694000 | I551: 0 | J551: 0 | K551: 0 | L551: =SUM(H551:K551) -> 4694000 | M551: 5 | N551: =ROUND((H551+I551+J551+K551)/IF($M$2>26,26,$M$2)*M551,0) -> 902692 | O551: 1 | P551: =ROUND((H551+I551+J551+K551)/IF($M$2>26,26,$M$2)*O551,0) -> 180538 | Q551: 0 | R551: =IF(M551>0,ROUND(N551/IF(M551>26,26,M551)/8*Q551*30%,0),0) -> 0 | S551: =N551+P551+R551 -> 1083230 | T551: 0 | U551: 0 | V551: 46000 | W551: 115000 | X551: 0 | Y551: 35000 | Z551: 0 | AC551: 0 | AD551: 0 | AE551: 0 | AG551: =ROUND(SUM(S551:AF551)-AA551,0) -> 1279230 | AH551: 0 | AI551: 0 | AJ551: 0 | AK551: 0 | AL551: 0 | AM551: =ROUND((N551/IF(M551>26,26,M551)/8*(AH551*$AH$5+AI551*$AI$5+AJ551*$AJ$5+AK551*$AK$5+AL551*$AL$5)),0) -> 0 | AN551: =ROUND(AG551+AM551,0) -> 1279230 | AO551: 0 | AP551: 0 | AQ551: 0 | AR551: 0 | AS551: 0 | AT551: =+ROUND(SUM(AN551:AN551)-SUM(AO551:AS551),0) -> 1279230 | AX551: TM | AY551: SK1 Bag | AZ551: 622 | BA551: =+IF(AY551="SK1 Box","Box",IF(AY551="Seaman","Seaman","Bag")) -> Bag
A552: =SUBTOTAL(3,B$6:B552) -> 547 | B552: C4213 | C552: Thị Liên | D552: 40835 | E552: FACTORY D | F552: P4 - FB2-4 | G552: Normal worker | H552: 5931000 | I552: 0 | J552: 0 | K552: 0 | L552: =SUM(H552:K552) -> 5931000 | M552: 24 | N552: =ROUND((H552+I552+J552+K552)/IF($M$2>26,26,$M$2)*M552,0) -> 5474769 | O552: 2 | P552: =ROUND((H552+I552+J552+K552)/IF($M$2>26,26,$M$2)*O552,0) -> 456231 | Q552: 0 | R552: =IF(M552>0,ROUND(N552/IF(M552>26,26,M552)/8*Q552*30%,0),0) -> 0 | S552: =N552+P552+R552 -> 5931000 | T552: 0 | U552: 0 | V552: 200000 | W552: 500000 | X552: 0 | Y552: 400000 | Z552: 535571 | AC552: 0 | AD552: 0 | AE552: 42771.633 | AG552: =ROUND(SUM(S552:AF552)-AA552,0) -> 7609343 | AH552: 36 | AI552: 0 | AJ552: 0 | AK552: 0 | AL552: 0 | AM552: =ROUND((N552/IF(M552>26,26,M552)/8*(AH552*$AH$5+AI552*$AI$5+AJ552*$AJ$5+AK552*$AK$5+AL552*$AL$5)),0) -> 1539779 | AN552: =ROUND(AG552+AM552,0) -> 9149122 | AO552: 622755 | AP552: 44100 | AQ552: 0 | AR552: 0 | AS552: 0 | AT552: =+ROUND(SUM(AN552:AN552)-SUM(AO552:AS552),0) -> 8482267 | AW552: THI LIEN | AX552: 050040845418 | AY552: SK1 Bag | AZ552: 622 | BA552: =+IF(AY552="SK1 Box","Box",IF(AY552="Seaman","Seaman","Bag")) -> Bag
A553: =SUBTOTAL(3,B$6:B553) -> 548 | B553: C5326 | C553: Lê Thị Đào | D553: 41334 | E553: FACTORY D | F553: P4 - FB2-4 | G553: Normal worker | H553: 5931000 | I553: 0 | J553: 0 | K553: 0 | L553: =SUM(H553:K553) -> 5931000 | M553: 23 | N553: =ROUND((H553+I553+J553+K553)/IF($M$2>26,26,$M$2)*M553,0) -> 5246654 | O553: 3 | P553: =ROUND((H553+I553+J553+K553)/IF($M$2>26,26,$M$2)*O553,0) -> 684346 | Q553: 0 | R553: =IF(M553>0,ROUND(N553/IF(M553>26,26,M553)/8*Q553*30%,0),0) -> 0 | S553: =N553+P553+R553 -> 5931000 | T553: 0 | U553: 0 | V553: 200000 | W553: 500000 | X553: 0 | Y553: 400000 | Z553: 564405 | AC553: 100000 | AD553: 0 | AE553: 42771.636 | AG553: =ROUND(SUM(S553:AF553)-AA553,0) -> 7738177 | AH553: 36 | AI553: 0 | AJ553: 0 | AK553: 0 | AL553: 0 | AM553: =ROUND((N553/IF(M553>26,26,M553)/8*(AH553*$AH$5+AI553*$AI$5+AJ553*$AJ$5+AK553*$AK$5+AL553*$AL$5)),0) -> 1539779 | AN553: =ROUND(AG553+AM553,0) -> 9277956 | AO553: 622755 | AP553: 44100 | AQ553: 0 | AR553: 0 | AS553: 0 | AT553: =+ROUND(SUM(AN553:AN553)-SUM(AO553:AS553),0) -> 8611101 | AW553: LE THI DAO | AX553: 050040934593 | AY553: SK1 Bag | AZ553: 622 | BA553: =+IF(AY553="SK1 Box","Box",IF(AY553="Seaman","Seaman","Bag")) -> Bag
A554: =SUBTOTAL(3,B$6:B554) -> 549 | B554: C6879 | C554: Phan Thị Bích | D554: 42790 | E554: FACTORY D | F554: P4 - FB2-4 | G554: Normal worker | H554: 5931000 | I554: 0 | J554: 0 | K554: 0 | L554: =SUM(H554:K554) -> 5931000 | M554: 24 | N554: =ROUND((H554+I554+J554+K554)/IF($M$2>26,26,$M$2)*M554,0) -> 5474769 | O554: 2 | P554: =ROUND((H554+I554+J554+K554)/IF($M$2>26,26,$M$2)*O554,0) -> 456231 | Q554: 0 | R554: =IF(M554>0,ROUND(N554/IF(M554>26,26,M554)/8*Q554*30%,0),0) -> 0 | S554: =N554+P554+R554 -> 5931000 | T554: 0 | U554: 0 | V554: 200000 | W554: 500000 | X554: 0 | Y554: 400000 | Z554: 476646 | AC554: 0 | AD554: 0 | AE554: 42771.633 | AG554: =ROUND(SUM(S554:AF554)-AA554,0) -> 7550418 | AH554: 36 | AI554: 0 | AJ554: 0 | AK554: 0 | AL554: 0 | AM554: =ROUND((N554/IF(M554>26,26,M554)/8*(AH554*$AH$5+AI554*$AI$5+AJ554*$AJ$5+AK554*$AK$5+AL554*$AL$5)),0) -> 1539779 | AN554: =ROUND(AG554+AM554,0) -> 9090197 | AO554: 622755 | AP554: 44100 | AQ554: 0 | AR554: 0 | AS554: 0 | AT554: =+ROUND(SUM(AN554:AN554)-SUM(AO554:AS554),0) -> 8423342 | AW554: PHAN THI BICH | AX554: 050079012121 | AY554: SK1 Bag | AZ554: 622 | BA554: =+IF(AY554="SK1 Box","Box",IF(AY554="Seaman","Seaman","Bag")) -> Bag
A555: =SUBTOTAL(3,B$6:B555) -> 550 | B555: C7197 | C555: Thị Thu | D555: 43172 | E555: FACTORY D | F555: P4 - FB2-4 | G555: Normal worker | H555: 5931000 | I555: 0 | J555: 0 | K555: 0 | L555: =SUM(H555:K555) -> 5931000 | M555: 24 | N555: =ROUND((H555+I555+J555+K555)/IF($M$2>26,26,$M$2)*M555,0) -> 5474769 | O555: 2 | P555: =ROUND((H555+I555+J555+K555)/IF($M$2>26,26,$M$2)*O555,0) -> 456231 | Q555: 0 | R555: =IF(M555>0,ROUND(N555/IF(M555>26,26,M555)/8*Q555*30%,0),0) -> 0 | S555: =N555+P555+R555 -> 5931000 | T555: 0 | U555: 0 | V555: 200000 | W555: 500000 | X555: 0 | Y555: 400000 | Z555: 602971 | AC555: 0 | AD555: 0 | AE555: 42771.633 | AG555: =ROUND(SUM(S555:AF555)-AA555,0) -> 7676743 | AH555: 36 | AI555: 0 | AJ555: 0 | AK555: 0 | AL555: 0 | AM555: =ROUND((N555/IF(M555>26,26,M555)/8*(AH555*$AH$5+AI555*$AI$5+AJ555*$AJ$5+AK555*$AK$5+AL555*$AL$5)),0) -> 1539779 | AN555: =ROUND(AG555+AM555,0) -> 9216522 | AO555: 622755 | AP555: 44100 | AQ555: 0 | AR555: 0 | AS555: 0 | AT555: =+ROUND(SUM(AN555:AN555)-SUM(AO555:AS555),0) -> 8549667 | AW555: THI THU | AX555: 050087243076 | AY555: SK1 Bag | AZ555: 622 | BA555: =+IF(AY555="SK1 Box","Box",IF(AY555="Seaman","Seaman","Bag")) -> Bag
A556: =SUBTOTAL(3,B$6:B556) -> 551 | B556: C7288 | C556: Hồ Thị Bông | D556: 43210 | E556: FACTORY D | F556: P4 - FB2-4 | G556: Normal worker | H556: 5931000 | I556: 0 | J556: 0 | K556: 0 | L556: =SUM(H556:K556) -> 5931000 | M556: 22 | N556: =ROUND((H556+I556+J556+K556)/IF($M$2>26,26,$M$2)*M556,0) -> 5018538 | O556: 2 | P556: =ROUND((H556+I556+J556+K556)/IF($M$2>26,26,$M$2)*O556,0) -> 456231 | Q556: 0 | R556: =IF(M556>0,ROUND(N556/IF(M556>26,26,M556)/8*Q556*30%,0),0) -> 0 | S556: =N556+P556+R556 -> 5474769 | T556: 0 | U556: 0 | V556: 200000 | W556: 0 | X556: 0 | Y556: 300000 | Z556: 514337 | AC556: 0 | AD556: 0 | AE556: 42771.631 | AG556: =ROUND(SUM(S556:AF556)-AA556,0) -> 6531878 | AH556: 32 | AI556: 0 | AJ556: 0 | AK556: 0 | AL556: 0 | AM556: =ROUND((N556/IF(M556>26,26,M556)/8*(AH556*$AH$5+AI556*$AI$5+AJ556*$AJ$5+AK556*$AK$5+AL556*$AL$5)),0) -> 1368692 | AN556: =ROUND(AG556+AM556,0) -> 7900570 | AO556: 622755 | AP556: 44100 | AQ556: 0 | AR556: 0 | AS556: 0 | AT556: =+ROUND(SUM(AN556:AN556)-SUM(AO556:AS556),0) -> 7233715 | AW556: HO THI BONG | AX556: 050056785989 | AY556: SK1 Bag | AZ556: 622 | BA556: =+IF(AY556="SK1 Box","Box",IF(AY556="Seaman","Seaman","Bag")) -> Bag
A557: =SUBTOTAL(3,B$6:B557) -> 552 | B557: C7818 | C557: Nguyễn Ngọc Anh | D557: 43511 | E557: FACTORY D | F557: P4 - FB2-4 | G557: Normal worker | H557: 5931000 | I557: 0 | J557: 0 | K557: 0 | L557: =SUM(H557:K557) -> 5931000 | M557: 23 | N557: =ROUND((H557+I557+J557+K557)/IF($M$2>26,26,$M$2)*M557,0) -> 5246654 | O557: 3 | P557: =ROUND((H557+I557+J557+K557)/IF($M$2>26,26,$M$2)*O557,0) -> 684346 | Q557: 0 | R557: =IF(M557>0,ROUND(N557/IF(M557>26,26,M557)/8*Q557*30%,0),0) -> 0 | S557: =N557+P557+R557 -> 5931000 | T557: 0 | U557: 0 | V557: 200000 | W557: 500000 | X557: 0 | Y557: 400000 | Z557: 563540 | AC557: 100000 | AD557: 0 | AE557: 42771.636 | AG557: =ROUND(SUM(S557:AF557)-AA557,0) -> 7737312 | AH557: 36 | AI557: 0 | AJ557: 0 | AK557: 0 | AL557: 0 | AM557: =ROUND((N557/IF(M557>26,26,M557)/8*(AH557*$AH$5+AI557*$AI$5+AJ557*$AJ$5+AK557*$AK$5+AL557*$AL$5)),0) -> 1539779 | AN557: =ROUND(AG557+AM557,0) -> 9277091 | AO557: 622755 | AP557: 44100 | AQ557: 0 | AR557: 0 | AS557: 0 | AT557: =+ROUND(SUM(AN557:AN557)-SUM(AO557:AS557),0) -> 8610236 | AW557: NGUYEN NGOC ANH | AX557: 050103659067 | AY557: SK1 Bag | AZ557: 622 | BA557: =+IF(AY557="SK1 Box","Box",IF(AY557="Seaman","Seaman","Bag")) -> Bag
A558: =SUBTOTAL(3,B$6:B558) -> 553 | B558: C8002 | C558: Trần Thị Lan | D558: 43517 | E558: FACTORY D | F558: P4 - FB2-4 | G558: Drill worker | H558: 5931000 | I558: 200000 | J558: 0 | K558: 0 | L558: =SUM(H558:K558) -> 6131000 | M558: 23 | N558: =ROUND((H558+I558+J558+K558)/IF($M$2>26,26,$M$2)*M558,0) -> 5423577 | O558: 3 | P558: =ROUND((H558+I558+J558+K558)/IF($M$2>26,26,$M$2)*O558,0) -> 707423 | Q558: 0 | R558: =IF(M558>0,ROUND(N558/IF(M558>26,26,M558)/8*Q558*30%,0),0) -> 0 | S558: =N558+P558+R558 -> 6131000 | T558: 0 | U558: 0 | V558: 200000 | W558: 500000 | X558: 0 | Y558: 400000 | Z558: 453910 | AC558: 0 | AD558: 0 | AE558: 44213.943 | AG558: =ROUND(SUM(S558:AF558)-AA558,0) -> 7729124 | AH558: 36 | AI558: 0 | AJ558: 0 | AK558: 0 | AL558: 0 | AM558: =ROUND((N558/IF(M558>26,26,M558)/8*(AH558*$AH$5+AI558*$AI$5+AJ558*$AJ$5+AK558*$AK$5+AL558*$AL$5)),0) -> 1591702 | AN558: =ROUND(AG558+AM558,0) -> 9320826 | AO558: 643755 | AP558: 44100 | AQ558: 0 | AR558: 0 | AS558: 0 | AT558: =+ROUND(SUM(AN558:AN558)-SUM(AO558:AS558),0) -> 8632971 | AW558: TRAN THI LAN | AX558: 050103659075 | AY558: SK1 Bag | AZ558: 622 | BA558: =+IF(AY558="SK1 Box","Box",IF(AY558="Seaman","Seaman","Bag")) -> Bag
A559: =SUBTOTAL(3,B$6:B559) -> 554 | B559: C8063 | C559: Điểu Sơn | D559: 43522 | E559: FACTORY D | F559: P4 - FB2-4 | G559: Drill worker | H559: 5931000 | I559: 200000 | J559: 0 | K559: 0 | L559: =SUM(H559:K559) -> 6131000 | M559: 23.8 | N559: =ROUND((H559+I559+J559+K559)/IF($M$2>26,26,$M$2)*M559,0) -> 5612223 | O559: 2 | P559: =ROUND((H559+I559+J559+K559)/IF($M$2>26,26,$M$2)*O559,0) -> 471615 | Q559: 0 | R559: =IF(M559>0,ROUND(N559/IF(M559>26,26,M559)/8*Q559*30%,0),0) -> 0 | S559: =N559+P559+R559 -> 6083838 | T559: 0 | U559: 0 | V559: 200000 | W559: 500000 | X559: 0 | Y559: 400000 | Z559: 457058 | AC559: 100000 | AD559: 0 | AE559: 0 | AG559: =ROUND(SUM(S559:AF559)-AA559,0) -> 7740896 | AH559: 36 | AI559: 0 | AJ559: 0 | AK559: 0 | AL559: 0 | AM559: =ROUND((N559/IF(M559>26,26,M559)/8*(AH559*$AH$5+AI559*$AI$5+AJ559*$AJ$5+AK559*$AK$5+AL559*$AL$5)),0) -> 1591702 | AN559: =ROUND(AG559+AM559,0) -> 9332598 | AO559: 643755 | AP559: 44100 | AQ559: 0 | AR559: 0 | AS559: 0 | AT559: =+ROUND(SUM(AN559:AN559)-SUM(AO559:AS559),0) -> 8644743 | AW559: DIEU SON | AX559: 050106514388 | AY559: SK1 Bag | AZ559: 622 | BA559: =+IF(AY559="SK1 Box","Box",IF(AY559="Seaman","Seaman","Bag")) -> Bag
A560: =SUBTOTAL(3,B$6:B560) -> 555 | B560: C8064 | C560: Hồ Thị Nhạ | D560: 43522 | E560: FACTORY D | F560: P4 - FB2-4 | G560: Drill worker | H560: 5931000 | I560: 200000 | J560: 0 | K560: 0 | L560: =SUM(H560:K560) -> 6131000 | M560: 23.8 | N560: =ROUND((H560+I560+J560+K560)/IF($M$2>26,26,$M$2)*M560,0) -> 5612223 | O560: 2 | P560: =ROUND((H560+I560+J560+K560)/IF($M$2>26,26,$M$2)*O560,0) -> 471615 | Q560: 0 | R560: =IF(M560>0,ROUND(N560/IF(M560>26,26,M560)/8*Q560*30%,0),0) -> 0 | S560: =N560+P560+R560 -> 6083838 | T560: 0 | U560: 0 | V560: 200000 | W560: 500000 | X560: 0 | Y560: 400000 | Z560: 571506 | AC560: 0 | AD560: 0 | AE560: 44213.942 | AG560: =ROUND(SUM(S560:AF560)-AA560,0) -> 7799558 | AH560: 36 | AI560: 0 | AJ560: 0 | AK560: 0 | AL560: 0 | AM560: =ROUND((N560/IF(M560>26,26,M560)/8*(AH560*$AH$5+AI560*$AI$5+AJ560*$AJ$5+AK560*$AK$5+AL560*$AL$5)),0) -> 1591702 | AN560: =ROUND(AG560+AM560,0) -> 9391260 | AO560: 643755 | AP560: 44100 | AQ560: 0 | AR560: 0 | AS560: 0 | AT560: =+ROUND(SUM(AN560:AN560)-SUM(AO560:AS560),0) -> 8703405 | AW560: HO THI NHA | AX560: 050103659032 | AY560: SK1 Bag | AZ560: 622 | BA560: =+IF(AY560="SK1 Box","Box",IF(AY560="Seaman","Seaman","Bag")) -> Bag
A561: =SUBTOTAL(3,B$6:B561) -> 556 | B561: C8293 | C561: Phan Nhật Hoàng | D561: 43532 | E561: FACTORY D | F561: P4 - FB2-4 | G561: Normal worker | H561: 5931000 | I561: 0 | J561: 0 | K561: 0 | L561: =SUM(H561:K561) -> 5931000 | M561: 23 | N561: =ROUND((H561+I561+J561+K561)/IF($M$2>26,26,$M$2)*M561,0) -> 5246654 | O561: 3 | P561: =ROUND((H561+I561+J561+K561)/IF($M$2>26,26,$M$2)*O561,0) -> 684346 | Q561: 0 | R561: =IF(M561>0,ROUND(N561/IF(M561>26,26,M561)/8*Q561*30%,0),0) -> 0 | S561: =N561+P561+R561 -> 5931000 | T561: 0 | U561: 0 | V561: 200000 | W561: 500000 | X561: 0 | Y561: 400000 | Z561: 480130 | AC561: 0 | AD561: 0 | AE561: 0 | AG561: =ROUND(SUM(S561:AF561)-AA561,0) -> 7511130 | AH561: 36 | AI561: 0 | AJ561: 0 | AK561: 0 | AL561: 0 | AM561: =ROUND((N561/IF(M561>26,26,M561)/8*(AH561*$AH$5+AI561*$AI$5+AJ561*$AJ$5+AK561*$AK$5+AL561*$AL$5)),0) -> 1539779 | AN561: =ROUND(AG561+AM561,0) -> 9050909 | AO561: 622755 | AP561: 44100 | AQ561: 0 | AR561: 0 | AS561: 0 | AT561: =+ROUND(SUM(AN561:AN561)-SUM(AO561:AS561),0) -> 8384054 | AW561: PHAN NHAT HOANG | AX561: 050103659482 | AY561: SK1 Bag | AZ561: 622 | BA561: =+IF(AY561="SK1 Box","Box",IF(AY561="Seaman","Seaman","Bag")) -> Bag
A562: =SUBTOTAL(3,B$6:B562) -> 557 | B562: C10604 | C562: Lê Anh Vũ | D562: 43575 | E562: FACTORY D | F562: P4 - FB2-5 | G562: Normal worker | H562: 5931000 | I562: 0 | J562: 0 | K562: 0 | L562: =SUM(H562:K562) -> 5931000 | M562: 22 | N562: =ROUND((H562+I562+J562+K562)/IF($M$2>26,26,$M$2)*M562,0) -> 5018538 | O562: 3 | P562: =ROUND((H562+I562+J562+K562)/IF($M$2>26,26,$M$2)*O562,0) -> 684346 | Q562: 0 | R562: =IF(M562>0,ROUND(N562/IF(M562>26,26,M562)/8*Q562*30%,0),0) -> 0 | S562: =N562+P562+R562 -> 5702884 | T562: 0 | U562: 0 | V562: 200000 | W562: 0 | X562: 0 | Y562: 300000 | Z562: 553222 | AC562: 0 | AD562: 0 | AE562: 0 | AG562: =ROUND(SUM(S562:AF562)-AA562,0) -> 6756106 | AH562: 28 | AI562: 0 | AJ562: 0 | AK562: 0 | AL562: 0 | AM562: =ROUND((N562/IF(M562>26,26,M562)/8*(AH562*$AH$5+AI562*$AI$5+AJ562*$AJ$5+AK562*$AK$5+AL562*$AL$5)),0) -> 1197606 | AN562: =ROUND(AG562+AM562,0) -> 7953712 | AO562: 622755 | AP562: 44100 | AQ562: 0 | AR562: 0 | AS562: 0 | AT562: =+ROUND(SUM(AN562:AN562)-SUM(AO562:AS562),0) -> 7286857 | AW562: LE ANH VU | AX562: 050106621176 | AY562: SK1 Bag | AZ562: 622 | BA562: =+IF(AY562="SK1 Box","Box",IF(AY562="Seaman","Seaman","Bag")) -> Bag
A563: =SUBTOTAL(3,B$6:B563) -> 558 | B563: C13707 | C563: Nguyễn Thị Hoàng | D563: 44281 | E563: FACTORY D | F563: P4 - FB2-5 | G563: Normal worker | H563: 5931000 | I563: 0 | J563: 0 | K563: 0 | L563: =SUM(H563:K563) -> 5931000 | M563: 23.9 | N563: =ROUND((H563+I563+J563+K563)/IF($M$2>26,26,$M$2)*M563,0) -> 5451958 | O563: 2 | P563: =ROUND((H563+I563+J563+K563)/IF($M$2>26,26,$M$2)*O563,0) -> 456231 | Q563: 0 | R563: =IF(M563>0,ROUND(N563/IF(M563>26,26,M563)/8*Q563*30%,0),0) -> 0 | S563: =N563+P563+R563 -> 5908189 | T563: 0 | U563: 0 | V563: 200000 | W563: 500000 | X563: 0 | Y563: 400000 | Z563: 602158 | AC563: 0 | AD563: 0 | AE563: 42771.637 | AG563: =ROUND(SUM(S563:AF563)-AA563,0) -> 7653119 | AH563: 36 | AI563: 0 | AJ563: 0 | AK563: 0 | AL563: 0 | AM563: =ROUND((N563/IF(M563>26,26,M563)/8*(AH563*$AH$5+AI563*$AI$5+AJ563*$AJ$5+AK563*$AK$5+AL563*$AL$5)),0) -> 1539779 | AN563: =ROUND(AG563+AM563,0) -> 9192898 | AO563: 622755 | AP563: 44100 | AQ563: 0 | AR563: 0 | AS563: 0 | AT563: =+ROUND(SUM(AN563:AN563)-SUM(AO563:AS563),0) -> 8526043 | AW563: NGUYEN THI HOANG | AX563: 050127672560 | AY563: SK1 Bag | AZ563: 622 | BA563: =+IF(AY563="SK1 Box","Box",IF(AY563="Seaman","Seaman","Bag")) -> Bag
... A619: =SUBTOTAL(3,B$6:B619) -> 614 | B619: C16467 | C619: Phùng Huệ Như | D619: 45710 | E619: FACTORY D | F619: P4 - Inspection | G619: Inspection worker | H619: 5023000 | I619: 300000 | J619: 0 | K619: 0 | L619: =SUM(H619:K619) -> 5323000 | M619: 24 | N619: =ROUND((H619+I619+J619+K619)/IF($M$2>26,26,$M$2)*M619,0) -> 4913538 | O619: 2 | P619: =ROUND((H619+I619+J619+K619)/IF($M$2>26,26,$M$2)*O619,0) -> 409462 | Q619: 0 | R619: =IF(M619>0,ROUND(N619/IF(M619>26,26,M619)/8*Q619*30%,0),0) -> 0 | S619: =N619+P619+R619 -> 5323000 | T619: 0 | U619: 0 | V619: 200000 | W619: 500000 | X619: 0 | Y619: 400000 | Z619: 545844 | AC619: 0 | AD619: 0 | AE619: 38387.016 | AG619: =ROUND(SUM(S619:AF619)-AA619,0) -> 7007231 | AH619: 38 | AI619: 0 | AJ619: 0 | AK619: 0 | AL619: 0 | AM619: =ROUND((N619/IF(M619>26,26,M619)/8*(AH619*$AH$5+AI619*$AI$5+AJ619*$AJ$5+AK619*$AK$5+AL619*$AL$5)),0) -> 1458707 | AN619: =ROUND(AG619+AM619,0) -> 8465938 | AO619: 558915 | AP619: 44100 | AQ619: 0 | AR619: 0 | AS619: 0 | AT619: =+ROUND(SUM(AN619:AN619)-SUM(AO619:AS619),0) -> 7862923 | AW619: PHUNG HUE NHU | AX619: 050158476190 | AY619: SK1 Bag | AZ619: 622 | BA619: =+IF(AY619="SK1 Box","Box",IF(AY619="Seaman","Seaman","Bag")) -> Bag
A620: =SUBTOTAL(3,B$6:B620) -> 615 | B620: C16606 | C620: Nguyễn Ngọc Huyền | D620: 45762 | E620: FACTORY D | F620: P4 - Inspection | G620: New worker | H620: 4694000 | I620: 0 | J620: 0 | K620: 0 | L620: =SUM(H620:K620) -> 4694000 | M620: 13 | N620: =ROUND((H620+I620+J620+K620)/IF($M$2>26,26,$M$2)*M620,0) -> 2347000 | O620: 1 | P620: =ROUND((H620+I620+J620+K620)/IF($M$2>26,26,$M$2)*O620,0) -> 180538 | Q620: 0 | R620: =IF(M620>0,ROUND(N620/IF(M620>26,26,M620)/8*Q620*30%,0),0) -> 0 | S620: =N620+P620+R620 -> 2527538 | T620: 0 | U620: 0 | V620: 108000 | W620: 269000 | X620: 0 | Y620: 81000 | Z620: 354797 | AC620: 0 | AD620: 0 | AE620: 33850.962 | AG620: =ROUND(SUM(S620:AF620)-AA620,0) -> 3374186 | AH620: 12 | AI620: 0 | AJ620: 0 | AK620: 0 | AL620: 0 | AM620: =ROUND((N620/IF(M620>26,26,M620)/8*(AH620*$AH$5+AI620*$AI$5+AJ620*$AJ$5+AK620*$AK$5+AL620*$AL$5)),0) -> 406212 | AN620: =ROUND(AG620+AM620,0) -> 3780398 | AO620: 0 | AP620: 0 | AQ620: 0 | AR620: 0 | AS620: 0 | AT620: =+ROUND(SUM(AN620:AN620)-SUM(AO620:AS620),0) -> 3780398 | AX620: TM | AY620: SK1 Bag | AZ620: 622 | BA620: =+IF(AY620="SK1 Box","Box",IF(AY620="Seaman","Seaman","Bag")) -> Bag
A621: =SUBTOTAL(3,B$6:B621) -> 616 | B621: C3716 | C621: Bùi Thị Ngọc Yến | D621: 40672 | E621: FACTORY D | F621: P4 - Inspection | G621: Bag Inspection leader | H621: 5931000 | I621: 2600000 | J621: 0 | K621: 500000 | L621: =SUM(H621:K621) -> 9031000 | M621: 24 | N621: =ROUND((H621+I621+J621+K621)/IF($M$2>26,26,$M$2)*M621,0) -> 8336308 | O621: 2 | P621: =ROUND((H621+I621+J621+K621)/IF($M$2>26,26,$M$2)*O621,0) -> 694692 | Q621: 0 | R621: =IF(M621>0,ROUND(N621/IF(M621>26,26,M621)/8*Q621*30%,0),0) -> 0 | S621: =N621+P621+R621 -> 9031000 | T621: 0 | U621: 0 | V621: 200000 | W621: 500000 | X621: 0 | Y621: 400000 | Z621: 546757 | AC621: 0 | AD621: 0 | AE621: 65127.406 | AG621: =ROUND(SUM(S621:AF621)-AA621,0) -> 10742884 | AH621: 38 | AI621: 0 | AJ621: 0 | AK621: 0 | AL621: 0 | AM621: =ROUND((N621/IF(M621>26,26,M621)/8*(AH621*$AH$5+AI621*$AI$5+AJ621*$AJ$5+AK621*$AK$5+AL621*$AL$5)),0) -> 2474841 | AN621: =ROUND(AG621+AM621,0) -> 13217725 | AO621: 948255 | AP621: 44100 | AQ621: 0 | AR621: 0 | AS621: 0 | AT621: =+ROUND(SUM(AN621:AN621)-SUM(AO621:AS621),0) -> 12225370 | AW621: BUI THI NGOC YEN | AX621: 050040850969 | AY621: SK1 Bag | AZ621: 622 | BA621: =+IF(AY621="SK1 Box","Box",IF(AY621="Seaman","Seaman","Bag")) -> Bag
A622: =SUBTOTAL(3,B$6:B622) -> 617 | B622: C6605 | C622: Trương Thị Cư | D622: 42621 | E622: FACTORY D | F622: P4 - Inspection | G622: Inspection worker | H622: 5931000 | I622: 700000 | J622: 0 | K622: 0 | L622: =SUM(H622:K622) -> 6631000 | M622: 24 | N622: =ROUND((H622+I622+J622+K622)/IF($M$2>26,26,$M$2)*M622,0) -> 6120923 | O622: 2 | P622: =ROUND((H622+I622+J622+K622)/IF($M$2>26,26,$M$2)*O622,0) -> 510077 | Q622: 0 | R622: =IF(M622>0,ROUND(N622/IF(M622>26,26,M622)/8*Q622*30%,0),0) -> 0 | S622: =N622+P622+R622 -> 6631000 | T622: 0 | U622: 0 | V622: 200000 | W622: 500000 | X622: 0 | Y622: 400000 | Z622: 564550 | AC622: 0 | AD622: 0 | AE622: 47819.711 | AG622: =ROUND(SUM(S622:AF622)-AA622,0) -> 8343370 | AH622: 23 | AI622: 0 | AJ622: 0 | AK622: 0 | AL622: 0 | AM622: =ROUND((N622/IF(M622>26,26,M622)/8*(AH622*$AH$5+AI622*$AI$5+AJ622*$AJ$5+AK622*$AK$5+AL622*$AL$5)),0) -> 1099853 | AN622: =ROUND(AG622+AM622,0) -> 9443223 | AO622: 696255 | AP622: 44100 | AQ622: 0 | AR622: 0 | AS622: 0 | AT622: =+ROUND(SUM(AN622:AN622)-SUM(AO622:AS622),0) -> 8702868 | AW622: TRUONG THI CU | AX622: 050067513158 | AY622: SK1 Bag | AZ622: 622 | BA622: =+IF(AY622="SK1 Box","Box",IF(AY622="Seaman","Seaman","Bag")) -> Bag
A623: =SUBTOTAL(3,B$6:B623) -> 618 | B623: C7264 | C623: Nguyễn Thị Xuân | D623: 43200 | E623: FACTORY D | F623: P4 - Inspection | G623: Inspection worker | H623: 5931000 | I623: 700000 | J623: 0 | K623: 0 | L623: =SUM(H623:K623) -> 6631000 | M623: 24 | N623: =ROUND((H623+I623+J623+K623)/IF($M$2>26,26,$M$2)*M623,0) -> 6120923 | O623: 2 | P623: =ROUND((H623+I623+J623+K623)/IF($M$2>26,26,$M$2)*O623,0) -> 510077 | Q623: 0 | R623: =IF(M623>0,ROUND(N623/IF(M623>26,26,M623)/8*Q623*30%,0),0) -> 0 | S623: =N623+P623+R623 -> 6631000 | T623: 0 | U623: 0 | V623: 200000 | W623: 500000 | X623: 0 | Y623: 400000 | Z623: 445046 | AC623: 0 | AD623: 0 | AE623: 47819.711 | AG623: =ROUND(SUM(S623:AF623)-AA623,0) -> 8223866 | AH623: 23 | AI623: 0 | AJ623: 0 | AK623: 0 | AL623: 0 | AM623: =ROUND((N623/IF(M623>26,26,M623)/8*(AH623*$AH$5+AI623*$AI$5+AJ623*$AJ$5+AK623*$AK$5+AL623*$AL$5)),0) -> 1099853 | AN623: =ROUND(AG623+AM623,0) -> 9323719 | AO623: 696255 | AP623: 44100 | AQ623: 0 | AR623: 0 | AS623: 0 | AT623: =+ROUND(SUM(AN623:AN623)-SUM(AO623:AS623),0) -> 8583364 | AW623: NGUYEN THI XUAN | AX623: 050088957137 | AY623: SK1 Bag | AZ623: 622 | BA623: =+IF(AY623="SK1 Box","Box",IF(AY623="Seaman","Seaman","Bag")) -> Bag
A624: =SUBTOTAL(3,B$6:B624) -> 619 | B624: C8000 | C624: Nguyễn Thị Ngọc Hồng Thắm | D624: 43517 | E624: FACTORY D | F624: P4 - Inspection | G624: Inspection worker | H624: 5931000 | I624: 700000 | J624: 0 | K624: 0 | L624: =SUM(H624:K624) -> 6631000 | M624: 22.8 | N624: =ROUND((H624+I624+J624+K624)/IF($M$2>26,26,$M$2)*M624,0) -> 5814877 | O624: 3 | P624: =ROUND((H624+I624+J624+K624)/IF($M$2>26,26,$M$2)*O624,0) -> 765115 | Q624: 0 | R624: =IF(M624>0,ROUND(N624/IF(M624>26,26,M624)/8*Q624*30%,0),0) -> 0 | S624: =N624+P624+R624 -> 6579992 | T624: 0 | U624: 0 | V624: 200000 | W624: 500000 | X624: 0 | Y624: 400000 | Z624: 819745 | AC624: 200000 | AD624: 0 | AE624: 47819.712 | AG624: =ROUND(SUM(S624:AF624)-AA624,0) -> 8747557 | AH624: 38 | AI624: 0 | AJ624: 0 | AK624: 0 | AL624: 0 | AM624: =ROUND((N624/IF(M624>26,26,M624)/8*(AH624*$AH$5+AI624*$AI$5+AJ624*$AJ$5+AK624*$AK$5+AL624*$AL$5)),0) -> 1817149 | AN624: =ROUND(AG624+AM624,0) -> 10564706 | AO624: 696255 | AP624: 44100 | AQ624: 0 | AR624: 0 | AS624: 0 | AT624: =+ROUND(SUM(AN624:AN624)-SUM(AO624:AS624),0) -> 9824351 | AW624: NGUYEN THI NGOC HONG THAM | AX624: 050095313199 | AY624: SK1 Bag | AZ624: 622 | BA624: =+IF(AY624="SK1 Box","Box",IF(AY624="Seaman","Seaman","Bag")) -> Bag
A625: =SUBTOTAL(3,B$6:B625) -> 620 | B625: C8468 | C625: Võ Thị Kim Chi | D625: 43543 | E625: FACTORY D | F625: P4 - Inspection | G625: Inspection worker | H625: 5931000 | I625: 700000 | J625: 0 | K625: 0 | L625: =SUM(H625:K625) -> 6631000 | M625: 24 | N625: =ROUND((H625+I625+J625+K625)/IF($M$2>26,26,$M$2)*M625,0) -> 6120923 | O625: 2 | P625: =ROUND((H625+I625+J625+K625)/IF($M$2>26,26,$M$2)*O625,0) -> 510077 | Q625: 0 | R625: =IF(M625>0,ROUND(N625/IF(M625>26,26,M625)/8*Q625*30%,0),0) -> 0 | S625: =N625+P625+R625 -> 6631000 | T625: 0 | U625: 0 | V625: 200000 | W625: 500000 | X625: 0 | Y625: 400000 | Z625: 681546 | AC625: 0 | AD625: 0 | AE625: 47819.711 | AG625: =ROUND(SUM(S625:AF625)-AA625,0) -> 8460366 | AH625: 38 | AI625: 0 | AJ625: 0 | AK625: 0 | AL625: 0 | AM625: =ROUND((N625/IF(M625>26,26,M625)/8*(AH625*$AH$5+AI625*$AI$5+AJ625*$AJ$5+AK625*$AK$5+AL625*$AL$5)),0) -> 1817149 | AN625: =ROUND(AG625+AM625,0) -> 10277515 | AO625: 696255 | AP625: 44100 | AQ625: 0 | AR625: 0 | AS625: 0 | AT625: =+ROUND(SUM(AN625:AN625)-SUM(AO625:AS625),0) -> 9537160 | AW625: VO THI KIM CHI | AX625: 050103659393 | AY625: SK1 Bag | AZ625: 622 | BA625: =+IF(AY625="SK1 Box","Box",IF(AY625="Seaman","Seaman","Bag")) -> Bag
A626: =SUBTOTAL(3,B$6:B626) -> 621 | B626: C15744 | C626: Lê Văn Tấn | D626: 45367 | E626: FACTORY D | F626: P4 - Packing Bag | G626: Packing worker | H626: 5538000 | I626: 200000 | J626: 0 | K626: 0 | L626: =SUM(H626:K626) -> 5738000 | M626: 22.5 | N626: =ROUND((H626+I626+J626+K626)/IF($M$2>26,26,$M$2)*M626,0) -> 4965577 | O626: 3 | P626: =ROUND((H626+I626+J626+K626)/IF($M$2>26,26,$M$2)*O626,0) -> 662077 | Q626: 0 | R626: =IF(M626>0,ROUND(N626/IF(M626>26,26,M626)/8*Q626*30%,0),0) -> 0 | S626: =N626+P626+R626 -> 5627654 | T626: 0 | U626: 0 | V626: 200000 | W626: 500000 | X626: 0 | Y626: 400000 | Z626: 552371 | AC626: 0 | AD626: 0 | AE626: 0 | AG626: =ROUND(SUM(S626:AF626)-AA626,0) -> 7280025 | AH626: 34 | AI626: 0 | AJ626: 0 | AK626: 0 | AL626: 0 | AM626: =ROUND((N626/IF(M626>26,26,M626)/8*(AH626*$AH$5+AI626*$AI$5+AJ626*$AJ$5+AK626*$AK$5+AL626*$AL$5)),0) -> 1406913 | AN626: =ROUND(AG626+AM626,0) -> 8686938 | AO626: 602490 | AP626: 44100 | AQ626: 0 | AR626: 0 | AS626: 0 | AT626: =+ROUND(SUM(AN626:AN626)-SUM(AO626:AS626),0) -> 8040348 | AW626: LE VAN TAN | AX626: 050089661835 | AY626: SK1 Bag | AZ626: 622 | BA626: =+IF(AY626="SK1 Box","Box",IF(AY626="Seaman","Seaman","Bag")) -> Bag
A627: =SUBTOTAL(3,B$6:B627) -> 622 | B627: C3163 | C627: Dư Quốc An | D627: 40420 | E627: FACTORY D | F627: P4 - Packing Bag | G627: Bag Packing leader | H627: 5931000 | I627: 2300000 | J627: 0 | K627: 500000 | L627: =SUM(H627:K627) -> 8731000 | M627: 23.8 | N627: =ROUND((H627+I627+J627+K627)/IF($M$2>26,26,$M$2)*M627,0) -> 7992223 | O627: 2 | P627: =ROUND((H627+I627+J627+K627)/IF($M$2>26,26,$M$2)*O627,0) -> 671615 | Q627: 0 | R627: =IF(M627>0,ROUND(N627/IF(M627>26,26,M627)/8*Q627*30%,0),0) -> 0 | S627: =N627+P627+R627 -> 8663838 | T627: 0 | U627: 0 | V627: 200000 | W627: 500000 | X627: 0 | Y627: 400000 | Z627: 542201 | AC627: 0 | AD627: 0 | AE627: 0 | AG627: =ROUND(SUM(S627:AF627)-AA627,0) -> 10306039 | AH627: 28 | AI627: 0 | AJ627: 0 | AK627: 0 | AL627: 0 | AM627: =ROUND((N627/IF(M627>26,26,M627)/8*(AH627*$AH$5+AI627*$AI$5+AJ627*$AJ$5+AK627*$AK$5+AL627*$AL$5)),0) -> 1762990 | AN627: =ROUND(AG627+AM627,0) -> 12069029 | AO627: 916755 | AP627: 44100 | AQ627: 0 | AR627: 0 | AS627: 0 | AT627: =+ROUND(SUM(AN627:AN627)-SUM(AO627:AS627),0) -> 11108174 | AW627: DU QUOC AN | AX627: 050040849553 | AY627: SK1 Bag | AZ627: 622 | BA627: =+IF(AY627="SK1 Box","Box",IF(AY627="Seaman","Seaman","Bag")) -> Bag
A628: =SUBTOTAL(3,B$6:B628) -> 623 | B628: C7168 | C628: Điểu Dẹn | D628: 43167 | E628: FACTORY D | F628: P4 - Packing Bag | G628: Packing worker | H628: 5931000 | I628: 600000 | J628: 0 | K628: 0 | L628: =SUM(H628:K628) -> 6531000 | M628: 23 | N628: =ROUND((H628+I628+J628+K628)/IF($M$2>26,26,$M$2)*M628,0) -> 5777423 | O628: 3 | P628: =ROUND((H628+I628+J628+K628)/IF($M$2>26,26,$M$2)*O628,0) -> 753577 | Q628: 0 | R628: =IF(M628>0,ROUND(N628/IF(M628>26,26,M628)/8*Q628*30%,0),0) -> 0 | S628: =N628+P628+R628 -> 6531000 | T628: 0 | U628: 0 | V628: 200000 | W628: 500000 | X628: 0 | Y628: 400000 | Z628: 653148 | AC628: 0 | AD628: 0 | AE628: 0 | AG628: =ROUND(SUM(S628:AF628)-AA628,0) -> 8284148 | AH628: 34 | AI628: 0 | AJ628: 0 | AK628: 0 | AL628: 0 | AM628: =ROUND((N628/IF(M628>26,26,M628)/8*(AH628*$AH$5+AI628*$AI$5+AJ628*$AJ$5+AK628*$AK$5+AL628*$AL$5)),0) -> 1601351 | AN628: =ROUND(AG628+AM628,0) -> 9885499 | AO628: 685755 | AP628: 44100 | AQ628: 0 | AR628: 0 | AS628: 0 | AT628: =+ROUND(SUM(AN628:AN628)-SUM(AO628:AS628),0) -> 9155644 | AW628: DIEU DEN | AX628: 050087243122 | AY628: SK1 Bag | AZ628: 622 | BA628: =+IF(AY628="SK1 Box","Box",IF(AY628="Seaman","Seaman","Bag")) -> Bag
A629: =SUBTOTAL(3,B$6:B629) -> 624 | B629: C7211 | C629: Hồ Thanh Tấn | D629: 43173 | E629: FACTORY D | F629: P4 - Packing Bag | G629: Packing worker | H629: 5931000 | I629: 600000 | J629: 0 | K629: 0 | L629: =SUM(H629:K629) -> 6531000 | M629: 24 | N629: =ROUND((H629+I629+J629+K629)/IF($M$2>26,26,$M$2)*M629,0) -> 6028615 | O629: 2 | P629: =ROUND((H629+I629+J629+K629)/IF($M$2>26,26,$M$2)*O629,0) -> 502385 | Q629: 0 | R629: =IF(M629>0,ROUND(N629/IF(M629>26,26,M629)/8*Q629*30%,0),0) -> 0 | S629: =N629+P629+R629 -> 6531000 | T629: 0 | U629: 0 | V629: 200000 | W629: 500000 | X629: 0 | Y629: 400000 | Z629: 468899 | AC629: 100000 | AD629: 0 | AE629: 0 | AG629: =ROUND(SUM(S629:AF629)-AA629,0) -> 8199899 | AH629: 21 | AI629: 0 | AJ629: 0 | AK629: 0 | AL629: 0 | AM629: =ROUND((N629/IF(M629>26,26,M629)/8*(AH629*$AH$5+AI629*$AI$5+AJ629*$AJ$5+AK629*$AK$5+AL629*$AL$5)),0) -> 989070 | AN629: =ROUND(AG629+AM629,0) -> 9188969 | AO629: 685755 | AP629: 44100 | AQ629: 0 | AR629: 0 | AS629: 0 | AT629: =+ROUND(SUM(AN629:AN629)-SUM(AO629:AS629),0) -> 8459114 | AW629: HO THANH TAN | AX629: 050087243068 | AY629: SK1 Bag | AZ629: 622 | BA629: =+IF(AY629="SK1 Box","Box",IF(AY629="Seaman","Seaman","Bag")) -> Bag
A630: =SUBTOTAL(3,B$6:B630) -> 625 | B630: C7212 | C630: Điểu My | D630: 43173 | E630: FACTORY D | F630: P4 - Packing Bag | G630: Packing worker | H630: 5931000 | I630: 600000 | J630: 0 | K630: 0 | L630: =SUM(H630:K630) -> 6531000 | M630: 22.8 | N630: =ROUND((H630+I630+J630+K630)/IF($M$2>26,26,$M$2)*M630,0) -> 5727185 | O630: 3 | P630: =ROUND((H630+I630+J630+K630)/IF($M$2>26,26,$M$2)*O630,0) -> 753577 | Q630: 0 | R630: =IF(M630>0,ROUND(N630/IF(M630>26,26,M630)/8*Q630*30%,0),0) -> 0 | S630: =N630+P630+R630 -> 6480762 | T630: 0 | U630: 0 | V630: 200000 | W630: 500000 | X630: 0 | Y630: 400000 | Z630: 410802 | AC630: 100000 | AD630: 0 | AE630: 0 | AG630: =ROUND(SUM(S630:AF630)-AA630,0) -> 8091564 | AH630: 25 | AI630: 0 | AJ630: 0 | AK630: 0 | AL630: 0 | AM630: =ROUND((N630/IF(M630>26,26,M630)/8*(AH630*$AH$5+AI630*$AI$5+AJ630*$AJ$5+AK630*$AK$5+AL630*$AL$5)),0) -> 1177464 | AN630: =ROUND(AG630+AM630,0) -> 9269028 | AO630: 685755 | AP630: 44100 | AQ630: 0 | AR630: 0 | AS630: 0 | AT630: =+ROUND(SUM(AN630:AN630)-SUM(AO630:AS630),0) -> 8539173 | AW630: DIEU MY | AX630: 050087500461 | AY630: SK1 Bag | AZ630: 622 | BA630: =+IF(AY630="SK1 Box","Box",IF(AY630="Seaman","Seaman","Bag")) -> Bag
A631: =SUBTOTAL(3,B$6:B631) -> 626 | B631: C7335 | C631: Điểu Út Bê | D631: 43262 | E631: FACTORY D | F631: P4 - Packing Bag | G631: Packing worker | H631: 5931000 | I631: 600000 | J631: 0 | K631: 0 | L631: =SUM(H631:K631) -> 6531000 | M631: 19.6 | N631: =ROUND((H631+I631+J631+K631)/IF($M$2>26,26,$M$2)*M631,0) -> 4923369 | O631: 2 | P631: =ROUND((H631+I631+J631+K631)/IF($M$2>26,26,$M$2)*O631,0) -> 502385 | Q631: 0 | R631: =IF(M631>0,ROUND(N631/IF(M631>26,26,M631)/8*Q631*30%,0),0) -> 0 | S631: =N631+P631+R631 -> 5425754 | T631: 0 | U631: 0 | V631: 200000 | W631: 0 | X631: 0 | Y631: 0 | Z631: 704693 | AC631: 0 | AD631: 0 | AE631: 0 | AG631: =ROUND(SUM(S631:AF631)-AA631,0) -> 6330447 | AH631: 25 | AI631: 0 | AJ631: 0 | AK631: 0 | AL631: 0 | AM631: =ROUND((N631/IF(M631>26,26,M631)/8*(AH631*$AH$5+AI631*$AI$5+AJ631*$AJ$5+AK631*$AK$5+AL631*$AL$5)),0) -> 1177464 | AN631: =ROUND(AG631+AM631,0) -> 7507911 | AO631: 685755 | AP631: 44100 | AQ631: 0 | AR631: 0 | AS631: 0 | AT631: =+ROUND(SUM(AN631:AN631)-SUM(AO631:AS631),0) -> 6778056 | AW631: DIEU UT BE | AX631: 050091855841 | AY631: SK1 Bag | AZ631: 622 | BA631: =+IF(AY631="SK1 Box","Box",IF(AY631="Seaman","Seaman","Bag")) -> Bag
A632: =SUBTOTAL(3,B$6:B632) -> 627 | B632: C7528 | C632: Huỳnh Tiểu Bảo | D632: 43398 | E632: FACTORY D | F632: P4 - Packing Bag | G632: Bag Packing vice leader | H632: 5931000 | I632: 1400000 | J632: 0 | K632: 500000 | L632: =SUM(H632:K632) -> 7831000 | M632: 22.6 | N632: =ROUND((H632+I632+J632+K632)/IF($M$2>26,26,$M$2)*M632,0) -> 6806946 | O632: 3 | P632: =ROUND((H632+I632+J632+K632)/IF($M$2>26,26,$M$2)*O632,0) -> 903577 | Q632: 0 | R632: =IF(M632>0,ROUND(N632/IF(M632>26,26,M632)/8*Q632*30%,0),0) -> 0 | S632: =N632+P632+R632 -> 7710523 | T632: 0 | U632: 0 | V632: 200000 | W632: 500000 | X632: 0 | Y632: 400000 | Z632: 514863 | AC632: 0 | AD632: 0 | AE632: 0 | AG632: =ROUND(SUM(S632:AF632)-AA632,0) -> 9325386 | AH632: 25 | AI632: 0 | AJ632: 0 | AK632: 0 | AL632: 0 | AM632: =ROUND((N632/IF(M632>26,26,M632)/8*(AH632*$AH$5+AI632*$AI$5+AJ632*$AJ$5+AK632*$AK$5+AL632*$AL$5)),0) -> 1411839 | AN632: =ROUND(AG632+AM632,0) -> 10737225 | AO632: 822255 | AP632: 44100 | AQ632: 0 | AR632: 0 | AS632: 0 | AT632: =+ROUND(SUM(AN632:AN632)-SUM(AO632:AS632),0) -> 9870870 | AW632: HUYNH TIEU BAO | AX632: 050098252085 | AY632: SK1 Bag | AZ632: 622 | BA632: =+IF(AY632="SK1 Box","Box",IF(AY632="Seaman","Seaman","Bag")) -> Bag
... A638: =SUBTOTAL(3,B$6:B638) -> 633 | B638: C5817 | C638: Lý Thị Kim Chi | D638: 41478 | E638: FACTORY D | F638: P4 - Production Office | G638: Factory vice manager | H638: 9319000 | I638: 7300000 | J638: 0 | K638: 1500000 | L638: =SUM(H638:K638) -> 18119000 | M638: 23.9 | N638: =ROUND((H638+I638+J638+K638)/IF($M$2>26,26,$M$2)*M638,0) -> 16655542 | O638: 2 | P638: =ROUND((H638+I638+J638+K638)/IF($M$2>26,26,$M$2)*O638,0) -> 1393769 | Q638: 0 | R638: =IF(M638>0,ROUND(N638/IF(M638>26,26,M638)/8*Q638*30%,0),0) -> 0 | S638: =N638+P638+R638 -> 18049311 | T638: 0 | U638: 0 | V638: 200000 | W638: 500000 | X638: 0 | Y638: 400000 | Z638: 0 | AC638: 100000 | AD638: 0 | AE638: 130665.86 | AG638: =ROUND(SUM(S638:AF638)-AA638,0) -> 19379977 | AH638: 23 | AI638: 0 | AJ638: 0 | AK638: 0 | AL638: 0 | AM638: =ROUND((N638/IF(M638>26,26,M638)/8*(AH638*$AH$5+AI638*$AI$5+AJ638*$AJ$5+AK638*$AK$5+AL638*$AL$5)),0) -> 3005315 | AN638: =ROUND(AG638+AM638,0) -> 22385292 | AO638: 1902495 | AP638: 44100 | AQ638: 0 | AR638: 70000 | AS638: 0 | AT638: =+ROUND(SUM(AN638:AN638)-SUM(AO638:AS638),0) -> 20368697 | AW638: LY THI KIM CHI | AX638: 050040860972 | AY638: SK1 Bag | AZ638: 627 | BA638: =+IF(AY638="SK1 Box","Box",IF(AY638="Seaman","Seaman","Bag")) -> Bag
A639: =SUBTOTAL(3,B$6:B639) -> 634 | B639: C6068 | C639: Trần Thị Cẩm Linh | D639: 41678 | E639: FACTORY D | F639: P4 - Production Office | G639: Factory manager | H639: 17900000 | I639: 11000000 | J639: 0 | K639: 0 | L639: =SUM(H639:K639) -> 28900000 | M639: 22.6 | N639: =ROUND((H639+I639+J639+K639)/IF($M$2>26,26,$M$2)*M639,0) -> 25120769 | O639: 2 | P639: =ROUND((H639+I639+J639+K639)/IF($M$2>26,26,$M$2)*O639,0) -> 2223077 | Q639: 0 | R639: =IF(M639>0,ROUND(N639/IF(M639>26,26,M639)/8*Q639*30%,0),0) -> 0 | S639: =N639+P639+R639 -> 27343846 | T639: 662308 | U639: 0 | V639: 0 | W639: 0 | X639: 0 | Y639: 0 | Z639: 0 | AC639: 0 | AD639: 0 | AE639: 208413.46 | AG639: =ROUND(SUM(S639:AF639)-AA639,0) -> 28214567 | AH639: 0 | AI639: 0 | AJ639: 0 | AK639: 0 | AL639: 0 | AM639: =ROUND((N639/IF(M639>26,26,M639)/8*(AH639*$AH$5+AI639*$AI$5+AJ639*$AJ$5+AK639*$AK$5+AL639*$AL$5)),0) -> 0 | AN639: =ROUND(AG639+AM639,0) -> 28214567 | AO639: 3034500 | AP639: 44100 | AQ639: 240888 | AR639: 0 | AS639: 0 | AT639: =+ROUND(SUM(AN639:AN639)-SUM(AO639:AS639),0) -> 24895079 | AW639: TRAN THI CAM LINH | AX639: 050040871311 | AY639: SK1 Bag | AZ639: 627 | BA639: Manager
A640: =SUBTOTAL(3,B$6:B640) -> 635 | B640: C6348 | C640: Võ Ngọc Minh | D640: 42173 | E640: FACTORY D | F640: P4 - Production Office | G640: Factory assistant | H640: 7019000 | I640: 2500000 | J640: 0 | K640: 0 | L640: =SUM(H640:K640) -> 9519000 | M640: 24 | N640: =ROUND((H640+I640+J640+K640)/IF($M$2>26,26,$M$2)*M640,0) -> 8786769 | O640: 2 | P640: =ROUND((H640+I640+J640+K640)/IF($M$2>26,26,$M$2)*O640,0) -> 732231 | Q640: 0 | R640: =IF(M640>0,ROUND(N640/IF(M640>26,26,M640)/8*Q640*30%,0),0) -> 0 | S640: =N640+P640+R640 -> 9519000 | T640: 0 | U640: 0 | V640: 200000 | W640: 500000 | X640: 0 | Y640: 400000 | Z640: 546757 | AC640: 0 | AD640: 0 | AE640: 68646.633 | AG640: =ROUND(SUM(S640:AF640)-AA640,0) -> 11234404 | AH640: 17 | AI640: 0 | AJ640: 0 | AK640: 0 | AL640: 0 | AM640: =ROUND((N640/IF(M640>26,26,M640)/8*(AH640*$AH$5+AI640*$AI$5+AJ640*$AJ$5+AK640*$AK$5+AL640*$AL$5)),0) -> 1166993 | AN640: =ROUND(AG640+AM640,0) -> 12401397 | AO640: 999495 | AP640: 44100 | AQ640: 0 | AR640: 0 | AS640: 0 | AT640: =+ROUND(SUM(AN640:AN640)-SUM(AO640:AS640),0) -> 11357802 | AW640: VO NGOC MINH | AX640: 050056441473 | AY640: SK1 Bag | AZ640: 627 | BA640: =+IF(AY640="SK1 Box","Box",IF(AY640="Seaman","Seaman","Bag")) -> Bag
A641: =SUBTOTAL(3,B$6:B641) -> 636 | B641: C13576 | C641: Đoàn Thị Thúy Vy | D641: 44272 | E641: FACTORY D | F641: P4 - QC | G641: QC worker | H641: 5931000 | I641: 1100000 | J641: 0 | K641: 0 | L641: =SUM(H641:K641) -> 7031000 | M641: 23.8 | N641: =ROUND((H641+I641+J641+K641)/IF($M$2>26,26,$M$2)*M641,0) -> 6436069 | O641: 2 | P641: =ROUND((H641+I641+J641+K641)/IF($M$2>26,26,$M$2)*O641,0) -> 540846 | Q641: 0 | R641: =IF(M641>0,ROUND(N641/IF(M641>26,26,M641)/8*Q641*30%,0),0) -> 0 | S641: =N641+P641+R641 -> 6976915 | T641: 0 | U641: 0 | V641: 200000 | W641: 500000 | X641: 0 | Y641: 400000 | Z641: 396700 | AC641: 0 | AD641: 0 | AE641: 50704.325 | AG641: =ROUND(SUM(S641:AF641)-AA641,0) -> 8524319 | AH641: 37 | AI641: 0 | AJ641: 0 | AK641: 0 | AL641: 0 | AM641: =ROUND((N641/IF(M641>26,26,M641)/8*(AH641*$AH$5+AI641*$AI$5+AJ641*$AJ$5+AK641*$AK$5+AL641*$AL$5)),0) -> 1876060 | AN641: =ROUND(AG641+AM641,0) -> 10400379 | AO641: 738255 | AP641: 44100 | AQ641: 0 | AR641: 0 | AS641: 0 | AT641: =+ROUND(SUM(AN641:AN641)-SUM(AO641:AS641),0) -> 9618024 | AW641: DOAN THI THUY VY | AX641: 050121836049 | AY641: SK1 Bag | AZ641: 622 | BA641: =+IF(AY641="SK1 Box","Box",IF(AY641="Seaman","Seaman","Bag")) -> Bag
A642: =SUBTOTAL(3,B$6:B642) -> 637 | B642: C14152 | C642: Hà Thị Mộng Bình | D642: 44329 | E642: FACTORY D | F642: P4 - QC | G642: QC worker | H642: 5931000 | I642: 1100000 | J642: 0 | K642: 0 | L642: =SUM(H642:K642) -> 7031000 | M642: 23.6 | N642: =ROUND((H642+I642+J642+K642)/IF($M$2>26,26,$M$2)*M642,0) -> 6381985 | O642: 2 | P642: =ROUND((H642+I642+J642+K642)/IF($M$2>26,26,$M$2)*O642,0) -> 540846 | Q642: 0 | R642: =IF(M642>0,ROUND(N642/IF(M642>26,26,M642)/8*Q642*30%,0),0) -> 0 | S642: =N642+P642+R642 -> 6922831 | T642: 0 | U642: 0 | V642: 200000 | W642: 500000 | X642: 0 | Y642: 400000 | Z642: 393300 | AC642: 200000 | AD642: 0 | AE642: 50704.33 | AG642: =ROUND(SUM(S642:AF642)-AA642,0) -> 8666835 | AH642: 37 | AI642: 0 | AJ642: 0 | AK642: 0 | AL642: 0 | AM642: =ROUND((N642/IF(M642>26,26,M642)/8*(AH642*$AH$5+AI642*$AI$5+AJ642*$AJ$5+AK642*$AK$5+AL642*$AL$5)),0) -> 1876060 | AN642: =ROUND(AG642+AM642,0) -> 10542895 | AO642: 738255 | AP642: 44100 | AQ642: 0 | AR642: 0 | AS642: 0 | AT642: =+ROUND(SUM(AN642:AN642)-SUM(AO642:AS642),0) -> 9760540 | AW642: HA THI MONG BINH | AX642: 050120866335 | AY642: SK1 Bag | AZ642: 622 | BA642: =+IF(AY642="SK1 Box","Box",IF(AY642="Seaman","Seaman","Bag")) -> Bag
A643: =SUBTOTAL(3,B$6:B643) -> 638 | B643: C14158 | C643: Nguyễn Hiến Chương | D643: 44330 | E643: FACTORY D | F643: P4 - QC | G643: QC worker | H643: 5931000 | I643: 1100000 | J643: 0 | K643: 0 | L643: =SUM(H643:K643) -> 7031000 | M643: 24 | N643: =ROUND((H643+I643+J643+K643)/IF($M$2>26,26,$M$2)*M643,0) -> 6490154 | O643: 2 | P643: =ROUND((H643+I643+J643+K643)/IF($M$2>26,26,$M$2)*O643,0) -> 540846 | Q643: 0 | R643: =IF(M643>0,ROUND(N643/IF(M643>26,26,M643)/8*Q643*30%,0),0) -> 0 | S643: =N643+P643+R643 -> 7031000 | T643: 0 | U643: 0 | V643: 200000 | W643: 500000 | X643: 0 | Y643: 400000 | Z643: 400000 | AC643: 0 | AD643: 0 | AE643: 0 | AG643: =ROUND(SUM(S643:AF643)-AA643,0) -> 8531000 | AH643: 32 | AI643: 0 | AJ643: 0 | AK643: 0 | AL643: 0 | AM643: =ROUND((N643/IF(M643>26,26,M643)/8*(AH643*$AH$5+AI643*$AI$5+AJ643*$AJ$5+AK643*$AK$5+AL643*$AL$5)),0) -> 1622539 | AN643: =ROUND(AG643+AM643,0) -> 10153539 | AO643: 738255 | AP643: 44100 | AQ643: 0 | AR643: 0 | AS643: 0 | AT643: =+ROUND(SUM(AN643:AN643)-SUM(AO643:AS643),0) -> 9371184 | AW643: NGUYEN HIEN CHUONG | AX643: 050121351592 | AY643: SK1 Bag | AZ643: 622 | BA643: =+IF(AY643="SK1 Box","Box",IF(AY643="Seaman","Seaman","Bag")) -> Bag
A644: =SUBTOTAL(3,B$6:B644) -> 639 | B644: C14256 | C644: Trần Tuấn Bảo | D644: 44343 | E644: FACTORY D | F644: P4 - QC | G644: QC worker | H644: 5931000 | I644: 1100000 | J644: 0 | K644: 0 | L644: =SUM(H644:K644) -> 7031000 | M644: 23 | N644: =ROUND((H644+I644+J644+K644)/IF($M$2>26,26,$M$2)*M644,0) -> 6219731 | O644: 3 | P644: =ROUND((H644+I644+J644+K644)/IF($M$2>26,26,$M$2)*O644,0) -> 811269 | Q644: 0 | R644: =IF(M644>0,ROUND(N644/IF(M644>26,26,M644)/8*Q644*30%,0),0) -> 0 | S644: =N644+P644+R644 -> 7031000 | T644: 0 | U644: 0 | V644: 200000 | W644: 500000 | X644: 0 | Y644: 400000 | Z644: 383300 | AC644: 0 | AD644: 0 | AE644: 0 | AG644: =ROUND(SUM(S644:AF644)-AA644,0) -> 8514300 | AH644: 32 | AI644: 0 | AJ644: 0 | AK644: 0 | AL644: 0 | AM644: =ROUND((N644/IF(M644>26,26,M644)/8*(AH644*$AH$5+AI644*$AI$5+AJ644*$AJ$5+AK644*$AK$5+AL644*$AL$5)),0) -> 1622539 | AN644: =ROUND(AG644+AM644,0) -> 10136839 | AO644: 738255 | AP644: 44100 | AQ644: 0 | AR644: 0 | AS644: 0 | AT644: =+ROUND(SUM(AN644:AN644)-SUM(AO644:AS644),0) -> 9354484 | AW644: TRAN TUAN BAO | AX644: 050128255963 | AY644: SK1 Bag | AZ644: 622 | BA644: =+IF(AY644="SK1 Box","Box",IF(AY644="Seaman","Seaman","Bag")) -> Bag
A645: =SUBTOTAL(3,B$6:B645) -> 640 | B645: C14270 | C645: Nguyễn Thị Hạ | D645: 44348 | E645: FACTORY D | F645: P4 - QC | G645: QC worker | H645: 5931000 | I645: 1100000 | J645: 0 | K645: 0 | L645: =SUM(H645:K645) -> 7031000 | M645: 23.8 | N645: =ROUND((H645+I645+J645+K645)/IF($M$2>26,26,$M$2)*M645,0) -> 6436069 | O645: 2 | P645: =ROUND((H645+I645+J645+K645)/IF($M$2>26,26,$M$2)*O645,0) -> 540846 | Q645: 0 | R645: =IF(M645>0,ROUND(N645/IF(M645>26,26,M645)/8*Q645*30%,0),0) -> 0 | S645: =N645+P645+R645 -> 6976915 | T645: 0 | U645: 0 | V645: 200000 | W645: 500000 | X645: 0 | Y645: 400000 | Z645: 396700 | AC645: 100000 | AD645: 0 | AE645: 50704.325 | AG645: =ROUND(SUM(S645:AF645)-AA645,0) -> 8624319 | AH645: 22 | AI645: 0 | AJ645: 0 | AK645: 0 | AL645: 0 | AM645: =ROUND((N645/IF(M645>26,26,M645)/8*(AH645*$AH$5+AI645*$AI$5+AJ645*$AJ$5+AK645*$AK$5+AL645*$AL$5)),0) -> 1115495 | AN645: =ROUND(AG645+AM645,0) -> 9739814 | AO645: 738255 | AP645: 44100 | AQ645: 0 | AR645: 0 | AS645: 0 | AT645: =+ROUND(SUM(AN645:AN645)-SUM(AO645:AS645),0) -> 8957459 | AW645: NGUYEN THI HA | AX645: 050129038931 | AY645: SK1 Bag | AZ645: 622 | BA645: =+IF(AY645="SK1 Box","Box",IF(AY645="Seaman","Seaman","Bag")) -> Bag
A646: =SUBTOTAL(3,B$6:B646) -> 641 | B646: C14436 | C646: Nguyễn Thị Ngọc Huỳnh | D646: 44601 | E646: FACTORY D | F646: P4 - QC | G646: QC worker | H646: 5931000 | I646: 1100000 | J646: 0 | K646: 0 | L646: =SUM(H646:K646) -> 7031000 | M646: 24 | N646: =ROUND((H646+I646+J646+K646)/IF($M$2>26,26,$M$2)*M646,0) -> 6490154 | O646: 2 | P646: =ROUND((H646+I646+J646+K646)/IF($M$2>26,26,$M$2)*O646,0) -> 540846 | Q646: 0 | R646: =IF(M646>0,ROUND(N646/IF(M646>26,26,M646)/8*Q646*30%,0),0) -> 0 | S646: =N646+P646+R646 -> 7031000 | T646: 0 | U646: 0 | V646: 200000 | W646: 500000 | X646: 0 | Y646: 400000 | Z646: 400000 | AC646: 0 | AD646: 0 | AE646: 50704.328 | AG646: =ROUND(SUM(S646:AF646)-AA646,0) -> 8581704 | AH646: 37 | AI646: 0 | AJ646: 0 | AK646: 0 | AL646: 0 | AM646: =ROUND((N646/IF(M646>26,26,M646)/8*(AH646*$AH$5+AI646*$AI$5+AJ646*$AJ$5+AK646*$AK$5+AL646*$AL$5)),0) -> 1876060 | AN646: =ROUND(AG646+AM646,0) -> 10457764 | AO646: 738255 | AP646: 44100 | AQ646: 0 | AR646: 0 | AS646: 0 | AT646: =+ROUND(SUM(AN646:AN646)-SUM(AO646:AS646),0) -> 9675409 | AW646: NGUYEN THI NGOC HUYNH | AX646: 050155392883 | AY646: SK1 Bag | AZ646: 622 | BA646: =+IF(AY646="SK1 Box","Box",IF(AY646="Seaman","Seaman","Bag")) -> Bag
A647: =SUBTOTAL(3,B$6:B647) -> 642 | B647: C14444 | C647: Phạm Thùy Hương | D647: 44602 | E647: FACTORY D | F647: P4 - QC | G647: QC worker | H647: 5931000 | I647: 1100000 | J647: 0 | K647: 0 | L647: =SUM(H647:K647) -> 7031000 | M647: 1 | N647: =ROUND((H647+I647+J647+K647)/IF($M$2>26,26,$M$2)*M647,0) -> 270423 | O647: 1 | P647: =ROUND((H647+I647+J647+K647)/IF($M$2>26,26,$M$2)*O647,0) -> 270423 | Q647: 0 | R647: =IF(M647>0,ROUND(N647/IF(M647>26,26,M647)/8*Q647*30%,0),0) -> 0 | S647: =N647+P647+R647 -> 540846 | T647: 0 | U647: 0 | V647: 0 | W647: 0 | X647: 0 | Y647: 0 | Z647: 0 | AC647: 0 | AD647: 0 | AE647: 0 | AG647: =ROUND(SUM(S647:AF647)-AA647,0) -> 540846 | AH647: 0 | AI647: 0 | AJ647: 0 | AK647: 0 | AL647: 0 | AM647: =ROUND((N647/IF(M647>26,26,M647)/8*(AH647*$AH$5+AI647*$AI$5+AJ647*$AJ$5+AK647*$AK$5+AL647*$AL$5)),0) -> 0 | AN647: =ROUND(AG647+AM647,0) -> 540846 | AO647: 0 | AP647: 44100 | AQ647: 0 | AR647: 0 | AS647: 0 | AT647: =+ROUND(SUM(AN647:AN647)-SUM(AO647:AS647),0) -> 496746 | AW647: PHAM THUY HUONG | AX647: 050053905495 | AY647: SK1 Bag | AZ647: 622 | BA647: =+IF(AY647="SK1 Box","Box",IF(AY647="Seaman","Seaman","Bag")) -> Bag
A648: =SUBTOTAL(3,B$6:B648) -> 643 | B648: C14811 | C648: Kpă H Mai Ly | D648: 44665 | E648: FACTORY D | F648: P4 - QC | G648: QC worker | H648: 5931000 | I648: 900000 | J648: 0 | K648: 0 | L648: =SUM(H648:K648) -> 6831000 | M648: 24 | N648: =ROUND((H648+I648+J648+K648)/IF($M$2>26,26,$M$2)*M648,0) -> 6305538 | O648: 2 | P648: =ROUND((H648+I648+J648+K648)/IF($M$2>26,26,$M$2)*O648,0) -> 525462 | Q648: 0 | R648: =IF(M648>0,ROUND(N648/IF(M648>26,26,M648)/8*Q648*30%,0),0) -> 0 | S648: =N648+P648+R648 -> 6831000 | T648: 0 | U648: 0 | V648: 200000 | W648: 500000 | X648: 0 | Y648: 400000 | Z648: 400000 | AC648: 100000 | AD648: 0 | AE648: 49262.016 | AG648: =ROUND(SUM(S648:AF648)-AA648,0) -> 8480262 | AH648: 22 | AI648: 0 | AJ648: 0 | AK648: 0 | AL648: 0 | AM648: =ROUND((N648/IF(M648>26,26,M648)/8*(AH648*$AH$5+AI648*$AI$5+AJ648*$AJ$5+AK648*$AK$5+AL648*$AL$5)),0) -> 1083764 | AN648: =ROUND(AG648+AM648,0) -> 9564026 | AO648: 717255 | AP648: 44100 | AQ648: 0 | AR648: 0 | AS648: 0 | AT648: =+ROUND(SUM(AN648:AN648)-SUM(AO648:AS648),0) -> 8802671 | AW648: KPA H MAI LY | AX648: 050122316073 | AY648: SK1 Bag | AZ648: 622 | BA648: =+IF(AY648="SK1 Box","Box",IF(AY648="Seaman","Seaman","Bag")) -> Bag
