Workbook

Sheet Sheet1
D2: Inside | E2: Outside | F2: Total
B3: 1 | C3: Payment Transfer - Foreign | D3: =+'Foreign Salary'!R11 -> 480497301 | E3: 0 | F3: =SUM(D3:E3) -> 480497301 | G3: =+F3-'Foreign Salary'!R11 -> 0
B4: 2 | C4: Payment Transfer | D4: 10547466313 | E4: 1126799307 | F4: =SUM(D4:E4) -> 11674265620 | G4: =+F4-Transfer!E1279 -> 269595426
B5: 3 | C5: Payment Cash | D5: 215764202 | E5: 21316040 | F5: =SUM(D5:E5) -> 237080242 | G5: =+F5-Cash!F18 -> 197683519
B6: 4 | C6: Payment cash - Ms Quyên Nurse Staff | D6: 0 | E6: 11464288 | F6: =SUM(D6:E6) -> 11464288
C7: Total | D7: =SUM(D3:D6) -> 11243727816 | E7: =SUM(E3:E6) -> 1159579635 | F7: =SUM(F3:F6) -> 12403307451
F8: =+F7-'TOTAL(payment)'!L119 -> 478743233

Sheet Manager
A1: STT | B1: Code | C1: Name | D1: Tổng thu nhập Total Gross Salary | E1: Phụ cấp Phụ Nữ Menstruation allowance | F1: Tiền thực lãnh Net Salary | G1: Bộ phận Dep | H1: Title/ Chức danh
A2: 1 | B2: C3402 | C2: Đoàn Thị Hiếu Loan | D2: =+VLOOKUP(B2,'Salary sheet'!$B$6:$AS$1291,40,0) -> 2562000 | E2: =VLOOKUP(B2,'Salary sheet'!$B$6:$AE$1318,30,0) -> 175961.54 | F2: =+D2-E2 -> 2386038.5 | G2: =VLOOKUP(B2,'Salary sheet'!$B$3:$G$1318,5,0) -> P6 - Production Office | H2: =VLOOKUP(B2,'Salary sheet'!$B$3:$G$1318,6,0) -> Factory manager
A3: 2 | B3: C5841 | C3: Trần Văn Nhân | D3: =+VLOOKUP(B3,'Salary sheet'!$B$6:$AS$1291,40,0) -> 2566200 | E3: =VLOOKUP(B3,'Salary sheet'!$B$6:$AE$1318,30,0) -> 0 | F3: =+D3-E3 -> 2566200 | G3: =VLOOKUP(B3,'Salary sheet'!$B$3:$G$1318,5,0) -> P6 - Production Office | H3: =VLOOKUP(B3,'Salary sheet'!$B$3:$G$1318,6,0) -> Factory manager
A4: 3 | B4: C3465 | C4: Lê Văn Khỏe | D4: =+VLOOKUP(B4,'Salary sheet'!$B$6:$AS$1291,40,0) -> 1944495 | E4: =VLOOKUP(B4,'Salary sheet'!$B$6:$AE$1318,30,0) -> 0 | F4: =+D4-E4 -> 1944495 | G4: =VLOOKUP(B4,'Salary sheet'!$B$3:$G$1318,5,0) -> P5 - Production Office | H4: =VLOOKUP(B4,'Salary sheet'!$B$3:$G$1318,6,0) -> Factory vice manager
A5: 4 | B5: C6068 | C5: Trần Thị Cẩm Linh | D5: =+VLOOKUP(B5,'Salary sheet'!$B$6:$AS$1291,40,0) -> 3034500 | E5: =VLOOKUP(B5,'Salary sheet'!$B$6:$AE$1318,30,0) -> 208413.46 | F5: =+D5-E5 -> 2826086.5 | G5: =VLOOKUP(B5,'Salary sheet'!$B$3:$G$1318,5,0) -> P4 - Production Office | H5: =VLOOKUP(B5,'Salary sheet'!$B$3:$G$1318,6,0) -> Factory manager
A6: 5 | B6: C6347 | C6: Đỗ Thị Thanh Tú | D6: =+VLOOKUP(B6,'Salary sheet'!$B$6:$AS$1291,40,0) -> 3066000 | E6: =VLOOKUP(B6,'Salary sheet'!$B$6:$AE$1318,30,0) -> 210576.93 | F6: =+D6-E6 -> 2855423.1 | G6: =VLOOKUP(B6,'Salary sheet'!$B$3:$G$1318,5,0) -> P0 - Design | H6: =VLOOKUP(B6,'Salary sheet'!$B$3:$G$1318,6,0) -> Design manager
A7: 6 | B7: C6407 | C7: Điểu Dũng | D7: =+VLOOKUP(B7,'Salary sheet'!$B$6:$AS$1291,40,0) -> 2551500 | E7: =VLOOKUP(B7,'Salary sheet'!$B$6:$AE$1318,30,0) -> 0 | F7: =+D7-E7 -> 2551500 | G7: =VLOOKUP(B7,'Salary sheet'!$B$3:$G$1318,5,0) -> P0 - Development | H7: =VLOOKUP(B7,'Salary sheet'!$B$3:$G$1318,6,0) -> Development manager
A8: 7 | B8: V004 | C8: Hồ Mạnh Hoàng | D8: =+VLOOKUP(B8,'Salary sheet'!$B$6:$AS$1291,40,0) -> 1850520 | E8: =VLOOKUP(B8,'Salary sheet'!$B$6:$AE$1318,30,0) -> 0 | F8: =+D8-E8 -> 1850520 | G8: =VLOOKUP(B8,'Salary sheet'!$B$3:$G$1318,5,0) -> P0 - Maintenance | H8: =VLOOKUP(B8,'Salary sheet'!$B$3:$G$1318,6,0) -> Maintenance Leader
A9: 8 | B9: C5097 | C9: Kiều Quốc Minh | D9: =+VLOOKUP(B9,'Salary sheet'!$B$6:$AS$1291,40,0) -> 3227700 | E9: =VLOOKUP(B9,'Salary sheet'!$B$6:$AE$1318,30,0) -> 0 | F9: =+D9-E9 -> 3227700 | G9: =VLOOKUP(B9,'Salary sheet'!$B$3:$G$1318,5,0) -> P0 - GC WIP | H9: =VLOOKUP(B9,'Salary sheet'!$B$3:$G$1318,6,0) -> GC WIP Manager
A10: 9 | B10: C5107 | C10: Roãn Văn Hòa | D10: =+VLOOKUP(B10,'Salary sheet'!$B$6:$AS$1291,40,0) -> 3969000 | E10: =VLOOKUP(B10,'Salary sheet'!$B$6:$AE$1318,30,0) -> 0 | F10: =+D10-E10 -> 3969000 | G10: =VLOOKUP(B10,'Salary sheet'!$B$3:$G$1318,5,0) -> P0 - Production Office | H10: =VLOOKUP(B10,'Salary sheet'!$B$3:$G$1318,6,0) -> Production Manager
A11: 10 | B11: C6332 | C11: Đỗ Văn Thái | D11: =+VLOOKUP(B11,'Salary sheet'!$B$6:$AS$1291,40,0) -> 3097500 | E11: =VLOOKUP(B11,'Salary sheet'!$B$6:$AE$1318,30,0) -> 0 | F11: =+D11-E11 -> 3097500 | G11: =VLOOKUP(B11,'Salary sheet'!$B$3:$G$1318,5,0) -> P1 - Production Office | H11: =VLOOKUP(B11,'Salary sheet'!$B$3:$G$1318,6,0) -> Factory manager
A12: 11 | B12: C0020 | C12: Phan Tuấn Khanh | D12: =+VLOOKUP(B12,'Salary sheet'!$B$6:$AS$1291,40,0) -> 3070200 | E12: =VLOOKUP(B12,'Salary sheet'!$B$6:$AE$1318,30,0) -> 0 | F12: =+D12-E12 -> 3070200 | G12: =VLOOKUP(B12,'Salary sheet'!$B$3:$G$1318,5,0) -> P2 - Production Office | H12: =VLOOKUP(B12,'Salary sheet'!$B$3:$G$1318,6,0) -> Factory manager
A13: 12 | B13: V054 | C13: Huỳnh Ngọc Thảo | D13: =+VLOOKUP(B13,'Salary sheet'!$B$6:$AS$1291,40,0) -> 3301200 | E13: =VLOOKUP(B13,'Salary sheet'!$B$6:$AE$1318,30,0) -> 226730.77 | F13: =+D13-E13 -> 3074469.2 | G13: =VLOOKUP(B13,'Salary sheet'!$B$3:$G$1318,5,0) -> P3 - Production Office | H13: =VLOOKUP(B13,'Salary sheet'!$B$3:$G$1318,6,0) -> Factory manager
... A17: 16 | B17: C14623 | C17: Trần Văn Hoài | D17: =+VLOOKUP(B17,'Salary sheet'!$B$6:$AS$1291,40,0) -> 3811500 | E17: =VLOOKUP(B17,'Salary sheet'!$B$6:$AE$1318,30,0) -> 0 | F17: =+D17-E17 -> 3811500 | G17: =VLOOKUP(B17,'Salary sheet'!$B$3:$G$1318,5,0) -> P5 - Production Office | H17: =VLOOKUP(B17,'Salary sheet'!$B$3:$G$1318,6,0) -> Factory manager
C18: Total | D18: =SUM(D2:D17) -> #N/A | E18: =SUM(E2:E17) -> #N/A | F18: =SUM(F2:F17) -> #N/A | G18: =SUM(G2:G17) -> #N/A | H18: =SUM(H2:H17) -> #N/A

Sheet SS
B1: Content | C1: Jun-May | D1: % | E1: Noted
B2: Working day | C2: 4186.2 | D2: 0.11849927 | E2: Working: Jun.2020: 26 days - May.2020: 24 days
B3: Paid leave | C3: -2887 | D3: -0.86076327 | E3: After Corona epidemic situationm,After Transportation of machinery SK1: Box - SK2: Bag - Normal working
B4: Night work + 30% | C4: 3478.5 | D4: 1.9775441 | E4: After Corona epidemic situation - Normal overtime
B5: Overtime 150% | C5: 41402.5 | D5: 9.3123032 | E5: After Corona epidemic situation - Normal overtime
B6: Overtime 200% | C6: 0 | D6: 0
B7: Overtime 210% | C7: 1267 | D7: 4.4770318 | E7: After Corona epidemic situation - Normal overtime
B9: Content | C9: Jan-Dec | D9: % | E9: Noted
B10: Working day | C10: -7837.9 | D10: -0.22161745 | E10: Jan.22: working day 22 day
E11: Dec: Isolate (7 day) working day 27 day (Total 35.366 day/ 1681 Preson)
B12: Paid leave | C12: 3842 | D12: 6.4033333 | E12: Jan.2022 Holiday 2 day (01+31/Jan/2022)
E13: Dec: No holiday
B14: Night work + 30% | C14: -2045.8 | D14: -0.71232591 | E14: Jan.22: working day 22 day
E15: Dec: Working day 27 day &Night work 2872 Hour
B16: Overtime 150% | C16: -12945 | D16: -0.19960834 | E16: Jan.22: working day 22 day
E17: Dec: Working day 27 day (Overtime 64.852 hour)
B18: Overtime 200% | C18: 1152 | D18: 33.882353 | E18: Jan.2022: Overtime Sunday 1186 Hour
E19: Dec: Overtime Sunday 34 Hour
B20: Overtime 210% | C20: -251 | D20: -0.47809524 | E20: Jan.2022: Working day 22 day (274 Hour)
E21: Dec: Working day 27 day (525 Hour)
B22: Overtime 300% | C22: -254.5 | D22: -1 | E22: Oct.2021 No overtime 300%
B25: Content | C25: Mar | D25: Feb | E25: ="Amount "&C25&" ~ "&D25 -> Amount Mar ~ Feb | F25: % | G25: Note
B26: Working Day | C26: 31007.9 | D26: 25659.4 | E26: =+C26-D26 -> 5348.5 | F26: =+E26/D26 -> 0.20844213 | G26: Feb: Working day 22 day Mar Working day 26 day
B27: Paid Leave | C27: 87 | D27: 2435 | E27: =+C27-D27 -> -2348 | F27: =+E27/D27 -> -0.96427105 | G27: Feb: Tet Holiday: 1 day (01/02) & Annual leave: 1 day (03/02) Mar: Marriage leave, funeral | J27: Marriage leave, labor accidents leave, funeral
B28: Annual Leave | E28: =+C28-D28 -> 0 | G28: Balance annual leave 2024
B29: extra pay for night work + 30% | C29: 4387 | D29: 3546.5 | E29: =+C29-D29 -> 840.5 | F29: =+E29/D29 -> 0.23699422 | G29: Increased night working hours (due to higher actual working days than last month)
B30: Overtime 150% | C30: 46222.5 | D30: 32182 | E30: =+C30-D30 -> 14040.5 | F30: =+E30/D30 -> 0.43628426 | G30: Increased overtime 150% : (due to higher actual working days than last month)
B31: Overtime 200% | C31: 199.5 | D31: 185.5 | E31: =+C31-D31 -> 14 | F31: =+E31/D31 -> 0.075471698 | G31: Overtime Sunday
B32: Overtime 210% | C32: 506.5 | D32: 240 | E32: =+C32-D32 -> 266.5 | F32: =+E32/D32 -> 1.1104167 | G32: Increased night working hours (due to higher actual working days than last month)
B33: Overtime 270% | E33: =+C33-D33 -> 0
B34: Overtime 300% | D34: 0 | E34: =+C34-D34 -> 0

Sheet TOTAL(payment)
A1: Công ty TNHH Bao Bì Cao Cấp S&K Vina
A3: BẢNG TỔNG KẾT LƯƠNG THÁNG 04 2025
A4: SUM OF SALARY OF APR 2025
A6: 0.54444444 | B6: Fac | C6: Dep new | D6: Dep Code | E6: # of worker | F6: Tổng thu nhập Total gross salary | G6: BHXH&BHYT, BHTN Social & Health Ins, Unempl-oyment Benefit | H6: KPCĐ Union Dues | I6: Thuế TNCN Personal Income Tax | J6: Đồng Phục Uniform | K6: Ứng Lương Advance | L6: Số Tiền (VND) Net salary | M6: Average
A7: =SUBTOTAL(3,B$7:B7) -> 1 | B7: Foreigners | C7: Foreigners | E7: 3 | F7: =+'Foreign Salary'!L11 -> 686964617 | G7: =+'Foreign Salary'!M11 -> 13338000 | H7: 0 | I7: =+'Foreign Salary'!P11 -> 193129316 | J7: 0 | K7: 0 | L7: =+(F7)-SUM(G7:K7) -> 480497301 | M7: =+L7/E7 -> 160165767
A8: =SUBTOTAL(3,B$7:B8) -> 2 | B8: SK2 | C8: P0 - Cleaning | D8: P0-CL-1-01 | E8: =COUNTIFS('Salary sheet'!$F$6:$F$2288,C8,'Salary sheet'!$E$6:$E$2288,B8) -> 4 | F8: =+SUMIFS('Salary sheet'!$AN$6:$AN$1292,'Salary sheet'!$F$6:$F$1292,'TOTAL(payment)'!C8,'Salary sheet'!$E$6:$E$1292,'TOTAL(payment)'!B8) -> 37891917 | G8: =+SUMIFS('Salary sheet'!$AO$6:$AO$2288,'Salary sheet'!$F$6:$F$2288,C8,'Salary sheet'!$E$6:$E$2288,B8) -> 2962470 | H8: =+SUMIFS('Salary sheet'!$AP$6:$AP$2288,'Salary sheet'!$F$6:$F$2288,C8,'Salary sheet'!$E$6:$E$2288,B8) -> 176400 | I8: =+SUMIFS('Salary sheet'!$AQ$6:$AQ$2288,'Salary sheet'!$F$6:$F$2288,C8,'Salary sheet'!$E$6:$E$2288,B8) -> 0 | J8: =+SUMIFS('Salary sheet'!$AR$6:$AR$2288,'Salary sheet'!$F$6:$F$2288,C8,'Salary sheet'!$E$6:$E$2288,B8) -> 0 | K8: =SUMIFS('Salary sheet'!$AS$6:$AS$1291,'Salary sheet'!$F$6:$F$1291,'TOTAL(payment)'!C8) -> 0 | L8: =+(F8)-SUM(G8:K8) -> 34753047 | M8: =+L8/E8 -> 8688261.8
A9: =SUBTOTAL(3,B$7:B9) -> 3 | B9: SK2 | C9: P0 - Design | D9: P0-DS-1-01 | E9: =COUNTIFS('Salary sheet'!$F$6:$F$2288,C9,'Salary sheet'!$E$6:$E$2288,B9) -> 4 | F9: =+SUMIFS('Salary sheet'!$AN$6:$AN$1292,'Salary sheet'!$F$6:$F$1292,'TOTAL(payment)'!C9,'Salary sheet'!$E$6:$E$1292,'TOTAL(payment)'!B9) -> 69105288 | G9: =+SUMIFS('Salary sheet'!$AO$6:$AO$2288,'Salary sheet'!$F$6:$F$2288,C9,'Salary sheet'!$E$6:$E$2288,B9) -> 7350000 | H9: =+SUMIFS('Salary sheet'!$AP$6:$AP$2288,'Salary sheet'!$F$6:$F$2288,C9,'Salary sheet'!$E$6:$E$2288,B9) -> 176400 | I9: =+SUMIFS('Salary sheet'!$AQ$6:$AQ$2288,'Salary sheet'!$F$6:$F$2288,C9,'Salary sheet'!$E$6:$E$2288,B9) -> 333370 | J9: =+SUMIFS('Salary sheet'!$AR$6:$AR$2288,'Salary sheet'!$F$6:$F$2288,C9,'Salary sheet'!$E$6:$E$2288,B9) -> 0 | K9: =SUMIFS('Salary sheet'!$AS$6:$AS$1291,'Salary sheet'!$F$6:$F$1291,'TOTAL(payment)'!C9) -> 0 | L9: =+(F9)-SUM(G9:K9) -> 61245518 | M9: =+L9/E9 -> 15311380
A10: =SUBTOTAL(3,B$7:B10) -> 4 | B10: SK2 | C10: P0 - Development | D10: P0-DE-1-01 | E10: =COUNTIFS('Salary sheet'!$F$6:$F$2288,C10,'Salary sheet'!$E$6:$E$2288,B10) -> 13 | F10: =+SUMIFS('Salary sheet'!$AN$6:$AN$1292,'Salary sheet'!$F$6:$F$1292,'TOTAL(payment)'!C10,'Salary sheet'!$E$6:$E$1292,'TOTAL(payment)'!B10) -> 148995921 | G10: =+SUMIFS('Salary sheet'!$AO$6:$AO$2288,'Salary sheet'!$F$6:$F$2288,C10,'Salary sheet'!$E$6:$E$2288,B10) -> 12238905 | H10: =+SUMIFS('Salary sheet'!$AP$6:$AP$2288,'Salary sheet'!$F$6:$F$2288,C10,'Salary sheet'!$E$6:$E$2288,B10) -> 573300 | I10: =+SUMIFS('Salary sheet'!$AQ$6:$AQ$2288,'Salary sheet'!$F$6:$F$2288,C10,'Salary sheet'!$E$6:$E$2288,B10) -> 97752 | J10: =+SUMIFS('Salary sheet'!$AR$6:$AR$2288,'Salary sheet'!$F$6:$F$2288,C10,'Salary sheet'!$E$6:$E$2288,B10) -> 0 | K10: =SUMIFS('Salary sheet'!$AS$6:$AS$1291,'Salary sheet'!$F$6:$F$1291,'TOTAL(payment)'!C10) -> 0 | L10: =+(F10)-SUM(G10:K10) -> 136085964 | M10: =+L10/E10 -> 10468151
A11: =SUBTOTAL(3,B$7:B11) -> 5 | B11: SK2 | C11: P0 - FG Warehouse | D11: P0-FG-1-01 | E11: =COUNTIFS('Salary sheet'!$F$6:$F$2288,C11,'Salary sheet'!$E$6:$E$2288,B11) -> 3 | F11: =+SUMIFS('Salary sheet'!$AN$6:$AN$1292,'Salary sheet'!$F$6:$F$1292,'TOTAL(payment)'!C11,'Salary sheet'!$E$6:$E$1292,'TOTAL(payment)'!B11) -> 32157502 | G11: =+SUMIFS('Salary sheet'!$AO$6:$AO$2288,'Salary sheet'!$F$6:$F$2288,C11,'Salary sheet'!$E$6:$E$2288,B11) -> 2592345 | H11: =+SUMIFS('Salary sheet'!$AP$6:$AP$2288,'Salary sheet'!$F$6:$F$2288,C11,'Salary sheet'!$E$6:$E$2288,B11) -> 132300 | I11: =+SUMIFS('Salary sheet'!$AQ$6:$AQ$2288,'Salary sheet'!$F$6:$F$2288,C11,'Salary sheet'!$E$6:$E$2288,B11) -> 0 | J11: =+SUMIFS('Salary sheet'!$AR$6:$AR$2288,'Salary sheet'!$F$6:$F$2288,C11,'Salary sheet'!$E$6:$E$2288,B11) -> 0 | K11: =SUMIFS('Salary sheet'!$AS$6:$AS$1291,'Salary sheet'!$F$6:$F$1291,'TOTAL(payment)'!C11) -> 0 | L11: =+(F11)-SUM(G11:K11) -> 29432857 | M11: =+L11/E11 -> 9810952.3
A12: =SUBTOTAL(3,B$7:B12) -> 6 | B12: SK2 | C12: P0 - GA-HR | D12: P0-HR-1-01 | E12: =COUNTIFS('Salary sheet'!$F$6:$F$2288,C12,'Salary sheet'!$E$6:$E$2288,B12) -> 3 | F12: =+SUMIFS('Salary sheet'!$AN$6:$AN$1292,'Salary sheet'!$F$6:$F$1292,'TOTAL(payment)'!C12,'Salary sheet'!$E$6:$E$1292,'TOTAL(payment)'!B12) -> 36890624 | G12: =+SUMIFS('Salary sheet'!$AO$6:$AO$2288,'Salary sheet'!$F$6:$F$2288,C12,'Salary sheet'!$E$6:$E$2288,B12) -> 3727500 | H12: =+SUMIFS('Salary sheet'!$AP$6:$AP$2288,'Salary sheet'!$F$6:$F$2288,C12,'Salary sheet'!$E$6:$E$2288,B12) -> 132300 | I12: =+SUMIFS('Salary sheet'!$AQ$6:$AQ$2288,'Salary sheet'!$F$6:$F$2288,C12,'Salary sheet'!$E$6:$E$2288,B12) -> 0 | J12: =+SUMIFS('Salary sheet'!$AR$6:$AR$2288,'Salary sheet'!$F$6:$F$2288,C12,'Salary sheet'!$E$6:$E$2288,B12) -> 0 | K12: =SUMIFS('Salary sheet'!$AS$6:$AS$1291,'Salary sheet'!$F$6:$F$1291,'TOTAL(payment)'!C12) -> 0 | L12: =+(F12)-SUM(G12:K12) -> 33030824 | M12: =+L12/E12 -> 11010275
A13: =SUBTOTAL(3,B$7:B13) -> 7 | B13: SK2 | C13: P0 - GC WIP | D13: P0-WP-1-01 | E13: =COUNTIFS('Salary sheet'!$F$6:$F$2288,C13,'Salary sheet'!$E$6:$E$2288,B13) -> 10 | F13: =+SUMIFS('Salary sheet'!$AN$6:$AN$1292,'Salary sheet'!$F$6:$F$1292,'TOTAL(payment)'!C13,'Salary sheet'!$E$6:$E$1292,'TOTAL(payment)'!B13) -> 132468353 | G13: =+SUMIFS('Salary sheet'!$AO$6:$AO$2288,'Salary sheet'!$F$6:$F$2288,C13,'Salary sheet'!$E$6:$E$2288,B13) -> 11025420 | H13: =+SUMIFS('Salary sheet'!$AP$6:$AP$2288,'Salary sheet'!$F$6:$F$2288,C13,'Salary sheet'!$E$6:$E$2288,B13) -> 441000 | I13: =+SUMIFS('Salary sheet'!$AQ$6:$AQ$2288,'Salary sheet'!$F$6:$F$2288,C13,'Salary sheet'!$E$6:$E$2288,B13) -> 170615 | J13: =+SUMIFS('Salary sheet'!$AR$6:$AR$2288,'Salary sheet'!$F$6:$F$2288,C13,'Salary sheet'!$E$6:$E$2288,B13) -> 0 | K13: =SUMIFS('Salary sheet'!$AS$6:$AS$1291,'Salary sheet'!$F$6:$F$1291,'TOTAL(payment)'!C13) -> 0 | L13: =+(F13)-SUM(G13:K13) -> 120831318 | M13: =+L13/E13 -> 12083132
A14: =SUBTOTAL(3,B$7:B14) -> 8 | B14: SK2 | C14: P0 - Maintenance | D14: P0-MA-1-01 | E14: =COUNTIFS('Salary sheet'!$F$6:$F$2288,C14,'Salary sheet'!$E$6:$E$2288,B14) -> 5 | F14: =+SUMIFS('Salary sheet'!$AN$6:$AN$1292,'Salary sheet'!$F$6:$F$1292,'TOTAL(payment)'!C14,'Salary sheet'!$E$6:$E$1292,'TOTAL(payment)'!B14) -> 75720308 | G14: =+SUMIFS('Salary sheet'!$AO$6:$AO$2288,'Salary sheet'!$F$6:$F$2288,C14,'Salary sheet'!$E$6:$E$2288,B14) -> 6744990 | H14: =+SUMIFS('Salary sheet'!$AP$6:$AP$2288,'Salary sheet'!$F$6:$F$2288,C14,'Salary sheet'!$E$6:$E$2288,B14) -> 220500 | I14: =+SUMIFS('Salary sheet'!$AQ$6:$AQ$2288,'Salary sheet'!$F$6:$F$2288,C14,'Salary sheet'!$E$6:$E$2288,B14) -> 87760 | J14: =+SUMIFS('Salary sheet'!$AR$6:$AR$2288,'Salary sheet'!$F$6:$F$2288,C14,'Salary sheet'!$E$6:$E$2288,B14) -> 0 | K14: =SUMIFS('Salary sheet'!$AS$6:$AS$1291,'Salary sheet'!$F$6:$F$1291,'TOTAL(payment)'!C14) -> 0 | L14: =+(F14)-SUM(G14:K14) -> 68667058 | M14: =+L14/E14 -> 13733412
A15: =SUBTOTAL(3,B$7:B15) -> 9 | B15: SK2 | C15: P0 - Marketing | D15: P0-MK-1-01 | E15: =COUNTIFS('Salary sheet'!$F$6:$F$2288,C15,'Salary sheet'!$E$6:$E$2288,B15) -> 9 | F15: =+SUMIFS('Salary sheet'!$AN$6:$AN$1292,'Salary sheet'!$F$6:$F$1292,'TOTAL(payment)'!C15,'Salary sheet'!$E$6:$E$1292,'TOTAL(payment)'!B15) -> 160153125 | G15: =+SUMIFS('Salary sheet'!$AO$6:$AO$2288,'Salary sheet'!$F$6:$F$2288,C15,'Salary sheet'!$E$6:$E$2288,B15) -> 16695000 | H15: =+SUMIFS('Salary sheet'!$AP$6:$AP$2288,'Salary sheet'!$F$6:$F$2288,C15,'Salary sheet'!$E$6:$E$2288,B15) -> 396900 | I15: =+SUMIFS('Salary sheet'!$AQ$6:$AQ$2288,'Salary sheet'!$F$6:$F$2288,C15,'Salary sheet'!$E$6:$E$2288,B15) -> 659735 | J15: =+SUMIFS('Salary sheet'!$AR$6:$AR$2288,'Salary sheet'!$F$6:$F$2288,C15,'Salary sheet'!$E$6:$E$2288,B15) -> 0 | K15: =SUMIFS('Salary sheet'!$AS$6:$AS$1291,'Salary sheet'!$F$6:$F$1291,'TOTAL(payment)'!C15) -> 0 | L15: =+(F15)-SUM(G15:K15) -> 142401490 | M15: =+L15/E15 -> 15822388
A16: =SUBTOTAL(3,B$7:B16) -> 10 | B16: SK2 | C16: P0 - Material Warehouse | D16: P0-MW-1-01 | E16: =COUNTIFS('Salary sheet'!$F$6:$F$2288,C16,'Salary sheet'!$E$6:$E$2288,B16) -> 5 | F16: =+SUMIFS('Salary sheet'!$AN$6:$AN$1292,'Salary sheet'!$F$6:$F$1292,'TOTAL(payment)'!C16,'Salary sheet'!$E$6:$E$1292,'TOTAL(payment)'!B16) -> 52639614 | G16: =+SUMIFS('Salary sheet'!$AO$6:$AO$2288,'Salary sheet'!$F$6:$F$2288,C16,'Salary sheet'!$E$6:$E$2288,B16) -> 4168306 | H16: =+SUMIFS('Salary sheet'!$AP$6:$AP$2288,'Salary sheet'!$F$6:$F$2288,C16,'Salary sheet'!$E$6:$E$2288,B16) -> 132300 | I16: =+SUMIFS('Salary sheet'!$AQ$6:$AQ$2288,'Salary sheet'!$F$6:$F$2288,C16,'Salary sheet'!$E$6:$E$2288,B16) -> 0 | J16: =+SUMIFS('Salary sheet'!$AR$6:$AR$2288,'Salary sheet'!$F$6:$F$2288,C16,'Salary sheet'!$E$6:$E$2288,B16) -> 0 | K16: =SUMIFS('Salary sheet'!$AS$6:$AS$1291,'Salary sheet'!$F$6:$F$1291,'TOTAL(payment)'!C16) -> 186299 | L16: =+(F16)-SUM(G16:K16) -> 48152709 | M16: =+L16/E16 -> 9630541.8
A17: =SUBTOTAL(3,B$7:B17) -> 11 | B17: SK2 | C17: P0 - Planning | D17: P0-PL-1-01 | E17: =COUNTIFS('Salary sheet'!$F$6:$F$2288,C17,'Salary sheet'!$E$6:$E$2288,B17) -> 9 | F17: =+SUMIFS('Salary sheet'!$AN$6:$AN$1292,'Salary sheet'!$F$6:$F$1292,'TOTAL(payment)'!C17,'Salary sheet'!$E$6:$E$1292,'TOTAL(payment)'!B17) -> 104930197 | G17: =+SUMIFS('Salary sheet'!$AO$6:$AO$2288,'Salary sheet'!$F$6:$F$2288,C17,'Salary sheet'!$E$6:$E$2288,B17) -> 10774995 | H17: =+SUMIFS('Salary sheet'!$AP$6:$AP$2288,'Salary sheet'!$F$6:$F$2288,C17,'Salary sheet'!$E$6:$E$2288,B17) -> 352800 | I17: =+SUMIFS('Salary sheet'!$AQ$6:$AQ$2288,'Salary sheet'!$F$6:$F$2288,C17,'Salary sheet'!$E$6:$E$2288,B17) -> 113181 | J17: =+SUMIFS('Salary sheet'!$AR$6:$AR$2288,'Salary sheet'!$F$6:$F$2288,C17,'Salary sheet'!$E$6:$E$2288,B17) -> 0 | K17: =SUMIFS('Salary sheet'!$AS$6:$AS$1291,'Salary sheet'!$F$6:$F$1291,'TOTAL(payment)'!C17) -> 0 | L17: =+(F17)-SUM(G17:K17) -> 93689221 | M17: =+L17/E17 -> 10409913
A18: =SUBTOTAL(3,B$7:B18) -> 12 | B18: SK2 | C18: P0 - Production Office | D18: P0-PO-1-01 | E18: =COUNTIFS('Salary sheet'!$F$6:$F$2288,C18,'Salary sheet'!$E$6:$E$2288,B18) -> 1 | F18: =+SUMIFS('Salary sheet'!$AN$6:$AN$1292,'Salary sheet'!$F$6:$F$1292,'TOTAL(payment)'!C18,'Salary sheet'!$E$6:$E$1292,'TOTAL(payment)'!B18) -> 38500000 | G18: =+SUMIFS('Salary sheet'!$AO$6:$AO$2288,'Salary sheet'!$F$6:$F$2288,C18,'Salary sheet'!$E$6:$E$2288,B18) -> 3969000 | H18: =+SUMIFS('Salary sheet'!$AP$6:$AP$2288,'Salary sheet'!$F$6:$F$2288,C18,'Salary sheet'!$E$6:$E$2288,B18) -> 44100 | I18: =+SUMIFS('Salary sheet'!$AQ$6:$AQ$2288,'Salary sheet'!$F$6:$F$2288,C18,'Salary sheet'!$E$6:$E$2288,B18) -> 283100 | J18: =+SUMIFS('Salary sheet'!$AR$6:$AR$2288,'Salary sheet'!$F$6:$F$2288,C18,'Salary sheet'!$E$6:$E$2288,B18) -> 0 | K18: =SUMIFS('Salary sheet'!$AS$6:$AS$1291,'Salary sheet'!$F$6:$F$1291,'TOTAL(payment)'!C18) -> 0 | L18: =+(F18)-SUM(G18:K18) -> 34203800 | M18: =+L18/E18 -> 34203800
A19: =SUBTOTAL(3,B$7:B19) -> 13 | B19: SK2 | C19: P0 - Purchasing | D19: P0-PU-1-01 | E19: =COUNTIFS('Salary sheet'!$F$6:$F$2288,C19,'Salary sheet'!$E$6:$E$2288,B19) -> 1 | F19: =+SUMIFS('Salary sheet'!$AN$6:$AN$1292,'Salary sheet'!$F$6:$F$1292,'TOTAL(payment)'!C19,'Salary sheet'!$E$6:$E$1292,'TOTAL(payment)'!B19) -> 9706348 | G19: =+SUMIFS('Salary sheet'!$AO$6:$AO$2288,'Salary sheet'!$F$6:$F$2288,C19,'Salary sheet'!$E$6:$E$2288,B19) -> 1012620 | H19: =+SUMIFS('Salary sheet'!$AP$6:$AP$2288,'Salary sheet'!$F$6:$F$2288,C19,'Salary sheet'!$E$6:$E$2288,B19) -> 44100 | I19: =+SUMIFS('Salary sheet'!$AQ$6:$AQ$2288,'Salary sheet'!$F$6:$F$2288,C19,'Salary sheet'!$E$6:$E$2288,B19) -> 0 | J19: =+SUMIFS('Salary sheet'!$AR$6:$AR$2288,'Salary sheet'!$F$6:$F$2288,C19,'Salary sheet'!$E$6:$E$2288,B19) -> 0 | K19: =SUMIFS('Salary sheet'!$AS$6:$AS$1291,'Salary sheet'!$F$6:$F$1291,'TOTAL(payment)'!C19) -> 0 | L19: =+(F19)-SUM(G19:K19) -> 8649628 | M19: =+L19/E19 -> 8649628
... A118: =SUBTOTAL(3,B$7:B118) -> 112 | B118: FACTORY A | C118: P8 - Slitter | D118: P8-CU-1-01 | E118: =COUNTIFS('Salary sheet'!$F$6:$F$2288,C118,'Salary sheet'!$E$6:$E$2288,B118) -> 1 | F118: =+SUMIFS('Salary sheet'!$AN$6:$AN$1292,'Salary sheet'!$F$6:$F$1292,'TOTAL(payment)'!C118,'Salary sheet'!$E$6:$E$1292,'TOTAL(payment)'!B118) -> 7912244 | G118: =+SUMIFS('Salary sheet'!$AO$6:$AO$2288,'Salary sheet'!$F$6:$F$2288,C118,'Salary sheet'!$E$6:$E$2288,B118) -> 627270 | H118: =+SUMIFS('Salary sheet'!$AP$6:$AP$2288,'Salary sheet'!$F$6:$F$2288,C118,'Salary sheet'!$E$6:$E$2288,B118) -> 44100 | I118: =+SUMIFS('Salary sheet'!$AQ$6:$AQ$2288,'Salary sheet'!$F$6:$F$2288,C118,'Salary sheet'!$E$6:$E$2288,B118) -> 0 | J118: =+SUMIFS('Salary sheet'!$AR$6:$AR$2288,'Salary sheet'!$F$6:$F$2288,C118,'Salary sheet'!$E$6:$E$2288,B118) -> 0 | K118: =SUMIFS('Salary sheet'!$AS$6:$AS$1291,'Salary sheet'!$F$6:$F$1291,'TOTAL(payment)'!C118) -> 0 | L118: =+(F118)-SUM(G118:K118) -> 7240874 | M118: =+L118/E118 -> 7240874
A119: x | E119: =SUM(E7:E118) -> 1289 | F119: =SUM(F7:F118) -> 13183558924 | G119: =SUM(G7:G118) -> 998000257 | H119: =SUM(H7:H118) -> 52434900 | I119: =SUM(I7:I118) -> 204791188 | J119: =SUM(J7:J118) -> 568500 | K119: =SUM(K7:K118) -> 3199861 | L119: =SUM(L7:L118) -> 11924564218 | M119: =SUM(M7:M112) -> 1.2193436e+09 | N119: =+L119-(L7+'Salary sheet'!AT1292) -> 11436826043
E120: =+E119-E7 -> 1286 | F120: =+F119-F7 -> 12496594307 | G120: =+G119-G7 -> 984662257 | H120: =+H119-H7 -> 52434900 | I120: =+I119-I7 -> 11661872 | J120: =+J119-J7 -> 568500 | K120: =+K119-K7 -> 3199861 | L120: =+L119-L7 -> 11444066917 | M120: =+M119-M7 -> 1.0591778e+09
E121: =+E119-E7-E120 -> 0 | F121: =+F119-F7-F120 -> 0 | G121: =+G119-G7-G120 -> 0 | H121: =+H119-H7-H120 -> 0 | I121: =+I119-I7-I120 -> 0 | J121: =+J119-J7-J120 -> 0 | K121: =+K119-K7-K120 -> 0 | L121: =+L119-L7-L120 -> 0
K123: Bình Phước, Ngày 30 tháng 04 năm 2025
B124: Người lập / Prepare by | G124: Kiểm tra/ Checked by | K124: Giám Đốc /Director
B132: Đỗ Thị Vân | G132: Nguyễn Thị Hà | K132: Kim Dong Woo

Sheet Foreign Salary
A1: Công ty TNHH Bao Bì Cao Cấp S&K Vina | H1: 26
A2: Lô B1 -B4 KCn Minh Hưng - Hàn Quốc | V2: SK1 Box | W2: =ROUND(R8/2,0)+ROUND(R9/2,0) -> 181751969
A3: H. Chơn Thành - Bình Phước | V3: SK1 Bag | W3: =+(R9+R8)-W2 -> 181751968
V4: SK2 | W4: =+R10 -> 116993364
A5: BẢNG LƯƠNG THÁNG 04 NĂM 2025 PAY-SHEET OF SALARY APR 2025 | W5: =+W4+W2+W3 -> 480497301
A6: Exchange Rate : 26,115 VND/USD | L6: 26115
A7: Stt No. | B7: Họ và tên Name | C7: Tên người thụ hưởng Beneficiary Name | D7: English name | E7: Fac | F7: Lương cơ bản Basic Salary (USD) | G7: Lương cơ bản Basic Salary (VND) | H7: Ngày công thực tế Actual Workday | I7: Lương cơ bản Basic Salary (USD) | J7: Month | K7: 13Th month bonus | L7: Lương CB Gross Salary VND | M7: BHXH,YT (9.5%) Insurance | N7: Nha o | O7: TNTT | P7: Thuế TNCN Personal income Tax | Q7: Advance | R7: Tiền thực lãnh Net salary VND | S7: Tiền thực lãnh Net salary USD (Paid) | T7: Contract salary | U7: Note
A8: 1 | B8: KIM DONG WOO | C8: KIM DONG WOO | D8: Mr DW | E8: FACTORY O | F8: 10300 | G8: =+F8*$L$6 -> 268984500 | H8: 26 | I8: =+F8/$H$1*H8 -> 10300 | L8: =ROUND((((K8+I8)*$L$6)),0) -> 268984500 | M8: =2340000*20*9.5% -> 4446000 | O8: =L8+N8-M8-11000000 -> 253538500 | P8: =ROUND(35%*O8-9850000,0) -> 78888475 | R8: =ROUND(L8-P8-M8-Q8,0) -> 185650025 | S8: =ROUND(R8/$L$6,2) -> 7108.94 | U8: SK1 Bag/Box
A9: 2 | B9: KIM JE MIN | C9: KIM JE MIN | D9: Mr JM | E9: FACTORY O | F9: 9750 | G9: =+F9*$L$6 -> 254621250 | H9: 26 | I9: =+F9/$H$1*H9 -> 9750 | L9: =ROUND((((K9+I9)*$L$6)),0) -> 254621250 | M9: =2340000*20*9.5% -> 4446000 | O9: =L9+N9-M9-11000000-4400000 -> 234775250 | P9: =ROUND(35%*O9-9850000,0) -> 72321338 | R9: =ROUND(L9-P9-M9-Q9,0) -> 177853912 | S9: =ROUND(R9/$L$6,2) -> 6810.41 | U9: SK1 Bag/Box | V9: ĐK 1 Người phụ thuộc từ tháng 10/2024
A10: 3 | B10: YUE FAMENG | C10: YUE FAMENG | D10: Mr Happy | E10: FACTORY H | F10: 6505.58 | G10: =+F10*$L$6 -> 1.6989322e+08 | H10: 25 | I10: =+F10/$H$1*H10 -> 6255.3654 | L10: =ROUND((((K10+I10)*$L$6)),0) -> 163358867 | M10: =2340000*20*9.5% -> 4446000 | O10: =L10+N10-M10-11000000 -> 147912867 | P10: =ROUND(35%*O10-9850000,0) -> 41919503 | R10: =ROUND(L10-P10-M10-Q10,0) -> 116993364 | S10: =ROUND(R10/$L$6,2) -> 4479.93 | U10: SK2
A11: TOTAL | F11: =SUM(F8:F10) -> 26555.58 | G11: =SUM(G8:G10) -> 6.9349897e+08 | H11: =SUM(H8:H10) -> 77 | I11: =SUM(I8:I10) -> 26305.365 | J11: =SUM(J8:J10) -> 0 | K11: =SUM(K8:K10) -> 0 | L11: =SUM(L8:L10) -> 686964617 | M11: =SUM(M8:M10) -> 13338000 | ... S11: =SUM(S8:S10) -> 18399.28
P14: =+'TOTAL(payment)'!K123 -> Bình Phước, Ngày 30 tháng 04 năm 2025
B15: Người lập / Prepare by | H15: Kiểm tra/ Checked by | P15: Giám Đốc /Director
B23: Đỗ Thị Vân | H23: Nguyễn Thị Hà | P23: Kim Dong Woo

Sheet Salary sheet
M2: 26
A3: BẢNG LƯƠNG THÁNG 04 NĂM 2025 PAY - SHEET OF APR 2025
A4: TT No. | B4: Mã thẻ Code | C4: Họ và tên Name | D4: Ngày vào Entry day | F4: Bộ phận Dep | G4: Title/ Chức danh | H4: Lương hợp đồng Contract salary | M4: Ngày làm việc thực tế Actual Working day | O4: Nghỉ có hưởng lương Paid leave | Q4: Ca đêm extra pay for night work + 30%) | S4: Lương, thưởng và các khoản hỗ trợ Salary, bonus, support fee | AG4: Cộng Total | AH4: Tăng ca Overtime | AN4: Tổng thu nhập Total Gross Salary | AO4: Khấu trừ Reduction | AT4: Tiền thực lãnh Net Salary | AU4: Ký nhận Signature | AW4: Tên TK | AX4: Số TK
E5: Fac | H5: Cơ bản Basic salary | I5: Trách nhiệm Responsibility | J5: Phụ cấp NNĐH Hazadouse allowance (>=5% of basic salary) | K5: Phụ cấp chức danh/Title Allowance | L5: Cộng Total | M5: Ngày công Day | N5: Lương CB + trách nhiệm Basic Salary + Responsibility | O5: Ngày công Day | P5: Lương CB + trách nhiệm Basic Salary + Responsibility | Q5: Giờ công Hour | R5: Lương CB + trách nhiệm Basic Salary + Responsibility | S5: Lương CB + trách nhiệm Basic salary + Responsibility | T5: Điện thoại, Telephone fee | U5: Tiền cơm Meal Allowance | V5: Hỗ trợ xăng + nhà trọ, Mileage, house | W5: Thưởng chuyên cần Diligent Bonus | X5: Phụ cấp PCCC PCCC / ATVSV allowance (30% of government basic salary and safety - hygency team) | Y5: Thưởng ABC ABC Bonus | Z5: Thưởng năng suất Production bonus | AA5: Ngày phép | AB5: Phép năm Annual Leave | AC5: Con nhỏ Support for baby (1-6) | AD5: Bảo hiểm, thất nghiệp Additional salary , insurance, Unempl-oyment Benefit, Bù Lương, Công Tác phí | AE5: Phụ cấp Phụ Nữ Menstruation allowance | AF5: 13Th Month Bonus | AH5: 1.5 | AI5: 2 | AJ5: 2.1 | AK5: 2.7 | AL5: 3 | AM5: Tổng tiền Amount | AO5: BHXH +YT, +TN Insurance | AP5: KPCĐ Union Dues | AQ5: Personal Income Tax Thuế TNCN | AR5: Đồng phục Uniform | AS5: Advance Chênh lệch HĐ/ Biên bản Paid | AY5: =+IF(B5="SK2","SK2",IF(B5="FACTORY A","SK1 Box",IF(B5="FACTORY D","SK1 Bag","Chia"))) -> Chia | BA5: =+IF(AY5="SK1 Box","Box",IF(AY5="Seaman","Seaman","Bag")) -> Bag
A6: =SUBTOTAL(3,B$6:B6) -> 0 | B6: C0873 | C6: Trần Thị Kim Phấn | D6: 39707 | E6: FACTORY A | F6: P6 - C.Box Assembly | G6: Box Positioning worker | H6: 5931000 | I6: 200000 | J6: 0 | K6: 0 | L6: =SUM(H6:K6) -> 6131000 | M6: 24 | N6: =ROUND((H6+I6+J6+K6)/IF($M$2>26,26,$M$2)*M6,0) -> 5659385 | O6: 2 | P6: =ROUND((H6+I6+J6+K6)/IF($M$2>26,26,$M$2)*O6,0) -> 471615 | Q6: 0 | R6: =IF(M6>0,ROUND(N6/IF(M6>26,26,M6)/8*Q6*30%,0),0) -> 0 | S6: =N6+P6+R6 -> 6131000 | T6: 0 | U6: 0 | V6: 200000 | W6: 500000 | X6: 0 | Y6: 0 | Z6: 188548 | AC6: 0 | AD6: 0 | AE6: 44213.945 | AG6: =ROUND(SUM(S6:AF6)-AA6,0) -> 7063762 | AH6: 28 | AI6: 0 | AJ6: 0 | AK6: 0 | AL6: 0 | AM6: =ROUND((N6/IF(M6>26,26,M6)/8*(AH6*$AH$5+AI6*$AI$5+AJ6*$AJ$5+AK6*$AK$5+AL6*$AL$5)),0) -> 1237990 | AN6: =ROUND(AG6+AM6,0) -> 8301752 | AO6: 643755 | AP6: 44100 | AQ6: =+VLOOKUP($B6,[1]Sheet1!$C$15:$BW$1300,52,0) -> 0 | AR6: 0 | AS6: 0 | AT6: =+ROUND(SUM(AN6:AN6)-SUM(AO6:AS6),0) -> 7613897 | AW6: TRAN THI KIM PHAN | AX6: 050040964964 | AY6: SK1 Box | AZ6: 622 | BA6: =+IF(AY6="SK1 Box","Box",IF(AY6="Seaman","Seaman","Bag")) -> Box
A7: =SUBTOTAL(3,B$6:B7) -> 0 | B7: C1007 | C7: Nguyễn Thị Hướng | D7: 39707 | E7: FACTORY A | F7: P6 - C.Box Assembly | G7: Box Positioning worker | H7: 5931000 | I7: 200000 | J7: 0 | K7: 300000 | L7: =SUM(H7:K7) -> 6431000 | M7: 23.8 | N7: =ROUND((H7+I7+J7+K7)/IF($M$2>26,26,$M$2)*M7,0) -> 5886838 | O7: 2 | P7: =ROUND((H7+I7+J7+K7)/IF($M$2>26,26,$M$2)*O7,0) -> 494692 | Q7: 0 | R7: =IF(M7>0,ROUND(N7/IF(M7>26,26,M7)/8*Q7*30%,0),0) -> 0 | S7: =N7+P7+R7 -> 6381530 | T7: 0 | U7: 0 | V7: 200000 | W7: 500000 | X7: 0 | Y7: 400000 | Z7: 603480 | AC7: 0 | AD7: 0 | AE7: 46377.4 | AG7: =ROUND(SUM(S7:AF7)-AA7,0) -> 8131387 | AH7: 28 | AI7: 0 | AJ7: 0 | AK7: 0 | AL7: 0 | AM7: =ROUND((N7/IF(M7>26,26,M7)/8*(AH7*$AH$5+AI7*$AI$5+AJ7*$AJ$5+AK7*$AK$5+AL7*$AL$5)),0) -> 1298567 | AN7: =ROUND(AG7+AM7,0) -> 9429954 | AO7: 675255 | AP7: 44100 | AQ7: =+VLOOKUP($B7,[1]Sheet1!$C$15:$BW$1300,52,0) -> 0 | AR7: 0 | AS7: 0 | AT7: =+ROUND(SUM(AN7:AN7)-SUM(AO7:AS7),0) -> 8710599 | AW7: NGUYEN THI HUONG | AX7: 050040850950 | AY7: SK1 Box | AZ7: 622 | BA7: =+IF(AY7="SK1 Box","Box",IF(AY7="Seaman","Seaman","Bag")) -> Box
A8: =SUBTOTAL(3,B$6:B8) -> 0 | B8: C1009 | C8: Hồ Thị Nga | D8: 39707 | E8: FACTORY A | F8: P6 - C.Box Assembly | G8: Box Positioning worker | H8: 5931000 | I8: 200000 | J8: 0 | K8: 0 | L8: =SUM(H8:K8) -> 6131000 | M8: 24 | N8: =ROUND((H8+I8+J8+K8)/IF($M$2>26,26,$M$2)*M8,0) -> 5659385 | O8: 2 | P8: =ROUND((H8+I8+J8+K8)/IF($M$2>26,26,$M$2)*O8,0) -> 471615 | Q8: 0 | R8: =IF(M8>0,ROUND(N8/IF(M8>26,26,M8)/8*Q8*30%,0),0) -> 0 | S8: =N8+P8+R8 -> 6131000 | T8: 0 | U8: 0 | V8: 200000 | W8: 500000 | X8: 0 | Y8: 400000 | Z8: 600597 | AC8: 0 | AD8: 0 | AE8: 44213.945 | AG8: =ROUND(SUM(S8:AF8)-AA8,0) -> 7875811 | AH8: 28 | AI8: 0 | AJ8: 0 | AK8: 0 | AL8: 0 | AM8: =ROUND((N8/IF(M8>26,26,M8)/8*(AH8*$AH$5+AI8*$AI$5+AJ8*$AJ$5+AK8*$AK$5+AL8*$AL$5)),0) -> 1237990 | AN8: =ROUND(AG8+AM8,0) -> 9113801 | AO8: 643755 | AP8: 44100 | AQ8: =+VLOOKUP($B8,[1]Sheet1!$C$15:$BW$1300,52,0) -> 0 | AR8: 0 | AS8: 0 | AT8: =+ROUND(SUM(AN8:AN8)-SUM(AO8:AS8),0) -> 8425946 | AW8: HO THI NGA | AX8: 050040952974 | AY8: SK1 Box | AZ8: 622 | BA8: =+IF(AY8="SK1 Box","Box",IF(AY8="Seaman","Seaman","Bag")) -> Box
A9: =SUBTOTAL(3,B$6:B9) -> 0 | B9: C10454 | C9: Trần Thị Liên | D9: 43556 | E9: FACTORY A | F9: P6 - C.Box Assembly | G9: Box Positioning worker | H9: 5931000 | I9: 200000 | J9: 0 | K9: 0 | L9: =SUM(H9:K9) -> 6131000 | M9: 24 | N9: =ROUND((H9+I9+J9+K9)/IF($M$2>26,26,$M$2)*M9,0) -> 5659385 | O9: 2 | P9: =ROUND((H9+I9+J9+K9)/IF($M$2>26,26,$M$2)*O9,0) -> 471615 | Q9: 0 | R9: =IF(M9>0,ROUND(N9/IF(M9>26,26,M9)/8*Q9*30%,0),0) -> 0 | S9: =N9+P9+R9 -> 6131000 | T9: 0 | U9: 0 | V9: 200000 | W9: 500000 | X9: 0 | Y9: 400000 | Z9: 606304 | AC9: 0 | AD9: 0 | AE9: 44213.945 | AG9: =ROUND(SUM(S9:AF9)-AA9,0) -> 7881518 | AH9: 28 | AI9: 0 | AJ9: 0 | AK9: 0 | AL9: 0 | AM9: =ROUND((N9/IF(M9>26,26,M9)/8*(AH9*$AH$5+AI9*$AI$5+AJ9*$AJ$5+AK9*$AK$5+AL9*$AL$5)),0) -> 1237990 | AN9: =ROUND(AG9+AM9,0) -> 9119508 | AO9: 643755 | AP9: 44100 | AQ9: =+VLOOKUP($B9,[1]Sheet1!$C$15:$BW$1300,52,0) -> 0 | AR9: 0 | AS9: 0 | AT9: =+ROUND(SUM(AN9:AN9)-SUM(AO9:AS9),0) -> 8431653 | AW9: TRAN THI LIEN | AX9: 050104743444 | AY9: SK1 Box | AZ9: 622 | BA9: =+IF(AY9="SK1 Box","Box",IF(AY9="Seaman","Seaman","Bag")) -> Box
A10: =SUBTOTAL(3,B$6:B10) -> 0 | B10: C10664 | C10: Nguyễn Hoài Hận | D10: 43595 | E10: FACTORY A | F10: P6 - C.Box Assembly | G10: Box Positioning worker | H10: 5931000 | I10: 200000 | J10: 0 | K10: 0 | L10: =SUM(H10:K10) -> 6131000 | M10: 23.7 | N10: =ROUND((H10+I10+J10+K10)/IF($M$2>26,26,$M$2)*M10,0) -> 5588642 | O10: 2 | P10: =ROUND((H10+I10+J10+K10)/IF($M$2>26,26,$M$2)*O10,0) -> 471615 | Q10: 0 | R10: =IF(M10>0,ROUND(N10/IF(M10>26,26,M10)/8*Q10*30%,0),0) -> 0 | S10: =N10+P10+R10 -> 6060257 | T10: 0 | U10: 0 | V10: 200000 | W10: 500000 | X10: 0 | Y10: 400000 | Z10: 603480 | AC10: 0 | AD10: 0 | AE10: 0 | AG10: =ROUND(SUM(S10:AF10)-AA10,0) -> 7763737 | AH10: 28 | AI10: 0 | AJ10: 0 | AK10: 0 | AL10: 0 | AM10: =ROUND((N10/IF(M10>26,26,M10)/8*(AH10*$AH$5+AI10*$AI$5+AJ10*$AJ$5+AK10*$AK$5+AL10*$AL$5)),0) -> 1237990 | AN10: =ROUND(AG10+AM10,0) -> 9001727 | AO10: 643755 | AP10: 44100 | AQ10: =+VLOOKUP($B10,[1]Sheet1!$C$15:$BW$1300,52,0) -> 0 | AR10: 0 | AS10: 0 | AT10: =+ROUND(SUM(AN10:AN10)-SUM(AO10:AS10),0) -> 8313872 | AW10: NGUYEN HOAI HAN | AX10: 050073573855 | AY10: SK1 Box | AZ10: 622 | BA10: =+IF(AY10="SK1 Box","Box",IF(AY10="Seaman","Seaman","Bag")) -> Box
A11: =SUBTOTAL(3,B$6:B11) -> 0 | B11: C10665 | C11: Lê Thị Kiều Loan | D11: 43595 | E11: FACTORY A | F11: P6 - C.Box Assembly | G11: Normal worker | H11: 5931000 | I11: 0 | J11: 0 | K11: 0 | L11: =SUM(H11:K11) -> 5931000 | M11: 24 | N11: =ROUND((H11+I11+J11+K11)/IF($M$2>26,26,$M$2)*M11,0) -> 5474769 | O11: 2 | P11: =ROUND((H11+I11+J11+K11)/IF($M$2>26,26,$M$2)*O11,0) -> 456231 | Q11: 0 | R11: =IF(M11>0,ROUND(N11/IF(M11>26,26,M11)/8*Q11*30%,0),0) -> 0 | S11: =N11+P11+R11 -> 5931000 | T11: 0 | U11: 0 | V11: 200000 | W11: 500000 | X11: 0 | Y11: 300000 | Z11: 606304 | AC11: 0 | AD11: 0 | AE11: 42771.633 | AG11: =ROUND(SUM(S11:AF11)-AA11,0) -> 7580076 | AH11: 24 | AI11: 0 | AJ11: 0 | AK11: 0 | AL11: 0 | AM11: =ROUND((N11/IF(M11>26,26,M11)/8*(AH11*$AH$5+AI11*$AI$5+AJ11*$AJ$5+AK11*$AK$5+AL11*$AL$5)),0) -> 1026519 | AN11: =ROUND(AG11+AM11,0) -> 8606595 | AO11: 622755 | AP11: 44100 | AQ11: =+VLOOKUP($B11,[1]Sheet1!$C$15:$BW$1300,52,0) -> 0 | AR11: 0 | AS11: 0 | AT11: =+ROUND(SUM(AN11:AN11)-SUM(AO11:AS11),0) -> 7939740 | AW11: LE THI KIEU LOAN | AX11: 050106514035 | AY11: SK1 Box | AZ11: 622 | BA11: =+IF(AY11="SK1 Box","Box",IF(AY11="Seaman","Seaman","Bag")) -> Box
A12: =SUBTOTAL(3,B$6:B12) -> 0 | B12: C1074 | C12: Phan Thị Thanh Tâm | D12: 39715 | E12: FACTORY A | F12: P6 - C.Box Assembly | G12: Box Positioning worker | H12: 5931000 | I12: 200000 | J12: 0 | K12: 0 | L12: =SUM(H12:K12) -> 6131000 | M12: 23.9 | N12: =ROUND((H12+I12+J12+K12)/IF($M$2>26,26,$M$2)*M12,0) -> 5635804 | O12: 2 | P12: =ROUND((H12+I12+J12+K12)/IF($M$2>26,26,$M$2)*O12,0) -> 471615 | Q12: 0 | R12: =IF(M12>0,ROUND(N12/IF(M12>26,26,M12)/8*Q12*30%,0),0) -> 0 | S12: =N12+P12+R12 -> 6107419 | T12: 0 | U12: 0 | V12: 200000 | W12: 500000 | X12: 0 | Y12: 400000 | Z12: 590658 | AC12: 100000 | AD12: 0 | AE12: 44213.944 | AG12: =ROUND(SUM(S12:AF12)-AA12,0) -> 7942291 | AH12: 28 | AI12: 0 | AJ12: 0 | AK12: 0 | AL12: 0 | AM12: =ROUND((N12/IF(M12>26,26,M12)/8*(AH12*$AH$5+AI12*$AI$5+AJ12*$AJ$5+AK12*$AK$5+AL12*$AL$5)),0) -> 1237990 | AN12: =ROUND(AG12+AM12,0) -> 9180281 | AO12: 643755 | AP12: 44100 | AQ12: =+VLOOKUP($B12,[1]Sheet1!$C$15:$BW$1300,52,0) -> 0 | AR12: 0 | AS12: 0 | AT12: =+ROUND(SUM(AN12:AN12)-SUM(AO12:AS12),0) -> 8492426 | AW12: PHAN THI THANH TAM | AX12: 050040932884 | AY12: SK1 Box | AZ12: 622 | BA12: =+IF(AY12="SK1 Box","Box",IF(AY12="Seaman","Seaman","Bag")) -> Box
A13: =SUBTOTAL(3,B$6:B13) -> 0 | B13: C11208 | C13: Lê Thị Bích Linh | D13: 43684 | E13: FACTORY A | F13: P6 - C.Box Assembly | G13: Box Positioning worker | H13: 5931000 | I13: 200000 | J13: 0 | K13: 0 | L13: =SUM(H13:K13) -> 6131000 | M13: 22.6 | N13: =ROUND((H13+I13+J13+K13)/IF($M$2>26,26,$M$2)*M13,0) -> 5329254 | O13: 3 | P13: =ROUND((H13+I13+J13+K13)/IF($M$2>26,26,$M$2)*O13,0) -> 707423 | Q13: 0 | R13: =IF(M13>0,ROUND(N13/IF(M13>26,26,M13)/8*Q13*30%,0),0) -> 0 | S13: =N13+P13+R13 -> 6036677 | T13: 0 | U13: 0 | V13: 200000 | W13: 500000 | X13: 0 | Y13: 400000 | Z13: 558491 | AC13: 0 | AD13: 0 | AE13: 44213.944 | AG13: =ROUND(SUM(S13:AF13)-AA13,0) -> 7739382 | AH13: 24 | AI13: 0 | AJ13: 0 | AK13: 0 | AL13: 0 | AM13: =ROUND((N13/IF(M13>26,26,M13)/8*(AH13*$AH$5+AI13*$AI$5+AJ13*$AJ$5+AK13*$AK$5+AL13*$AL$5)),0) -> 1061135 | AN13: =ROUND(AG13+AM13,0) -> 8800517 | AO13: 643755 | AP13: 44100 | AQ13: =+VLOOKUP($B13,[1]Sheet1!$C$15:$BW$1300,52,0) -> 0 | AR13: 0 | AS13: 0 | AT13: =+ROUND(SUM(AN13:AN13)-SUM(AO13:AS13),0) -> 8112662 | AW13: LE THI BICH LINH | AX13: 050111434058 | AY13: SK1 Box | AZ13: 622 | BA13: =+IF(AY13="SK1 Box","Box",IF(AY13="Seaman","Seaman","Bag")) -> Box
A14: =SUBTOTAL(3,B$6:B14) -> 0 | B14: C11863 | C14: Trần Hải Nam | D14: 43874 | E14: FACTORY A | F14: P6 - C.Box Assembly | G14: Stickers Box worker | H14: 5931000 | I14: 200000 | J14: 0 | K14: 0 | L14: =SUM(H14:K14) -> 6131000 | M14: 24 | N14: =ROUND((H14+I14+J14+K14)/IF($M$2>26,26,$M$2)*M14,0) -> 5659385 | O14: 2 | P14: =ROUND((H14+I14+J14+K14)/IF($M$2>26,26,$M$2)*O14,0) -> 471615 | Q14: 0 | R14: =IF(M14>0,ROUND(N14/IF(M14>26,26,M14)/8*Q14*30%,0),0) -> 0 | S14: =N14+P14+R14 -> 6131000 | T14: 0 | U14: 0 | V14: 200000 | W14: 500000 | X14: 0 | Y14: 400000 | Z14: 906304 | AC14: 0 | AD14: 0 | AE14: 0 | AG14: =ROUND(SUM(S14:AF14)-AA14,0) -> 8137304 | AH14: 28 | AI14: 0 | AJ14: 0 | AK14: 0 | AL14: 0 | AM14: =ROUND((N14/IF(M14>26,26,M14)/8*(AH14*$AH$5+AI14*$AI$5+AJ14*$AJ$5+AK14*$AK$5+AL14*$AL$5)),0) -> 1237990 | AN14: =ROUND(AG14+AM14,0) -> 9375294 | AO14: 643755 | AP14: 44100 | AQ14: =+VLOOKUP($B14,[1]Sheet1!$C$15:$BW$1300,52,0) -> 0 | AR14: 0 | AS14: 0 | AT14: =+ROUND(SUM(AN14:AN14)-SUM(AO14:AS14),0) -> 8687439 | AW14: TRAN HAI NAM | AX14: 050116653033 | AY14: SK1 Box | AZ14: 622 | BA14: =+IF(AY14="SK1 Box","Box",IF(AY14="Seaman","Seaman","Bag")) -> Box
A15: =SUBTOTAL(3,B$6:B15) -> 0 | B15: C1271 | C15: Hồ Thị Nga | D15: 39766 | E15: FACTORY A | F15: P6 - C.Box Assembly | G15: Box Positioning worker | H15: 5931000 | I15: 200000 | J15: 0 | K15: 0 | L15: =SUM(H15:K15) -> 6131000 | M15: 24 | N15: =ROUND((H15+I15+J15+K15)/IF($M$2>26,26,$M$2)*M15,0) -> 5659385 | O15: 2 | P15: =ROUND((H15+I15+J15+K15)/IF($M$2>26,26,$M$2)*O15,0) -> 471615 | Q15: 0 | R15: =IF(M15>0,ROUND(N15/IF(M15>26,26,M15)/8*Q15*30%,0),0) -> 0 | S15: =N15+P15+R15 -> 6131000 | T15: 0 | U15: 0 | V15: 200000 | W15: 500000 | X15: 0 | Y15: 0 | Z15: 181391 | AC15: 0 | AD15: 0 | AE15: 44213.945 | AG15: =ROUND(SUM(S15:AF15)-AA15,0) -> 7056605 | AH15: 28 | AI15: 0 | AJ15: 0 | AK15: 0 | AL15: 0 | AM15: =ROUND((N15/IF(M15>26,26,M15)/8*(AH15*$AH$5+AI15*$AI$5+AJ15*$AJ$5+AK15*$AK$5+AL15*$AL$5)),0) -> 1237990 | AN15: =ROUND(AG15+AM15,0) -> 8294595 | AO15: 643755 | AP15: 44100 | AQ15: =+VLOOKUP($B15,[1]Sheet1!$C$15:$BW$1300,52,0) -> 0 | AR15: 0 | AS15: 0 | AT15: =+ROUND(SUM(AN15:AN15)-SUM(AO15:AS15),0) -> 7606740 | AW15: HO THI NGA | AX15: 050040933910 | AY15: SK1 Box | AZ15: 622 | BA15: =+IF(AY15="SK1 Box","Box",IF(AY15="Seaman","Seaman","Bag")) -> Box
A16: =SUBTOTAL(3,B$6:B16) -> 0 | B16: C12741 | C16: Nguyễn Thị Trúc Ly | D16: 44064 | E16: FACTORY A | F16: P6 - C.Box Assembly | G16: Box Positioning worker | H16: 5931000 | I16: 200000 | J16: 0 | K16: 0 | L16: =SUM(H16:K16) -> 6131000 | M16: 24 | N16: =ROUND((H16+I16+J16+K16)/IF($M$2>26,26,$M$2)*M16,0) -> 5659385 | O16: 2 | P16: =ROUND((H16+I16+J16+K16)/IF($M$2>26,26,$M$2)*O16,0) -> 471615 | Q16: 0 | R16: =IF(M16>0,ROUND(N16/IF(M16>26,26,M16)/8*Q16*30%,0),0) -> 0 | S16: =N16+P16+R16 -> 6131000 | T16: 0 | U16: 0 | V16: 200000 | W16: 500000 | X16: 0 | Y16: 400000 | Z16: 603480 | AC16: 200000 | AD16: 0 | AE16: 44213.945 | AG16: =ROUND(SUM(S16:AF16)-AA16,0) -> 8078694 | AH16: 28 | AI16: 0 | AJ16: 0 | AK16: 0 | AL16: 0 | AM16: =ROUND((N16/IF(M16>26,26,M16)/8*(AH16*$AH$5+AI16*$AI$5+AJ16*$AJ$5+AK16*$AK$5+AL16*$AL$5)),0) -> 1237990 | AN16: =ROUND(AG16+AM16,0) -> 9316684 | AO16: 643755 | AP16: 44100 | AQ16: =+VLOOKUP($B16,[1]Sheet1!$C$15:$BW$1300,52,0) -> 0 | AR16: 0 | AS16: 0 | AT16: =+ROUND(SUM(AN16:AN16)-SUM(AO16:AS16),0) -> 8628829 | AW16: NGUYEN THI TRUC LY | AX16: 050114056372 | AY16: SK1 Box | AZ16: 622 | BA16: =+IF(AY16="SK1 Box","Box",IF(AY16="Seaman","Seaman","Bag")) -> Box
A17: =SUBTOTAL(3,B$6:B17) -> 0 | B17: C12781 | C17: Lê Thị Ánh Thương | D17: 44069 | E17: FACTORY A | F17: P6 - C.Box Assembly | G17: Technician worker | H17: 5931000 | I17: 1100000 | J17: 0 | K17: 0 | L17: =SUM(H17:K17) -> 7031000 | M17: 23.7 | N17: =ROUND((H17+I17+J17+K17)/IF($M$2>26,26,$M$2)*M17,0) -> 6409027 | O17: 2 | P17: =ROUND((H17+I17+J17+K17)/IF($M$2>26,26,$M$2)*O17,0) -> 540846 | Q17: 0 | R17: =IF(M17>0,ROUND(N17/IF(M17>26,26,M17)/8*Q17*30%,0),0) -> 0 | S17: =N17+P17+R17 -> 6949873 | T17: 0 | U17: 0 | V17: 200000 | W17: 500000 | X17: 0 | Y17: 400000 | Z17: 585715 | AC17: 100000 | AD17: 0 | AE17: 50704.328 | AG17: =ROUND(SUM(S17:AF17)-AA17,0) -> 8786292 | AH17: 28 | AI17: 0 | AJ17: 0 | AK17: 0 | AL17: 0 | AM17: =ROUND((N17/IF(M17>26,26,M17)/8*(AH17*$AH$5+AI17*$AI$5+AJ17*$AJ$5+AK17*$AK$5+AL17*$AL$5)),0) -> 1419721 | AN17: =ROUND(AG17+AM17,0) -> 10206013 | AO17: 738255 | AP17: 44100 | AQ17: =+VLOOKUP($B17,[1]Sheet1!$C$15:$BW$1300,52,0) -> 0 | AR17: 0 | AS17: 0 | AT17: =+ROUND(SUM(AN17:AN17)-SUM(AO17:AS17),0) -> 9423658 | AW17: LE THI ANH THUONG | AX17: 050040933661 | AY17: SK1 Box | AZ17: 622 | BA17: =+IF(AY17="SK1 Box","Box",IF(AY17="Seaman","Seaman","Bag")) -> Box
... A261: =SUBTOTAL(3,B$6:B261) -> 0 | B261: C11922 | C261: Nguyễn Thị Hồng Thuận | D261: 43878 | E261: FACTORY A | F261: P6 - Production Office | G261: Factory vice manager | H261: 7643000 | I261: 7300000 | J261: 0 | K261: 0 | L261: =SUM(H261:K261) -> 14943000 | M261: 23.6 | N261: =ROUND((H261+I261+J261+K261)/IF($M$2>26,26,$M$2)*M261,0) -> 13563646 | O261: 2 | P261: =ROUND((H261+I261+J261+K261)/IF($M$2>26,26,$M$2)*O261,0) -> 1149462 | Q261: 0 | R261: =IF(M261>0,ROUND(N261/IF(M261>26,26,M261)/8*Q261*30%,0),0) -> 0 | S261: =N261+P261+R261 -> 14713108 | T261: 0 | U261: 0 | V261: 200000 | W261: 500000 | X261: 0 | Y261: 400000 | Z261: 0 | AC261: 0 | AD261: 0 | AE261: 107762.02 | AG261: =ROUND(SUM(S261:AF261)-AA261,0) -> 15920870 | AH261: 28 | AI261: 0 | AJ261: 0 | AK261: 0 | AL261: 0 | AM261: =ROUND((N261/IF(M261>26,26,M261)/8*(AH261*$AH$5+AI261*$AI$5+AJ261*$AJ$5+AK261*$AK$5+AL261*$AL$5)),0) -> 3017337 | AN261: =ROUND(AG261+AM261,0) -> 18938207 | AO261: 1569015 | AP261: 44100 | AQ261: =+VLOOKUP($B261,[1]Sheet1!$C$15:$BW$1300,52,0) -> 0 | AR261: 0 | AS261: 0 | AT261: =+ROUND(SUM(AN261:AN261)-SUM(AO261:AS261),0) -> 17325092 | AW261: NGUYEN THI HONG THUAN | AX261: 050040933090 | AY261: SK1 Box | AZ261: 627 | BA261: =+IF(AY261="SK1 Box","Box",IF(AY261="Seaman","Seaman","Bag")) -> Box
A262: =SUBTOTAL(3,B$6:B262) -> 0 | B262: C3402 | C262: Đoàn Thị Hiếu Loan | D262: 40589 | E262: FACTORY A | F262: P6 - Production Office | G262: Factory manager | H262: 13094000 | I262: 11306000 | J262: 0 | K262: 0 | L262: =SUM(H262:K262) -> 24400000 | M262: 24 | N262: =ROUND((H262+I262+J262+K262)/IF($M$2>26,26,$M$2)*M262,0) -> 22523077 | O262: 2 | P262: =ROUND((H262+I262+J262+K262)/IF($M$2>26,26,$M$2)*O262,0) -> 1876923 | Q262: 0 | R262: =IF(M262>0,ROUND(N262/IF(M262>26,26,M262)/8*Q262*30%,0),0) -> 0 | S262: =N262+P262+R262 -> 24400000 | T262: 150000 | U262: 0 | V262: 0 | W262: 0 | X262: 0 | Y262: 0 | Z262: 0 | AC262: 0 | AD262: 0 | AE262: 175961.54 | AG262: =ROUND(SUM(S262:AF262)-AA262,0) -> 24725962 | AH262: 0 | AI262: 0 | AJ262: 0 | AK262: 0 | AL262: 0 | AM262: =ROUND((N262/IF(M262>26,26,M262)/8*(AH262*$AH$5+AI262*$AI$5+AJ262*$AJ$5+AK262*$AK$5+AL262*$AL$5)),0) -> 0 | AN262: =ROUND(AG262+AM262,0) -> 24725962 | AO262: 2562000 | AP262: 44100 | AQ262: =+VLOOKUP($B262,[1]Sheet1!$C$15:$BW$1300,52,0) -> 115698 | AR262: 0 | AS262: 0 | AT262: =+ROUND(SUM(AN262:AN262)-SUM(AO262:AS262),0) -> 22004164 | AW262: DOAN THI HIEU LOAN | AX262: 050153746262 | AY262: SK1 Box | AZ262: 627 | BA262: Manager
A263: =SUBTOTAL(3,B$6:B263) -> 0 | B263: C5606 | C263: Nguyễn Thị Liên | D263: 41369 | E263: FACTORY A | F263: P6 - Production Office | G263: Factory assistant | H263: 6576000 | I263: 2000000 | J263: 0 | K263: 0 | L263: =SUM(H263:K263) -> 8576000 | M263: 23.8 | N263: =ROUND((H263+I263+J263+K263)/IF($M$2>26,26,$M$2)*M263,0) -> 7850338 | O263: 2 | P263: =ROUND((H263+I263+J263+K263)/IF($M$2>26,26,$M$2)*O263,0) -> 659692 | Q263: 0 | R263: =IF(M263>0,ROUND(N263/IF(M263>26,26,M263)/8*Q263*30%,0),0) -> 0 | S263: =N263+P263+R263 -> 8510030 | T263: 0 | U263: 0 | V263: 200000 | W263: 500000 | X263: 0 | Y263: 400000 | Z263: 411209 | AC263: 0 | AD263: 0 | AE263: 61846.15 | AG263: =ROUND(SUM(S263:AF263)-AA263,0) -> 10083085 | AH263: 28 | AI263: 0 | AJ263: 0 | AK263: 0 | AL263: 0 | AM263: =ROUND((N263/IF(M263>26,26,M263)/8*(AH263*$AH$5+AI263*$AI$5+AJ263*$AJ$5+AK263*$AK$5+AL263*$AL$5)),0) -> 1731692 | AN263: =ROUND(AG263+AM263,0) -> 11814777 | AO263: 900480 | AP263: 44100 | AQ263: =+VLOOKUP($B263,[1]Sheet1!$C$15:$BW$1300,52,0) -> 0 | AR263: 0 | AS263: 0 | AT263: =+ROUND(SUM(AN263:AN263)-SUM(AO263:AS263),0) -> 10870197 | AW263: NGUYEN THI LIEN | AX263: 050040965057 | AY263: SK1 Box | AZ263: 627 | BA263: =+IF(AY263="SK1 Box","Box",IF(AY263="Seaman","Seaman","Bag")) -> Box
A264: =SUBTOTAL(3,B$6:B264) -> 0 | B264: C5841 | C264: Trần Văn Nhân | D264: 41491 | E264: FACTORY A | F264: P6 - Production Office | G264: Factory manager | H264: 15240000 | I264: 9200000 | J264: 0 | K264: 0 | L264: =SUM(H264:K264) -> 24440000 | M264: 23.7 | N264: =ROUND((H264+I264+J264+K264)/IF($M$2>26,26,$M$2)*M264,0) -> 22278000 | O264: 2 | P264: =ROUND((H264+I264+J264+K264)/IF($M$2>26,26,$M$2)*O264,0) -> 1880000 | Q264: 0 | R264: =IF(M264>0,ROUND(N264/IF(M264>26,26,M264)/8*Q264*30%,0),0) -> 0 | S264: =N264+P264+R264 -> 24158000 | T264: 691923 | U264: 0 | V264: 0 | W264: 0 | X264: 0 | Y264: 0 | Z264: 0 | AC264: 0 | AD264: 0 | AE264: 0 | AG264: =ROUND(SUM(S264:AF264)-AA264,0) -> 24849923 | AH264: 0 | AI264: 0 | AJ264: 0 | AK264: 0 | AL264: 0 | AM264: =ROUND((N264/IF(M264>26,26,M264)/8*(AH264*$AH$5+AI264*$AI$5+AJ264*$AJ$5+AK264*$AK$5+AL264*$AL$5)),0) -> 0 | AN264: =ROUND(AG264+AM264,0) -> 24849923 | AO264: 2566200 | AP264: 44100 | AQ264: =+VLOOKUP($B264,[1]Sheet1!$C$15:$BW$1300,52,0) -> 94590 | AR264: 0 | AS264: 0 | AT264: =+ROUND(SUM(AN264:AN264)-SUM(AO264:AS264),0) -> 22145033 | AW264: TRAN VAN NHAN | AX264: 050040817023 | AY264: SK1 Box | AZ264: 627 | BA264: Manager
A265: =SUBTOTAL(3,B$6:B265) -> 0 | B265: C6063 | C265: Đồng Thị Thu Hiền | D265: 41621 | E265: FACTORY A | F265: P6 - Production Office | G265: Factory vice manager | H265: 6876000 | I265: 6600000 | J265: 0 | K265: 0 | L265: =SUM(H265:K265) -> 13476000 | M265: 24 | N265: =ROUND((H265+I265+J265+K265)/IF($M$2>26,26,$M$2)*M265,0) -> 12439385 | O265: 2 | P265: =ROUND((H265+I265+J265+K265)/IF($M$2>26,26,$M$2)*O265,0) -> 1036615 | Q265: 0 | R265: =IF(M265>0,ROUND(N265/IF(M265>26,26,M265)/8*Q265*30%,0),0) -> 0 | S265: =N265+P265+R265 -> 13476000 | T265: 0 | U265: 0 | V265: 200000 | W265: 500000 | X265: 0 | Y265: 400000 | Z265: 0 | AC265: 0 | AD265: 0 | AE265: 97182.695 | AG265: =ROUND(SUM(S265:AF265)-AA265,0) -> 14673183 | AH265: 28 | AI265: 0 | AJ265: 0 | AK265: 0 | AL265: 0 | AM265: =ROUND((N265/IF(M265>26,26,M265)/8*(AH265*$AH$5+AI265*$AI$5+AJ265*$AJ$5+AK265*$AK$5+AL265*$AL$5)),0) -> 2721115 | AN265: =ROUND(AG265+AM265,0) -> 17394298 | AO265: 1414980 | AP265: 44100 | AQ265: =+VLOOKUP($B265,[1]Sheet1!$C$15:$BW$1300,52,0) -> 0 | AR265: 0 | AS265: 0 | AT265: =+ROUND(SUM(AN265:AN265)-SUM(AO265:AS265),0) -> 15935218 | AW265: DONG THI THU HIEN | AX265: 050040958301 | AY265: SK1 Box | AZ265: 627 | BA265: =+IF(AY265="SK1 Box","Box",IF(AY265="Seaman","Seaman","Bag")) -> Box
A266: =SUBTOTAL(3,B$6:B266) -> 0 | B266: C13547 | C266: Nguyễn Thị Cẩm Tiên | D266: 44270 | E266: FACTORY A | F266: P6 - QC | G266: QC Worker | H266: 5931000 | I266: 1100000 | J266: 0 | K266: 0 | L266: =SUM(H266:K266) -> 7031000 | M266: 24 | N266: =ROUND((H266+I266+J266+K266)/IF($M$2>26,26,$M$2)*M266,0) -> 6490154 | O266: 2 | P266: =ROUND((H266+I266+J266+K266)/IF($M$2>26,26,$M$2)*O266,0) -> 540846 | Q266: 0 | R266: =IF(M266>0,ROUND(N266/IF(M266>26,26,M266)/8*Q266*30%,0),0) -> 0 | S266: =N266+P266+R266 -> 7031000 | T266: 0 | U266: 0 | V266: 200000 | W266: 500000 | X266: 0 | Y266: 400000 | Z266: 400000 | AC266: 100000 | AD266: 0 | AE266: 50704.328 | AG266: =ROUND(SUM(S266:AF266)-AA266,0) -> 8681704 | AH266: 0 | AI266: 0 | AJ266: 0 | AK266: 0 | AL266: 0 | AM266: =ROUND((N266/IF(M266>26,26,M266)/8*(AH266*$AH$5+AI266*$AI$5+AJ266*$AJ$5+AK266*$AK$5+AL266*$AL$5)),0) -> 0 | AN266: =ROUND(AG266+AM266,0) -> 8681704 | AO266: 738255 | AP266: 44100 | AQ266: =+VLOOKUP($B266,[1]Sheet1!$C$15:$BW$1300,52,0) -> 0 | AR266: 0 | AS266: 0 | AT266: =+ROUND(SUM(AN266:AN266)-SUM(AO266:AS266),0) -> 7899349 | AW266: NGUYEN THI CAM TIEN | AX266: 050040965758 | AY266: SK1 Box | AZ266: 622 | BA266: =+IF(AY266="SK1 Box","Box",IF(AY266="Seaman","Seaman","Bag")) -> Box
A267: =SUBTOTAL(3,B$6:B267) -> 0 | B267: C13762 | C267: Nguyễn Thị Tuyết Ngân | D267: 44287 | E267: FACTORY A | F267: P6 - QC | G267: QC worker | H267: 5931000 | I267: 1100000 | J267: 0 | K267: 0 | L267: =SUM(H267:K267) -> 7031000 | M267: 24 | N267: =ROUND((H267+I267+J267+K267)/IF($M$2>26,26,$M$2)*M267,0) -> 6490154 | O267: 2 | P267: =ROUND((H267+I267+J267+K267)/IF($M$2>26,26,$M$2)*O267,0) -> 540846 | Q267: 0 | R267: =IF(M267>0,ROUND(N267/IF(M267>26,26,M267)/8*Q267*30%,0),0) -> 0 | S267: =N267+P267+R267 -> 7031000 | T267: 0 | U267: 0 | V267: 200000 | W267: 500000 | X267: 0 | Y267: 400000 | Z267: 500000 | AC267: 100000 | AD267: 0 | AE267: 50704.328 | AG267: =ROUND(SUM(S267:AF267)-AA267,0) -> 8781704 | AH267: 21.5 | AI267: 0 | AJ267: 0 | AK267: 0 | AL267: 0 | AM267: =ROUND((N267/IF(M267>26,26,M267)/8*(AH267*$AH$5+AI267*$AI$5+AJ267*$AJ$5+AK267*$AK$5+AL267*$AL$5)),0) -> 1090143 | AN267: =ROUND(AG267+AM267,0) -> 9871847 | AO267: 738255 | AP267: 44100 | AQ267: =+VLOOKUP($B267,[1]Sheet1!$C$15:$BW$1300,52,0) -> 0 | AR267: 0 | AS267: 0 | AT267: =+ROUND(SUM(AN267:AN267)-SUM(AO267:AS267),0) -> 9089492 | AW267: NGUYEN THI TUYET NGAN | AX267: 050127345462 | AY267: SK1 Box | AZ267: 622 | BA267: =+IF(AY267="SK1 Box","Box",IF(AY267="Seaman","Seaman","Bag")) -> Box
A268: =SUBTOTAL(3,B$6:B268) -> 0 | B268: C15453 | C268: Đặng Vũ Thảo Huyền | D268: 45164 | E268: FACTORY A | F268: P6 - QC | G268: QC worker | H268: 5538000 | I268: 500000 | J268: 0 | K268: 0 | L268: =SUM(H268:K268) -> 6038000 | M268: 23.5 | N268: =ROUND((H268+I268+J268+K268)/IF($M$2>26,26,$M$2)*M268,0) -> 5457423 | O268: 2 | P268: =ROUND((H268+I268+J268+K268)/IF($M$2>26,26,$M$2)*O268,0) -> 464462 | Q268: 0 | R268: =IF(M268>0,ROUND(N268/IF(M268>26,26,M268)/8*Q268*30%,0),0) -> 0 | S268: =N268+P268+R268 -> 5921885 | T268: 0 | U268: 0 | V268: 200000 | W268: 500000 | X268: 0 | Y268: 400000 | Z268: 391700 | AC268: 0 | AD268: 0 | AE268: 43543.269 | AG268: =ROUND(SUM(S268:AF268)-AA268,0) -> 7457128 | AH268: 28 | AI268: 0 | AJ268: 0 | AK268: 0 | AL268: 0 | AM268: =ROUND((N268/IF(M268>26,26,M268)/8*(AH268*$AH$5+AI268*$AI$5+AJ268*$AJ$5+AK268*$AK$5+AL268*$AL$5)),0) -> 1219212 | AN268: =ROUND(AG268+AM268,0) -> 8676340 | AO268: 633990 | AP268: 44100 | AQ268: =+VLOOKUP($B268,[1]Sheet1!$C$15:$BW$1300,52,0) -> 0 | AR268: 0 | AS268: 0 | AT268: =+ROUND(SUM(AN268:AN268)-SUM(AO268:AS268),0) -> 7998250 | AW268: DANG VU THAO HUYEN | AX268: 050120705986 | AY268: SK1 Box | AZ268: 622 | BA268: =+IF(AY268="SK1 Box","Box",IF(AY268="Seaman","Seaman","Bag")) -> Box
A269: =SUBTOTAL(3,B$6:B269) -> 0 | B269: C15906 | C269: Phạm Thị Thu Thương | D269: 45419 | E269: FACTORY A | F269: P6 - QC | G269: QC worker | H269: 5274000 | I269: 500000 | J269: 0 | K269: 0 | L269: =SUM(H269:K269) -> 5774000 | M269: 22.8 | N269: =ROUND((H269+I269+J269+K269)/IF($M$2>26,26,$M$2)*M269,0) -> 5063354 | O269: 3 | P269: =ROUND((H269+I269+J269+K269)/IF($M$2>26,26,$M$2)*O269,0) -> 666231 | Q269: 0 | R269: =IF(M269>0,ROUND(N269/IF(M269>26,26,M269)/8*Q269*30%,0),0) -> 0 | S269: =N269+P269+R269 -> 5729585 | T269: 0 | U269: 0 | V269: 200000 | W269: 500000 | X269: 0 | Y269: 400000 | Z269: 380000 | AC269: 0 | AD269: 0 | AE269: 41639.424 | AG269: =ROUND(SUM(S269:AF269)-AA269,0) -> 7251224 | AH269: 24 | AI269: 0 | AJ269: 0 | AK269: 0 | AL269: 0 | AM269: =ROUND((N269/IF(M269>26,26,M269)/8*(AH269*$AH$5+AI269*$AI$5+AJ269*$AJ$5+AK269*$AK$5+AL269*$AL$5)),0) -> 999346 | AN269: =ROUND(AG269+AM269,0) -> 8250570 | AO269: 606270 | AP269: 44100 | AQ269: =+VLOOKUP($B269,[1]Sheet1!$C$15:$BW$1300,52,0) -> 0 | AR269: 0 | AS269: 0 | AT269: =+ROUND(SUM(AN269:AN269)-SUM(AO269:AS269),0) -> 7600200 | AW269: PHAM THI THU THUONG | AX269: 050135011281 | AY269: SK1 Box | AZ269: 622 | BA269: =+IF(AY269="SK1 Box","Box",IF(AY269="Seaman","Seaman","Bag")) -> Box
A270: =SUBTOTAL(3,B$6:B270) -> 0 | B270: C15959 | C270: Khiếu Thị Hoàng Vân | D270: 45444 | E270: FACTORY A | F270: P6 - QC | G270: QC worker | H270: 5274000 | I270: 500000 | J270: 0 | K270: 0 | L270: =SUM(H270:K270) -> 5774000 | M270: 23.8 | N270: =ROUND((H270+I270+J270+K270)/IF($M$2>26,26,$M$2)*M270,0) -> 5285431 | O270: 2 | P270: =ROUND((H270+I270+J270+K270)/IF($M$2>26,26,$M$2)*O270,0) -> 444154 | Q270: 0 | R270: =IF(M270>0,ROUND(N270/IF(M270>26,26,M270)/8*Q270*30%,0),0) -> 0 | S270: =N270+P270+R270 -> 5729585 | T270: 0 | U270: 0 | V270: 200000 | W270: 500000 | X270: 0 | Y270: 400000 | Z270: 396700 | AC270: 0 | AD270: 0 | AE270: 41639.425 | AG270: =ROUND(SUM(S270:AF270)-AA270,0) -> 7267924 | AH270: 28 | AI270: 0 | AJ270: 0 | AK270: 0 | AL270: 0 | AM270: =ROUND((N270/IF(M270>26,26,M270)/8*(AH270*$AH$5+AI270*$AI$5+AJ270*$AJ$5+AK270*$AK$5+AL270*$AL$5)),0) -> 1165904 | AN270: =ROUND(AG270+AM270,0) -> 8433828 | AO270: 606270 | AP270: 44100 | AQ270: =+VLOOKUP($B270,[1]Sheet1!$C$15:$BW$1300,52,0) -> 0 | AR270: 0 | AS270: 0 | AT270: =+ROUND(SUM(AN270:AN270)-SUM(AO270:AS270),0) -> 7783458 | AW270: KHIEU THI HOANG VAN | AX270: 050074107580 | AY270: SK1 Box | AZ270: 622 | BA270: =+IF(AY270="SK1 Box","Box",IF(AY270="Seaman","Seaman","Bag")) -> Box
A271: =SUBTOTAL(3,B$6:B271) -> 0 | B271: C16460 | C271: Hà Nguyễn Tấn Trung | D271: 45710 | E271: FACTORY A | F271: P6 - QC | G271: QC worker | H271: 5023000 | I271: 500000 | J271: 0 | K271: 0 | L271: =SUM(H271:K271) -> 5523000 | M271: 23 | N271: =ROUND((H271+I271+J271+K271)/IF($M$2>26,26,$M$2)*M271,0) -> 4885731 | O271: 3 | P271: =ROUND((H271+I271+J271+K271)/IF($M$2>26,26,$M$2)*O271,0) -> 637269 | Q271: 0 | R271: =IF(M271>0,ROUND(N271/IF(M271>26,26,M271)/8*Q271*30%,0),0) -> 0 | S271: =N271+P271+R271 -> 5523000 | T271: 0 | U271: 0 | V271: 200000 | W271: 500000 | X271: 0 | Y271: 400000 | Z271: 383300 | AC271: 0 | AD271: 0 | AE271: 0 | AG271: =ROUND(SUM(S271:AF271)-AA271,0) -> 7006300 | AH271: 20 | AI271: 0 | AJ271: 0 | AK271: 0 | AL271: 0 | AM271: =ROUND((N271/IF(M271>26,26,M271)/8*(AH271*$AH$5+AI271*$AI$5+AJ271*$AJ$5+AK271*$AK$5+AL271*$AL$5)),0) -> 796587 | AN271: =ROUND(AG271+AM271,0) -> 7802887 | AO271: 579915 | AP271: 0 | AQ271: =+VLOOKUP($B271,[1]Sheet1!$C$15:$BW$1300,52,0) -> 0 | AR271: 0 | AS271: 0 | AT271: =+ROUND(SUM(AN271:AN271)-SUM(AO271:AS271),0) -> 7222972 | AW271: HA NGUYEN TAN TRUNG | AX271: 050968075690 | AY271: SK1 Box | AZ271: 622 | BA271: =+IF(AY271="SK1 Box","Box",IF(AY271="Seaman","Seaman","Bag")) -> Box
A272: =SUBTOTAL(3,B$6:B272) -> 0 | B272: C2982 | C272: Đỗ Thị Nga | D272: 40369 | E272: FACTORY A | F272: P6 - QC | G272: QC worker | H272: 5931000 | I272: 1100000 | J272: 0 | K272: 0 | L272: =SUM(H272:K272) -> 7031000 | M272: 23.9 | N272: =ROUND((H272+I272+J272+K272)/IF($M$2>26,26,$M$2)*M272,0) -> 6463112 | O272: 2 | P272: =ROUND((H272+I272+J272+K272)/IF($M$2>26,26,$M$2)*O272,0) -> 540846 | Q272: 0 | R272: =IF(M272>0,ROUND(N272/IF(M272>26,26,M272)/8*Q272*30%,0),0) -> 0 | S272: =N272+P272+R272 -> 7003958 | T272: 0 | U272: 0 | V272: 200000 | W272: 500000 | X272: 0 | Y272: 400000 | Z272: 398300 | AC272: 100000 | AD272: 0 | AE272: 50704.331 | AG272: =ROUND(SUM(S272:AF272)-AA272,0) -> 8652962 | AH272: 28 | AI272: 0 | AJ272: 0 | AK272: 0 | AL272: 0 | AM272: =ROUND((N272/IF(M272>26,26,M272)/8*(AH272*$AH$5+AI272*$AI$5+AJ272*$AJ$5+AK272*$AK$5+AL272*$AL$5)),0) -> 1419721 | AN272: =ROUND(AG272+AM272,0) -> 10072683 | AO272: 738255 | AP272: 44100 | AQ272: =+VLOOKUP($B272,[1]Sheet1!$C$15:$BW$1300,52,0) -> 0 | AR272: 0 | AS272: 0 | AT272: =+ROUND(SUM(AN272:AN272)-SUM(AO272:AS272),0) -> 9290328 | AW272: DO THI NGA | AX272: 050040966088 | AY272: SK1 Box | AZ272: 622 | BA272: =+IF(AY272="SK1 Box","Box",IF(AY272="Seaman","Seaman","Bag")) -> Box
A273: =SUBTOTAL(3,B$6:B273) -> 0 | B273: C6248 | C273: Huỳnh Văn Mẫu Tám | D273: 41764 | E273: FACTORY A | F273: P6 - QC | G273: Box QC leader | H273: 8176000 | I273: 3200000 | J273: 0 | K273: 5200000 | L273: =SUM(H273:K273) -> 16576000 | M273: 23.9 | N273: =ROUND((H273+I273+J273+K273)/IF($M$2>26,26,$M$2)*M273,0) -> 15237169 | O273: 2 | P273: =ROUND((H273+I273+J273+K273)/IF($M$2>26,26,$M$2)*O273,0) -> 1275077 | Q273: 0 | R273: =IF(M273>0,ROUND(N273/IF(M273>26,26,M273)/8*Q273*30%,0),0) -> 0 | S273: =N273+P273+R273 -> 16512246 | T273: 0 | U273: 0 | V273: 200000 | W273: 500000 | X273: 0 | Y273: 400000 | Z273: 697100 | AC273: 100000 | AD273: 0 | AE273: 0 | AG273: =ROUND(SUM(S273:AF273)-AA273,0) -> 18409346 | AH273: 28 | AI273: 0 | AJ273: 0 | AK273: 0 | AL273: 0 | AM273: =ROUND((N273/IF(M273>26,26,M273)/8*(AH273*$AH$5+AI273*$AI$5+AJ273*$AJ$5+AK273*$AK$5+AL273*$AL$5)),0) -> 3347077 | AN273: =ROUND(AG273+AM273,0) -> 21756423 | AO273: 1740480 | AP273: 44100 | AQ273: =+VLOOKUP($B273,[1]Sheet1!$C$15:$BW$1300,52,0) -> 0 | AR273: 0 | AS273: 0 | AT273: =+ROUND(SUM(AN273:AN273)-SUM(AO273:AS273),0) -> 19971843 | AW273: HUYNH VAN MAU TAM | AX273: 050042516527 | AY273: SK1 Box | AZ273: 622 | BA273: =+IF(AY273="SK1 Box","Box",IF(AY273="Seaman","Seaman","Bag")) -> Box
A274: =SUBTOTAL(3,B$6:B274) -> 0 | B274: C14461 | C274: Nguyễn Ngọc Tùng | D274: 44604 | E274: FACTORY A | F274: P6 - WIP | G274: WIP worker | H274: 5931000 | I274: 500000 | J274: 0 | K274: 0 | L274: =SUM(H274:K274) -> 6431000 | M274: 23.9 | N274: =ROUND((H274+I274+J274+K274)/IF($M$2>26,26,$M$2)*M274,0) -> 5911573 | O274: 2 | P274: =ROUND((H274+I274+J274+K274)/IF($M$2>26,26,$M$2)*O274,0) -> 494692 | Q274: 0 | R274: =IF(M274>0,ROUND(N274/IF(M274>26,26,M274)/8*Q274*30%,0),0) -> 0 | S274: =N274+P274+R274 -> 6406265 | T274: 0 | U274: 0 | V274: 200000 | W274: 500000 | X274: 0 | Y274: 400000 | Z274: 590813 | AC274: 0 | AD274: 0 | AE274: 0 | AG274: =ROUND(SUM(S274:AF274)-AA274,0) -> 8097078 | AH274: 28 | AI274: 0 | AJ274: 0 | AK274: 0 | AL274: 0 | AM274: =ROUND((N274/IF(M274>26,26,M274)/8*(AH274*$AH$5+AI274*$AI$5+AJ274*$AJ$5+AK274*$AK$5+AL274*$AL$5)),0) -> 1298567 | AN274: =ROUND(AG274+AM274,0) -> 9395645 | AO274: 675255 | AP274: 44100 | AQ274: =+VLOOKUP($B274,[1]Sheet1!$C$15:$BW$1300,52,0) -> 0 | AR274: 0 | AS274: 0 | AT274: =+ROUND(SUM(AN274:AN274)-SUM(AO274:AS274),0) -> 8676290 | AW274: NGUYEN NGOC TUNG | AX274: 050131181482 | AY274: SK1 Box | AZ274: 622 | BA274: =+IF(AY274="SK1 Box","Box",IF(AY274="Seaman","Seaman","Bag")) -> Box
A275: =SUBTOTAL(3,B$6:B275) -> 0 | B275: C15431 | C275: Lê Thanh Hiền | D275: 45005 | E275: FACTORY A | F275: P8 - Lami | G275: Auto Machine sub-operator-A | H275: 5815000 | I275: 800000 | J275: 292000 | K275: 100000 | L275: =SUM(H275:K275) -> 7007000 | M275: 18.6 | N275: =ROUND((H275+I275+J275+K275)/IF($M$2>26,26,$M$2)*M275,0) -> 5012700 | O275: 2 | P275: =ROUND((H275+I275+J275+K275)/IF($M$2>26,26,$M$2)*O275,0) -> 539000 | Q275: 0 | R275: =IF(M275>0,ROUND(N275/IF(M275>26,26,M275)/8*Q275*30%,0),0) -> 0 | S275: =N275+P275+R275 -> 5551700 | T275: 0 | U275: 0 | V275: 200000 | W275: 0 | X275: 200000 | Y275: 0 | Z275: 348482 | AC275: 0 | AD275: 0 | AE275: 0 | AG275: =ROUND(SUM(S275:AF275)-AA275,0) -> 6300182 | AH275: 28 | AI275: 0 | AJ275: 0 | AK275: 0 | AL275: 0 | AM275: =ROUND((N275/IF(M275>26,26,M275)/8*(AH275*$AH$5+AI275*$AI$5+AJ275*$AJ$5+AK275*$AK$5+AL275*$AL$5)),0) -> 1414875 | AN275: =ROUND(AG275+AM275,0) -> 7715057 | AO275: 735735 | AP275: 44100 | AQ275: =+VLOOKUP($B275,[1]Sheet1!$C$15:$BW$1300,52,0) -> 0 | AR275: 0 | AS275: 0 | AT275: =+ROUND(SUM(AN275:AN275)-SUM(AO275:AS275),0) -> 6935222 | AW275: LE THANH HIEN | AX275: 050122289671 | AY275: Seaman | AZ275: 622 | BA275: =+IF(AY275="SK1 Box","Box",IF(AY275="Seaman","Seaman","Bag")) -> Seaman
A276: =SUBTOTAL(3,B$6:B276) -> 0 | B276: C15564 | C276: Lê Văn Nhớ | D276: 45344 | E276: FACTORY A | F276: P8 - Lami | G276: Auto Machine Assistant-A | H276: 5538000 | I276: 600000 | J276: 278000 | K276: 0 | L276: =SUM(H276:K276) -> 6416000 | M276: 23 | N276: =ROUND((H276+I276+J276+K276)/IF($M$2>26,26,$M$2)*M276,0) -> 5675692 | O276: 2 | P276: =ROUND((H276+I276+J276+K276)/IF($M$2>26,26,$M$2)*O276,0) -> 493538 | Q276: 0 | R276: =IF(M276>0,ROUND(N276/IF(M276>26,26,M276)/8*Q276*30%,0),0) -> 0 | S276: =N276+P276+R276 -> 6169230 | T276: 0 | U276: 0 | V276: 200000 | W276: 0 | X276: 0 | Y276: 400000 | Z276: 371683 | AC276: 0 | AD276: 0 | AE276: 0 | AG276: =ROUND(SUM(S276:AF276)-AA276,0) -> 7140913 | AH276: 28 | AI276: 0 | AJ276: 0 | AK276: 0 | AL276: 0 | AM276: =ROUND((N276/IF(M276>26,26,M276)/8*(AH276*$AH$5+AI276*$AI$5+AJ276*$AJ$5+AK276*$AK$5+AL276*$AL$5)),0) -> 1295538 | AN276: =ROUND(AG276+AM276,0) -> 8436451 | AO276: 673680 | AP276: 44100 | AQ276: =+VLOOKUP($B276,[1]Sheet1!$C$15:$BW$1300,52,0) -> 0 | AR276: 0 | AS276: 0 | AT276: =+ROUND(SUM(AN276:AN276)-SUM(AO276:AS276),0) -> 7718671 | AW276: LE VAN NHO | AX276: 050151637091 | AY276: Seaman | AZ276: 622 | BA276: =+IF(AY276="SK1 Box","Box",IF(AY276="Seaman","Seaman","Bag")) -> Seaman
... A279: =SUBTOTAL(3,B$6:B279) -> 0 | B279: C14632 | C279: Nguyễn Chính Tín | D279: 44621 | E279: FACTORY A | F279: P8 - Packing | G279: Packing worker | H279: 5931000 | I279: 200000 | J279: 0 | K279: 0 | L279: =SUM(H279:K279) -> 6131000 | M279: 23.9 | N279: =ROUND((H279+I279+J279+K279)/IF($M$2>26,26,$M$2)*M279,0) -> 5635804 | O279: 2 | P279: =ROUND((H279+I279+J279+K279)/IF($M$2>26,26,$M$2)*O279,0) -> 471615 | Q279: 0 | R279: =IF(M279>0,ROUND(N279/IF(M279>26,26,M279)/8*Q279*30%,0),0) -> 0 | S279: =N279+P279+R279 -> 6107419 | T279: 0 | U279: 0 | V279: 200000 | W279: 500000 | X279: 0 | Y279: 300000 | Z279: 360449 | AC279: 0 | AD279: 0 | AE279: 0 | AG279: =ROUND(SUM(S279:AF279)-AA279,0) -> 7467868 | AH279: 20 | AI279: 0 | AJ279: 0 | AK279: 0 | AL279: 0 | AM279: =ROUND((N279/IF(M279>26,26,M279)/8*(AH279*$AH$5+AI279*$AI$5+AJ279*$AJ$5+AK279*$AK$5+AL279*$AL$5)),0) -> 884279 | AN279: =ROUND(AG279+AM279,0) -> 8352147 | AO279: 643755 | AP279: 44100 | AQ279: =+VLOOKUP($B279,[1]Sheet1!$C$15:$BW$1300,52,0) -> 0 | AR279: 140000 | AS279: 0 | AT279: =+ROUND(SUM(AN279:AN279)-SUM(AO279:AS279),0) -> 7524292 | AW279: NGUYEN CHINH TIN | AX279: 050051381723 | AY279: Seaman | AZ279: 622 | BA279: =+IF(AY279="SK1 Box","Box",IF(AY279="Seaman","Seaman","Bag")) -> Seaman
A280: =SUBTOTAL(3,B$6:B280) -> 0 | B280: C15912 | C280: Dương Kim Đỗ | D280: 45414 | E280: FACTORY A | F280: P8 - Production Office | G280: Factory manager | H280: 14500000 | I280: 13000000 | J280: 0 | K280: 0 | L280: =SUM(H280:K280) -> 27500000 | M280: 24 | N280: =ROUND((H280+I280+J280+K280)/IF($M$2>26,26,$M$2)*M280,0) -> 25384615 | O280: 2 | P280: =ROUND((H280+I280+J280+K280)/IF($M$2>26,26,$M$2)*O280,0) -> 2115385 | Q280: 0 | R280: =IF(M280>0,ROUND(N280/IF(M280>26,26,M280)/8*Q280*30%,0),0) -> 0 | S280: =N280+P280+R280 -> 27500000 | T280: 500000 | U280: 0 | V280: 0 | W280: 0 | X280: 0 | Y280: 0 | Z280: 0 | AC280: 0 | AD280: 0 | AE280: 0 | AG280: =ROUND(SUM(S280:AF280)-AA280,0) -> 28000000 | AH280: 0 | AI280: 0 | AJ280: 0 | AK280: 0 | AL280: 0 | AM280: =ROUND((N280/IF(M280>26,26,M280)/8*(AH280*$AH$5+AI280*$AI$5+AJ280*$AJ$5+AK280*$AK$5+AL280*$AL$5)),0) -> 0 | AN280: =ROUND(AG280+AM280,0) -> 28000000 | AO280: 2887500 | AP280: 44100 | AQ280: =+VLOOKUP($B280,[1]Sheet1!$C$15:$BW$1300,52,0) -> 245625 | AR280: 0 | AS280: 0 | AT280: =+ROUND(SUM(AN280:AN280)-SUM(AO280:AS280),0) -> 24822775 | AW280: DUONG KIM DO | AX280: 050153623608 | AY280: Seaman | AZ280: 627 | BA280: Manager
A281: =SUBTOTAL(3,B$6:B281) -> 0 | B281: C13485 | C281: Hồ Vĩnh Bình | D281: 44264 | E281: FACTORY A | F281: P8 - QC | G281: Lab Staff | H281: 6500000 | I281: 3800000 | J281: 0 | K281: 0 | L281: =SUM(H281:K281) -> 10300000 | M281: 24 | N281: =ROUND((H281+I281+J281+K281)/IF($M$2>26,26,$M$2)*M281,0) -> 9507692 | O281: 2 | P281: =ROUND((H281+I281+J281+K281)/IF($M$2>26,26,$M$2)*O281,0) -> 792308 | Q281: 0 | R281: =IF(M281>0,ROUND(N281/IF(M281>26,26,M281)/8*Q281*30%,0),0) -> 0 | S281: =N281+P281+R281 -> 10300000 | T281: 500000 | U281: 0 | V281: 200000 | W281: 500000 | X281: 0 | Y281: 400000 | Z281: 250000 | AC281: 100000 | AD281: 0 | AE281: 0 | AG281: =ROUND(SUM(S281:AF281)-AA281,0) -> 12250000 | AH281: 28 | AI281: 0 | AJ281: 0 | AK281: 0 | AL281: 0 | AM281: =ROUND((N281/IF(M281>26,26,M281)/8*(AH281*$AH$5+AI281*$AI$5+AJ281*$AJ$5+AK281*$AK$5+AL281*$AL$5)),0) -> 2079808 | AN281: =ROUND(AG281+AM281,0) -> 14329808 | AO281: 1081500 | AP281: 44100 | AQ281: =+VLOOKUP($B281,[1]Sheet1!$C$15:$BW$1300,52,0) -> 0 | AR281: 0 | AS281: 0 | AT281: =+ROUND(SUM(AN281:AN281)-SUM(AO281:AS281),0) -> 13204208 | AW281: HO VINH BINH | AX281: 050094096895 | AY281: Seaman | AZ281: 622 | BA281: =+IF(AY281="SK1 Box","Box",IF(AY281="Seaman","Seaman","Bag")) -> Seaman
A282: =SUBTOTAL(3,B$6:B282) -> 0 | B282: C16068 | C282: Trần Thị Thảo Sương | D282: 45502 | E282: FACTORY A | F282: P8 - QC | G282: QC worker | H282: 5274000 | I282: 500000 | J282: 0 | K282: 0 | L282: =SUM(H282:K282) -> 5774000 | M282: 22.7 | N282: =ROUND((H282+I282+J282+K282)/IF($M$2>26,26,$M$2)*M282,0) -> 5041146 | O282: 3 | P282: =ROUND((H282+I282+J282+K282)/IF($M$2>26,26,$M$2)*O282,0) -> 666231 | Q282: 0 | R282: =IF(M282>0,ROUND(N282/IF(M282>26,26,M282)/8*Q282*30%,0),0) -> 0 | S282: =N282+P282+R282 -> 5707377 | T282: 0 | U282: 0 | V282: 200000 | W282: 500000 | X282: 0 | Y282: 400000 | Z282: 378300 | AC282: 0 | AD282: 0 | AE282: 41639.422 | AG282: =ROUND(SUM(S282:AF282)-AA282,0) -> 7227316 | AH282: 8 | AI282: 0 | AJ282: 0 | AK282: 0 | AL282: 0 | AM282: =ROUND((N282/IF(M282>26,26,M282)/8*(AH282*$AH$5+AI282*$AI$5+AJ282*$AJ$5+AK282*$AK$5+AL282*$AL$5)),0) -> 333115 | AN282: =ROUND(AG282+AM282,0) -> 7560431 | AO282: 606270 | AP282: 44100 | AQ282: =+VLOOKUP($B282,[1]Sheet1!$C$15:$BW$1300,52,0) -> 0 | AR282: 0 | AS282: 0 | AT282: =+ROUND(SUM(AN282:AN282)-SUM(AO282:AS282),0) -> 6910061 | AW282: TRAN THI THAO SUONG | AX282: 050155274732 | AY282: Seaman | AZ282: 622 | BA282: =+IF(AY282="SK1 Box","Box",IF(AY282="Seaman","Seaman","Bag")) -> Seaman
A283: =SUBTOTAL(3,B$6:B283) -> 0 | B283: C10711 | C283: Nguyễn Mạnh Hùng | D283: 43602 | E283: FACTORY A | F283: P8 - Sheeter | G283: Auto Machine operator-C | H283: 5931000 | I283: 2100000 | J283: 0 | K283: 0 | L283: =SUM(H283:K283) -> 8031000 | M283: 23.5 | N283: =ROUND((H283+I283+J283+K283)/IF($M$2>26,26,$M$2)*M283,0) -> 7258788 | O283: 2 | P283: =ROUND((H283+I283+J283+K283)/IF($M$2>26,26,$M$2)*O283,0) -> 617769 | Q283: 0 | R283: =IF(M283>0,ROUND(N283/IF(M283>26,26,M283)/8*Q283*30%,0),0) -> 0 | S283: =N283+P283+R283 -> 7876557 | T283: 0 | U283: 0 | V283: 200000 | W283: 500000 | X283: 0 | Y283: 300000 | Z283: 513173 | AC283: 0 | AD283: 0 | AE283: 0 | AG283: =ROUND(SUM(S283:AF283)-AA283,0) -> 9389730 | AH283: 28 | AI283: 0 | AJ283: 0 | AK283: 0 | AL283: 0 | AM283: =ROUND((N283/IF(M283>26,26,M283)/8*(AH283*$AH$5+AI283*$AI$5+AJ283*$AJ$5+AK283*$AK$5+AL283*$AL$5)),0) -> 1621644 | AN283: =ROUND(AG283+AM283,0) -> 11011374 | AO283: 843255 | AP283: 44100 | AQ283: =+VLOOKUP($B283,[1]Sheet1!$C$15:$BW$1300,52,0) -> 0 | AR283: 0 | AS283: 0 | AT283: =+ROUND(SUM(AN283:AN283)-SUM(AO283:AS283),0) -> 10124019 | AW283: NGUYEN MANH HUNG | AX283: 050093875998 | AY283: Seaman | AZ283: 622 | BA283: =+IF(AY283="SK1 Box","Box",IF(AY283="Seaman","Seaman","Bag")) -> Seaman
A284: =SUBTOTAL(3,B$6:B284) -> 0 | B284: C15964 | C284: Võ Thị Thanh Vân | D284: 45446 | E284: FACTORY A | F284: P8 - Sheeter | G284: Auto Machine sub-operator-C | H284: 5274000 | I284: 400000 | J284: 0 | K284: 0 | L284: =SUM(H284:K284) -> 5674000 | M284: 23.6 | N284: =ROUND((H284+I284+J284+K284)/IF($M$2>26,26,$M$2)*M284,0) -> 5150246 | O284: 2 | P284: =ROUND((H284+I284+J284+K284)/IF($M$2>26,26,$M$2)*O284,0) -> 436462 | Q284: 0 | R284: =IF(M284>0,ROUND(N284/IF(M284>26,26,M284)/8*Q284*30%,0),0) -> 0 | S284: =N284+P284+R284 -> 5586708 | T284: 0 | U284: 0 | V284: 200000 | W284: 500000 | X284: 0 | Y284: 400000 | Z284: 427378 | AC284: 0 | AD284: 0 | AE284: 40918.268 | AG284: =ROUND(SUM(S284:AF284)-AA284,0) -> 7155004 | AH284: 24 | AI284: 0 | AJ284: 0 | AK284: 0 | AL284: 0 | AM284: =ROUND((N284/IF(M284>26,26,M284)/8*(AH284*$AH$5+AI284*$AI$5+AJ284*$AJ$5+AK284*$AK$5+AL284*$AL$5)),0) -> 982038 | AN284: =ROUND(AG284+AM284,0) -> 8137042 | AO284: 595770 | AP284: 44100 | AQ284: =+VLOOKUP($B284,[1]Sheet1!$C$15:$BW$1300,52,0) -> 0 | AR284: 0 | AS284: 0 | AT284: =+ROUND(SUM(AN284:AN284)-SUM(AO284:AS284),0) -> 7497172 | AW284: VO THI THANH VAN | AX284: 050130754136 | AY284: Seaman | AZ284: 622 | BA284: =+IF(AY284="SK1 Box","Box",IF(AY284="Seaman","Seaman","Bag")) -> Seaman
A285: =SUBTOTAL(3,B$6:B285) -> 0 | B285: C15998 | C285: Lưu Thị Thu Hà | D285: 45458 | E285: FACTORY A | F285: P8 - Sheeter | G285: Auto Machine sub-operator-C | H285: 5274000 | I285: 400000 | J285: 0 | K285: 0 | L285: =SUM(H285:K285) -> 5674000 | M285: 22.6 | N285: =ROUND((H285+I285+J285+K285)/IF($M$2>26,26,$M$2)*M285,0) -> 4932015 | O285: 3 | P285: =ROUND((H285+I285+J285+K285)/IF($M$2>26,26,$M$2)*O285,0) -> 654692 | Q285: 0 | R285: =IF(M285>0,ROUND(N285/IF(M285>26,26,M285)/8*Q285*30%,0),0) -> 0 | S285: =N285+P285+R285 -> 5586707 | T285: 0 | U285: 0 | V285: 200000 | W285: 500000 | X285: 0 | Y285: 300000 | Z285: 376230 | AC285: 100000 | AD285: 0 | AE285: 40918.266 | AG285: =ROUND(SUM(S285:AF285)-AA285,0) -> 7103855 | AH285: 20 | AI285: 0 | AJ285: 0 | AK285: 0 | AL285: 0 | AM285: =ROUND((N285/IF(M285>26,26,M285)/8*(AH285*$AH$5+AI285*$AI$5+AJ285*$AJ$5+AK285*$AK$5+AL285*$AL$5)),0) -> 818365 | AN285: =ROUND(AG285+AM285,0) -> 7922220 | AO285: 595770 | AP285: 44100 | AQ285: =+VLOOKUP($B285,[1]Sheet1!$C$15:$BW$1300,52,0) -> 0 | AR285: 130000 | AS285: 0 | AT285: =+ROUND(SUM(AN285:AN285)-SUM(AO285:AS285),0) -> 7152350 | AW285: LUU THI THU HA | AX285: 050116972929 | AY285: Seaman | AZ285: 622 | BA285: =+IF(AY285="SK1 Box","Box",IF(AY285="Seaman","Seaman","Bag")) -> Seaman
A286: =SUBTOTAL(3,B$6:B286) -> 0 | B286: C16066 | C286: Đàm Văn Long | D286: 45496 | E286: FACTORY A | F286: P8 - Sheeter | G286: Auto Machine operator-C | H286: 5274000 | I286: 700000 | J286: 0 | K286: 0 | L286: =SUM(H286:K286) -> 5974000 | M286: 24 | N286: =ROUND((H286+I286+J286+K286)/IF($M$2>26,26,$M$2)*M286,0) -> 5514462 | O286: 2 | P286: =ROUND((H286+I286+J286+K286)/IF($M$2>26,26,$M$2)*O286,0) -> 459538 | Q286: 0 | R286: =IF(M286>0,ROUND(N286/IF(M286>26,26,M286)/8*Q286*30%,0),0) -> 0 | S286: =N286+P286+R286 -> 5974000 | T286: 0 | U286: 0 | V286: 200000 | W286: 500000 | X286: 0 | Y286: 400000 | Z286: 415112 | AC286: 0 | AD286: 0 | AE286: 0 | AG286: =ROUND(SUM(S286:AF286)-AA286,0) -> 7489112 | AH286: 28 | AI286: 0 | AJ286: 0 | AK286: 0 | AL286: 0 | AM286: =ROUND((N286/IF(M286>26,26,M286)/8*(AH286*$AH$5+AI286*$AI$5+AJ286*$AJ$5+AK286*$AK$5+AL286*$AL$5)),0) -> 1206289 | AN286: =ROUND(AG286+AM286,0) -> 8695401 | AO286: 627270 | AP286: 44100 | AQ286: =+VLOOKUP($B286,[1]Sheet1!$C$15:$BW$1300,52,0) -> 0 | AR286: 0 | AS286: 0 | AT286: =+ROUND(SUM(AN286:AN286)-SUM(AO286:AS286),0) -> 8024031 | AW286: DAM VAN LONG | AX286: 050153900131 | AY286: Seaman | AZ286: 622 | BA286: =+IF(AY286="SK1 Box","Box",IF(AY286="Seaman","Seaman","Bag")) -> Seaman
A287: =SUBTOTAL(3,B$6:B287) -> 0 | B287: C16436 | C287: Châu Khắc Cường | D287: 45701 | E287: FACTORY A | F287: P8 - Sheeter | G287: Auto Machine sub-operator-C | H287: 5023000 | I287: 400000 | J287: 0 | K287: 0 | L287: =SUM(H287:K287) -> 5423000 | M287: 22.9 | N287: =ROUND((H287+I287+J287+K287)/IF($M$2>26,26,$M$2)*M287,0) -> 4776412 | O287: 2 | P287: =ROUND((H287+I287+J287+K287)/IF($M$2>26,26,$M$2)*O287,0) -> 417154 | Q287: 0 | R287: =IF(M287>0,ROUND(N287/IF(M287>26,26,M287)/8*Q287*30%,0),0) -> 0 | S287: =N287+P287+R287 -> 5193566 | T287: 0 | U287: 0 | V287: 200000 | W287: 0 | X287: 0 | Y287: 400000 | Z287: 448574 | AC287: 0 | AD287: 0 | AE287: 0 | AG287: =ROUND(SUM(S287:AF287)-AA287,0) -> 6242140 | AH287: 20 | AI287: 0 | AJ287: 0 | AK287: 0 | AL287: 0 | AM287: =ROUND((N287/IF(M287>26,26,M287)/8*(AH287*$AH$5+AI287*$AI$5+AJ287*$AJ$5+AK287*$AK$5+AL287*$AL$5)),0) -> 782164 | AN287: =ROUND(AG287+AM287,0) -> 7024304 | AO287: 569415 | AP287: 44100 | AQ287: =+VLOOKUP($B287,[1]Sheet1!$C$15:$BW$1300,52,0) -> 0 | AR287: 0 | AS287: 0 | AT287: =+ROUND(SUM(AN287:AN287)-SUM(AO287:AS287),0) -> 6410789 | AW287: CHAU KHAC CUONG | AX287: 050040786225 | AY287: Seaman | AZ287: 622 | BA287: =+IF(AY287="SK1 Box","Box",IF(AY287="Seaman","Seaman","Bag")) -> Seaman
A288: =SUBTOTAL(3,B$6:B288) -> 0 | B288: C16610 | C288: Đỗ Quốc Thái | D288: 45762 | E288: FACTORY A | F288: P8 - Sheeter | G288: New worker | H288: 4694000 | I288: 0 | J288: 0 | K288: 0 | L288: =SUM(H288:K288) -> 4694000 | M288: 13 | N288: =ROUND((H288+I288+J288+K288)/IF($M$2>26,26,$M$2)*M288,0) -> 2347000 | O288: 1 | P288: =ROUND((H288+I288+J288+K288)/IF($M$2>26,26,$M$2)*O288,0) -> 180538 | Q288: 0 | R288: =IF(M288>0,ROUND(N288/IF(M288>26,26,M288)/8*Q288*30%,0),0) -> 0 | S288: =N288+P288+R288 -> 2527538 | T288: 0 | U288: 0 | V288: 108000 | W288: 269000 | X288: 0 | Y288: 81000 | Z288: 205921 | AC288: 0 | AD288: 0 | AE288: 0 | AG288: =ROUND(SUM(S288:AF288)-AA288,0) -> 3191459 | AH288: 4 | AI288: 0 | AJ288: 0 | AK288: 0 | AL288: 0 | AM288: =ROUND((N288/IF(M288>26,26,M288)/8*(AH288*$AH$5+AI288*$AI$5+AJ288*$AJ$5+AK288*$AK$5+AL288*$AL$5)),0) -> 135404 | AN288: =ROUND(AG288+AM288,0) -> 3326863 | AO288: 0 | AP288: 0 | AQ288: =+VLOOKUP($B288,[1]Sheet1!$C$15:$BW$1300,52,0) -> 0 | AR288: 0 | AS288: 0 | AT288: =+ROUND(SUM(AN288:AN288)-SUM(AO288:AS288),0) -> 3326863 | AW288: DO QUOC THAI | AX288: 050357954722 | AY288: Seaman | AZ288: 622 | BA288: =+IF(AY288="SK1 Box","Box",IF(AY288="Seaman","Seaman","Bag")) -> Seaman
A289: =SUBTOTAL(3,B$6:B289) -> 1 | B289: C16123 | C289: Quách Văn Hiền | D289: 45528 | E289: FACTORY A | F289: P8 - Slitter | G289: Auto Machine operator-C | H289: 5274000 | I289: 700000 | J289: 0 | K289: 0 | L289: =SUM(H289:K289) -> 5974000 | M289: 22.6 | N289: =ROUND((H289+I289+J289+K289)/IF($M$2>26,26,$M$2)*M289,0) -> 5192785 | O289: 3 | P289: =ROUND((H289+I289+J289+K289)/IF($M$2>26,26,$M$2)*O289,0) -> 689308 | Q289: 0 | R289: =IF(M289>0,ROUND(N289/IF(M289>26,26,M289)/8*Q289*30%,0),0) -> 0 | S289: =N289+P289+R289 -> 5882093 | T289: 0 | U289: 0 | V289: 200000 | W289: 500000 | X289: 0 | Y289: 300000 | Z289: 340843 | AC289: 0 | AD289: 0 | AE289: 0 | AG289: =ROUND(SUM(S289:AF289)-AA289,0) -> 7222936 | AH289: 16 | AI289: 0 | AJ289: 0 | AK289: 0 | AL289: 0 | AM289: =ROUND((N289/IF(M289>26,26,M289)/8*(AH289*$AH$5+AI289*$AI$5+AJ289*$AJ$5+AK289*$AK$5+AL289*$AL$5)),0) -> 689308 | AN289: =ROUND(AG289+AM289,0) -> 7912244 | AO289: 627270 | AP289: 44100 | AQ289: =+VLOOKUP($B289,[1]Sheet1!$C$15:$BW$1300,52,0) -> 0 | AR289: 0 | AS289: 0 | AT289: =+ROUND(SUM(AN289:AN289)-SUM(AO289:AS289),0) -> 7240874 | AW289: QUACH VAN HIEN | AX289: 050058821966 | AY289: Seaman | AZ289: 622 | BA289: =+IF(AY289="SK1 Box","Box",IF(AY289="Seaman","Seaman","Bag")) -> Seaman
A290: =SUBTOTAL(3,B$6:B290) -> 1 | B290: C13358 | C290: Phan Hồ Hải | D290: 44257 | E290: FACTORY B | F290: P5 - Auto Paper lami Box | G290: Auto Machine Operator-C | H290: 5931000 | I290: 1500000 | J290: 0 | K290: 0 | L290: =SUM(H290:K290) -> 7431000 | M290: 23.8 | N290: =ROUND((H290+I290+J290+K290)/IF($M$2>26,26,$M$2)*M290,0) -> 6802223 | O290: 2 | P290: =ROUND((H290+I290+J290+K290)/IF($M$2>26,26,$M$2)*O290,0) -> 571615 | Q290: 0 | R290: =IF(M290>0,ROUND(N290/IF(M290>26,26,M290)/8*Q290*30%,0),0) -> 0 | S290: =N290+P290+R290 -> 7373838 | T290: 0 | U290: 0 | V290: 200000 | W290: 500000 | X290: 0 | Y290: 400000 | Z290: 190110 | AC290: 0 | AD290: 0 | AE290: 0 | AG290: =ROUND(SUM(S290:AF290)-AA290,0) -> 8663948 | AH290: 20 | AI290: 0 | AJ290: 0 | AK290: 0 | AL290: 0 | AM290: =ROUND((N290/IF(M290>26,26,M290)/8*(AH290*$AH$5+AI290*$AI$5+AJ290*$AJ$5+AK290*$AK$5+AL290*$AL$5)),0) -> 1071779 | AN290: =ROUND(AG290+AM290,0) -> 9735727 | AO290: 780255 | AP290: 44100 | AQ290: =+VLOOKUP($B290,[1]Sheet1!$C$15:$BW$1300,52,0) -> 0 | AR290: 0 | AS290: 0 | AT290: =+ROUND(SUM(AN290:AN290)-SUM(AO290:AS290),0) -> 8911372 | AW290: PHAN HO HAI | AX290: 050126776729 | AY290: SK1 Box | AZ290: 622 | BA290: =+IF(AY290="SK1 Box","Box",IF(AY290="Seaman","Seaman","Bag")) -> Box
A291: =SUBTOTAL(3,B$6:B291) -> 1 | B291: C2287 | C291: Trần Văn Dũng | D291: 40233 | E291: FACTORY B | F291: P5 - Auto Paper lami Box | G291: Auto Machine leader-C | H291: 5931000 | I291: 3500000 | J291: 0 | K291: 200000 | L291: =SUM(H291:K291) -> 9631000 | M291: 23.8 | N291: =ROUND((H291+I291+J291+K291)/IF($M$2>26,26,$M$2)*M291,0) -> 8816069 | O291: 2 | P291: =ROUND((H291+I291+J291+K291)/IF($M$2>26,26,$M$2)*O291,0) -> 740846 | Q291: 0 | R291: =IF(M291>0,ROUND(N291/IF(M291>26,26,M291)/8*Q291*30%,0),0) -> 0 | S291: =N291+P291+R291 -> 9556915 | T291: 0 | U291: 0 | V291: 200000 | W291: 500000 | X291: 0 | Y291: 400000 | Z291: 532606 | AC291: 0 | AD291: 0 | AE291: 0 | AG291: =ROUND(SUM(S291:AF291)-AA291,0) -> 11189521 | AH291: 20 | AI291: 0 | AJ291: 0 | AK291: 0 | AL291: 0 | AM291: =ROUND((N291/IF(M291>26,26,M291)/8*(AH291*$AH$5+AI291*$AI$5+AJ291*$AJ$5+AK291*$AK$5+AL291*$AL$5)),0) -> 1389087 | AN291: =ROUND(AG291+AM291,0) -> 12578608 | AO291: 1011255 | AP291: 44100 | AQ291: =+VLOOKUP($B291,[1]Sheet1!$C$15:$BW$1300,52,0) -> 10216 | AR291: 0 | AS291: 0 | AT291: =+ROUND(SUM(AN291:AN291)-SUM(AO291:AS291),0) -> 11513037 | AW291: TRAN VAN DUNG | AX291: 050040819042 | AY291: SK1 Box | AZ291: 622 | BA291: =+IF(AY291="SK1 Box","Box",IF(AY291="Seaman","Seaman","Bag")) -> Box
A292: =SUBTOTAL(3,B$6:B292) -> 1 | B292: C7226 | C292: Võ Minh Thủ | D292: 43179 | E292: FACTORY B | F292: P5 - Auto Paper lami Box | G292: Auto Machine operator-C | H292: 5931000 | I292: 2100000 | J292: 0 | K292: 500000 | L292: =SUM(H292:K292) -> 8531000 | M292: 24 | N292: =ROUND((H292+I292+J292+K292)/IF($M$2>26,26,$M$2)*M292,0) -> 7874769 | O292: 2 | P292: =ROUND((H292+I292+J292+K292)/IF($M$2>26,26,$M$2)*O292,0) -> 656231 | Q292: 0 | R292: =IF(M292>0,ROUND(N292/IF(M292>26,26,M292)/8*Q292*30%,0),0) -> 0 | S292: =N292+P292+R292 -> 8531000 | T292: 0 | U292: 0 | V292: 200000 | W292: 500000 | X292: 0 | Y292: 400000 | Z292: 483317 | AC292: 100000 | AD292: 0 | AE292: 0 | AG292: =ROUND(SUM(S292:AF292)-AA292,0) -> 10214317 | AH292: 20 | AI292: 0 | AJ292: 0 | AK292: 0 | AL292: 0 | AM292: =ROUND((N292/IF(M292>26,26,M292)/8*(AH292*$AH$5+AI292*$AI$5+AJ292*$AJ$5+AK292*$AK$5+AL292*$AL$5)),0) -> 1230433 | AN292: =ROUND(AG292+AM292,0) -> 11444750 | AO292: 895755 | AP292: 44100 | AQ292: =+VLOOKUP($B292,[1]Sheet1!$C$15:$BW$1300,52,0) -> 0 | AR292: 0 | AS292: 0 | AT292: =+ROUND(SUM(AN292:AN292)-SUM(AO292:AS292),0) -> 10504895 | AW292: VO MINH THU | AX292: 050040902543 | AY292: SK1 Box | AZ292: 622 | BA292: =+IF(AY292="SK1 Box","Box",IF(AY292="Seaman","Seaman","Bag")) -> Box
... A378: =SUBTOTAL(3,B$6:B378) -> 1 | B378: C1306 | C378: Nguyễn Thị Thanh Mỹ | D378: 39776 | E378: FACTORY B | F378: P5 - Production Office | G378: Plan staff | H378: 7119000 | I378: 2500000 | J378: 0 | K378: 2000000 | L378: =SUM(H378:K378) -> 11619000 | M378: 22.6 | N378: =ROUND((H378+I378+J378+K378)/IF($M$2>26,26,$M$2)*M378,0) -> 10099592 | O378: 3 | P378: =ROUND((H378+I378+J378+K378)/IF($M$2>26,26,$M$2)*O378,0) -> 1340654 | Q378: 0 | R378: =IF(M378>0,ROUND(N378/IF(M378>26,26,M378)/8*Q378*30%,0),0) -> 0 | S378: =N378+P378+R378 -> 11440246 | T378: 0 | U378: 0 | V378: 200000 | W378: 500000 | X378: 0 | Y378: 400000 | Z378: 345834 | AC378: 100000 | AD378: 0 | AE378: 83790.863 | AG378: =ROUND(SUM(S378:AF378)-AA378,0) -> 13069871 | AH378: 0 | AI378: 0 | AJ378: 0 | AK378: 0 | AL378: 0 | AM378: =ROUND((N378/IF(M378>26,26,M378)/8*(AH378*$AH$5+AI378*$AI$5+AJ378*$AJ$5+AK378*$AK$5+AL378*$AL$5)),0) -> 0 | AN378: =ROUND(AG378+AM378,0) -> 13069871 | AO378: 1219995 | AP378: 44100 | AQ378: =+VLOOKUP($B378,[1]Sheet1!$C$15:$BW$1300,52,0) -> 0 | AR378: 0 | AS378: 0 | AT378: =+ROUND(SUM(AN378:AN378)-SUM(AO378:AS378),0) -> 11805776 | AW378: NGUYEN THI THANH MY | AX378: 050040823201 | AY378: SK1 Bag | AZ378: 627 | BA378: =+IF(AY378="SK1 Box","Box",IF(AY378="Seaman","Seaman","Bag")) -> Bag
A379: =SUBTOTAL(3,B$6:B379) -> 1 | B379: C14623 | C379: Trần Văn Hoài | D379: 44621 | E379: FACTORY B | F379: P5 - Production Office | G379: Factory manager | H379: 15800000 | I379: 20500000 | J379: 0 | K379: 0 | L379: =SUM(H379:K379) -> 36300000 | M379: 23.5 | N379: =ROUND((H379+I379+J379+K379)/IF($M$2>26,26,$M$2)*M379,0) -> 32809615 | O379: 2 | P379: =ROUND((H379+I379+J379+K379)/IF($M$2>26,26,$M$2)*O379,0) -> 2792308 | Q379: 0 | R379: =IF(M379>0,ROUND(N379/IF(M379>26,26,M379)/8*Q379*30%,0),0) -> 0 | S379: =N379+P379+R379 -> 35601923 | T379: 490385 | U379: 0 | V379: 0 | W379: 0 | X379: 0 | Y379: 0 | Z379: 0 | AC379: 0 | AD379: 0 | AE379: 0 | AG379: =ROUND(SUM(S379:AF379)-AA379,0) -> 36092308 | AH379: 0 | AI379: 0 | AJ379: 0 | AK379: 0 | AL379: 0 | AM379: =ROUND((N379/IF(M379>26,26,M379)/8*(AH379*$AH$5+AI379*$AI$5+AJ379*$AJ$5+AK379*$AK$5+AL379*$AL$5)),0) -> 0 | AN379: =ROUND(AG379+AM379,0) -> 36092308 | AO379: 3811500 | AP379: 0 | AQ379: =+VLOOKUP($B379,[1]Sheet1!$C$15:$BW$1300,52,0) -> 519042 | AR379: 0 | AS379: 0 | AT379: =+ROUND(SUM(AN379:AN379)-SUM(AO379:AS379),0) -> 31761766 | AW379: TRAN VAN HOAI | AX379: 050040818690 | AY379: SK1 Box | AZ379: 627 | BA379: Manager
A380: =SUBTOTAL(3,B$6:B380) -> 1 | B380: C14762 | C380: Bùi Thị Yến Thu | D380: 44649 | E380: FACTORY B | F380: P5 - Production Office | G380: Plan staff | H380: 5773000 | I380: 1900000 | J380: 0 | K380: 0 | L380: =SUM(H380:K380) -> 7673000 | M380: 23 | N380: =ROUND((H380+I380+J380+K380)/IF($M$2>26,26,$M$2)*M380,0) -> 6787654 | O380: 3 | P380: =ROUND((H380+I380+J380+K380)/IF($M$2>26,26,$M$2)*O380,0) -> 885346 | Q380: 0 | R380: =IF(M380>0,ROUND(N380/IF(M380>26,26,M380)/8*Q380*30%,0),0) -> 0 | S380: =N380+P380+R380 -> 7673000 | T380: 0 | U380: 0 | V380: 200000 | W380: 500000 | X380: 0 | Y380: 400000 | Z380: 351955 | AC380: 0 | AD380: 0 | AE380: 55334.136 | AG380: =ROUND(SUM(S380:AF380)-AA380,0) -> 9180289 | AH380: 0 | AI380: 0 | AJ380: 0 | AK380: 0 | AL380: 0 | AM380: =ROUND((N380/IF(M380>26,26,M380)/8*(AH380*$AH$5+AI380*$AI$5+AJ380*$AJ$5+AK380*$AK$5+AL380*$AL$5)),0) -> 0 | AN380: =ROUND(AG380+AM380,0) -> 9180289 | AO380: 805665 | AP380: 44100 | AQ380: =+VLOOKUP($B380,[1]Sheet1!$C$15:$BW$1300,52,0) -> 0 | AR380: 0 | AS380: 0 | AT380: =+ROUND(SUM(AN380:AN380)-SUM(AO380:AS380),0) -> 8330524 | AW380: BUI THI YEN THU | AX380: 050066285429 | AY380: SK1 Bag | AZ380: 627 | BA380: =+IF(AY380="SK1 Box","Box",IF(AY380="Seaman","Seaman","Bag")) -> Bag
A381: =SUBTOTAL(3,B$6:B381) -> 1 | B381: C3465 | C381: Lê Văn Khỏe | D381: 40596 | E381: FACTORY B | F381: P5 - Production Office | G381: Factory vice manager | H381: 11219000 | I381: 7300000 | J381: 0 | K381: 0 | L381: =SUM(H381:K381) -> 18519000 | M381: 22.8 | N381: =ROUND((H381+I381+J381+K381)/IF($M$2>26,26,$M$2)*M381,0) -> 16239738 | O381: 3 | P381: =ROUND((H381+I381+J381+K381)/IF($M$2>26,26,$M$2)*O381,0) -> 2136808 | Q381: 0 | R381: =IF(M381>0,ROUND(N381/IF(M381>26,26,M381)/8*Q381*30%,0),0) -> 0 | S381: =N381+P381+R381 -> 18376546 | T381: 0 | U381: 0 | V381: 200000 | W381: 500000 | X381: 0 | Y381: 400000 | Z381: 0 | AC381: 0 | AD381: 0 | AE381: 0 | AG381: =ROUND(SUM(S381:AF381)-AA381,0) -> 19476546 | AH381: 17 | AI381: 0 | AJ381: 0 | AK381: 0 | AL381: 0 | AM381: =ROUND((N381/IF(M381>26,26,M381)/8*(AH381*$AH$5+AI381*$AI$5+AJ381*$AJ$5+AK381*$AK$5+AL381*$AL$5)),0) -> 2270358 | AN381: =ROUND(AG381+AM381,0) -> 21746904 | AO381: 1944495 | AP381: 44100 | AQ381: =+VLOOKUP($B381,[1]Sheet1!$C$15:$BW$1300,52,0) -> 0 | AR381: 0 | AS381: 0 | AT381: =+ROUND(SUM(AN381:AN381)-SUM(AO381:AS381),0) -> 19758309 | AW381: LE VAN KHOE | AX381: 050040934399 | AY381: SK1 Box | AZ381: 627 | BA381: =+IF(AY381="SK1 Box","Box",IF(AY381="Seaman","Seaman","Bag")) -> Box
A382: =SUBTOTAL(3,B$6:B382) -> 1 | B382: C4110 | C382: Đàm Thị Thủy | D382: 40819 | E382: FACTORY B | F382: P5 - Production Office | G382: Factory vice manager | H382: 8076000 | I382: 7300000 | J382: 0 | K382: 0 | L382: =SUM(H382:K382) -> 15376000 | M382: 24 | N382: =ROUND((H382+I382+J382+K382)/IF($M$2>26,26,$M$2)*M382,0) -> 14193231 | O382: 2 | P382: =ROUND((H382+I382+J382+K382)/IF($M$2>26,26,$M$2)*O382,0) -> 1182769 | Q382: 0 | R382: =IF(M382>0,ROUND(N382/IF(M382>26,26,M382)/8*Q382*30%,0),0) -> 0 | S382: =N382+P382+R382 -> 15376000 | T382: 0 | U382: 0 | V382: 200000 | W382: 500000 | X382: 0 | Y382: 400000 | Z382: 0 | AC382: 0 | AD382: 0 | AE382: 110884.62 | AG382: =ROUND(SUM(S382:AF382)-AA382,0) -> 16586885 | AH382: 25 | AI382: 0 | AJ382: 0 | AK382: 0 | AL382: 0 | AM382: =ROUND((N382/IF(M382>26,26,M382)/8*(AH382*$AH$5+AI382*$AI$5+AJ382*$AJ$5+AK382*$AK$5+AL382*$AL$5)),0) -> 2772115 | AN382: =ROUND(AG382+AM382,0) -> 19359000 | AO382: 1614480 | AP382: 44100 | AQ382: =+VLOOKUP($B382,[1]Sheet1!$C$15:$BW$1300,52,0) -> 0 | AR382: 0 | AS382: 0 | AT382: =+ROUND(SUM(AN382:AN382)-SUM(AO382:AS382),0) -> 17700420 | AW382: DAM THI THUY | AX382: 050040820369 | AY382: SK1 Bag | AZ382: 627 | BA382: =+IF(AY382="SK1 Box","Box",IF(AY382="Seaman","Seaman","Bag")) -> Bag
A383: =SUBTOTAL(3,B$6:B383) -> 1 | B383: C15710 | C383: Văn Thị Vũ Thường | D383: 45360 | E383: FACTORY B | F383: P5 - QC | G383: Bag QC vice leader | H383: 5538000 | I383: 1900000 | J383: 0 | K383: 0 | L383: =SUM(H383:K383) -> 7438000 | M383: 22 | N383: =ROUND((H383+I383+J383+K383)/IF($M$2>26,26,$M$2)*M383,0) -> 6293692 | O383: 2 | P383: =ROUND((H383+I383+J383+K383)/IF($M$2>26,26,$M$2)*O383,0) -> 572154 | Q383: 0 | R383: =IF(M383>0,ROUND(N383/IF(M383>26,26,M383)/8*Q383*30%,0),0) -> 0 | S383: =N383+P383+R383 -> 6865846 | T383: 0 | U383: 0 | V383: 200000 | W383: 0 | X383: 0 | Y383: 300000 | Z383: 458300 | AC383: 100000 | AD383: 0 | AE383: 53639.42 | AG383: =ROUND(SUM(S383:AF383)-AA383,0) -> 7977785 | AH383: 16 | AI383: 0 | AJ383: 0 | AK383: 0 | AL383: 0 | AM383: =ROUND((N383/IF(M383>26,26,M383)/8*(AH383*$AH$5+AI383*$AI$5+AJ383*$AJ$5+AK383*$AK$5+AL383*$AL$5)),0) -> 858231 | AN383: =ROUND(AG383+AM383,0) -> 8836016 | AO383: 780990 | AP383: 44100 | AQ383: =+VLOOKUP($B383,[1]Sheet1!$C$15:$BW$1300,52,0) -> 0 | AR383: 0 | AS383: 0 | AT383: =+ROUND(SUM(AN383:AN383)-SUM(AO383:AS383),0) -> 8010926 | AW383: VAN THI VU THUONG | AX383: 050040823015 | AY383: SK1 Bag | AZ383: 622 | BA383: =+IF(AY383="SK1 Box","Box",IF(AY383="Seaman","Seaman","Bag")) -> Bag
A384: =SUBTOTAL(3,B$6:B384) -> 1 | B384: C15937 | C384: Lê Thị Cẩm Nhung | D384: 45432 | E384: FACTORY B | F384: P5 - QC | G384: QC worker | H384: 5274000 | I384: 500000 | J384: 0 | K384: 0 | L384: =SUM(H384:K384) -> 5774000 | M384: 24 | N384: =ROUND((H384+I384+J384+K384)/IF($M$2>26,26,$M$2)*M384,0) -> 5329846 | O384: 2 | P384: =ROUND((H384+I384+J384+K384)/IF($M$2>26,26,$M$2)*O384,0) -> 444154 | Q384: 0 | R384: =IF(M384>0,ROUND(N384/IF(M384>26,26,M384)/8*Q384*30%,0),0) -> 0 | S384: =N384+P384+R384 -> 5774000 | T384: 0 | U384: 0 | V384: 200000 | W384: 500000 | X384: 0 | Y384: 400000 | Z384: 400000 | AC384: 0 | AD384: 0 | AE384: 41639.422 | AG384: =ROUND(SUM(S384:AF384)-AA384,0) -> 7315639 | AH384: 20 | AI384: 0 | AJ384: 0 | AK384: 0 | AL384: 0 | AM384: =ROUND((N384/IF(M384>26,26,M384)/8*(AH384*$AH$5+AI384*$AI$5+AJ384*$AJ$5+AK384*$AK$5+AL384*$AL$5)),0) -> 832788 | AN384: =ROUND(AG384+AM384,0) -> 8148427 | AO384: 606270 | AP384: 44100 | AQ384: =+VLOOKUP($B384,[1]Sheet1!$C$15:$BW$1300,52,0) -> 0 | AR384: 0 | AS384: 0 | AT384: =+ROUND(SUM(AN384:AN384)-SUM(AO384:AS384),0) -> 7498057 | AW384: LE THI CAM NHUNG | AX384: 050153430923 | AY384: SK1 Box | AZ384: 622 | BA384: =+IF(AY384="SK1 Box","Box",IF(AY384="Seaman","Seaman","Bag")) -> Box
A385: =SUBTOTAL(3,B$6:B385) -> 1 | B385: C16417 | C385: Huỳnh Thị Thu Hương | D385: 45696 | E385: FACTORY B | F385: P5 - QC | G385: QC worker | H385: 5023000 | I385: 500000 | J385: 0 | K385: 0 | L385: =SUM(H385:K385) -> 5523000 | M385: 24 | N385: =ROUND((H385+I385+J385+K385)/IF($M$2>26,26,$M$2)*M385,0) -> 5098154 | O385: 2 | P385: =ROUND((H385+I385+J385+K385)/IF($M$2>26,26,$M$2)*O385,0) -> 424846 | Q385: 0 | R385: =IF(M385>0,ROUND(N385/IF(M385>26,26,M385)/8*Q385*30%,0),0) -> 0 | S385: =N385+P385+R385 -> 5523000 | T385: 0 | U385: 0 | V385: 200000 | W385: 500000 | X385: 0 | Y385: 400000 | Z385: 400000 | AC385: 0 | AD385: 0 | AE385: 39829.328 | AG385: =ROUND(SUM(S385:AF385)-AA385,0) -> 7062829 | AH385: 24 | AI385: 0 | AJ385: 0 | AK385: 0 | AL385: 0 | AM385: =ROUND((N385/IF(M385>26,26,M385)/8*(AH385*$AH$5+AI385*$AI$5+AJ385*$AJ$5+AK385*$AK$5+AL385*$AL$5)),0) -> 955904 | AN385: =ROUND(AG385+AM385,0) -> 8018733 | AO385: 579915 | AP385: 44100 | AQ385: =+VLOOKUP($B385,[1]Sheet1!$C$15:$BW$1300,52,0) -> 0 | AR385: 0 | AS385: 0 | AT385: =+ROUND(SUM(AN385:AN385)-SUM(AO385:AS385),0) -> 7394718 | AW385: HUYNH THI THU HUONG | AX385: 050133547131 | AY385: SK1 Box | AZ385: 622 | BA385: =+IF(AY385="SK1 Box","Box",IF(AY385="Seaman","Seaman","Bag")) -> Box
A386: =SUBTOTAL(3,B$6:B386) -> 1 | B386: C16447 | C386: Võ Thị Bích Ngọc | D386: 45706 | E386: FACTORY B | F386: P5 - QC | G386: QC worker | H386: 5023000 | I386: 500000 | J386: 0 | K386: 0 | L386: =SUM(H386:K386) -> 5523000 | M386: 22.8 | N386: =ROUND((H386+I386+J386+K386)/IF($M$2>26,26,$M$2)*M386,0) -> 4843246 | O386: 3 | P386: =ROUND((H386+I386+J386+K386)/IF($M$2>26,26,$M$2)*O386,0) -> 637269 | Q386: 0 | R386: =IF(M386>0,ROUND(N386/IF(M386>26,26,M386)/8*Q386*30%,0),0) -> 0 | S386: =N386+P386+R386 -> 5480515 | T386: 0 | U386: 0 | V386: 200000 | W386: 500000 | X386: 0 | Y386: 400000 | Z386: 285000 | AC386: 0 | AD386: 0 | AE386: 39829.326 | AG386: =ROUND(SUM(S386:AF386)-AA386,0) -> 6905344 | AH386: 12 | AI386: 0 | AJ386: 0 | AK386: 0 | AL386: 0 | AM386: =ROUND((N386/IF(M386>26,26,M386)/8*(AH386*$AH$5+AI386*$AI$5+AJ386*$AJ$5+AK386*$AK$5+AL386*$AL$5)),0) -> 477952 | AN386: =ROUND(AG386+AM386,0) -> 7383296 | AO386: 579915 | AP386: 44100 | AQ386: =+VLOOKUP($B386,[1]Sheet1!$C$15:$BW$1300,52,0) -> 0 | AR386: 0 | AS386: 0 | AT386: =+ROUND(SUM(AN386:AN386)-SUM(AO386:AS386),0) -> 6759281 | AW386: VO THI BICH NGOC | AX386: 050118892981 | AY386: SK1 Bag | AZ386: 622 | BA386: =+IF(AY386="SK1 Box","Box",IF(AY386="Seaman","Seaman","Bag")) -> Bag
A387: =SUBTOTAL(3,B$6:B387) -> 1 | B387: C2079 | C387: Huỳnh Mẫu Bảy | D387: 40091 | E387: FACTORY B | F387: P5 - QC | G387: Bag QC leader | H387: 6641000 | I387: 3200000 | J387: 0 | K387: 2000000 | L387: =SUM(H387:K387) -> 11841000 | M387: 24 | N387: =ROUND((H387+I387+J387+K387)/IF($M$2>26,26,$M$2)*M387,0) -> 10930154 | O387: 2 | P387: =ROUND((H387+I387+J387+K387)/IF($M$2>26,26,$M$2)*O387,0) -> 910846 | Q387: 0 | R387: =IF(M387>0,ROUND(N387/IF(M387>26,26,M387)/8*Q387*30%,0),0) -> 0 | S387: =N387+P387+R387 -> 11841000 | T387: 0 | U387: 0 | V387: 200000 | W387: 500000 | X387: 0 | Y387: 400000 | Z387: 700000 | AC387: 0 | AD387: 0 | AE387: 0 | AG387: =ROUND(SUM(S387:AF387)-AA387,0) -> 13641000 | AH387: 24 | AI387: 0 | AJ387: 0 | AK387: 0 | AL387: 0 | AM387: =ROUND((N387/IF(M387>26,26,M387)/8*(AH387*$AH$5+AI387*$AI$5+AJ387*$AJ$5+AK387*$AK$5+AL387*$AL$5)),0) -> 2049404 | AN387: =ROUND(AG387+AM387,0) -> 15690404 | AO387: 1243305 | AP387: 44100 | AQ387: =+VLOOKUP($B387,[1]Sheet1!$C$15:$BW$1300,52,0) -> 0 | AR387: 0 | AS387: 0 | AT387: =+ROUND(SUM(AN387:AN387)-SUM(AO387:AS387),0) -> 14402999 | AW387: HUYNH MAU BAY | AX387: 050040931926 | AY387: SK1 Bag | AZ387: 622 | BA387: =+IF(AY387="SK1 Box","Box",IF(AY387="Seaman","Seaman","Bag")) -> Bag
A388: =SUBTOTAL(3,B$6:B388) -> 1 | B388: C5204 | C388: Lê Mộng Hằng | D388: 41172 | E388: FACTORY B | F388: P5 - QC | G388: QC worker | H388: 5931000 | I388: 1100000 | J388: 0 | K388: 0 | L388: =SUM(H388:K388) -> 7031000 | M388: 24 | N388: =ROUND((H388+I388+J388+K388)/IF($M$2>26,26,$M$2)*M388,0) -> 6490154 | O388: 2 | P388: =ROUND((H388+I388+J388+K388)/IF($M$2>26,26,$M$2)*O388,0) -> 540846 | Q388: 0 | R388: =IF(M388>0,ROUND(N388/IF(M388>26,26,M388)/8*Q388*30%,0),0) -> 0 | S388: =N388+P388+R388 -> 7031000 | T388: 0 | U388: 0 | V388: 200000 | W388: 500000 | X388: 0 | Y388: 400000 | Z388: 400000 | AC388: 0 | AD388: 0 | AE388: 50704.328 | AG388: =ROUND(SUM(S388:AF388)-AA388,0) -> 8581704 | AH388: 20 | AI388: 0 | AJ388: 0 | AK388: 0 | AL388: 0 | AM388: =ROUND((N388/IF(M388>26,26,M388)/8*(AH388*$AH$5+AI388*$AI$5+AJ388*$AJ$5+AK388*$AK$5+AL388*$AL$5)),0) -> 1014087 | AN388: =ROUND(AG388+AM388,0) -> 9595791 | AO388: 738255 | AP388: 44100 | AQ388: =+VLOOKUP($B388,[1]Sheet1!$C$15:$BW$1300,52,0) -> 0 | AR388: 0 | AS388: 0 | AT388: =+ROUND(SUM(AN388:AN388)-SUM(AO388:AS388),0) -> 8813436 | AW388: LE MONG HANG | AX388: 050040924237 | AY388: SK1 Box | AZ388: 622 | BA388: =+IF(AY388="SK1 Box","Box",IF(AY388="Seaman","Seaman","Bag")) -> Box
A389: =SUBTOTAL(3,B$6:B389) -> 1 | B389: C5531 | C389: Vũ Thị Phương | D389: 41334 | E389: FACTORY B | F389: P5 - QC | G389: QC worker | H389: 5931000 | I389: 1100000 | J389: 0 | K389: 500000 | L389: =SUM(H389:K389) -> 7531000 | M389: 22.9 | N389: =ROUND((H389+I389+J389+K389)/IF($M$2>26,26,$M$2)*M389,0) -> 6633073 | O389: 3 | P389: =ROUND((H389+I389+J389+K389)/IF($M$2>26,26,$M$2)*O389,0) -> 868962 | Q389: 0 | R389: =IF(M389>0,ROUND(N389/IF(M389>26,26,M389)/8*Q389*30%,0),0) -> 0 | S389: =N389+P389+R389 -> 7502035 | T389: 0 | U389: 0 | V389: 200000 | W389: 500000 | X389: 0 | Y389: 400000 | Z389: 381700 | AC389: 100000 | AD389: 0 | AE389: 54310.096 | AG389: =ROUND(SUM(S389:AF389)-AA389,0) -> 9138045 | AH389: 16 | AI389: 0 | AJ389: 0 | AK389: 0 | AL389: 0 | AM389: =ROUND((N389/IF(M389>26,26,M389)/8*(AH389*$AH$5+AI389*$AI$5+AJ389*$AJ$5+AK389*$AK$5+AL389*$AL$5)),0) -> 868962 | AN389: =ROUND(AG389+AM389,0) -> 10007007 | AO389: 790755 | AP389: 44100 | AQ389: =+VLOOKUP($B389,[1]Sheet1!$C$15:$BW$1300,52,0) -> 0 | AR389: 0 | AS389: 0 | AT389: =+ROUND(SUM(AN389:AN389)-SUM(AO389:AS389),0) -> 9172152 | AW389: VU THI PHUONG | AX389: 050040932450 | AY389: SK1 Bag | AZ389: 622 | BA389: =+IF(AY389="SK1 Box","Box",IF(AY389="Seaman","Seaman","Bag")) -> Bag
A390: =SUBTOTAL(3,B$6:B390) -> 1 | B390: C13967 | C390: Lê Thị Huỳnh Như | D390: 44306 | E390: FACTORY B | F390: P5 - Semi HS Bag | G390: Semi Machine sub-operator | H390: 5931000 | I390: 400000 | J390: 0 | K390: 0 | L390: =SUM(H390:K390) -> 6331000 | M390: 24 | N390: =ROUND((H390+I390+J390+K390)/IF($M$2>26,26,$M$2)*M390,0) -> 5844000 | O390: 2 | P390: =ROUND((H390+I390+J390+K390)/IF($M$2>26,26,$M$2)*O390,0) -> 487000 | Q390: 0 | R390: =IF(M390>0,ROUND(N390/IF(M390>26,26,M390)/8*Q390*30%,0),0) -> 0 | S390: =N390+P390+R390 -> 6331000 | T390: 0 | U390: 0 | V390: 200000 | W390: 500000 | X390: 0 | Y390: 400000 | Z390: 556478 | AC390: 100000 | AD390: 0 | AE390: 45656.25 | AG390: =ROUND(SUM(S390:AF390)-AA390,0) -> 8133134 | AH390: 24 | AI390: 0 | AJ390: 0 | AK390: 0 | AL390: 0 | AM390: =ROUND((N390/IF(M390>26,26,M390)/8*(AH390*$AH$5+AI390*$AI$5+AJ390*$AJ$5+AK390*$AK$5+AL390*$AL$5)),0) -> 1095750 | AN390: =ROUND(AG390+AM390,0) -> 9228884 | AO390: 664755 | AP390: 44100 | AQ390: =+VLOOKUP($B390,[1]Sheet1!$C$15:$BW$1300,52,0) -> 0 | AR390: 0 | AS390: 0 | AT390: =+ROUND(SUM(AN390:AN390)-SUM(AO390:AS390),0) -> 8520029 | AW390: LE THI HUYNH NHU | AX390: 050127733071 | AY390: SK1 Bag | AZ390: 622 | BA390: =+IF(AY390="SK1 Box","Box",IF(AY390="Seaman","Seaman","Bag")) -> Bag
A391: =SUBTOTAL(3,B$6:B391) -> 1 | B391: C1478 | C391: Nguyễn Thị Ngọc Lan | D391: 39811 | E391: FACTORY B | F391: P5 - Semi HS Bag | G391: Semi machine operator | H391: 5931000 | I391: 900000 | J391: 0 | K391: 0 | L391: =SUM(H391:K391) -> 6831000 | M391: 23 | N391: =ROUND((H391+I391+J391+K391)/IF($M$2>26,26,$M$2)*M391,0) -> 6042808 | O391: 3 | P391: =ROUND((H391+I391+J391+K391)/IF($M$2>26,26,$M$2)*O391,0) -> 788192 | Q391: 0 | R391: =IF(M391>0,ROUND(N391/IF(M391>26,26,M391)/8*Q391*30%,0),0) -> 0 | S391: =N391+P391+R391 -> 6831000 | T391: 0 | U391: 0 | V391: 200000 | W391: 500000 | X391: 0 | Y391: 400000 | Z391: 334718 | AC391: 0 | AD391: 0 | AE391: 49262.022 | AG391: =ROUND(SUM(S391:AF391)-AA391,0) -> 8314980 | AH391: 20 | AI391: 0 | AJ391: 0 | AK391: 0 | AL391: 0 | AM391: =ROUND((N391/IF(M391>26,26,M391)/8*(AH391*$AH$5+AI391*$AI$5+AJ391*$AJ$5+AK391*$AK$5+AL391*$AL$5)),0) -> 985240 | AN391: =ROUND(AG391+AM391,0) -> 9300220 | AO391: 717255 | AP391: 44100 | AQ391: =+VLOOKUP($B391,[1]Sheet1!$C$15:$BW$1300,52,0) -> 0 | AR391: 0 | AS391: 0 | AT391: =+ROUND(SUM(AN391:AN391)-SUM(AO391:AS391),0) -> 8538865 | AW391: NGUYEN THI NGOC LAN | AX391: 050040931748 | AY391: SK1 Bag | AZ391: 622 | BA391: =+IF(AY391="SK1 Box","Box",IF(AY391="Seaman","Seaman","Bag")) -> Bag
... A550: =SUBTOTAL(3,B$6:B550) -> 1 | B550: C16543 | C550: Đỗ Hoài Hận | D550: 45736 | E550: FACTORY D | F550: P4 - FB2-4 | G550: Normal worker | H550: 4694000 | I550: 0 | J550: 0 | K550: 0 | L550: =SUM(H550:K550) -> 4694000 | M550: 23 | N550: =ROUND((H550+I550+J550+K550)/IF($M$2>26,26,$M$2)*M550,0) -> 4152385 | O550: 3 | P550: =ROUND((H550+I550+J550+K550)/IF($M$2>26,26,$M$2)*O550,0) -> 541615 | Q550: 0 | R550: =IF(M550>0,ROUND(N550/IF(M550>26,26,M550)/8*Q550*30%,0),0) -> 0 | S550: =N550+P550+R550 -> 4694000 | T550: 0 | U550: 0 | V550: 200000 | W550: 500000 | X550: 0 | Y550: 400000 | Z550: 185238 | AC550: 0 | AD550: 113884 | AE550: 0 | AG550: =ROUND(SUM(S550:AF550)-AA550,0) -> 6093122 | AH550: 12 | AI550: 0 | AJ550: 0 | AK550: 0 | AL550: 0 | AM550: =ROUND((N550/IF(M550>26,26,M550)/8*(AH550*$AH$5+AI550*$AI$5+AJ550*$AJ$5+AK550*$AK$5+AL550*$AL$5)),0) -> 406212 | AN550: =ROUND(AG550+AM550,0) -> 6499334 | AO550: 0 | AP550: 0 | AQ550: =+VLOOKUP($B550,[1]Sheet1!$C$15:$BW$1300,52,0) -> 0 | AR550: 0 | AS550: 0 | AT550: =+ROUND(SUM(AN550:AN550)-SUM(AO550:AS550),0) -> 6499334 | AW550: DO HOAI HAN | AX550: 056409022006 | AY550: SK1 Bag | AZ550: 622 | BA550: =+IF(AY550="SK1 Box","Box",IF(AY550="Seaman","Seaman","Bag")) -> Bag
A551: =SUBTOTAL(3,B$6:B551) -> 1 | B551: C16629 | C551: Mạc Thị Hòa | D551: 45771 | E551: FACTORY D | F551: P4 - FB2-4 | G551: New worker | H551: 4694000 | I551: 0 | J551: 0 | K551: 0 | L551: =SUM(H551:K551) -> 4694000 | M551: 5 | N551: =ROUND((H551+I551+J551+K551)/IF($M$2>26,26,$M$2)*M551,0) -> 902692 | O551: 1 | P551: =ROUND((H551+I551+J551+K551)/IF($M$2>26,26,$M$2)*O551,0) -> 180538 | Q551: 0 | R551: =IF(M551>0,ROUND(N551/IF(M551>26,26,M551)/8*Q551*30%,0),0) -> 0 | S551: =N551+P551+R551 -> 1083230 | T551: 0 | U551: 0 | V551: 46000 | W551: 115000 | X551: 0 | Y551: 35000 | Z551: 0 | AC551: 0 | AD551: 0 | AE551: 0 | AG551: =ROUND(SUM(S551:AF551)-AA551,0) -> 1279230 | AH551: 0 | AI551: 0 | AJ551: 0 | AK551: 0 | AL551: 0 | AM551: =ROUND((N551/IF(M551>26,26,M551)/8*(AH551*$AH$5+AI551*$AI$5+AJ551*$AJ$5+AK551*$AK$5+AL551*$AL$5)),0) -> 0 | AN551: =ROUND(AG551+AM551,0) -> 1279230 | AO551: 0 | AP551: 0 | AQ551: =+VLOOKUP($B551,[1]Sheet1!$C$15:$BW$1300,52,0) -> 0 | AR551: 0 | AS551: 0 | AT551: =+ROUND(SUM(AN551:AN551)-SUM(AO551:AS551),0) -> 1279230 | AX551: TM | AY551: SK1 Bag | AZ551: 622 | BA551: =+IF(AY551="SK1 Box","Box",IF(AY551="Seaman","Seaman","Bag")) -> Bag
A552: =SUBTOTAL(3,B$6:B552) -> 1 | B552: C4213 | C552: Thị Liên | D552: 40835 | E552: FACTORY D | F552: P4 - FB2-4 | G552: Normal worker | H552: 5931000 | I552: 0 | J552: 0 | K552: 0 | L552: =SUM(H552:K552) -> 5931000 | M552: 24 | N552: =ROUND((H552+I552+J552+K552)/IF($M$2>26,26,$M$2)*M552,0) -> 5474769 | O552: 2 | P552: =ROUND((H552+I552+J552+K552)/IF($M$2>26,26,$M$2)*O552,0) -> 456231 | Q552: 0 | R552: =IF(M552>0,ROUND(N552/IF(M552>26,26,M552)/8*Q552*30%,0),0) -> 0 | S552: =N552+P552+R552 -> 5931000 | T552: 0 | U552: 0 | V552: 200000 | W552: 500000 | X552: 0 | Y552: 400000 | Z552: 535571 | AC552: 0 | AD552: 0 | AE552: 42771.633 | AG552: =ROUND(SUM(S552:AF552)-AA552,0) -> 7609343 | AH552: 12 | AI552: 0 | AJ552: 0 | AK552: 0 | AL552: 0 | AM552: =ROUND((N552/IF(M552>26,26,M552)/8*(AH552*$AH$5+AI552*$AI$5+AJ552*$AJ$5+AK552*$AK$5+AL552*$AL$5)),0) -> 513260 | AN552: =ROUND(AG552+AM552,0) -> 8122603 | AO552: 622755 | AP552: 44100 | AQ552: =+VLOOKUP($B552,[1]Sheet1!$C$15:$BW$1300,52,0) -> 0 | AR552: 0 | AS552: 0 | AT552: =+ROUND(SUM(AN552:AN552)-SUM(AO552:AS552),0) -> 7455748 | AW552: THI LIEN | AX552: 050040845418 | AY552: SK1 Bag | AZ552: 622 | BA552: =+IF(AY552="SK1 Box","Box",IF(AY552="Seaman","Seaman","Bag")) -> Bag
A553: =SUBTOTAL(3,B$6:B553) -> 1 | B553: C5326 | C553: Lê Thị Đào | D553: 41334 | E553: FACTORY D | F553: P4 - FB2-4 | G553: Normal worker | H553: 5931000 | I553: 0 | J553: 0 | K553: 0 | L553: =SUM(H553:K553) -> 5931000 | M553: 23 | N553: =ROUND((H553+I553+J553+K553)/IF($M$2>26,26,$M$2)*M553,0) -> 5246654 | O553: 3 | P553: =ROUND((H553+I553+J553+K553)/IF($M$2>26,26,$M$2)*O553,0) -> 684346 | Q553: 0 | R553: =IF(M553>0,ROUND(N553/IF(M553>26,26,M553)/8*Q553*30%,0),0) -> 0 | S553: =N553+P553+R553 -> 5931000 | T553: 0 | U553: 0 | V553: 200000 | W553: 500000 | X553: 0 | Y553: 400000 | Z553: 564405 | AC553: 100000 | AD553: 0 | AE553: 42771.636 | AG553: =ROUND(SUM(S553:AF553)-AA553,0) -> 7738177 | AH553: 12 | AI553: 0 | AJ553: 0 | AK553: 0 | AL553: 0 | AM553: =ROUND((N553/IF(M553>26,26,M553)/8*(AH553*$AH$5+AI553*$AI$5+AJ553*$AJ$5+AK553*$AK$5+AL553*$AL$5)),0) -> 513260 | AN553: =ROUND(AG553+AM553,0) -> 8251437 | AO553: 622755 | AP553: 44100 | AQ553: =+VLOOKUP($B553,[1]Sheet1!$C$15:$BW$1300,52,0) -> 0 | AR553: 0 | AS553: 0 | AT553: =+ROUND(SUM(AN553:AN553)-SUM(AO553:AS553),0) -> 7584582 | AW553: LE THI DAO | AX553: 050040934593 | AY553: SK1 Bag | AZ553: 622 | BA553: =+IF(AY553="SK1 Box","Box",IF(AY553="Seaman","Seaman","Bag")) -> Bag
A554: =SUBTOTAL(3,B$6:B554) -> 1 | B554: C6879 | C554: Phan Thị Bích | D554: 42790 | E554: FACTORY D | F554: P4 - FB2-4 | G554: Normal worker | H554: 5931000 | I554: 0 | J554: 0 | K554: 0 | L554: =SUM(H554:K554) -> 5931000 | M554: 24 | N554: =ROUND((H554+I554+J554+K554)/IF($M$2>26,26,$M$2)*M554,0) -> 5474769 | O554: 2 | P554: =ROUND((H554+I554+J554+K554)/IF($M$2>26,26,$M$2)*O554,0) -> 456231 | Q554: 0 | R554: =IF(M554>0,ROUND(N554/IF(M554>26,26,M554)/8*Q554*30%,0),0) -> 0 | S554: =N554+P554+R554 -> 5931000 | T554: 0 | U554: 0 | V554: 200000 | W554: 500000 | X554: 0 | Y554: 400000 | Z554: 476646 | AC554: 0 | AD554: 0 | AE554: 42771.633 | AG554: =ROUND(SUM(S554:AF554)-AA554,0) -> 7550418 | AH554: 12 | AI554: 0 | AJ554: 0 | AK554: 0 | AL554: 0 | AM554: =ROUND((N554/IF(M554>26,26,M554)/8*(AH554*$AH$5+AI554*$AI$5+AJ554*$AJ$5+AK554*$AK$5+AL554*$AL$5)),0) -> 513260 | AN554: =ROUND(AG554+AM554,0) -> 8063678 | AO554: 622755 | AP554: 44100 | AQ554: =+VLOOKUP($B554,[1]Sheet1!$C$15:$BW$1300,52,0) -> 0 | AR554: 0 | AS554: 0 | AT554: =+ROUND(SUM(AN554:AN554)-SUM(AO554:AS554),0) -> 7396823 | AW554: PHAN THI BICH | AX554: 050079012121 | AY554: SK1 Bag | AZ554: 622 | BA554: =+IF(AY554="SK1 Box","Box",IF(AY554="Seaman","Seaman","Bag")) -> Bag
A555: =SUBTOTAL(3,B$6:B555) -> 1 | B555: C7197 | C555: Thị Thu | D555: 43172 | E555: FACTORY D | F555: P4 - FB2-4 | G555: Normal worker | H555: 5931000 | I555: 0 | J555: 0 | K555: 0 | L555: =SUM(H555:K555) -> 5931000 | M555: 24 | N555: =ROUND((H555+I555+J555+K555)/IF($M$2>26,26,$M$2)*M555,0) -> 5474769 | O555: 2 | P555: =ROUND((H555+I555+J555+K555)/IF($M$2>26,26,$M$2)*O555,0) -> 456231 | Q555: 0 | R555: =IF(M555>0,ROUND(N555/IF(M555>26,26,M555)/8*Q555*30%,0),0) -> 0 | S555: =N555+P555+R555 -> 5931000 | T555: 0 | U555: 0 | V555: 200000 | W555: 500000 | X555: 0 | Y555: 400000 | Z555: 602971 | AC555: 0 | AD555: 0 | AE555: 42771.633 | AG555: =ROUND(SUM(S555:AF555)-AA555,0) -> 7676743 | AH555: 12 | AI555: 0 | AJ555: 0 | AK555: 0 | AL555: 0 | AM555: =ROUND((N555/IF(M555>26,26,M555)/8*(AH555*$AH$5+AI555*$AI$5+AJ555*$AJ$5+AK555*$AK$5+AL555*$AL$5)),0) -> 513260 | AN555: =ROUND(AG555+AM555,0) -> 8190003 | AO555: 622755 | AP555: 44100 | AQ555: =+VLOOKUP($B555,[1]Sheet1!$C$15:$BW$1300,52,0) -> 0 | AR555: 0 | AS555: 0 | AT555: =+ROUND(SUM(AN555:AN555)-SUM(AO555:AS555),0) -> 7523148 | AW555: THI THU | AX555: 050087243076 | AY555: SK1 Bag | AZ555: 622 | BA555: =+IF(AY555="SK1 Box","Box",IF(AY555="Seaman","Seaman","Bag")) -> Bag
A556: =SUBTOTAL(3,B$6:B556) -> 1 | B556: C7288 | C556: Hồ Thị Bông | D556: 43210 | E556: FACTORY D | F556: P4 - FB2-4 | G556: Normal worker | H556: 5931000 | I556: 0 | J556: 0 | K556: 0 | L556: =SUM(H556:K556) -> 5931000 | M556: 22 | N556: =ROUND((H556+I556+J556+K556)/IF($M$2>26,26,$M$2)*M556,0) -> 5018538 | O556: 2 | P556: =ROUND((H556+I556+J556+K556)/IF($M$2>26,26,$M$2)*O556,0) -> 456231 | Q556: 0 | R556: =IF(M556>0,ROUND(N556/IF(M556>26,26,M556)/8*Q556*30%,0),0) -> 0 | S556: =N556+P556+R556 -> 5474769 | T556: 0 | U556: 0 | V556: 200000 | W556: 0 | X556: 0 | Y556: 300000 | Z556: 514337 | AC556: 0 | AD556: 0 | AE556: 42771.631 | AG556: =ROUND(SUM(S556:AF556)-AA556,0) -> 6531878 | AH556: 12 | AI556: 0 | AJ556: 0 | AK556: 0 | AL556: 0 | AM556: =ROUND((N556/IF(M556>26,26,M556)/8*(AH556*$AH$5+AI556*$AI$5+AJ556*$AJ$5+AK556*$AK$5+AL556*$AL$5)),0) -> 513260 | AN556: =ROUND(AG556+AM556,0) -> 7045138 | AO556: 622755 | AP556: 44100 | AQ556: =+VLOOKUP($B556,[1]Sheet1!$C$15:$BW$1300,52,0) -> 0 | AR556: 0 | AS556: 0 | AT556: =+ROUND(SUM(AN556:AN556)-SUM(AO556:AS556),0) -> 6378283 | AW556: HO THI BONG | AX556: 050056785989 | AY556: SK1 Bag | AZ556: 622 | BA556: =+IF(AY556="SK1 Box","Box",IF(AY556="Seaman","Seaman","Bag")) -> Bag
A557: =SUBTOTAL(3,B$6:B557) -> 1 | B557: C7818 | C557: Nguyễn Ngọc Anh | D557: 43511 | E557: FACTORY D | F557: P4 - FB2-4 | G557: Normal worker | H557: 5931000 | I557: 0 | J557: 0 | K557: 0 | L557: =SUM(H557:K557) -> 5931000 | M557: 23 | N557: =ROUND((H557+I557+J557+K557)/IF($M$2>26,26,$M$2)*M557,0) -> 5246654 | O557: 3 | P557: =ROUND((H557+I557+J557+K557)/IF($M$2>26,26,$M$2)*O557,0) -> 684346 | Q557: 0 | R557: =IF(M557>0,ROUND(N557/IF(M557>26,26,M557)/8*Q557*30%,0),0) -> 0 | S557: =N557+P557+R557 -> 5931000 | T557: 0 | U557: 0 | V557: 200000 | W557: 500000 | X557: 0 | Y557: 400000 | Z557: 563540 | AC557: 100000 | AD557: 0 | AE557: 42771.636 | AG557: =ROUND(SUM(S557:AF557)-AA557,0) -> 7737312 | AH557: 12 | AI557: 0 | AJ557: 0 | AK557: 0 | AL557: 0 | AM557: =ROUND((N557/IF(M557>26,26,M557)/8*(AH557*$AH$5+AI557*$AI$5+AJ557*$AJ$5+AK557*$AK$5+AL557*$AL$5)),0) -> 513260 | AN557: =ROUND(AG557+AM557,0) -> 8250572 | AO557: 622755 | AP557: 44100 | AQ557: =+VLOOKUP($B557,[1]Sheet1!$C$15:$BW$1300,52,0) -> 0 | AR557: 0 | AS557: 0 | AT557: =+ROUND(SUM(AN557:AN557)-SUM(AO557:AS557),0) -> 7583717 | AW557: NGUYEN NGOC ANH | AX557: 050103659067 | AY557: SK1 Bag | AZ557: 622 | BA557: =+IF(AY557="SK1 Box","Box",IF(AY557="Seaman","Seaman","Bag")) -> Bag
A558: =SUBTOTAL(3,B$6:B558) -> 1 | B558: C8002 | C558: Trần Thị Lan | D558: 43517 | E558: FACTORY D | F558: P4 - FB2-4 | G558: Drill worker | H558: 5931000 | I558: 200000 | J558: 0 | K558: 0 | L558: =SUM(H558:K558) -> 6131000 | M558: 23 | N558: =ROUND((H558+I558+J558+K558)/IF($M$2>26,26,$M$2)*M558,0) -> 5423577 | O558: 3 | P558: =ROUND((H558+I558+J558+K558)/IF($M$2>26,26,$M$2)*O558,0) -> 707423 | Q558: 0 | R558: =IF(M558>0,ROUND(N558/IF(M558>26,26,M558)/8*Q558*30%,0),0) -> 0 | S558: =N558+P558+R558 -> 6131000 | T558: 0 | U558: 0 | V558: 200000 | W558: 500000 | X558: 0 | Y558: 400000 | Z558: 453910 | AC558: 0 | AD558: 0 | AE558: 44213.943 | AG558: =ROUND(SUM(S558:AF558)-AA558,0) -> 7729124 | AH558: 12 | AI558: 0 | AJ558: 0 | AK558: 0 | AL558: 0 | AM558: =ROUND((N558/IF(M558>26,26,M558)/8*(AH558*$AH$5+AI558*$AI$5+AJ558*$AJ$5+AK558*$AK$5+AL558*$AL$5)),0) -> 530567 | AN558: =ROUND(AG558+AM558,0) -> 8259691 | AO558: 643755 | AP558: 44100 | AQ558: =+VLOOKUP($B558,[1]Sheet1!$C$15:$BW$1300,52,0) -> 0 | AR558: 0 | AS558: 0 | AT558: =+ROUND(SUM(AN558:AN558)-SUM(AO558:AS558),0) -> 7571836 | AW558: TRAN THI LAN | AX558: 050103659075 | AY558: SK1 Bag | AZ558: 622 | BA558: =+IF(AY558="SK1 Box","Box",IF(AY558="Seaman","Seaman","Bag")) -> Bag
A559: =SUBTOTAL(3,B$6:B559) -> 1 | B559: C8063 | C559: Điểu Sơn | D559: 43522 | E559: FACTORY D | F559: P4 - FB2-4 | G559: Drill worker | H559: 5931000 | I559: 200000 | J559: 0 | K559: 0 | L559: =SUM(H559:K559) -> 6131000 | M559: 23.8 | N559: =ROUND((H559+I559+J559+K559)/IF($M$2>26,26,$M$2)*M559,0) -> 5612223 | O559: 2 | P559: =ROUND((H559+I559+J559+K559)/IF($M$2>26,26,$M$2)*O559,0) -> 471615 | Q559: 0 | R559: =IF(M559>0,ROUND(N559/IF(M559>26,26,M559)/8*Q559*30%,0),0) -> 0 | S559: =N559+P559+R559 -> 6083838 | T559: 0 | U559: 0 | V559: 200000 | W559: 500000 | X559: 0 | Y559: 400000 | Z559: 457058 | AC559: 100000 | AD559: 0 | AE559: 0 | AG559: =ROUND(SUM(S559:AF559)-AA559,0) -> 7740896 | AH559: 12 | AI559: 0 | AJ559: 0 | AK559: 0 | AL559: 0 | AM559: =ROUND((N559/IF(M559>26,26,M559)/8*(AH559*$AH$5+AI559*$AI$5+AJ559*$AJ$5+AK559*$AK$5+AL559*$AL$5)),0) -> 530567 | AN559: =ROUND(AG559+AM559,0) -> 8271463 | AO559: 643755 | AP559: 44100 | AQ559: =+VLOOKUP($B559,[1]Sheet1!$C$15:$BW$1300,52,0) -> 0 | AR559: 0 | AS559: 0 | AT559: =+ROUND(SUM(AN559:AN559)-SUM(AO559:AS559),0) -> 7583608 | AW559: DIEU SON | AX559: 050106514388 | AY559: SK1 Bag | AZ559: 622 | BA559: =+IF(AY559="SK1 Box","Box",IF(AY559="Seaman","Seaman","Bag")) -> Bag
A560: =SUBTOTAL(3,B$6:B560) -> 1 | B560: C8064 | C560: Hồ Thị Nhạ | D560: 43522 | E560: FACTORY D | F560: P4 - FB2-4 | G560: Drill worker | H560: 5931000 | I560: 200000 | J560: 0 | K560: 0 | L560: =SUM(H560:K560) -> 6131000 | M560: 23.8 | N560: =ROUND((H560+I560+J560+K560)/IF($M$2>26,26,$M$2)*M560,0) -> 5612223 | O560: 2 | P560: =ROUND((H560+I560+J560+K560)/IF($M$2>26,26,$M$2)*O560,0) -> 471615 | Q560: 0 | R560: =IF(M560>0,ROUND(N560/IF(M560>26,26,M560)/8*Q560*30%,0),0) -> 0 | S560: =N560+P560+R560 -> 6083838 | T560: 0 | U560: 0 | V560: 200000 | W560: 500000 | X560: 0 | Y560: 400000 | Z560: 571506 | AC560: 0 | AD560: 0 | AE560: 44213.942 | AG560: =ROUND(SUM(S560:AF560)-AA560,0) -> 7799558 | AH560: 12 | AI560: 0 | AJ560: 0 | AK560: 0 | AL560: 0 | AM560: =ROUND((N560/IF(M560>26,26,M560)/8*(AH560*$AH$5+AI560*$AI$5+AJ560*$AJ$5+AK560*$AK$5+AL560*$AL$5)),0) -> 530567 | AN560: =ROUND(AG560+AM560,0) -> 8330125 | AO560: 643755 | AP560: 44100 | AQ560: =+VLOOKUP($B560,[1]Sheet1!$C$15:$BW$1300,52,0) -> 0 | AR560: 0 | AS560: 0 | AT560: =+ROUND(SUM(AN560:AN560)-SUM(AO560:AS560),0) -> 7642270 | AW560: HO THI NHA | AX560: 050103659032 | AY560: SK1 Bag | AZ560: 622 | BA560: =+IF(AY560="SK1 Box","Box",IF(AY560="Seaman","Seaman","Bag")) -> Bag
A561: =SUBTOTAL(3,B$6:B561) -> 1 | B561: C8293 | C561: Phan Nhật Hoàng | D561: 43532 | E561: FACTORY D | F561: P4 - FB2-4 | G561: Normal worker | H561: 5931000 | I561: 0 | J561: 0 | K561: 0 | L561: =SUM(H561:K561) -> 5931000 | M561: 23 | N561: =ROUND((H561+I561+J561+K561)/IF($M$2>26,26,$M$2)*M561,0) -> 5246654 | O561: 3 | P561: =ROUND((H561+I561+J561+K561)/IF($M$2>26,26,$M$2)*O561,0) -> 684346 | Q561: 0 | R561: =IF(M561>0,ROUND(N561/IF(M561>26,26,M561)/8*Q561*30%,0),0) -> 0 | S561: =N561+P561+R561 -> 5931000 | T561: 0 | U561: 0 | V561: 200000 | W561: 500000 | X561: 0 | Y561: 400000 | Z561: 480130 | AC561: 0 | AD561: 0 | AE561: 0 | AG561: =ROUND(SUM(S561:AF561)-AA561,0) -> 7511130 | AH561: 12 | AI561: 0 | AJ561: 0 | AK561: 0 | AL561: 0 | AM561: =ROUND((N561/IF(M561>26,26,M561)/8*(AH561*$AH$5+AI561*$AI$5+AJ561*$AJ$5+AK561*$AK$5+AL561*$AL$5)),0) -> 513260 | AN561: =ROUND(AG561+AM561,0) -> 8024390 | AO561: 622755 | AP561: 44100 | AQ561: =+VLOOKUP($B561,[1]Sheet1!$C$15:$BW$1300,52,0) -> 0 | AR561: 0 | AS561: 0 | AT561: =+ROUND(SUM(AN561:AN561)-SUM(AO561:AS561),0) -> 7357535 | AW561: PHAN NHAT HOANG | AX561: 050103659482 | AY561: SK1 Bag | AZ561: 622 | BA561: =+IF(AY561="SK1 Box","Box",IF(AY561="Seaman","Seaman","Bag")) -> Bag
A562: =SUBTOTAL(3,B$6:B562) -> 1 | B562: C10604 | C562: Lê Anh Vũ | D562: 43575 | E562: FACTORY D | F562: P4 - FB2-5 | G562: Normal worker | H562: 5931000 | I562: 0 | J562: 0 | K562: 0 | L562: =SUM(H562:K562) -> 5931000 | M562: 22 | N562: =ROUND((H562+I562+J562+K562)/IF($M$2>26,26,$M$2)*M562,0) -> 5018538 | O562: 3 | P562: =ROUND((H562+I562+J562+K562)/IF($M$2>26,26,$M$2)*O562,0) -> 684346 | Q562: 0 | R562: =IF(M562>0,ROUND(N562/IF(M562>26,26,M562)/8*Q562*30%,0),0) -> 0 | S562: =N562+P562+R562 -> 5702884 | T562: 0 | U562: 0 | V562: 200000 | W562: 0 | X562: 0 | Y562: 300000 | Z562: 553222 | AC562: 0 | AD562: 0 | AE562: 0 | AG562: =ROUND(SUM(S562:AF562)-AA562,0) -> 6756106 | AH562: 12 | AI562: 0 | AJ562: 0 | AK562: 0 | AL562: 0 | AM562: =ROUND((N562/IF(M562>26,26,M562)/8*(AH562*$AH$5+AI562*$AI$5+AJ562*$AJ$5+AK562*$AK$5+AL562*$AL$5)),0) -> 513260 | AN562: =ROUND(AG562+AM562,0) -> 7269366 | AO562: 622755 | AP562: 44100 | AQ562: =+VLOOKUP($B562,[1]Sheet1!$C$15:$BW$1300,52,0) -> 0 | AR562: 0 | AS562: 0 | AT562: =+ROUND(SUM(AN562:AN562)-SUM(AO562:AS562),0) -> 6602511 | AW562: LE ANH VU | AX562: 050106621176 | AY562: SK1 Bag | AZ562: 622 | BA562: =+IF(AY562="SK1 Box","Box",IF(AY562="Seaman","Seaman","Bag")) -> Bag
A563: =SUBTOTAL(3,B$6:B563) -> 1 | B563: C13707 | C563: Nguyễn Thị Hoàng | D563: 44281 | E563: FACTORY D | F563: P4 - FB2-5 | G563: Normal worker | H563: 5931000 | I563: 0 | J563: 0 | K563: 0 | L563: =SUM(H563:K563) -> 5931000 | M563: 23.9 | N563: =ROUND((H563+I563+J563+K563)/IF($M$2>26,26,$M$2)*M563,0) -> 5451958 | O563: 2 | P563: =ROUND((H563+I563+J563+K563)/IF($M$2>26,26,$M$2)*O563,0) -> 456231 | Q563: 0 | R563: =IF(M563>0,ROUND(N563/IF(M563>26,26,M563)/8*Q563*30%,0),0) -> 0 | S563: =N563+P563+R563 -> 5908189 | T563: 0 | U563: 0 | V563: 200000 | W563: 500000 | X563: 0 | Y563: 400000 | Z563: 602158 | AC563: 0 | AD563: 0 | AE563: 42771.637 | AG563: =ROUND(SUM(S563:AF563)-AA563,0) -> 7653119 | AH563: 12 | AI563: 0 | AJ563: 0 | AK563: 0 | AL563: 0 | AM563: =ROUND((N563/IF(M563>26,26,M563)/8*(AH563*$AH$5+AI563*$AI$5+AJ563*$AJ$5+AK563*$AK$5+AL563*$AL$5)),0) -> 513260 | AN563: =ROUND(AG563+AM563,0) -> 8166379 | AO563: 622755 | AP563: 44100 | AQ563: =+VLOOKUP($B563,[1]Sheet1!$C$15:$BW$1300,52,0) -> 0 | AR563: 0 | AS563: 0 | AT563: =+ROUND(SUM(AN563:AN563)-SUM(AO563:AS563),0) -> 7499524 | AW563: NGUYEN THI HOANG | AX563: 050127672560 | AY563: SK1 Bag | AZ563: 622 | BA563: =+IF(AY563="SK1 Box","Box",IF(AY563="Seaman","Seaman","Bag")) -> Bag
... A619: =SUBTOTAL(3,B$6:B619) -> 1 | B619: C16467 | C619: Phùng Huệ Như | D619: 45710 | E619: FACTORY D | F619: P4 - Inspection | G619: Inspection worker | H619: 5023000 | I619: 300000 | J619: 0 | K619: 0 | L619: =SUM(H619:K619) -> 5323000 | M619: 24 | N619: =ROUND((H619+I619+J619+K619)/IF($M$2>26,26,$M$2)*M619,0) -> 4913538 | O619: 2 | P619: =ROUND((H619+I619+J619+K619)/IF($M$2>26,26,$M$2)*O619,0) -> 409462 | Q619: 0 | R619: =IF(M619>0,ROUND(N619/IF(M619>26,26,M619)/8*Q619*30%,0),0) -> 0 | S619: =N619+P619+R619 -> 5323000 | T619: 0 | U619: 0 | V619: 200000 | W619: 500000 | X619: 0 | Y619: 400000 | Z619: 545844 | AC619: 0 | AD619: 0 | AE619: 38387.016 | AG619: =ROUND(SUM(S619:AF619)-AA619,0) -> 7007231 | AH619: 13 | AI619: 0 | AJ619: 0 | AK619: 0 | AL619: 0 | AM619: =ROUND((N619/IF(M619>26,26,M619)/8*(AH619*$AH$5+AI619*$AI$5+AJ619*$AJ$5+AK619*$AK$5+AL619*$AL$5)),0) -> 499031 | AN619: =ROUND(AG619+AM619,0) -> 7506262 | AO619: 558915 | AP619: 44100 | AQ619: =+VLOOKUP($B619,[1]Sheet1!$C$15:$BW$1300,52,0) -> 0 | AR619: 0 | AS619: 0 | AT619: =+ROUND(SUM(AN619:AN619)-SUM(AO619:AS619),0) -> 6903247 | AW619: PHUNG HUE NHU | AX619: 050158476190 | AY619: SK1 Bag | AZ619: 622 | BA619: =+IF(AY619="SK1 Box","Box",IF(AY619="Seaman","Seaman","Bag")) -> Bag
A620: =SUBTOTAL(3,B$6:B620) -> 1 | B620: C16606 | C620: Nguyễn Ngọc Huyền | D620: 45762 | E620: FACTORY D | F620: P4 - Inspection | G620: New worker | H620: 4694000 | I620: 0 | J620: 0 | K620: 0 | L620: =SUM(H620:K620) -> 4694000 | M620: 13 | N620: =ROUND((H620+I620+J620+K620)/IF($M$2>26,26,$M$2)*M620,0) -> 2347000 | O620: 1 | P620: =ROUND((H620+I620+J620+K620)/IF($M$2>26,26,$M$2)*O620,0) -> 180538 | Q620: 0 | R620: =IF(M620>0,ROUND(N620/IF(M620>26,26,M620)/8*Q620*30%,0),0) -> 0 | S620: =N620+P620+R620 -> 2527538 | T620: 0 | U620: 0 | V620: 108000 | W620: 269000 | X620: 0 | Y620: 81000 | Z620: 354797 | AC620: 0 | AD620: 0 | AE620: 33850.962 | AG620: =ROUND(SUM(S620:AF620)-AA620,0) -> 3374186 | AH620: 4 | AI620: 0 | AJ620: 0 | AK620: 0 | AL620: 0 | AM620: =ROUND((N620/IF(M620>26,26,M620)/8*(AH620*$AH$5+AI620*$AI$5+AJ620*$AJ$5+AK620*$AK$5+AL620*$AL$5)),0) -> 135404 | AN620: =ROUND(AG620+AM620,0) -> 3509590 | AO620: 0 | AP620: 0 | AQ620: =+VLOOKUP($B620,[1]Sheet1!$C$15:$BW$1300,52,0) -> 0 | AR620: 0 | AS620: 0 | AT620: =+ROUND(SUM(AN620:AN620)-SUM(AO620:AS620),0) -> 3509590 | AX620: TM | AY620: SK1 Bag | AZ620: 622 | BA620: =+IF(AY620="SK1 Box","Box",IF(AY620="Seaman","Seaman","Bag")) -> Bag
A621: =SUBTOTAL(3,B$6:B621) -> 1 | B621: C3716 | C621: Bùi Thị Ngọc Yến | D621: 40672 | E621: FACTORY D | F621: P4 - Inspection | G621: Bag Inspection leader | H621: 5931000 | I621: 2600000 | J621: 0 | K621: 500000 | L621: =SUM(H621:K621) -> 9031000 | M621: 24 | N621: =ROUND((H621+I621+J621+K621)/IF($M$2>26,26,$M$2)*M621,0) -> 8336308 | O621: 2 | P621: =ROUND((H621+I621+J621+K621)/IF($M$2>26,26,$M$2)*O621,0) -> 694692 | Q621: 0 | R621: =IF(M621>0,ROUND(N621/IF(M621>26,26,M621)/8*Q621*30%,0),0) -> 0 | S621: =N621+P621+R621 -> 9031000 | T621: 0 | U621: 0 | V621: 200000 | W621: 500000 | X621: 0 | Y621: 400000 | Z621: 546757 | AC621: 0 | AD621: 0 | AE621: 65127.406 | AG621: =ROUND(SUM(S621:AF621)-AA621,0) -> 10742884 | AH621: 13 | AI621: 0 | AJ621: 0 | AK621: 0 | AL621: 0 | AM621: =ROUND((N621/IF(M621>26,26,M621)/8*(AH621*$AH$5+AI621*$AI$5+AJ621*$AJ$5+AK621*$AK$5+AL621*$AL$5)),0) -> 846656 | AN621: =ROUND(AG621+AM621,0) -> 11589540 | AO621: 948255 | AP621: 44100 | AQ621: =+VLOOKUP($B621,[1]Sheet1!$C$15:$BW$1300,52,0) -> 0 | AR621: 0 | AS621: 0 | AT621: =+ROUND(SUM(AN621:AN621)-SUM(AO621:AS621),0) -> 10597185 | AW621: BUI THI NGOC YEN | AX621: 050040850969 | AY621: SK1 Bag | AZ621: 622 | BA621: =+IF(AY621="SK1 Box","Box",IF(AY621="Seaman","Seaman","Bag")) -> Bag
A622: =SUBTOTAL(3,B$6:B622) -> 1 | B622: C6605 | C622: Trương Thị Cư | D622: 42621 | E622: FACTORY D | F622: P4 - Inspection | G622: Inspection worker | H622: 5931000 | I622: 700000 | J622: 0 | K622: 0 | L622: =SUM(H622:K622) -> 6631000 | M622: 24 | N622: =ROUND((H622+I622+J622+K622)/IF($M$2>26,26,$M$2)*M622,0) -> 6120923 | O622: 2 | P622: =ROUND((H622+I622+J622+K622)/IF($M$2>26,26,$M$2)*O622,0) -> 510077 | Q622: 0 | R622: =IF(M622>0,ROUND(N622/IF(M622>26,26,M622)/8*Q622*30%,0),0) -> 0 | S622: =N622+P622+R622 -> 6631000 | T622: 0 | U622: 0 | V622: 200000 | W622: 500000 | X622: 0 | Y622: 400000 | Z622: 564550 | AC622: 0 | AD622: 0 | AE622: 47819.711 | AG622: =ROUND(SUM(S622:AF622)-AA622,0) -> 8343370 | AH622: 13 | AI622: 0 | AJ622: 0 | AK622: 0 | AL622: 0 | AM622: =ROUND((N622/IF(M622>26,26,M622)/8*(AH622*$AH$5+AI622*$AI$5+AJ622*$AJ$5+AK622*$AK$5+AL622*$AL$5)),0) -> 621656 | AN622: =ROUND(AG622+AM622,0) -> 8965026 | AO622: 696255 | AP622: 44100 | AQ622: =+VLOOKUP($B622,[1]Sheet1!$C$15:$BW$1300,52,0) -> 0 | AR622: 0 | AS622: 0 | AT622: =+ROUND(SUM(AN622:AN622)-SUM(AO622:AS622),0) -> 8224671 | AW622: TRUONG THI CU | AX622: 050067513158 | AY622: SK1 Bag | AZ622: 622 | BA622: =+IF(AY622="SK1 Box","Box",IF(AY622="Seaman","Seaman","Bag")) -> Bag
A623: =SUBTOTAL(3,B$6:B623) -> 1 | B623: C7264 | C623: Nguyễn Thị Xuân | D623: 43200 | E623: FACTORY D | F623: P4 - Inspection | G623: Inspection worker | H623: 5931000 | I623: 700000 | J623: 0 | K623: 0 | L623: =SUM(H623:K623) -> 6631000 | M623: 24 | N623: =ROUND((H623+I623+J623+K623)/IF($M$2>26,26,$M$2)*M623,0) -> 6120923 | O623: 2 | P623: =ROUND((H623+I623+J623+K623)/IF($M$2>26,26,$M$2)*O623,0) -> 510077 | Q623: 0 | R623: =IF(M623>0,ROUND(N623/IF(M623>26,26,M623)/8*Q623*30%,0),0) -> 0 | S623: =N623+P623+R623 -> 6631000 | T623: 0 | U623: 0 | V623: 200000 | W623: 500000 | X623: 0 | Y623: 400000 | Z623: 445046 | AC623: 0 | AD623: 0 | AE623: 47819.711 | AG623: =ROUND(SUM(S623:AF623)-AA623,0) -> 8223866 | AH623: 13 | AI623: 0 | AJ623: 0 | AK623: 0 | AL623: 0 | AM623: =ROUND((N623/IF(M623>26,26,M623)/8*(AH623*$AH$5+AI623*$AI$5+AJ623*$AJ$5+AK623*$AK$5+AL623*$AL$5)),0) -> 621656 | AN623: =ROUND(AG623+AM623,0) -> 8845522 | AO623: 696255 | AP623: 44100 | AQ623: =+VLOOKUP($B623,[1]Sheet1!$C$15:$BW$1300,52,0) -> 0 | AR623: 0 | AS623: 0 | AT623: =+ROUND(SUM(AN623:AN623)-SUM(AO623:AS623),0) -> 8105167 | AW623: NGUYEN THI XUAN | AX623: 050088957137 | AY623: SK1 Bag | AZ623: 622 | BA623: =+IF(AY623="SK1 Box","Box",IF(AY623="Seaman","Seaman","Bag")) -> Bag
A624: =SUBTOTAL(3,B$6:B624) -> 1 | B624: C8000 | C624: Nguyễn Thị Ngọc Hồng Thắm | D624: 43517 | E624: FACTORY D | F624: P4 - Inspection | G624: Inspection worker | H624: 5931000 | I624: 700000 | J624: 0 | K624: 0 | L624: =SUM(H624:K624) -> 6631000 | M624: 22.8 | N624: =ROUND((H624+I624+J624+K624)/IF($M$2>26,26,$M$2)*M624,0) -> 5814877 | O624: 3 | P624: =ROUND((H624+I624+J624+K624)/IF($M$2>26,26,$M$2)*O624,0) -> 765115 | Q624: 0 | R624: =IF(M624>0,ROUND(N624/IF(M624>26,26,M624)/8*Q624*30%,0),0) -> 0 | S624: =N624+P624+R624 -> 6579992 | T624: 0 | U624: 0 | V624: 200000 | W624: 500000 | X624: 0 | Y624: 400000 | Z624: 819745 | AC624: 200000 | AD624: 0 | AE624: 47819.712 | AG624: =ROUND(SUM(S624:AF624)-AA624,0) -> 8747557 | AH624: 13 | AI624: 0 | AJ624: 0 | AK624: 0 | AL624: 0 | AM624: =ROUND((N624/IF(M624>26,26,M624)/8*(AH624*$AH$5+AI624*$AI$5+AJ624*$AJ$5+AK624*$AK$5+AL624*$AL$5)),0) -> 621656 | AN624: =ROUND(AG624+AM624,0) -> 9369213 | AO624: 696255 | AP624: 44100 | AQ624: =+VLOOKUP($B624,[1]Sheet1!$C$15:$BW$1300,52,0) -> 0 | AR624: 0 | AS624: 0 | AT624: =+ROUND(SUM(AN624:AN624)-SUM(AO624:AS624),0) -> 8628858 | AW624: NGUYEN THI NGOC HONG THAM | AX624: 050095313199 | AY624: SK1 Bag | AZ624: 622 | BA624: =+IF(AY624="SK1 Box","Box",IF(AY624="Seaman","Seaman","Bag")) -> Bag
A625: =SUBTOTAL(3,B$6:B625) -> 1 | B625: C8468 | C625: Võ Thị Kim Chi | D625: 43543 | E625: FACTORY D | F625: P4 - Inspection | G625: Inspection worker | H625: 5931000 | I625: 700000 | J625: 0 | K625: 0 | L625: =SUM(H625:K625) -> 6631000 | M625: 24 | N625: =ROUND((H625+I625+J625+K625)/IF($M$2>26,26,$M$2)*M625,0) -> 6120923 | O625: 2 | P625: =ROUND((H625+I625+J625+K625)/IF($M$2>26,26,$M$2)*O625,0) -> 510077 | Q625: 0 | R625: =IF(M625>0,ROUND(N625/IF(M625>26,26,M625)/8*Q625*30%,0),0) -> 0 | S625: =N625+P625+R625 -> 6631000 | T625: 0 | U625: 0 | V625: 200000 | W625: 500000 | X625: 0 | Y625: 400000 | Z625: 681546 | AC625: 0 | AD625: 0 | AE625: 47819.711 | AG625: =ROUND(SUM(S625:AF625)-AA625,0) -> 8460366 | AH625: 13 | AI625: 0 | AJ625: 0 | AK625: 0 | AL625: 0 | AM625: =ROUND((N625/IF(M625>26,26,M625)/8*(AH625*$AH$5+AI625*$AI$5+AJ625*$AJ$5+AK625*$AK$5+AL625*$AL$5)),0) -> 621656 | AN625: =ROUND(AG625+AM625,0) -> 9082022 | AO625: 696255 | AP625: 44100 | AQ625: =+VLOOKUP($B625,[1]Sheet1!$C$15:$BW$1300,52,0) -> 0 | AR625: 0 | AS625: 0 | AT625: =+ROUND(SUM(AN625:AN625)-SUM(AO625:AS625),0) -> 8341667 | AW625: VO THI KIM CHI | AX625: 050103659393 | AY625: SK1 Bag | AZ625: 622 | BA625: =+IF(AY625="SK1 Box","Box",IF(AY625="Seaman","Seaman","Bag")) -> Bag
A626: =SUBTOTAL(3,B$6:B626) -> 1 | B626: C15744 | C626: Lê Văn Tấn | D626: 45367 | E626: FACTORY D | F626: P4 - Packing Bag | G626: Packing worker | H626: 5538000 | I626: 200000 | J626: 0 | K626: 0 | L626: =SUM(H626:K626) -> 5738000 | M626: 22.5 | N626: =ROUND((H626+I626+J626+K626)/IF($M$2>26,26,$M$2)*M626,0) -> 4965577 | O626: 3 | P626: =ROUND((H626+I626+J626+K626)/IF($M$2>26,26,$M$2)*O626,0) -> 662077 | Q626: 0 | R626: =IF(M626>0,ROUND(N626/IF(M626>26,26,M626)/8*Q626*30%,0),0) -> 0 | S626: =N626+P626+R626 -> 5627654 | T626: 0 | U626: 0 | V626: 200000 | W626: 500000 | X626: 0 | Y626: 400000 | Z626: 552371 | AC626: 0 | AD626: 0 | AE626: 0 | AG626: =ROUND(SUM(S626:AF626)-AA626,0) -> 7280025 | AH626: 13 | AI626: 0 | AJ626: 0 | AK626: 0 | AL626: 0 | AM626: =ROUND((N626/IF(M626>26,26,M626)/8*(AH626*$AH$5+AI626*$AI$5+AJ626*$AJ$5+AK626*$AK$5+AL626*$AL$5)),0) -> 537938 | AN626: =ROUND(AG626+AM626,0) -> 7817963 | AO626: 602490 | AP626: 44100 | AQ626: =+VLOOKUP($B626,[1]Sheet1!$C$15:$BW$1300,52,0) -> 0 | AR626: 0 | AS626: 0 | AT626: =+ROUND(SUM(AN626:AN626)-SUM(AO626:AS626),0) -> 7171373 | AW626: LE VAN TAN | AX626: 050089661835 | AY626: SK1 Bag | AZ626: 622 | BA626: =+IF(AY626="SK1 Box","Box",IF(AY626="Seaman","Seaman","Bag")) -> Bag
A627: =SUBTOTAL(3,B$6:B627) -> 1 | B627: C3163 | C627: Dư Quốc An | D627: 40420 | E627: FACTORY D | F627: P4 - Packing Bag | G627: Bag Packing leader | H627: 5931000 | I627: 2300000 | J627: 0 | K627: 500000 | L627: =SUM(H627:K627) -> 8731000 | M627: 23.8 | N627: =ROUND((H627+I627+J627+K627)/IF($M$2>26,26,$M$2)*M627,0) -> 7992223 | O627: 2 | P627: =ROUND((H627+I627+J627+K627)/IF($M$2>26,26,$M$2)*O627,0) -> 671615 | Q627: 0 | R627: =IF(M627>0,ROUND(N627/IF(M627>26,26,M627)/8*Q627*30%,0),0) -> 0 | S627: =N627+P627+R627 -> 8663838 | T627: 0 | U627: 0 | V627: 200000 | W627: 500000 | X627: 0 | Y627: 400000 | Z627: 542201 | AC627: 0 | AD627: 0 | AE627: 0 | AG627: =ROUND(SUM(S627:AF627)-AA627,0) -> 10306039 | AH627: 12 | AI627: 0 | AJ627: 0 | AK627: 0 | AL627: 0 | AM627: =ROUND((N627/IF(M627>26,26,M627)/8*(AH627*$AH$5+AI627*$AI$5+AJ627*$AJ$5+AK627*$AK$5+AL627*$AL$5)),0) -> 755567 | AN627: =ROUND(AG627+AM627,0) -> 11061606 | AO627: 916755 | AP627: 44100 | AQ627: =+VLOOKUP($B627,[1]Sheet1!$C$15:$BW$1300,52,0) -> 0 | AR627: 0 | AS627: 0 | AT627: =+ROUND(SUM(AN627:AN627)-SUM(AO627:AS627),0) -> 10100751 | AW627: DU QUOC AN | AX627: 050040849553 | AY627: SK1 Bag | AZ627: 622 | BA627: =+IF(AY627="SK1 Box","Box",IF(AY627="Seaman","Seaman","Bag")) -> Bag
A628: =SUBTOTAL(3,B$6:B628) -> 1 | B628: C7168 | C628: Điểu Dẹn | D628: 43167 | E628: FACTORY D | F628: P4 - Packing Bag | G628: Packing worker | H628: 5931000 | I628: 600000 | J628: 0 | K628: 0 | L628: =SUM(H628:K628) -> 6531000 | M628: 23 | N628: =ROUND((H628+I628+J628+K628)/IF($M$2>26,26,$M$2)*M628,0) -> 5777423 | O628: 3 | P628: =ROUND((H628+I628+J628+K628)/IF($M$2>26,26,$M$2)*O628,0) -> 753577 | Q628: 0 | R628: =IF(M628>0,ROUND(N628/IF(M628>26,26,M628)/8*Q628*30%,0),0) -> 0 | S628: =N628+P628+R628 -> 6531000 | T628: 0 | U628: 0 | V628: 200000 | W628: 500000 | X628: 0 | Y628: 400000 | Z628: 653148 | AC628: 0 | AD628: 0 | AE628: 0 | AG628: =ROUND(SUM(S628:AF628)-AA628,0) -> 8284148 | AH628: 9 | AI628: 0 | AJ628: 0 | AK628: 0 | AL628: 0 | AM628: =ROUND((N628/IF(M628>26,26,M628)/8*(AH628*$AH$5+AI628*$AI$5+AJ628*$AJ$5+AK628*$AK$5+AL628*$AL$5)),0) -> 423887 | AN628: =ROUND(AG628+AM628,0) -> 8708035 | AO628: 685755 | AP628: 44100 | AQ628: =+VLOOKUP($B628,[1]Sheet1!$C$15:$BW$1300,52,0) -> 0 | AR628: 0 | AS628: 0 | AT628: =+ROUND(SUM(AN628:AN628)-SUM(AO628:AS628),0) -> 7978180 | AW628: DIEU DEN | AX628: 050087243122 | AY628: SK1 Bag | AZ628: 622 | BA628: =+IF(AY628="SK1 Box","Box",IF(AY628="Seaman","Seaman","Bag")) -> Bag
A629: =SUBTOTAL(3,B$6:B629) -> 1 | B629: C7211 | C629: Hồ Thanh Tấn | D629: 43173 | E629: FACTORY D | F629: P4 - Packing Bag | G629: Packing worker | H629: 5931000 | I629: 600000 | J629: 0 | K629: 0 | L629: =SUM(H629:K629) -> 6531000 | M629: 24 | N629: =ROUND((H629+I629+J629+K629)/IF($M$2>26,26,$M$2)*M629,0) -> 6028615 | O629: 2 | P629: =ROUND((H629+I629+J629+K629)/IF($M$2>26,26,$M$2)*O629,0) -> 502385 | Q629: 0 | R629: =IF(M629>0,ROUND(N629/IF(M629>26,26,M629)/8*Q629*30%,0),0) -> 0 | S629: =N629+P629+R629 -> 6531000 | T629: 0 | U629: 0 | V629: 200000 | W629: 500000 | X629: 0 | Y629: 400000 | Z629: 468899 | AC629: 100000 | AD629: 0 | AE629: 0 | AG629: =ROUND(SUM(S629:AF629)-AA629,0) -> 8199899 | AH629: 12 | AI629: 0 | AJ629: 0 | AK629: 0 | AL629: 0 | AM629: =ROUND((N629/IF(M629>26,26,M629)/8*(AH629*$AH$5+AI629*$AI$5+AJ629*$AJ$5+AK629*$AK$5+AL629*$AL$5)),0) -> 565183 | AN629: =ROUND(AG629+AM629,0) -> 8765082 | AO629: 685755 | AP629: 44100 | AQ629: =+VLOOKUP($B629,[1]Sheet1!$C$15:$BW$1300,52,0) -> 0 | AR629: 0 | AS629: 0 | AT629: =+ROUND(SUM(AN629:AN629)-SUM(AO629:AS629),0) -> 8035227 | AW629: HO THANH TAN | AX629: 050087243068 | AY629: SK1 Bag | AZ629: 622 | BA629: =+IF(AY629="SK1 Box","Box",IF(AY629="Seaman","Seaman","Bag")) -> Bag
A630: =SUBTOTAL(3,B$6:B630) -> 1 | B630: C7212 | C630: Điểu My | D630: 43173 | E630: FACTORY D | F630: P4 - Packing Bag | G630: Packing worker | H630: 5931000 | I630: 600000 | J630: 0 | K630: 0 | L630: =SUM(H630:K630) -> 6531000 | M630: 22.8 | N630: =ROUND((H630+I630+J630+K630)/IF($M$2>26,26,$M$2)*M630,0) -> 5727185 | O630: 3 | P630: =ROUND((H630+I630+J630+K630)/IF($M$2>26,26,$M$2)*O630,0) -> 753577 | Q630: 0 | R630: =IF(M630>0,ROUND(N630/IF(M630>26,26,M630)/8*Q630*30%,0),0) -> 0 | S630: =N630+P630+R630 -> 6480762 | T630: 0 | U630: 0 | V630: 200000 | W630: 500000 | X630: 0 | Y630: 400000 | Z630: 410802 | AC630: 100000 | AD630: 0 | AE630: 0 | AG630: =ROUND(SUM(S630:AF630)-AA630,0) -> 8091564 | AH630: 12 | AI630: 0 | AJ630: 0 | AK630: 0 | AL630: 0 | AM630: =ROUND((N630/IF(M630>26,26,M630)/8*(AH630*$AH$5+AI630*$AI$5+AJ630*$AJ$5+AK630*$AK$5+AL630*$AL$5)),0) -> 565183 | AN630: =ROUND(AG630+AM630,0) -> 8656747 | AO630: 685755 | AP630: 44100 | AQ630: =+VLOOKUP($B630,[1]Sheet1!$C$15:$BW$1300,52,0) -> 0 | AR630: 0 | AS630: 0 | AT630: =+ROUND(SUM(AN630:AN630)-SUM(AO630:AS630),0) -> 7926892 | AW630: DIEU MY | AX630: 050087500461 | AY630: SK1 Bag | AZ630: 622 | BA630: =+IF(AY630="SK1 Box","Box",IF(AY630="Seaman","Seaman","Bag")) -> Bag
A631: =SUBTOTAL(3,B$6:B631) -> 1 | B631: C7335 | C631: Điểu Út Bê | D631: 43262 | E631: FACTORY D | F631: P4 - Packing Bag | G631: Packing worker | H631: 5931000 | I631: 600000 | J631: 0 | K631: 0 | L631: =SUM(H631:K631) -> 6531000 | M631: 19.6 | N631: =ROUND((H631+I631+J631+K631)/IF($M$2>26,26,$M$2)*M631,0) -> 4923369 | O631: 2 | P631: =ROUND((H631+I631+J631+K631)/IF($M$2>26,26,$M$2)*O631,0) -> 502385 | Q631: 0 | R631: =IF(M631>0,ROUND(N631/IF(M631>26,26,M631)/8*Q631*30%,0),0) -> 0 | S631: =N631+P631+R631 -> 5425754 | T631: 0 | U631: 0 | V631: 200000 | W631: 0 | X631: 0 | Y631: 0 | Z631: 704693 | AC631: 0 | AD631: 0 | AE631: 0 | AG631: =ROUND(SUM(S631:AF631)-AA631,0) -> 6330447 | AH631: 9 | AI631: 0 | AJ631: 0 | AK631: 0 | AL631: 0 | AM631: =ROUND((N631/IF(M631>26,26,M631)/8*(AH631*$AH$5+AI631*$AI$5+AJ631*$AJ$5+AK631*$AK$5+AL631*$AL$5)),0) -> 423887 | AN631: =ROUND(AG631+AM631,0) -> 6754334 | AO631: 685755 | AP631: 44100 | AQ631: =+VLOOKUP($B631,[1]Sheet1!$C$15:$BW$1300,52,0) -> 0 | AR631: 0 | AS631: 0 | AT631: =+ROUND(SUM(AN631:AN631)-SUM(AO631:AS631),0) -> 6024479 | AW631: DIEU UT BE | AX631: 050091855841 | AY631: SK1 Bag | AZ631: 622 | BA631: =+IF(AY631="SK1 Box","Box",IF(AY631="Seaman","Seaman","Bag")) -> Bag
A632: =SUBTOTAL(3,B$6:B632) -> 1 | B632: C7528 | C632: Huỳnh Tiểu Bảo | D632: 43398 | E632: FACTORY D | F632: P4 - Packing Bag | G632: Bag Packing vice leader | H632: 5931000 | I632: 1400000 | J632: 0 | K632: 500000 | L632: =SUM(H632:K632) -> 7831000 | M632: 22.6 | N632: =ROUND((H632+I632+J632+K632)/IF($M$2>26,26,$M$2)*M632,0) -> 6806946 | O632: 3 | P632: =ROUND((H632+I632+J632+K632)/IF($M$2>26,26,$M$2)*O632,0) -> 903577 | Q632: 0 | R632: =IF(M632>0,ROUND(N632/IF(M632>26,26,M632)/8*Q632*30%,0),0) -> 0 | S632: =N632+P632+R632 -> 7710523 | T632: 0 | U632: 0 | V632: 200000 | W632: 500000 | X632: 0 | Y632: 400000 | Z632: 514863 | AC632: 0 | AD632: 0 | AE632: 0 | AG632: =ROUND(SUM(S632:AF632)-AA632,0) -> 9325386 | AH632: 8 | AI632: 0 | AJ632: 0 | AK632: 0 | AL632: 0 | AM632: =ROUND((N632/IF(M632>26,26,M632)/8*(AH632*$AH$5+AI632*$AI$5+AJ632*$AJ$5+AK632*$AK$5+AL632*$AL$5)),0) -> 451788 | AN632: =ROUND(AG632+AM632,0) -> 9777174 | AO632: 822255 | AP632: 44100 | AQ632: =+VLOOKUP($B632,[1]Sheet1!$C$15:$BW$1300,52,0) -> 0 | AR632: 0 | AS632: 0 | AT632: =+ROUND(SUM(AN632:AN632)-SUM(AO632:AS632),0) -> 8910819 | AW632: HUYNH TIEU BAO | AX632: 050098252085 | AY632: SK1 Bag | AZ632: 622 | BA632: =+IF(AY632="SK1 Box","Box",IF(AY632="Seaman","Seaman","Bag")) -> Bag
... A638: =SUBTOTAL(3,B$6:B638) -> 1 | B638: C5817 | C638: Lý Thị Kim Chi | D638: 41478 | E638: FACTORY D | F638: P4 - Production Office | G638: Factory vice manager | H638: 9319000 | I638: 7300000 | J638: 0 | K638: 1500000 | L638: =SUM(H638:K638) -> 18119000 | M638: 23.9 | N638: =ROUND((H638+I638+J638+K638)/IF($M$2>26,26,$M$2)*M638,0) -> 16655542 | O638: 2 | P638: =ROUND((H638+I638+J638+K638)/IF($M$2>26,26,$M$2)*O638,0) -> 1393769 | Q638: 0 | R638: =IF(M638>0,ROUND(N638/IF(M638>26,26,M638)/8*Q638*30%,0),0) -> 0 | S638: =N638+P638+R638 -> 18049311 | T638: 0 | U638: 0 | V638: 200000 | W638: 500000 | X638: 0 | Y638: 400000 | Z638: 0 | AC638: 100000 | AD638: 0 | AE638: 130665.86 | AG638: =ROUND(SUM(S638:AF638)-AA638,0) -> 19379977 | AH638: 13 | AI638: 0 | AJ638: 0 | AK638: 0 | AL638: 0 | AM638: =ROUND((N638/IF(M638>26,26,M638)/8*(AH638*$AH$5+AI638*$AI$5+AJ638*$AJ$5+AK638*$AK$5+AL638*$AL$5)),0) -> 1698656 | AN638: =ROUND(AG638+AM638,0) -> 21078633 | AO638: 1902495 | AP638: 44100 | AQ638: =+VLOOKUP($B638,[1]Sheet1!$C$15:$BW$1300,52,0) -> 0 | AR638: 70000 | AS638: 0 | AT638: =+ROUND(SUM(AN638:AN638)-SUM(AO638:AS638),0) -> 19062038 | AW638: LY THI KIM CHI | AX638: 050040860972 | AY638: SK1 Bag | AZ638: 627 | BA638: =+IF(AY638="SK1 Box","Box",IF(AY638="Seaman","Seaman","Bag")) -> Bag
A639: =SUBTOTAL(3,B$6:B639) -> 1 | B639: C6068 | C639: Trần Thị Cẩm Linh | D639: 41678 | E639: FACTORY D | F639: P4 - Production Office | G639: Factory manager | H639: 17900000 | I639: 11000000 | J639: 0 | K639: 0 | L639: =SUM(H639:K639) -> 28900000 | M639: 22.6 | N639: =ROUND((H639+I639+J639+K639)/IF($M$2>26,26,$M$2)*M639,0) -> 25120769 | O639: 2 | P639: =ROUND((H639+I639+J639+K639)/IF($M$2>26,26,$M$2)*O639,0) -> 2223077 | Q639: 0 | R639: =IF(M639>0,ROUND(N639/IF(M639>26,26,M639)/8*Q639*30%,0),0) -> 0 | S639: =N639+P639+R639 -> 27343846 | T639: 662308 | U639: 0 | V639: 0 | W639: 0 | X639: 0 | Y639: 0 | Z639: 0 | AC639: 0 | AD639: 0 | AE639: 208413.46 | AG639: =ROUND(SUM(S639:AF639)-AA639,0) -> 28214567 | AH639: 0 | AI639: 0 | AJ639: 0 | AK639: 0 | AL639: 0 | AM639: =ROUND((N639/IF(M639>26,26,M639)/8*(AH639*$AH$5+AI639*$AI$5+AJ639*$AJ$5+AK639*$AK$5+AL639*$AL$5)),0) -> 0 | AN639: =ROUND(AG639+AM639,0) -> 28214567 | AO639: 3034500 | AP639: 44100 | AQ639: =+VLOOKUP($B639,[1]Sheet1!$C$15:$BW$1300,52,0) -> 240888 | AR639: 0 | AS639: 0 | AT639: =+ROUND(SUM(AN639:AN639)-SUM(AO639:AS639),0) -> 24895079 | AW639: TRAN THI CAM LINH | AX639: 050040871311 | AY639: SK1 Bag | AZ639: 627 | BA639: Manager
A640: =SUBTOTAL(3,B$6:B640) -> 1 | B640: C6348 | C640: Võ Ngọc Minh | D640: 42173 | E640: FACTORY D | F640: P4 - Production Office | G640: Factory assistant | H640: 7019000 | I640: 2500000 | J640: 0 | K640: 0 | L640: =SUM(H640:K640) -> 9519000 | M640: 24 | N640: =ROUND((H640+I640+J640+K640)/IF($M$2>26,26,$M$2)*M640,0) -> 8786769 | O640: 2 | P640: =ROUND((H640+I640+J640+K640)/IF($M$2>26,26,$M$2)*O640,0) -> 732231 | Q640: 0 | R640: =IF(M640>0,ROUND(N640/IF(M640>26,26,M640)/8*Q640*30%,0),0) -> 0 | S640: =N640+P640+R640 -> 9519000 | T640: 0 | U640: 0 | V640: 200000 | W640: 500000 | X640: 0 | Y640: 400000 | Z640: 546757 | AC640: 0 | AD640: 0 | AE640: 68646.633 | AG640: =ROUND(SUM(S640:AF640)-AA640,0) -> 11234404 | AH640: 8 | AI640: 0 | AJ640: 0 | AK640: 0 | AL640: 0 | AM640: =ROUND((N640/IF(M640>26,26,M640)/8*(AH640*$AH$5+AI640*$AI$5+AJ640*$AJ$5+AK640*$AK$5+AL640*$AL$5)),0) -> 549173 | AN640: =ROUND(AG640+AM640,0) -> 11783577 | AO640: 999495 | AP640: 44100 | AQ640: =+VLOOKUP($B640,[1]Sheet1!$C$15:$BW$1300,52,0) -> 0 | AR640: 0 | AS640: 0 | AT640: =+ROUND(SUM(AN640:AN640)-SUM(AO640:AS640),0) -> 10739982 | AW640: VO NGOC MINH | AX640: 050056441473 | AY640: SK1 Bag | AZ640: 627 | BA640: =+IF(AY640="SK1 Box","Box",IF(AY640="Seaman","Seaman","Bag")) -> Bag
A641: =SUBTOTAL(3,B$6:B641) -> 1 | B641: C13576 | C641: Đoàn Thị Thúy Vy | D641: 44272 | E641: FACTORY D | F641: P4 - QC | G641: QC worker | H641: 5931000 | I641: 1100000 | J641: 0 | K641: 0 | L641: =SUM(H641:K641) -> 7031000 | M641: 23.8 | N641: =ROUND((H641+I641+J641+K641)/IF($M$2>26,26,$M$2)*M641,0) -> 6436069 | O641: 2 | P641: =ROUND((H641+I641+J641+K641)/IF($M$2>26,26,$M$2)*O641,0) -> 540846 | Q641: 0 | R641: =IF(M641>0,ROUND(N641/IF(M641>26,26,M641)/8*Q641*30%,0),0) -> 0 | S641: =N641+P641+R641 -> 6976915 | T641: 0 | U641: 0 | V641: 200000 | W641: 500000 | X641: 0 | Y641: 400000 | Z641: 396700 | AC641: 0 | AD641: 0 | AE641: 50704.325 | AG641: =ROUND(SUM(S641:AF641)-AA641,0) -> 8524319 | AH641: 12 | AI641: 0 | AJ641: 0 | AK641: 0 | AL641: 0 | AM641: =ROUND((N641/IF(M641>26,26,M641)/8*(AH641*$AH$5+AI641*$AI$5+AJ641*$AJ$5+AK641*$AK$5+AL641*$AL$5)),0) -> 608452 | AN641: =ROUND(AG641+AM641,0) -> 9132771 | AO641: 738255 | AP641: 44100 | AQ641: =+VLOOKUP($B641,[1]Sheet1!$C$15:$BW$1300,52,0) -> 0 | AR641: 0 | AS641: 0 | AT641: =+ROUND(SUM(AN641:AN641)-SUM(AO641:AS641),0) -> 8350416 | AW641: DOAN THI THUY VY | AX641: 050121836049 | AY641: SK1 Bag | AZ641: 622 | BA641: =+IF(AY641="SK1 Box","Box",IF(AY641="Seaman","Seaman","Bag")) -> Bag
A642: =SUBTOTAL(3,B$6:B642) -> 1 | B642: C14152 | C642: Hà Thị Mộng Bình | D642: 44329 | E642: FACTORY D | F642: P4 - QC | G642: QC worker | H642: 5931000 | I642: 1100000 | J642: 0 | K642: 0 | L642: =SUM(H642:K642) -> 7031000 | M642: 23.6 | N642: =ROUND((H642+I642+J642+K642)/IF($M$2>26,26,$M$2)*M642,0) -> 6381985 | O642: 2 | P642: =ROUND((H642+I642+J642+K642)/IF($M$2>26,26,$M$2)*O642,0) -> 540846 | Q642: 0 | R642: =IF(M642>0,ROUND(N642/IF(M642>26,26,M642)/8*Q642*30%,0),0) -> 0 | S642: =N642+P642+R642 -> 6922831 | T642: 0 | U642: 0 | V642: 200000 | W642: 500000 | X642: 0 | Y642: 400000 | Z642: 393300 | AC642: 200000 | AD642: 0 | AE642: 50704.33 | AG642: =ROUND(SUM(S642:AF642)-AA642,0) -> 8666835 | AH642: 12 | AI642: 0 | AJ642: 0 | AK642: 0 | AL642: 0 | AM642: =ROUND((N642/IF(M642>26,26,M642)/8*(AH642*$AH$5+AI642*$AI$5+AJ642*$AJ$5+AK642*$AK$5+AL642*$AL$5)),0) -> 608452 | AN642: =ROUND(AG642+AM642,0) -> 9275287 | AO642: 738255 | AP642: 44100 | AQ642: =+VLOOKUP($B642,[1]Sheet1!$C$15:$BW$1300,52,0) -> 0 | AR642: 0 | AS642: 0 | AT642: =+ROUND(SUM(AN642:AN642)-SUM(AO642:AS642),0) -> 8492932 | AW642: HA THI MONG BINH | AX642: 050120866335 | AY642: SK1 Bag | AZ642: 622 | BA642: =+IF(AY642="SK1 Box","Box",IF(AY642="Seaman","Seaman","Bag")) -> Bag
A643: =SUBTOTAL(3,B$6:B643) -> 1 | B643: C14158 | C643: Nguyễn Hiến Chương | D643: 44330 | E643: FACTORY D | F643: P4 - QC | G643: QC worker | H643: 5931000 | I643: 1100000 | J643: 0 | K643: 0 | L643: =SUM(H643:K643) -> 7031000 | M643: 24 | N643: =ROUND((H643+I643+J643+K643)/IF($M$2>26,26,$M$2)*M643,0) -> 6490154 | O643: 2 | P643: =ROUND((H643+I643+J643+K643)/IF($M$2>26,26,$M$2)*O643,0) -> 540846 | Q643: 0 | R643: =IF(M643>0,ROUND(N643/IF(M643>26,26,M643)/8*Q643*30%,0),0) -> 0 | S643: =N643+P643+R643 -> 7031000 | T643: 0 | U643: 0 | V643: 200000 | W643: 500000 | X643: 0 | Y643: 400000 | Z643: 400000 | AC643: 0 | AD643: 0 | AE643: 0 | AG643: =ROUND(SUM(S643:AF643)-AA643,0) -> 8531000 | AH643: 8 | AI643: 0 | AJ643: 0 | AK643: 0 | AL643: 0 | AM643: =ROUND((N643/IF(M643>26,26,M643)/8*(AH643*$AH$5+AI643*$AI$5+AJ643*$AJ$5+AK643*$AK$5+AL643*$AL$5)),0) -> 405635 | AN643: =ROUND(AG643+AM643,0) -> 8936635 | AO643: 738255 | AP643: 44100 | AQ643: =+VLOOKUP($B643,[1]Sheet1!$C$15:$BW$1300,52,0) -> 0 | AR643: 0 | AS643: 0 | AT643: =+ROUND(SUM(AN643:AN643)-SUM(AO643:AS643),0) -> 8154280 | AW643: NGUYEN HIEN CHUONG | AX643: 050121351592 | AY643: SK1 Bag | AZ643: 622 | BA643: =+IF(AY643="SK1 Box","Box",IF(AY643="Seaman","Seaman","Bag")) -> Bag
A644: =SUBTOTAL(3,B$6:B644) -> 1 | B644: C14256 | C644: Trần Tuấn Bảo | D644: 44343 | E644: FACTORY D | F644: P4 - QC | G644: QC worker | H644: 5931000 | I644: 1100000 | J644: 0 | K644: 0 | L644: =SUM(H644:K644) -> 7031000 | M644: 23 | N644: =ROUND((H644+I644+J644+K644)/IF($M$2>26,26,$M$2)*M644,0) -> 6219731 | O644: 3 | P644: =ROUND((H644+I644+J644+K644)/IF($M$2>26,26,$M$2)*O644,0) -> 811269 | Q644: 0 | R644: =IF(M644>0,ROUND(N644/IF(M644>26,26,M644)/8*Q644*30%,0),0) -> 0 | S644: =N644+P644+R644 -> 7031000 | T644: 0 | U644: 0 | V644: 200000 | W644: 500000 | X644: 0 | Y644: 400000 | Z644: 383300 | AC644: 0 | AD644: 0 | AE644: 0 | AG644: =ROUND(SUM(S644:AF644)-AA644,0) -> 8514300 | AH644: 12 | AI644: 0 | AJ644: 0 | AK644: 0 | AL644: 0 | AM644: =ROUND((N644/IF(M644>26,26,M644)/8*(AH644*$AH$5+AI644*$AI$5+AJ644*$AJ$5+AK644*$AK$5+AL644*$AL$5)),0) -> 608452 | AN644: =ROUND(AG644+AM644,0) -> 9122752 | AO644: 738255 | AP644: 44100 | AQ644: =+VLOOKUP($B644,[1]Sheet1!$C$15:$BW$1300,52,0) -> 0 | AR644: 0 | AS644: 0 | AT644: =+ROUND(SUM(AN644:AN644)-SUM(AO644:AS644),0) -> 8340397 | AW644: TRAN TUAN BAO | AX644: 050128255963 | AY644: SK1 Bag | AZ644: 622 | BA644: =+IF(AY644="SK1 Box","Box",IF(AY644="Seaman","Seaman","Bag")) -> Bag
A645: =SUBTOTAL(3,B$6:B645) -> 1 | B645: C14270 | C645: Nguyễn Thị Hạ | D645: 44348 | E645: FACTORY D | F645: P4 - QC | G645: QC worker | H645: 5931000 | I645: 1100000 | J645: 0 | K645: 0 | L645: =SUM(H645:K645) -> 7031000 | M645: 23.8 | N645: =ROUND((H645+I645+J645+K645)/IF($M$2>26,26,$M$2)*M645,0) -> 6436069 | O645: 2 | P645: =ROUND((H645+I645+J645+K645)/IF($M$2>26,26,$M$2)*O645,0) -> 540846 | Q645: 0 | R645: =IF(M645>0,ROUND(N645/IF(M645>26,26,M645)/8*Q645*30%,0),0) -> 0 | S645: =N645+P645+R645 -> 6976915 | T645: 0 | U645: 0 | V645: 200000 | W645: 500000 | X645: 0 | Y645: 400000 | Z645: 396700 | AC645: 100000 | AD645: 0 | AE645: 50704.325 | AG645: =ROUND(SUM(S645:AF645)-AA645,0) -> 8624319 | AH645: 13 | AI645: 0 | AJ645: 0 | AK645: 0 | AL645: 0 | AM645: =ROUND((N645/IF(M645>26,26,M645)/8*(AH645*$AH$5+AI645*$AI$5+AJ645*$AJ$5+AK645*$AK$5+AL645*$AL$5)),0) -> 659156 | AN645: =ROUND(AG645+AM645,0) -> 9283475 | AO645: 738255 | AP645: 44100 | AQ645: =+VLOOKUP($B645,[1]Sheet1!$C$15:$BW$1300,52,0) -> 0 | AR645: 0 | AS645: 0 | AT645: =+ROUND(SUM(AN645:AN645)-SUM(AO645:AS645),0) -> 8501120 | AW645: NGUYEN THI HA | AX645: 050129038931 | AY645: SK1 Bag | AZ645: 622 | BA645: =+IF(AY645="SK1 Box","Box",IF(AY645="Seaman","Seaman","Bag")) -> Bag
A646: =SUBTOTAL(3,B$6:B646) -> 1 | B646: C14436 | C646: Nguyễn Thị Ngọc Huỳnh | D646: 44601 | E646: FACTORY D | F646: P4 - QC | G646: QC worker | H646: 5931000 | I646: 1100000 | J646: 0 | K646: 0 | L646: =SUM(H646:K646) -> 7031000 | M646: 24 | N646: =ROUND((H646+I646+J646+K646)/IF($M$2>26,26,$M$2)*M646,0) -> 6490154 | O646: 2 | P646: =ROUND((H646+I646+J646+K646)/IF($M$2>26,26,$M$2)*O646,0) -> 540846 | Q646: 0 | R646: =IF(M646>0,ROUND(N646/IF(M646>26,26,M646)/8*Q646*30%,0),0) -> 0 | S646: =N646+P646+R646 -> 7031000 | T646: 0 | U646: 0 | V646: 200000 | W646: 500000 | X646: 0 | Y646: 400000 | Z646: 400000 | AC646: 0 | AD646: 0 | AE646: 50704.328 | AG646: =ROUND(SUM(S646:AF646)-AA646,0) -> 8581704 | AH646: 12 | AI646: 0 | AJ646: 0 | AK646: 0 | AL646: 0 | AM646: =ROUND((N646/IF(M646>26,26,M646)/8*(AH646*$AH$5+AI646*$AI$5+AJ646*$AJ$5+AK646*$AK$5+AL646*$AL$5)),0) -> 608452 | AN646: =ROUND(AG646+AM646,0) -> 9190156 | AO646: 738255 | AP646: 44100 | AQ646: =+VLOOKUP($B646,[1]Sheet1!$C$15:$BW$1300,52,0) -> 0 | AR646: 0 | AS646: 0 | AT646: =+ROUND(SUM(AN646:AN646)-SUM(AO646:AS646),0) -> 8407801 | AW646: NGUYEN THI NGOC HUYNH | AX646: 050155392883 | AY646: SK1 Bag | AZ646: 622 | BA646: =+IF(AY646="SK1 Box","Box",IF(AY646="Seaman","Seaman","Bag")) -> Bag
A647: =SUBTOTAL(3,B$6:B647) -> 1 | B647: C14444 | C647: Phạm Thùy Hương | D647: 44602 | E647: FACTORY D | F647: P4 - QC | G647: QC worker | H647: 5931000 | I647: 1100000 | J647: 0 | K647: 0 | L647: =SUM(H647:K647) -> 7031000 | M647: 1 | N647: =ROUND((H647+I647+J647+K647)/IF($M$2>26,26,$M$2)*M647,0) -> 270423 | O647: 1 | P647: =ROUND((H647+I647+J647+K647)/IF($M$2>26,26,$M$2)*O647,0) -> 270423 | Q647: 0 | R647: =IF(M647>0,ROUND(N647/IF(M647>26,26,M647)/8*Q647*30%,0),0) -> 0 | S647: =N647+P647+R647 -> 540846 | T647: 0 | U647: 0 | V647: 0 | W647: 0 | X647: 0 | Y647: 0 | Z647: 0 | AC647: 0 | AD647: 0 | AE647: 0 | AG647: =ROUND(SUM(S647:AF647)-AA647,0) -> 540846 | AH647: 0 | AI647: 0 | AJ647: 0 | AK647: 0 | AL647: 0 | AM647: =ROUND((N647/IF(M647>26,26,M647)/8*(AH647*$AH$5+AI647*$AI$5+AJ647*$AJ$5+AK647*$AK$5+AL647*$AL$5)),0) -> 0 | AN647: =ROUND(AG647+AM647,0) -> 540846 | AO647: 0 | AP647: 44100 | AQ647: =+VLOOKUP($B647,[1]Sheet1!$C$15:$BW$1300,52,0) -> 0 | AR647: 0 | AS647: 0 | AT647: =+ROUND(SUM(AN647:AN647)-SUM(AO647:AS647),0) -> 496746 | AW647: PHAM THUY HUONG | AX647: 050053905495 | AY647: SK1 Bag | AZ647: 622 | BA647: =+IF(AY647="SK1 Box","Box",IF(AY647="Seaman","Seaman","Bag")) -> Bag
A648: =SUBTOTAL(3,B$6:B648) -> 1 | B648: C14811 | C648: Kpă H Mai Ly | D648: 44665 | E648: FACTORY D | F648: P4 - QC | G648: QC worker | H648: 5931000 | I648: 900000 | J648: 0 | K648: 0 | L648: =SUM(H648:K648) -> 6831000 | M648: 24 | N648: =ROUND((H648+I648+J648+K648)/IF($M$2>26,26,$M$2)*M648,0) -> 6305538 | O648: 2 | P648: =ROUND((H648+I648+J648+K648)/IF($M$2>26,26,$M$2)*O648,0) -> 525462 | Q648: 0 | R648: =IF(M648>0,ROUND(N648/IF(M648>26,26,M648)/8*Q648*30%,0),0) -> 0 | S648: =N648+P648+R648 -> 6831000 | T648: 0 | U648: 0 | V648: 200000 | W648: 500000 | X648: 0 | Y648: 400000 | Z648: 400000 | AC648: 100000 | AD648: 0 | AE648: 49262.016 | AG648: =ROUND(SUM(S648:AF648)-AA648,0) -> 8480262 | AH648: 13 | AI648: 0 | AJ648: 0 | AK648: 0 | AL648: 0 | AM648: =ROUND((N648/IF(M648>26,26,M648)/8*(AH648*$AH$5+AI648*$AI$5+AJ648*$AJ$5+AK648*$AK$5+AL648*$AL$5)),0) -> 640406 | AN648: =ROUND(AG648+AM648,0) -> 9120668 | AO648: 717255 | AP648: 44100 | AQ648: =+VLOOKUP($B648,[1]Sheet1!$C$15:$BW$1300,52,0) -> 0 | AR648: 0 | AS648: 0 | AT648: =+ROUND(SUM(AN648:AN648)-SUM(AO648:AS648),0) -> 8359313 | AW648: KPA H MAI LY | AX648: 050122316073 | AY648: SK1 Bag | AZ648: 622 | BA648: =+IF(AY648="SK1 Box","Box",IF(AY648="Seaman","Seaman","Bag")) -> Bag
A649: =SUBTOTAL(3,B$6:B649) -> 1 | B649: C15396 | C649: Nguyễn Thị Ánh Nguyệt | D649: 44973 | E649: FACTORY D | F649: P4 - QC | G649: QC worker | H649: 5815000 | I649: 700000 | J649: 0 | K649: 0 | L649: =SUM(H649:K649) -> 6515000 | M649: 22.6 | N649: =ROUND((H649+I649+J649+K649)/IF($M$2>26,26,$M$2)*M649,0) -> 5663038 | O649: 3 | P649: =ROUND((H649+I649+J649+K649)/IF($M$2>26,26,$M$2)*O649,0) -> 751731 | Q649: 0 | R649: =IF(M649>0,ROUND(N649/IF(M649>26,26,M649)/8*Q649*30%,0),0) -> 0 | S649: =N649+P649+R649 -> 6414769 | T649: 0 | U649: 0 | V649: 200000 | W649: 500000 | X649: 0 | Y649: 400000 | Z649: 376700 | AC649: 100000 | AD649: 0 | AE649: 46983.169 | AG649: =ROUND(SUM(S649:AF649)-AA649,0) -> 8038452 | AH649: 17 | AI649: 0 | AJ649: 0 | AK649: 0 | AL649: 0 | AM649: =ROUND((N649/IF(M649>26,26,M649)/8*(AH649*$AH$5+AI649*$AI$5+AJ649*$AJ$5+AK649*$AK$5+AL649*$AL$5)),0) -> 798714 | AN649: =ROUND(AG649+AM649,0) -> 8837166 | AO649: 684075 | AP649: 44100 | AQ649: =+VLOOKUP($B649,[1]Sheet1!$C$15:$BW$1300,52,0) -> 0 | AR649: 0 | AS649: 0 | AT649: =+ROUND(SUM(AN649:AN649)-SUM(AO649:AS649),0) -> 8108991 | AW649: NGUYEN THI ANH NGUYET | AX649: 050108107526 | AY649: SK1 Bag | AZ649: 622 | BA649: =+IF(AY649="SK1 Box","Box",IF(AY649="Seaman","Seaman","Bag")) -> Bag
...

Sheet Transfer
C2: BẢNG CHI LƯƠNG THÁNG 04 NĂM 2025 TRANSFER - SHEET APR 2025
B3: Danh sách số:……………………………..
B4: Ngày : | C4: =TODAY() -> 45792
A5: STT | B5: MST | C5: HO TEN (Tieng viet khong dau) | D5: SO TAI KHOAN (Format kieu text) | E5: SO TIEN (Format kieu Number, khong dau phan cach) | F5: NOI DUNG THANH TOAN (Tieng viet khong dau, khong ky tu dac biet, toi da 100 ky tu) | G5: Ghi chú
A6: =SUBTOTAL(3,B$6:B6) -> 1 | B6: C0873 | C6: =+VLOOKUP(B6,'Salary sheet'!$B$6:$AX$1386,48,0) -> TRAN THI KIM PHAN | D6: =+VLOOKUP(B6,'Salary sheet'!$B$6:$BW$1386,49,0) -> 050040964964 | E6: =+VLOOKUP(B6,'Salary sheet'!$B$6:$AT$1292,45,0) -> 7613897 | F6: Lương tháng 04/2025 | G6: =+VLOOKUP(B6,'Salary sheet'!$B$6:$E$2281,4,0) -> FACTORY A | H6: =+VLOOKUP(B6,'Salary sheet'!$B$6:$AZ$1386,50,0) -> SK1 Box | I6: =+CONCATENATE(B6,C6,D6) -> C0873TRAN THI KIM PHAN050040964964 | J6: =+VLOOKUP(B6,'[2]04 2025'!$B$2:$F$1371,5,0) -> C0873TRAN THI KIM PHAN050040964964 | K6: =+IF(J6=I6,1,0) -> 1
A7: =SUBTOTAL(3,B$6:B7) -> 2 | B7: C1007 | C7: =+VLOOKUP(B7,'Salary sheet'!$B$6:$AX$1386,48,0) -> NGUYEN THI HUONG | D7: =+VLOOKUP(B7,'Salary sheet'!$B$6:$BW$1386,49,0) -> 050040850950 | E7: =+VLOOKUP(B7,'Salary sheet'!$B$6:$AT$1292,45,0) -> 8710599 | F7: Lương tháng 04/2025 | G7: =+VLOOKUP(B7,'Salary sheet'!$B$6:$E$2281,4,0) -> FACTORY A | H7: =+VLOOKUP(B7,'Salary sheet'!$B$6:$AZ$1386,50,0) -> SK1 Box | I7: =+CONCATENATE(B7,C7,D7) -> C1007NGUYEN THI HUONG050040850950 | J7: =+VLOOKUP(B7,'[2]04 2025'!$B$2:$F$1371,5,0) -> C1007NGUYEN THI HUONG050040850950 | K7: =+IF(J7=I7,1,0) -> 1
A8: =SUBTOTAL(3,B$6:B8) -> 3 | B8: C1009 | C8: =+VLOOKUP(B8,'Salary sheet'!$B$6:$AX$1386,48,0) -> HO THI NGA | D8: =+VLOOKUP(B8,'Salary sheet'!$B$6:$BW$1386,49,0) -> 050040952974 | E8: =+VLOOKUP(B8,'Salary sheet'!$B$6:$AT$1292,45,0) -> 8425946 | F8: Lương tháng 04/2025 | G8: =+VLOOKUP(B8,'Salary sheet'!$B$6:$E$2281,4,0) -> FACTORY A | H8: =+VLOOKUP(B8,'Salary sheet'!$B$6:$AZ$1386,50,0) -> SK1 Box | I8: =+CONCATENATE(B8,C8,D8) -> C1009HO THI NGA050040952974 | J8: =+VLOOKUP(B8,'[2]04 2025'!$B$2:$F$1371,5,0) -> C1009HO THI NGA050040952974 | K8: =+IF(J8=I8,1,0) -> 1
A9: =SUBTOTAL(3,B$6:B9) -> 4 | B9: C10454 | C9: =+VLOOKUP(B9,'Salary sheet'!$B$6:$AX$1386,48,0) -> TRAN THI LIEN | D9: =+VLOOKUP(B9,'Salary sheet'!$B$6:$BW$1386,49,0) -> 050104743444 | E9: =+VLOOKUP(B9,'Salary sheet'!$B$6:$AT$1292,45,0) -> 8431653 | F9: Lương tháng 04/2025 | G9: =+VLOOKUP(B9,'Salary sheet'!$B$6:$E$2281,4,0) -> FACTORY A | H9: =+VLOOKUP(B9,'Salary sheet'!$B$6:$AZ$1386,50,0) -> SK1 Box | I9: =+CONCATENATE(B9,C9,D9) -> C10454TRAN THI LIEN050104743444 | J9: =+VLOOKUP(B9,'[2]04 2025'!$B$2:$F$1371,5,0) -> C10454TRAN THI LIEN050104743444 | K9: =+IF(J9=I9,1,0) -> 1
A10: =SUBTOTAL(3,B$6:B10) -> 5 | B10: C10664 | C10: =+VLOOKUP(B10,'Salary sheet'!$B$6:$AX$1386,48,0) -> NGUYEN HOAI HAN | D10: =+VLOOKUP(B10,'Salary sheet'!$B$6:$BW$1386,49,0) -> 050073573855 | E10: =+VLOOKUP(B10,'Salary sheet'!$B$6:$AT$1292,45,0) -> 8313872 | F10: Lương tháng 04/2025 | G10: =+VLOOKUP(B10,'Salary sheet'!$B$6:$E$2281,4,0) -> FACTORY A | H10: =+VLOOKUP(B10,'Salary sheet'!$B$6:$AZ$1386,50,0) -> SK1 Box | I10: =+CONCATENATE(B10,C10,D10) -> C10664NGUYEN HOAI HAN050073573855 | J10: =+VLOOKUP(B10,'[2]04 2025'!$B$2:$F$1371,5,0) -> C10664NGUYEN HOAI HAN050073573855 | K10: =+IF(J10=I10,1,0) -> 1
A11: =SUBTOTAL(3,B$6:B11) -> 6 | B11: C10665 | C11: =+VLOOKUP(B11,'Salary sheet'!$B$6:$AX$1386,48,0) -> LE THI KIEU LOAN | D11: =+VLOOKUP(B11,'Salary sheet'!$B$6:$BW$1386,49,0) -> 050106514035 | E11: =+VLOOKUP(B11,'Salary sheet'!$B$6:$AT$1292,45,0) -> 7939740 | F11: Lương tháng 04/2025 | G11: =+VLOOKUP(B11,'Salary sheet'!$B$6:$E$2281,4,0) -> FACTORY A | H11: =+VLOOKUP(B11,'Salary sheet'!$B$6:$AZ$1386,50,0) -> SK1 Box | I11: =+CONCATENATE(B11,C11,D11) -> C10665LE THI KIEU LOAN050106514035 | J11: =+VLOOKUP(B11,'[2]04 2025'!$B$2:$F$1371,5,0) -> C10665LE THI KIEU LOAN050106514035 | K11: =+IF(J11=I11,1,0) -> 1
A12: =SUBTOTAL(3,B$6:B12) -> 7 | B12: C1074 | C12: =+VLOOKUP(B12,'Salary sheet'!$B$6:$AX$1386,48,0) -> PHAN THI THANH TAM | D12: =+VLOOKUP(B12,'Salary sheet'!$B$6:$BW$1386,49,0) -> 050040932884 | E12: =+VLOOKUP(B12,'Salary sheet'!$B$6:$AT$1292,45,0) -> 8492426 | F12: Lương tháng 04/2025 | G12: =+VLOOKUP(B12,'Salary sheet'!$B$6:$E$2281,4,0) -> FACTORY A | H12: =+VLOOKUP(B12,'Salary sheet'!$B$6:$AZ$1386,50,0) -> SK1 Box | I12: =+CONCATENATE(B12,C12,D12) -> C1074PHAN THI THANH TAM050040932884 | J12: =+VLOOKUP(B12,'[2]04 2025'!$B$2:$F$1371,5,0) -> C1074PHAN THI THANH TAM050040932884 | K12: =+IF(J12=I12,1,0) -> 1
A13: =SUBTOTAL(3,B$6:B13) -> 8 | B13: C11208 | C13: =+VLOOKUP(B13,'Salary sheet'!$B$6:$AX$1386,48,0) -> LE THI BICH LINH | D13: =+VLOOKUP(B13,'Salary sheet'!$B$6:$BW$1386,49,0) -> 050111434058 | E13: =+VLOOKUP(B13,'Salary sheet'!$B$6:$AT$1292,45,0) -> 8112662 | F13: Lương tháng 04/2025 | G13: =+VLOOKUP(B13,'Salary sheet'!$B$6:$E$2281,4,0) -> FACTORY A | H13: =+VLOOKUP(B13,'Salary sheet'!$B$6:$AZ$1386,50,0) -> SK1 Box | I13: =+CONCATENATE(B13,C13,D13) -> C11208LE THI BICH LINH050111434058 | J13: =+VLOOKUP(B13,'[2]04 2025'!$B$2:$F$1371,5,0) -> C11208LE THI BICH LINH050111434058 | K13: =+IF(J13=I13,1,0) -> 1
A14: =SUBTOTAL(3,B$6:B14) -> 9 | B14: C11863 | C14: =+VLOOKUP(B14,'Salary sheet'!$B$6:$AX$1386,48,0) -> TRAN HAI NAM | D14: =+VLOOKUP(B14,'Salary sheet'!$B$6:$BW$1386,49,0) -> 050116653033 | E14: =+VLOOKUP(B14,'Salary sheet'!$B$6:$AT$1292,45,0) -> 8687439 | F14: Lương tháng 04/2025 | G14: =+VLOOKUP(B14,'Salary sheet'!$B$6:$E$2281,4,0) -> FACTORY A | H14: =+VLOOKUP(B14,'Salary sheet'!$B$6:$AZ$1386,50,0) -> SK1 Box | I14: =+CONCATENATE(B14,C14,D14) -> C11863TRAN HAI NAM050116653033 | J14: =+VLOOKUP(B14,'[2]04 2025'!$B$2:$F$1371,5,0) -> C11863TRAN HAI NAM050116653033 | K14: =+IF(J14=I14,1,0) -> 1
A15: =SUBTOTAL(3,B$6:B15) -> 10 | B15: C1271 | C15: =+VLOOKUP(B15,'Salary sheet'!$B$6:$AX$1386,48,0) -> HO THI NGA | D15: =+VLOOKUP(B15,'Salary sheet'!$B$6:$BW$1386,49,0) -> 050040933910 | E15: =+VLOOKUP(B15,'Salary sheet'!$B$6:$AT$1292,45,0) -> 7606740 | F15: Lương tháng 04/2025 | G15: =+VLOOKUP(B15,'Salary sheet'!$B$6:$E$2281,4,0) -> FACTORY A | H15: =+VLOOKUP(B15,'Salary sheet'!$B$6:$AZ$1386,50,0) -> SK1 Box | I15: =+CONCATENATE(B15,C15,D15) -> C1271HO THI NGA050040933910 | J15: =+VLOOKUP(B15,'[2]04 2025'!$B$2:$F$1371,5,0) -> C1271HO THI NGA050040933910 | K15: =+IF(J15=I15,1,0) -> 1
A16: =SUBTOTAL(3,B$6:B16) -> 11 | B16: C12741 | C16: =+VLOOKUP(B16,'Salary sheet'!$B$6:$AX$1386,48,0) -> NGUYEN THI TRUC LY | D16: =+VLOOKUP(B16,'Salary sheet'!$B$6:$BW$1386,49,0) -> 050114056372 | E16: =+VLOOKUP(B16,'Salary sheet'!$B$6:$AT$1292,45,0) -> 8628829 | F16: Lương tháng 04/2025 | G16: =+VLOOKUP(B16,'Salary sheet'!$B$6:$E$2281,4,0) -> FACTORY A | H16: =+VLOOKUP(B16,'Salary sheet'!$B$6:$AZ$1386,50,0) -> SK1 Box | I16: =+CONCATENATE(B16,C16,D16) -> C12741NGUYEN THI TRUC LY050114056372 | J16: =+VLOOKUP(B16,'[2]04 2025'!$B$2:$F$1371,5,0) -> C12741NGUYEN THI TRUC LY050114056372 | K16: =+IF(J16=I16,1,0) -> 1
A17: =SUBTOTAL(3,B$6:B17) -> 12 | B17: C12781 | C17: =+VLOOKUP(B17,'Salary sheet'!$B$6:$AX$1386,48,0) -> LE THI ANH THUONG | D17: =+VLOOKUP(B17,'Salary sheet'!$B$6:$BW$1386,49,0) -> 050040933661 | E17: =+VLOOKUP(B17,'Salary sheet'!$B$6:$AT$1292,45,0) -> 9423658 | F17: Lương tháng 04/2025 | G17: =+VLOOKUP(B17,'Salary sheet'!$B$6:$E$2281,4,0) -> FACTORY A | H17: =+VLOOKUP(B17,'Salary sheet'!$B$6:$AZ$1386,50,0) -> SK1 Box | I17: =+CONCATENATE(B17,C17,D17) -> C12781LE THI ANH THUONG050040933661 | J17: =+VLOOKUP(B17,'[2]04 2025'!$B$2:$F$1371,5,0) -> C12781LE THI ANH THUONG050040933661 | K17: =+IF(J17=I17,1,0) -> 1
... A1278: =SUBTOTAL(3,B$6:B1278) -> 1273 | B1278: C7271 | C1278: =+VLOOKUP(B1278,'Salary sheet'!$B$6:$AX$1386,48,0) -> BUI KHAC THIN | D1278: =+VLOOKUP(B1278,'Salary sheet'!$B$6:$BW$1386,49,0) -> 050088957722 | E1278: =+VLOOKUP(B1278,'Salary sheet'!$B$6:$AT$1292,45,0) -> 8781781 | F1278: Lương tháng 04/2025 | G1278: =+VLOOKUP(B1278,'Salary sheet'!$B$6:$E$2281,4,0) -> SK2 | H1278: =+VLOOKUP(B1278,'Salary sheet'!$B$6:$AZ$1386,50,0) -> SK2 | I1278: =+CONCATENATE(B1278,C1278,D1278) -> C7271BUI KHAC THIN050088957722 | J1278: =+VLOOKUP(B1278,'[2]04 2025'!$B$2:$F$1371,5,0) -> C7271BUI KHAC THIN050088957722 | K1278: =+IF(J1278=I1278,1,0) -> 1
C1279: Total | E1279: =SUM(E6:E1278) -> 11404670194
E1282: Bình Phước, Ngày tháng năm 2025 | H1282: =+E1279 -> 11404670194
E1283: Giám đốc | F1283: =+SUMIF($H$6:$H$1279,G1283,$E$6:$E$1279) -> 3633278721 | G1283: SK1 Box | H1283: =+Cash!F18 -> 39396723
F1284: =+SUMIF($H$6:$H$1279,G1284,$E$6:$E$1279) -> 2837555897 | G1284: SK1 Bag | H1284: =+H1283+H1282 -> 11444066917
F1285: =+SUMIF($H$6:$H$1279,G1285,$E$6:$E$1279) -> 4766339057 | G1285: SK2 | H1285: =+'Salary sheet'!AT1292 -> 7240874
F1286: =+SUMIF($H$6:$H$1279,G1286,$E$6:$E$1279) -> 167496519 | G1286: Seaman
F1287: =SUM(F1283:F1286) -> 11404670194 | G1287: Total | H1287: =+H1285-H1284 -> -11436826043
H1289: \
H1290: SK1 Box
H1291: \
H1292: SK1 Bag
H1293: SK2

Sheet Cash
A2: BẢNG LƯƠNG THÁNG 04 NĂM 2025 CASH - SHEET OF APR 2025
E3: Hình thức thanh toán: Tiền mặt/Cashing
A4: TT No. | B4: Mã thẻ Code | C4: Họ và tên Full Name | D4: Ngày vào Entry day | E4: Bộ phận Dept | F4: Thực lãnh Amount | G4: Ký nhận Signature | H4: Remark | I4: Fac | J4: SK
A5: =SUBTOTAL(3,B$5:B5) -> 1 | B5: C16629 | C5: Mạc Thị Hòa | D5: 45771 | E5: =+VLOOKUP(B5,'Salary sheet'!$B$6:$AU$1432,5,0) -> P4 - FB2-4 | F5: =+VLOOKUP(B5,'Salary sheet'!$B$6:$AT$1292,45,0) -> 1279230 | H5: New worker | I5: =+VLOOKUP(B5,'Salary sheet'!$B$6:$AU$1432,4,0) -> FACTORY D | J5: =+VLOOKUP(B5,'Salary sheet'!$B$6:$AZ$1291,50,0) -> SK1 Bag | M5: ID card need update new
A6: =SUBTOTAL(3,B$5:B6) -> 2 | B6: C16606 | C6: Nguyễn Ngọc Huyền | D6: 45762 | E6: =+VLOOKUP(B6,'Salary sheet'!$B$6:$AU$1432,5,0) -> P4 - Inspection | F6: =+VLOOKUP(B6,'Salary sheet'!$B$6:$AT$1292,45,0) -> 3509590 | H6: New worker | I6: =+VLOOKUP(B6,'Salary sheet'!$B$6:$AU$1432,4,0) -> FACTORY D | J6: =+VLOOKUP(B6,'Salary sheet'!$B$6:$AZ$1291,50,0) -> SK1 Bag
A7: =SUBTOTAL(3,B$5:B7) -> 3 | B7: C16633 | C7: Tô Hoàng Long | D7: 45771 | E7: =+VLOOKUP(B7,'Salary sheet'!$B$6:$AU$1432,5,0) -> P7 - FG Warehouse | F7: =+VLOOKUP(B7,'Salary sheet'!$B$6:$AT$1292,45,0) -> 1201096 | H7: New worker | I7: =+VLOOKUP(B7,'Salary sheet'!$B$6:$AU$1432,4,0) -> FACTORY O | J7: =+VLOOKUP(B7,'Salary sheet'!$B$6:$AZ$1291,50,0) -> SK1 Bag
A8: =SUBTOTAL(3,B$5:B8) -> 4 | B8: C16599 | C8: Nguyễn Thanh Cường | D8: 45761 | E8: =+VLOOKUP(B8,'Salary sheet'!$B$6:$AU$1432,5,0) -> P0 - Planning | F8: =+VLOOKUP(B8,'Salary sheet'!$B$6:$AT$1292,45,0) -> 5769232 | H8: New worker | I8: =+VLOOKUP(B8,'Salary sheet'!$B$6:$AU$1432,4,0) -> SK2 | J8: =+VLOOKUP(B8,'Salary sheet'!$B$6:$AZ$1291,50,0) -> SK2
A9: =SUBTOTAL(3,B$5:B9) -> 5 | B9: C16614 | C9: Vi Thị Kim Nhung | D9: 45765 | E9: =+VLOOKUP(B9,'Salary sheet'!$B$6:$AU$1432,5,0) -> P2 - Inspection | F9: =+VLOOKUP(B9,'Salary sheet'!$B$6:$AT$1292,45,0) -> 2752135 | H9: New worker | I9: =+VLOOKUP(B9,'Salary sheet'!$B$6:$AU$1432,4,0) -> SK2 | J9: =+VLOOKUP(B9,'Salary sheet'!$B$6:$AZ$1291,50,0) -> SK2
A10: =SUBTOTAL(3,B$5:B10) -> 6 | B10: C16624 | C10: Trần Văn Đông | D10: 45769 | E10: =+VLOOKUP(B10,'Salary sheet'!$B$6:$AU$1432,5,0) -> P2 - J cut | F10: =+VLOOKUP(B10,'Salary sheet'!$B$6:$AT$1292,45,0) -> 1550038 | H10: New worker | I10: =+VLOOKUP(B10,'Salary sheet'!$B$6:$AU$1432,4,0) -> SK2 | J10: =+VLOOKUP(B10,'Salary sheet'!$B$6:$AZ$1291,50,0) -> SK2
A11: =SUBTOTAL(3,B$5:B11) -> 7 | B11: C16635 | C11: Nguyễn Sa Hun | D11: 45772 | E11: =+VLOOKUP(B11,'Salary sheet'!$B$6:$AU$1432,5,0) -> P2 - QC | F11: =+VLOOKUP(B11,'Salary sheet'!$B$6:$AT$1292,45,0) -> 1065692 | H11: New worker | I11: =+VLOOKUP(B11,'Salary sheet'!$B$6:$AU$1432,4,0) -> SK2 | J11: =+VLOOKUP(B11,'Salary sheet'!$B$6:$AZ$1291,50,0) -> SK2
A12: =SUBTOTAL(3,B$5:B12) -> 8 | B12: C15673 | C12: Nguyễn Thị Giầu | D12: 45355 | E12: =+VLOOKUP(B12,'Salary sheet'!$B$6:$AU$1432,5,0) -> P3 - Assembly 1A | F12: =+VLOOKUP(B12,'Salary sheet'!$B$6:$AT$1292,45,0) -> 8400055 | H12: ID card need update new | I12: =+VLOOKUP(B12,'Salary sheet'!$B$6:$AU$1432,4,0) -> SK2 | J12: =+VLOOKUP(B12,'Salary sheet'!$B$6:$AZ$1291,50,0) -> SK2
A13: =SUBTOTAL(3,B$5:B13) -> 9 | B13: C16636 | C13: Hoàng Trung Hiếu | D13: 45772 | E13: =+VLOOKUP(B13,'Salary sheet'!$B$6:$AU$1432,5,0) -> P3 - Assembly 2A | F13: =+VLOOKUP(B13,'Salary sheet'!$B$6:$AT$1292,45,0) -> 639615 | H13: New worker | I13: =+VLOOKUP(B13,'Salary sheet'!$B$6:$AU$1432,4,0) -> SK2 | J13: =+VLOOKUP(B13,'Salary sheet'!$B$6:$AZ$1291,50,0) -> SK2
A14: =SUBTOTAL(3,B$5:B14) -> 10 | B14: C16592 | C14: Nguyễn Văn Mạnh | D14: 45757 | E14: =+VLOOKUP(B14,'Salary sheet'!$B$6:$AU$1432,5,0) -> P3 - Assembly 2B | F14: =+VLOOKUP(B14,'Salary sheet'!$B$6:$AT$1292,45,0) -> 3953230 | H14: New worker | I14: =+VLOOKUP(B14,'Salary sheet'!$B$6:$AU$1432,4,0) -> SK2 | J14: =+VLOOKUP(B14,'Salary sheet'!$B$6:$AZ$1291,50,0) -> SK2
A15: =SUBTOTAL(3,B$5:B15) -> 11 | B15: C16593 | C15: Phạm Văn Dương | D15: 45757 | E15: =+VLOOKUP(B15,'Salary sheet'!$B$6:$AU$1432,5,0) -> P3 - Assembly 2B | F15: =+VLOOKUP(B15,'Salary sheet'!$B$6:$AT$1292,45,0) -> 4650115 | H15: New worker | I15: =+VLOOKUP(B15,'Salary sheet'!$B$6:$AU$1432,4,0) -> SK2 | J15: =+VLOOKUP(B15,'Salary sheet'!$B$6:$AZ$1291,50,0) -> SK2
A16: =SUBTOTAL(3,B$5:B16) -> 12 | B16: C16600 | C16: Phạm Thị Ngọc Huân | D16: 45761 | E16: =+VLOOKUP(B16,'Salary sheet'!$B$6:$AU$1432,5,0) -> P3 - Assembly 2B | F16: =+VLOOKUP(B16,'Salary sheet'!$B$6:$AT$1292,45,0) -> 3773542 | H16: New worker | I16: =+VLOOKUP(B16,'Salary sheet'!$B$6:$AU$1432,4,0) -> SK2 | J16: =+VLOOKUP(B16,'Salary sheet'!$B$6:$AZ$1291,50,0) -> SK2
A17: =SUBTOTAL(3,B$5:B17) -> 13 | B17: C16634 | C17: Quang Thị Duyên | D17: 45772 | E17: =+VLOOKUP(B17,'Salary sheet'!$B$6:$AU$1432,5,0) -> P3 - QC | F17: =+VLOOKUP(B17,'Salary sheet'!$B$6:$AT$1292,45,0) -> 853153 | H17: New worker | I17: =+VLOOKUP(B17,'Salary sheet'!$B$6:$AU$1432,4,0) -> SK2 | J17: =+VLOOKUP(B17,'Salary sheet'!$B$6:$AZ$1291,50,0) -> SK2
C18: TỔNG CỘNG | F18: =SUM(F5:F17) -> 39396723
F19: =+F18-G31 -> 0
G20: Bình Phước, Ngày tháng năm 2025
B21: Người kiểm tra | D21: Người kiểm tra | G21: Người Lập
B22: Checked by | D22: Checked by
G27: =+SUMIF($J$5:$J$23,H27,$F$5:$F$23) -> 0 | H27: SK1 Box
G28: =+SUMIF($J$5:$J$23,H28,$F$5:$F$23) -> 5989916 | H28: SK1 Bag
G29: =+SUMIF($J$5:$J$23,H29,$F$5:$F$23) -> 33406807 | H29: SK2
G30: =+SUMIF($J$5:$J$23,H30,$F$5:$F$23) -> 0 | H30: Seaman
G31: =SUBTOTAL(9,G27:G30) -> 39396723 | H31: Total

Sheet Cash - Dep
A2: TIỀN MẶT THEO BỘ PHẬN 04 2025 (CASH - DEPARMENT APR 2025)
A4: TT No. | B4: Bộ phận Dept | C4: Thực lãnh Amount | D4: Ký nhận Signature | E4: Giữ lại | F4: Chi ngày 10
A5: =SUBTOTAL(3,B$5:B5) -> 1 | B5: P0 - Planning | C5: =SUMIFS(Cash!$F$5:$F$17,Cash!$E$5:$E$17,'Cash - Dep'!B5) -> 5769232 | E5: =SUMIFS(Cash!$F$4:$F$23,Cash!$K$4:$K$23,'Cash - Dep'!$E$4,Cash!$E$4:$E$23,'Cash - Dep'!B5) -> 0 | F5: =+ROUND(C5-E5,0) -> 5769232
A6: =SUBTOTAL(3,B$5:B6) -> 2 | B6: P2 - Inspection | C6: =SUMIFS(Cash!$F$5:$F$17,Cash!$E$5:$E$17,'Cash - Dep'!B6) -> 2752135 | E6: =SUMIFS(Cash!$F$4:$F$23,Cash!$K$4:$K$23,'Cash - Dep'!$E$4,Cash!$E$4:$E$23,'Cash - Dep'!B6) -> 0 | F6: =+ROUND(C6-E6,0) -> 2752135
A7: =SUBTOTAL(3,B$5:B7) -> 3 | B7: P2 - J cut | C7: =SUMIFS(Cash!$F$5:$F$17,Cash!$E$5:$E$17,'Cash - Dep'!B7) -> 1550038 | E7: =SUMIFS(Cash!$F$4:$F$23,Cash!$K$4:$K$23,'Cash - Dep'!$E$4,Cash!$E$4:$E$23,'Cash - Dep'!B7) -> 0 | F7: =+ROUND(C7-E7,0) -> 1550038
A8: =SUBTOTAL(3,B$5:B8) -> 4 | B8: P2 - QC | C8: =SUMIFS(Cash!$F$5:$F$17,Cash!$E$5:$E$17,'Cash - Dep'!B8) -> 1065692 | E8: =SUMIFS(Cash!$F$4:$F$23,Cash!$K$4:$K$23,'Cash - Dep'!$E$4,Cash!$E$4:$E$23,'Cash - Dep'!B8) -> 0 | F8: =+ROUND(C8-E8,0) -> 1065692
A9: =SUBTOTAL(3,B$5:B9) -> 5 | B9: P3 - Assembly 1A | C9: =SUMIFS(Cash!$F$5:$F$17,Cash!$E$5:$E$17,'Cash - Dep'!B9) -> 8400055 | E9: =SUMIFS(Cash!$F$4:$F$23,Cash!$K$4:$K$23,'Cash - Dep'!$E$4,Cash!$E$4:$E$23,'Cash - Dep'!B9) -> 0 | F9: =+ROUND(C9-E9,0) -> 8400055
A10: =SUBTOTAL(3,B$5:B10) -> 6 | B10: P3 - Assembly 2A | C10: =SUMIFS(Cash!$F$5:$F$17,Cash!$E$5:$E$17,'Cash - Dep'!B10) -> 639615 | E10: =SUMIFS(Cash!$F$4:$F$23,Cash!$K$4:$K$23,'Cash - Dep'!$E$4,Cash!$E$4:$E$23,'Cash - Dep'!B10) -> 0 | F10: =+ROUND(C10-E10,0) -> 639615
A11: =SUBTOTAL(3,B$5:B11) -> 7 | B11: P3 - Assembly 2B | C11: =SUMIFS(Cash!$F$5:$F$17,Cash!$E$5:$E$17,'Cash - Dep'!B11) -> 12376887 | E11: =SUMIFS(Cash!$F$4:$F$23,Cash!$K$4:$K$23,'Cash - Dep'!$E$4,Cash!$E$4:$E$23,'Cash - Dep'!B11) -> 0 | F11: =+ROUND(C11-E11,0) -> 12376887
A12: =SUBTOTAL(3,B$5:B12) -> 8 | B12: P3 - QC | C12: =SUMIFS(Cash!$F$5:$F$17,Cash!$E$5:$E$17,'Cash - Dep'!B12) -> 853153 | E12: =SUMIFS(Cash!$F$4:$F$23,Cash!$K$4:$K$23,'Cash - Dep'!$E$4,Cash!$E$4:$E$23,'Cash - Dep'!B12) -> 0 | F12: =+ROUND(C12-E12,0) -> 853153
A13: =SUBTOTAL(3,B$5:B13) -> 9 | B13: P4 - FB2-4 | C13: =SUMIFS(Cash!$F$5:$F$17,Cash!$E$5:$E$17,'Cash - Dep'!B13) -> 1279230 | E13: =SUMIFS(Cash!$F$4:$F$23,Cash!$K$4:$K$23,'Cash - Dep'!$E$4,Cash!$E$4:$E$23,'Cash - Dep'!B13) -> 0 | F13: =+ROUND(C13-E13,0) -> 1279230
A14: =SUBTOTAL(3,B$5:B14) -> 10 | B14: P4 - Inspection | C14: =SUMIFS(Cash!$F$5:$F$17,Cash!$E$5:$E$17,'Cash - Dep'!B14) -> 3509590 | E14: =SUMIFS(Cash!$F$4:$F$23,Cash!$K$4:$K$23,'Cash - Dep'!$E$4,Cash!$E$4:$E$23,'Cash - Dep'!B14) -> 0 | F14: =+ROUND(C14-E14,0) -> 3509590
A15: =SUBTOTAL(3,B$5:B15) -> 11 | B15: P7 - FG Warehouse | C15: =SUMIFS(Cash!$F$5:$F$17,Cash!$E$5:$E$17,'Cash - Dep'!B15) -> 1201096 | E15: =SUMIFS(Cash!$F$4:$F$23,Cash!$K$4:$K$23,'Cash - Dep'!$E$4,Cash!$E$4:$E$23,'Cash - Dep'!B15) -> 0 | F15: =+ROUND(C15-E15,0) -> 1201096
A16: TỔNG CỘNG | C16: =SUM(C5:C15) -> 39396723 | E16: =SUM(E5:E15) -> 0 | F16: =SUM(F5:F15) -> 39396723
C17: =+Cash!F18 -> 39396723
B19: Người kiểm tra | D19: Manager
B20: Checked by | D20: Checked by

Sheet Comparison summary
B1: COMPARISON SUMMARY | P1: Not Include Korean
P2: Not Include Korean
B3: Exchange rate:2017 | D3: 22700 | E3: 22700 | F3: 22700 | G3: 22700 | H3: 22700 | I3: 22700 | J3: 22700 | K3: 22700 | L3: 22700 | M3: 22700 | N3: 22700 | O3: 22700 | Q3: 22500
B4: Exchange rate:2018 | D4: 22745 | E4: 22790 | F4: 22810 | G4: 22800 | H4: 22835 | I4: 22990 | J4: 23310 | K4: =+[3]Average!AF3 -> 23340 | L4: 23365 | M4: 23390 | N4: 23365 | O4: 23235
B5: Exchange rate:2019 | D5: 23250 | E5: 23245 | F5: 23245 | G5: 23320 | H5: 23470 | I5: 23320 | J5: 23270 | K5: 23240 | L5: 23250 | M5: 23250 | N5: 23225 | O5: 23220
B6: Exchange rate:2020 | D6: 23230 | E6: 23310 | F6: 23660 | G6: 23535 | H6: 23380 | I6: 23300 | J6: 23270 | K6: 23270 | L6: 23270 | M6: 23270 | N6: 23230 | O6: 23190
B7: Exchange rate:2021 | D7: 23230 | E7: 23310 | F7: 23660 | G7: 23535 | H7: 23380 | I7: 23300 | J7: 23270 | K7: 22870 | L7: 22860 | M7: 22850 | N7: 22795 | O7: 22915
B8: Exchange rate:2022 | D8: 22730 | E8: 22930 | F8: 22960 | G8: 23080 | H8: 23300 | I8: 23380 | J8: 23450 | K8: 23550 | L8: 23970 | M8: 24880 | N8: 24735 | O8: 23640
B9: Exchange rate:2023 | D9: 23570 | E9: 23895 | F9: 23585 | G9: 23580 | H9: 23610 | I9: 23700 | J9: 23805 | K9: 24180 | L9: 24450 | M9: 24680 | N9: 24380 | O9: 24350
B10: Exchange rate:2024
B11: 1) | C11: Currency | D11: Jan | E11: Feb | F11: Mar | G11: Apr | H11: May | I11: Jun | J11: Jul | K11: Aug | L11: Sep | M11: Oct | N11: Nov | O11: Dec | P11: G. Total | Q11: Average
B12: Average salary
B13: 2016 | C13: VND | D13: 5639851.3 | E13: 7094675.9 | F13: 6975597.1 | G13: 7396945.6 | H13: 8158010.3 | I13: 8707228.4 | J13: 8073722.7 | K13: 8103327.1 | L13: 7788570.5 | M13: 8110049.6 | N13: 8021292.3 | O13: 8526000.3 | P13: =+SUM(D13:O13) -> 92595271 | Q13: =AVERAGE(D13:O13) -> 7716272.6
B14: 2017 | C14: VND | D14: 7419611.8 | E14: 7036665.1 | F14: 8214537.2 | G14: 8422068 | H14: 7974682.7 | I14: 7479780.8 | J14: 7838982.4 | K14: 9052133.7 | L14: 10075133 | M14: 10189479 | N14: 9616396.2 | O14: 9512442.3 | P14: =+SUM(D14:O14) -> 1.0283191e+08 | Q14: =+[4]Average!O11 -> 9428987.9
B15: 2018 | C15: VND | D15: 9057034 | E15: 6829832.8 | F15: 9238934.4 | G15: 8710293.3 | H15: 9387345.8 | I15: 9373152.8 | J15: 9127505.3 | K15: 9877891.4 | L15: 9777987.3 | M15: 10075783 | N15: 9686533.6 | O15: 9451918.4 | P15: =+SUM(D15:O15) -> 1.1059421e+08 | Q15: =+[3]Average!AP11 -> 9220117
B16: 2019 | C16: VND | D16: 7272544.2 | E16: 5585409.2 | F16: 6947495.8 | G16: 6526761.7 | H16: 7064922.8 | I16: 7096702.8 | J16: 7697503.6 | K16: 7974855.2 | L16: 7666429.8 | M16: 7823190.7 | N16: 6673934.7 | O16: 6719094.1 | P16: =+SUM(D16:O16) -> 85048845 | Q16: =AVERAGE(D16:O16) -> 7087403.7
B17: 2020 | C17: VND | D17: 7549344.1 | E17: 8110653.7 | F17: 7035931 | G17: 6377334.3 | H17: 6516058.2 | I17: 7710116.1 | J17: 10610022 | K17: 10837583 | L17: 8847384.2 | M17: 8755691.3 | N17: 8880206.3 | O17: 10737012 | P17: =+SUM(D17:O17) -> 1.0196734e+08 | Q17: =AVERAGE(D17:O17) -> 8497278
B18: 2021 | C18: VND | D18: 9422084.2 | E18: 6867223.3 | F18: 9638378.5 | G18: 9769954.1 | H18: 10368919 | I18: 10748634 | J18: 8901381.3 | K18: 13492328 | L18: 12377056 | M18: 7357014.1 | N18: 6150079 | O18: 9041384.9 | P18: =+SUM(D18:O18) -> 1.1413444e+08 | Q18: =AVERAGE(D18:O18) -> 9511203 | R18: x
B19: 2022 | C19: VND | D19: 12831225 | E19: 8332957.9 | F19: 9670187.7 | G19: 9821279.4 | H19: 9651342.9 | I19: 9425095.2 | J19: 9508049.8 | K19: 9938897.7 | L19: 8442788.4 | M19: 8117583.2 | N19: 7648571.1 | O19: 7889869.2 | P19: =+SUM(D19:O19) -> 1.1127785e+08 | Q19: =AVERAGE(D19:O19) -> 9273154
B20: 2023 | C20: VND | D20: 12121791 | E20: 8728625 | F20: 9802908.7 | G20: 9530853.1 | H20: 10098894 | I20: 11111326 | J20: 10614054 | K20: 10797197 | L20: 9683665.9 | M20: 9921167.5 | N20: 8905570.8 | O20: 10181530 | P20: =+SUM(D20:O20) -> 1.2149758e+08 | Q20: =AVERAGE(D20:O20) -> 10124799
B21: 2024 | C21: VND
B22: Comparison 2024/2023 | D22: =+(D21-D20)/D20 -> -1 | E22: =+(E21-E20)/E20 -> -1 | F22: =+(F21-F20)/F20 -> -1 | G22: =+(G21-G20)/G20 -> -1 | H22: =+(H21-H20)/H20 -> -1 | I22: =+(I21-I20)/I20 -> -1 | J22: =+(J21-J20)/J20 -> -1 | K22: =+(K21-K20)/K20 -> -1 | ... O22: =+(O21-O20)/O20 -> -1 | P22: =+(P20-P19)/P19 -> 0.091839806 | Q22: =+(Q20-Q19)/Q19 -> 0.091839806
B23: Total employee
B24: 2016 | D24: 884 | E24: 883 | F24: 842 | G24: 817 | H24: 805 | I24: 804 | J24: 842 | K24: 1016 | L24: 1081 | M24: 1064 | N24: 1048 | O24: 1055 | P24: =+SUM(D24:O24) -> 11141 | Q24: =AVERAGE(D24:O24) -> 928.41667
B25: 2017 | D25: 1035 | E25: 1056 | F25: 1047 | G25: 1019 | H25: 1008 | I25: 984 | J25: 972 | K25: 991 | L25: 979 | M25: 953 | N25: 942 | O25: 977 | P25: =+SUM(D25:O25) -> 11963 | Q25: =AVERAGE(D25:O25) -> 996.91667
B26: 2018 | D26: 976 | E26: 937 | F26: 998 | G26: 1005 | H26: 1005 | I26: 1000 | J26: 984 | K26: 1001 | L26: 1021 | M26: 1056 | N26: 1072 | O26: 1199 | Q26: =AVERAGE(D26:O26) -> 1021.1667
B27: 2019 | D27: 1504 | E27: 1709 | F27: 2075 | G27: 2149 | H27: 2217 | I27: 2229 | J27: 2241 | K27: 2204 | L27: 2202 | M27: 2256 | N27: 2186 | O27: 2208 | P27: =+SUM(D27:O27) -> 25180 | Q27: =AVERAGE(D27:O27) -> 2098.3333
B28: 2020 | D28: 1736 | E28: 1752 | F28: 1750 | G28: 1750 | H28: 1644 | I28: 1653 | J28: 1688 | K28: 1759 | L28: 1793 | M28: 1800 | N28: 1788 | O28: 1808 | P28: =+SUM(D28:O28) -> 20921 | Q28: =AVERAGE(D28:O28) -> 1743.4167
B29: 2021 | D29: 1745 | E29: 1762 | F29: 1974 | G29: 2065 | H29: 2128 | I29: 2113 | J29: 2063 | K29: 1250 | L29: 1174 | M29: 1772 | N29: 1751 | O29: 1693 | P29: =+SUM(D29:O29) -> 21490 | Q29: =AVERAGE(D29:O29) -> 1790.8333 | R29: x
B30: 2022 | D30: 1549 | E30: 1633 | F30: 1628 | G30: 1601 | H30: 1665 | I30: 1706 | J30: 1658 | K30: 1663 | L30: 1568 | M30: 1511 | N30: 1467 | O30: 1482 | P30: =+SUM(D30:O30) -> 19131 | Q30: =AVERAGE(D30:O30) -> 1594.25
B31: 2023 | D31: 1395 | E31: 1382 | F31: 1349 | G31: 1321 | H31: 1270 | I31: 1225 | J31: 1212 | K31: 1231 | L31: 1210 | M31: 1206 | N31: 1193 | O31: 1240 | P31: =+SUM(D31:O31) -> 15234 | Q31: =AVERAGE(D31:O31) -> 1269.5
B32: 2024
B33: Comparison 2024/2023 | D33: =+(D32-D31)/D31 -> -1 | E33: =+(E32-E31)/E31 -> -1 | F33: =+(F32-F31)/F31 -> -1 | G33: =+(G32-G31)/G31 -> -1 | H33: =+(H32-H31)/H31 -> -1 | I33: =+(I32-I31)/I31 -> -1 | J33: =+(J32-J31)/J31 -> -1 | K33: =+(K32-K31)/K31 -> -1 | ... O33: =+(O32-O31)/O31 -> -1 | P33: =+(P31-P30)/P30 -> -0.2037008 | Q33: =+(Q31-Q30)/Q30 -> -0.2037008
B34: 2016 Salary vs Shipping amount
B35: Total salary | C35: VND | D35: 4985628539 | E35: 6264598796 | F35: 5873452717 | G35: 6043304524 | H35: 6567198286 | I35: 7000611623 | J35: 6798074532 | K35: 8232980373 | L35: 8419444750 | M35: 8629092753 | N35: 8406314282 | O35: 9481813094 | Q35: =AVERAGE(D35:O35) -> 7.2252095e+09
C36: USD | D36: 223570.79 | E36: 280923.71 | F36: 263383.53 | G36: 271000.2 | H36: 294493.2 | I36: 313928.77 | J36: 304846.39 | K36: 369191.94 | L36: 377553.58 | M36: 386954.83 | N36: 373613.97 | O36: 421413.92 | Q36: =AVERAGE(D36:O36) -> 323406.24
B37: Total shipping amount | C37: USD | D37: 1987291.4 | E37: 1199083.5 | F37: 1873767.3 | G37: 1773881.3 | H37: 1849495.3 | I37: 2031953.9 | J37: 2689634.8 | K37: 2612671.3 | L37: 2993469.1 | M37: 3980024.2 | N37: 2885257.6 | O37: 2914375.3 | Q37: =AVERAGE(D37:O37) -> 2399242.1
B38: Percentage | D38: =D36/D37 -> 0.11250026 | E38: 0.23428203 | F38: =F36/F37 -> 0.14056363 | G38: =G36/G37 -> 0.15277246 | H38: =H36/H37 -> 0.15922895 | I38: =I36/I37 -> 0.15449601 | J38: =J36/J37 -> 0.11334119 | K38: =K36/K37 -> 0.14130823 | L38: =L36/L37 -> 0.12612577 | M38: 0.097224242 | N38: =N36/N37 -> 0.12949068 | O38: 0.092937551 | Q38: =Q36/Q37 -> 0.13479517
B39: Total Vina amount | C39: USD | D39: 1330265.3 | E39: 776254.62 | F39: 1245667.5 | G39: 1176874.2 | H39: 1233247.5 | I39: 1439778.2 | J39: 1884162.4 | K39: 1944249.7 | L39: 2480298.5 | M39: 3378138.8 | N39: 2446838.4 | O39: 2455810.7 | Q39: =AVERAGE(D39:O39) -> 1815965.5
B40: Percentage | D40: =D36/D39 -> 0.16806481 | E40: 0.36189635 | F40: =F36/F39 -> 0.21143968 | G40: =G36/G39 -> 0.23027118 | H40: =H36/H39 -> 0.23879488 | I40: =I36/I39 -> 0.21803968 | J40: =J36/J39 -> 0.16179412 | K40: =K36/K39 -> 0.18988916 | L40: =L36/L39 -> 0.15222102 | M40: 0.11454675 | N40: =N36/N39 -> 0.15269254 | O40: 0.1715987 | Q40: =Q36/Q39 -> 0.17809052
B41: 2017 Salary vs Shipping amount
B42: Total salary | C42: VND | D42: =+[3]Average!C5 -> 7.6422001e+09 | E42: =+[3]Average!D5 -> 7.3955351e+09 | F42: =+[3]Average!E5 -> 8.5595478e+09 | G42: =+[3]Average!F5 -> 8.539977e+09 | H42: =+[3]Average!G5 -> 7.9986067e+09 | I42: =+[3]Average!H5 -> 7.3227054e+09 | J42: =+[3]Average!I5 -> 7.580296e+09 | K42: =+[3]Average!J5 -> 8.9163517e+09 | ... O42: =+[3]Average!N5 -> 9.2365815e+09 | Q42: =AVERAGE(D42:O42) -> 8.4704408e+09
C43: USD | D43: =+D42/D3 -> 336660.8 | E43: =+E42/E3 -> 325794.5 | F43: =+F42/F3 -> 377072.59 | G43: =+G42/G3 -> 376210.44 | H43: =+H42/H3 -> 352361.53 | I43: =+I42/I4 -> 318516.98 | J43: =+J42/J3 -> 333933.74 | K43: =+K42/K3 -> 392790.82 | L43: =+L42/L3 -> 431854.84 | M43: =+M42/M3 -> 425085.31 | N43: =+N42/N3 -> 396517.48 | O43: =+O42/O3 -> 406897.86 | Q43: =AVERAGE(D43:O43) -> 372808.07
B44: Total shipping amount | C44: USD | D44: 2495199.9 | E44: 1902208.8 | F44: 2488804.8 | G44: 2657488.2 | H44: 2305065.6 | I44: 1919010.6 | J44: 2247982.5 | K44: 2965495.4 | L44: 3630914.2 | M44: 3246484.6 | N44: 2427016.8 | O44: 3060043.5 | Q44: =AVERAGE(D44:O44) -> 2612142.9
B45: Percentage | D45: =D43/D44 -> 0.13492338 | E45: =E43/E44 -> 0.17127168 | F45: =F43/F44 -> 0.1515075 | G45: =G43/G44 -> 0.14156618 | H45: =H43/H44 -> 0.15286399 | I45: =I43/I44 -> 0.16597979 | J45: =J43/J44 -> 0.14854819 | K45: =K43/K44 -> 0.13245369 | ... O45: =O43/O44 -> 0.13297127 | Q45: =Q43/Q44 -> 0.14272116
B46: Total Vina amount | C46: USD | D46: 1971480.1 | E46: 1455562.7 | F46: 1786971.5 | G46: 2062606.3 | H46: 1787595.3 | I46: 1474122.6 | J46: 1759182.9 | K46: 2325160.8 | L46: 2862590 | M46: 2586948.8 | N46: 2069141.3 | O46: 2624582.2 | Q46: =AVERAGE(D46:O46) -> 2063828.7
B47: Percentage | D47: =D43/D46 -> 0.1707655 | E47: =E43/E46 -> 0.22382718 | F47: =F43/F46 -> 0.21101209 | G47: =G43/G46 -> 0.18239566 | H47: =H43/H46 -> 0.19711483 | I47: =I43/I46 -> 0.21607224 | J47: =J43/J46 -> 0.18982321 | K47: =K43/K46 -> 0.16893061 | ... O47: =O43/O46 -> 0.15503338 | Q47: =Q43/Q46 -> 0.18063906
B48: Total salary 2017 vs 2016 | D48: =(D42-D35)/D35 -> 0.53284587 | E48: =(E42-E35)/E35 -> 0.18052812 | F48: =(F42-F35)/F35 -> 0.45732811 | G48: =(G42-G35)/G35 -> 0.41313034 | H48: =(H42-H35)/H35 -> 0.21796333 | I48: =(I42-I35)/I35 -> 0.046009375 | J48: =(J42-J35)/J35 -> 0.11506515 | K48: =(K42-K35)/K35 -> 0.083004126 | L48: =(L42-L35)/L35 -> 0.16434102 | M48: -0.0071024385 | N48: =(N42-N35)/N35 -> 0.070736413 | O48: -0.0047428345 | Q48: =(Q42-Q35)/Q35 -> 0.17234535
B49: 2018 Salary vs Shipping amount
B50: Total salary | C50: VND | D50: =+[4]Average!Q4 -> 9.6545452e+09 | E50: =+[4]Average!R4 -> 7.0825142e+09 | F50: =+[4]Average!S4 -> 9.1835007e+09 | G50: 8.7190036e+09 | H50: =+[3]Average!Z5 -> 7285700591 | I50: 9.3356602e+09 | J50: 8.9449552e+09 | K50: =+[3]Average!AF5 -> 7659084972 | L50: =+[3]Average!AH5 -> 7632254225 | M50: =+[3]Average!AJ5 -> 8072850333 | N50: =+[3]Average!AL5 -> 7998313641 | O50: =+[3]Average!AN5 -> 8704287799 | Q50: =AVERAGE(D50:O50) -> 8.3560559e+09
C51: USD | D51: =+D50/D4 -> 424468.9 | E51: =+E50/E4 -> 310772.89 | F51: =+F50/F4 -> 402608.54 | G51: =+G50/G4 -> 382412.44 | H51: =+H50/H4 -> 319058.49 | I51: =+I50/I4 -> 406074.82 | J51: =+J50/J4 -> 383738.96 | K51: =+K50/K4 -> 328152.74 | ... O51: =+O50/O4 -> 374619.66 | Q51: =AVERAGE(D51:O51) -> 362168.51
B52: Total shipping amount | C52: USD | D52: 2741485.8 | E52: 1667558.9 | F52: 2714999.5 | G52: 2505468.3 | H52: 2892729.3 | I52: 2588625.7 | J52: 2382754.2 | K52: 3080107.1 | L52: 2772137.6 | M52: 4078998.3 | N52: 3497759.3 | O52: 3131843.6 | Q52: =AVERAGE(D52:O52) -> 2837872.3
B53: Percentage | D53: =D51/D52 -> 0.1548317 | E53: =E51/E52 -> 0.18636397 | F53: =F51/F52 -> 0.14829047 | G53: =G51/G52 -> 0.15263112 | H53: =H51/H52 -> 0.1102967 | I53: =I51/I52 -> 0.15686888 | J53: =J51/J52 -> 0.16104849 | K53: =K51/K52 -> 0.10653939 | ... O53: =O51/O52 -> 0.11961634 | Q53: =Q51/Q52 -> 0.12761974
B54: Total Vina amount | C54: USD | D54: 2016502.6 | E54: 1341925 | F54: 2203671.5 | G54: 2006802.5 | H54: 2388287 | I54: 2151890.5 | J54: 1971039.7 | K54: 2651543.1 | L54: 2389961.3 | M54: 3517272 | N54: 3135932.6 | O54: 2805415.5 | Q54: =AVERAGE(D54:O54) -> 2381686.9
B55: Percentage | D55: =D51/D54 -> 0.21049757 | E55: =E51/E54 -> 0.23158738 | F55: =F51/F54 -> 0.18269898 | G55: =G51/G54 -> 0.19055809 | H55: =H51/H54 -> 0.13359303 | I55: =I51/I54 -> 0.18870608 | J55: =J51/J54 -> 0.1946886 | K55: =K51/K54 -> 0.12375916 | ... O55: =O51/O54 -> 0.13353446 | Q55: =Q51/Q54 -> 0.15206386
B56: Total salary 2018 vs 2017 | D56: =+(D50-D42)/D42 -> 0.26332013 | E56: =+(E50-E42)/E42 -> -0.04232566 | F56: =+(F50-F42)/F42 -> 0.072895555 | G56: =+(G50-G42)/G42 -> 0.020963367 | H56: =+(H50-H42)/H42 -> -0.089128789 | I56: =+(I50-I42)/I42 -> 0.27489222 | J56: =+(J50-J42)/J42 -> 0.18002717 | K56: =+(K50-K42)/K42 -> -0.14100686 | ... O56: =+(O50-O42)/O42 -> -0.057628861 | Q56: =(Q50-Q42)/Q42 -> -0.013504008
B57: 2019 Salary vs Shipping amount
B58: Total salary | C58: VND | D58: 1.0937907e+10 | E58: 9545464405 | F58: 14416053864 | G58: 14026010814 | H58: 1.5662934e+10 | I58: 1.5818551e+10 | J58: 17250105666 | K58: 1.7576581e+10 | L58: 1.6896811e+10 | M58: 17649118212 | N58: 14589221339 | O58: 1.483576e+10 | P58: =+SUM(D58:O58) -> 1.7920452e+11 | Q58: =AVERAGE(D58:O58) -> 1.493371e+10
C59: USD | D59: =+D58/D5 -> 470447.59 | E59: =+E58/E5 -> 410645.92 | F59: =+F58/F5 -> 620178.7 | G59: =+G58/G5 -> 601458.44 | H59: =+H58/H5 -> 667359.77 | I59: =+I58/I5 -> 678325.49 | J59: =+J58/J5 -> 741302.35 | K59: =+K58/K5 -> 756307.26 | ... O59: =+O58/O5 -> 638921.61 | P59: =+SUM(D59:O59) -> 7698962.4 | Q59: =AVERAGE(D59:O59) -> 641580.2
B60: Total shipping amount | C60: USD | D60: 4291675.3 | E60: 1466595.6 | F60: 3609759.2 | G60: 3475679.8 | H60: 4036823.9 | I60: 3473209.7 | J60: 4355517.2 | K60: 5128775.3 | L60: 5608231.9 | M60: 6843626.4 | N60: 4062174.2 | O60: 4568594.4 | P60: =+SUM(D60:O60) -> 50920663 | Q60: =AVERAGE(D60:O60) -> 4243388.6
B61: Percentage | D61: =D59/D60 -> 0.10961864 | E61: =E59/E60 -> 0.27999941 | F61: =F59/F60 -> 0.17180611 | G61: =G59/G60 -> 0.17304771 | H61: =H59/H60 -> 0.16531803 | I61: =I59/I60 -> 0.1953022 | J61: =J59/J60 -> 0.17019847 | K61: =K59/K60 -> 0.14746352 | ... Q61: =Q59/Q60 -> 0.15119525
B62: Total Vina amount | C62: USD | D62: 3854384.7 | E62: 1221643.1 | F62: 3045648 | G62: 2929172.8 | H62: 3458729.3 | I62: 2929172.8 | J62: 3712127.8 | K62: 4450842.6 | L62: 4941394.1 | M62: 5774914.2 | N62: 3473884.3 | O62: 3862871.9 | P62: =+SUM(D62:O62) -> 43654786 | Q62: =AVERAGE(D62:O62) -> 3637898.8
B63: Percentage | D63: =D59/D62 -> 0.12205518 | E63: =E59/E62 -> 0.33614229 | F63: =F59/F62 -> 0.20362783 | G63: =G59/G62 -> 0.20533389 | H63: =H59/H62 -> 0.19294941 | I63: =I59/I62 -> 0.23157579 | J63: =J59/J62 -> 0.19969742 | K63: =K59/K62 -> 0.16992451 | ... Q63: =Q59/Q62 -> 0.1763601
B64: Total salary 2019 vs 2018 | D64: =+(D58-D50)/D50 -> 0.1329282 | E64: =+(E58-E50)/E50 -> 0.34775084 | F64: =+(F58-F50)/F50 -> 0.56977761 | G64: =+(G58-G50)/G50 -> 0.60867129 | H64: =+(H58-H50)/H50 -> 1.1498185 | I64: =+(I58-I50)/I50 -> 0.69442228 | J64: =+(J58-J50)/J50 -> 0.92847312 | K64: =+(K58-K50)/K50 -> 1.2948669 | ... O64: =+(O58-O50)/O50 -> 0.70441972 | Q64: =(Q58-Q50)/Q50 -> 0.78717208
B65: 2020Salary vs Shipping amount
B66: Total salary | C66: VND | D66: 1.5511171e+10 | E66: 17662048991 | F66: 1.7177784e+10 | G66: 11682502533 | H66: 10911324590 | I66: 1.4405106e+10 | J66: 23464528569 | K66: 25889308850 | L66: 20683922318 | M66: 17596543903 | N66: 17788549233 | O66: 2.315919e+10 | P66: =+SUM(D66:O66) -> 2.1593198e+11 | Q66: =AVERAGE(D66:O66) -> 1.7994332e+10
C67: USD | D67: 606536.22 | E67: 673793.52 | F67: 691399.02 | G67: 496388.47 | H67: =+H66/H6 -> 466694.81 | I67: =+I66/I6 -> 618244.89 | J67: =+J66/J6 -> 1008359.6 | K67: =+K66/K6 -> 1112561.6 | L67: =+L66/L6 -> 888866.45 | M67: =+M66/M6 -> 756190.11 | N67: =+N66/N6 -> 765757.61 | O67: =+O66/O6 -> 998671.4 | P67: =+SUM(D67:O67) -> 9083463.7 | Q67: =AVERAGE(D67:O67) -> 756955.31
B68: Total shipping amount | C68: USD | D68: 3419473.3 | E68: 3294800.7 | F68: 2816592.4 | G68: 1804414.7 | H68: 1835029 | I68: 2158484.6 | J68: 5351263.3 | K68: 5076018 | L68: 4979280.6 | M68: 4834063.2 | N68: 3997080.2 | O68: 3613884.6 | P68: =+SUM(D68:O68) -> 43180385 | Q68: =AVERAGE(D68:O68) -> 3598365.4
B69: Percentage | D69: =D67/D68 -> 0.17737709 | E69: =E67/E68 -> 0.20450205 | F69: =F67/F68 -> 0.24547358 | G69: =G67/G68 -> 0.27509667 | H69: =H67/H68 -> 0.25432558 | I69: =I67/I68 -> 0.28642544 | J69: =J67/J68 -> 0.18843394 | K69: =K67/K68 -> 0.21918 | ... Q69: =Q67/Q68 -> 0.21036088
B70: Total Vina amount | C70: USD | D70: 2874088.2 | E70: 2812161 | F70: 2386361.8 | G70: 1483041.2 | H70: 1569432.2 | I70: 1856854 | J70: 4836700.6 | K70: 4574294.8 | L70: 4537212.3 | M70: 4092720.9 | N70: 3374933.1 | O70: 3048751.4 | P70: =+SUM(D70:O70) -> 37446552 | Q70: =AVERAGE(D70:O70) -> 3120546
B71: Percentage | D71: =D67/D70 -> 0.21103605 | E71: =E67/E70 -> 0.23959991 | F71: =F67/F70 -> 0.28972934 | G71: =G67/G70 -> 0.33470984 | H71: =H67/H70 -> 0.29736538 | I71: =I67/I70 -> 0.33295288 | J71: =J67/J70 -> 0.20848089 | K71: =K67/K70 -> 0.24322036 | ... Q71: =Q67/Q70 -> 0.24257143
B72: Total salary 2020 vs 2019 | D72: =+(D66-D58)/D58 -> 0.4181115 | E72: =+(E66-E58)/E58 -> 0.85030798 | F72: =+(F66-F58)/F58 -> 0.19157324 | G72: =+(G66-G58)/G58 -> -0.16708302 | H72: =+(H66-H58)/H58 -> -0.30336649 | I72: =+(I66-I58)/I58 -> -0.089353616 | J72: =+(J66-J58)/J58 -> 0.36025419 | K72: =+(K66-K58)/K58 -> 0.47294341 | ... Q72: =+(Q66-Q58)/Q58 -> 0.20494719
B73: 2021Salary vs Shipping amount
B74: Total salary | C74: VND | D74: 16441536846 | E74: 12100047441 | F74: 19026159085 | G74: 20174955250 | H74: 22065059663 | I74: 22711863549 | J74: 18363549693 | K74: 16865410206 | L74: 14530663270 | M74: 13036628991 | N74: 10768788412 | O74: 15196366669 | P74: =+SUM(D74:H74) -> 89807758285 | Q74: =AVERAGE(D74:H74) -> 17961551657 | R74: x
C75: USD | D75: 710678.06 | E75: 523811.58 | F75: 821154.9 | G75: 871300.16 | H75: 953340.23 | I75: 982772.11 | J75: 796510.51 | K75: 737446.88 | L75: 635637.06 | M75: 570530.81 | N75: 472418.88 | O75: 663162.41 | P75: =+SUM(D75:H75) -> 3880284.9 | Q75: =AVERAGE(D75:H75) -> 776056.99 | R75: x
B76: Total shipping amount | C76: USD | D76: 4797270.1 | E76: 1842388.1 | F76: 4563503.7 | G76: 4075732.2 | H76: 4058380.5 | I76: 4400840 | J76: 5517803.1 | K76: 5957489.8 | L76: 3722947.4 | M76: 3390972.8 | N76: 3277692.9 | O76: 2911783.3 | P76: =+SUM(D76:H76) -> 19337275 | Q76: =AVERAGE(D76:H76) -> 3867454.9 | R76: x | S76: katie
B77: Percentage | D77: 0.14814218 | E77: 0.2843112 | F77: 0.17993957 | G77: 0.21377758 | H77: 0.23490657 | I77: 0.22331467 | J77: 0.14435283 | K77: 0.12378483 | L77: 0.1707349 | M77: 0.16824989 | N77: 0.14413153 | O77: 0.22775129 | P77: =P75/P76 -> 0.20066348 | Q77: =Q75/Q76 -> 0.20066348
B78: Total Vina amount | C78: USD | D78: 3785994 | E78: 1600923.7 | F78: 3904152.1 | G78: 3509591 | H78: 3600402.4 | I78: 3934112.9 | J78: 5036755.6 | K78: 5599388 | L78: 3472228.8 | M78: 3048561.9 | N78: 2965559.7 | O78: 2606420.2 | P78: =+SUM(D78:H78) -> 16401063 | Q78: =AVERAGE(D78:H78) -> 3280212.6 | R78: x | S78: katie
B79: Percentage | D79: 0.18771241 | E79: 0.32719335 | F79: 0.21032861 | G79: 0.24826259 | H79: 0.26478714 | I79: 0.24980781 | J79: 0.1581396 | K79: 0.13170134 | L79: 0.18306313 | M79: 0.18714752 | N79: 0.15930176 | O79: 0.25443419 | P79: =P75/P78 -> 0.2365874 | Q79: =Q75/Q78 -> 0.2365874
B80: Total salary 2021 vs 2020 | D80: =+(D74-D66)/D66 -> 0.059980369 | E80: =+(E74-E66)/E66 -> -0.31491259 | F80: =+(F74-F66)/F66 -> 0.10760265 | G80: =+(G74-G66)/G66 -> 0.7269378 | H80: =+(H74-H66)/H66 -> 1.0222164 | I80: =+(I74-I66)/I66 -> 0.57665371 | J80: =+(J74-J66)/J66 -> -0.21739107 | K80: =+(K74-K66)/K66 -> -0.34855695 | ... Q80: =+(Q74-Q66)/Q66 -> -0.0018216841
B81: 2022 Salary vs Shipping amount
B82: Total salary | C82: VND | D82: 12076676872 | E82: 13607720288 | F82: 15586464931 | G82: 15723868311 | H82: 16069485993 | I82: 16079212492 | J82: 15764346648 | K82: 16528386837 | L82: 13238292228 | M82: 12265668166 | N82: 11220453850 | O82: 11692786208 | P82: =+SUM(D82:O82) -> 169853362824 | Q82: =AVERAGE(D82:O82) -> 14154446902 | R82: x
C83: USD | D83: 874420.06 | E83: 593446.15 | F83: 678853 | G83: 681276.79 | H83: 689677.51 | I83: 687733.64 | J83: 672253.59 | K83: 701842.33 | L83: 552285.87 | M83: 492993.09 | N83: 453626.6 | O83: 494618.71 | P83: =+SUM(D83:O83) -> 7573027.3 | Q83: =AVERAGE(D83:O83) -> 631085.61 | R83: x
B84: Total shipping amount | C84: USD | D84: 4155635.1 | E84: 2455440.7 | F84: 3670805.7 | G84: 4327561.4 | H84: 4162712 | I84: 5078232.8 | J84: 6017079.2 | K84: 6225964.6 | L84: 4275739 | M84: 4220745.3 | N84: 2672276.4 | O84: 3303252.1 | P84: =+SUM(D84:O84) -> 50565444 | Q84: =AVERAGE(D84:O84) -> 4213787 | R84: x | S84: katie-J
B85: Percentage | D85: =+D83/D84 -> 0.21041791 | E85: 0.2416862 | F85: 0.18493297 | G85: 0.15742741 | H85: 0.16567985 | I85: 0.13542775 | J85: 0.11172424 | K85: 0.11272829 | L85: 0.12916735 | M85: 0.11680238 | N85: 0.16975287 | O85: 0.1497369 | P85: =P83/P84 -> 0.14976685 | Q85: =Q83/Q84 -> 0.14976685
B86: Total Vina amount | C86: USD | D86: 3798938.2 | E86: 2259735.9 | F86: 3400819.4 | G86: 3996271 | H86: 3848453.1 | I86: 4759217.8 | J86: 5697148.2 | K86: 5924715.8 | L86: 3917083.4 | M86: 3850367.1 | N86: 2379177.5 | O86: 2838387.3 | P86: =+SUM(D86:O86) -> 46670315 | Q86: =AVERAGE(D86:O86) -> 3889192.9 | R86: x | S86: katie-K
B87: Percentage | D87: =+D83/D86 -> 0.23017486 | E87: 0.26261748 | F87: 0.19961454 | G87: 0.17047813 | H87: 0.17920902 | I87: 0.1445056 | J87: 0.11799826 | K87: 0.11846008 | L87: 0.14099416 | M87: 0.12803795 | N87: 0.1906653 | O87: 0.17426047 | P87: =P83/P86 -> 0.16226647 | Q87: =Q83/Q86 -> 0.16226647
B88: Total salary 2022 vs 2021 | D88: -0.26547761 | E88: 0.12460057 | F88: -0.18078763 | G88: -0.22062438 | H88: -0.27172252 | I88: -0.29203465 | J88: -0.14154143 | K88: -0.019983111 | L88: -0.088940953 | M88: -0.059138051 | N88: 0.041942085 | O88: -0.23055382 | P88: =+(P82-P66)/P66 -> -0.21339413 | Q88: =+(Q82-Q66)/Q66 -> -0.21339413
B89: 2023 Salary vs Shipping amount
B90: Total salary | C90: VND | D90: 16909898910 | E90: 12062959803 | F90: 13224123797 | G90: 12590256975 | H90: 12825595507 | I90: 13611374601 | J90: 12864233613 | K90: 13291349691 | L90: 11717235750 | M90: 11964928006 | N90: 10624345914 | O90: 12625097142 | P90: =+SUM(D90:O90) -> 154311399709 | Q90: =AVERAGE(D90:O90) -> 1.2859283e+10 | R90: x
C91: USD | D91: 717433.13 | E91: 504831.96 | F91: 560700.61 | G91: 533937.95 | H91: 543227.26 | I91: 574319.6 | J91: 540400.49 | K91: 549683.61 | L91: 479232.55 | M91: 484802.59 | N91: 435781.21 | O91: 518484.48 | P91: =+SUM(D91:O91) -> 6442835.4 | Q91: =AVERAGE(D91:O91) -> 536902.95 | R91: x
B92: Total shipping amount | C92: USD | D92: 1817830.8 | E92: 2754400.5 | F92: 3421718.6 | G92: 3319419.5 | H92: 2805726 | I92: 3591467.6 | J92: 4100164.2 | K92: 6293063.7 | L92: 4115701.8 | M92: 4270134.4 | N92: 3255400.8 | O92: 3112909 | P92: =+SUM(D92:O92) -> 42857937 | Q92: =AVERAGE(D92:O92) -> 3571494.7 | R92: x | S92: katie-J
B93: Percentage | D93: =+D91/D92 -> 0.39466442 | E93: =+E91/E92 -> 0.18328197 | F93: =+F91/F92 -> 0.1638652 | G93: =+G91/G92 -> 0.16085281 | H93: =+H91/H92 -> 0.19361379 | I93: =+I91/I92 -> 0.15991223 | J93: =+J91/J92 -> 0.13179972 | K93: =+K91/K92 -> 0.087347536 | ... Q93: =+Q91/Q92 -> 0.15033004
B94: Total Vina amount | C94: USD | D94: 1595547.2 | E94: 2435137.1 | F94: 2997796.9 | G94: 2985052.3 | H94: 2495845.6 | I94: 3270514.1 | J94: 3830218.2 | K94: 5927862.8 | L94: 3764651.9 | M94: 3636585.5 | N94: 2842440.8 | O94: 2694017.2 | P94: =+SUM(D94:O94) -> 38475670 | Q94: =AVERAGE(D94:O94) -> 3206305.8 | R94: x | S94: katie-K
B95: Percentage | D95: =+D91/D94 -> 0.44964709 | E95: =+E91/E94 -> 0.20731152 | F95: =+F91/F94 -> 0.18703755 | G95: =+G91/G94 -> 0.17887056 | H95: =+H91/H94 -> 0.21765259 | I95: =+I91/I94 -> 0.1756053 | J95: =+J91/J94 -> 0.14108869 | K95: =+K91/K94 -> 0.092728801 | ... Q95: =+Q91/Q94 -> 0.1674522
B96: Total salary 2023 vs 2022 | D96: =+(D90-D74)/D74 -> 0.028486514 | E96: =+(E90-E74)/E74 -> -0.003065082 | F96: =+(F90-F74)/F74 -> -0.30495042 | G96: =+(G90-G74)/G74 -> -0.37594623 | H96: =+(H90-H74)/H74 -> -0.41873733 | I96: =+(I90-I74)/I74 -> -0.40069319 | J96: =+(J90-J74)/J74 -> -0.29946912 | K96: =+(K90-K74)/K74 -> -0.21191661 | ... Q96: =+(Q90-Q74)/Q74 -> -0.28406612
B97: 2024 Salary vs Shipping amount
B98: Total salary | C98: VND | P98: =+SUM(D98:O98) -> 0 | Q98: =AVERAGE(D98:O98) -> #DIV/0! | R98: x
C99: USD | P99: =+SUM(D99:O99) -> 0 | Q99: =AVERAGE(D99:O99) -> #DIV/0! | R99: x
B100: Total shipping amount | C100: USD | P100: =+SUM(D100:O100) -> 0 | Q100: =AVERAGE(D100:O100) -> #DIV/0! | R100: x | S100: katie-J
...

Sheet So sánh giờ
A1: Công ty TNHH Bao Bì Cao Cấp S&K Vina | N1: O | O1: AA | P1: Q | Q1: AH | R1: AI | S1: AJ | T1: AK | U1: AL | AE1: O | AF1: AA | AG1: Q | AH1: AH | AI1: AI | AJ1: AJ | AK1: AK | AL1: AL | AV1: O | AW1: AA | AX1: Q | AY1: AH | AZ1: AI | BA1: AJ | BB1: AK | BC1: AL
E2: 45748 | V2: 45717 | AM2: 45689 | BD2: 45658
A3: STT No. | B3: Fac | C3: Dep new | D3: Dep Code | E3: # of worker | F3: Tổng thu nhập Total gross salary | G3: BHXH&BHYT, BHTN Social & Health Ins, Unempl-oyment Benefit | H3: KPCĐ Union Dues | I3: Thuế TNCN Personal Income Tax | J3: Đồng Phục Uniform | K3: Ứng Lương Advance | L3: Số Tiền (VND) Net salary | M3: Actual Working day | N3: Paid leave | O3: Annual Leave | P3: extra pay for night work + 30% | Q3: 1.5 | R3: 2 | S3: 2.1 | T3: 2.7 | U3: 3 | V3: # of worker | W3: Tổng thu nhập Total gross salary | X3: BHXH&BHYT, BHTN Social & Health Ins, Unempl-oyment Benefit | Y3: KPCĐ Union Dues | Z3: Thuế TNCN Personal Income Tax | AA3: Đồng Phục Uniform | AB3: Ứng Lương Advance | AC3: Số Tiền (VND) Net salary | AD3: Actual Working day | AE3: Paid leave | AF3: Annual Leave | AG3: extra pay for night work + 30% | AH3: 1.5 | AI3: 2 | AJ3: 2.1 | AK3: 2.7 | AL3: 3 | AM3: # of worker | AN3: Tổng thu nhập Total gross salary | AO3: BHXH&BHYT, BHTN Social & Health Ins, Unempl-oyment Benefit | AP3: KPCĐ Union Dues | AQ3: Thuế TNCN Personal Income Tax | AR3: Đồng Phục Uniform | AS3: Ứng Lương Advance | AT3: Số Tiền (VND) Net salary | AU3: Actual Working day | AV3: Paid leave | AW3: Annual Leave | AX3: extra pay for night work + 30% | AY3: 1.5 | AZ3: 2 | BA3: 2.1 | BB3: 2.7 | BC3: 3 | BD3: # of worker | BE3: Tổng thu nhập Total gross salary | BF3: BHXH&BHYT, BHTN Social & Health Ins, Unempl-oyment Benefit | BG3: KPCĐ Union Dues | BH3: Thuế TNCN Personal Income Tax | BI3: Đồng Phục Uniform | BJ3: Ứng Lương Advance | BK3: Số Tiền (VND) Net salary | BL3: Actual Working day | BM3: Paid leave | BN3: Annual Leave | BO3: extra pay for night work + 30% | BP3: 1.5 | BQ3: 2 | BR3: 2.1 | BS3: 2.7 | BT3: 3
A4: =SUBTOTAL(3,B$4:B4) -> 1 | B4: Foreigners | C4: Foreigners | E4: 3 | F4: =+'Foreign Salary'!L11 -> 686964617 | G4: =+'Foreign Salary'!M11 -> 13338000 | H4: 0 | I4: =+'Foreign Salary'!P11 -> 193129316 | J4: 0 | K4: =+'Foreign Salary'!Q11 -> 0 | L4: =+(F4)-SUM(G4:K4) -> 480497301 | M4: =SUMIFS('Salary sheet'!$M$6:$M$13045,'Salary sheet'!$F$6:$F$13045,'So sánh giờ'!$C4) -> 0 | N4: =SUMIFS('Salary sheet'!$O$6:$O$13045,'Salary sheet'!$F$6:$F$13045,'So sánh giờ'!$C4) -> 0 | O4: =SUMIFS('Salary sheet'!$AA$6:$AA$13045,'Salary sheet'!$F$6:$F$13045,'So sánh giờ'!$C4) -> 0 | P4: =SUMIFS('Salary sheet'!$Q$6:$Q$13045,'Salary sheet'!$F$6:$F$13045,'So sánh giờ'!$C4) -> 0 | Q4: =SUMIFS('Salary sheet'!$AH$6:$AH$13045,'Salary sheet'!$F$6:$F$13045,'So sánh giờ'!$C4) -> 0 | R4: =SUMIFS('Salary sheet'!$AI$6:$AI$13045,'Salary sheet'!$F$6:$F$13045,'So sánh giờ'!$C4) -> 0 | S4: =SUMIFS('Salary sheet'!$AJ$6:$AJ$13045,'Salary sheet'!$F$6:$F$13045,'So sánh giờ'!$C4) -> 0 | T4: =SUMIFS('Salary sheet'!$AK$6:$AK$13045,'Salary sheet'!$F$6:$F$13045,'So sánh giờ'!$C4) -> 0 | U4: =SUMIFS('Salary sheet'!$AL$6:$AL$13045,'Salary sheet'!$F$6:$F$13045,'So sánh giờ'!$C4) -> 0 | V4: 3 | W4: 669487099 | X4: 13338000 | Y4: 0 | Z4: 187012185 | AA4: 0 | AB4: 0 | AC4: 469136914 | AD4: 0 | AE4: 0 | AF4: 0 | AG4: 0 | AH4: 0 | AI4: 0 | AJ4: 0 | AK4: 0 | AL4: 0 | AM4: 3 | AN4: 681681739 | AO4: 13338000 | AP4: 0 | AQ4: 191280309 | AR4: 0 | AS4: 0 | AT4: 477063430 | AU4: 0 | AV4: 0 | AW4: 0 | AX4: 0 | AY4: 0 | AZ4: 0 | BA4: 0 | BB4: 0 | BC4: 0 | BD4: 3 | BE4: 1285996102 | BF4: 13338000 | BG4: 0 | BH4: 402790336 | BI4: 0 | BJ4: 0 | BK4: 869867766 | BL4: 0 | BM4: 0 | BN4: 0 | BO4: 0 | BP4: 0 | BQ4: 0 | BR4: 0 | BS4: 0 | BT4: 0
A5: =SUBTOTAL(3,B$4:B5) -> 2 | B5: SK2 | C5: P0 - Cleaning | D5: P0-CL-1-01 | E5: =COUNTIFS('Salary sheet'!$F$6:$F$2288,C5,'Salary sheet'!$E$6:$E$2288,B5) -> 4 | F5: =+SUMIFS('Salary sheet'!$AN$6:$AN$1292,'Salary sheet'!$F$6:$F$1292,'So sánh giờ'!C5,'Salary sheet'!$E$6:$E$1292,'So sánh giờ'!B5) -> 37891917 | G5: =+SUMIFS('Salary sheet'!$AO$6:$AO$2288,'Salary sheet'!$F$6:$F$2288,C5,'Salary sheet'!$E$6:$E$2288,B5) -> 2962470 | H5: =+SUMIFS('Salary sheet'!$AP$6:$AP$2288,'Salary sheet'!$F$6:$F$2288,C5,'Salary sheet'!$E$6:$E$2288,B5) -> 176400 | I5: =+SUMIFS('Salary sheet'!$AQ$6:$AQ$2288,'Salary sheet'!$F$6:$F$2288,C5,'Salary sheet'!$E$6:$E$2288,B5) -> 0 | J5: =+SUMIFS('Salary sheet'!$AR$6:$AR$2288,'Salary sheet'!$F$6:$F$2288,C5,'Salary sheet'!$E$6:$E$2288,B5) -> 0 | K5: =SUMIFS('Salary sheet'!$AS$6:$AS$1291,'Salary sheet'!$F$6:$F$1291,'So sánh giờ'!C5) -> 0 | L5: =+(F5)-SUM(G5:K5) -> 34753047 | M5: =SUMIFS('Salary sheet'!$M$6:$M$13045,'Salary sheet'!$F$6:$F$13045,'So sánh giờ'!$C5) -> 94.5 | N5: =SUMIFS('Salary sheet'!$O$6:$O$13045,'Salary sheet'!$F$6:$F$13045,'So sánh giờ'!$C5) -> 9 | O5: =SUMIFS('Salary sheet'!$AA$6:$AA$13045,'Salary sheet'!$F$6:$F$13045,'So sánh giờ'!$C5) -> 0 | P5: =SUMIFS('Salary sheet'!$Q$6:$Q$13045,'Salary sheet'!$F$6:$F$13045,'So sánh giờ'!$C5) -> 0 | Q5: =SUMIFS('Salary sheet'!$AH$6:$AH$13045,'Salary sheet'!$F$6:$F$13045,'So sánh giờ'!$C5) -> 86 | R5: =SUMIFS('Salary sheet'!$AI$6:$AI$13045,'Salary sheet'!$F$6:$F$13045,'So sánh giờ'!$C5) -> 0 | S5: =SUMIFS('Salary sheet'!$AJ$6:$AJ$13045,'Salary sheet'!$F$6:$F$13045,'So sánh giờ'!$C5) -> 0 | T5: =SUMIFS('Salary sheet'!$AK$6:$AK$13045,'Salary sheet'!$F$6:$F$13045,'So sánh giờ'!$C5) -> 0 | U5: =SUMIFS('Salary sheet'!$AL$6:$AL$13045,'Salary sheet'!$F$6:$F$13045,'So sánh giờ'!$C5) -> 0 | V5: 5 | W5: 45863314 | X5: 3681930 | Y5: 220500 | Z5: 0 | AA5: 0 | AB5: 0 | AC5: 41960884 | AD5: 128.7 | AE5: 1 | AF5: 0 | AG5: 0 | AH5: 100.5 | AI5: 0 | AJ5: 0 | AK5: 0 | AL5: 0 | AM5: 5 | AN5: 44631780 | AO5: 3681930 | AP5: 220500 | AQ5: 0 | AR5: 0 | AS5: 0 | AT5: 40729350 | AU5: 110 | AV5: 10 | AW5: 0 | AX5: 0 | AY5: 58 | AZ5: 8 | BA5: 0 | BB5: 0 | BC5: 0 | BD5: 5 | BE5: 71883791 | BF5: 3633210 | BG5: 220500 | BH5: 438426 | BI5: 0 | BJ5: 0 | BK5: 67591655 | BL5: 97.8 | BM5: 35 | BN5: 0 | BO5: 0 | BP5: 72 | BQ5: 0 | BR5: 0 | BS5: 0 | BT5: 0
A6: =SUBTOTAL(3,B$4:B6) -> 3 | B6: SK2 | C6: P0 - Design | D6: P0-DS-1-01 | E6: =COUNTIFS('Salary sheet'!$F$6:$F$2288,C6,'Salary sheet'!$E$6:$E$2288,B6) -> 4 | F6: =+SUMIFS('Salary sheet'!$AN$6:$AN$1292,'Salary sheet'!$F$6:$F$1292,'So sánh giờ'!C6,'Salary sheet'!$E$6:$E$1292,'So sánh giờ'!B6) -> 69105288 | G6: =+SUMIFS('Salary sheet'!$AO$6:$AO$2288,'Salary sheet'!$F$6:$F$2288,C6,'Salary sheet'!$E$6:$E$2288,B6) -> 7350000 | H6: =+SUMIFS('Salary sheet'!$AP$6:$AP$2288,'Salary sheet'!$F$6:$F$2288,C6,'Salary sheet'!$E$6:$E$2288,B6) -> 176400 | I6: =+SUMIFS('Salary sheet'!$AQ$6:$AQ$2288,'Salary sheet'!$F$6:$F$2288,C6,'Salary sheet'!$E$6:$E$2288,B6) -> 333370 | J6: =+SUMIFS('Salary sheet'!$AR$6:$AR$2288,'Salary sheet'!$F$6:$F$2288,C6,'Salary sheet'!$E$6:$E$2288,B6) -> 0 | K6: =SUMIFS('Salary sheet'!$AS$6:$AS$1291,'Salary sheet'!$F$6:$F$1291,'So sánh giờ'!C6) -> 0 | L6: =+(F6)-SUM(G6:K6) -> 61245518 | M6: =SUMIFS('Salary sheet'!$M$6:$M$13045,'Salary sheet'!$F$6:$F$13045,'So sánh giờ'!$C6) -> 91.5 | N6: =SUMIFS('Salary sheet'!$O$6:$O$13045,'Salary sheet'!$F$6:$F$13045,'So sánh giờ'!$C6) -> 10 | O6: =SUMIFS('Salary sheet'!$AA$6:$AA$13045,'Salary sheet'!$F$6:$F$13045,'So sánh giờ'!$C6) -> 0 | P6: =SUMIFS('Salary sheet'!$Q$6:$Q$13045,'Salary sheet'!$F$6:$F$13045,'So sánh giờ'!$C6) -> 0 | Q6: =SUMIFS('Salary sheet'!$AH$6:$AH$13045,'Salary sheet'!$F$6:$F$13045,'So sánh giờ'!$C6) -> 0 | R6: =SUMIFS('Salary sheet'!$AI$6:$AI$13045,'Salary sheet'!$F$6:$F$13045,'So sánh giờ'!$C6) -> 0 | S6: =SUMIFS('Salary sheet'!$AJ$6:$AJ$13045,'Salary sheet'!$F$6:$F$13045,'So sánh giờ'!$C6) -> 0 | T6: =SUMIFS('Salary sheet'!$AK$6:$AK$13045,'Salary sheet'!$F$6:$F$13045,'So sánh giờ'!$C6) -> 0 | U6: =SUMIFS('Salary sheet'!$AL$6:$AL$13045,'Salary sheet'!$F$6:$F$13045,'So sánh giờ'!$C6) -> 0 | V6: 4 | W6: 70760097 | X6: 7350000 | Y6: 176400 | Z6: 335216 | AA6: 0 | AB6: 0 | AC6: 62898481 | AD6: 100.8 | AE6: 0 | AF6: 0 | AG6: 0 | AH6: 0 | AI6: 16 | AJ6: 0 | AK6: 0 | AL6: 0 | AM6: 4 | AN6: 67950104 | AO6: 7350000 | AP6: 176400 | AQ6: 288734 | AR6: 180000 | AS6: 0 | AT6: 59954970 | AU6: 83.1 | AV6: 8 | AW6: 0 | AX6: 0 | AY6: 0 | AZ6: 0 | BA6: 0 | BB6: 0 | BC6: 0 | BD6: 4 | BE6: 137095637 | BF6: 7350000 | BG6: 176400 | BH6: 8511746 | BI6: 0 | BJ6: 0 | BK6: 121057491 | BL6: 77.5 | BM6: 28 | BN6: 0 | BO6: 0 | BP6: 0 | BQ6: 0 | BR6: 0 | BS6: 0 | BT6: 0
