Workbook

Sheet Sheet1
A1: 1
A2: 2
A3: 3 | B3: 2 | C3: 2 | D3: 2 | E3: 2 | F3: 2 | G3: 1 | H3: 1 | I3: 1 | J3: 1 | K3: 1 | L3: 1 | M3: 1 | N3: 1 | O3: 1 | P3: 1 | Q3: 1 | R3: 1 | S3: 1 | T3: 1 | U3: 1 | V3: 1 | W3: 1 | X3: 1 | Y3: 1 | Z3: 1 | AA3: 1 | AB3: 1 | AC3: 1 | AD3: 1 | AE3: 1 | AF3: 1 | AG3: 1 | AH3: 1 | AI3: 1 | AJ3: 1 | AK3: 1 | AL3: 1 | AM3: 1 | AN3: 1 | AO3: 1 | AP3: 1 | AQ3: 1 | AR3: 1 | AS3: 1 | AT3: 1 | AU3: 1 | AV3: 1 | AW3: 1 | AX3: 1 | AY3: 1 | AZ3: 1 | BA3: 1 | BB3: 1 | BC3: 1 | BD3: 1 | BE3: 1 | BF3: 1 | BG3: 1 | BH3: 1 | BI3: 1 | BJ3: 1 | BK3: 1 | BL3: 1 | BM3: 1 | BN3: 1 | BO3: 1 | BP3: 1 | BQ3: 1 | BR3: 1 | BS3: 1 | BT3: 1 | BU3: 1 | BV3: 1 | BW3: 1 | BX3: 1 | BY3: 1 | BZ3: 1 | CA3: 1 | CB3: 1 | CC3: 1 | CD3: 1 | CE3: 1 | CF3: 1 | CG3: 1 | CH3: 1 | CI3: 1 | CJ3: 1 | CK3: 1 | CL3: 1 | CM3: 1 | CN3: 1 | CO3: 1 | CP3: 1
A4: 4 | B4: No | C4: NameEN | D4: NameKR | E4: MaCongViecAll | F4: GroupbyChucDanhAll | G4: SoLuongNVAll | H4: BasicSalaryAll | I4: PhuCapAll | J4: TienTangCaAll | K4: Luong1GioAll | L4: GioLamViecKhongCoNghiAll | M4: GioTangCa150All | N4: GioTangCaCN200All | O4: GioTangCaDem210All | P4: GioTangCaDemCN270All | Q4: GioTangCaLe300All | R4: GioTangCaDemLe390All | S4: TongTangCaAll | T4: TongTangCaVaHCDaChuyenAll | U4: GioLamDem130All | V4: TienCaDem130All | W4: TongLuongAll | X4: CongDoanCtyTraAll | Y4: BHCtyTraAll | Z4: TongChiPhiAll | AA4: BHNVDongAll | AB4: TTCNAll | AC4: CongDoanNVDongAll | AD4: TroCapConNhoAll | AE4: TroCapPhuNuAll | AF4: HoTroKhacAll | AG4: ThucNhanAll | AH4: LuongChoViecAll | AI4: MaCongViecD1 | AJ4: GroupbyChucDanhD1 | AK4: SoLuongNVD1 | AL4: BasicSalaryD1 | AM4: PhuCapD1 | AN4: TienTangCaD1 | AO4: Luong1GioD1 | AP4: GioLamViecKhongCoNghiD1 | AQ4: GioTangCa150D1 | AR4: GioTangCaCN200D1 | AS4: GioTangCaDem210D1 | AT4: GioTangCaDemCN270D1 | AU4: GioTangCaLe300D1 | AV4: GioTangCaDemLe390D1 | AW4: TongTangCaD1 | AX4: TongTangCaVaHCDaChuyenD1 | AY4: GioLamDem130D1 | AZ4: TienCaDem130D1 | BA4: TongLuongD1 | BB4: CongDoanCtyTraD1 | BC4: BHCtyTraD1 | BD4: TongChiPhiD1 | BE4: BHNVDongD1 | BF4: TTCND1 | BG4: CongDoanNVDongD1 | BH4: TroCapConNhoD1 | BI4: TroCapPhuNuD1 | BJ4: HoTroKhacD1 | BK4: ThucNhanD1 | BL4: LuongChoViecD1 | BM4: MaCongViecD2 | BN4: GroupbyChucDanhD2 | BO4: SoLuongNVD2 | BP4: BasicSalaryD2 | BQ4: PhuCapD2 | BR4: TienTangCaD2 | BS4: Luong1GioD2 | BT4: GioLamViecKhongCoNghiD2 | BU4: GioTangCa150D2 | BV4: GioTangCaCN200D2 | BW4: GioTangCaDem210D2 | BX4: GioTangCaDemCN270D2 | BY4: GioTangCaLe300D2 | BZ4: GioTangCaDemLe390D2 | CA4: TongTangCaD2 | CB4: TongTangCaVaHCDaChuyenD2 | CC4: GioLamDem130D2 | CD4: TienCaDem130D2 | CE4: TongLuongD2 | CF4: CongDoanCtyTraD2 | CG4: BHCtyTraD2 | CH4: TongChiPhiD2 | CI4: BHNVDongD2 | CJ4: TTCND2 | CK4: CongDoanNVDongD2 | CL4: TroCapConNhoD2 | CM4: TroCapPhuNuD2 | CN4: HoTroKhacD2 | CO4: ThucNhanD2 | CP4: LuongChoViecD2 | CQ4: MaCongViecAllVT | CR4: GroupbyViTriAllVT | CS4: SoLuongNVAllVT | CT4: BasicSalaryAllVT | CU4: PhuCapAllVT | CV4: TienTangCaAllVT | CW4: Luong1GioAllVT | CX4: GioLamViecKhongCoNghiAllVT | CY4: GioTangCa150AllVT | CZ4: GioTangCaCN200AllVT | DA4: GioTangCaDem210AllVT | DB4: GioTangCaDemCN270AllVT | DC4: GioTangCaLe300AllVT | DD4: GioTangCaDemLe390AllVT | DE4: TongTangCaAllVT | DF4: TongTangCaVaHCDaChuyenAllVT | DG4: GioLamDem130AllVT | DH4: TienCaDem130AllVT | DI4: TongLuongAllVT | DJ4: CongDoanCtyTraAllVT | DK4: BHCtyTraAllVT | DL4: TongChiPhiAllVT | DM4: BHNVDongAllVT | DN4: TTCNAllVT | DO4: CongDoanNVDongAllVT | DP4: TroCapConNhoAllVT | DQ4: TroCapPhuNuAllVT | DR4: HoTroKhacAllVT | DS4: ThucNhanAllVT | DT4: LuongChoViecAllVT | DU4: MaCongViecD1VT | DV4: GroupbyViTriD1VT | DW4: SoLuongNVD1VT | DX4: BasicSalaryD1VT | DY4: PhuCapD1VT | DZ4: TienTangCaD1VT | EA4: Luong1GioD1VT | EB4: GioLamViecKhongCoNghiD1VT | EC4: GioTangCa150D1VT | ED4: GioTangCaCN200D1VT | EE4: GioTangCaDem210D1VT | EF4: GioTangCaDemCN270D1VT | EG4: GioTangCaLe300D1VT | EH4: GioTangCaDemLe390D1VT | EI4: TongTangCaD1VT | EJ4: TongTangCaVaHCDaChuyenD1VT | EK4: GioLamDem130D1VT | EL4: TienCaDem130D1VT | EM4: TongLuongD1VT | EN4: CongDoanCtyTraD1VT | EO4: BHCtyTraD1VT | EP4: TongChiPhiD1VT | EQ4: BHNVDongD1VT | ER4: TTCND1VT | ES4: CongDoanNVDongD1VT | ET4: TroCapConNhoD1VT | EU4: TroCapPhuNuD1VT | EV4: HoTroKhacD1VT | EW4: ThucNhanD1VT | EX4: LuongChoViecD1VT | EY4: MaCongViecD2VT | EZ4: GroupbyViTriD2VT | FA4: SoLuongNVD2VT | FB4: BasicSalaryD2VT | FC4: PhuCapD2VT | FD4: TienTangCaD2VT | FE4: Luong1GioD2VT | FF4: GioLamViecKhongCoNghiD2VT | FG4: GioTangCa150D2VT | FH4: GioTangCaCN200D2VT | FI4: GioTangCaDem210D2VT | FJ4: GioTangCaDemCN270D2VT | FK4: GioTangCaLe300D2VT | FL4: GioTangCaDemLe390D2VT | FM4: TongTangCaD2VT | FN4: TongTangCaVaHCDaChuyenD2VT | FO4: GioLamDem130D2VT | FP4: TienCaDem130D2VT | FQ4: TongLuongD2VT | FR4: CongDoanCtyTraD2VT | FS4: BHCtyTraD2VT | FT4: TongChiPhiD2VT | FU4: BHNVDongD2VT | FV4: TTCND2VT | FW4: CongDoanNVDongD2VT | FX4: TroCapConNhoD2VT | FY4: TroCapPhuNuD2VT | FZ4: HoTroKhacD2VT | GA4: ThucNhanD2VT | GB4: LuongChoViecD2VT | GC4: ActualWorkingDay | GD4: PublicHoliday | GE4: WorkingSaturday | GF4: SaturdayOT
B6: 1

Sheet Sum
A1: =TEXT(Sheet1!A1*28,"MMM") & " " & Sheet1!A2 & " SALARY" -> Jan 2 SALARY
A2: TOTAL
A3: Classification | E3: Manpower | F3: Basic salary (A) | G3: Allowance (B) | H3: OT amount '© | I3: OVERTIME | S3: All 30% | U3: Total salary (A+B+C + D) | V3: Union paid by company | W3: Insurance paied by company | X3: Total amount | Y3: Insurance paied by employee (10.5%) (E) | Z3: PIT | AA3: Union fee paid by employee | AB3: Child allowance | AC3: Women allowance | AD3: Resignation support | AE3: Net income | AF3: Bonus
I4: Unit price/hour | J4: Working hour excluded Annual leave | K4: (150%) Số giờ tăng ca ngày thường / Normal working day OT No. | L4: (200%) Tăng ca ngày nghỉ | M4: 210% tăng ca đêm ngày thường | N4: 270% tăng ca đêm ngày nghỉ | O4: 300% tăng ca ngày lễ, tết | P4: 390% tăng ca đêm ngày lễ, tết | Q4: Total OT hour | R4: Total working & OT converted | S4: Hour | T4: Amount (D)
A5: Office | B5: Office 1 | C5: 1st floor | D5: Indirect | E5: =Sheet1!G6 -> 0 | F5: =Sheet1!H6 -> 0 | G5: =Sheet1!I6 -> 0 | H5: =Sheet1!J6 -> 0 | I5: =Sheet1!K6 -> 0 | J5: =Sheet1!L6 -> 0 | K5: =Sheet1!M6 -> 0 | L5: =Sheet1!N6 -> 0 | ... AF5: =Sheet1!AH6 -> 0
B6: Office 2 | C6: 2nd floor | D6: Admin | E6: =Sheet1!G7 -> 0 | F6: =Sheet1!H7 -> 0 | G6: =Sheet1!I7 -> 0 | H6: =Sheet1!J7 -> 0 | I6: =Sheet1!K7 -> 0 | J6: =Sheet1!L7 -> 0 | K6: =Sheet1!M7 -> 0 | L6: =Sheet1!N7 -> 0 | ... AF6: =Sheet1!AH7 -> 0
B7: Subtotal | E7: =SUBTOTAL(9,E5:E6) -> 0 | F7: =SUBTOTAL(9,F5:F6) -> 0 | G7: =SUBTOTAL(9,G5:G6) -> 0 | H7: =SUBTOTAL(9,H5:H6) -> 0 | I7: =U7/R7 -> #DIV/0! | J7: =SUBTOTAL(9,J5:J6) -> 0 | K7: =SUBTOTAL(9,K5:K6) -> 0 | L7: =SUBTOTAL(9,L5:L6) -> 0 | M7: =SUBTOTAL(9,M5:M6) -> 0 | N7: =SUBTOTAL(9,N5:N6) -> 0 | O7: =SUBTOTAL(9,O5:O6) -> 0 | P7: =SUBTOTAL(9,P5:P6) -> 0 | Q7: =SUBTOTAL(9,Q5:Q6) -> 0 | ... AE7: =SUBTOTAL(9,AE5:AE6) -> 0
A8: Worker | B8: Warehouse | C8: Delivery | D8: Indirect | E8: =Sheet1!G8 -> 0 | F8: =Sheet1!H8 -> 0 | G8: =Sheet1!I8 -> 0 | H8: =Sheet1!J8 -> 0 | I8: =Sheet1!K8 -> 0 | J8: =Sheet1!L8 -> 0 | K8: =Sheet1!M8 -> 0 | L8: =Sheet1!N8 -> 0 | ... AF8: =Sheet1!AH8 -> 0
C9: MCT worker | D9: Indirect | E9: =Sheet1!G9 -> 0 | F9: =Sheet1!H9 -> 0 | G9: =Sheet1!I9 -> 0 | H9: =Sheet1!J9 -> 0 | I9: =Sheet1!K9 -> 0 | J9: =Sheet1!L9 -> 0 | K9: =Sheet1!M9 -> 0 | L9: =Sheet1!N9 -> 0 | ... AF9: =Sheet1!AH9 -> 0
C10: Subtotal | E10: =SUBTOTAL(9,E8:E9) -> 0 | F10: =SUBTOTAL(9,F8:F9) -> 0 | G10: =SUBTOTAL(9,G8:G9) -> 0 | H10: =SUBTOTAL(9,H8:H9) -> 0 | I10: =U10/R10 -> #DIV/0! | J10: =SUBTOTAL(9,J8:J9) -> 0 | K10: =SUBTOTAL(9,K8:K9) -> 0 | L10: =SUBTOTAL(9,L8:L9) -> 0 | M10: =SUBTOTAL(9,M8:M9) -> 0 | N10: =SUBTOTAL(9,N8:N9) -> 0 | O10: =SUBTOTAL(9,O8:O9) -> 0 | P10: =SUBTOTAL(9,P8:P9) -> 0 | Q10: =SUBTOTAL(9,Q8:Q9) -> 0 | ... AE10: =SUBTOTAL(9,AE8:AE9) -> 0
B11: Manufacture | C11: FM/DF Production | D11: Direct | E11: =Sheet1!G10 -> 0 | F11: =Sheet1!H10 -> 0 | G11: =Sheet1!I10 -> 0 | H11: =Sheet1!J10 -> 0 | I11: =Sheet1!K10 -> 0 | J11: =Sheet1!L10 -> 0 | K11: =Sheet1!M10 -> 0 | L11: =Sheet1!N10 -> 0 | ... AF11: =Sheet1!AH10 -> 0 | AG11: =+((L11+N11)/11.5)/E11 -> #DIV/0!
C12: MET/MMT | D12: Indirect | E12: =Sheet1!G11 -> 0 | F12: =Sheet1!H11 -> 0 | G12: =Sheet1!I11 -> 0 | H12: =Sheet1!J11 -> 0 | I12: =Sheet1!K11 -> 0 | J12: =Sheet1!L11 -> 0 | K12: =Sheet1!M11 -> 0 | L12: =Sheet1!N11 -> 0 | ... AF12: =Sheet1!AH11 -> 0 | AG12: =+((L12+N12)/11.5)/E12 -> #DIV/0!
C13: MAT worker | D13: Direct | E13: =Sheet1!G13 -> 0 | F13: =Sheet1!H13 -> 0 | G13: =Sheet1!I13 -> 0 | H13: =Sheet1!J13 -> 0 | I13: =Sheet1!K13 -> 0 | J13: =Sheet1!L13 -> 0 | K13: =Sheet1!M13 -> 0 | L13: =Sheet1!N13 -> 0 | ... AF13: =Sheet1!AH13 -> 0 | AG13: =+((L13+N13)/11.5)/E13 -> #DIV/0!
C14: MAT_Seasonal worker | D14: Direct | E14: 0 | F14: 0 | G14: 0 | H14: 0 | I14: 0 | J14: 0 | K14: 0 | L14: 0 | M14: 0 | N14: 0 | O14: 0 | P14: 0 | Q14: 0 | R14: 0 | S14: 0 | T14: 0 | U14: 0 | V14: 0 | W14: 0 | X14: 0 | Y14: 0 | Z14: 0 | AA14: 0 | AB14: 0 | AC14: 0 | AD14: 0 | AE14: 0 | AF14: 0 | AG14: =+((L14+N14)/11.5)/E14 -> #DIV/0!
C15: Subtotal | E15: =SUBTOTAL(9,E11:E14) -> 0 | F15: =SUBTOTAL(9,F11:F14) -> 0 | G15: =SUBTOTAL(9,G11:G14) -> 0 | H15: =SUBTOTAL(9,H11:H14) -> 0 | I15: =U15/R15 -> #DIV/0! | J15: =SUBTOTAL(9,J11:J14) -> 0 | K15: =SUBTOTAL(9,K11:K14) -> 0 | L15: =SUBTOTAL(9,L11:L14) -> 0 | M15: =SUBTOTAL(9,M11:M14) -> 0 | N15: =SUBTOTAL(9,N11:N14) -> 0 | O15: =SUBTOTAL(9,O11:O14) -> 0 | P15: =SUBTOTAL(9,P11:P14) -> 0 | Q15: =SUBTOTAL(9,Q11:Q14) -> 0 | ... AE15: =SUBTOTAL(9,AE11:AE14) -> 0 | AG15: =+((L15+N15)/11.5)/E15 -> #DIV/0!
B16: Quality | C16: FM/DF QC | D16: Direct | E16: =Sheet1!G14 -> 0 | F16: =Sheet1!H14 -> 0 | G16: =Sheet1!I14 -> 0 | H16: =Sheet1!J14 -> 0 | I16: =Sheet1!K14 -> 0 | J16: =Sheet1!L14 -> 0 | K16: =Sheet1!M14 -> 0 | L16: =Sheet1!N14 -> 0 | ... AF16: =Sheet1!AH14 -> 0 | AG16: =+((L16+N16)/11)/E16 -> #DIV/0!
C17: V/I | D17: Direct | E17: =Sheet1!G15 -> 0 | F17: =Sheet1!H15 -> 0 | G17: =Sheet1!I15 -> 0 | H17: =Sheet1!J15 -> 0 | I17: =Sheet1!K15 -> 0 | J17: =Sheet1!L15 -> 0 | K17: =Sheet1!M15 -> 0 | L17: =Sheet1!N15 -> 0 | ... AF17: =Sheet1!AH15 -> 0 | AG17: =+((L17+N17)/11)/E17 -> #DIV/0!
C18: Auto, Brushing, deburring | D18: Direct | E18: =Sheet1!G16 -> 0 | F18: =Sheet1!H16 -> 0 | G18: =Sheet1!I16 -> 0 | H18: =Sheet1!J16 -> 0 | I18: =Sheet1!K16 -> 0 | J18: =Sheet1!L16 -> 0 | K18: =Sheet1!M16 -> 0 | L18: =Sheet1!N16 -> 0 | ... AF18: =Sheet1!AH16 -> 0 | AG18: =+((L18+N18)/11)/E18 -> #DIV/0!
C19: Other indirect (PQC) | D19: Indirect | E19: =Sheet1!G19 -> 0 | F19: =Sheet1!H19 -> 0 | G19: =Sheet1!I19 -> 0 | H19: =Sheet1!J19 -> 0 | I19: =Sheet1!K19 -> 0 | J19: =Sheet1!L19 -> 0 | K19: =Sheet1!M19 -> 0 | L19: =Sheet1!N19 -> 0 | ... AF19: =Sheet1!AH19 -> 0 | AG19: =+((L19+N19)/11)/E19 -> #DIV/0!
C20: Packing | D20: Indirect | E20: =Sheet1!G20 -> 0 | F20: =Sheet1!H20 -> 0 | G20: =Sheet1!I20 -> 0 | H20: =Sheet1!J20 -> 0 | I20: =Sheet1!K20 -> 0 | J20: =Sheet1!L20 -> 0 | K20: =Sheet1!M20 -> 0 | L20: =Sheet1!N20 -> 0 | ... AF20: =Sheet1!AH20 -> 0 | AG20: =+((L20+N20)/11)/E20 -> #DIV/0!
C21: Seasonal worker | D21: Direct | E21: 0 | F21: 0 | G21: 0 | H21: 0 | I21: 0 | J21: 0 | K21: 0 | L21: 0 | M21: 0 | N21: 0 | O21: 0 | P21: 0 | Q21: 0 | R21: 0 | S21: 0 | T21: 0 | U21: 0 | V21: 0 | W21: 0 | X21: 0 | Y21: 0 | Z21: 0 | AA21: 0 | AB21: 0 | AC21: 0 | AD21: 0 | AE21: 0 | AF21: 0 | AG21: =+((L21+N21)/11)/E21 -> #DIV/0!
C22: Subtotal | E22: =SUBTOTAL(9,E16:E21) -> 0 | F22: =SUBTOTAL(9,F16:F21) -> 0 | G22: =SUBTOTAL(9,G16:G21) -> 0 | H22: =SUBTOTAL(9,H16:H21) -> 0 | I22: =U22/R22 -> #DIV/0! | J22: =SUBTOTAL(9,J16:J21) -> 0 | K22: =SUBTOTAL(9,K16:K21) -> 0 | L22: =SUBTOTAL(9,L16:L21) -> 0 | M22: =SUBTOTAL(9,M16:M21) -> 0 | N22: =SUBTOTAL(9,N16:N21) -> 0 | O22: =SUBTOTAL(9,O16:O21) -> 0 | P22: =SUBTOTAL(9,P16:P21) -> 0 | Q22: =SUBTOTAL(9,Q16:Q21) -> 0 | ... AE22: =SUBTOTAL(9,AE16:AE21) -> 0 | AG22: =+((L22+N22)/11)/E22 -> #DIV/0!
A23: Other | B23: Service | C23: Service | D23: Indirect | E23: =Sheet1!G21 -> 0 | F23: =Sheet1!H21 -> 0 | G23: =Sheet1!I21 -> 0 | H23: =Sheet1!J21 -> 0 | I23: =Sheet1!K21 -> 0 | J23: =Sheet1!L21 -> 0 | K23: =Sheet1!M21 -> 0 | L23: =Sheet1!N21 -> 0 | ... AF23: =Sheet1!AH21 -> 0
B24: Cleaner | C24: Cleaner | D24: Indirect | E24: =Sheet1!G22 -> 0 | F24: =Sheet1!H22 -> 0 | G24: =Sheet1!I22 -> 0 | H24: =Sheet1!J22 -> 0 | I24: =Sheet1!K22 -> 0 | J24: =Sheet1!L22 -> 0 | K24: =Sheet1!M22 -> 0 | L24: =Sheet1!N22 -> 0 | ... AF24: =Sheet1!AH22 -> 0
B25: Subtotal | E25: =SUBTOTAL(9,E23:E24) -> 0 | F25: =SUBTOTAL(9,F23:F24) -> 0 | G25: =SUBTOTAL(9,G23:G24) -> 0 | H25: =SUBTOTAL(9,H23:H24) -> 0 | I25: =U25/R25 -> #DIV/0! | J25: =SUBTOTAL(9,J23:J24) -> 0 | K25: =SUBTOTAL(9,K23:K24) -> 0 | L25: =SUBTOTAL(9,L23:L24) -> 0 | M25: =SUBTOTAL(9,M23:M24) -> 0 | N25: =SUBTOTAL(9,N23:N24) -> 0 | O25: =SUBTOTAL(9,O23:O24) -> 0 | P25: =SUBTOTAL(9,P23:P24) -> 0 | Q25: =SUBTOTAL(9,Q23:Q24) -> 0 | ... AE25: =SUBTOTAL(9,AE23:AE24) -> 0
A26: Sub-Total | E26: =SUBTOTAL(9,E5:E25) -> 0 | F26: =SUBTOTAL(9,F5:F25) -> 0 | G26: =SUBTOTAL(9,G5:G25) -> 0 | H26: =SUBTOTAL(9,H5:H25) -> 0 | I26: =U26/R26 -> #DIV/0! | J26: =SUBTOTAL(9,J5:J25) -> 0 | K26: =SUBTOTAL(9,K5:K25) -> 0 | L26: =SUBTOTAL(9,L5:L25) -> 0 | M26: =SUBTOTAL(9,M5:M25) -> 0 | N26: =SUBTOTAL(9,N5:N25) -> 0 | O26: =SUBTOTAL(9,O5:O25) -> 0 | P26: =SUBTOTAL(9,P5:P25) -> 0 | Q26: =SUBTOTAL(9,Q5:Q25) -> 0 | ... W26: =SUBTOTAL(9,W5:W25) -> 0 | X26: =U26+V26+W26 -> 0 | Y26: =SUBTOTAL(9,Y5:Y25) -> 0 | Z26: =SUBTOTAL(9,Z5:Z25) -> 0 | AA26: =SUBTOTAL(9,AA5:AA25) -> 0 | AB26: =SUBTOTAL(9,AB5:AB25) -> 0 | AC26: =SUBTOTAL(9,AC5:AC25) -> 0 | AD26: =SUBTOTAL(9,AD5:AD25) -> 0 | AE26: =SUBTOTAL(9,AE5:AE25) -> 0 | AG26: =+(AG22+AG15)/2 -> #DIV/0!
A28: Classification | E28: M/P | F28: Basic salary (A) | G28: Allowance (B) | H28: OT amount '© | I28: OVERTIME | S28: All 30% | U28: Total salary (A+B+C + D) | V28: Union paid by company | W28: Insurance paied by company | X28: Total amount | Y28: Insurance paied by employee (10.5%) (E) | Z28: PIT | AA28: Union fee paid by employee | AB28: CV allowance | AC28: Pay tax | AD28: Resignation support | AE28: Net income | AF28: Net income
I29: Unit price/hour | J29: Working day | K29: (150%) Số giờ tăng ca ngày thường / Normal working day OT No. | L29: (200%) Tăng ca ngày nghỉ | M29: 210% tăng ca đêm ngày thường | N29: 270% tăng ca đêm ngày nghỉ | O29: 300% tăng ca ngày lễ, tết | P29: 390% tăng ca đêm ngày lễ, tết | Q29: Total OT hour | R29: Total working and OT hour converted | S29: Hour | T29: Amount (D)
A30: =+D30 -> Direct | D30: Direct | E30: =Sheet1!CS6 -> 0 | F30: =Sheet1!CT6 -> 0 | G30: =Sheet1!CU6 -> 0 | H30: =Sheet1!CV6 -> 0 | I30: =Sheet1!CW6 -> 0 | J30: =Sheet1!CX6 -> 0 | K30: =Sheet1!CY6 -> 0 | L30: =Sheet1!CZ6 -> 0 | ... AF30: =Sheet1!DT6 -> 0
A31: =+D31 -> Indirect | D31: Indirect | E31: =Sheet1!CS7 -> 0 | F31: =Sheet1!CT7 -> 0 | G31: =Sheet1!CU7 -> 0 | H31: =Sheet1!CV7 -> 0 | I31: =Sheet1!CW7 -> 0 | J31: =Sheet1!CX7 -> 0 | K31: =Sheet1!CY7 -> 0 | L31: =Sheet1!CZ7 -> 0 | ... AF31: =Sheet1!DT7 -> 0
A32: =+D32 -> Admin | D32: Admin | E32: =Sheet1!CS8 -> 0 | F32: =Sheet1!CT8 -> 0 | G32: =Sheet1!CU8 -> 0 | H32: =Sheet1!CV8 -> 0 | I32: =Sheet1!CW8 -> 0 | J32: =Sheet1!CX8 -> 0 | K32: =Sheet1!CY8 -> 0 | L32: =Sheet1!CZ8 -> 0 | ... AF32: =Sheet1!DT8 -> 0
A33: Seasonal worker | D33: =+A33 -> Seasonal worker | E33: =Sheet1!CS9 -> 0 | F33: =Sheet1!CT9 -> 0 | G33: =Sheet1!CU9 -> 0 | H33: =Sheet1!CV9 -> 0 | I33: =Sheet1!CW9 -> 0 | J33: =Sheet1!CX9 -> 0 | K33: =Sheet1!CY9 -> 0 | L33: =Sheet1!CZ9 -> 0 | ... AF33: =Sheet1!DT9 -> 0
A34: Total | E34: =SUBTOTAL(9,E30:E33) -> 0 | F34: =SUBTOTAL(9,F30:F33) -> 0 | G34: =SUBTOTAL(9,G30:G33) -> 0 | H34: =SUBTOTAL(9,H30:H33) -> 0 | I34: =U34/R34 -> #DIV/0! | J34: =SUBTOTAL(9,J30:J33) -> 0 | K34: =SUBTOTAL(9,K30:K33) -> 0 | L34: =SUBTOTAL(9,L30:L33) -> 0 | M34: =SUBTOTAL(9,M30:M33) -> 0 | N34: =SUBTOTAL(9,N30:N33) -> 0 | O34: =SUBTOTAL(9,O30:O33) -> 0 | P34: =SUBTOTAL(9,P30:P33) -> 0 | Q34: =SUBTOTAL(9,Q30:Q33) -> 0 | ... W34: =SUBTOTAL(9,W30:W33) -> 0 | X34: =U34+V34+W34 -> 0 | Y34: =SUBTOTAL(9,Y30:Y33) -> 0 | Z34: =SUBTOTAL(9,Z30:Z33) -> 0 | AA34: =SUBTOTAL(9,AA30:AA33) -> 0 | AB34: =SUBTOTAL(9,AB30:AB33) -> 0 | AC34: =SUBTOTAL(9,AC30:AC33) -> 0 | AD34: =SUBTOTAL(9,AD30:AD33) -> 0 | AE34: =SUBTOTAL(9,AE30:AE33) -> 0 | AF34: =SUBTOTAL(9,AF30:AF33) -> 0
E35: =+E34-E26 -> 0 | F35: =+F34-F26 -> 0 | G35: =+G34-G26 -> 0 | H35: =+H34-H26 -> 0 | I35: =+I34-I26 -> #DIV/0! | J35: =+J34-J26 -> 0 | K35: =+K34-K26 -> 0 | L35: =+L34-L26 -> 0 | ... AF35: =+AF34-AF26 -> 0
A36: Month | B36: Working day | H36: OT day | J36: Total actual working day | M36: =+T26+H26 -> 0 | O36: Class | P36: Working hour | Q36: OT | R36: Total OT+ working hour | S36: 0.3 | T36: TOTAL MANHOUR | U36: Attendance rate Included AL
B37: Actual working day | C37: Public holiday | D37: Summer holiday | E37: Working Saturday | F37: Calendar | G37: Calculate salary working day | H37: Saturday | I37: Sunday | O37: Pro | P37: =+J15 -> 0 | Q37: =R37-P37 -> 0 | R37: =+R15 -> 0 | S37: =+S15 -> 0 | T37: =+R37+S37 -> 0 | U37: =+(U34-T34-H34-AB34-AC34-AD34)/(G34+F34) -> #DIV/0! | AE37: =+AE26-AE65-AE99 -> 0 | AF37: =+AF26-AF65-AF99 -> 0
A38: =TEXT(Sheet1!A1*28,"MMM") -> Jan | B38: =Sheet1!GC6 -> 0 | C38: =Sheet1!GD6 -> 0 | D38: 0 | E38: =Sheet1!GE6 -> 0 | F38: =B38+E38 -> 0 | G38: =D38+F38+C38 -> 0 | H38: =Sheet1!GF6 -> 0 | I38: =AG26-H38 -> #DIV/0! | J38: =F38+H38+I38 -> #DIV/0! | O38: QCT | P38: =+J22 -> 0 | Q38: =R38-P38 -> 0 | R38: =+R22 -> 0 | S38: =+S22 -> 0 | T38: =+R38+S38 -> 0
A41: D1
A42: Classification | E42: Manpower | F42: Basic salary (A) | G42: Allowance (B) | H42: OT amount '© | I42: OVERTIME | S42: All 30% | U42: Total salary (A+B+C + D) | V42: Union paid by company | W42: Insurance paied by company | X42: Total amount | Y42: Insurance paied by employee (10.5%) (E) | Z42: PIT | AA42: Union fee paid by employee | AB42: CV allowance | AC42: Pay tax | AD42: Resignation support | AE42: Net income | AF42: Bonus
I43: Unit price/hour | J43: Working hour excluded Annual leave | K43: (150%) Số giờ tăng ca ngày thường / Normal working day OT No. | L43: (200%) Tăng ca ngày nghỉ | M43: 210% tăng ca đêm ngày thường | N43: 270% tăng ca đêm ngày nghỉ | O43: 300% tăng ca ngày lễ, tết | P43: 390% tăng ca đêm ngày lễ, tết | Q43: Total OT hour | R43: Total working & OT converted | S43: Hour | T43: Amount (D)
A44: Office | B44: Office 1 | C44: 1st floor | D44: Indirect | E44: =Sheet1!AK6 -> 0 | F44: =Sheet1!AL6 -> 0 | G44: =Sheet1!AM6 -> 0 | H44: =Sheet1!AN6 -> 0 | I44: =Sheet1!AO6 -> 0 | J44: =Sheet1!AP6 -> 0 | K44: =Sheet1!AQ6 -> 0 | L44: =Sheet1!AR6 -> 0 | ... AF44: =Sheet1!BL6 -> 0
B45: Office 2 | C45: 2nd floor | D45: Admin | E45: =Sheet1!AK7 -> 0 | F45: =Sheet1!AL7 -> 0 | G45: =Sheet1!AM7 -> 0 | H45: =Sheet1!AN7 -> 0 | I45: =Sheet1!AO7 -> 0 | J45: =Sheet1!AP7 -> 0 | K45: =Sheet1!AQ7 -> 0 | L45: =Sheet1!AR7 -> 0 | ... AF45: =Sheet1!BL7 -> 0
B46: Subtotal | E46: =SUBTOTAL(9,E44:E45) -> 0 | F46: =SUBTOTAL(9,F44:F45) -> 0 | G46: =SUBTOTAL(9,G44:G45) -> 0 | H46: =SUBTOTAL(9,H44:H45) -> 0 | I46: =U46/R46 -> #DIV/0! | J46: =SUBTOTAL(9,J44:J45) -> 0 | K46: =SUBTOTAL(9,K44:K45) -> 0 | L46: =SUBTOTAL(9,L44:L45) -> 0 | M46: =SUBTOTAL(9,M44:M45) -> 0 | N46: =SUBTOTAL(9,N44:N45) -> 0 | O46: =SUBTOTAL(9,O44:O45) -> 0 | P46: =SUBTOTAL(9,P44:P45) -> 0 | Q46: =SUBTOTAL(9,Q44:Q45) -> 0 | ... AF46: =SUBTOTAL(9,AF44:AF45) -> 0
A47: Worker | B47: Warehouse | C47: Delivery | D47: Indirect | E47: =Sheet1!AK8 -> 0 | F47: =Sheet1!AL8 -> 0 | G47: =Sheet1!AM8 -> 0 | H47: =Sheet1!AN8 -> 0 | I47: =Sheet1!AO8 -> 0 | J47: =Sheet1!AP8 -> 0 | K47: =Sheet1!AQ8 -> 0 | L47: =Sheet1!AR8 -> 0 | ... AF47: =Sheet1!BL8 -> 0
C48: MCT worker | D48: Indirect | E48: =Sheet1!AK9 -> 0 | F48: =Sheet1!AL9 -> 0 | G48: =Sheet1!AM9 -> 0 | H48: =Sheet1!AN9 -> 0 | I48: =Sheet1!AO9 -> 0 | J48: =Sheet1!AP9 -> 0 | K48: =Sheet1!AQ9 -> 0 | L48: =Sheet1!AR9 -> 0 | ... AF48: =Sheet1!BL9 -> 0
C49: Subtotal | E49: =SUBTOTAL(9,E47:E48) -> 0 | F49: =SUBTOTAL(9,F47:F48) -> 0 | G49: =SUBTOTAL(9,G47:G48) -> 0 | H49: =SUBTOTAL(9,H47:H48) -> 0 | I49: =U49/R49 -> #DIV/0! | J49: =SUBTOTAL(9,J47:J48) -> 0 | K49: =SUBTOTAL(9,K47:K48) -> 0 | L49: =SUBTOTAL(9,L47:L48) -> 0 | M49: =SUBTOTAL(9,M47:M48) -> 0 | N49: =SUBTOTAL(9,N47:N48) -> 0 | O49: =SUBTOTAL(9,O47:O48) -> 0 | P49: =SUBTOTAL(9,P47:P48) -> 0 | Q49: =SUBTOTAL(9,Q47:Q48) -> 0 | ... AF49: =SUBTOTAL(9,AF47:AF48) -> 0
B50: Manufacture | C50: FM/DF Production | D50: Direct | E50: =Sheet1!AK10 -> 0 | F50: =Sheet1!AL10 -> 0 | G50: =Sheet1!AM10 -> 0 | H50: =Sheet1!AN10 -> 0 | I50: =Sheet1!AO10 -> 0 | J50: =Sheet1!AP10 -> 0 | K50: =Sheet1!AQ10 -> 0 | L50: =Sheet1!AR10 -> 0 | ... AF50: =Sheet1!BL10 -> 0
C51: MET/MMT | D51: Indirect | E51: =Sheet1!AK11 -> 0 | F51: =Sheet1!AL11 -> 0 | G51: =Sheet1!AM11 -> 0 | H51: =Sheet1!AN11 -> 0 | I51: =Sheet1!AO11 -> 0 | J51: =Sheet1!AP11 -> 0 | K51: =Sheet1!AQ11 -> 0 | L51: =Sheet1!AR11 -> 0 | ... AF51: =Sheet1!BL11 -> 0
C52: MAT worker | D52: Direct | E52: =Sheet1!AK13 -> 0 | F52: =Sheet1!AL13 -> 0 | G52: =Sheet1!AM13 -> 0 | H52: =Sheet1!AN13 -> 0 | I52: =Sheet1!AO13 -> 0 | J52: =Sheet1!AP13 -> 0 | K52: =Sheet1!AQ13 -> 0 | L52: =Sheet1!AR13 -> 0 | ... AF52: =Sheet1!BL13 -> 0
C53: MAT_Seasonal worker | D53: Direct | E53: 0 | F53: 0 | G53: 0 | H53: 0 | I53: 0 | J53: 0 | K53: 0 | L53: 0 | M53: 0 | N53: 0 | O53: 0 | P53: 0 | Q53: 0 | R53: 0 | S53: 0 | T53: 0 | U53: 0 | V53: 0 | W53: 0 | X53: 0 | Y53: 0 | Z53: 0 | AA53: 0 | AB53: 0 | AC53: 0 | AD53: 0 | AE53: 0 | AF53: 0
C54: Subtotal | E54: =SUBTOTAL(9,E50:E53) -> 0 | F54: =SUBTOTAL(9,F50:F53) -> 0 | G54: =SUBTOTAL(9,G50:G53) -> 0 | H54: =SUBTOTAL(9,H50:H53) -> 0 | I54: =U54/R54 -> #DIV/0! | J54: =SUBTOTAL(9,J50:J53) -> 0 | K54: =SUBTOTAL(9,K50:K53) -> 0 | L54: =SUBTOTAL(9,L50:L53) -> 0 | M54: =SUBTOTAL(9,M50:M53) -> 0 | N54: =SUBTOTAL(9,N50:N53) -> 0 | O54: =SUBTOTAL(9,O50:O53) -> 0 | P54: =SUBTOTAL(9,P50:P53) -> 0 | Q54: =SUBTOTAL(9,Q50:Q53) -> 0 | ... AF54: =SUBTOTAL(9,AF50:AF53) -> 0
B55: Quality | C55: FM/DF QC | D55: Direct | E55: =Sheet1!AK14 -> 0 | F55: =Sheet1!AL14 -> 0 | G55: =Sheet1!AM14 -> 0 | H55: =Sheet1!AN14 -> 0 | I55: =Sheet1!AO14 -> 0 | J55: =Sheet1!AP14 -> 0 | K55: =Sheet1!AQ14 -> 0 | L55: =Sheet1!AR14 -> 0 | ... AF55: =Sheet1!BL14 -> 0
C56: V/I | D56: Direct | E56: =Sheet1!AK15 -> 0 | F56: =Sheet1!AL15 -> 0 | G56: =Sheet1!AM15 -> 0 | H56: =Sheet1!AN15 -> 0 | I56: =Sheet1!AO15 -> 0 | J56: =Sheet1!AP15 -> 0 | K56: =Sheet1!AQ15 -> 0 | L56: =Sheet1!AR15 -> 0 | ... AF56: =Sheet1!BL15 -> 0
C57: Auto, Brushing, deburring | D57: Direct | E57: =Sheet1!AK16 -> 0 | F57: =Sheet1!AL16 -> 0 | G57: =Sheet1!AM16 -> 0 | H57: =Sheet1!AN16 -> 0 | I57: =Sheet1!AO16 -> 0 | J57: =Sheet1!AP16 -> 0 | K57: =Sheet1!AQ16 -> 0 | L57: =Sheet1!AR16 -> 0 | ... AF57: =Sheet1!BL16 -> 0
C58: Other indirect (PQC) | D58: Indirect | E58: =Sheet1!AK19 -> 0 | F58: =Sheet1!AL19 -> 0 | G58: =Sheet1!AM19 -> 0 | H58: =Sheet1!AN19 -> 0 | I58: =Sheet1!AO19 -> 0 | J58: =Sheet1!AP19 -> 0 | K58: =Sheet1!AQ19 -> 0 | L58: =Sheet1!AR19 -> 0 | ... AF58: =Sheet1!BL19 -> 0
C59: Packing | D59: Indirect | E59: =Sheet1!AK20 -> 0 | F59: =Sheet1!AL20 -> 0 | G59: =Sheet1!AM20 -> 0 | H59: =Sheet1!AN20 -> 0 | I59: =Sheet1!AO20 -> 0 | J59: =Sheet1!AP20 -> 0 | K59: =Sheet1!AQ20 -> 0 | L59: =Sheet1!AR20 -> 0 | ... AF59: =Sheet1!BL20 -> 0
C60: Seasonal worker | D60: Direct | E60: 0 | F60: 0 | G60: 0 | H60: 0 | I60: 0 | J60: 0 | K60: 0 | L60: 0 | M60: 0 | N60: 0 | O60: 0 | P60: 0 | Q60: 0 | R60: 0 | S60: 0 | T60: 0 | U60: 0 | V60: 0 | W60: 0 | X60: 0 | Y60: 0 | Z60: 0 | AA60: 0 | AB60: 0 | AC60: 0 | AD60: 0 | AE60: 0 | AF60: 0
C61: Subtotal | E61: =SUBTOTAL(9,E55:E60) -> 0 | F61: =SUBTOTAL(9,F55:F60) -> 0 | G61: =SUBTOTAL(9,G55:G60) -> 0 | H61: =SUBTOTAL(9,H55:H60) -> 0 | I61: =U61/R61 -> #DIV/0! | J61: =SUBTOTAL(9,J55:J60) -> 0 | K61: =SUBTOTAL(9,K55:K60) -> 0 | L61: =SUBTOTAL(9,L55:L60) -> 0 | M61: =SUBTOTAL(9,M55:M60) -> 0 | N61: =SUBTOTAL(9,N55:N60) -> 0 | O61: =SUBTOTAL(9,O55:O60) -> 0 | P61: =SUBTOTAL(9,P55:P60) -> 0 | Q61: =SUBTOTAL(9,Q55:Q60) -> 0 | ... AF61: =SUBTOTAL(9,AF55:AF60) -> 0
A62: Other | B62: Service | C62: Service | D62: Indirect | E62: =Sheet1!AK21 -> 0 | F62: =Sheet1!AL21 -> 0 | G62: =Sheet1!AM21 -> 0 | H62: =Sheet1!AN21 -> 0 | I62: =Sheet1!AO21 -> 0 | J62: =Sheet1!AP21 -> 0 | K62: =Sheet1!AQ21 -> 0 | L62: =Sheet1!AR21 -> 0 | ... AF62: =Sheet1!BL21 -> 0
B63: Cleaner | C63: Cleaner | D63: Indirect | E63: =Sheet1!AK22 -> 0 | F63: =Sheet1!AL22 -> 0 | G63: =Sheet1!AM22 -> 0 | H63: =Sheet1!AN22 -> 0 | I63: =Sheet1!AO22 -> 0 | J63: =Sheet1!AP22 -> 0 | K63: =Sheet1!AQ22 -> 0 | L63: =Sheet1!AR22 -> 0 | ... AF63: =Sheet1!BL22 -> 0
B64: Subtotal | E64: =SUBTOTAL(9,E62:E63) -> 0 | F64: =SUBTOTAL(9,F62:F63) -> 0 | G64: =SUBTOTAL(9,G62:G63) -> 0 | H64: =SUBTOTAL(9,H62:H63) -> 0 | I64: =U64/R64 -> #DIV/0! | J64: =SUBTOTAL(9,J62:J63) -> 0 | K64: =SUBTOTAL(9,K62:K63) -> 0 | L64: =SUBTOTAL(9,L62:L63) -> 0 | M64: =SUBTOTAL(9,M62:M63) -> 0 | N64: =SUBTOTAL(9,N62:N63) -> 0 | O64: =SUBTOTAL(9,O62:O63) -> 0 | P64: =SUBTOTAL(9,P62:P63) -> 0 | Q64: =SUBTOTAL(9,Q62:Q63) -> 0 | ... AF64: =SUBTOTAL(9,AF62:AF63) -> 0
A65: Sub-Total | E65: =SUBTOTAL(9,E44:E64) -> 0 | F65: =SUBTOTAL(9,F44:F64) -> 0 | G65: =SUBTOTAL(9,G44:G64) -> 0 | H65: =SUBTOTAL(9,H44:H64) -> 0 | I65: =U65/R65 -> #DIV/0! | J65: =SUBTOTAL(9,J44:J64) -> 0 | K65: =SUBTOTAL(9,K44:K64) -> 0 | L65: =SUBTOTAL(9,L44:L64) -> 0 | M65: =SUBTOTAL(9,M44:M64) -> 0 | N65: =SUBTOTAL(9,N44:N64) -> 0 | O65: =SUBTOTAL(9,O44:O64) -> 0 | P65: =SUBTOTAL(9,P44:P64) -> 0 | Q65: =SUBTOTAL(9,Q44:Q64) -> 0 | ... W65: =SUBTOTAL(9,W44:W64) -> 0 | X65: =U65+V65+W65 -> 0 | Y65: =SUBTOTAL(9,Y44:Y64) -> 0 | Z65: =SUBTOTAL(9,Z44:Z64) -> 0 | AA65: =SUBTOTAL(9,AA44:AA64) -> 0 | AB65: =SUBTOTAL(9,AB44:AB64) -> 0 | AC65: =SUBTOTAL(9,AC44:AC64) -> 0 | AD65: =SUBTOTAL(9,AD44:AD64) -> 0 | AE65: =SUBTOTAL(9,AE44:AE64) -> 0 | AF65: =SUBTOTAL(9,AF44:AF64) -> 0
A67: Classification | E67: M/P | F67: Basic salary (A) | G67: Allowance (B) | H67: OT amount '© | I67: OVERTIME | S67: All 30% | U67: Total salary (A+B+C + D) | V67: Union paid by company | W67: Insurance paied by company | X67: Total amount | Y67: Insurance paied by employee (10.5%) (E) | Z67: PIT | AA67: Union fee paid by employee | AB67: CV allowance | AC67: Pay tax | AD67: Resignation support | AE67: Net income | AF67: Net income
I68: Unit price/hour | J68: Working hour excluded Annual leave | K68: (150%) Số giờ tăng ca ngày thường / Normal working day OT No. | L68: (200%) Tăng ca ngày nghỉ | M68: 210% tăng ca đêm ngày thường | N68: 270% tăng ca đêm ngày nghỉ | O68: 300% tăng ca ngày lễ, tết | P68: 390% tăng ca đêm ngày lễ, tết | Q68: Total OT hour | R68: Total working and OT hour converted | S68: Hour | T68: Amount (D)
A69: =+D69 -> Direct | D69: Direct | E69: =Sheet1!DW6 -> 0 | F69: =Sheet1!DX6 -> 0 | G69: =Sheet1!DY6 -> 0 | H69: =Sheet1!DZ6 -> 0 | I69: =Sheet1!EA6 -> 0 | J69: =Sheet1!EB6 -> 0 | K69: =Sheet1!EC6 -> 0 | L69: =Sheet1!ED6 -> 0 | ... AF69: =Sheet1!EX6 -> 0
A70: =+D70 -> Indirect | D70: Indirect | E70: =Sheet1!DW7 -> 0 | F70: =Sheet1!DX7 -> 0 | G70: =Sheet1!DY7 -> 0 | H70: =Sheet1!DZ7 -> 0 | I70: =Sheet1!EA7 -> 0 | J70: =Sheet1!EB7 -> 0 | K70: =Sheet1!EC7 -> 0 | L70: =Sheet1!ED7 -> 0 | ... AF70: =Sheet1!EX7 -> 0
A71: =+D71 -> Admin | D71: Admin | E71: =Sheet1!DW8 -> 0 | F71: =Sheet1!DX8 -> 0 | G71: =Sheet1!DY8 -> 0 | H71: =Sheet1!DZ8 -> 0 | I71: =Sheet1!EA8 -> 0 | J71: =Sheet1!EB8 -> 0 | K71: =Sheet1!EC8 -> 0 | L71: =Sheet1!ED8 -> 0 | ... AF71: =Sheet1!EX8 -> 0
A72: Seasonal worker | D72: =+A72 -> Seasonal worker | E72: =Sheet1!DW9 -> 0 | F72: =Sheet1!DX9 -> 0 | G72: =Sheet1!DY9 -> 0 | H72: =Sheet1!DZ9 -> 0 | I72: =Sheet1!EA9 -> 0 | J72: =Sheet1!EB9 -> 0 | K72: =Sheet1!EC9 -> 0 | L72: =Sheet1!ED9 -> 0 | ... AF72: =Sheet1!EX9 -> 0
A73: Total | E73: =SUBTOTAL(9,E69:E72) -> 0 | F73: =SUBTOTAL(9,F69:F72) -> 0 | G73: =SUBTOTAL(9,G69:G72) -> 0 | H73: =SUBTOTAL(9,H69:H72) -> 0 | I73: =U73/R73 -> #DIV/0! | J73: =SUBTOTAL(9,J69:J72) -> 0 | K73: =SUBTOTAL(9,K69:K72) -> 0 | L73: =SUBTOTAL(9,L69:L72) -> 0 | M73: =SUBTOTAL(9,M69:M72) -> 0 | N73: =SUBTOTAL(9,N69:N72) -> 0 | O73: =SUBTOTAL(9,O69:O72) -> 0 | P73: =SUBTOTAL(9,P69:P72) -> 0 | Q73: =SUBTOTAL(9,Q69:Q72) -> 0 | ... W73: =SUBTOTAL(9,W69:W72) -> 0 | X73: =U73+V73+W73 -> 0 | Y73: =SUBTOTAL(9,Y69:Y72) -> 0 | Z73: =SUBTOTAL(9,Z69:Z72) -> 0 | AA73: =SUBTOTAL(9,AA69:AA72) -> 0 | AB73: =SUBTOTAL(9,AB69:AB72) -> 0 | AC73: =SUBTOTAL(9,AC69:AC72) -> 0 | AD73: =SUBTOTAL(9,AD69:AD72) -> 0 | AE73: =SUBTOTAL(9,AE69:AE72) -> 0 | AF73: =SUBTOTAL(9,AF69:AF72) -> 0
E74: =+E73-E65 -> 0 | F74: =+F73-F65 -> 0 | G74: =+G73-G65 -> 0 | H74: =+H73-H65 -> 0 | I74: =+I73-I65 -> #DIV/0! | J74: =+J73-J65 -> 0 | K74: =+K73-K65 -> 0 | L74: =+L73-L65 -> 0 | ... AF74: =+AF73-AF65 -> 0
A75: D2
A76: Classification | E76: Manpower | F76: Basic salary (A) | G76: Allowance (B) | H76: OT amount '© | I76: OVERTIME | S76: All 30% | U76: Total salary (A+B+C + D) | V76: Union paid by company | W76: Insurance paied by company | X76: Total amount | Y76: Insurance paied by employee (10.5%) (E) | Z76: PIT | AA76: Union fee paid by employee | AB76: CV allowance | AC76: Pay tax | AD76: Resignation support | AE76: Net income | AF76: Net income
I77: Unit price/hour | J77: Working hour excluded Annual leave | K77: (150%) Số giờ tăng ca ngày thường / Normal working day OT No. | L77: (200%) Tăng ca ngày nghỉ | M77: 210% tăng ca đêm ngày thường | N77: 270% tăng ca đêm ngày nghỉ | O77: 300% tăng ca ngày lễ, tết | P77: 390% tăng ca đêm ngày lễ, tết | Q77: Total OT hour | R77: Total working & OT converted | S77: Hour | T77: Amount (D)
A78: Office | B78: Office 1 | C78: 1st floor | D78: Indirect | E78: =Sheet1!BO6 -> 0 | F78: =Sheet1!BP6 -> 0 | G78: =Sheet1!BQ6 -> 0 | H78: =Sheet1!BR6 -> 0 | I78: =Sheet1!BS6 -> 0 | J78: =Sheet1!BT6 -> 0 | K78: =Sheet1!BU6 -> 0 | L78: =Sheet1!BV6 -> 0 | ... AE78: =Sheet1!CO6 -> 0
B79: Office 2 | C79: 2nd floor | D79: Admin | E79: =Sheet1!BO7 -> 0 | F79: =Sheet1!BP7 -> 0 | G79: =Sheet1!BQ7 -> 0 | H79: =Sheet1!BR7 -> 0 | I79: =Sheet1!BS7 -> 0 | J79: =Sheet1!BT7 -> 0 | K79: =Sheet1!BU7 -> 0 | L79: =Sheet1!BV7 -> 0 | ... AE79: =Sheet1!CO7 -> 0
B80: Subtotal | E80: =SUBTOTAL(9,E78:E79) -> 0 | F80: =SUBTOTAL(9,F78:F79) -> 0 | G80: =SUBTOTAL(9,G78:G79) -> 0 | H80: =SUBTOTAL(9,H78:H79) -> 0 | I80: =U80/R80 -> #DIV/0! | J80: =SUBTOTAL(9,J78:J79) -> 0 | K80: =SUBTOTAL(9,K78:K79) -> 0 | L80: =SUBTOTAL(9,L78:L79) -> 0 | M80: =SUBTOTAL(9,M78:M79) -> 0 | N80: =SUBTOTAL(9,N78:N79) -> 0 | O80: =SUBTOTAL(9,O78:O79) -> 0 | P80: =SUBTOTAL(9,P78:P79) -> 0 | Q80: =SUBTOTAL(9,Q78:Q79) -> 0 | ... AE80: =SUBTOTAL(9,AE78:AE79) -> 0
A81: Worker | B81: Warehouse | C81: Delivery | D81: Indirect | E81: =Sheet1!BO8 -> 0 | F81: =Sheet1!BP8 -> 0 | G81: =Sheet1!BQ8 -> 0 | H81: =Sheet1!BR8 -> 0 | I81: =Sheet1!BS8 -> 0 | J81: =Sheet1!BT8 -> 0 | K81: =Sheet1!BU8 -> 0 | L81: =Sheet1!BV8 -> 0 | ... AE81: =Sheet1!CO8 -> 0
C82: MCT worker | D82: Indirect | E82: =Sheet1!BO9 -> 0 | F82: =Sheet1!BP9 -> 0 | G82: =Sheet1!BQ9 -> 0 | H82: =Sheet1!BR9 -> 0 | I82: =Sheet1!BS9 -> 0 | J82: =Sheet1!BT9 -> 0 | K82: =Sheet1!BU9 -> 0 | L82: =Sheet1!BV9 -> 0 | ... AE82: =Sheet1!CO9 -> 0
C83: Subtotal | E83: =SUBTOTAL(9,E81:E82) -> 0 | F83: =SUBTOTAL(9,F81:F82) -> 0 | G83: =SUBTOTAL(9,G81:G82) -> 0 | H83: =SUBTOTAL(9,H81:H82) -> 0 | I83: =U83/R83 -> #DIV/0! | J83: =SUBTOTAL(9,J81:J82) -> 0 | K83: =SUBTOTAL(9,K81:K82) -> 0 | L83: =SUBTOTAL(9,L81:L82) -> 0 | M83: =SUBTOTAL(9,M81:M82) -> 0 | N83: =SUBTOTAL(9,N81:N82) -> 0 | O83: =SUBTOTAL(9,O81:O82) -> 0 | P83: =SUBTOTAL(9,P81:P82) -> 0 | Q83: =SUBTOTAL(9,Q81:Q82) -> 0 | ... AE83: =SUBTOTAL(9,AE81:AE82) -> 0
B84: Manufacture | C84: FM/DF Production | D84: Direct | E84: =Sheet1!BO10 -> 0 | F84: =Sheet1!BP10 -> 0 | G84: =Sheet1!BQ10 -> 0 | H84: =Sheet1!BR10 -> 0 | I84: =Sheet1!BS10 -> 0 | J84: =Sheet1!BT10 -> 0 | K84: =Sheet1!BU10 -> 0 | L84: =Sheet1!BV10 -> 0 | ... AE84: =Sheet1!CO10 -> 0
C85: MET/MMT | D85: Indirect | E85: =Sheet1!BO11 -> 0 | F85: =Sheet1!BP11 -> 0 | G85: =Sheet1!BQ11 -> 0 | H85: =Sheet1!BR11 -> 0 | I85: =Sheet1!BS11 -> 0 | J85: =Sheet1!BT11 -> 0 | K85: =Sheet1!BU11 -> 0 | L85: =Sheet1!BV11 -> 0 | ... AE85: =Sheet1!CO11 -> 0
C86: MAT worker | D86: Direct | E86: =Sheet1!BO13 -> 0 | F86: =Sheet1!BP13 -> 0 | G86: =Sheet1!BQ13 -> 0 | H86: =Sheet1!BR13 -> 0 | I86: =Sheet1!BS13 -> 0 | J86: =Sheet1!BT13 -> 0 | K86: =Sheet1!BU13 -> 0 | L86: =Sheet1!BV13 -> 0 | ... AE86: =Sheet1!CO13 -> 0
C87: MAT_Seasonal worker | D87: Direct | E87: 0 | F87: 0 | G87: 0 | H87: 0 | I87: 0 | J87: 0 | K87: 0 | L87: 0 | M87: 0 | N87: 0 | O87: 0 | P87: 0 | Q87: 0 | R87: 0 | S87: 0 | T87: 0 | U87: 0 | V87: 0 | W87: 0 | X87: 0 | Y87: 0 | Z87: 0 | AA87: 0 | AB87: 0 | AC87: 0 | AD87: 0 | AE87: 0
C88: Subtotal | E88: =SUBTOTAL(9,E84:E87) -> 0 | F88: =SUBTOTAL(9,F84:F87) -> 0 | G88: =SUBTOTAL(9,G84:G87) -> 0 | H88: =SUBTOTAL(9,H84:H87) -> 0 | I88: =U88/R88 -> #DIV/0! | J88: =SUBTOTAL(9,J84:J87) -> 0 | K88: =SUBTOTAL(9,K84:K87) -> 0 | L88: =SUBTOTAL(9,L84:L87) -> 0 | M88: =SUBTOTAL(9,M84:M87) -> 0 | N88: =SUBTOTAL(9,N84:N87) -> 0 | O88: =SUBTOTAL(9,O84:O87) -> 0 | P88: =SUBTOTAL(9,P84:P87) -> 0 | Q88: =SUBTOTAL(9,Q84:Q87) -> 0 | ... AE88: =SUBTOTAL(9,AE84:AE87) -> 0
B89: Quality | C89: FM/DF QC | D89: Direct | E89: =Sheet1!BO14 -> 0 | F89: =Sheet1!BP14 -> 0 | G89: =Sheet1!BQ14 -> 0 | H89: =Sheet1!BR14 -> 0 | I89: =Sheet1!BS14 -> 0 | J89: =Sheet1!BT14 -> 0 | K89: =Sheet1!BU14 -> 0 | L89: =Sheet1!BV14 -> 0 | ... AE89: =Sheet1!CO14 -> 0
C90: V/I | D90: Direct | E90: =Sheet1!BO15 -> 0 | F90: =Sheet1!BP15 -> 0 | G90: =Sheet1!BQ15 -> 0 | H90: =Sheet1!BR15 -> 0 | I90: =Sheet1!BS15 -> 0 | J90: =Sheet1!BT15 -> 0 | K90: =Sheet1!BU15 -> 0 | L90: =Sheet1!BV15 -> 0 | ... AE90: =Sheet1!CO15 -> 0
C91: Auto, Brushing, deburring | D91: Direct | E91: =Sheet1!BO16 -> 0 | F91: =Sheet1!BP16 -> 0 | G91: =Sheet1!BQ16 -> 0 | H91: =Sheet1!BR16 -> 0 | I91: =Sheet1!BS16 -> 0 | J91: =Sheet1!BT16 -> 0 | K91: =Sheet1!BU16 -> 0 | L91: =Sheet1!BV16 -> 0 | ... AE91: =Sheet1!CO16 -> 0
C92: Other indirect (PQC) | D92: Indirect | E92: =Sheet1!BO19 -> 0 | F92: =Sheet1!BP19 -> 0 | G92: =Sheet1!BQ19 -> 0 | H92: =Sheet1!BR19 -> 0 | I92: =Sheet1!BS19 -> 0 | J92: =Sheet1!BT19 -> 0 | K92: =Sheet1!BU19 -> 0 | L92: =Sheet1!BV19 -> 0 | ... AE92: =Sheet1!CO19 -> 0
C93: Packing | D93: Indirect | E93: =Sheet1!BO20 -> 0 | F93: =Sheet1!BP20 -> 0 | G93: =Sheet1!BQ20 -> 0 | H93: =Sheet1!BR20 -> 0 | I93: =Sheet1!BS20 -> 0 | J93: =Sheet1!BT20 -> 0 | K93: =Sheet1!BU20 -> 0 | L93: =Sheet1!BV20 -> 0 | ... AE93: =Sheet1!CO20 -> 0
C94: Seasonal worker | D94: Direct | E94: 0 | F94: 0 | G94: 0 | H94: 0 | I94: 0 | J94: 0 | K94: 0 | L94: 0 | M94: 0 | N94: 0 | O94: 0 | P94: 0 | Q94: 0 | R94: 0 | S94: 0 | T94: 0 | U94: 0 | V94: 0 | W94: 0 | X94: 0 | Y94: 0 | Z94: 0 | AA94: 0 | AB94: 0 | AC94: 0 | AD94: 0 | AE94: 0
C95: Subtotal | E95: =SUBTOTAL(9,E89:E94) -> 0 | F95: =SUBTOTAL(9,F89:F94) -> 0 | G95: =SUBTOTAL(9,G89:G94) -> 0 | H95: =SUBTOTAL(9,H89:H94) -> 0 | I95: =U95/R95 -> #DIV/0! | J95: =SUBTOTAL(9,J89:J94) -> 0 | K95: =SUBTOTAL(9,K89:K94) -> 0 | L95: =SUBTOTAL(9,L89:L94) -> 0 | M95: =SUBTOTAL(9,M89:M94) -> 0 | N95: =SUBTOTAL(9,N89:N94) -> 0 | O95: =SUBTOTAL(9,O89:O94) -> 0 | P95: =SUBTOTAL(9,P89:P94) -> 0 | Q95: =SUBTOTAL(9,Q89:Q94) -> 0 | ... AE95: =SUBTOTAL(9,AE89:AE94) -> 0
A96: Other | B96: Service | C96: Service | D96: Indirect | E96: =Sheet1!BO21 -> 0 | F96: =Sheet1!BP21 -> 0 | G96: =Sheet1!BQ21 -> 0 | H96: =Sheet1!BR21 -> 0 | I96: =Sheet1!BS21 -> 0 | J96: =Sheet1!BT21 -> 0 | K96: =Sheet1!BU21 -> 0 | L96: =Sheet1!BV21 -> 0 | ... AE96: =Sheet1!CO21 -> 0
B97: Cleaner | C97: Cleaner | D97: Indirect | E97: =Sheet1!BO22 -> 0 | F97: =Sheet1!BP22 -> 0 | G97: =Sheet1!BQ22 -> 0 | H97: =Sheet1!BR22 -> 0 | I97: =Sheet1!BS22 -> 0 | J97: =Sheet1!BT22 -> 0 | K97: =Sheet1!BU22 -> 0 | L97: =Sheet1!BV22 -> 0 | ... AE97: =Sheet1!CO22 -> 0
B98: Subtotal | E98: =SUBTOTAL(9,E96:E97) -> 0 | F98: =SUBTOTAL(9,F96:F97) -> 0 | G98: =SUBTOTAL(9,G96:G97) -> 0 | H98: =SUBTOTAL(9,H96:H97) -> 0 | I98: =U98/R98 -> #DIV/0! | J98: =SUBTOTAL(9,J96:J97) -> 0 | K98: =SUBTOTAL(9,K96:K97) -> 0 | L98: =SUBTOTAL(9,L96:L97) -> 0 | M98: =SUBTOTAL(9,M96:M97) -> 0 | N98: =SUBTOTAL(9,N96:N97) -> 0 | O98: =SUBTOTAL(9,O96:O97) -> 0 | P98: =SUBTOTAL(9,P96:P97) -> 0 | Q98: =SUBTOTAL(9,Q96:Q97) -> 0 | ... AE98: =SUBTOTAL(9,AE96:AE97) -> 0
A99: Sub-Total | E99: =SUBTOTAL(9,E78:E98) -> 0 | F99: =SUBTOTAL(9,F78:F98) -> 0 | G99: =SUBTOTAL(9,G78:G98) -> 0 | H99: =SUBTOTAL(9,H78:H98) -> 0 | I99: =U99/R99 -> #DIV/0! | J99: =SUBTOTAL(9,J78:J98) -> 0 | K99: =SUBTOTAL(9,K78:K98) -> 0 | L99: =SUBTOTAL(9,L78:L98) -> 0 | M99: =SUBTOTAL(9,M78:M98) -> 0 | N99: =SUBTOTAL(9,N78:N98) -> 0 | O99: =SUBTOTAL(9,O78:O98) -> 0 | P99: =SUBTOTAL(9,P78:P98) -> 0 | Q99: =SUBTOTAL(9,Q78:Q98) -> 0 | ... W99: =SUBTOTAL(9,W78:W98) -> 0 | X99: =U99+V99+W99 -> 0 | Y99: =SUBTOTAL(9,Y78:Y98) -> 0 | Z99: =SUBTOTAL(9,Z78:Z98) -> 0 | AA99: =SUBTOTAL(9,AA78:AA98) -> 0 | AB99: =SUBTOTAL(9,AB78:AB98) -> 0 | AC99: =SUBTOTAL(9,AC78:AC98) -> 0 | AD99: =SUBTOTAL(9,AD78:AD98) -> 0 | AE99: =SUBTOTAL(9,AE78:AE98) -> 0
A101: Classification | E101: M/P | F101: Basic salary (A) | G101: Allowance (B) | H101: OT amount '© | I101: OVERTIME | S101: All 30% | U101: Total salary (A+B+C + D) | V101: Union paid by company | W101: Insurance paied by company | X101: Total amount | Y101: Insurance paied by employee (10.5%) (E) | Z101: PIT | AA101: Union fee paid by employee | AB101: CV allowance | AC101: Pay tax | AD101: Resignation support | AE101: Net income | AF101: Net income
I102: Unit price/hour | J102: Working day | K102: (150%) Số giờ tăng ca ngày thường / Normal working day OT No. | L102: (200%) Tăng ca ngày nghỉ | M102: 210% tăng ca đêm ngày thường | N102: 270% tăng ca đêm ngày nghỉ | O102: 300% tăng ca ngày lễ, tết | P102: 390% tăng ca đêm ngày lễ, tết | Q102: Total OT hour | R102: Total working and OT hour converted | S102: Hour | T102: Amount (D)
A103: =+D103 -> Direct | D103: Direct | E103: =Sheet1!FA6 -> 0 | F103: =Sheet1!FB6 -> 0 | G103: =Sheet1!FC6 -> 0 | H103: =Sheet1!FD6 -> 0 | I103: =Sheet1!FE6 -> 0 | J103: =Sheet1!FF6 -> 0 | K103: =Sheet1!FG6 -> 0 | L103: =Sheet1!FH6 -> 0 | ... AF103: =Sheet1!GB6 -> 0
A104: =+D104 -> Indirect | D104: Indirect | E104: =Sheet1!FA7 -> 0 | F104: =Sheet1!FB7 -> 0 | G104: =Sheet1!FC7 -> 0 | H104: =Sheet1!FD7 -> 0 | I104: =Sheet1!FE7 -> 0 | J104: =Sheet1!FF7 -> 0 | K104: =Sheet1!FG7 -> 0 | L104: =Sheet1!FH7 -> 0 | ... AF104: =Sheet1!GB7 -> 0
A105: =+D105 -> Admin | D105: Admin | E105: =Sheet1!FA8 -> 0 | F105: =Sheet1!FB8 -> 0 | G105: =Sheet1!FC8 -> 0 | H105: =Sheet1!FD8 -> 0 | I105: =Sheet1!FE8 -> 0 | J105: =Sheet1!FF8 -> 0 | K105: =Sheet1!FG8 -> 0 | L105: =Sheet1!FH8 -> 0 | ... AF105: =Sheet1!GB8 -> 0
...

Sheet 보고서
A1: 2023 년 01월 Actual 대비 현지인 노무비 차이분석
A3: 23.02.07 | M3: 단위:명,일,시간,$
A4: Classtication | D4: OP | G4: Actual | J4: Diff (증감) | M4: Remark
D5: Total | E5: D1 | F5: D2 | G5: Total | H5: D1 | I5: D2 | J5: Total | K5: D1 | L5: D2
A6: 매출액 | C6: KVP | J6: =G6-D6 -> 0 | K6: =H6-E6 -> 0 | L6: =I6-F6 -> 0
C7: DY | J7: =G7-D7 -> 0 | K7: =H7-E7 -> 0 | L7: =I7-F7 -> 0
C8: 바이백 | J8: =G8-D8 -> 0 | K8: =H8-E8 -> 0 | L8: =I8-F8 -> 0
C9: 계 | J9: =J8+J7+J6 -> 0 | K9: =K8+K7+K6 -> 0 | L9: =I9-F9 -> 0
C10: 증가율 | J10: =J9/D9 -> #DIV/0! | K10: =K9/E9 -> #DIV/0! | L10: =L9/F9 -> #DIV/0!
A11: Working day (작업일수/월) | C11: 정취 | D11: 18 | E11: =+D11 -> 18 | F11: =+E11 -> 18 | G11: =Sum!F38 -> 0 | H11: =+G11 -> 0 | I11: =+H11 -> 0 | J11: =+G11-D11 -> -18 | K11: =+H11-E11 -> -18 | L11: =+I11-F11 -> -18
C12: 특근 | D12: =+'[1]Compare D1'!$I$30+'[1]Compare D1'!$J$30 -> 4.9484177 | E12: =+D12 -> 4.9484177 | F12: =+E12 -> 4.9484177 | G12: =Sum!H38+Sum!I38 -> #DIV/0! | H12: =+G12 -> #DIV/0! | I12: =+H12 -> #DIV/0! | J12: =+G12-D12 -> #DIV/0! | K12: =+H12-E12 -> #DIV/0! | L12: =+I12-F12 -> #DIV/0!
C13: 계 | D13: =+D12+D11 -> 22.948418 | E13: =+D13 -> 22.948418 | F13: =+E13 -> 22.948418 | G13: =+G12+G11 -> #DIV/0! | H13: =+G13 -> #DIV/0! | I13: =+H13 -> #DIV/0! | J13: =+G13-D13 -> #DIV/0! | K13: =+H13-E13 -> #DIV/0! | L13: =+I13-F13 -> #DIV/0!
A14: MP (소요인원/월) | B14: MCT | C14: 직접 | F14: =+D14-E14 -> 0 | I14: =+G14-H14 -> 0 | J14: =+G14-D14 -> 0 | K14: =+H14-E14 -> 0 | L14: =+I14-F14 -> 0
C15: 간접 | D15: =+'[2]OP 01.2023 Total'!E10 -> 7 | E15: =+[2]D1_B1!E10 -> 7 | F15: =+D15-E15 -> 0 | G15: =Sum!E10 -> 0 | H15: =Sum!E10 -> 0 | I15: =+G15-H15 -> 0 | J15: =+G15-D15 -> -7 | K15: =+H15-E15 -> -7 | L15: =+I15-F15 -> 0
C16: 계 | D16: =+D15 -> 7 | E16: =+E15 -> 7 | F16: =+D16-E16 -> 0 | G16: =+G15 -> 0 | H16: =+H15 -> 0 | I16: =+G16-H16 -> 0 | J16: =+G16-D16 -> -7 | K16: =+H16-E16 -> -7 | L16: =+I16-F16 -> 0
B17: MAT/MMT/MET | C17: 직접 | D17: =+'[2]OP 01.2023 Total'!E11+'[2]OP 01.2023 Total'!E13+'[2]OP 01.2023 Total'!E14 -> 148 | E17: =+[2]D1_B1!E11+[2]D1_B1!E13+[2]D1_B1!E14 -> 124 | F17: =+D17-E17 -> 24 | G17: =Sum!E11+Sum!E13+Sum!E14 -> 0 | H17: =Sum!E11+Sum!E13+Sum!E14 -> 0 | I17: =+G17-H17 -> 0 | J17: =+G17-D17 -> -148 | K17: =+H17-E17 -> -124 | L17: =+I17-F17 -> -24
C18: 간접 | D18: =+'[2]OP 01.2023 Total'!E12 -> 10 | E18: =+[2]D1_B1!E12 -> 10 | F18: =+D18-E18 -> 0 | G18: =Sum!E12 -> 0 | H18: =Sum!E12 -> 0 | I18: =+G18-H18 -> 0 | J18: =+G18-D18 -> -10 | K18: =+H18-E18 -> -10 | L18: =+I18-F18 -> 0
C19: 계 | D19: =+D17+D18 -> 158 | E19: =+E17+E18 -> 134 | F19: =+D19-E19 -> 24 | G19: =+G18+G17 -> 0 | H19: =+H18+H17 -> 0 | I19: =+G19-H19 -> 0 | J19: =+G19-D19 -> -158 | K19: =+H19-E19 -> -134 | L19: =+I19-F19 -> -24
B20: QCT | C20: 직접 | D20: =+'[2]OP 01.2023 Total'!E16+'[2]OP 01.2023 Total'!E17+'[2]OP 01.2023 Total'!E18+'[2]OP 01.2023 Total'!E21 -> 153 | E20: =+[2]D1_B1!E16+[2]D1_B1!E17+[2]D1_B1!E18+[2]D1_B1!E21 -> 135 | F20: =+D20-E20 -> 18 | G20: =Sum!E16+Sum!E17+Sum!E18 -> 0 | H20: =Sum!E17+Sum!E17+Sum!E21 -> 0 | I20: =+G20-H20 -> 0 | J20: =+G20-D20 -> -153 | K20: =+H20-E20 -> -135 | L20: =+I20-F20 -> -18
C21: 간접 | D21: =+'[2]OP 01.2023 Total'!E19+'[2]OP 01.2023 Total'!E20 -> 24 | E21: =+[2]D1_B1!E19+[2]D1_B1!E20 -> 16 | F21: =+D21-E21 -> 8 | G21: =Sum!E19+Sum!E20 -> 0 | H21: =Sum!E19+Sum!E20 -> 0 | I21: =+G21-H21 -> 0 | J21: =+G21-D21 -> -24 | K21: =+H21-E21 -> -16 | L21: =+I21-F21 -> -8
C22: 계 | D22: =+D21+D20 -> 177 | E22: =+E21+E20 -> 151 | F22: =+D22-E22 -> 26 | G22: =+G21+G20 -> 0 | H22: =+H21+H20 -> 0 | I22: =+G22-H22 -> 0 | J22: =+G22-D22 -> -177 | K22: =+H22-E22 -> -151 | L22: =+I22-F22 -> -26
B23: Admin | C23: 일반 | D23: =+'[2]OP 01.2023 Total'!E6 -> 11 | E23: =+[2]D1_B1!E6 -> 10 | F23: =+D23-E23 -> 1 | G23: =Sum!E6 -> 0 | H23: =Sum!E6 -> 0 | I23: =+G23-H23 -> 0 | J23: =+G23-D23 -> -11 | K23: =+H23-E23 -> -10 | L23: =+I23-F23 -> -1
C24: 간접 | D24: =+'[2]OP 01.2023 Total'!E5 -> 17 | E24: =+[2]D1_B1!E5 -> 16 | F24: =+D24-E24 -> 1 | G24: =Sum!E5 -> 0 | H24: =Sum!E5 -> 0 | I24: =+G24-H24 -> 0 | J24: =+G24-D24 -> -17 | K24: =+H24-E24 -> -16 | L24: =+I24-F24 -> -1
C25: 계 | D25: =+D24+D23 -> 28 | E25: =+E24+E23 -> 26 | F25: =+D25-E25 -> 2 | G25: =+G24+G23 -> 0 | H25: =+H24+H23 -> 0 | I25: =+G25-H25 -> 0 | J25: =+G25-D25 -> -28 | K25: =+H25-E25 -> -26 | L25: =+I25-F25 -> -2
B26: Other | C26: 직접 | F26: =+D26-E26 -> 0 | I26: =+G26-H26 -> 0 | J26: =+G26-D26 -> 0 | K26: =+H26-E26 -> 0 | L26: =+I26-F26 -> 0
C27: 간접 | D27: =+'[2]OP 01.2023 Total'!E25 -> 3 | E27: =+[2]D1_B1!E25 -> 3 | F27: =+D27-E27 -> 0 | G27: =Sum!E25 -> 0 | H27: =Sum!E25 -> 0 | I27: =+G27-H27 -> 0 | J27: =+G27-D27 -> -3 | K27: =+H27-E27 -> -3 | L27: =+I27-F27 -> 0
C28: 계 | D28: =+D27 -> 3 | E28: =+E27 -> 3 | F28: =+D28-E28 -> 0 | G28: =+G27+G26 -> 0 | H28: =+H27+H26 -> 0 | I28: =+G28-H28 -> 0 | J28: =+G28-D28 -> -3 | K28: =+H28-E28 -> -3 | L28: =+I28-F28 -> 0
B29: Total | C29: 일반 | D29: =+D23 -> 11 | E29: =+E23 -> 10 | F29: =+D29-E29 -> 1 | G29: =+G23 -> 0 | H29: =+H23 -> 0 | I29: =+G29-H29 -> 0 | J29: =+G29-D29 -> -11 | K29: =+H29-E29 -> -10 | L29: =+I29-F29 -> -1
C30: 직접 | D30: =+D14+D17+D20+D26 -> 301 | E30: =+E14+E17+E20+E26 -> 259 | F30: =+D30-E30 -> 42 | G30: =+G14+G17+G20+G26 -> 0 | H30: =+H14+H17+H20+H26 -> 0 | I30: =+G30-H30 -> 0 | J30: =+G30-D30 -> -301 | K30: =+H30-E30 -> -259 | L30: =+I30-F30 -> -42
C31: 간접 | D31: =+D15+D18+D21+D24+D27 -> 61 | E31: =+E15+E18+E21+E24+E27 -> 52 | F31: =+D31-E31 -> 9 | G31: =+G15+G18+G21+G24+G27 -> 0 | H31: =+H15+H18+H21+H24+H27 -> 0 | I31: =+G31-H31 -> 0 | J31: =+G31-D31 -> -61 | K31: =+H31-E31 -> -52 | L31: =+I31-F31 -> -9
C32: 계 | D32: =+D29+D30+D31 -> 373 | E32: =+E29+E30+E31 -> 321 | F32: =+D32-E32 -> 52 | G32: =+G29+G30+G31 -> 0 | H32: =+H29+H30+H31 -> 0 | I32: =+G32-H32 -> 0 | J32: =+G32-D32 -> -373 | K32: =+H32-E32 -> -321 | L32: =+I32-F32 -> -52
A33: MH Manhour (환산작업시간/월) | B33: MCT | C33: 직접 | F33: =+D33-E33 -> 0 | J33: =+G33-D33 -> 0 | K33: =+H33-E33 -> 0 | L33: =+I33-F33 -> 0
C34: 간접 | D34: =+'[2]OP 01.2023 Total'!R10+'[2]OP 01.2023 Total'!S10 -> 2367.115 | E34: =+[2]D1_B1!R10+[2]D1_B1!S10 -> 2367.115 | F34: =+D34-E34 -> 0 | G34: =Sum!R10+Sum!S10 -> 0 | H34: =Sum!R10+Sum!S10 -> 0 | I34: =+G34-H34 -> 0 | J34: =+G34-D34 -> -2367.115 | K34: =+H34-E34 -> -2367.115 | L34: =+I34-F34 -> 0
C35: 계 | D35: =+D34 -> 2367.115 | E35: =+E34 -> 2367.115 | F35: =+D35-E35 -> 0 | G35: =+G34 -> 0 | H35: =+H34 -> 0 | I35: =+G35-H35 -> 0 | J35: =+G35-D35 -> -2367.115 | K35: =+H35-E35 -> -2367.115 | L35: =+I35-F35 -> 0
B36: MAT/MMT/MET | C36: 직접 | D36: =+'[2]OP 01.2023 Total'!R11+'[2]OP 01.2023 Total'!S11+'[2]OP 01.2023 Total'!R13+'[2]OP 01.2023 Total'!S13+'[2]OP 01.2023 Total'!R14+'[2]OP 01.2023 Total'!S14 -> 57022.04 | E36: =+[2]D1_B1!R11+[2]D1_B1!S11+[2]D1_B1!R13+[2]D1_B1!S13 -> 47150.305 | F36: =+D36-E36 -> 9871.735 | G36: =Sum!R11+Sum!S10+Sum!R12+Sum!S12+Sum!R13+Sum!S13 -> 0 | H36: =Sum!R11+Sum!S10+Sum!R12+Sum!S12+Sum!R13+Sum!S13 -> 0 | I36: =+G36-H36 -> 0 | J36: =+G36-D36 -> -57022.04 | K36: =+H36-E36 -> -47150.305 | L36: =+I36-F36 -> -9871.735
C37: 간접 | D37: =+'[2]OP 01.2023 Total'!R12+'[2]OP 01.2023 Total'!S12 -> 3900.32 | E37: =+[2]D1_B1!R12+[2]D1_B1!S12 -> 3900.32 | F37: =+D37-E37 -> 0 | G37: =Sum!R12+Sum!S12 -> 0 | H37: =Sum!R12+Sum!S12 -> 0 | I37: =+G37-H37 -> 0 | J37: =+G37-D37 -> -3900.32 | K37: =+H37-E37 -> -3900.32 | L37: =+I37-F37 -> 0
C38: 계 | D38: =+D37+D36 -> 60922.36 | E38: =+E37+E36 -> 51050.625 | F38: =+D38-E38 -> 9871.735 | G38: =+G37+G36 -> 0 | H38: =+H37+H36 -> 0 | I38: =+G38-H38 -> 0 | J38: =+G38-D38 -> -60922.36 | K38: =+H38-E38 -> -51050.625 | L38: =+I38-F38 -> -9871.735 | M38: =J38/D38 -> -1
B39: QCT | C39: 직접 | D39: =+'[2]OP 01.2023 Total'!R16+'[2]OP 01.2023 Total'!S16+'[2]OP 01.2023 Total'!R17+'[2]OP 01.2023 Total'!S17+'[2]OP 01.2023 Total'!R18+'[2]OP 01.2023 Total'!S18 -> 51004.075 | E39: =+[2]D1_B1!R16+[2]D1_B1!S16+[2]D1_B1!R17+[2]D1_B1!S17+[2]D1_B1!R18+[2]D1_B1!S18+[2]D1_B1!R21+[2]D1_B1!S21 -> 44156.95 | F39: =+D39-E39 -> 6847.125 | G39: =Sum!R16+Sum!S16+Sum!R17+Sum!S17+Sum!R18+Sum!S18+Sum!R21+Sum!S21 -> 0 | H39: =Sum!R16+Sum!S16+Sum!R17+Sum!S17+Sum!R18+Sum!S18+Sum!R21+Sum!S21 -> 0 | I39: =+G39-H39 -> 0 | J39: =+G39-D39 -> -51004.075 | K39: =+H39-E39 -> -44156.95 | L39: =+I39-F39 -> -6847.125
C40: 간접 | D40: =+'[2]OP 01.2023 Total'!R19+'[2]OP 01.2023 Total'!S19+'[2]OP 01.2023 Total'!R20+'[2]OP 01.2023 Total'!S20 -> 8085.45 | E40: =+[2]D1_B1!R19+[2]D1_B1!S19+[2]D1_B1!R20+[2]D1_B1!S20 -> 5241.15 | F40: =+D40-E40 -> 2844.3 | G40: =Sum!R19+Sum!S19+Sum!R20+Sum!S20 -> 0 | H40: =Sum!R19+Sum!S19+Sum!R20+Sum!S20 -> 0 | I40: =+G40-H40 -> 0 | J40: =+G40-D40 -> -8085.45 | K40: =+H40-E40 -> -5241.15 | L40: =+I40-F40 -> -2844.3
C41: 계 | D41: =+D40+D39 -> 59089.525 | E41: =+E40+E39 -> 49398.1 | F41: =+D41-E41 -> 9691.425 | G41: =+G40+G39 -> 0 | H41: =+H40+H39 -> 0 | I41: =+G41-H41 -> 0 | J41: =+G41-D41 -> -59089.525 | K41: =+H41-E41 -> -49398.1 | L41: =+I41-F41 -> -9691.425 | M41: =J41/D41 -> -1
B42: Admin | C42: 일반 | D42: =+'[2]OP 01.2023 Total'!R6 -> 2121.35 | E42: =+[2]D1_B1!R6 -> 1928.5 | F42: =+D42-E42 -> 192.85 | G42: =Sum!R6 -> 0 | H42: =Sum!R6 -> 0 | I42: =+G42-H42 -> 0 | K42: =+H42-E42 -> -1928.5 | L42: =+I42-F42 -> -192.85
C43: 간접 | D43: =+'[2]OP 01.2023 Total'!R5 -> 3972.9 | E43: =+[2]D1_B1!R5 -> 3739.2 | F43: =+D43-E43 -> 233.7 | G43: =Sum!R5 -> 0 | H43: =Sum!R5 -> 0 | I43: =+G43-H43 -> 0 | J43: =+G43-D43 -> -3972.9 | K43: =+H43-E43 -> -3739.2 | L43: =+I43-F43 -> -233.7
C44: 계 | D44: =+D43+D42 -> 6094.25 | E44: =+E43+E42 -> 5667.7 | F44: =+D44-E44 -> 426.55 | G44: =++G42 -> 0 | H44: =++H42 -> 0 | I44: =+G44-H44 -> 0 | J44: =+G44-D44 -> -6094.25 | K44: =+H44-E44 -> -5667.7 | L44: =+I44-F44 -> -426.55
B45: Other | C45: 직접 | F45: =+D45-E45 -> 0 | I45: =+G45-H45 -> 0 | J45: =+G45-D45 -> 0 | K45: =+H45-E45 -> 0 | L45: =+I45-F45 -> 0
C46: 간접 | D46: =+'[2]OP 01.2023 Total'!R25 -> 706.95 | E46: =+[2]D1_B1!R25 -> 706.95 | F46: =+D46-E46 -> 0 | G46: =Sum!R25 -> 0 | H46: =Sum!R25 -> 0 | I46: =+G46-H46 -> 0 | J46: =+G46-D46 -> -706.95 | K46: =+H46-E46 -> -706.95 | L46: =+I46-F46 -> 0
C47: 계 | D47: =+D46 -> 706.95 | E47: =+E46 -> 706.95 | F47: =+D47-E47 -> 0 | G47: =+G46 -> 0 | H47: =+H46 -> 0 | I47: =+G47-H47 -> 0 | J47: =+G47-D47 -> -706.95 | K47: =+H47-E47 -> -706.95 | L47: =+I47-F47 -> 0
B48: Total | C48: 일반 | D48: =+D42 -> 2121.35 | E48: =+E42 -> 1928.5 | F48: =+D48-E48 -> 192.85 | G48: =+G42 -> 0 | H48: =+H42 -> 0 | I48: =+G48-H48 -> 0 | J48: =+G48-D48 -> -2121.35 | K48: =+H48-E48 -> -1928.5 | L48: =+I48-F48 -> -192.85
C49: 직접 | D49: =+D33+D36+D39+D45 -> 108026.11 | E49: =+E33+E36+E39+E45 -> 91307.255 | F49: =+D49-E49 -> 16718.86 | G49: =+G33+G36+G39+G45 -> 0 | H49: =+H33+H36+H39+H45 -> 0 | I49: =+G49-H49 -> 0 | J49: =+G49-D49 -> -108026.11 | K49: =+H49-E49 -> -91307.255 | L49: =+I49-F49 -> -16718.86
C50: 간접 | D50: =+D34+D37+D40+D43+D46 -> 19032.735 | E50: =+E34+E37+E40+E43+E46 -> 15954.735 | F50: =+D50-E50 -> 3078 | G50: =+G34+G37+G40+G43+G46 -> 0 | H50: =+H34+H37+H40+H43+H46 -> 0 | I50: =+G50-H50 -> 0 | J50: =+G50-D50 -> -19032.735 | K50: =+H50-E50 -> -15954.735 | L50: =+I50-F50 -> -3078
C51: 계 | D51: =+D48+D49+D50 -> 129180.2 | E51: =+E48+E49+E50 -> 109190.49 | F51: =+D51-E51 -> 19989.71 | G51: =+G48+G49+G50 -> 0 | H51: =+H48+H49+H50 -> 0 | I51: =+G51-H51 -> 0 | J51: =+G51-D51 -> -129180.2 | K51: =+H51-E51 -> -109190.49 | L51: =+I51-F51 -> -19989.71 | M51: =J51/D51 -> -1
A52: Gross salary (USD) | B52: MCT | C52: 직접 | F52: =+D52-E52 -> 0 | I52: =+G52-H52 -> 0 | J52: =+G52-D52 -> 0 | K52: =+H52-E52 -> 0 | L52: =+I52-F52 -> 0
C53: 간접 | D53: =+'[2]OP 01.2023 Total'!U10/23200 -> 3587.6829 | E53: =+[2]D1_B1!U10/23200 -> 3587.6829 | F53: =+D53-E53 -> 0 | G53: =Sum!U10/23200 -> 0 | H53: =Sum!U10/2320 -> 0 | I53: =+G53-H53 -> 0 | J53: =+G53-D53 -> -3587.6829 | K53: =+H53-E53 -> -3587.6829 | L53: =+I53-F53 -> 0
C54: 계 | D54: =+D53 -> 3587.6829 | E54: =+E53 -> 3587.6829 | F54: =+D54-E54 -> 0 | G54: =+G53 -> 0 | H54: =+H53 -> 0 | I54: =+G54-H54 -> 0 | J54: =+G54-D54 -> -3587.6829 | K54: =+H54-E54 -> -3587.6829 | L54: =+I54-F54 -> 0
B55: MAT/MMT/MET | C55: 직접 | D55: =+('[2]OP 01.2023 Total'!U15-'[2]OP 01.2023 Total'!U12)/23200 -> 76088.409 | E55: =+([2]D1_B1!U15-[2]D1_B1!U12)/23200 -> 63905.725 | F55: =+D55-E55 -> 12182.683 | G55: =(Sum!U15-Sum!U12)/23200 -> 0 | H55: =(Sum!U11+Sum!U13+Sum!U14)/23200 -> 0 | I55: =+G55-H55 -> 0 | J55: =+G55-D55 -> -76088.409 | K55: =+H55-E55 -> -63905.725 | L55: =+I55-F55 -> -12182.683
C56: 간접 | D56: =+'[2]OP 01.2023 Total'!U12/23200 -> 5926.7588 | E56: =+[2]D1_B1!U12/23200 -> 5926.7588 | F56: =+D56-E56 -> 0 | G56: =Sum!U12/23200 -> 0 | H56: =Sum!U12/23200 -> 0 | I56: =+G56-H56 -> 0 | J56: =+G56-D56 -> -5926.7588 | K56: =+H56-E56 -> -5926.7588 | L56: =+I56-F56 -> 0
C57: 계 | D57: =+D56+D55 -> 82015.168 | E57: =+E56+E55 -> 69832.484 | F57: =+D57-E57 -> 12182.683 | G57: =+G56+G55 -> 0 | H57: =+H56+H55 -> 0 | I57: =+G57-H57 -> 0 | J57: =+G57-D57 -> -82015.168 | K57: =+H57-E57 -> -69832.484 | L57: =+I57-F57 -> -12182.683 | M57: =J57/D57 -> -1
B58: QCT | C58: 직접 | D58: =+('[2]OP 01.2023 Total'!U16+'[2]OP 01.2023 Total'!U17+'[2]OP 01.2023 Total'!U18)/23200 -> 67603.443 | E58: =+([2]D1_B1!U16+[2]D1_B1!U17+[2]D1_B1!U18)/23200 -> 58795.996 | F58: =+D58-E58 -> 8807.447 | G58: =(Sum!U16+Sum!U17+Sum!U18+Sum!U21)/23200 -> 0 | H58: =(Sum!U23-Sum!U22-Sum!U19)/23200 -> 0 | I58: =+G58-H58 -> 0 | J58: =+G58-D58 -> -67603.443 | K58: =+H58-E58 -> -58795.996 | L58: =+I58-F58 -> -8807.447
C59: 간접 | D59: =+('[2]OP 01.2023 Total'!U19+'[2]OP 01.2023 Total'!U20)/23200 -> 10670.763 | E59: =+([2]D1_B1!U19+[2]D1_B1!U20)/23200 -> 7014.735 | F59: =+D59-E59 -> 3656.0279 | G59: =(Sum!U19+Sum!U20)/23200 -> 0 | H59: =(Sum!U19+Sum!U20)/23200 -> 0 | I59: 0 | J59: =+G59-D59 -> -10670.763 | K59: =+H59-E59 -> -7014.735 | L59: =+I59-F59 -> -3656.0279
C60: 계 | D60: =+D59+D58 -> 78274.206 | E60: =+E59+E58 -> 65810.731 | F60: =+D60-E60 -> 12463.475 | G60: =+G59+G58 -> 0 | H60: =+H59+H58 -> 0 | I60: =+G60-H60 -> 0 | J60: =+G60-D60 -> -78274.206 | K60: =+H60-E60 -> -65810.731 | L60: =+I60-F60 -> -12463.475 | M60: =J60/D60 -> -1
B61: Admin | C61: 일반 | D61: =+'[2]OP 01.2023 Total'!U6/23200 -> 8074.2504 | E61: =+[2]D1_B1!U6/23200 -> 7472.431 | F61: =+D61-E61 -> 601.81939 | G61: =Sum!U6/23200 -> 0 | H61: =Sum!U6/23200 -> 0 | I61: =+G61-H61 -> 0 | J61: =+G61-D61 -> -8074.2504 | K61: =+H61-E61 -> -7472.431 | L61: =+I61-F61 -> -601.81939
C62: 간접 | D62: =+'[2]OP 01.2023 Total'!U5/23200 -> 12908.431 | E62: =+[2]D1_B1!U5/23200 -> 12262.086 | F62: =+D62-E62 -> 646.34429 | G62: =Sum!U5/23200 -> 0 | H62: =Sum!U5/23200 -> 0 | I62: =+G62-H62 -> 0 | J62: =+G62-D62 -> -12908.431 | K62: =+H62-E62 -> -12262.086 | L62: =+I62-F62 -> -646.34429
C63: 계 | D63: =+D61+D62 -> 20982.681 | E63: =+E61+E62 -> 19734.517 | F63: =+D63-E63 -> 1248.1637 | G63: =+G61+G62 -> 0 | H63: =+H61+H62 -> 0 | I63: =+G63-H63 -> 0 | J63: =+G63-D63 -> -20982.681 | K63: =+H63-E63 -> -19734.517 | L63: =+I63-F63 -> -1248.1637
B64: Other | C64: 직접 | F64: =+D64-E64 -> 0 | I64: =+G64-H64 -> 0 | J64: =+G64-D64 -> 0 | K64: =+H64-E64 -> 0 | L64: =+I64-F64 -> 0
C65: 간접 | D65: =+'[2]OP 01.2023 Total'!U25/23200 -> 1187.0033 | E65: =+[2]D1_B1!U25/23200 -> 1187.0033 | F65: =+D65-E65 -> 0 | G65: =Sum!U25/23200 -> 0 | H65: =Sum!U25/23200 -> 0 | I65: =+G65-H65 -> 0 | J65: =+G65-D65 -> -1187.0033 | K65: =+H65-E65 -> -1187.0033 | L65: =+I65-F65 -> 0
C66: 계 | D66: =+D65+D64 -> 1187.0033 | E66: =+E65+E64 -> 1187.0033 | F66: =+D66-E66 -> 0 | G66: =+G65+G64 -> 0 | H66: =+H65+H64 -> 0 | I66: =+G66-H66 -> 0 | J66: =+G66-D66 -> -1187.0033 | K66: =+H66-E66 -> -1187.0033 | L66: =+I66-F66 -> 0
B67: 합계 | C67: 일반 | D67: =+D61 -> 8074.2504 | E67: =+E61 -> 7472.431 | F67: =+D67-E67 -> 601.81939 | G67: =+G61 -> 0 | H67: =+H61 -> 0 | I67: =+G67-H67 -> 0 | J67: =+G67-D67 -> -8074.2504 | K67: =+H67-E67 -> -7472.431 | L67: =+I67-F67 -> -601.81939
C68: 직접 | D68: =+D52+D55+D58+D64 -> 143691.85 | E68: =+E52+E55+E58+E64 -> 122701.72 | F68: =+D68-E68 -> 20990.131 | G68: =+G52+G55+G58+G64 -> 0 | H68: =+H52+H55+H58+H64 -> 0 | I68: =+G68-H68 -> 0 | J68: =+G68-D68 -> -143691.85 | K68: =+H68-E68 -> -122701.72 | L68: =+I68-F68 -> -20990.131
C69: 간접 | D69: =+D53+D56+D59+D62+D65 -> 34280.639 | E69: =+E53+E56+E59+E62+E65 -> 29978.266 | F69: =+D69-E69 -> 4302.3722 | G69: =+G53+G56+G59+G62+G65 -> 0 | H69: =+H53+H56+H59+H62+H65 -> 0 | I69: =+G69-H69 -> 0 | J69: =+G69-D69 -> -34280.639 | K69: =+H69-E69 -> -29978.266 | L69: =+I69-F69 -> -4302.3722
C70: 계 | D70: =+D67+D68+D69 -> 186046.74 | E70: =+E67+E68+E69 -> 160152.42 | F70: =+D70-E70 -> 25894.322 | G70: =+G67+G68+G69 -> 0 | H70: =+H67+H68+H69 -> 0 | I70: =+G70-H70 -> 0 | J70: =+G70-D70 -> -186046.74 | K70: =+H70-E70 -> -160152.42 | L70: =+I70-F70 -> -25894.322 | M70: =J70/D70 -> -1
E72: ** 노무비 증가원인 요약 | G72: 1) 바이백 물량 증가 | I72: : D. M/CORE 200,000개 증가. 하우징 350바 14,400개 증가
G73: 2) HV10 감마플랜지 26,500개/ 스풀 37,217개/ 폴 NH 31,867개 증가
G74: 3) 밸브바디 82,000개 증가, T/P 37,000개 증가
E75: ** 장비가동 | G75: 1) BP : 111대, 2) OP : 108대 비가동 : 3대 (시마다 1대, 제현장비 2대)
D76: =+D70*23200 -> 4.3162844e+09 | E76: =+E70*23200 -> 3.7155361e+09 | G76: =+G70*23200 -> 0 | H76: =+H70*23200 -> 0
D77: =+'[3]OP 01.2023 Total'!U26 -> 4.3162844e+09 | E77: =+[3]D1_B1!U26 -> 3.7155361e+09 | G77: =+'[3]ACtual 01.2023 Total'!U26 -> 3955012739 | H77: =+'[3]Actual D1_01.2023'!U26 -> 3416428568
D78: =+D76-D77 -> 0 | E78: =+E76-E77 -> 0 | F78: =+F76-F77 -> 0 | G78: =+G76-G77 -> -3955012739 | H78: =+H76-H77 -> -3416428568 | I78: =+I76-I77 -> 0
