Workbook
Name Insurance__Company_payment: 'MVP_Nov & Dec Actual'!$B$25:$B$28
Name Insurance__Company_payment: #REF!

Sheet Sheet1
A1: 1
A2: 2 | B2: No | C2: SoLuongNhanVien | D2: SoLuongNhanVienThangCu | E2: ChucDanh1 | F2: ChucDanh | G2: Salary_Month | H2: Salary_Year | I2: SoLuongNV | J2: BasicSalary | K2: PhuCap | L2: TienLuongHC | M2: TienTangCa | N2: Luong1Gio | O2: GioLamViecKhongCoNghi | P2: GioTangCa150 | Q2: TienTangCa150 | R2: GioTangCaCN200 | S2: TienTangCaCN200 | T2: GioTangCaDem210 | U2: TienTangCaDem210 | V2: GioTangCaDemCN270 | W2: TienTangCaDemCN270 | X2: GioTangCaLe300 | Y2: TienTangCaLe300 | Z2: GioTangCaDemLe390 | AA2: TienTangCaDemLe390 | AB2: TongTangCa | AC2: TongTangCaVaHCDaChuyen | AD2: GioLamDem130 | AE2: TienCaDem130 | AF2: TongLuong | AG2: CongDoanCtyTra | AH2: BHCtyTra | AI2: TongChiPhi | AJ2: BHNVDong | AK2: TTCN | AL2: CongDoanNVDong | AM2: TroCapConNho | AN2: TroCapPhuNu | AO2: HoTroKhac | AP2: ThucNhan | AQ2: LuongChoViec | AR2: SoNVDongBH | AS2: SoTienDongBH | AT2: SoNguoiDongThue | AU2: SoTienDongThue | AV2: SoNguoiDongCongDoan | AW2: SoTienDongCongDoan | AX2: ActualWorkingDay | AY2: PublicHoliday | AZ2: WorkingSaturday | BA2: SaturdayOT
A3: 3 | B3: 2 | C3: 2 | D3: 2 | E3: 1 | F3: 1 | G3: 1 | H3: 1 | I3: 1 | J3: 1 | K3: 1 | L3: 1 | M3: 1 | N3: 1 | O3: 1 | P3: 1 | Q3: 1 | R3: 1 | S3: 1 | T3: 1 | U3: 1 | V3: 1 | W3: 1 | X3: 1 | Y3: 1 | Z3: 1 | AA3: 1 | AB3: 1 | AC3: 1 | AD3: 1 | AE3: 1 | AF3: 1 | AG3: 1 | AH3: 1 | AI3: 1 | AJ3: 1 | AK3: 1 | AL3: 1 | AM3: 1 | AN3: 1 | AO3: 1 | AP3: 1 | AQ3: 1 | AR3: 1 | AS3: 1 | AT3: 1 | AU3: 1 | AV3: 1 | AW3: 1 | AX3: 1 | AY3: 1 | AZ3: 1 | BA3: 1
A4: 4
A5: 5

Sheet MVP_Nov & Dec Actual
B1: ="ACTUAL SALARY COMPARISION ANALYSIS_"&UPPER(TEXT(DATE(Sheet1!A2,Sheet1!A1,1),"MMM yyyy"))&" & "&UPPER(TEXT(DATE(Sheet1!A2,Sheet1!A1,1),"MMM yyyy"))&"" -> ACTUAL SALARY COMPARISION ANALYSIS_JAN 1902 & JAN 1902
F2: ="Date: " & TEXT(TODAY(),"dd-MM-YYYY") -> Date: 17-02-2023
L3: Unit: VND
A4: Section | E4: Dec - Actual (B) | G4: Jan - Actual (A) | I4: Different (B-A) | K4: Reason | L4: Remarks
E5: Person (Hour) | F5: Amount | G5: Person (Hour) | H5: Amount | I5: =+G5 -> Person (Hour) | J5: Amount
B6: Person | C6: Person | G6: 233P | J6: 18P | K6: New employee working in QC, Production in MVP & training Korea
B7: Total salary | C7: Basic salary | E7: =Sheet1!I5 -> 0 | F7: =Sheet1!J5 -> 0 | G7: =Sheet1!I6 -> 0 | H7: =Sheet1!J6 -> 0 | I7: =+G7-E7 -> 0 | J7: =+H7-F7 -> 0 | L7: =+'[1]MVP_Dec Plan & actual)'!L7:L14 -> (Total employees: 380P ( Maternity: 0P, quited job: 5P; Temporary OP: 0P remaining: 3755P)
C8: Allowance | E8: =E7 -> 0 | F8: =Sheet1!K5 -> 0 | G8: =G7 -> 0 | H8: =Sheet1!K6 -> 0 | I8: =+G8-E8 -> 0 | J8: =+H8-F8 -> 0
C9: Over time & Allowance 30% | D9: Allowance night shift 30% | E9: =Sheet1!T5 -> 0 | F9: =Sheet1!U5 -> 0 | G9: =Sheet1!T6 -> 0 | H9: =Sheet1!U6 -> 0 | I9: =+G9-E9 -> 0 | J9: =+H9-F9 -> 0 | K9: =" - Working day in " & UPPER(TEXT(DATE(Sheet1!A2,Sheet1!A1,1),"MMM, yyyy")) & " : "& Sheet1!$AX$5 &" days - Working day in " & UPPER(TEXT(DATE(Sheet1!A2,Sheet1!A1,1)-1,"MMM, yyyy")) & " : "& Sheet1!$AX$5 &" days" -> - Working day in JAN, 1902 : days - Working day in DEC, 1901 : days
D10: Normal (150%) | E10: =Sheet1!P5 -> 0 | F10: =Sheet1!Q5 -> 0 | G10: =Sheet1!P6 -> 0 | H10: =Sheet1!Q6 -> 0 | I10: =+G10-E10 -> 0 | J10: =+H10-F10 -> 0 | K10: ="- " & $O$10 &" : "& Sheet1!$AX$5 &" normal day 150% (" & ROUND(M10,2) & " h/m) - " & O11 &": "& Sheet1!$AX$5 &" normal day 150% (" & ROUND(N10,2) &" h/m)" -> #DIV/0! | M10: =+E10/E7 -> #DIV/0! | N10: =+G10/G7 -> #DIV/0! | O10: =UPPER(TEXT(DATE(Sheet1!$A$2,Sheet1!$A$1,1)-1,"MMM")) -> DEC
D11: Sunday (200%) | E11: =Sheet1!R5 -> 0 | F11: =Sheet1!S5 -> 0 | G11: =Sheet1!R6 -> 0 | H11: =Sheet1!S6 -> 0 | I11: =+G11-E11 -> 0 | J11: =+H11-F11 -> 0 | K11: ="- " & $O$10 &" : "& Sheet1!$AX$5 &" normal day 200% (" & ROUND(M11,2) & " h/m) - " & $O$11 &": "& Sheet1!$AX$5 &" normal day 200% (" & ROUND(N11,2) &" h/m)" -> #DIV/0! | M11: =+E11/$E$7 -> #DIV/0! | N11: =+G11/$G$7 -> #DIV/0! | O11: =UPPER(TEXT(Sheet1!$A$1*28,"MMM")) -> JAN
D12: Normal (210%) | E12: =Sheet1!T5 -> 0 | F12: =Sheet1!U5 -> 0 | G12: =Sheet1!T6 -> 0 | H12: =Sheet1!U6 -> 0 | I12: =+G12-E12 -> 0 | J12: =+H12-F12 -> 0 | K12: ="- " & $O$10 &" : "& Sheet1!$AX$5 &" normal day 210% (" & ROUND(M12,2) & " h/m) - " & $O$11 &": "& Sheet1!$AX$5 &" normal day 210% (" & ROUND(N12,2) &" h/m)" -> #DIV/0! | M12: =+E12/$E$7 -> #DIV/0! | N12: =+G12/$G$7 -> #DIV/0!
D13: Sunday (270%) | E13: =Sheet1!V5 -> 0 | F13: =Sheet1!W5 -> 0 | G13: =Sheet1!V6 -> 0 | H13: =Sheet1!W6 -> 0 | I13: =+G13-E13 -> 0 | J13: =+H13-F13 -> 0 | K13: ="- " & $O$10 &" : "& Sheet1!$AX$5 &" normal day 270% (" & ROUND(M13,2) & " h/m) - " & $O$11 &": "& Sheet1!$AX$5 &" normal day 270% (" & ROUND(N13,2) &" h/m)" -> #DIV/0! | M13: =+E13/$E$7 -> #DIV/0! | N13: =+G13/$G$7 -> #DIV/0!
D14: Sunday (300%) | E14: =Sheet1!X5 -> 0 | F14: =Sheet1!Y5 -> 0 | G14: =Sheet1!X6 -> 0 | H14: =Sheet1!Y6 -> 0 | I14: =+G14-E14 -> 0 | J14: =+H14-F14 -> 0 | K14: ="- " & $O$10 &" : "& Sheet1!$AX$5 &" normal day 300% (" & ROUND(M14,2) & " h/m) - " & $O$11 &": "& Sheet1!$AX$5 &" normal day 300% (" & ROUND(N14,2) &" h/m)" -> #DIV/0! | M14: =+E14/$E$7 -> #DIV/0! | N14: =+G14/$G$7 -> #DIV/0!
D15: Sunday (390%) | E15: =Sheet1!Z5 -> 0 | F15: =Sheet1!AA5 -> 0 | G15: =Sheet1!Z6 -> 0 | H15: =Sheet1!AA6 -> 0 | I15: =+G15-E15 -> 0 | J15: =+H15-F15 -> 0 | K15: ="- " & $O$10 &" : "& Sheet1!$AX$5 &" normal day 390% (" & ROUND(M15,2) & " h/m) - " & $O$11 &": "& Sheet1!$AX$5 &" normal day 390% (" & ROUND(N15,2) &" h/m)" -> #DIV/0! | M15: =+E15/$E$7 -> #DIV/0! | N15: =+G15/$G$7 -> #DIV/0!
D16: Subtotal | E16: =SUBTOTAL(9,E9:E13) -> 0 | F16: =SUBTOTAL(9,F9:F13) -> 0 | G16: =SUBTOTAL(9,G9:G13) -> 0 | H16: =SUBTOTAL(9,H9:H13) -> 0 | I16: =+G16-E16 -> 0 | J16: =+H16-F16 -> 0
C17: Gross salary | D17: Monthly salary | F17: =Sheet1!L5 -> 0 | H17: =Sheet1!L6 -> 0 | I17: =+G17-E17 -> 0 | J17: =+H17-F17 -> 0
D18: Attendance ratio (%) | F18: =(F22-F16)/(F7+F8) -> #DIV/0! | H18: =(H22-H16)/(H7+H8) -> #DIV/0! | I18: =+G18-E18 -> 0 | J18: =+H18-F18 -> #DIV/0!
C19: Home working | J19: =+H19-F19 -> 0
C20: Cv allowance | J20: =+H20-F20 -> 0
C21: Temporary worker | I21: =+G21-E21 -> 0 | J21: =+H21-F21 -> 0
B22: Total A= (1) + (2) | F22: =F16+F17+F21 -> 0 | H22: =H16+H17+H21 -> 0 | I22: =+G22-E22 -> 0 | J22: =+H22-F22 -> 0
C23: Tax refund (4) | J23: =+H23-F23 -> 0
B24: Deduction | C24: Insurance (Employee payment) | E24: =Sheet1!AR5 -> 0 | F24: =Sheet1!AS5 -> 0 | G24: =Sheet1!AR6 -> 0 | H24: =Sheet1!AS6 -> 0 | I24: =+G24-E24 -> 0 | J24: =+H24-F24 -> 0
C25: PIT | E25: =Sheet1!AT5 -> 0 | F25: =Sheet1!AU5 -> 0 | G25: =Sheet1!AT6 -> 0 | H25: =Sheet1!AU6 -> 0 | I25: =+G25-E25 -> 0 | J25: =+H25-F25 -> 0 | K25: =+'[1]MVP_Dec Plan & actual)'!K26 -> - JAN.2023 included 355P join insurance
C26: Union | E26: =Sheet1!AV5 -> 0 | F26: =Sheet1!AW5 -> 0 | G26: =Sheet1!AV6 -> 0 | H26: =Sheet1!AW6 -> 0 | I26: =+G26-E26 -> 0 | J26: =+H26-F26 -> 0
B27: Total B (5) | F27: =SUBTOTAL(9,F24:F26) -> 0 | H27: =SUBTOTAL(9,H24:H26) -> 0 | I27: =+G27-E27 -> 0 | J27: =+H27-F27 -> 0 | K27: - Trade union fee: 30.000 VND / person (Deduct directly from employees' salary
C28: Pay tax (6) | I28: =+G28-E28 -> 0 | J28: =+H28-F28 -> 0
B29: Net income(excluded bonus ) (7)= Total A-Total B + (3) | F29: =F22-F27-F21 -> 0 | H29: =H22-H27-H21 -> 0 | I29: =+G29-E29 -> 0 | J29: =+H29-F29 -> 0
B30: Net income(Included temporary +bonus ) (8)= Total A-Total B + (3) | F30: =F22-F27 -> 0 | H30: =H22-H27 -> 0 | I30: =+G30-E30 -> 0 | J30: =+H30-F30 -> 0

Sheet MP
B2: M/P | C2: ='MVP_Nov & Dec Actual'!O10 -> DEC | D2: ='MVP_Nov & Dec Actual'!O11 -> JAN | E2: Diff | I2: Section | J2: Dec | K2: Jan | L2: Different
B3: Auto | C3: =Sheet1!D7 -> 0 | D3: =Sheet1!C7 -> 0 | E3: =D3-C3 -> 0 | I3: 30% night shift | J3: ='MVP_Nov & Dec Actual'!E9 -> 0 | K3: ='MVP_Nov & Dec Actual'!G9 -> 0 | L3: =+K3-J3 -> 0
B4: Brushing | C4: =Sheet1!D8 -> 0 | D4: =Sheet1!C8 -> 0 | E4: =D4-C4 -> 0 | I4: OT Normal 150% (h/m) | J4: ='MVP_Nov & Dec Actual'!E10 -> 0 | K4: ='MVP_Nov & Dec Actual'!G10 -> 0 | L4: =+K4-J4 -> 0
B5: Cleaner | C5: =Sheet1!D9 -> 0 | D5: =Sheet1!C9 -> 0 | E5: =D5-C5 -> 0 | I5: OT Sunday 200% (h/m) | J5: ='MVP_Nov & Dec Actual'!E11 -> 0 | K5: ='MVP_Nov & Dec Actual'!G11 -> 0 | L5: =+K5-J5 -> 0
B6: Deburing | C6: =Sheet1!D10 -> 0 | D6: =Sheet1!C10 -> 0 | E6: =D6-C6 -> 0 | I6: OT Sunday 210% (h/m) | J6: ='MVP_Nov & Dec Actual'!E12 -> 0 | K6: ='MVP_Nov & Dec Actual'!G12 -> 0 | L6: =+K6-J6 -> 0
B7: Delivery | C7: =Sheet1!D11 -> 0 | D7: =Sheet1!C11 -> 0 | E7: =D7-C7 -> 0 | I7: OT Sunday 270% (h/m) | J7: ='MVP_Nov & Dec Actual'!E13 -> 0 | K7: ='MVP_Nov & Dec Actual'!G13 -> 0 | L7: =+K7-J7 -> 0
B8: FM/DFProduction | C8: =Sheet1!D12 -> 0 | D8: =Sheet1!C12 -> 0 | E8: =D8-C8 -> 0 | I8: OT Holiday 300% (h/m) | J8: ='MVP_Nov & Dec Actual'!E14 -> 0 | K8: ='MVP_Nov & Dec Actual'!G14 -> 0 | L8: =+K8-J8 -> 0
B9: FM/DFQC | C9: =Sheet1!D13 -> 0 | D9: =Sheet1!C13 -> 0 | E9: =D9-C9 -> 0 | I9: OT Holiday 390% (h/m) | J9: ='MVP_Nov & Dec Actual'!E15 -> 0 | K9: ='MVP_Nov & Dec Actual'!G15 -> 0 | L9: =+K9-J9 -> 0
B10: MATworker | C10: =Sheet1!D14 -> 0 | D10: =Sheet1!C14 -> 0 | E10: =D10-C10 -> 0
B11: MCTworker | C11: =Sheet1!D15 -> 0 | D11: =Sheet1!C15 -> 0 | E11: =D11-C11 -> 0
B12: METworker | C12: =Sheet1!D16 -> 0 | D12: =Sheet1!C16 -> 0 | E12: =D12-C12 -> 0
B13: MMTworker | C13: =Sheet1!D17 -> 0 | D13: =Sheet1!C17 -> 0 | E13: =D13-C13 -> 0
B14: Office1 | C14: =Sheet1!D18 -> 0 | D14: =Sheet1!C18 -> 0 | E14: =D14-C14 -> 0
B15: Office2 | C15: =Sheet1!D19 -> 0 | D15: =Sheet1!C19 -> 0 | E15: =D15-C15 -> 0
B16: Packing | C16: =Sheet1!D20 -> 0 | D16: =Sheet1!C20 -> 0 | E16: =D16-C16 -> 0
B17: PQC/OQC | C17: =Sheet1!D21 -> 0 | D17: =Sheet1!C21 -> 0 | E17: =D17-C17 -> 0
B18: Service | C18: =Sheet1!D22 -> 0 | D18: =Sheet1!C22 -> 0 | E18: =D18-C18 -> 0
B19: V/I | C19: =Sheet1!D23 -> 0 | D19: =Sheet1!C23 -> 0 | E19: =D19-C19 -> 0
B20: Total | C20: =SUM(C3:C19) -> 0 | D20: =SUM(D3:D19) -> 0 | E20: =D20-C20 -> 0
