Workbook

Sheet Sheet1
A1: 1 | B1: CÔNG TY TNHH SHINSUNG VINA
A2: 2 | B2: Lô CN04, khu công nghiệp Cẩm Khê, TT.Cẩm Khê, H.Cẩm Khê, T.Phú Thọ
A3: 3 | B3: ="PAYROLL " & UPPER(TEXT(A1*29,"MMMMMM")) & " " & A2 -> PAYROLL JANUARY 2
A4: 4 | B4: ="From 1st - " & DAY(EOMONTH(DATE(A2,A1,1),0)) & " " & TEXT(A1*29,"MMMMMM") & " " & A2 -> From 1st - 31 January 2
A5: 5 | B5: ="Tỷ giá Vietinbank: " & TEXT(BY13,"dd/MM/yyyy") -> Tỷ giá Vietinbank: 00/01/1900 | E5: 25160 | F5: =$BX$13 -> 0
A6: 6 | B6: No | C6: Employee_ID | D6: FullName | K6: CD1 | M6: CD2 | N6: CD14 | O6: CD16 | P6: CD11 | AM6: NguoiPhuThuoc | AR6: CD6 | AS6: HT18 | AW6: HT17 | AZ6: BankAccount | BC6: Key | BD6: Salary_Month | BE6: Salary_Year | BF6: cct_wt1 | BG6: cct_wt9 | BH6: cct_wt3 | BI6: cct_wt5 | BJ6: cct_wt4 | BK6: cct_wt7 | BL6: ctv_wt1 | BM6: ctv_wt9 | BN6: ctv_wt3 | BO6: ctv_wt5 | BP6: ctv_wt4 | BQ6: ctv_wt7 | BR6: pct_PhepHuongLuong | BS6: ptv_Phephuongluong | BT6: LuongTinhBH | BU6: SocialInsurance | BV6: HealthInsurance | BW6: NgayCongTieuChuan | BX6: TyGiaUSD | BY6: NgayApDungTyGia | BZ6: CD7
B7: 2 | C7: 2 | D7: 2 | E7: 2 | F7: 1 | G7: 1 | H7: 1 | I7: 1 | J7: 1 | K7: 1 | L7: 1 | M7: 1 | N7: 1 | O7: 1 | P7: 1 | Q7: 1 | R7: 1 | S7: 1 | T7: 1 | U7: 1 | V7: 1 | W7: 1 | X7: 1 | Y7: 1 | Z7: 1 | AA7: 1 | AB7: 1 | AC7: 1 | AD7: 1 | AE7: 1 | AF7: 1 | AG7: 1 | AH7: 1 | AI7: 1 | AJ7: 1 | AK7: 1 | AL7: 1 | AM7: 1 | AN7: 1 | AO7: 1 | AP7: 1 | AQ7: 1 | AR7: 1 | AS7: 1 | AT7: 1 | AU7: 1 | AV7: 1 | AW7: 1 | AX7: 1 | AY7: 1 | BC7: Key | BD7: Salary_Month | BE7: Salary_Year
C8: Employee_ID | F8: s2 | G8: s3 | H8: s4 | I8: s5 | J8: s6 | K8: s7 | L8: s1 | M8: s8 | N8: s9 | O8: s10 | P8: s11 | Q8: s12 | R8: s13 | S8: s14 | T8: s15 | U8: s16 | V8: s17 | W8: s18 | X8: s19 | Y8: s20 | Z8: s21 | AA8: s22 | AB8: s23 | AC8: s24 | AD8: s25 | AE8: s26 | AF8: s27 | AG8: s28 | AH8: s29 | AI8: s30 | AJ8: s31 | AK8: s32 | AL8: s33 | AM8: s34 | AN8: s35 | AO8: s36 | AP8: s37 | AQ8: s38 | AT8: s39 | AU8: s40 | AV8: s41 | AW8: s42 | AX8: s43 | AY8: s44 | BC8: Key | BD8: Salary_Month | BE8: Salary_Year
C9: Employee_ID | BC9: Key | BD9: Salary_Month | BE9: Salary_Year
B10: STT (No) | C10: Mã nhân viên | D10: Họ và tên (First and last name) | E10: Vị trí (Location) | F10: Giờ công cơ bản thực tế (The actual basic hourly) | G10: Giờ công làm thêm (Hours of overtime) | K10: Lương cơ bản (Basic salary) USD | L10: Lương cơ bản (Basic salary) | M10: Các khoản phụ cấp (Allowances) | S10: Tổng các khoản phụ cấp (Total allowances) | T10: Lương đóng bảo hiểm | U10: Lương giờ công | V10: Tổng lương giờ công cơ bản | W10: Lương giờ công làm thêm | AB10: Tổng lương | AC10: BH tính vào chi phí / Isuarance payable by company | AH10: BH khấu trừ lương / Isuarance deductions from salary | AL10: Thuế TNCN /Personal income tax | AX10: Thực nhận | AZ10: Số tài khoản | BA10: Ký nhận | BF10: Công chính thức | BL10: Công thử việc
G11: Tăng ca ngày | H11: Tăng ca đêm | I11: Tăng ca CN 200% | J11: Tăng ca ngày lễ 300% | M11: Phụ cấp trách nhiệm | N11: Phụ cấp điện thoại | O11: Phụ cấp xăng xe | P11: Phụ cấp nhà ở | Q11: Phụ cấp đi lại | R11: Chuyên cần (Diligence) | W11: Tăng ca ngày 150% | X11: Tăng ca đêm | Y11: Tăng ca CN 200% | Z11: Tăng ca ngày lễ 300% | AA11: Tổng lương làm thêm | AC11: Lương đóng bảo hiểm/Salary base for insurance | AD11: BHXH / Social Insurance 17.5% | AE11: BHYT / Health Insurance 3%건강보험 (회사분) | AF11: BHTN / Unemployment Insurance 1% | AG11: Cộng /Amount Isurance | AH11: BHXH / Social Insurance 8% | AI11: BHYT / Health Insurance 1,5% 건강보험 (개인분) | AJ11: BHTN / Unemployment Insurance 1% | AK11: Cộng 10.5%/Amount Isurance | AL11: Giảm trừ bản thân (기본공제금 ) (VND) | AM11: Số người phụ thuộc /Number Deduction family | AN11: Giảm trừ người phụ thuộc /deduction-family 4400000/1person | AO11: Tax excemption | AP11: Thu nhập chịu thuế | AQ11: Tiền BHSK tính thuế TNCN | AR11: Tiền thuê nhà thực tế | AS11: Vé máy bay | AT11: Thu nhập chịu thuế bảo gồm tiền BHSK + vé máy bay | AU11: Thu nhập tính thuế (과세 대상 금액) (VND) | AV11: Thuế TNCN (개인소득세) ( VND) | AW11: Truy thu Thuế TNCN | AX11: VND | AY11: USD (Quy đổi) | BF11: Giờ 100% | BG11: Giờ 130% | BH11: Giờ 150 | BI11: Giờ 200% | BJ11: Giờ 200% CN | BK11: Giờ 300% Lễ | BL11: Giờ 100% | BM11: Giờ 130% | BN11: Giờ 150 | BO11: Giờ 200% | BP11: Giờ 200% CN | BQ11: Giờ 300% Lễ | BR11: Phép hưởng lương CT | BS11: Phép hưởng lương TV | BT11: Lương tính BH | BU11: BHXH | BV11: BHYT | BW11: Ngày công tiêu chuẩn | BX11: Tỷ giá USD | BY11: Ngày áp dụng tỷ giá | BZ11: Tiền BHSK
B12: -1 | D12: -2 | E12: -3 | F12: -4 | G12: -5 | H12: (5a) | I12: -6 | J12: -7 | L12: -8 | M12: -9 | N12: -10 | O12: -11 | P12: (11 a) | Q12: (11b) | R12: -12 | S12: (13)=10+11+11a+11b+ 12 | T12: (14)=(8)+(9) | U12: (15)=(14)/4 | V12: (16)=(15)*(4) | W12: (17)=(5)* (15)*150% | X12: (17a) | Y12: (18)=(6)* (15)*200% | Z12: (19)=(7)* (15)*300% | AA12: (20)= (17)+(18)+(19) | AB12: (21)=(13)+(16)+ (20) | AC12: (22)=(8)+ (10) | AD12: (23)=(22)x17% | AE12: (24)=(22)x3% | AF12: 25 | AG12: (26)=(23)+(24) | AH12: 27 | AI12: (28)=(22)x1.5% | AJ12: 29 | AK12: (30)=(27)+(28)+(29) | AL12: -31 | AM12: (31a) | AN12: (32)= (31a)x4400000 | AO12: -33 | AP12: (34)=(21)-(33) | AU12: (35)=(21)-(31)-(32)-(33) | AV12: -36 | AX12: -37 | AY12: -38 | AZ12: -39 | BA12: -40
B13: 1 | F13: =BF13+BG13+BL13+BM13+BR13+BS13 -> 0 | G13: =BH13+BN13 -> 0 | H13: =BI13+BO13 -> 0 | I13: =BJ13+BP13 -> 0 | J13: =BK13+BQ13 -> 0 | K13: 0 | L13: =IF(K13>1000000,K13,K13*$F$5) -> 0 | S13: =SUM(N13:R13) -> 0 | T13: =L13+M13 -> 0 | U13: =T13/F13 -> #DIV/0! | V13: =U13*F13 -> #DIV/0! | W13: =U13*G13*150% -> #DIV/0! | X13: =U13*H13*195% -> #DIV/0! | Y13: =U13*I13*200% -> #DIV/0! | Z13: =U13*J13*300% -> #DIV/0! | AA13: =SUM(W13:Z13) -> #DIV/0! | AB13: =S13+V13+AA13 -> #DIV/0! | AC13: =MIN(T13,BT13*20) -> 0 | AD13: =IF(BU13=0,0,IF(AND(BU13=2,(BF13+BR13)/8<BW13-14),0,AC13*17.5%)) -> 0 | AE13: =IF(BV13=0,0,IF(AND(BV13=2,(BF13+BR13)/8<BW13-14),0,AC13*3%)) -> 0 | AG13: =AD13+AE13+AF13 -> 0 | AH13: =IF(AD13>0,AC13*8%,0) -> 0 | AI13: =IF(AE13>0,AC13*1.5%,0) -> 0 | AK13: =AH13+AI13+AJ13 -> 0 | AL13: 11000000 | AM13: 0 | AN13: =+AM13*4400000 -> 0 | AP13: =AB13-AO13 -> #DIV/0! | AQ13: =BZ13/12 -> 0 | AR13: 0 | AS13: 0 | AT13: =AP13+AQ13+AR13+AS13 -> #DIV/0! | AU13: =(AT13-AL13-AN13-AK13) -> #DIV/0! | AV13: =ROUND(IF(AU13<=5000000,AU13*5%,IF(AND(AU13>5000000,AU13<=10000000),AU13*10%-250000,IF(AND(AU13>10000000,AU13<=18000000),AU13*15%-750000,IF(AND(AU13>18000000,AU13<=32000000),AU13*20%-1650000,IF(AND(AU13>32000000,AU13<=52000000),AU13*25%-3250000,IF(AND(AU13>52000000,AU13<80000000),AU13*30%-5850000,IF(AU13>80000000,AU13*35%-9850000))))))),0) -> #DIV/0! | AW13: 0 | AX13: =AB13-AK13-AV13-AW13 -> #DIV/0! | AY13: =AX13/F5 -> #DIV/0! | AZ13: 0 | BF13: 0 | BG13: 0 | BH13: 0 | BI13: 0 | BJ13: 0 | BK13: 0 | BL13: 0 | BM13: 0 | BN13: 0 | BO13: 0 | BP13: 0 | BQ13: 0 | BR13: 0 | BS13: 0 | BT13: 0 | BU13: 0 | BV13: 0 | BW13: 0 | BX13: 0 | BY13: 0 | BZ13: 0

Sheet Mr. Shin
A1: CÔNG TY TNHH SHINSUNG VINA
A2: Lô CN04, khu công nghiệp Cẩm Khê, TT.Cẩm Khê, H.Cẩm Khê, T.Phú Thọ
A3: =Sheet1!B3 -> PAYROLL JANUARY 2
A4: =Sheet1!B4 -> From 1st - 31 January 2
A6: =Sheet1!B5 -> Tỷ giá Vietinbank: 00/01/1900 | D6: =Sheet1!E5 -> 25160 | E6: =Sheet1!F5 -> 0
A8: STT (No) | B8: Mã nhân viên (Employee ID) | C8: Họ và tên (First and last name) | D8: Vị trí (Location) | E8: Giờ công cơ bản thực tế (The actual basic hourly) | F8: Giờ công làm thêm (Hours of overtime) | J8: Lương cơ bản (Basic salary) USD | K8: Lương cơ bản (Basic salary) | L8: Các khoản phụ cấp (Allowances) | R8: Tổng các khoản phụ cấp (Total allowances) | S8: Lương đóng bảo hiểm | T8: Lương giờ công | U8: Tổng lương giờ công cơ bản | V8: Lương giờ công làm thêm | AA8: Tổng lương | AB8: BH tính vào chi phí / Isuarance payable by company | AG8: BH khấu trừ lương / Isuarance deductions from salary | AK8: Thuế TNCN /Personal income tax | AW8: Thực nhận | AY8: Số tài khoản | AZ8: Ký nhận
F9: Tăng ca ngày | G9: Tăng ca đêm | H9: Tăng ca CN 200% | I9: Tăng ca ngày lễ 300% | L9: Phụ cấp trách nhiệm | M9: Phụ cấp điện thoại | N9: Phụ cấp xăng xe | O9: Phụ cấp nhà ở | P9: Phụ cấp đi lại | Q9: Chuyên cần (Diligence) | V9: Tăng ca ngày 150% | W9: Tăng ca đêm | X9: Tăng ca CN 200% | Y9: Tăng ca ngày lễ 300% | Z9: Tổng lương làm thêm | AB9: Lương đóng bảo hiểm/Salary base for insurance | AC9: BHXH / Social Insurance 17.5% | AD9: BHYT / Health Insurance 3%건강보험 (회사분) | AE9: BHTN / Unemployment Insurance 1% | AF9: Cộng /Amount Isurance | AG9: BHXH / Social Insurance 8% | AH9: BHYT / Health Insurance 1,5% 건강보험 (개인분) | AI9: BHTN / Unemployment Insurance 1% | AJ9: Cộng 10.5%/Amount Isurance | AK9: Giảm trừ bản thân (기본공제금 ) (VND) | AL9: Số người phụ thuộc /Number Deduction family | AM9: Giảm trừ người phụ thuộc /deduction-family 4400000/1person | AN9: Tax excemption | AO9: Thu nhập chịu thuế | AP9: Tiền BHSK tính thuế TNCN | AQ9: Tiền thuê nhà | AR9: Vé máy bay | AS9: Thu nhập chịu thuế bảo gồm tiền BHSK + vé máy bay | AT9: Thu nhập tính thuế (과세 대상 금액) (VND) | AU9: Thuế TNCN (개인소득세) ( VND) | AV9: Truy thu Thuế TNCN | AW9: VND | AX9: USD (Quy đổi)
A10: -1 | C10: -2 | D10: -3 | E10: -4 | F10: -5 | G10: (5a) | H10: -6 | I10: -7 | K10: -8 | L10: -9 | M10: -10 | N10: -11 | O10: (11 a) | P10: (11b) | Q10: -12 | R10: (13)=10+11+11a+11b+ 12 | S10: (14)=(8)+(9) | T10: (15)=(14)/4 | U10: (16)=(15)*(4) | V10: (17)=(5)* (15)*150% | W10: (17a) | X10: (18)=(6)* (15)*200% | Y10: (19)=(7)* (15)*300% | Z10: (20)= (17)+(18)+(19) | AA10: (21)=(13)+(16)+ (20) | AB10: (22)=(8)+ (10) | AC10: (23)=(22)x17% | AD10: (24)=(22)x3% | AE10: 25 | AF10: (26)=(23)+(24) | AG10: 27 | AH10: (28)=(22)x1.5% | AI10: 29 | AJ10: (30)=(27)+(28)+(29) | AK10: -31 | AL10: (31a) | AM10: (32)= (31a)x4400000 | AN10: -33 | AO10: (34)=(21)-(33) | AT10: (35)=(21)-(31)-(32)-(33) | AU10: -36 | AW10: -37 | AX10: -38 | AY10: -39 | AZ10: -40
A11: 1 | C11: Shin Chun Ki | D11: TGĐ | E11: 208 | K11: =2500*E6 -> 0 | R11: =SUM(M11:Q11) -> 0 | S11: =K11+L11 -> 0 | T11: =S11/E11 -> 0 | U11: =T11*E11 -> 0 | V11: =T11*F11*150% -> 0 | X11: =T11*H11*200% -> 0 | Y11: =T11*I11*300% -> 0 | Z11: =SUM(V11:Y11) -> 0 | AA11: =R11+U11+Z11 -> 0 | AB11: 29800000 | AC11: =AB11*5% -> 1490000 | AD11: =AB11*3% -> 894000 | AF11: =AC11+AD11+AE11 -> 2384000 | AH11: =AB11*1.5% -> 447000 | AJ11: =AG11+AH11+AI11 -> 447000 | AK11: 11000000 | AL11: 3 | AM11: =AL11*4400000 -> 13200000 | AN11: =M11 -> 0 | AO11: =AA11-AN11 -> 0 | AT11: =(AA11-AK11-AM11-AN11-AJ11) -> -24647000 | AU11: =ROUND(IF(AT11<=5000000,AT11*5%,IF(AND(AT11>5000000,AT11<=10000000),AT11*10%-250000,IF(AND(AT11>10000000,AT11<=18000000),AT11*15%-750000,IF(AND(AT11>18000000,AT11<=32000000),AT11*20%-1650000,IF(AND(AT11>32000000,AT11<=52000000),AT11*25%-3250000,IF(AND(AT11>52000000,AT11<80000000),AT11*30%-5850000,IF(AT11>80000000,AT11*35%-9850000))))))),0) -> -1232350 | AW11: =AA11-AJ11-AU11 -> 785350 | AX11: =+AW11/E6 -> #DIV/0!
A12: 1 | B12: SS-TGĐ | C12: Shin Chun Ki | D12: Nhà quản lý | E12: =_xlfn.IFNA(VLOOKUP(B12,Sheet1!$C$12:$AY$20,4,0),0) -> 0 | F12: =_xlfn.IFNA(VLOOKUP(B12,Sheet1!$C$12:$AY$20,5,0),0) -> 0 | G12: =_xlfn.IFNA(VLOOKUP(B12,Sheet1!$C$12:$AY$20,6,0),0) -> 0 | H12: =_xlfn.IFNA(VLOOKUP(B12,Sheet1!$C$12:$AY$20,7,0),0) -> 0 | I12: =_xlfn.IFNA(VLOOKUP(B12,Sheet1!$C$12:$AY$20,8,0),0) -> 0 | J12: =_xlfn.IFNA(VLOOKUP(B12,Sheet1!$C$12:$AY$20,9,0),0) -> 0 | K12: =J12*E6 -> 0 | L12: =_xlfn.IFNA(VLOOKUP(B12,Sheet1!$C$12:$AY$20,11,0),0) -> 0 | M12: =_xlfn.IFNA(VLOOKUP(B12,Sheet1!$C$12:$AY$20,12,0),0) -> 0 | N12: =_xlfn.IFNA(VLOOKUP(B12,Sheet1!$C$12:$AY$20,13,0),0) -> 0 | O12: =_xlfn.IFNA(VLOOKUP(B12,Sheet1!$C$12:$AY$20,14,0),0) -> 0 | P12: =_xlfn.IFNA(VLOOKUP(B12,Sheet1!$C$12:$AY$20,15,0),0) -> 0 | Q12: =_xlfn.IFNA(VLOOKUP(B12,Sheet1!$C$12:$AY$20,16,0),0) -> 0 | R12: =SUM(M12:Q12) -> 0 | S12: =K12+L12 -> 0 | T12: =S12/E12 -> #DIV/0! | U12: =T12*E12 -> #DIV/0! | V12: =T12*F12*150% -> #DIV/0! | W12: =T12*G12*195% -> #DIV/0! | X12: =T12*H12*200% -> #DIV/0! | Y12: =T12*I12*300% -> #DIV/0! | Z12: =SUM(V12:Y12) -> #DIV/0! | AA12: =R12+U12+Z12 -> #DIV/0! | AB12: =_xlfn.IFNA(VLOOKUP(B12,Sheet1!$C$12:$AY$20,27,0),0) -> 0 | AC12: =_xlfn.IFNA(VLOOKUP(B12,Sheet1!$C$12:$AY$20,28,0),0) -> 0 | AD12: =_xlfn.IFNA(VLOOKUP(B12,Sheet1!$C$12:$AY$20,29,0),0) -> 0 | AF12: =AC12+AD12+AE12 -> 0 | AG12: =_xlfn.IFNA(VLOOKUP(B12,Sheet1!$C$12:$AY$20,32,0),0) -> 0 | AH12: =_xlfn.IFNA(VLOOKUP(B12,Sheet1!$C$12:$AY$20,33,0),0) -> 0 | AJ12: =AG12+AH12+AI12 -> 0 | AK12: 11000000 | AL12: =_xlfn.IFNA(VLOOKUP(B12,Sheet1!$C$12:$AY$20,37,0),0) -> 0 | AM12: =+AL12*4400000 -> 0 | AO12: =AA12-AN12 -> #DIV/0! | AP12: =_xlfn.IFNA(VLOOKUP(B12,Sheet1!$C$13:$AZ$23,41,0),0) -> 0 | AQ12: =_xlfn.IFNA(VLOOKUP(B12,Sheet1!$C$13:$AZ$23,42,0),0) -> 0 | AR12: =_xlfn.IFNA(VLOOKUP(B12,Sheet1!$C$13:$AZ$23,43,0),0) -> 0 | AS12: =AO12+AP12+AR12+AQ12 -> #DIV/0! | AT12: =(AS12-AK12-AM12-AJ12) -> #DIV/0! | AU12: =ROUND(IF(AT12<=5000000,AT12*5%,IF(AND(AT12>5000000,AT12<=10000000),AT12*10%-250000,IF(AND(AT12>10000000,AT12<=18000000),AT12*15%-750000,IF(AND(AT12>18000000,AT12<=32000000),AT12*20%-1650000,IF(AND(AT12>32000000,AT12<=52000000),AT12*25%-3250000,IF(AND(AT12>52000000,AT12<80000000),AT12*30%-5850000,IF(AT12>80000000,AT12*35%-9850000))))))),0) -> #DIV/0! | AV12: 0 | AW12: =AA12-AJ12-AU12-AV12 -> #DIV/0! | AX12: =AW12/E6 -> #DIV/0! | AY12: =_xlfn.IFNA(VLOOKUP(B12,Sheet1!$C$13:$AZ$22,50,0),0) -> 0

Sheet Mr. Lim
A1: CÔNG TY TNHH SHINSUNG VINA
A2: Lô CN04, khu công nghiệp Cẩm Khê, TT.Cẩm Khê, H.Cẩm Khê, T.Phú Thọ
A3: =Sheet1!B3 -> PAYROLL JANUARY 2
A4: =Sheet1!B4 -> From 1st - 31 January 2
A6: =Sheet1!B5 -> Tỷ giá Vietinbank: 00/01/1900 | D6: =Sheet1!E5 -> 25160 | E6: =Sheet1!F5 -> 0
A8: STT (No) | B8: Mã nhân viên (Employee ID) | C8: Họ và tên (First and last name) | D8: Vị trí (Location) | E8: Giờ công cơ bản thực tế (The actual basic hourly) | F8: Giờ công làm thêm (Hours of overtime) | J8: Lương cơ bản (Basic salary) USD | K8: Lương cơ bản (Basic salary) | L8: Các khoản phụ cấp (Allowances) | R8: Tổng các khoản phụ cấp (Total allowances) | S8: Lương đóng bảo hiểm | T8: Lương giờ công | U8: Tổng lương giờ công cơ bản | V8: Lương giờ công làm thêm | AA8: Tổng lương | AB8: BH tính vào chi phí / Isuarance payable by company | AG8: BH khấu trừ lương / Isuarance deductions from salary | AK8: Thuế TNCN /Personal income tax | AW8: Thực nhận | AY8: Số tài khoản | AZ8: Ký nhận
F9: Tăng ca ngày | G9: Tăng ca đêm | H9: Tăng ca CN 200% | I9: Tăng ca ngày lễ 300% | L9: Phụ cấp trách nhiệm | M9: Phụ cấp điện thoại | N9: Phụ cấp xăng xe | O9: Phụ cấp nhà ở | P9: Phụ cấp đi lại | Q9: Chuyên cần (Diligence) | V9: Tăng ca ngày 150% | W9: Tăng ca đêm | X9: Tăng ca CN 200% | Y9: Tăng ca ngày lễ 300% | Z9: Tổng lương làm thêm | AB9: Lương đóng bảo hiểm/Salary base for insurance | AC9: BHXH / Social Insurance 17.5% | AD9: BHYT / Health Insurance 3%건강보험 (회사분) | AE9: BHTN / Unemployment Insurance 1% | AF9: Cộng /Amount Isurance | AG9: BHXH / Social Insurance 8% | AH9: BHYT / Health Insurance 1,5% 건강보험 (개인분) | AI9: BHTN / Unemployment Insurance 1% | AJ9: Cộng 10.5%/Amount Isurance | AK9: Giảm trừ bản thân (기본공제금 ) (VND) | AL9: Số người phụ thuộc /Number Deduction family | AM9: Giảm trừ người phụ thuộc /deduction-family 4400000/1person | AN9: Tax excemption | AO9: Thu nhập chịu thuế | AP9: Tiền BHSK tính thuế TNCN | AQ9: Tiền thuê nhà | AR9: Vé máy bay | AS9: Thu nhập chịu thuế bảo gồm tiền BHSK + vé máy bay | AT9: Thu nhập tính thuế (과세 대상 금액) (VND) | AU9: Thuế TNCN (개인소득세) ( VND) | AV9: Truy thu Thuế TNCN | AW9: VND | AX9: USD (Quy đổi)
A10: -1 | C10: -2 | D10: -3 | E10: -4 | F10: -5 | G10: (5a) | H10: -6 | I10: -7 | K10: -8 | L10: -9 | M10: -10 | N10: -11 | O10: (11 a) | P10: (11b) | Q10: -12 | R10: (13)=10+11+11a+11b+ 12 | S10: (14)=(8)+(9) | T10: (15)=(14)/4 | U10: (16)=(15)*(4) | V10: (17)=(5)* (15)*150% | W10: (17a) | X10: (18)=(6)* (15)*200% | Y10: (19)=(7)* (15)*300% | Z10: (20)= (17)+(18)+(19) | AA10: (21)=(13)+(16)+ (20) | AB10: (22)=(8)+ (10) | AC10: (23)=(22)x17% | AD10: (24)=(22)x3% | AE10: 25 | AF10: (26)=(23)+(24) | AG10: 27 | AH10: (28)=(22)x1.5% | AI10: 29 | AJ10: (30)=(27)+(28)+(29) | AK10: -31 | AL10: (31a) | AM10: (32)= (31a)x4400000 | AN10: -33 | AO10: (34)=(21)-(33) | AT10: (35)=(21)-(31)-(32)-(33) | AU10: -36 | AW10: -37 | AX10: -38 | AY10: -39 | AZ10: -40
A11: 1 | C11: Shin Chun Ki | D11: TGĐ | E11: 208 | K11: =2500*E6 -> 0 | R11: =SUM(M11:Q11) -> 0 | S11: =K11+L11 -> 0 | T11: =S11/E11 -> 0 | U11: =T11*E11 -> 0 | V11: =T11*F11*150% -> 0 | X11: =T11*H11*200% -> 0 | Y11: =T11*I11*300% -> 0 | Z11: =SUM(V11:Y11) -> 0 | AA11: =R11+U11+Z11 -> 0 | AB11: 29800000 | AC11: =AB11*5% -> 1490000 | AD11: =AB11*3% -> 894000 | AF11: =AC11+AD11+AE11 -> 2384000 | AH11: =AB11*1.5% -> 447000 | AJ11: =AG11+AH11+AI11 -> 447000 | AK11: 11000000 | AL11: 3 | AM11: =AL11*4400000 -> 13200000 | AN11: =M11 -> 0 | AO11: =AA11-AN11 -> 0 | AT11: =(AA11-AK11-AM11-AN11-AJ11) -> -24647000 | AU11: =ROUND(IF(AT11<=5000000,AT11*5%,IF(AND(AT11>5000000,AT11<=10000000),AT11*10%-250000,IF(AND(AT11>10000000,AT11<=18000000),AT11*15%-750000,IF(AND(AT11>18000000,AT11<=32000000),AT11*20%-1650000,IF(AND(AT11>32000000,AT11<=52000000),AT11*25%-3250000,IF(AND(AT11>52000000,AT11<80000000),AT11*30%-5850000,IF(AT11>80000000,AT11*35%-9850000))))))),0) -> -1232350 | AW11: =AA11-AJ11-AU11 -> 785350 | AX11: =+AW11/E6 -> #DIV/0!
A12: 1 | B12: SS-QLKD | C12: Lim Heungsub | D12: Nhà quản lý | E12: =_xlfn.IFNA(VLOOKUP(B12,Sheet1!$C$12:$AY$20,4,0),0) -> 0 | F12: =_xlfn.IFNA(VLOOKUP(B12,Sheet1!$C$12:$AY$20,5,0),0) -> 0 | G12: =_xlfn.IFNA(VLOOKUP(B12,Sheet1!$C$12:$AY$20,6,0),0) -> 0 | H12: =_xlfn.IFNA(VLOOKUP(B12,Sheet1!$C$12:$AY$20,7,0),0) -> 0 | I12: =_xlfn.IFNA(VLOOKUP(B12,Sheet1!$C$12:$AY$20,8,0),0) -> 0 | J12: =_xlfn.IFNA(VLOOKUP(B12,Sheet1!$C$12:$AY$20,9,0),0) -> 0 | K12: =J12*E6 -> 0 | L12: =_xlfn.IFNA(VLOOKUP(B12,Sheet1!$C$12:$AY$20,11,0),0) -> 0 | M12: =_xlfn.IFNA(VLOOKUP(B12,Sheet1!$C$12:$AY$20,12,0),0) -> 0 | N12: =_xlfn.IFNA(VLOOKUP(B12,Sheet1!$C$12:$AY$20,13,0),0) -> 0 | O12: =_xlfn.IFNA(VLOOKUP(B12,Sheet1!$C$12:$AY$20,14,0),0) -> 0 | P12: =_xlfn.IFNA(VLOOKUP(B12,Sheet1!$C$12:$AY$20,15,0),0) -> 0 | Q12: =_xlfn.IFNA(VLOOKUP(B12,Sheet1!$C$12:$AY$20,16,0),0) -> 0 | R12: =SUM(M12:Q12) -> 0 | S12: =K12+L12 -> 0 | T12: =S12/E12 -> #DIV/0! | U12: =T12*E12 -> #DIV/0! | V12: =T12*F12*150% -> #DIV/0! | W12: =T12*G12*195% -> #DIV/0! | X12: =T12*H12*200% -> #DIV/0! | Y12: =T12*I12*300% -> #DIV/0! | Z12: =SUM(V12:Y12) -> #DIV/0! | AA12: =R12+U12+Z12 -> #DIV/0! | AB12: =_xlfn.IFNA(VLOOKUP(B12,Sheet1!$C$12:$AY$20,27,0),0) -> 0 | AC12: =_xlfn.IFNA(VLOOKUP(B12,Sheet1!$C$12:$AY$20,28,0),0) -> 0 | AD12: =_xlfn.IFNA(VLOOKUP(B12,Sheet1!$C$12:$AY$20,29,0),0) -> 0 | AF12: =AC12+AD12+AE12 -> 0 | AG12: =_xlfn.IFNA(VLOOKUP(B12,Sheet1!$C$12:$AY$20,32,0),0) -> 0 | AH12: =_xlfn.IFNA(VLOOKUP(B12,Sheet1!$C$12:$AY$20,33,0),0) -> 0 | AJ12: =AG12+AH12+AI12 -> 0 | AK12: 11000000 | AL12: =_xlfn.IFNA(VLOOKUP(B12,Sheet1!$C$12:$AY$20,37,0),0) -> 0 | AM12: =+AL12*4400000 -> 0 | AO12: =AA12-AN12 -> #DIV/0! | AP12: =_xlfn.IFNA(VLOOKUP(B12,Sheet1!$C$13:$AZ$23,41,0),0) -> 0 | AQ12: =_xlfn.IFNA(VLOOKUP(B12,Sheet1!$C$13:$AZ$23,42,0),0) -> 0 | AR12: =_xlfn.IFNA(VLOOKUP(B12,Sheet1!$C$13:$AZ$23,43,0),0) -> 0 | AS12: =AO12+AP12+AR12+AQ12 -> #DIV/0! | AT12: =(AS12-AK12-AM12-AJ12) -> #DIV/0! | AU12: =ROUND(IF(AT12<=5000000,AT12*5%,IF(AND(AT12>5000000,AT12<=10000000),AT12*10%-250000,IF(AND(AT12>10000000,AT12<=18000000),AT12*15%-750000,IF(AND(AT12>18000000,AT12<=32000000),AT12*20%-1650000,IF(AND(AT12>32000000,AT12<=52000000),AT12*25%-3250000,IF(AND(AT12>52000000,AT12<80000000),AT12*30%-5850000,IF(AT12>80000000,AT12*35%-9850000))))))),0) -> #DIV/0! | AV12: 0 | AW12: =AA12-AJ12-AU12-AV12 -> #DIV/0! | AX12: =AW12/E6 -> #DIV/0! | AY12: =_xlfn.IFNA(VLOOKUP(B12,Sheet1!$C$13:$AZ$22,50,0),0) -> 0

Sheet Mr. Moon
A1: CÔNG TY TNHH SHINSUNG VINA
A2: Lô CN04, khu công nghiệp Cẩm Khê, TT.Cẩm Khê, H.Cẩm Khê, T.Phú Thọ
A3: =Sheet1!B3 -> PAYROLL JANUARY 2
A4: =Sheet1!B4 -> From 1st - 31 January 2
A6: =Sheet1!B5 -> Tỷ giá Vietinbank: 00/01/1900 | D6: =Sheet1!E5 -> 25160 | E6: =Sheet1!F5 -> 0
A8: STT (No) | B8: Mã nhân viên (Employee ID) | C8: Họ và tên (First and last name) | D8: Vị trí (Location) | E8: Giờ công cơ bản thực tế (The actual basic hourly) | F8: Giờ công làm thêm (Hours of overtime) | J8: Lương cơ bản (Basic salary) USD | K8: Lương cơ bản (Basic salary) | L8: Các khoản phụ cấp (Allowances) | R8: Tổng các khoản phụ cấp (Total allowances) | S8: Lương đóng bảo hiểm | T8: Lương giờ công | U8: Tổng lương giờ công cơ bản | V8: Lương giờ công làm thêm | AA8: Tổng lương | AB8: BH tính vào chi phí / Isuarance payable by company | AG8: BH khấu trừ lương / Isuarance deductions from salary | AK8: Thuế TNCN /Personal income tax | AW8: Thực nhận | AY8: Số tài khoản | AZ8: Ký nhận
F9: Tăng ca ngày | G9: Tăng ca đêm | H9: Tăng ca CN 200% | I9: Tăng ca ngày lễ 300% | L9: Phụ cấp trách nhiệm | M9: Phụ cấp điện thoại | N9: Phụ cấp xăng xe | O9: Phụ cấp nhà ở | P9: Phụ cấp đi lại | Q9: Chuyên cần (Diligence) | V9: Tăng ca ngày 150% | W9: Tăng ca đêm | X9: Tăng ca CN 200% | Y9: Tăng ca ngày lễ 300% | Z9: Tổng lương làm thêm | AB9: Lương đóng bảo hiểm/Salary base for insurance | AC9: BHXH / Social Insurance 17.5% | AD9: BHYT / Health Insurance 3%건강보험 (회사분) | AE9: BHTN / Unemployment Insurance 1% | AF9: Cộng /Amount Isurance | AG9: BHXH / Social Insurance 8% | AH9: BHYT / Health Insurance 1,5% 건강보험 (개인분) | AI9: BHTN / Unemployment Insurance 1% | AJ9: Cộng 10.5%/Amount Isurance | AK9: Giảm trừ bản thân (기본공제금 ) (VND) | AL9: Số người phụ thuộc /Number Deduction family | AM9: Giảm trừ người phụ thuộc /deduction-family 4400000/1person | AN9: Tax excemption | AO9: Thu nhập chịu thuế | AP9: Tiền BHSK tính thuế TNCN | AQ9: Tiền thuê nhà | AR9: Vé máy bay | AS9: Thu nhập chịu thuế bảo gồm tiền BHSK + vé máy bay | AT9: Thu nhập tính thuế (과세 대상 금액) (VND) | AU9: Thuế TNCN (개인소득세) ( VND) | AV9: Truy thu Thuế TNCN | AW9: VND | AX9: USD (Quy đổi)
A10: -1 | C10: -2 | D10: -3 | E10: -4 | F10: -5 | G10: (5a) | H10: -6 | I10: -7 | K10: -8 | L10: -9 | M10: -10 | N10: -11 | O10: (11 a) | P10: (11b) | Q10: -12 | R10: (13)=10+11+11a+11b+ 12 | S10: (14)=(8)+(9) | T10: (15)=(14)/4 | U10: (16)=(15)*(4) | V10: (17)=(5)* (15)*150% | W10: (17a) | X10: (18)=(6)* (15)*200% | Y10: (19)=(7)* (15)*300% | Z10: (20)= (17)+(18)+(19) | AA10: (21)=(13)+(16)+ (20) | AB10: (22)=(8)+ (10) | AC10: (23)=(22)x17% | AD10: (24)=(22)x3% | AE10: 25 | AF10: (26)=(23)+(24) | AG10: 27 | AH10: (28)=(22)x1.5% | AI10: 29 | AJ10: (30)=(27)+(28)+(29) | AK10: -31 | AL10: (31a) | AM10: (32)= (31a)x4400000 | AN10: -33 | AO10: (34)=(21)-(33) | AT10: (35)=(21)-(31)-(32)-(33) | AU10: -36 | AW10: -37 | AX10: -38 | AY10: -39 | AZ10: -40
A11: 1 | C11: Shin Chun Ki | D11: TGĐ | E11: 208 | K11: =2500*E6 -> 0 | R11: =SUM(M11:Q11) -> 0 | S11: =K11+L11 -> 0 | T11: =S11/E11 -> 0 | U11: =T11*E11 -> 0 | V11: =T11*F11*150% -> 0 | X11: =T11*H11*200% -> 0 | Y11: =T11*I11*300% -> 0 | Z11: =SUM(V11:Y11) -> 0 | AA11: =R11+U11+Z11 -> 0 | AB11: 29800000 | AC11: =AB11*5% -> 1490000 | AD11: =AB11*3% -> 894000 | AF11: =AC11+AD11+AE11 -> 2384000 | AH11: =AB11*1.5% -> 447000 | AJ11: =AG11+AH11+AI11 -> 447000 | AK11: 11000000 | AL11: 3 | AM11: =AL11*4400000 -> 13200000 | AN11: =M11 -> 0 | AO11: =AA11-AN11 -> 0 | AT11: =(AA11-AK11-AM11-AN11-AJ11) -> -24647000 | AU11: =ROUND(IF(AT11<=5000000,AT11*5%,IF(AND(AT11>5000000,AT11<=10000000),AT11*10%-250000,IF(AND(AT11>10000000,AT11<=18000000),AT11*15%-750000,IF(AND(AT11>18000000,AT11<=32000000),AT11*20%-1650000,IF(AND(AT11>32000000,AT11<=52000000),AT11*25%-3250000,IF(AND(AT11>52000000,AT11<80000000),AT11*30%-5850000,IF(AT11>80000000,AT11*35%-9850000))))))),0) -> -1232350 | AW11: =AA11-AJ11-AU11 -> 785350 | AX11: =+AW11/E6 -> #DIV/0!
A12: 1 | B12: SS-GĐĐH | C12: Moon Han Soo | D12: Nhà quản lý | E12: =_xlfn.IFNA(VLOOKUP(B12,Sheet1!$C$12:$AY$20,4,0),0) -> 0 | F12: =_xlfn.IFNA(VLOOKUP(B12,Sheet1!$C$12:$AY$20,5,0),0) -> 0 | G12: =_xlfn.IFNA(VLOOKUP(B12,Sheet1!$C$12:$AY$20,6,0),0) -> 0 | H12: =_xlfn.IFNA(VLOOKUP(B12,Sheet1!$C$12:$AY$20,7,0),0) -> 0 | I12: =_xlfn.IFNA(VLOOKUP(B12,Sheet1!$C$12:$AY$20,8,0),0) -> 0 | J12: =_xlfn.IFNA(VLOOKUP(B12,Sheet1!$C$12:$AY$20,9,0),0) -> 0 | K12: =J12*E6 -> 0 | L12: =_xlfn.IFNA(VLOOKUP(B12,Sheet1!$C$12:$AY$20,11,0),0) -> 0 | M12: =_xlfn.IFNA(VLOOKUP(B12,Sheet1!$C$12:$AY$20,12,0),0) -> 0 | N12: =_xlfn.IFNA(VLOOKUP(B12,Sheet1!$C$12:$AY$20,13,0),0) -> 0 | O12: =_xlfn.IFNA(VLOOKUP(B12,Sheet1!$C$12:$AY$20,14,0),0) -> 0 | P12: =_xlfn.IFNA(VLOOKUP(B12,Sheet1!$C$12:$AY$20,15,0),0) -> 0 | Q12: =_xlfn.IFNA(VLOOKUP(B12,Sheet1!$C$12:$AY$20,16,0),0) -> 0 | R12: =SUM(M12:Q12) -> 0 | S12: =K12+L12 -> 0 | T12: =S12/E12 -> #DIV/0! | U12: =T12*E12 -> #DIV/0! | V12: =T12*F12*150% -> #DIV/0! | W12: =T12*G12*195% -> #DIV/0! | X12: =T12*H12*200% -> #DIV/0! | Y12: =T12*I12*300% -> #DIV/0! | Z12: =SUM(V12:Y12) -> #DIV/0! | AA12: =R12+U12+Z12 -> #DIV/0! | AB12: =_xlfn.IFNA(VLOOKUP(B12,Sheet1!$C$12:$AY$20,27,0),0) -> 0 | AC12: =_xlfn.IFNA(VLOOKUP(B12,Sheet1!$C$12:$AY$20,28,0),0) -> 0 | AD12: =_xlfn.IFNA(VLOOKUP(B12,Sheet1!$C$12:$AY$20,29,0),0) -> 0 | AF12: =AC12+AD12+AE12 -> 0 | AG12: =_xlfn.IFNA(VLOOKUP(B12,Sheet1!$C$12:$AY$20,32,0),0) -> 0 | AH12: =_xlfn.IFNA(VLOOKUP(B12,Sheet1!$C$12:$AY$20,33,0),0) -> 0 | AJ12: =AG12+AH12+AI12 -> 0 | AK12: 11000000 | AL12: =_xlfn.IFNA(VLOOKUP(B12,Sheet1!$C$12:$AY$20,37,0),0) -> 0 | AM12: =+AL12*4400000 -> 0 | AO12: =AA12-AN12 -> #DIV/0! | AP12: =_xlfn.IFNA(VLOOKUP(B12,Sheet1!$C$13:$AZ$23,41,0),0) -> 0 | AQ12: =_xlfn.IFNA(VLOOKUP(B12,Sheet1!$C$13:$AZ$23,42,0),0) -> 0 | AR12: =_xlfn.IFNA(VLOOKUP(B12,Sheet1!$C$13:$AZ$23,43,0),0) -> 0 | AS12: =AO12+AP12+AR12+AQ12 -> #DIV/0! | AT12: =(AS12-AK12-AM12-AJ12) -> #DIV/0! | AU12: =ROUND(IF(AT12<=5000000,AT12*5%,IF(AND(AT12>5000000,AT12<=10000000),AT12*10%-250000,IF(AND(AT12>10000000,AT12<=18000000),AT12*15%-750000,IF(AND(AT12>18000000,AT12<=32000000),AT12*20%-1650000,IF(AND(AT12>32000000,AT12<=52000000),AT12*25%-3250000,IF(AND(AT12>52000000,AT12<80000000),AT12*30%-5850000,IF(AT12>80000000,AT12*35%-9850000))))))),0) -> #DIV/0! | AV12: 0 | AW12: =AA12-AJ12-AU12-AV12 -> #DIV/0! | AX12: =AW12/E6 -> #DIV/0! | AY12: =_xlfn.IFNA(VLOOKUP(B12,Sheet1!$C$13:$AZ$22,50,0),0) -> 0

Sheet Mr. Yang
A1: CÔNG TY TNHH SHINSUNG VINA
A2: Lô CN04, khu công nghiệp Cẩm Khê, TT.Cẩm Khê, H.Cẩm Khê, T.Phú Thọ
A3: =Sheet1!B3 -> PAYROLL JANUARY 2
A4: =Sheet1!B4 -> From 1st - 31 January 2
A6: =Sheet1!B5 -> Tỷ giá Vietinbank: 00/01/1900 | D6: =Sheet1!E5 -> 25160 | E6: =Sheet1!F5 -> 0
A8: STT (No) | B8: Mã nhân viên (Employee ID) | C8: Họ và tên (First and last name) | D8: Vị trí (Location) | E8: Giờ công cơ bản thực tế (The actual basic hourly) | F8: Giờ công làm thêm (Hours of overtime) | J8: Lương cơ bản (Basic salary) USD | K8: Lương cơ bản (Basic salary) | L8: Các khoản phụ cấp (Allowances) | R8: Tổng các khoản phụ cấp (Total allowances) | S8: Lương đóng bảo hiểm | T8: Lương giờ công | U8: Tổng lương giờ công cơ bản | V8: Lương giờ công làm thêm | AA8: Tổng lương | AB8: BH tính vào chi phí / Isuarance payable by company | AG8: BH khấu trừ lương / Isuarance deductions from salary | AK8: Thuế TNCN /Personal income tax | AW8: Thực nhận | AY8: Số tài khoản | AZ8: Ký nhận
F9: Tăng ca ngày | G9: Tăng ca đêm | H9: Tăng ca CN 200% | I9: Tăng ca ngày lễ 300% | L9: Phụ cấp trách nhiệm | M9: Phụ cấp điện thoại | N9: Phụ cấp xăng xe | O9: Phụ cấp nhà ở | P9: Phụ cấp đi lại | Q9: Chuyên cần (Diligence) | V9: Tăng ca ngày 150% | W9: Tăng ca đêm | X9: Tăng ca CN 200% | Y9: Tăng ca ngày lễ 300% | Z9: Tổng lương làm thêm | AB9: Lương đóng bảo hiểm/Salary base for insurance | AC9: BHXH / Social Insurance 17.5% | AD9: BHYT / Health Insurance 3%건강보험 (회사분) | AE9: BHTN / Unemployment Insurance 1% | AF9: Cộng /Amount Isurance | AG9: BHXH / Social Insurance 8% | AH9: BHYT / Health Insurance 1,5% 건강보험 (개인분) | AI9: BHTN / Unemployment Insurance 1% | AJ9: Cộng 10.5%/Amount Isurance | AK9: Giảm trừ bản thân (기본공제금 ) (VND) | AL9: Số người phụ thuộc /Number Deduction family | AM9: Giảm trừ người phụ thuộc /deduction-family 4400000/1person | AN9: Tax excemption | AO9: Thu nhập chịu thuế | AP9: Tiền BHSK tính thuế TNCN | AQ9: Tiền thuê nhà | AR9: Vé máy bay | AS9: Thu nhập chịu thuế bảo gồm tiền BHSK + vé máy bay | AT9: Thu nhập tính thuế (과세 대상 금액) (VND) | AU9: Thuế TNCN (개인소득세) ( VND) | AV9: Truy thu Thuế TNCN | AW9: VND | AX9: USD (Quy đổi)
A10: -1 | C10: -2 | D10: -3 | E10: -4 | F10: -5 | G10: (5a) | H10: -6 | I10: -7 | K10: -8 | L10: -9 | M10: -10 | N10: -11 | O10: (11 a) | P10: (11b) | Q10: -12 | R10: (13)=10+11+11a+11b+ 12 | S10: (14)=(8)+(9) | T10: (15)=(14)/4 | U10: (16)=(15)*(4) | V10: (17)=(5)* (15)*150% | W10: (17a) | X10: (18)=(6)* (15)*200% | Y10: (19)=(7)* (15)*300% | Z10: (20)= (17)+(18)+(19) | AA10: (21)=(13)+(16)+ (20) | AB10: (22)=(8)+ (10) | AC10: (23)=(22)x17% | AD10: (24)=(22)x3% | AE10: 25 | AF10: (26)=(23)+(24) | AG10: 27 | AH10: (28)=(22)x1.5% | AI10: 29 | AJ10: (30)=(27)+(28)+(29) | AK10: -31 | AL10: (31a) | AM10: (32)= (31a)x4400000 | AN10: -33 | AO10: (34)=(21)-(33) | AT10: (35)=(21)-(31)-(32)-(33) | AU10: -36 | AW10: -37 | AX10: -38 | AY10: -39 | AZ10: -40
A11: 1 | C11: Shin Chun Ki | D11: TGĐ | E11: 208 | K11: =2500*E6 -> 0 | R11: =SUM(M11:Q11) -> 0 | S11: =K11+L11 -> 0 | T11: =S11/E11 -> 0 | U11: =T11*E11 -> 0 | V11: =T11*F11*150% -> 0 | X11: =T11*H11*200% -> 0 | Y11: =T11*I11*300% -> 0 | Z11: =SUM(V11:Y11) -> 0 | AA11: =R11+U11+Z11 -> 0 | AB11: 29800000 | AC11: =AB11*5% -> 1490000 | AD11: =AB11*3% -> 894000 | AF11: =AC11+AD11+AE11 -> 2384000 | AH11: =AB11*1.5% -> 447000 | AJ11: =AG11+AH11+AI11 -> 447000 | AK11: 11000000 | AL11: 3 | AM11: =AL11*4400000 -> 13200000 | AN11: =M11 -> 0 | AO11: =AA11-AN11 -> 0 | AT11: =(AA11-AK11-AM11-AN11-AJ11) -> -24647000 | AU11: =ROUND(IF(AT11<=5000000,AT11*5%,IF(AND(AT11>5000000,AT11<=10000000),AT11*10%-250000,IF(AND(AT11>10000000,AT11<=18000000),AT11*15%-750000,IF(AND(AT11>18000000,AT11<=32000000),AT11*20%-1650000,IF(AND(AT11>32000000,AT11<=52000000),AT11*25%-3250000,IF(AND(AT11>52000000,AT11<80000000),AT11*30%-5850000,IF(AT11>80000000,AT11*35%-9850000))))))),0) -> -1232350 | AW11: =AA11-AJ11-AU11 -> 785350 | AX11: =+AW11/E6 -> #DIV/0!
A12: 1 | B12: SS-TPSX | C12: Yang Dao Jun | D12: Nhà quản lý | E12: =_xlfn.IFNA(VLOOKUP(B12,Sheet1!$C$12:$AY$20,4,0),0) -> 0 | F12: =_xlfn.IFNA(VLOOKUP(B12,Sheet1!$C$12:$AY$20,5,0),0) -> 0 | G12: =_xlfn.IFNA(VLOOKUP(B12,Sheet1!$C$12:$AY$20,6,0),0) -> 0 | H12: =_xlfn.IFNA(VLOOKUP(B12,Sheet1!$C$12:$AY$20,7,0),0) -> 0 | I12: =_xlfn.IFNA(VLOOKUP(B12,Sheet1!$C$12:$AY$20,8,0),0) -> 0 | J12: =_xlfn.IFNA(VLOOKUP(B12,Sheet1!$C$12:$AY$20,9,0),0) -> 0 | K12: =J12*E6 -> 0 | L12: =_xlfn.IFNA(VLOOKUP(B12,Sheet1!$C$12:$AY$20,11,0),0) -> 0 | M12: =_xlfn.IFNA(VLOOKUP(B12,Sheet1!$C$12:$AY$20,12,0),0) -> 0 | N12: =_xlfn.IFNA(VLOOKUP(B12,Sheet1!$C$12:$AY$20,13,0),0) -> 0 | O12: =_xlfn.IFNA(VLOOKUP(B12,Sheet1!$C$12:$AY$20,14,0),0) -> 0 | P12: =_xlfn.IFNA(VLOOKUP(B12,Sheet1!$C$12:$AY$20,15,0),0) -> 0 | Q12: =_xlfn.IFNA(VLOOKUP(B12,Sheet1!$C$12:$AY$20,16,0),0) -> 0 | R12: =SUM(M12:Q12) -> 0 | S12: =K12+L12 -> 0 | T12: =S12/E12 -> #DIV/0! | U12: =T12*E12 -> #DIV/0! | V12: =T12*F12*150% -> #DIV/0! | W12: =T12*G12*195% -> #DIV/0! | X12: =T12*H12*200% -> #DIV/0! | Y12: =T12*I12*300% -> #DIV/0! | Z12: =SUM(V12:Y12) -> #DIV/0! | AA12: =R12+U12+Z12 -> #DIV/0! | AB12: =_xlfn.IFNA(VLOOKUP(B12,Sheet1!$C$12:$AY$20,27,0),0) -> 0 | AC12: =_xlfn.IFNA(VLOOKUP(B12,Sheet1!$C$12:$AY$20,28,0),0) -> 0 | AD12: =_xlfn.IFNA(VLOOKUP(B12,Sheet1!$C$12:$AY$20,29,0),0) -> 0 | AF12: =AC12+AD12+AE12 -> 0 | AG12: =_xlfn.IFNA(VLOOKUP(B12,Sheet1!$C$12:$AY$20,32,0),0) -> 0 | AH12: =_xlfn.IFNA(VLOOKUP(B12,Sheet1!$C$12:$AY$20,33,0),0) -> 0 | AJ12: =AG12+AH12+AI12 -> 0 | AK12: 11000000 | AL12: =_xlfn.IFNA(VLOOKUP(B12,Sheet1!$C$12:$AY$20,37,0),0) -> 0 | AM12: =+AL12*4400000 -> 0 | AO12: =AA12-AN12 -> #DIV/0! | AP12: =_xlfn.IFNA(VLOOKUP(B12,Sheet1!$C$13:$AZ$23,41,0),0) -> 0 | AQ12: =_xlfn.IFNA(VLOOKUP(B12,Sheet1!$C$13:$AZ$23,42,0),0) -> 0 | AR12: =_xlfn.IFNA(VLOOKUP(B12,Sheet1!$C$13:$AZ$23,43,0),0) -> 0 | AS12: =AO12+AP12+AR12+AQ12 -> #DIV/0! | AT12: =(AS12-AK12-AM12-AJ12) -> #DIV/0! | AU12: =ROUND(IF(AT12<=5000000,AT12*5%,IF(AND(AT12>5000000,AT12<=10000000),AT12*10%-250000,IF(AND(AT12>10000000,AT12<=18000000),AT12*15%-750000,IF(AND(AT12>18000000,AT12<=32000000),AT12*20%-1650000,IF(AND(AT12>32000000,AT12<=52000000),AT12*25%-3250000,IF(AND(AT12>52000000,AT12<80000000),AT12*30%-5850000,IF(AT12>80000000,AT12*35%-9850000))))))),0) -> #DIV/0! | AV12: 0 | AW12: =AA12-AJ12-AU12-AV12 -> #DIV/0! | AX12: =AW12/E6 -> #DIV/0! | AY12: =_xlfn.IFNA(VLOOKUP(B12,Sheet1!$C$13:$AZ$22,50,0),0) -> 0

Sheet Mr. Choi
A1: CÔNG TY TNHH SHINSUNG VINA
A2: Lô CN04, khu công nghiệp Cẩm Khê, TT.Cẩm Khê, H.Cẩm Khê, T.Phú Thọ
A3: =Sheet1!B3 -> PAYROLL JANUARY 2
A4: =Sheet1!B4 -> From 1st - 31 January 2
A6: =Sheet1!B5 -> Tỷ giá Vietinbank: 00/01/1900 | D6: =Sheet1!E5 -> 25160 | E6: =Sheet1!F5 -> 0
A8: STT (No) | B8: Mã nhân viên (Employee ID) | C8: Họ và tên (First and last name) | D8: Vị trí (Location) | E8: Giờ công cơ bản thực tế (The actual basic hourly) | F8: Giờ công làm thêm (Hours of overtime) | J8: Lương cơ bản (Basic salary) USD | K8: Lương cơ bản (Basic salary) | L8: Các khoản phụ cấp (Allowances) | R8: Tổng các khoản phụ cấp (Total allowances) | S8: Lương đóng bảo hiểm | T8: Lương giờ công | U8: Tổng lương giờ công cơ bản | V8: Lương giờ công làm thêm | AA8: Tổng lương | AB8: BH tính vào chi phí / Isuarance payable by company | AG8: BH khấu trừ lương / Isuarance deductions from salary | AK8: Thuế TNCN /Personal income tax | AW8: Thực nhận | AY8: Số tài khoản | AZ8: Ký nhận
F9: Tăng ca ngày | G9: Tăng ca đêm | H9: Tăng ca CN 200% | I9: Tăng ca ngày lễ 300% | L9: Phụ cấp trách nhiệm | M9: Phụ cấp điện thoại | N9: Phụ cấp xăng xe | O9: Phụ cấp nhà ở | P9: Phụ cấp đi lại | Q9: Chuyên cần (Diligence) | V9: Tăng ca ngày 150% | W9: Tăng ca đêm | X9: Tăng ca CN 200% | Y9: Tăng ca ngày lễ 300% | Z9: Tổng lương làm thêm | AB9: Lương đóng bảo hiểm/Salary base for insurance | AC9: BHXH / Social Insurance 17.5% | AD9: BHYT / Health Insurance 3%건강보험 (회사분) | AE9: BHTN / Unemployment Insurance 1% | AF9: Cộng /Amount Isurance | AG9: BHXH / Social Insurance 8% | AH9: BHYT / Health Insurance 1,5% 건강보험 (개인분) | AI9: BHTN / Unemployment Insurance 1% | AJ9: Cộng 10.5%/Amount Isurance | AK9: Giảm trừ bản thân (기본공제금 ) (VND) | AL9: Số người phụ thuộc /Number Deduction family | AM9: Giảm trừ người phụ thuộc /deduction-family 4400000/1person | AN9: Tax excemption | AO9: Thu nhập chịu thuế | AP9: Tiền BHSK tính thuế TNCN | AQ9: Tiền thuê nhà | AR9: Vé máy bay | AS9: Thu nhập chịu thuế bảo gồm tiền BHSK + vé máy bay | AT9: Thu nhập tính thuế (과세 대상 금액) (VND) | AU9: Thuế TNCN (개인소득세) ( VND) | AV9: Truy thu Thuế TNCN | AW9: VND | AX9: USD (Quy đổi)
A10: -1 | C10: -2 | D10: -3 | E10: -4 | F10: -5 | G10: (5a) | H10: -6 | I10: -7 | K10: -8 | L10: -9 | M10: -10 | N10: -11 | O10: (11 a) | P10: (11b) | Q10: -12 | R10: (13)=10+11+11a+11b+ 12 | S10: (14)=(8)+(9) | T10: (15)=(14)/4 | U10: (16)=(15)*(4) | V10: (17)=(5)* (15)*150% | W10: (17a) | X10: (18)=(6)* (15)*200% | Y10: (19)=(7)* (15)*300% | Z10: (20)= (17)+(18)+(19) | AA10: (21)=(13)+(16)+ (20) | AB10: (22)=(8)+ (10) | AC10: (23)=(22)x17% | AD10: (24)=(22)x3% | AE10: 25 | AF10: (26)=(23)+(24) | AG10: 27 | AH10: (28)=(22)x1.5% | AI10: 29 | AJ10: (30)=(27)+(28)+(29) | AK10: -31 | AL10: (31a) | AM10: (32)= (31a)x4400000 | AN10: -33 | AO10: (34)=(21)-(33) | AT10: (35)=(21)-(31)-(32)-(33) | AU10: -36 | AW10: -37 | AX10: -38 | AY10: -39 | AZ10: -40
A11: 1 | C11: Shin Chun Ki | D11: TGĐ | E11: 208 | K11: =2500*E6 -> 0 | R11: =SUM(M11:Q11) -> 0 | S11: =K11+L11 -> 0 | T11: =S11/E11 -> 0 | U11: =T11*E11 -> 0 | V11: =T11*F11*150% -> 0 | X11: =T11*H11*200% -> 0 | Y11: =T11*I11*300% -> 0 | Z11: =SUM(V11:Y11) -> 0 | AA11: =R11+U11+Z11 -> 0 | AB11: 29800000 | AC11: =AB11*5% -> 1490000 | AD11: =AB11*3% -> 894000 | AF11: =AC11+AD11+AE11 -> 2384000 | AH11: =AB11*1.5% -> 447000 | AJ11: =AG11+AH11+AI11 -> 447000 | AK11: 11000000 | AL11: 3 | AM11: =AL11*4400000 -> 13200000 | AN11: =M11 -> 0 | AO11: =AA11-AN11 -> 0 | AT11: =(AA11-AK11-AM11-AN11-AJ11) -> -24647000 | AU11: =ROUND(IF(AT11<=5000000,AT11*5%,IF(AND(AT11>5000000,AT11<=10000000),AT11*10%-250000,IF(AND(AT11>10000000,AT11<=18000000),AT11*15%-750000,IF(AND(AT11>18000000,AT11<=32000000),AT11*20%-1650000,IF(AND(AT11>32000000,AT11<=52000000),AT11*25%-3250000,IF(AND(AT11>52000000,AT11<80000000),AT11*30%-5850000,IF(AT11>80000000,AT11*35%-9850000))))))),0) -> -1232350 | AW11: =AA11-AJ11-AU11 -> 785350 | AX11: =+AW11/E6 -> #DIV/0!
A12: 1 | B12: SS-KTSX | C12: Choi Jin Sun | D12: Nhà quản lý | E12: =_xlfn.IFNA(VLOOKUP(B12,Sheet1!$C$12:$AY$20,4,0),0) -> 0 | F12: =_xlfn.IFNA(VLOOKUP(B12,Sheet1!$C$12:$AY$20,5,0),0) -> 0 | G12: =_xlfn.IFNA(VLOOKUP(B12,Sheet1!$C$12:$AY$20,6,0),0) -> 0 | H12: =_xlfn.IFNA(VLOOKUP(B12,Sheet1!$C$12:$AY$20,7,0),0) -> 0 | I12: =_xlfn.IFNA(VLOOKUP(B12,Sheet1!$C$12:$AY$20,8,0),0) -> 0 | J12: =_xlfn.IFNA(VLOOKUP(B12,Sheet1!$C$12:$AY$20,9,0),0) -> 0 | K12: =J12*E6 -> 0 | L12: =_xlfn.IFNA(VLOOKUP(B12,Sheet1!$C$12:$AY$20,11,0),0) -> 0 | M12: =_xlfn.IFNA(VLOOKUP(B12,Sheet1!$C$12:$AY$20,12,0),0) -> 0 | N12: =_xlfn.IFNA(VLOOKUP(B12,Sheet1!$C$12:$AY$20,13,0),0) -> 0 | O12: =_xlfn.IFNA(VLOOKUP(B12,Sheet1!$C$12:$AY$20,14,0),0) -> 0 | P12: =_xlfn.IFNA(VLOOKUP(B12,Sheet1!$C$12:$AY$20,15,0),0) -> 0 | Q12: =_xlfn.IFNA(VLOOKUP(B12,Sheet1!$C$12:$AY$20,16,0),0) -> 0 | R12: =SUM(M12:Q12) -> 0 | S12: =K12+L12 -> 0 | T12: =S12/E12 -> #DIV/0! | U12: =T12*E12 -> #DIV/0! | V12: =T12*F12*150% -> #DIV/0! | W12: =T12*G12*195% -> #DIV/0! | X12: =T12*H12*200% -> #DIV/0! | Y12: =T12*I12*300% -> #DIV/0! | Z12: =SUM(V12:Y12) -> #DIV/0! | AA12: =R12+U12+Z12 -> #DIV/0! | AB12: =_xlfn.IFNA(VLOOKUP(B12,Sheet1!$C$12:$AY$20,27,0),0) -> 0 | AC12: =_xlfn.IFNA(VLOOKUP(B12,Sheet1!$C$12:$AY$20,28,0),0) -> 0 | AD12: =_xlfn.IFNA(VLOOKUP(B12,Sheet1!$C$12:$AY$20,29,0),0) -> 0 | AF12: =AC12+AD12+AE12 -> 0 | AG12: =_xlfn.IFNA(VLOOKUP(B12,Sheet1!$C$12:$AY$20,32,0),0) -> 0 | AH12: =_xlfn.IFNA(VLOOKUP(B12,Sheet1!$C$12:$AY$20,33,0),0) -> 0 | AJ12: =AG12+AH12+AI12 -> 0 | AK12: 11000000 | AL12: =_xlfn.IFNA(VLOOKUP(B12,Sheet1!$C$12:$AY$20,37,0),0) -> 0 | AM12: =+AL12*4400000 -> 0 | AO12: =AA12-AN12 -> #DIV/0! | AP12: =_xlfn.IFNA(VLOOKUP(B12,Sheet1!$C$13:$AZ$23,41,0),0) -> 0 | AQ12: =_xlfn.IFNA(VLOOKUP(B12,Sheet1!$C$13:$AZ$23,42,0),0) -> 0 | AR12: =_xlfn.IFNA(VLOOKUP(B12,Sheet1!$C$13:$AZ$23,43,0),0) -> 0 | AS12: =AO12+AP12+AR12+AQ12 -> #DIV/0! | AT12: =(AS12-AK12-AM12-AJ12) -> #DIV/0! | AU12: =ROUND(IF(AT12<=5000000,AT12*5%,IF(AND(AT12>5000000,AT12<=10000000),AT12*10%-250000,IF(AND(AT12>10000000,AT12<=18000000),AT12*15%-750000,IF(AND(AT12>18000000,AT12<=32000000),AT12*20%-1650000,IF(AND(AT12>32000000,AT12<=52000000),AT12*25%-3250000,IF(AND(AT12>52000000,AT12<80000000),AT12*30%-5850000,IF(AT12>80000000,AT12*35%-9850000))))))),0) -> #DIV/0! | AV12: 0 | AW12: =AA12-AJ12-AU12-AV12 -> #DIV/0! | AX12: =AW12/E6 -> #DIV/0! | AY12: =_xlfn.IFNA(VLOOKUP(B12,Sheet1!$C$13:$AZ$22,50,0),0) -> 0

Sheet Mr. Hwang
A1: CÔNG TY TNHH SHINSUNG VINA
A2: Lô CN04, khu công nghiệp Cẩm Khê, TT.Cẩm Khê, H.Cẩm Khê, T.Phú Thọ
A3: =Sheet1!B3 -> PAYROLL JANUARY 2
A4: =Sheet1!B4 -> From 1st - 31 January 2
A6: =Sheet1!B5 -> Tỷ giá Vietinbank: 00/01/1900 | D6: =Sheet1!E5 -> 25160 | E6: =Sheet1!F5 -> 0
A8: STT (No) | B8: Mã nhân viên (Employee ID) | C8: Họ và tên (First and last name) | D8: Vị trí (Location) | E8: Giờ công cơ bản thực tế (The actual basic hourly) | F8: Giờ công làm thêm (Hours of overtime) | J8: Lương cơ bản (Basic salary) USD | K8: Lương cơ bản (Basic salary) | L8: Các khoản phụ cấp (Allowances) | R8: Tổng các khoản phụ cấp (Total allowances) | S8: Lương đóng bảo hiểm | T8: Lương giờ công | U8: Tổng lương giờ công cơ bản | V8: Lương giờ công làm thêm | AA8: Tổng lương | AB8: BH tính vào chi phí / Isuarance payable by company | AG8: BH khấu trừ lương / Isuarance deductions from salary | AK8: Thuế TNCN /Personal income tax | AW8: Thực nhận | AY8: Số tài khoản | AZ8: Ký nhận
F9: Tăng ca ngày | G9: Tăng ca đêm | H9: Tăng ca CN 200% | I9: Tăng ca ngày lễ 300% | L9: Phụ cấp trách nhiệm | M9: Phụ cấp điện thoại | N9: Phụ cấp xăng xe | O9: Phụ cấp nhà ở | P9: Phụ cấp đi lại | Q9: Chuyên cần (Diligence) | V9: Tăng ca ngày 150% | W9: Tăng ca đêm | X9: Tăng ca CN 200% | Y9: Tăng ca ngày lễ 300% | Z9: Tổng lương làm thêm | AB9: Lương đóng bảo hiểm/Salary base for insurance | AC9: BHXH / Social Insurance 17.5% | AD9: BHYT / Health Insurance 3%건강보험 (회사분) | AE9: BHTN / Unemployment Insurance 1% | AF9: Cộng /Amount Isurance | AG9: BHXH / Social Insurance 8% | AH9: BHYT / Health Insurance 1,5% 건강보험 (개인분) | AI9: BHTN / Unemployment Insurance 1% | AJ9: Cộng 10.5%/Amount Isurance | AK9: Giảm trừ bản thân (기본공제금 ) (VND) | AL9: Số người phụ thuộc /Number Deduction family | AM9: Giảm trừ người phụ thuộc /deduction-family 4400000/1person | AN9: Tax excemption | AO9: Thu nhập chịu thuế | AP9: Tiền BHSK tính thuế TNCN | AQ9: Tiền thuê nhà | AR9: Vé máy bay | AS9: Thu nhập chịu thuế bảo gồm tiền BHSK + vé máy bay | AT9: Thu nhập tính thuế (과세 대상 금액) (VND) | AU9: Thuế TNCN (개인소득세) ( VND) | AV9: Truy thu Thuế TNCN | AW9: VND | AX9: USD (Quy đổi)
A10: -1 | C10: -2 | D10: -3 | E10: -4 | F10: -5 | G10: (5a) | H10: -6 | I10: -7 | K10: -8 | L10: -9 | M10: -10 | N10: -11 | O10: (11 a) | P10: (11b) | Q10: -12 | R10: (13)=10+11+11a+11b+ 12 | S10: (14)=(8)+(9) | T10: (15)=(14)/4 | U10: (16)=(15)*(4) | V10: (17)=(5)* (15)*150% | W10: (17a) | X10: (18)=(6)* (15)*200% | Y10: (19)=(7)* (15)*300% | Z10: (20)= (17)+(18)+(19) | AA10: (21)=(13)+(16)+ (20) | AB10: (22)=(8)+ (10) | AC10: (23)=(22)x17% | AD10: (24)=(22)x3% | AE10: 25 | AF10: (26)=(23)+(24) | AG10: 27 | AH10: (28)=(22)x1.5% | AI10: 29 | AJ10: (30)=(27)+(28)+(29) | AK10: -31 | AL10: (31a) | AM10: (32)= (31a)x4400000 | AN10: -33 | AO10: (34)=(21)-(33) | AT10: (35)=(21)-(31)-(32)-(33) | AU10: -36 | AW10: -37 | AX10: -38 | AY10: -39 | AZ10: -40
A11: 1 | C11: Shin Chun Ki | D11: TGĐ | E11: 208 | K11: =2500*E6 -> 0 | R11: =SUM(M11:Q11) -> 0 | S11: =K11+L11 -> 0 | T11: =S11/E11 -> 0 | U11: =T11*E11 -> 0 | V11: =T11*F11*150% -> 0 | X11: =T11*H11*200% -> 0 | Y11: =T11*I11*300% -> 0 | Z11: =SUM(V11:Y11) -> 0 | AA11: =R11+U11+Z11 -> 0 | AB11: 29800000 | AC11: =AB11*5% -> 1490000 | AD11: =AB11*3% -> 894000 | AF11: =AC11+AD11+AE11 -> 2384000 | AH11: =AB11*1.5% -> 447000 | AJ11: =AG11+AH11+AI11 -> 447000 | AK11: 11000000 | AL11: 3 | AM11: =AL11*4400000 -> 13200000 | AN11: =M11 -> 0 | AO11: =AA11-AN11 -> 0 | AT11: =(AA11-AK11-AM11-AN11-AJ11) -> -24647000 | AU11: =ROUND(IF(AT11<=5000000,AT11*5%,IF(AND(AT11>5000000,AT11<=10000000),AT11*10%-250000,IF(AND(AT11>10000000,AT11<=18000000),AT11*15%-750000,IF(AND(AT11>18000000,AT11<=32000000),AT11*20%-1650000,IF(AND(AT11>32000000,AT11<=52000000),AT11*25%-3250000,IF(AND(AT11>52000000,AT11<80000000),AT11*30%-5850000,IF(AT11>80000000,AT11*35%-9850000))))))),0) -> -1232350 | AW11: =AA11-AJ11-AU11 -> 785350 | AX11: =+AW11/E6 -> #DIV/0!
A12: 1 | B12: SS-QLSX | C12: Hwang Seungyun | D12: Nhà quản lý | E12: =_xlfn.IFNA(VLOOKUP(B12,Sheet1!$C$12:$AY$20,4,0),0) -> 0 | F12: =_xlfn.IFNA(VLOOKUP(B12,Sheet1!$C$12:$AY$20,5,0),0) -> 0 | G12: =_xlfn.IFNA(VLOOKUP(B12,Sheet1!$C$12:$AY$20,6,0),0) -> 0 | H12: =_xlfn.IFNA(VLOOKUP(B12,Sheet1!$C$12:$AY$20,7,0),0) -> 0 | I12: =_xlfn.IFNA(VLOOKUP(B12,Sheet1!$C$12:$AY$20,8,0),0) -> 0 | J12: =_xlfn.IFNA(VLOOKUP(B12,Sheet1!$C$12:$AY$20,9,0),0) -> 0 | K12: =J12*E6 -> 0 | L12: =_xlfn.IFNA(VLOOKUP(B12,Sheet1!$C$12:$AY$20,11,0),0) -> 0 | M12: =_xlfn.IFNA(VLOOKUP(B12,Sheet1!$C$12:$AY$20,12,0),0) -> 0 | N12: =_xlfn.IFNA(VLOOKUP(B12,Sheet1!$C$12:$AY$20,13,0),0) -> 0 | O12: =_xlfn.IFNA(VLOOKUP(B12,Sheet1!$C$12:$AY$20,14,0),0) -> 0 | P12: =_xlfn.IFNA(VLOOKUP(B12,Sheet1!$C$12:$AY$20,15,0),0) -> 0 | Q12: =_xlfn.IFNA(VLOOKUP(B12,Sheet1!$C$12:$AY$20,16,0),0) -> 0 | R12: =SUM(M12:Q12) -> 0 | S12: =K12+L12 -> 0 | T12: =S12/E12 -> #DIV/0! | U12: =T12*E12 -> #DIV/0! | V12: =T12*F12*150% -> #DIV/0! | W12: =T12*G12*195% -> #DIV/0! | X12: =T12*H12*200% -> #DIV/0! | Y12: =T12*I12*300% -> #DIV/0! | Z12: =SUM(V12:Y12) -> #DIV/0! | AA12: =R12+U12+Z12 -> #DIV/0! | AB12: =_xlfn.IFNA(VLOOKUP(B12,Sheet1!$C$12:$AY$20,27,0),0) -> 0 | AC12: =_xlfn.IFNA(VLOOKUP(B12,Sheet1!$C$12:$AY$20,28,0),0) -> 0 | AD12: =_xlfn.IFNA(VLOOKUP(B12,Sheet1!$C$12:$AY$20,29,0),0) -> 0 | AF12: =AC12+AD12+AE12 -> 0 | AG12: =_xlfn.IFNA(VLOOKUP(B12,Sheet1!$C$12:$AY$20,32,0),0) -> 0 | AH12: =_xlfn.IFNA(VLOOKUP(B12,Sheet1!$C$12:$AY$20,33,0),0) -> 0 | AJ12: =AG12+AH12+AI12 -> 0 | AK12: 11000000 | AL12: =_xlfn.IFNA(VLOOKUP(B12,Sheet1!$C$12:$AY$20,37,0),0) -> 0 | AM12: =+AL12*4400000 -> 0 | AO12: =AA12-AN12 -> #DIV/0! | AP12: =_xlfn.IFNA(VLOOKUP(B12,Sheet1!$C$13:$AZ$23,41,0),0) -> 0 | AQ12: =_xlfn.IFNA(VLOOKUP(B12,Sheet1!$C$13:$AZ$23,42,0),0) -> 0 | AR12: =_xlfn.IFNA(VLOOKUP(B12,Sheet1!$C$13:$AZ$23,43,0),0) -> 0 | AS12: =AO12+AP12+AR12+AQ12 -> #DIV/0! | AT12: =(AS12-AK12-AM12-AJ12) -> #DIV/0! | AU12: =ROUND(IF(AT12<=5000000,AT12*5%,IF(AND(AT12>5000000,AT12<=10000000),AT12*10%-250000,IF(AND(AT12>10000000,AT12<=18000000),AT12*15%-750000,IF(AND(AT12>18000000,AT12<=32000000),AT12*20%-1650000,IF(AND(AT12>32000000,AT12<=52000000),AT12*25%-3250000,IF(AND(AT12>52000000,AT12<80000000),AT12*30%-5850000,IF(AT12>80000000,AT12*35%-9850000))))))),0) -> #DIV/0! | AV12: 0 | AW12: =AA12-AJ12-AU12-AV12 -> #DIV/0! | AX12: =AW12/E6 -> #DIV/0! | AY12: =_xlfn.IFNA(VLOOKUP(B12,Sheet1!$C$13:$AZ$22,50,0),0) -> 0
